package com.google.android.gms.dynamite;

final class zza
  extends Thread
{
  zza(ThreadGroup paramThreadGroup, String paramString)
  {
    super(paramThreadGroup, "GmsDynamite");
  }
  
  /* Error */
  public final void run()
  {
    // Byte code:
    //   0: bipush 19
    //   2: invokestatic 21	android/os/Process:setThreadPriority	(I)V
    //   5: aload_0
    //   6: monitorenter
    //   7: aload_0
    //   8: invokevirtual 26	java/lang/Object:wait	()V
    //   11: goto -4 -> 7
    //   14: astore_1
    //   15: goto +7 -> 22
    //   18: astore_1
    //   19: aload_0
    //   20: monitorexit
    //   21: return
    //   22: aload_0
    //   23: monitorexit
    //   24: aload_1
    //   25: athrow
    // Local variable table:
    //   start	length	slot	name	signature
    //   0	26	0	this	zza
    //   14	1	1	localObject	Object
    //   18	7	1	localInterruptedException	InterruptedException
    // Exception table:
    //   from	to	target	type
    //   7	11	14	finally
    //   19	21	14	finally
    //   22	24	14	finally
    //   7	11	18	java/lang/InterruptedException
  }
}


/* Location:              C:\Users\Ria\Documents\slope apk\dex-tools-v2.4\classes-dex2jar.jar!\com\google\android\gms\dynamite\zza.class
 * Java compiler version: 6 (50.0)
 * JD-Core Version:       0.7.1
 */