package com.google.android.gms.internal.ads;

public class zzalx
  implements zzalb
{
  protected final zzalz zza;
  @Deprecated
  protected final zzalw zzb;
  private final zzalw zzc;
  
  public zzalx(zzalw paramzzalw)
  {
    this.zzc = paramzzalw;
    this.zzb = paramzzalw;
    this.zza = localzzalz;
  }
  
  /* Error */
  public zzale zza(zzali paramzzali)
    throws zzalr
  {
    // Byte code:
    //   0: invokestatic 40	android/os/SystemClock:elapsedRealtime	()J
    //   3: lstore 5
    //   5: invokestatic 46	java/util/Collections:emptyList	()Ljava/util/List;
    //   8: pop
    //   9: iconst_1
    //   10: istore_2
    //   11: aload_1
    //   12: invokevirtual 52	com/google/android/gms/internal/ads/zzali:zzd	()Lcom/google/android/gms/internal/ads/zzakr;
    //   15: astore 10
    //   17: aload 10
    //   19: ifnonnull +11 -> 30
    //   22: invokestatic 56	java/util/Collections:emptyMap	()Ljava/util/Map;
    //   25: astore 9
    //   27: goto +66 -> 93
    //   30: new 58	java/util/HashMap
    //   33: astore 9
    //   35: aload 9
    //   37: invokespecial 59	java/util/HashMap:<init>	()V
    //   40: aload 10
    //   42: getfield 64	com/google/android/gms/internal/ads/zzakr:zzb	Ljava/lang/String;
    //   45: astore 11
    //   47: aload 11
    //   49: ifnull +15 -> 64
    //   52: aload 9
    //   54: ldc 66
    //   56: aload 11
    //   58: invokeinterface 72 3 0
    //   63: pop
    //   64: aload 10
    //   66: getfield 75	com/google/android/gms/internal/ads/zzakr:zzd	J
    //   69: lstore 7
    //   71: lload 7
    //   73: lconst_0
    //   74: lcmp
    //   75: ifle +18 -> 93
    //   78: aload 9
    //   80: ldc 77
    //   82: lload 7
    //   84: invokestatic 82	com/google/android/gms/internal/ads/zzamf:zzc	(J)Ljava/lang/String;
    //   87: invokeinterface 72 3 0
    //   92: pop
    //   93: aload_1
    //   94: invokevirtual 86	com/google/android/gms/internal/ads/zzali:zzk	()Ljava/lang/String;
    //   97: astore 10
    //   99: new 58	java/util/HashMap
    //   102: astore 11
    //   104: aload 11
    //   106: invokespecial 59	java/util/HashMap:<init>	()V
    //   109: aload 11
    //   111: aload 9
    //   113: invokevirtual 90	java/util/HashMap:putAll	(Ljava/util/Map;)V
    //   116: aload 11
    //   118: aload_1
    //   119: invokevirtual 93	com/google/android/gms/internal/ads/zzali:zzl	()Ljava/util/Map;
    //   122: invokevirtual 90	java/util/HashMap:putAll	(Ljava/util/Map;)V
    //   125: new 95	java/net/URL
    //   128: astore 9
    //   130: aload 9
    //   132: aload 10
    //   134: invokespecial 98	java/net/URL:<init>	(Ljava/lang/String;)V
    //   137: aload 9
    //   139: invokevirtual 102	java/net/URL:openConnection	()Ljava/net/URLConnection;
    //   142: checkcast 104	java/net/HttpURLConnection
    //   145: astore 10
    //   147: aload 10
    //   149: invokestatic 108	java/net/HttpURLConnection:getFollowRedirects	()Z
    //   152: invokevirtual 112	java/net/HttpURLConnection:setInstanceFollowRedirects	(Z)V
    //   155: aload_1
    //   156: invokevirtual 115	com/google/android/gms/internal/ads/zzali:zzb	()I
    //   159: istore_3
    //   160: aload 10
    //   162: iload_3
    //   163: invokevirtual 118	java/net/HttpURLConnection:setConnectTimeout	(I)V
    //   166: aload 10
    //   168: iload_3
    //   169: invokevirtual 121	java/net/HttpURLConnection:setReadTimeout	(I)V
    //   172: aload 10
    //   174: iconst_0
    //   175: invokevirtual 124	java/net/HttpURLConnection:setUseCaches	(Z)V
    //   178: aload 10
    //   180: iconst_1
    //   181: invokevirtual 127	java/net/HttpURLConnection:setDoInput	(Z)V
    //   184: ldc -127
    //   186: aload 9
    //   188: invokevirtual 132	java/net/URL:getProtocol	()Ljava/lang/String;
    //   191: invokevirtual 138	java/lang/String:equals	(Ljava/lang/Object;)Z
    //   194: pop
    //   195: aload 11
    //   197: invokevirtual 142	java/util/HashMap:keySet	()Ljava/util/Set;
    //   200: invokeinterface 148 1 0
    //   205: astore 12
    //   207: aload 12
    //   209: invokeinterface 153 1 0
    //   214: ifeq +35 -> 249
    //   217: aload 12
    //   219: invokeinterface 157 1 0
    //   224: checkcast 134	java/lang/String
    //   227: astore 9
    //   229: aload 10
    //   231: aload 9
    //   233: aload 11
    //   235: aload 9
    //   237: invokevirtual 161	java/util/HashMap:get	(Ljava/lang/Object;)Ljava/lang/Object;
    //   240: checkcast 134	java/lang/String
    //   243: invokevirtual 165	java/net/HttpURLConnection:setRequestProperty	(Ljava/lang/String;Ljava/lang/String;)V
    //   246: goto -39 -> 207
    //   249: aload_1
    //   250: invokevirtual 167	com/google/android/gms/internal/ads/zzali:zza	()I
    //   253: ifeq +81 -> 334
    //   256: aload 10
    //   258: ldc -87
    //   260: invokevirtual 172	java/net/HttpURLConnection:setRequestMethod	(Ljava/lang/String;)V
    //   263: aload_1
    //   264: invokevirtual 176	com/google/android/gms/internal/ads/zzali:zzx	()[B
    //   267: astore 11
    //   269: aload 11
    //   271: ifnull +70 -> 341
    //   274: aload 10
    //   276: iconst_1
    //   277: invokevirtual 179	java/net/HttpURLConnection:setDoOutput	(Z)V
    //   280: aload 10
    //   282: invokevirtual 182	java/net/HttpURLConnection:getRequestProperties	()Ljava/util/Map;
    //   285: ldc -72
    //   287: invokeinterface 187 2 0
    //   292: ifne +12 -> 304
    //   295: aload 10
    //   297: ldc -72
    //   299: ldc -67
    //   301: invokevirtual 165	java/net/HttpURLConnection:setRequestProperty	(Ljava/lang/String;Ljava/lang/String;)V
    //   304: new 191	java/io/DataOutputStream
    //   307: astore 9
    //   309: aload 9
    //   311: aload 10
    //   313: invokevirtual 195	java/net/HttpURLConnection:getOutputStream	()Ljava/io/OutputStream;
    //   316: invokespecial 198	java/io/DataOutputStream:<init>	(Ljava/io/OutputStream;)V
    //   319: aload 9
    //   321: aload 11
    //   323: invokevirtual 202	java/io/DataOutputStream:write	([B)V
    //   326: aload 9
    //   328: invokevirtual 205	java/io/DataOutputStream:close	()V
    //   331: goto +10 -> 341
    //   334: aload 10
    //   336: ldc -49
    //   338: invokevirtual 172	java/net/HttpURLConnection:setRequestMethod	(Ljava/lang/String;)V
    //   341: aload 10
    //   343: invokevirtual 210	java/net/HttpURLConnection:getResponseCode	()I
    //   346: istore_3
    //   347: iload_3
    //   348: iconst_m1
    //   349: if_icmpeq +815 -> 1164
    //   352: aload_1
    //   353: invokevirtual 167	com/google/android/gms/internal/ads/zzali:zza	()I
    //   356: pop
    //   357: iload_3
    //   358: bipush 100
    //   360: if_icmplt +10 -> 370
    //   363: iload_3
    //   364: sipush 200
    //   367: if_icmplt +70 -> 437
    //   370: iload_3
    //   371: sipush 204
    //   374: if_icmpeq +63 -> 437
    //   377: iload_3
    //   378: sipush 304
    //   381: if_icmpeq +56 -> 437
    //   384: aload 10
    //   386: invokevirtual 213	java/net/HttpURLConnection:getHeaderFields	()Ljava/util/Map;
    //   389: invokestatic 218	com/google/android/gms/internal/ads/zzami:zza	(Ljava/util/Map;)Ljava/util/List;
    //   392: astore 9
    //   394: aload 10
    //   396: invokevirtual 221	java/net/HttpURLConnection:getContentLength	()I
    //   399: istore 4
    //   401: new 223	com/google/android/gms/internal/ads/zzamh
    //   404: astore 11
    //   406: aload 11
    //   408: aload 10
    //   410: invokespecial 226	com/google/android/gms/internal/ads/zzamh:<init>	(Ljava/net/HttpURLConnection;)V
    //   413: new 228	com/google/android/gms/internal/ads/zzamg
    //   416: dup
    //   417: iload_3
    //   418: aload 9
    //   420: iload 4
    //   422: aload 11
    //   424: invokespecial 231	com/google/android/gms/internal/ads/zzamg:<init>	(ILjava/util/List;ILjava/io/InputStream;)V
    //   427: astore 9
    //   429: goto +33 -> 462
    //   432: astore 9
    //   434: goto +755 -> 1189
    //   437: new 228	com/google/android/gms/internal/ads/zzamg
    //   440: dup
    //   441: iload_3
    //   442: aload 10
    //   444: invokevirtual 213	java/net/HttpURLConnection:getHeaderFields	()Ljava/util/Map;
    //   447: invokestatic 218	com/google/android/gms/internal/ads/zzami:zza	(Ljava/util/Map;)Ljava/util/List;
    //   450: iconst_m1
    //   451: aconst_null
    //   452: invokespecial 231	com/google/android/gms/internal/ads/zzamg:<init>	(ILjava/util/List;ILjava/io/InputStream;)V
    //   455: astore 9
    //   457: aload 10
    //   459: invokevirtual 234	java/net/HttpURLConnection:disconnect	()V
    //   462: aload 9
    //   464: invokevirtual 235	com/google/android/gms/internal/ads/zzamg:zzb	()I
    //   467: istore_2
    //   468: aload 9
    //   470: invokevirtual 237	com/google/android/gms/internal/ads/zzamg:zzd	()Ljava/util/List;
    //   473: astore 12
    //   475: iload_2
    //   476: sipush 304
    //   479: if_icmpne +347 -> 826
    //   482: invokestatic 40	android/os/SystemClock:elapsedRealtime	()J
    //   485: lload 5
    //   487: lsub
    //   488: lstore 7
    //   490: aload_1
    //   491: invokevirtual 52	com/google/android/gms/internal/ads/zzali:zzd	()Lcom/google/android/gms/internal/ads/zzakr;
    //   494: astore 10
    //   496: aload 10
    //   498: ifnonnull +27 -> 525
    //   501: new 239	com/google/android/gms/internal/ads/zzale
    //   504: dup
    //   505: sipush 304
    //   508: aconst_null
    //   509: iconst_1
    //   510: lload 7
    //   512: aload 12
    //   514: invokespecial 242	com/google/android/gms/internal/ads/zzale:<init>	(I[BZJLjava/util/List;)V
    //   517: astore 10
    //   519: aload 10
    //   521: astore_1
    //   522: goto +302 -> 824
    //   525: new 244	java/util/TreeSet
    //   528: astore 11
    //   530: aload 11
    //   532: getstatic 248	java/lang/String:CASE_INSENSITIVE_ORDER	Ljava/util/Comparator;
    //   535: invokespecial 251	java/util/TreeSet:<init>	(Ljava/util/Comparator;)V
    //   538: aload 12
    //   540: invokeinterface 256 1 0
    //   545: ifne +46 -> 591
    //   548: aload 12
    //   550: invokeinterface 257 1 0
    //   555: astore 13
    //   557: aload 13
    //   559: invokeinterface 153 1 0
    //   564: ifeq +27 -> 591
    //   567: aload 11
    //   569: aload 13
    //   571: invokeinterface 157 1 0
    //   576: checkcast 259	com/google/android/gms/internal/ads/zzala
    //   579: invokevirtual 261	com/google/android/gms/internal/ads/zzala:zza	()Ljava/lang/String;
    //   582: invokeinterface 264 2 0
    //   587: pop
    //   588: goto -31 -> 557
    //   591: new 266	java/util/ArrayList
    //   594: astore 13
    //   596: aload 13
    //   598: aload 12
    //   600: invokespecial 269	java/util/ArrayList:<init>	(Ljava/util/Collection;)V
    //   603: aload 10
    //   605: getfield 273	com/google/android/gms/internal/ads/zzakr:zzh	Ljava/util/List;
    //   608: astore 12
    //   610: aload 12
    //   612: ifnull +75 -> 687
    //   615: aload 12
    //   617: invokeinterface 256 1 0
    //   622: ifne +177 -> 799
    //   625: aload 10
    //   627: getfield 273	com/google/android/gms/internal/ads/zzakr:zzh	Ljava/util/List;
    //   630: invokeinterface 257 1 0
    //   635: astore 12
    //   637: aload 12
    //   639: invokeinterface 153 1 0
    //   644: ifeq +155 -> 799
    //   647: aload 12
    //   649: invokeinterface 157 1 0
    //   654: checkcast 259	com/google/android/gms/internal/ads/zzala
    //   657: astore 14
    //   659: aload 11
    //   661: aload 14
    //   663: invokevirtual 261	com/google/android/gms/internal/ads/zzala:zza	()Ljava/lang/String;
    //   666: invokeinterface 276 2 0
    //   671: ifne -34 -> 637
    //   674: aload 13
    //   676: aload 14
    //   678: invokeinterface 277 2 0
    //   683: pop
    //   684: goto -47 -> 637
    //   687: aload 10
    //   689: getfield 281	com/google/android/gms/internal/ads/zzakr:zzg	Ljava/util/Map;
    //   692: invokeinterface 282 1 0
    //   697: ifne +102 -> 799
    //   700: aload 10
    //   702: getfield 281	com/google/android/gms/internal/ads/zzakr:zzg	Ljava/util/Map;
    //   705: invokeinterface 285 1 0
    //   710: invokeinterface 148 1 0
    //   715: astore 12
    //   717: aload 12
    //   719: invokeinterface 153 1 0
    //   724: ifeq +75 -> 799
    //   727: aload 12
    //   729: invokeinterface 157 1 0
    //   734: checkcast 287	java/util/Map$Entry
    //   737: astore 15
    //   739: aload 11
    //   741: aload 15
    //   743: invokeinterface 290 1 0
    //   748: invokeinterface 276 2 0
    //   753: ifne -36 -> 717
    //   756: new 259	com/google/android/gms/internal/ads/zzala
    //   759: astore 14
    //   761: aload 14
    //   763: aload 15
    //   765: invokeinterface 290 1 0
    //   770: checkcast 134	java/lang/String
    //   773: aload 15
    //   775: invokeinterface 293 1 0
    //   780: checkcast 134	java/lang/String
    //   783: invokespecial 295	com/google/android/gms/internal/ads/zzala:<init>	(Ljava/lang/String;Ljava/lang/String;)V
    //   786: aload 13
    //   788: aload 14
    //   790: invokeinterface 277 2 0
    //   795: pop
    //   796: goto -79 -> 717
    //   799: new 239	com/google/android/gms/internal/ads/zzale
    //   802: dup
    //   803: sipush 304
    //   806: aload 10
    //   808: getfield 298	com/google/android/gms/internal/ads/zzakr:zza	[B
    //   811: iconst_1
    //   812: lload 7
    //   814: aload 13
    //   816: invokespecial 242	com/google/android/gms/internal/ads/zzale:<init>	(I[BZJLjava/util/List;)V
    //   819: astore 10
    //   821: aload 10
    //   823: astore_1
    //   824: aload_1
    //   825: areturn
    //   826: aload 9
    //   828: invokevirtual 301	com/google/android/gms/internal/ads/zzamg:zzc	()Ljava/io/InputStream;
    //   831: astore 15
    //   833: aload 15
    //   835: ifnull +154 -> 989
    //   838: aload 9
    //   840: invokevirtual 302	com/google/android/gms/internal/ads/zzamg:zza	()I
    //   843: istore_3
    //   844: aload_0
    //   845: getfield 28	com/google/android/gms/internal/ads/zzalx:zza	Lcom/google/android/gms/internal/ads/zzalz;
    //   848: astore 13
    //   850: new 304	com/google/android/gms/internal/ads/zzaml
    //   853: astore 14
    //   855: aload 14
    //   857: aload 13
    //   859: iload_3
    //   860: invokespecial 307	com/google/android/gms/internal/ads/zzaml:<init>	(Lcom/google/android/gms/internal/ads/zzalz;I)V
    //   863: aload 13
    //   865: sipush 1024
    //   868: invokevirtual 310	com/google/android/gms/internal/ads/zzalz:zzb	(I)[B
    //   871: astore 10
    //   873: aload 15
    //   875: aload 10
    //   877: invokevirtual 316	java/io/InputStream:read	([B)I
    //   880: istore_3
    //   881: iload_3
    //   882: iconst_m1
    //   883: if_icmpeq +20 -> 903
    //   886: aload 14
    //   888: aload 10
    //   890: iconst_0
    //   891: iload_3
    //   892: invokevirtual 319	com/google/android/gms/internal/ads/zzaml:write	([BII)V
    //   895: goto -22 -> 873
    //   898: astore 11
    //   900: goto +54 -> 954
    //   903: aload 14
    //   905: invokevirtual 322	com/google/android/gms/internal/ads/zzaml:toByteArray	()[B
    //   908: astore 11
    //   910: aload 15
    //   912: invokevirtual 323	java/io/InputStream:close	()V
    //   915: goto +15 -> 930
    //   918: astore 15
    //   920: ldc_w 325
    //   923: iconst_0
    //   924: anewarray 4	java/lang/Object
    //   927: invokestatic 330	com/google/android/gms/internal/ads/zzalu:zzd	(Ljava/lang/String;[Ljava/lang/Object;)V
    //   930: aload 13
    //   932: aload 10
    //   934: invokevirtual 332	com/google/android/gms/internal/ads/zzalz:zza	([B)V
    //   937: aload 14
    //   939: invokevirtual 333	com/google/android/gms/internal/ads/zzaml:close	()V
    //   942: aload 11
    //   944: astore 10
    //   946: goto +48 -> 994
    //   949: astore 11
    //   951: aconst_null
    //   952: astore 10
    //   954: aload 15
    //   956: invokevirtual 323	java/io/InputStream:close	()V
    //   959: goto +15 -> 974
    //   962: astore 12
    //   964: ldc_w 325
    //   967: iconst_0
    //   968: anewarray 4	java/lang/Object
    //   971: invokestatic 330	com/google/android/gms/internal/ads/zzalu:zzd	(Ljava/lang/String;[Ljava/lang/Object;)V
    //   974: aload 13
    //   976: aload 10
    //   978: invokevirtual 332	com/google/android/gms/internal/ads/zzalz:zza	([B)V
    //   981: aload 14
    //   983: invokevirtual 333	com/google/android/gms/internal/ads/zzaml:close	()V
    //   986: aload 11
    //   988: athrow
    //   989: iconst_0
    //   990: newarray <illegal type>
    //   992: astore 10
    //   994: invokestatic 40	android/os/SystemClock:elapsedRealtime	()J
    //   997: lload 5
    //   999: lsub
    //   1000: lstore 7
    //   1002: getstatic 336	com/google/android/gms/internal/ads/zzalu:zzb	Z
    //   1005: ifne +18 -> 1023
    //   1008: lload 7
    //   1010: ldc2_w 337
    //   1013: lcmp
    //   1014: ifle +6 -> 1020
    //   1017: goto +6 -> 1023
    //   1020: goto +74 -> 1094
    //   1023: aload 10
    //   1025: ifnull +14 -> 1039
    //   1028: aload 10
    //   1030: arraylength
    //   1031: invokestatic 344	java/lang/Integer:valueOf	(I)Ljava/lang/Integer;
    //   1034: astore 11
    //   1036: goto +8 -> 1044
    //   1039: ldc_w 346
    //   1042: astore 11
    //   1044: ldc_w 348
    //   1047: iconst_5
    //   1048: anewarray 4	java/lang/Object
    //   1051: dup
    //   1052: iconst_0
    //   1053: aload_1
    //   1054: aastore
    //   1055: dup
    //   1056: iconst_1
    //   1057: lload 7
    //   1059: invokestatic 353	java/lang/Long:valueOf	(J)Ljava/lang/Long;
    //   1062: aastore
    //   1063: dup
    //   1064: iconst_2
    //   1065: aload 11
    //   1067: aastore
    //   1068: dup
    //   1069: iconst_3
    //   1070: iload_2
    //   1071: invokestatic 344	java/lang/Integer:valueOf	(I)Ljava/lang/Integer;
    //   1074: aastore
    //   1075: dup
    //   1076: iconst_4
    //   1077: aload_1
    //   1078: invokevirtual 357	com/google/android/gms/internal/ads/zzali:zzy	()Lcom/google/android/gms/internal/ads/zzakw;
    //   1081: invokevirtual 360	com/google/android/gms/internal/ads/zzakw:zza	()I
    //   1084: invokestatic 344	java/lang/Integer:valueOf	(I)Ljava/lang/Integer;
    //   1087: aastore
    //   1088: invokestatic 362	com/google/android/gms/internal/ads/zzalu:zza	(Ljava/lang/String;[Ljava/lang/Object;)V
    //   1091: goto -71 -> 1020
    //   1094: iload_2
    //   1095: sipush 200
    //   1098: if_icmplt +30 -> 1128
    //   1101: iload_2
    //   1102: sipush 299
    //   1105: if_icmpgt +23 -> 1128
    //   1108: new 239	com/google/android/gms/internal/ads/zzale
    //   1111: dup
    //   1112: iload_2
    //   1113: aload 10
    //   1115: iconst_0
    //   1116: invokestatic 40	android/os/SystemClock:elapsedRealtime	()J
    //   1119: lload 5
    //   1121: lsub
    //   1122: aload 12
    //   1124: invokespecial 242	com/google/android/gms/internal/ads/zzale:<init>	(I[BZJLjava/util/List;)V
    //   1127: areturn
    //   1128: new 34	java/io/IOException
    //   1131: astore 11
    //   1133: aload 11
    //   1135: invokespecial 363	java/io/IOException:<init>	()V
    //   1138: aload 11
    //   1140: athrow
    //   1141: astore 12
    //   1143: aload 10
    //   1145: astore 11
    //   1147: aload 12
    //   1149: astore 10
    //   1151: goto +63 -> 1214
    //   1154: astore 10
    //   1156: goto +55 -> 1211
    //   1159: astore 10
    //   1161: goto +50 -> 1211
    //   1164: new 34	java/io/IOException
    //   1167: astore 9
    //   1169: aload 9
    //   1171: ldc_w 365
    //   1174: invokespecial 366	java/io/IOException:<init>	(Ljava/lang/String;)V
    //   1177: aload 9
    //   1179: athrow
    //   1180: astore 9
    //   1182: goto +5 -> 1187
    //   1185: astore 9
    //   1187: iconst_0
    //   1188: istore_2
    //   1189: iload_2
    //   1190: ifne +8 -> 1198
    //   1193: aload 10
    //   1195: invokevirtual 234	java/net/HttpURLConnection:disconnect	()V
    //   1198: aload 9
    //   1200: athrow
    //   1201: astore 10
    //   1203: goto +5 -> 1208
    //   1206: astore 10
    //   1208: aconst_null
    //   1209: astore 9
    //   1211: aconst_null
    //   1212: astore 11
    //   1214: aload 10
    //   1216: instanceof 368
    //   1219: ifeq +26 -> 1245
    //   1222: new 370	com/google/android/gms/internal/ads/zzamk
    //   1225: dup
    //   1226: ldc_w 372
    //   1229: new 374	com/google/android/gms/internal/ads/zzalq
    //   1232: dup
    //   1233: invokespecial 375	com/google/android/gms/internal/ads/zzalq:<init>	()V
    //   1236: aconst_null
    //   1237: invokespecial 378	com/google/android/gms/internal/ads/zzamk:<init>	(Ljava/lang/String;Lcom/google/android/gms/internal/ads/zzalr;Lcom/google/android/gms/internal/ads/zzamj;)V
    //   1240: astore 9
    //   1242: goto +178 -> 1420
    //   1245: aload 10
    //   1247: instanceof 380
    //   1250: ifne +267 -> 1517
    //   1253: aload 9
    //   1255: ifnull +252 -> 1507
    //   1258: aload 9
    //   1260: invokevirtual 235	com/google/android/gms/internal/ads/zzamg:zzb	()I
    //   1263: istore_2
    //   1264: ldc_w 382
    //   1267: iconst_2
    //   1268: anewarray 4	java/lang/Object
    //   1271: dup
    //   1272: iconst_0
    //   1273: iload_2
    //   1274: invokestatic 344	java/lang/Integer:valueOf	(I)Ljava/lang/Integer;
    //   1277: aastore
    //   1278: dup
    //   1279: iconst_1
    //   1280: aload_1
    //   1281: invokevirtual 86	com/google/android/gms/internal/ads/zzali:zzk	()Ljava/lang/String;
    //   1284: aastore
    //   1285: invokestatic 384	com/google/android/gms/internal/ads/zzalu:zzb	(Ljava/lang/String;[Ljava/lang/Object;)V
    //   1288: aload 11
    //   1290: ifnull +107 -> 1397
    //   1293: aload 9
    //   1295: invokevirtual 237	com/google/android/gms/internal/ads/zzamg:zzd	()Ljava/util/List;
    //   1298: astore 9
    //   1300: new 239	com/google/android/gms/internal/ads/zzale
    //   1303: dup
    //   1304: iload_2
    //   1305: aload 11
    //   1307: iconst_0
    //   1308: invokestatic 40	android/os/SystemClock:elapsedRealtime	()J
    //   1311: lload 5
    //   1313: lsub
    //   1314: aload 9
    //   1316: invokespecial 242	com/google/android/gms/internal/ads/zzale:<init>	(I[BZJLjava/util/List;)V
    //   1319: astore 9
    //   1321: iload_2
    //   1322: sipush 401
    //   1325: if_icmpeq +47 -> 1372
    //   1328: iload_2
    //   1329: sipush 403
    //   1332: if_icmpne +6 -> 1338
    //   1335: goto +37 -> 1372
    //   1338: iload_2
    //   1339: sipush 400
    //   1342: if_icmplt +20 -> 1362
    //   1345: iload_2
    //   1346: sipush 499
    //   1349: if_icmpgt +13 -> 1362
    //   1352: new 386	com/google/android/gms/internal/ads/zzakv
    //   1355: dup
    //   1356: aload 9
    //   1358: invokespecial 389	com/google/android/gms/internal/ads/zzakv:<init>	(Lcom/google/android/gms/internal/ads/zzale;)V
    //   1361: athrow
    //   1362: new 391	com/google/android/gms/internal/ads/zzalp
    //   1365: dup
    //   1366: aload 9
    //   1368: invokespecial 392	com/google/android/gms/internal/ads/zzalp:<init>	(Lcom/google/android/gms/internal/ads/zzale;)V
    //   1371: athrow
    //   1372: new 370	com/google/android/gms/internal/ads/zzamk
    //   1375: dup
    //   1376: ldc_w 394
    //   1379: new 396	com/google/android/gms/internal/ads/zzakq
    //   1382: dup
    //   1383: aload 9
    //   1385: invokespecial 397	com/google/android/gms/internal/ads/zzakq:<init>	(Lcom/google/android/gms/internal/ads/zzale;)V
    //   1388: aconst_null
    //   1389: invokespecial 378	com/google/android/gms/internal/ads/zzamk:<init>	(Ljava/lang/String;Lcom/google/android/gms/internal/ads/zzalr;Lcom/google/android/gms/internal/ads/zzamj;)V
    //   1392: astore 9
    //   1394: goto -152 -> 1242
    //   1397: new 370	com/google/android/gms/internal/ads/zzamk
    //   1400: dup
    //   1401: ldc_w 399
    //   1404: new 401	com/google/android/gms/internal/ads/zzald
    //   1407: dup
    //   1408: invokespecial 402	com/google/android/gms/internal/ads/zzald:<init>	()V
    //   1411: aconst_null
    //   1412: invokespecial 378	com/google/android/gms/internal/ads/zzamk:<init>	(Ljava/lang/String;Lcom/google/android/gms/internal/ads/zzalr;Lcom/google/android/gms/internal/ads/zzamj;)V
    //   1415: astore 9
    //   1417: goto -175 -> 1242
    //   1420: aload_1
    //   1421: invokevirtual 357	com/google/android/gms/internal/ads/zzali:zzy	()Lcom/google/android/gms/internal/ads/zzakw;
    //   1424: astore 10
    //   1426: aload_1
    //   1427: invokevirtual 115	com/google/android/gms/internal/ads/zzali:zzb	()I
    //   1430: istore_2
    //   1431: aload 10
    //   1433: aload 9
    //   1435: invokestatic 405	com/google/android/gms/internal/ads/zzamk:zza	(Lcom/google/android/gms/internal/ads/zzamk;)Lcom/google/android/gms/internal/ads/zzalr;
    //   1438: invokevirtual 408	com/google/android/gms/internal/ads/zzakw:zzc	(Lcom/google/android/gms/internal/ads/zzalr;)V
    //   1441: aload_1
    //   1442: ldc_w 410
    //   1445: iconst_2
    //   1446: anewarray 4	java/lang/Object
    //   1449: dup
    //   1450: iconst_0
    //   1451: aload 9
    //   1453: invokestatic 413	com/google/android/gms/internal/ads/zzamk:zzb	(Lcom/google/android/gms/internal/ads/zzamk;)Ljava/lang/String;
    //   1456: aastore
    //   1457: dup
    //   1458: iconst_1
    //   1459: iload_2
    //   1460: invokestatic 344	java/lang/Integer:valueOf	(I)Ljava/lang/Integer;
    //   1463: aastore
    //   1464: invokestatic 417	java/lang/String:format	(Ljava/lang/String;[Ljava/lang/Object;)Ljava/lang/String;
    //   1467: invokevirtual 420	com/google/android/gms/internal/ads/zzali:zzm	(Ljava/lang/String;)V
    //   1470: goto -1465 -> 5
    //   1473: astore 10
    //   1475: aload_1
    //   1476: ldc_w 422
    //   1479: iconst_2
    //   1480: anewarray 4	java/lang/Object
    //   1483: dup
    //   1484: iconst_0
    //   1485: aload 9
    //   1487: invokestatic 413	com/google/android/gms/internal/ads/zzamk:zzb	(Lcom/google/android/gms/internal/ads/zzamk;)Ljava/lang/String;
    //   1490: aastore
    //   1491: dup
    //   1492: iconst_1
    //   1493: iload_2
    //   1494: invokestatic 344	java/lang/Integer:valueOf	(I)Ljava/lang/Integer;
    //   1497: aastore
    //   1498: invokestatic 417	java/lang/String:format	(Ljava/lang/String;[Ljava/lang/Object;)Ljava/lang/String;
    //   1501: invokevirtual 420	com/google/android/gms/internal/ads/zzali:zzm	(Ljava/lang/String;)V
    //   1504: aload 10
    //   1506: athrow
    //   1507: new 424	com/google/android/gms/internal/ads/zzalf
    //   1510: dup
    //   1511: aload 10
    //   1513: invokespecial 427	com/google/android/gms/internal/ads/zzalf:<init>	(Ljava/lang/Throwable;)V
    //   1516: athrow
    //   1517: new 429	java/lang/RuntimeException
    //   1520: dup
    //   1521: ldc_w 431
    //   1524: aload_1
    //   1525: invokevirtual 86	com/google/android/gms/internal/ads/zzali:zzk	()Ljava/lang/String;
    //   1528: invokestatic 434	java/lang/String:valueOf	(Ljava/lang/Object;)Ljava/lang/String;
    //   1531: invokevirtual 438	java/lang/String:concat	(Ljava/lang/String;)Ljava/lang/String;
    //   1534: aload 10
    //   1536: invokespecial 441	java/lang/RuntimeException:<init>	(Ljava/lang/String;Ljava/lang/Throwable;)V
    //   1539: athrow
    // Local variable table:
    //   start	length	slot	name	signature
    //   0	1540	0	this	zzalx
    //   0	1540	1	paramzzali	zzali
    //   10	1484	2	i	int
    //   159	733	3	j	int
    //   399	22	4	k	int
    //   3	1309	5	l1	long
    //   69	989	7	l2	long
    //   25	403	9	localObject1	Object
    //   432	1	9	localObject2	Object
    //   455	723	9	localObject3	Object
    //   1180	1	9	localObject4	Object
    //   1185	14	9	localObject5	Object
    //   1209	277	9	localObject6	Object
    //   15	1135	10	localObject7	Object
    //   1154	1	10	localIOException1	java.io.IOException
    //   1159	35	10	localIOException2	java.io.IOException
    //   1201	1	10	localIOException3	java.io.IOException
    //   1206	40	10	localIOException4	java.io.IOException
    //   1424	8	10	localzzakw	zzakw
    //   1473	62	10	localzzalr	zzalr
    //   45	695	11	localObject8	Object
    //   898	1	11	localObject9	Object
    //   908	35	11	arrayOfByte	byte[]
    //   949	38	11	localObject10	Object
    //   1034	272	11	localObject11	Object
    //   205	523	12	localObject12	Object
    //   962	161	12	localIOException5	java.io.IOException
    //   1141	7	12	localIOException6	java.io.IOException
    //   555	420	13	localObject13	Object
    //   657	325	14	localObject14	Object
    //   737	174	15	localObject15	Object
    //   918	37	15	localIOException7	java.io.IOException
    // Exception table:
    //   from	to	target	type
    //   384	429	432	finally
    //   873	881	898	finally
    //   886	895	898	finally
    //   903	910	898	finally
    //   910	915	918	java/io/IOException
    //   863	873	949	finally
    //   954	959	962	java/io/IOException
    //   994	1008	1141	java/io/IOException
    //   1028	1036	1141	java/io/IOException
    //   1044	1091	1141	java/io/IOException
    //   1108	1128	1141	java/io/IOException
    //   1128	1141	1141	java/io/IOException
    //   844	863	1154	java/io/IOException
    //   920	930	1154	java/io/IOException
    //   930	942	1154	java/io/IOException
    //   964	974	1154	java/io/IOException
    //   974	989	1154	java/io/IOException
    //   989	994	1154	java/io/IOException
    //   462	475	1159	java/io/IOException
    //   482	496	1159	java/io/IOException
    //   501	519	1159	java/io/IOException
    //   525	557	1159	java/io/IOException
    //   557	588	1159	java/io/IOException
    //   591	610	1159	java/io/IOException
    //   615	637	1159	java/io/IOException
    //   637	684	1159	java/io/IOException
    //   687	717	1159	java/io/IOException
    //   717	796	1159	java/io/IOException
    //   799	821	1159	java/io/IOException
    //   826	833	1159	java/io/IOException
    //   838	844	1159	java/io/IOException
    //   1164	1180	1180	finally
    //   195	207	1185	finally
    //   207	246	1185	finally
    //   249	269	1185	finally
    //   274	304	1185	finally
    //   304	331	1185	finally
    //   334	341	1185	finally
    //   341	347	1185	finally
    //   352	357	1185	finally
    //   437	457	1185	finally
    //   1193	1198	1201	java/io/IOException
    //   1198	1201	1201	java/io/IOException
    //   11	17	1206	java/io/IOException
    //   22	27	1206	java/io/IOException
    //   30	47	1206	java/io/IOException
    //   52	64	1206	java/io/IOException
    //   64	71	1206	java/io/IOException
    //   78	93	1206	java/io/IOException
    //   93	195	1206	java/io/IOException
    //   457	462	1206	java/io/IOException
    //   1431	1441	1473	com/google/android/gms/internal/ads/zzalr
  }
}


/* Location:              C:\Users\Ria\Documents\slope apk\dex-tools-v2.4\classes-dex2jar.jar!\com\google\android\gms\internal\ads\zzalx.class
 * Java compiler version: 6 (50.0)
 * JD-Core Version:       0.7.1
 */