package com.google.android.gms.internal.ads;

final class zzape
  implements Runnable
{
  /* Error */
  public final void run()
  {
    // Byte code:
    //   0: ldc 17
    //   2: invokestatic 23	java/security/MessageDigest:getInstance	(Ljava/lang/String;)Ljava/security/MessageDigest;
    //   5: invokestatic 29	com/google/android/gms/internal/ads/zzapf:zzc	(Ljava/security/MessageDigest;)V
    //   8: getstatic 33	com/google/android/gms/internal/ads/zzapf:zzb	Ljava/util/concurrent/CountDownLatch;
    //   11: astore_1
    //   12: aload_1
    //   13: invokevirtual 38	java/util/concurrent/CountDownLatch:countDown	()V
    //   16: return
    //   17: astore_1
    //   18: getstatic 33	com/google/android/gms/internal/ads/zzapf:zzb	Ljava/util/concurrent/CountDownLatch;
    //   21: invokevirtual 38	java/util/concurrent/CountDownLatch:countDown	()V
    //   24: aload_1
    //   25: athrow
    //   26: astore_1
    //   27: getstatic 33	com/google/android/gms/internal/ads/zzapf:zzb	Ljava/util/concurrent/CountDownLatch;
    //   30: astore_1
    //   31: goto -19 -> 12
    // Local variable table:
    //   start	length	slot	name	signature
    //   0	34	0	this	zzape
    //   11	2	1	localCountDownLatch1	java.util.concurrent.CountDownLatch
    //   17	8	1	localObject	Object
    //   26	1	1	localNoSuchAlgorithmException	java.security.NoSuchAlgorithmException
    //   30	1	1	localCountDownLatch2	java.util.concurrent.CountDownLatch
    // Exception table:
    //   from	to	target	type
    //   0	8	17	finally
    //   0	8	26	java/security/NoSuchAlgorithmException
  }
}


/* Location:              C:\Users\Ria\Documents\slope apk\dex-tools-v2.4\classes-dex2jar.jar!\com\google\android\gms\internal\ads\zzape.class
 * Java compiler version: 6 (50.0)
 * JD-Core Version:       0.7.1
 */