package com.google.android.gms.internal.ads;

final class zzarp
  implements Runnable
{
  final zzarr zzb;
  
  zzarp(zzarr paramzzarr, int paramInt, boolean paramBoolean) {}
  
  /* Error */
  public final void run()
  {
    // Byte code:
    //   0: aload_0
    //   1: getfield 14	com/google/android/gms/internal/ads/zzarp:zzb	Lcom/google/android/gms/internal/ads/zzarr;
    //   4: astore 4
    //   6: aload_0
    //   7: getfield 16	com/google/android/gms/internal/ads/zzarp:zza	I
    //   10: istore_1
    //   11: iload_1
    //   12: ifle +14 -> 26
    //   15: iload_1
    //   16: sipush 1000
    //   19: imul
    //   20: i2l
    //   21: lstore_2
    //   22: lload_2
    //   23: invokestatic 29	java/lang/Thread:sleep	(J)V
    //   26: aload 4
    //   28: getfield 34	com/google/android/gms/internal/ads/zzarr:zza	Landroid/content/Context;
    //   31: invokevirtual 40	android/content/Context:getPackageManager	()Landroid/content/pm/PackageManager;
    //   34: aload 4
    //   36: getfield 34	com/google/android/gms/internal/ads/zzarr:zza	Landroid/content/Context;
    //   39: invokevirtual 44	android/content/Context:getPackageName	()Ljava/lang/String;
    //   42: iconst_0
    //   43: invokevirtual 50	android/content/pm/PackageManager:getPackageInfo	(Ljava/lang/String;I)Landroid/content/pm/PackageInfo;
    //   46: astore 5
    //   48: aload 4
    //   50: getfield 34	com/google/android/gms/internal/ads/zzarr:zza	Landroid/content/Context;
    //   53: astore 4
    //   55: aload 4
    //   57: aload 4
    //   59: invokevirtual 44	android/content/Context:getPackageName	()Ljava/lang/String;
    //   62: aload 5
    //   64: getfield 55	android/content/pm/PackageInfo:versionCode	I
    //   67: invokestatic 61	java/lang/Integer:toString	(I)Ljava/lang/String;
    //   70: invokestatic 66	com/google/android/gms/internal/ads/zzfjb:zza	(Landroid/content/Context;Ljava/lang/String;Ljava/lang/String;)Lcom/google/android/gms/internal/ads/zzaol;
    //   73: astore 4
    //   75: goto +8 -> 83
    //   78: astore 4
    //   80: aconst_null
    //   81: astore 4
    //   83: aload_0
    //   84: getfield 14	com/google/android/gms/internal/ads/zzarp:zzb	Lcom/google/android/gms/internal/ads/zzarr;
    //   87: aload 4
    //   89: invokestatic 70	com/google/android/gms/internal/ads/zzarr:zzm	(Lcom/google/android/gms/internal/ads/zzarr;Lcom/google/android/gms/internal/ads/zzaol;)V
    //   92: aload_0
    //   93: getfield 16	com/google/android/gms/internal/ads/zzarp:zza	I
    //   96: iconst_4
    //   97: if_icmpge +83 -> 180
    //   100: aload 4
    //   102: ifnonnull +6 -> 108
    //   105: goto +61 -> 166
    //   108: aload 4
    //   110: invokevirtual 76	com/google/android/gms/internal/ads/zzaol:zzaj	()Z
    //   113: ifeq +53 -> 166
    //   116: aload 4
    //   118: invokevirtual 79	com/google/android/gms/internal/ads/zzaol:zzh	()Ljava/lang/String;
    //   121: ldc 81
    //   123: invokevirtual 87	java/lang/String:equals	(Ljava/lang/Object;)Z
    //   126: ifne +40 -> 166
    //   129: aload 4
    //   131: invokevirtual 90	com/google/android/gms/internal/ads/zzaol:zzak	()Z
    //   134: ifeq +32 -> 166
    //   137: aload 4
    //   139: invokevirtual 94	com/google/android/gms/internal/ads/zzaol:zzf	()Lcom/google/android/gms/internal/ads/zzaou;
    //   142: invokevirtual 99	com/google/android/gms/internal/ads/zzaou:zze	()Z
    //   145: ifeq +21 -> 166
    //   148: aload 4
    //   150: invokevirtual 94	com/google/android/gms/internal/ads/zzaol:zzf	()Lcom/google/android/gms/internal/ads/zzaou;
    //   153: invokevirtual 102	com/google/android/gms/internal/ads/zzaou:zza	()J
    //   156: ldc2_w 103
    //   159: lcmp
    //   160: ifeq +6 -> 166
    //   163: goto +17 -> 180
    //   166: aload_0
    //   167: getfield 14	com/google/android/gms/internal/ads/zzarp:zzb	Lcom/google/android/gms/internal/ads/zzarr;
    //   170: aload_0
    //   171: getfield 16	com/google/android/gms/internal/ads/zzarp:zza	I
    //   174: iconst_1
    //   175: iadd
    //   176: iconst_1
    //   177: invokevirtual 108	com/google/android/gms/internal/ads/zzarr:zzo	(IZ)V
    //   180: return
    //   181: astore 5
    //   183: goto -157 -> 26
    // Local variable table:
    //   start	length	slot	name	signature
    //   0	186	0	this	zzarp
    //   10	10	1	i	int
    //   21	2	2	l	long
    //   4	70	4	localObject1	Object
    //   78	1	4	localObject2	Object
    //   81	68	4	localzzaol	zzaol
    //   46	17	5	localPackageInfo	android.content.pm.PackageInfo
    //   181	1	5	localInterruptedException	InterruptedException
    // Exception table:
    //   from	to	target	type
    //   26	75	78	finally
    //   22	26	181	java/lang/InterruptedException
  }
}


/* Location:              C:\Users\Ria\Documents\slope apk\dex-tools-v2.4\classes-dex2jar.jar!\com\google\android\gms\internal\ads\zzarp.class
 * Java compiler version: 6 (50.0)
 * JD-Core Version:       0.7.1
 */