package com.google.android.gms.internal.ads;

import android.content.Context;
import android.util.Log;
import android.util.Pair;
import com.google.android.gms.ads.identifier.AdvertisingIdClient;
import com.google.android.gms.common.GooglePlayServicesNotAvailableException;
import com.google.android.gms.common.GooglePlayServicesRepairableException;
import dalvik.system.DexClassLoader;
import java.io.File;
import java.io.IOException;
import java.lang.reflect.Method;
import java.util.HashMap;
import java.util.Map;
import java.util.concurrent.ExecutionException;
import java.util.concurrent.ExecutorService;
import java.util.concurrent.Future;
import java.util.concurrent.TimeUnit;
import java.util.concurrent.TimeoutException;

public final class zzarr
{
  private static final String zzd = "zzarr";
  protected final Context zza;
  protected boolean zzb;
  protected boolean zzc;
  private ExecutorService zze;
  private DexClassLoader zzf;
  private zzaqw zzg;
  private byte[] zzh;
  private volatile AdvertisingIdClient zzi = null;
  private volatile boolean zzj;
  private Future zzk;
  private final boolean zzl;
  private volatile zzaol zzm;
  private Future zzn;
  private zzaql zzo;
  private final Map zzp;
  private boolean zzq;
  private zzark zzr;
  
  private zzarr(Context paramContext)
  {
    boolean bool = false;
    this.zzj = false;
    this.zzk = null;
    this.zzm = null;
    this.zzn = null;
    this.zzb = false;
    this.zzc = false;
    this.zzq = false;
    Context localContext = paramContext.getApplicationContext();
    if (localContext != null) {
      bool = true;
    }
    this.zzl = bool;
    if (localContext != null) {
      paramContext = localContext;
    }
    this.zza = paramContext;
    this.zzp = new HashMap();
    if (this.zzr != null) {
      return;
    }
    this.zzr = new zzark(paramContext);
  }
  
  /* Error */
  public static zzarr zzg(Context paramContext, String paramString1, String paramString2, boolean paramBoolean)
  {
    // Byte code:
    //   0: new 2	com/google/android/gms/internal/ads/zzarr
    //   3: dup
    //   4: aload_0
    //   5: invokespecial 95	com/google/android/gms/internal/ads/zzarr:<init>	(Landroid/content/Context;)V
    //   8: astore_2
    //   9: new 97	com/google/android/gms/internal/ads/zzarn
    //   12: astore_0
    //   13: aload_0
    //   14: invokespecial 98	com/google/android/gms/internal/ads/zzarn:<init>	()V
    //   17: aload_2
    //   18: aload_0
    //   19: invokestatic 104	java/util/concurrent/Executors:newCachedThreadPool	(Ljava/util/concurrent/ThreadFactory;)Ljava/util/concurrent/ExecutorService;
    //   22: putfield 106	com/google/android/gms/internal/ads/zzarr:zze	Ljava/util/concurrent/ExecutorService;
    //   25: aload_2
    //   26: iload_3
    //   27: putfield 48	com/google/android/gms/internal/ads/zzarr:zzj	Z
    //   30: iload_3
    //   31: ifeq +28 -> 59
    //   34: aload_2
    //   35: getfield 106	com/google/android/gms/internal/ads/zzarr:zze	Ljava/util/concurrent/ExecutorService;
    //   38: astore_1
    //   39: new 108	com/google/android/gms/internal/ads/zzaro
    //   42: astore_0
    //   43: aload_0
    //   44: aload_2
    //   45: invokespecial 111	com/google/android/gms/internal/ads/zzaro:<init>	(Lcom/google/android/gms/internal/ads/zzarr;)V
    //   48: aload_2
    //   49: aload_1
    //   50: aload_0
    //   51: invokeinterface 117 2 0
    //   56: putfield 50	com/google/android/gms/internal/ads/zzarr:zzk	Ljava/util/concurrent/Future;
    //   59: aload_2
    //   60: getfield 106	com/google/android/gms/internal/ads/zzarr:zze	Ljava/util/concurrent/ExecutorService;
    //   63: astore_1
    //   64: new 119	com/google/android/gms/internal/ads/zzarq
    //   67: astore_0
    //   68: aload_0
    //   69: aload_2
    //   70: invokespecial 120	com/google/android/gms/internal/ads/zzarq:<init>	(Lcom/google/android/gms/internal/ads/zzarr;)V
    //   73: aload_1
    //   74: aload_0
    //   75: invokeinterface 124 2 0
    //   80: invokestatic 130	com/google/android/gms/common/GoogleApiAvailabilityLight:getInstance	()Lcom/google/android/gms/common/GoogleApiAvailabilityLight;
    //   83: astore_0
    //   84: aload_0
    //   85: aload_2
    //   86: getfield 70	com/google/android/gms/internal/ads/zzarr:zza	Landroid/content/Context;
    //   89: invokevirtual 134	com/google/android/gms/common/GoogleApiAvailabilityLight:getApkVersion	(Landroid/content/Context;)I
    //   92: ifle +8 -> 100
    //   95: iconst_1
    //   96: istore_3
    //   97: goto +5 -> 102
    //   100: iconst_0
    //   101: istore_3
    //   102: aload_2
    //   103: iload_3
    //   104: putfield 56	com/google/android/gms/internal/ads/zzarr:zzb	Z
    //   107: aload_0
    //   108: aload_2
    //   109: getfield 70	com/google/android/gms/internal/ads/zzarr:zza	Landroid/content/Context;
    //   112: invokevirtual 137	com/google/android/gms/common/GoogleApiAvailabilityLight:isGooglePlayServicesAvailable	(Landroid/content/Context;)I
    //   115: ifne +8 -> 123
    //   118: iconst_1
    //   119: istore_3
    //   120: goto +5 -> 125
    //   123: iconst_0
    //   124: istore_3
    //   125: aload_2
    //   126: iload_3
    //   127: putfield 58	com/google/android/gms/internal/ads/zzarr:zzc	Z
    //   130: aload_2
    //   131: iconst_0
    //   132: iconst_1
    //   133: invokevirtual 140	com/google/android/gms/internal/ads/zzarr:zzo	(IZ)V
    //   136: invokestatic 145	com/google/android/gms/internal/ads/zzaru:zzc	()Z
    //   139: ifeq +38 -> 177
    //   142: getstatic 151	com/google/android/gms/internal/ads/zzbbk:zzcV	Lcom/google/android/gms/internal/ads/zzbbc;
    //   145: astore_0
    //   146: invokestatic 156	com/google/android/gms/ads/internal/client/zzba:zzc	()Lcom/google/android/gms/internal/ads/zzbbi;
    //   149: aload_0
    //   150: invokevirtual 161	com/google/android/gms/internal/ads/zzbbi:zzb	(Lcom/google/android/gms/internal/ads/zzbbc;)Ljava/lang/Object;
    //   153: checkcast 163	java/lang/Boolean
    //   156: invokevirtual 166	java/lang/Boolean:booleanValue	()Z
    //   159: ifne +6 -> 165
    //   162: goto +15 -> 177
    //   165: new 168	java/lang/IllegalStateException
    //   168: astore_0
    //   169: aload_0
    //   170: ldc -86
    //   172: invokespecial 173	java/lang/IllegalStateException:<init>	(Ljava/lang/String;)V
    //   175: aload_0
    //   176: athrow
    //   177: new 175	com/google/android/gms/internal/ads/zzaqw
    //   180: astore_0
    //   181: aload_0
    //   182: aconst_null
    //   183: invokespecial 178	com/google/android/gms/internal/ads/zzaqw:<init>	(Ljava/security/SecureRandom;)V
    //   186: aload_2
    //   187: aload_0
    //   188: putfield 180	com/google/android/gms/internal/ads/zzarr:zzg	Lcom/google/android/gms/internal/ads/zzaqw;
    //   191: ldc -74
    //   193: iconst_0
    //   194: invokestatic 187	com/google/android/gms/internal/ads/zzapb:zzb	(Ljava/lang/String;Z)[B
    //   197: astore_1
    //   198: aload_1
    //   199: arraylength
    //   200: bipush 32
    //   202: if_icmpne +373 -> 575
    //   205: aload_1
    //   206: iconst_4
    //   207: bipush 16
    //   209: invokestatic 193	java/nio/ByteBuffer:wrap	([BII)Ljava/nio/ByteBuffer;
    //   212: astore 5
    //   214: bipush 16
    //   216: newarray <illegal type>
    //   218: astore_1
    //   219: aload 5
    //   221: aload_1
    //   222: invokevirtual 197	java/nio/ByteBuffer:get	([B)Ljava/nio/ByteBuffer;
    //   225: pop
    //   226: iconst_0
    //   227: istore 4
    //   229: iload 4
    //   231: bipush 16
    //   233: if_icmpge +21 -> 254
    //   236: aload_1
    //   237: iload 4
    //   239: aload_1
    //   240: iload 4
    //   242: baload
    //   243: bipush 68
    //   245: ixor
    //   246: i2b
    //   247: bastore
    //   248: iinc 4 1
    //   251: goto -22 -> 229
    //   254: aload_2
    //   255: aload_1
    //   256: putfield 199	com/google/android/gms/internal/ads/zzarr:zzh	[B
    //   259: aload_2
    //   260: getfield 70	com/google/android/gms/internal/ads/zzarr:zza	Landroid/content/Context;
    //   263: invokevirtual 203	android/content/Context:getCacheDir	()Ljava/io/File;
    //   266: astore_1
    //   267: aload_1
    //   268: astore_0
    //   269: aload_1
    //   270: ifnonnull +31 -> 301
    //   273: aload_2
    //   274: getfield 70	com/google/android/gms/internal/ads/zzarr:zza	Landroid/content/Context;
    //   277: ldc -51
    //   279: iconst_0
    //   280: invokevirtual 209	android/content/Context:getDir	(Ljava/lang/String;I)Ljava/io/File;
    //   283: astore_0
    //   284: aload_0
    //   285: ifnull +6 -> 291
    //   288: goto +13 -> 301
    //   291: new 84	com/google/android/gms/internal/ads/zzarh
    //   294: astore_0
    //   295: aload_0
    //   296: invokespecial 210	com/google/android/gms/internal/ads/zzarh:<init>	()V
    //   299: aload_0
    //   300: athrow
    //   301: new 212	java/io/File
    //   304: astore_1
    //   305: aload_1
    //   306: ldc -42
    //   308: iconst_2
    //   309: anewarray 4	java/lang/Object
    //   312: dup
    //   313: iconst_0
    //   314: aload_0
    //   315: aastore
    //   316: dup
    //   317: iconst_1
    //   318: ldc -40
    //   320: aastore
    //   321: invokestatic 222	java/lang/String:format	(Ljava/lang/String;[Ljava/lang/Object;)Ljava/lang/String;
    //   324: invokespecial 223	java/io/File:<init>	(Ljava/lang/String;)V
    //   327: aload_1
    //   328: invokevirtual 226	java/io/File:exists	()Z
    //   331: ifne +63 -> 394
    //   334: aload_2
    //   335: getfield 180	com/google/android/gms/internal/ads/zzarr:zzg	Lcom/google/android/gms/internal/ads/zzaqw;
    //   338: aload_2
    //   339: getfield 199	com/google/android/gms/internal/ads/zzarr:zzh	[B
    //   342: ldc -28
    //   344: invokevirtual 231	com/google/android/gms/internal/ads/zzaqw:zzb	([BLjava/lang/String;)[B
    //   347: astore 5
    //   349: aload_1
    //   350: invokevirtual 234	java/io/File:createNewFile	()Z
    //   353: pop
    //   354: new 236	java/io/FileOutputStream
    //   357: astore 6
    //   359: aload 6
    //   361: aload_1
    //   362: invokespecial 239	java/io/FileOutputStream:<init>	(Ljava/io/File;)V
    //   365: getstatic 245	android/os/Build$VERSION:SDK_INT	I
    //   368: bipush 33
    //   370: if_icmplt +8 -> 378
    //   373: aload_1
    //   374: invokevirtual 248	java/io/File:setReadOnly	()Z
    //   377: pop
    //   378: aload 6
    //   380: aload 5
    //   382: iconst_0
    //   383: aload 5
    //   385: arraylength
    //   386: invokevirtual 252	java/io/FileOutputStream:write	([BII)V
    //   389: aload 6
    //   391: invokevirtual 255	java/io/FileOutputStream:close	()V
    //   394: aload_2
    //   395: aload_0
    //   396: ldc -40
    //   398: invokespecial 259	com/google/android/gms/internal/ads/zzarr:zzx	(Ljava/io/File;Ljava/lang/String;)Z
    //   401: pop
    //   402: new 261	dalvik/system/DexClassLoader
    //   405: astore 5
    //   407: aload 5
    //   409: aload_1
    //   410: invokevirtual 265	java/io/File:getAbsolutePath	()Ljava/lang/String;
    //   413: aload_0
    //   414: invokevirtual 265	java/io/File:getAbsolutePath	()Ljava/lang/String;
    //   417: aconst_null
    //   418: aload_2
    //   419: getfield 70	com/google/android/gms/internal/ads/zzarr:zza	Landroid/content/Context;
    //   422: invokevirtual 269	android/content/Context:getClassLoader	()Ljava/lang/ClassLoader;
    //   425: invokespecial 272	dalvik/system/DexClassLoader:<init>	(Ljava/lang/String;Ljava/lang/String;Ljava/lang/String;Ljava/lang/ClassLoader;)V
    //   428: aload_2
    //   429: aload 5
    //   431: putfield 274	com/google/android/gms/internal/ads/zzarr:zzf	Ldalvik/system/DexClassLoader;
    //   434: aload_1
    //   435: invokestatic 277	com/google/android/gms/internal/ads/zzarr:zzy	(Ljava/io/File;)V
    //   438: aload_2
    //   439: aload_0
    //   440: ldc -40
    //   442: invokespecial 281	com/google/android/gms/internal/ads/zzarr:zzw	(Ljava/io/File;Ljava/lang/String;)V
    //   445: ldc_w 283
    //   448: iconst_2
    //   449: anewarray 4	java/lang/Object
    //   452: dup
    //   453: iconst_0
    //   454: aload_0
    //   455: aastore
    //   456: dup
    //   457: iconst_1
    //   458: ldc -40
    //   460: aastore
    //   461: invokestatic 222	java/lang/String:format	(Ljava/lang/String;[Ljava/lang/Object;)Ljava/lang/String;
    //   464: invokestatic 286	com/google/android/gms/internal/ads/zzarr:zzz	(Ljava/lang/String;)V
    //   467: new 288	com/google/android/gms/internal/ads/zzaql
    //   470: astore_0
    //   471: aload_0
    //   472: aload_2
    //   473: invokespecial 289	com/google/android/gms/internal/ads/zzaql:<init>	(Lcom/google/android/gms/internal/ads/zzarr;)V
    //   476: aload_2
    //   477: aload_0
    //   478: putfield 291	com/google/android/gms/internal/ads/zzarr:zzo	Lcom/google/android/gms/internal/ads/zzaql;
    //   481: aload_2
    //   482: iconst_1
    //   483: putfield 60	com/google/android/gms/internal/ads/zzarr:zzq	Z
    //   486: goto +128 -> 614
    //   489: astore 5
    //   491: aload_1
    //   492: invokestatic 277	com/google/android/gms/internal/ads/zzarr:zzy	(Ljava/io/File;)V
    //   495: aload_2
    //   496: aload_0
    //   497: ldc -40
    //   499: invokespecial 281	com/google/android/gms/internal/ads/zzarr:zzw	(Ljava/io/File;Ljava/lang/String;)V
    //   502: ldc_w 283
    //   505: iconst_2
    //   506: anewarray 4	java/lang/Object
    //   509: dup
    //   510: iconst_0
    //   511: aload_0
    //   512: aastore
    //   513: dup
    //   514: iconst_1
    //   515: ldc -40
    //   517: aastore
    //   518: invokestatic 222	java/lang/String:format	(Ljava/lang/String;[Ljava/lang/Object;)Ljava/lang/String;
    //   521: invokestatic 286	com/google/android/gms/internal/ads/zzarr:zzz	(Ljava/lang/String;)V
    //   524: aload 5
    //   526: athrow
    //   527: astore_0
    //   528: new 84	com/google/android/gms/internal/ads/zzarh
    //   531: astore_1
    //   532: aload_1
    //   533: aload_0
    //   534: invokespecial 294	com/google/android/gms/internal/ads/zzarh:<init>	(Ljava/lang/Throwable;)V
    //   537: aload_1
    //   538: athrow
    //   539: astore_1
    //   540: new 84	com/google/android/gms/internal/ads/zzarh
    //   543: astore_0
    //   544: aload_0
    //   545: aload_1
    //   546: invokespecial 294	com/google/android/gms/internal/ads/zzarh:<init>	(Ljava/lang/Throwable;)V
    //   549: aload_0
    //   550: athrow
    //   551: astore_1
    //   552: new 84	com/google/android/gms/internal/ads/zzarh
    //   555: astore_0
    //   556: aload_0
    //   557: aload_1
    //   558: invokespecial 294	com/google/android/gms/internal/ads/zzarh:<init>	(Ljava/lang/Throwable;)V
    //   561: aload_0
    //   562: athrow
    //   563: astore_1
    //   564: new 84	com/google/android/gms/internal/ads/zzarh
    //   567: astore_0
    //   568: aload_0
    //   569: aload_1
    //   570: invokespecial 294	com/google/android/gms/internal/ads/zzarh:<init>	(Ljava/lang/Throwable;)V
    //   573: aload_0
    //   574: athrow
    //   575: new 88	com/google/android/gms/internal/ads/zzaqv
    //   578: astore_1
    //   579: aload_1
    //   580: aload_0
    //   581: invokespecial 297	com/google/android/gms/internal/ads/zzaqv:<init>	(Lcom/google/android/gms/internal/ads/zzaqw;)V
    //   584: aload_1
    //   585: athrow
    //   586: astore_1
    //   587: new 88	com/google/android/gms/internal/ads/zzaqv
    //   590: astore 5
    //   592: aload 5
    //   594: aload_0
    //   595: aload_1
    //   596: invokespecial 300	com/google/android/gms/internal/ads/zzaqv:<init>	(Lcom/google/android/gms/internal/ads/zzaqw;Ljava/lang/Throwable;)V
    //   599: aload 5
    //   601: athrow
    //   602: astore_1
    //   603: new 84	com/google/android/gms/internal/ads/zzarh
    //   606: astore_0
    //   607: aload_0
    //   608: aload_1
    //   609: invokespecial 294	com/google/android/gms/internal/ads/zzarh:<init>	(Ljava/lang/Throwable;)V
    //   612: aload_0
    //   613: athrow
    //   614: aload_2
    //   615: areturn
    //   616: astore_0
    //   617: goto -3 -> 614
    //   620: astore_0
    //   621: goto -491 -> 130
    // Local variable table:
    //   start	length	slot	name	signature
    //   0	624	0	paramContext	Context
    //   0	624	1	paramString1	String
    //   0	624	2	paramString2	String
    //   0	624	3	paramBoolean	boolean
    //   227	22	4	i	int
    //   212	218	5	localObject1	Object
    //   489	36	5	localObject2	Object
    //   590	10	5	localzzaqv	zzaqv
    //   357	33	6	localFileOutputStream	java.io.FileOutputStream
    // Exception table:
    //   from	to	target	type
    //   402	434	489	finally
    //   259	267	527	java/lang/NullPointerException
    //   273	284	527	java/lang/NullPointerException
    //   291	301	527	java/lang/NullPointerException
    //   301	378	527	java/lang/NullPointerException
    //   378	394	527	java/lang/NullPointerException
    //   394	402	527	java/lang/NullPointerException
    //   434	467	527	java/lang/NullPointerException
    //   491	527	527	java/lang/NullPointerException
    //   259	267	539	com/google/android/gms/internal/ads/zzaqv
    //   273	284	539	com/google/android/gms/internal/ads/zzaqv
    //   291	301	539	com/google/android/gms/internal/ads/zzaqv
    //   301	378	539	com/google/android/gms/internal/ads/zzaqv
    //   378	394	539	com/google/android/gms/internal/ads/zzaqv
    //   394	402	539	com/google/android/gms/internal/ads/zzaqv
    //   434	467	539	com/google/android/gms/internal/ads/zzaqv
    //   491	527	539	com/google/android/gms/internal/ads/zzaqv
    //   259	267	551	java/io/IOException
    //   273	284	551	java/io/IOException
    //   291	301	551	java/io/IOException
    //   301	378	551	java/io/IOException
    //   378	394	551	java/io/IOException
    //   394	402	551	java/io/IOException
    //   434	467	551	java/io/IOException
    //   491	527	551	java/io/IOException
    //   259	267	563	java/io/FileNotFoundException
    //   273	284	563	java/io/FileNotFoundException
    //   291	301	563	java/io/FileNotFoundException
    //   301	378	563	java/io/FileNotFoundException
    //   378	394	563	java/io/FileNotFoundException
    //   394	402	563	java/io/FileNotFoundException
    //   434	467	563	java/io/FileNotFoundException
    //   491	527	563	java/io/FileNotFoundException
    //   191	226	586	java/lang/IllegalArgumentException
    //   575	586	586	java/lang/IllegalArgumentException
    //   191	226	602	com/google/android/gms/internal/ads/zzaqv
    //   254	259	602	com/google/android/gms/internal/ads/zzaqv
    //   575	586	602	com/google/android/gms/internal/ads/zzaqv
    //   587	602	602	com/google/android/gms/internal/ads/zzaqv
    //   9	30	616	com/google/android/gms/internal/ads/zzarh
    //   34	59	616	com/google/android/gms/internal/ads/zzarh
    //   59	80	616	com/google/android/gms/internal/ads/zzarh
    //   130	162	616	com/google/android/gms/internal/ads/zzarh
    //   165	177	616	com/google/android/gms/internal/ads/zzarh
    //   177	191	616	com/google/android/gms/internal/ads/zzarh
    //   191	226	616	com/google/android/gms/internal/ads/zzarh
    //   254	259	616	com/google/android/gms/internal/ads/zzarh
    //   259	267	616	com/google/android/gms/internal/ads/zzarh
    //   273	284	616	com/google/android/gms/internal/ads/zzarh
    //   291	301	616	com/google/android/gms/internal/ads/zzarh
    //   301	378	616	com/google/android/gms/internal/ads/zzarh
    //   378	394	616	com/google/android/gms/internal/ads/zzarh
    //   394	402	616	com/google/android/gms/internal/ads/zzarh
    //   434	467	616	com/google/android/gms/internal/ads/zzarh
    //   467	486	616	com/google/android/gms/internal/ads/zzarh
    //   491	527	616	com/google/android/gms/internal/ads/zzarh
    //   528	539	616	com/google/android/gms/internal/ads/zzarh
    //   540	551	616	com/google/android/gms/internal/ads/zzarh
    //   552	563	616	com/google/android/gms/internal/ads/zzarh
    //   564	575	616	com/google/android/gms/internal/ads/zzarh
    //   575	586	616	com/google/android/gms/internal/ads/zzarh
    //   587	602	616	com/google/android/gms/internal/ads/zzarh
    //   603	614	616	com/google/android/gms/internal/ads/zzarh
    //   80	95	620	finally
    //   102	118	620	finally
    //   125	130	620	finally
  }
  
  private final void zzv()
  {
    try
    {
      if ((this.zzi == null) && (this.zzl))
      {
        AdvertisingIdClient localAdvertisingIdClient = new com/google/android/gms/ads/identifier/AdvertisingIdClient;
        localAdvertisingIdClient.<init>(this.zza);
        localAdvertisingIdClient.start();
        this.zzi = localAdvertisingIdClient;
      }
      return;
    }
    catch (GooglePlayServicesNotAvailableException|IOException|GooglePlayServicesRepairableException localGooglePlayServicesNotAvailableException)
    {
      this.zzi = null;
    }
  }
  
  /* Error */
  private final void zzw(File paramFile, String paramString)
  {
    // Byte code:
    //   0: new 212	java/io/File
    //   3: dup
    //   4: ldc_w 318
    //   7: iconst_2
    //   8: anewarray 4	java/lang/Object
    //   11: dup
    //   12: iconst_0
    //   13: aload_1
    //   14: aastore
    //   15: dup
    //   16: iconst_1
    //   17: ldc -40
    //   19: aastore
    //   20: invokestatic 222	java/lang/String:format	(Ljava/lang/String;[Ljava/lang/Object;)Ljava/lang/String;
    //   23: invokespecial 223	java/io/File:<init>	(Ljava/lang/String;)V
    //   26: astore 9
    //   28: aload 9
    //   30: invokevirtual 226	java/io/File:exists	()Z
    //   33: ifeq +4 -> 37
    //   36: return
    //   37: new 212	java/io/File
    //   40: dup
    //   41: ldc_w 283
    //   44: iconst_2
    //   45: anewarray 4	java/lang/Object
    //   48: dup
    //   49: iconst_0
    //   50: aload_1
    //   51: aastore
    //   52: dup
    //   53: iconst_1
    //   54: ldc -40
    //   56: aastore
    //   57: invokestatic 222	java/lang/String:format	(Ljava/lang/String;[Ljava/lang/Object;)Ljava/lang/String;
    //   60: invokespecial 223	java/io/File:<init>	(Ljava/lang/String;)V
    //   63: astore 8
    //   65: aload 8
    //   67: invokevirtual 226	java/io/File:exists	()Z
    //   70: ifne +4 -> 74
    //   73: return
    //   74: aload 8
    //   76: invokevirtual 322	java/io/File:length	()J
    //   79: lstore 4
    //   81: lload 4
    //   83: lconst_0
    //   84: lcmp
    //   85: ifgt +4 -> 89
    //   88: return
    //   89: lload 4
    //   91: l2i
    //   92: newarray <illegal type>
    //   94: astore_1
    //   95: aconst_null
    //   96: astore_2
    //   97: aconst_null
    //   98: astore 7
    //   100: new 324	java/io/FileInputStream
    //   103: astore 6
    //   105: aload 6
    //   107: aload 8
    //   109: invokespecial 325	java/io/FileInputStream:<init>	(Ljava/io/File;)V
    //   112: aload 6
    //   114: aload_1
    //   115: invokevirtual 329	java/io/FileInputStream:read	([B)I
    //   118: istore_3
    //   119: iload_3
    //   120: ifgt +14 -> 134
    //   123: aload 6
    //   125: invokevirtual 330	java/io/FileInputStream:close	()V
    //   128: aload 8
    //   130: invokestatic 277	com/google/android/gms/internal/ads/zzarr:zzy	(Ljava/io/File;)V
    //   133: return
    //   134: getstatic 336	java/lang/System:out	Ljava/io/PrintStream;
    //   137: ldc_w 338
    //   140: invokevirtual 343	java/io/PrintStream:print	(Ljava/lang/String;)V
    //   143: getstatic 336	java/lang/System:out	Ljava/io/PrintStream;
    //   146: ldc_w 338
    //   149: invokevirtual 343	java/io/PrintStream:print	(Ljava/lang/String;)V
    //   152: getstatic 336	java/lang/System:out	Ljava/io/PrintStream;
    //   155: ldc_w 338
    //   158: invokevirtual 343	java/io/PrintStream:print	(Ljava/lang/String;)V
    //   161: invokestatic 348	com/google/android/gms/internal/ads/zzaop:zza	()Lcom/google/android/gms/internal/ads/zzaoo;
    //   164: astore_2
    //   165: getstatic 351	android/os/Build$VERSION:SDK	Ljava/lang/String;
    //   168: invokevirtual 355	java/lang/String:getBytes	()[B
    //   171: astore 10
    //   173: getstatic 360	com/google/android/gms/internal/ads/zzgno:zzb	Lcom/google/android/gms/internal/ads/zzgno;
    //   176: astore 7
    //   178: aload_2
    //   179: aload 10
    //   181: iconst_0
    //   182: aload 10
    //   184: arraylength
    //   185: invokestatic 363	com/google/android/gms/internal/ads/zzgno:zzv	([BII)Lcom/google/android/gms/internal/ads/zzgno;
    //   188: invokevirtual 368	com/google/android/gms/internal/ads/zzaoo:zzc	(Lcom/google/android/gms/internal/ads/zzgno;)Lcom/google/android/gms/internal/ads/zzaoo;
    //   191: pop
    //   192: ldc -40
    //   194: invokevirtual 355	java/lang/String:getBytes	()[B
    //   197: astore 7
    //   199: aload_2
    //   200: aload 7
    //   202: iconst_0
    //   203: aload 7
    //   205: arraylength
    //   206: invokestatic 363	com/google/android/gms/internal/ads/zzgno:zzv	([BII)Lcom/google/android/gms/internal/ads/zzgno;
    //   209: invokevirtual 370	com/google/android/gms/internal/ads/zzaoo:zzd	(Lcom/google/android/gms/internal/ads/zzgno;)Lcom/google/android/gms/internal/ads/zzaoo;
    //   212: pop
    //   213: aload_0
    //   214: getfield 180	com/google/android/gms/internal/ads/zzarr:zzg	Lcom/google/android/gms/internal/ads/zzaqw;
    //   217: aload_0
    //   218: getfield 199	com/google/android/gms/internal/ads/zzarr:zzh	[B
    //   221: aload_1
    //   222: invokevirtual 373	com/google/android/gms/internal/ads/zzaqw:zza	([B[B)Ljava/lang/String;
    //   225: invokevirtual 355	java/lang/String:getBytes	()[B
    //   228: astore_1
    //   229: aload_2
    //   230: aload_1
    //   231: iconst_0
    //   232: aload_1
    //   233: arraylength
    //   234: invokestatic 363	com/google/android/gms/internal/ads/zzgno:zzv	([BII)Lcom/google/android/gms/internal/ads/zzgno;
    //   237: invokevirtual 375	com/google/android/gms/internal/ads/zzaoo:zza	(Lcom/google/android/gms/internal/ads/zzgno;)Lcom/google/android/gms/internal/ads/zzaoo;
    //   240: pop
    //   241: aload_1
    //   242: invokestatic 380	com/google/android/gms/internal/ads/zzapf:zze	([B)[B
    //   245: astore_1
    //   246: aload_2
    //   247: aload_1
    //   248: iconst_0
    //   249: aload_1
    //   250: arraylength
    //   251: invokestatic 363	com/google/android/gms/internal/ads/zzgno:zzv	([BII)Lcom/google/android/gms/internal/ads/zzgno;
    //   254: invokevirtual 382	com/google/android/gms/internal/ads/zzaoo:zzb	(Lcom/google/android/gms/internal/ads/zzgno;)Lcom/google/android/gms/internal/ads/zzaoo;
    //   257: pop
    //   258: aload 9
    //   260: invokevirtual 234	java/io/File:createNewFile	()Z
    //   263: pop
    //   264: new 236	java/io/FileOutputStream
    //   267: astore_1
    //   268: aload_1
    //   269: aload 9
    //   271: invokespecial 239	java/io/FileOutputStream:<init>	(Ljava/io/File;)V
    //   274: aload_2
    //   275: invokevirtual 388	com/google/android/gms/internal/ads/zzgos:zzal	()Lcom/google/android/gms/internal/ads/zzgow;
    //   278: checkcast 345	com/google/android/gms/internal/ads/zzaop
    //   281: invokevirtual 393	com/google/android/gms/internal/ads/zzgmx:zzax	()[B
    //   284: astore_2
    //   285: aload_1
    //   286: aload_2
    //   287: iconst_0
    //   288: aload_2
    //   289: arraylength
    //   290: invokevirtual 252	java/io/FileOutputStream:write	([BII)V
    //   293: aload_1
    //   294: invokevirtual 255	java/io/FileOutputStream:close	()V
    //   297: aload 6
    //   299: invokevirtual 330	java/io/FileInputStream:close	()V
    //   302: aload_1
    //   303: invokevirtual 255	java/io/FileOutputStream:close	()V
    //   306: aload 8
    //   308: invokestatic 277	com/google/android/gms/internal/ads/zzarr:zzy	(Ljava/io/File;)V
    //   311: return
    //   312: astore 7
    //   314: aload_1
    //   315: astore_2
    //   316: aload 7
    //   318: astore_1
    //   319: goto +6 -> 325
    //   322: astore_1
    //   323: aconst_null
    //   324: astore_2
    //   325: goto +19 -> 344
    //   328: astore_1
    //   329: aconst_null
    //   330: astore_1
    //   331: aload 6
    //   333: astore_2
    //   334: goto +43 -> 377
    //   337: astore_1
    //   338: aconst_null
    //   339: astore_2
    //   340: aload 7
    //   342: astore 6
    //   344: aload 6
    //   346: ifnull +13 -> 359
    //   349: aload 6
    //   351: invokevirtual 330	java/io/FileInputStream:close	()V
    //   354: goto +5 -> 359
    //   357: astore 6
    //   359: aload_2
    //   360: ifnull +7 -> 367
    //   363: aload_2
    //   364: invokevirtual 255	java/io/FileOutputStream:close	()V
    //   367: aload 8
    //   369: invokestatic 277	com/google/android/gms/internal/ads/zzarr:zzy	(Ljava/io/File;)V
    //   372: aload_1
    //   373: athrow
    //   374: astore_1
    //   375: aconst_null
    //   376: astore_1
    //   377: aload_2
    //   378: ifnull +11 -> 389
    //   381: aload_2
    //   382: invokevirtual 330	java/io/FileInputStream:close	()V
    //   385: goto +4 -> 389
    //   388: astore_2
    //   389: aload_1
    //   390: ifnull +7 -> 397
    //   393: aload_1
    //   394: invokevirtual 255	java/io/FileOutputStream:close	()V
    //   397: aload 8
    //   399: invokestatic 277	com/google/android/gms/internal/ads/zzarr:zzy	(Ljava/io/File;)V
    //   402: return
    //   403: astore_1
    //   404: goto -276 -> 128
    //   407: astore_2
    //   408: goto -77 -> 331
    //   411: astore_2
    //   412: goto -110 -> 302
    //   415: astore_1
    //   416: goto -110 -> 306
    //   419: astore_2
    //   420: goto -53 -> 367
    //   423: astore_1
    //   424: goto -27 -> 397
    // Local variable table:
    //   start	length	slot	name	signature
    //   0	427	0	this	zzarr
    //   0	427	1	paramFile	File
    //   0	427	2	paramString	String
    //   118	2	3	i	int
    //   79	11	4	l	long
    //   103	247	6	localObject1	Object
    //   357	1	6	localIOException	IOException
    //   98	106	7	localObject2	Object
    //   312	29	7	localObject3	Object
    //   63	335	8	localFile1	File
    //   26	244	9	localFile2	File
    //   171	12	10	arrayOfByte	byte[]
    // Exception table:
    //   from	to	target	type
    //   274	297	312	finally
    //   112	119	322	finally
    //   134	274	322	finally
    //   112	119	328	java/io/IOException
    //   112	119	328	java/security/NoSuchAlgorithmException
    //   112	119	328	com/google/android/gms/internal/ads/zzaqv
    //   134	274	328	java/io/IOException
    //   134	274	328	java/security/NoSuchAlgorithmException
    //   134	274	328	com/google/android/gms/internal/ads/zzaqv
    //   100	112	337	finally
    //   349	354	357	java/io/IOException
    //   100	112	374	java/io/IOException
    //   100	112	374	java/security/NoSuchAlgorithmException
    //   100	112	374	com/google/android/gms/internal/ads/zzaqv
    //   381	385	388	java/io/IOException
    //   123	128	403	java/io/IOException
    //   274	297	407	java/io/IOException
    //   274	297	407	java/security/NoSuchAlgorithmException
    //   274	297	407	com/google/android/gms/internal/ads/zzaqv
    //   297	302	411	java/io/IOException
    //   302	306	415	java/io/IOException
    //   363	367	419	java/io/IOException
    //   393	397	423	java/io/IOException
  }
  
  /* Error */
  private final boolean zzx(File paramFile, String paramString)
  {
    // Byte code:
    //   0: new 212	java/io/File
    //   3: dup
    //   4: ldc_w 318
    //   7: iconst_2
    //   8: anewarray 4	java/lang/Object
    //   11: dup
    //   12: iconst_0
    //   13: aload_1
    //   14: aastore
    //   15: dup
    //   16: iconst_1
    //   17: ldc -40
    //   19: aastore
    //   20: invokestatic 222	java/lang/String:format	(Ljava/lang/String;[Ljava/lang/Object;)Ljava/lang/String;
    //   23: invokespecial 223	java/io/File:<init>	(Ljava/lang/String;)V
    //   26: astore 7
    //   28: aload 7
    //   30: invokevirtual 226	java/io/File:exists	()Z
    //   33: ifne +5 -> 38
    //   36: iconst_0
    //   37: ireturn
    //   38: new 212	java/io/File
    //   41: dup
    //   42: ldc_w 283
    //   45: iconst_2
    //   46: anewarray 4	java/lang/Object
    //   49: dup
    //   50: iconst_0
    //   51: aload_1
    //   52: aastore
    //   53: dup
    //   54: iconst_1
    //   55: ldc -40
    //   57: aastore
    //   58: invokestatic 222	java/lang/String:format	(Ljava/lang/String;[Ljava/lang/Object;)Ljava/lang/String;
    //   61: invokespecial 223	java/io/File:<init>	(Ljava/lang/String;)V
    //   64: astore 6
    //   66: aload 6
    //   68: invokevirtual 226	java/io/File:exists	()Z
    //   71: ifne +334 -> 405
    //   74: aconst_null
    //   75: astore_1
    //   76: aconst_null
    //   77: astore_2
    //   78: aload 7
    //   80: invokevirtual 322	java/io/File:length	()J
    //   83: lstore_3
    //   84: lload_3
    //   85: lconst_0
    //   86: lcmp
    //   87: ifgt +10 -> 97
    //   90: aload 7
    //   92: invokestatic 277	com/google/android/gms/internal/ads/zzarr:zzy	(Ljava/io/File;)V
    //   95: iconst_0
    //   96: ireturn
    //   97: lload_3
    //   98: l2i
    //   99: newarray <illegal type>
    //   101: astore 8
    //   103: new 324	java/io/FileInputStream
    //   106: dup
    //   107: aload 7
    //   109: invokespecial 325	java/io/FileInputStream:<init>	(Ljava/io/File;)V
    //   112: astore 5
    //   114: aload 5
    //   116: aload 8
    //   118: invokevirtual 329	java/io/FileInputStream:read	([B)I
    //   121: ifgt +25 -> 146
    //   124: getstatic 395	com/google/android/gms/internal/ads/zzarr:zzd	Ljava/lang/String;
    //   127: ldc_w 397
    //   130: invokestatic 403	android/util/Log:d	(Ljava/lang/String;Ljava/lang/String;)I
    //   133: pop
    //   134: aload 7
    //   136: invokestatic 277	com/google/android/gms/internal/ads/zzarr:zzy	(Ljava/io/File;)V
    //   139: aload 5
    //   141: invokevirtual 330	java/io/FileInputStream:close	()V
    //   144: iconst_0
    //   145: ireturn
    //   146: aload 8
    //   148: invokestatic 408	com/google/android/gms/internal/ads/zzgoi:zza	()Lcom/google/android/gms/internal/ads/zzgoi;
    //   151: invokestatic 411	com/google/android/gms/internal/ads/zzaop:zzd	([BLcom/google/android/gms/internal/ads/zzgoi;)Lcom/google/android/gms/internal/ads/zzaop;
    //   154: astore_1
    //   155: new 218	java/lang/String
    //   158: astore_2
    //   159: aload_2
    //   160: aload_1
    //   161: invokevirtual 414	com/google/android/gms/internal/ads/zzaop:zzh	()Lcom/google/android/gms/internal/ads/zzgno;
    //   164: invokevirtual 417	com/google/android/gms/internal/ads/zzgno:zzA	()[B
    //   167: invokespecial 420	java/lang/String:<init>	([B)V
    //   170: ldc -40
    //   172: aload_2
    //   173: invokevirtual 424	java/lang/String:equals	(Ljava/lang/Object;)Z
    //   176: ifeq +130 -> 306
    //   179: aload_1
    //   180: invokevirtual 426	com/google/android/gms/internal/ads/zzaop:zzf	()Lcom/google/android/gms/internal/ads/zzgno;
    //   183: invokevirtual 417	com/google/android/gms/internal/ads/zzgno:zzA	()[B
    //   186: aload_1
    //   187: invokevirtual 428	com/google/android/gms/internal/ads/zzaop:zze	()Lcom/google/android/gms/internal/ads/zzgno;
    //   190: invokevirtual 417	com/google/android/gms/internal/ads/zzgno:zzA	()[B
    //   193: invokestatic 380	com/google/android/gms/internal/ads/zzapf:zze	([B)[B
    //   196: invokestatic 433	java/util/Arrays:equals	([B[B)Z
    //   199: ifeq +107 -> 306
    //   202: aload_1
    //   203: invokevirtual 435	com/google/android/gms/internal/ads/zzaop:zzg	()Lcom/google/android/gms/internal/ads/zzgno;
    //   206: invokevirtual 417	com/google/android/gms/internal/ads/zzgno:zzA	()[B
    //   209: getstatic 351	android/os/Build$VERSION:SDK	Ljava/lang/String;
    //   212: invokevirtual 355	java/lang/String:getBytes	()[B
    //   215: invokestatic 433	java/util/Arrays:equals	([B[B)Z
    //   218: ifne +6 -> 224
    //   221: goto +85 -> 306
    //   224: aload_0
    //   225: getfield 180	com/google/android/gms/internal/ads/zzarr:zzg	Lcom/google/android/gms/internal/ads/zzaqw;
    //   228: astore_2
    //   229: aload_0
    //   230: getfield 199	com/google/android/gms/internal/ads/zzarr:zzh	[B
    //   233: astore 8
    //   235: new 218	java/lang/String
    //   238: astore 7
    //   240: aload 7
    //   242: aload_1
    //   243: invokevirtual 428	com/google/android/gms/internal/ads/zzaop:zze	()Lcom/google/android/gms/internal/ads/zzgno;
    //   246: invokevirtual 417	com/google/android/gms/internal/ads/zzgno:zzA	()[B
    //   249: invokespecial 420	java/lang/String:<init>	([B)V
    //   252: aload_2
    //   253: aload 8
    //   255: aload 7
    //   257: invokevirtual 231	com/google/android/gms/internal/ads/zzaqw:zzb	([BLjava/lang/String;)[B
    //   260: astore_2
    //   261: aload 6
    //   263: invokevirtual 234	java/io/File:createNewFile	()Z
    //   266: pop
    //   267: new 236	java/io/FileOutputStream
    //   270: dup
    //   271: aload 6
    //   273: invokespecial 239	java/io/FileOutputStream:<init>	(Ljava/io/File;)V
    //   276: astore_1
    //   277: aload_1
    //   278: aload_2
    //   279: iconst_0
    //   280: aload_2
    //   281: arraylength
    //   282: invokevirtual 252	java/io/FileOutputStream:write	([BII)V
    //   285: aload 5
    //   287: invokevirtual 330	java/io/FileInputStream:close	()V
    //   290: aload_1
    //   291: invokevirtual 255	java/io/FileOutputStream:close	()V
    //   294: iconst_1
    //   295: ireturn
    //   296: astore 6
    //   298: aload_1
    //   299: astore_2
    //   300: aload 6
    //   302: astore_1
    //   303: goto +26 -> 329
    //   306: aload 7
    //   308: invokestatic 277	com/google/android/gms/internal/ads/zzarr:zzy	(Ljava/io/File;)V
    //   311: aload 5
    //   313: invokevirtual 330	java/io/FileInputStream:close	()V
    //   316: iconst_0
    //   317: ireturn
    //   318: astore_1
    //   319: aload 5
    //   321: invokevirtual 330	java/io/FileInputStream:close	()V
    //   324: iconst_0
    //   325: ireturn
    //   326: astore_1
    //   327: aconst_null
    //   328: astore_2
    //   329: goto +22 -> 351
    //   332: astore_1
    //   333: aconst_null
    //   334: astore_1
    //   335: aload 5
    //   337: astore_2
    //   338: goto +47 -> 385
    //   341: astore_1
    //   342: aconst_null
    //   343: astore 6
    //   345: aload_2
    //   346: astore 5
    //   348: aload 6
    //   350: astore_2
    //   351: aload 5
    //   353: ifnull +13 -> 366
    //   356: aload 5
    //   358: invokevirtual 330	java/io/FileInputStream:close	()V
    //   361: goto +5 -> 366
    //   364: astore 5
    //   366: aload_2
    //   367: ifnull +7 -> 374
    //   370: aload_2
    //   371: invokevirtual 255	java/io/FileOutputStream:close	()V
    //   374: aload_1
    //   375: athrow
    //   376: astore_2
    //   377: aconst_null
    //   378: astore 5
    //   380: aload_1
    //   381: astore_2
    //   382: aload 5
    //   384: astore_1
    //   385: aload_2
    //   386: ifnull +11 -> 397
    //   389: aload_2
    //   390: invokevirtual 330	java/io/FileInputStream:close	()V
    //   393: goto +4 -> 397
    //   396: astore_2
    //   397: aload_1
    //   398: ifnull +7 -> 405
    //   401: aload_1
    //   402: invokevirtual 255	java/io/FileOutputStream:close	()V
    //   405: iconst_0
    //   406: ireturn
    //   407: astore_1
    //   408: goto -264 -> 144
    //   411: astore_2
    //   412: goto -77 -> 335
    //   415: astore_2
    //   416: goto -126 -> 290
    //   419: astore_1
    //   420: goto -126 -> 294
    //   423: astore_1
    //   424: goto -108 -> 316
    //   427: astore_1
    //   428: goto -104 -> 324
    //   431: astore_2
    //   432: goto -58 -> 374
    //   435: astore_1
    //   436: goto -31 -> 405
    // Local variable table:
    //   start	length	slot	name	signature
    //   0	439	0	this	zzarr
    //   0	439	1	paramFile	File
    //   0	439	2	paramString	String
    //   83	15	3	l	long
    //   112	245	5	localObject1	Object
    //   364	1	5	localIOException	IOException
    //   378	5	5	localObject2	Object
    //   64	208	6	localFile	File
    //   296	5	6	localObject3	Object
    //   343	6	6	localObject4	Object
    //   26	281	7	localObject5	Object
    //   101	153	8	arrayOfByte	byte[]
    // Exception table:
    //   from	to	target	type
    //   277	285	296	finally
    //   146	155	318	java/lang/NullPointerException
    //   114	139	326	finally
    //   146	155	326	finally
    //   155	221	326	finally
    //   224	277	326	finally
    //   306	311	326	finally
    //   114	139	332	java/io/IOException
    //   114	139	332	java/security/NoSuchAlgorithmException
    //   114	139	332	com/google/android/gms/internal/ads/zzaqv
    //   146	155	332	java/io/IOException
    //   146	155	332	java/security/NoSuchAlgorithmException
    //   146	155	332	com/google/android/gms/internal/ads/zzaqv
    //   155	221	332	java/io/IOException
    //   155	221	332	java/security/NoSuchAlgorithmException
    //   155	221	332	com/google/android/gms/internal/ads/zzaqv
    //   224	277	332	java/io/IOException
    //   224	277	332	java/security/NoSuchAlgorithmException
    //   224	277	332	com/google/android/gms/internal/ads/zzaqv
    //   306	311	332	java/io/IOException
    //   306	311	332	java/security/NoSuchAlgorithmException
    //   306	311	332	com/google/android/gms/internal/ads/zzaqv
    //   78	84	341	finally
    //   90	95	341	finally
    //   97	114	341	finally
    //   356	361	364	java/io/IOException
    //   78	84	376	java/io/IOException
    //   78	84	376	java/security/NoSuchAlgorithmException
    //   78	84	376	com/google/android/gms/internal/ads/zzaqv
    //   90	95	376	java/io/IOException
    //   90	95	376	java/security/NoSuchAlgorithmException
    //   90	95	376	com/google/android/gms/internal/ads/zzaqv
    //   97	114	376	java/io/IOException
    //   97	114	376	java/security/NoSuchAlgorithmException
    //   97	114	376	com/google/android/gms/internal/ads/zzaqv
    //   389	393	396	java/io/IOException
    //   139	144	407	java/io/IOException
    //   277	285	411	java/io/IOException
    //   277	285	411	java/security/NoSuchAlgorithmException
    //   277	285	411	com/google/android/gms/internal/ads/zzaqv
    //   285	290	415	java/io/IOException
    //   290	294	419	java/io/IOException
    //   311	316	423	java/io/IOException
    //   319	324	427	java/io/IOException
    //   370	374	431	java/io/IOException
    //   401	405	435	java/io/IOException
  }
  
  private static final void zzy(File paramFile)
  {
    if (!paramFile.exists())
    {
      Log.d(zzd, String.format("File %s not found. No need for deletion", new Object[] { paramFile.getAbsolutePath() }));
      return;
    }
    paramFile.delete();
  }
  
  private static final void zzz(String paramString)
  {
    zzy(new File(paramString));
  }
  
  public final int zza()
  {
    if (this.zzo != null) {
      return zzaql.zzd();
    }
    return Integer.MIN_VALUE;
  }
  
  public final Context zzb()
  {
    return this.zza;
  }
  
  public final zzaol zzc()
  {
    return this.zzm;
  }
  
  public final zzaql zzd()
  {
    return this.zzo;
  }
  
  public final zzaqw zze()
  {
    return this.zzg;
  }
  
  final zzark zzf()
  {
    return this.zzr;
  }
  
  public final AdvertisingIdClient zzh()
  {
    if (!this.zzj) {
      return null;
    }
    if (this.zzi != null) {
      return this.zzi;
    }
    Future localFuture = this.zzk;
    if (localFuture != null) {}
    try
    {
      try
      {
        localFuture.get(2000L, TimeUnit.MILLISECONDS);
        this.zzk = null;
      }
      catch (TimeoutException localTimeoutException)
      {
        this.zzk.cancel(true);
      }
    }
    catch (InterruptedException|ExecutionException localInterruptedException)
    {
      for (;;) {}
    }
    return this.zzi;
  }
  
  public final DexClassLoader zzi()
  {
    return this.zzf;
  }
  
  public final Method zzj(String paramString1, String paramString2)
  {
    paramString1 = (zzate)this.zzp.get(new Pair(paramString1, paramString2));
    if (paramString1 == null) {
      return null;
    }
    return paramString1.zza();
  }
  
  public final ExecutorService zzk()
  {
    return this.zze;
  }
  
  public final Future zzl()
  {
    return this.zzn;
  }
  
  final void zzo(int paramInt, boolean paramBoolean)
  {
    if (this.zzc)
    {
      Future localFuture = this.zze.submit(new zzarp(this, paramInt, true));
      if (paramInt == 0) {
        this.zzn = localFuture;
      }
    }
  }
  
  public final boolean zzp()
  {
    return this.zzc;
  }
  
  public final boolean zzq()
  {
    return this.zzb;
  }
  
  public final boolean zzr()
  {
    return this.zzq;
  }
  
  public final boolean zzs()
  {
    return this.zzr.zza();
  }
  
  public final boolean zzt(String paramString1, String paramString2, Class... paramVarArgs)
  {
    Pair localPair = new Pair(paramString1, paramString2);
    if (!this.zzp.containsKey(localPair))
    {
      this.zzp.put(localPair, new zzate(this, paramString1, paramString2, paramVarArgs));
      return true;
    }
    return false;
  }
  
  public final byte[] zzu()
  {
    return this.zzh;
  }
}


/* Location:              C:\Users\Ria\Documents\slope apk\dex-tools-v2.4\classes-dex2jar.jar!\com\google\android\gms\internal\ads\zzarr.class
 * Java compiler version: 6 (50.0)
 * JD-Core Version:       0.7.1
 */