package com.google.android.gms.internal.ads;

import java.util.concurrent.ExecutorService;

public final class zzaxc
{
  final zzaxd zza;
  private final byte[] zzb;
  private int zzc;
  
  /* Error */
  private final void zzd()
  {
    // Byte code:
    //   0: aload_0
    //   1: monitorenter
    //   2: aload_0
    //   3: getfield 14	com/google/android/gms/internal/ads/zzaxc:zza	Lcom/google/android/gms/internal/ads/zzaxd;
    //   6: astore_1
    //   7: aload_1
    //   8: getfield 31	com/google/android/gms/internal/ads/zzaxd:zzb	Z
    //   11: ifeq +73 -> 84
    //   14: aload_1
    //   15: getfield 34	com/google/android/gms/internal/ads/zzaxd:zza	Lcom/google/android/gms/internal/ads/zzatt;
    //   18: aload_0
    //   19: getfield 19	com/google/android/gms/internal/ads/zzaxc:zzb	[B
    //   22: invokeinterface 40 2 0
    //   27: aload_0
    //   28: getfield 14	com/google/android/gms/internal/ads/zzaxc:zza	Lcom/google/android/gms/internal/ads/zzaxd;
    //   31: getfield 34	com/google/android/gms/internal/ads/zzaxd:zza	Lcom/google/android/gms/internal/ads/zzatt;
    //   34: iconst_0
    //   35: invokeinterface 44 2 0
    //   40: aload_0
    //   41: getfield 14	com/google/android/gms/internal/ads/zzaxc:zza	Lcom/google/android/gms/internal/ads/zzaxd;
    //   44: getfield 34	com/google/android/gms/internal/ads/zzaxd:zza	Lcom/google/android/gms/internal/ads/zzatt;
    //   47: aload_0
    //   48: getfield 46	com/google/android/gms/internal/ads/zzaxc:zzc	I
    //   51: invokeinterface 49 2 0
    //   56: aload_0
    //   57: getfield 14	com/google/android/gms/internal/ads/zzaxc:zza	Lcom/google/android/gms/internal/ads/zzaxd;
    //   60: getfield 34	com/google/android/gms/internal/ads/zzaxd:zza	Lcom/google/android/gms/internal/ads/zzatt;
    //   63: aconst_null
    //   64: invokeinterface 53 2 0
    //   69: aload_0
    //   70: getfield 14	com/google/android/gms/internal/ads/zzaxc:zza	Lcom/google/android/gms/internal/ads/zzaxd;
    //   73: getfield 34	com/google/android/gms/internal/ads/zzaxd:zza	Lcom/google/android/gms/internal/ads/zzatt;
    //   76: invokeinterface 56 1 0
    //   81: aload_0
    //   82: monitorexit
    //   83: return
    //   84: aload_0
    //   85: monitorexit
    //   86: return
    //   87: astore_1
    //   88: goto +13 -> 101
    //   91: astore_1
    //   92: ldc 58
    //   94: aload_1
    //   95: invokestatic 63	com/google/android/gms/internal/ads/zzbzt:zzf	(Ljava/lang/String;Ljava/lang/Throwable;)V
    //   98: aload_0
    //   99: monitorexit
    //   100: return
    //   101: aload_0
    //   102: monitorexit
    //   103: aload_1
    //   104: athrow
    // Local variable table:
    //   start	length	slot	name	signature
    //   0	105	0	this	zzaxc
    //   6	9	1	localzzaxd	zzaxd
    //   87	1	1	localObject	Object
    //   91	13	1	localRemoteException	android.os.RemoteException
    // Exception table:
    //   from	to	target	type
    //   2	81	87	finally
    //   92	98	87	finally
    //   2	81	91	android/os/RemoteException
  }
  
  public final zzaxc zza(int paramInt)
  {
    this.zzc = paramInt;
    return this;
  }
  
  public final void zzc()
  {
    try
    {
      ExecutorService localExecutorService = zzaxd.zza(this.zza);
      zzaxa localzzaxa = new com/google/android/gms/internal/ads/zzaxa;
      localzzaxa.<init>(this);
      localExecutorService.execute(localzzaxa);
      return;
    }
    finally
    {
      localObject = finally;
      throw ((Throwable)localObject);
    }
  }
}


/* Location:              C:\Users\Ria\Documents\slope apk\dex-tools-v2.4\classes-dex2jar.jar!\com\google\android\gms\internal\ads\zzaxc.class
 * Java compiler version: 6 (50.0)
 * JD-Core Version:       0.7.1
 */