package com.google.android.gms.internal.ads;

import android.content.Context;

public final class zzbkd
  implements zzalb
{
  private volatile zzbjq zza;
  private final Context zzb;
  
  public zzbkd(Context paramContext)
  {
    this.zzb = paramContext;
  }
  
  /* Error */
  public final zzale zza(zzali paramzzali)
    throws zzalr
  {
    // Byte code:
    //   0: getstatic 46	com/google/android/gms/internal/ads/zzbjr:CREATOR	Landroid/os/Parcelable$Creator;
    //   3: astore 8
    //   5: aload_1
    //   6: invokevirtual 52	com/google/android/gms/internal/ads/zzali:zzl	()Ljava/util/Map;
    //   9: astore 10
    //   11: aload 10
    //   13: invokeinterface 58 1 0
    //   18: istore_2
    //   19: iload_2
    //   20: anewarray 60	java/lang/String
    //   23: astore 8
    //   25: iload_2
    //   26: anewarray 60	java/lang/String
    //   29: astore 9
    //   31: aload 10
    //   33: invokeinterface 64 1 0
    //   38: invokeinterface 70 1 0
    //   43: astore 10
    //   45: iconst_0
    //   46: istore_3
    //   47: iconst_0
    //   48: istore_2
    //   49: aload 10
    //   51: invokeinterface 76 1 0
    //   56: ifeq +49 -> 105
    //   59: aload 10
    //   61: invokeinterface 80 1 0
    //   66: checkcast 82	java/util/Map$Entry
    //   69: astore 11
    //   71: aload 8
    //   73: iload_2
    //   74: aload 11
    //   76: invokeinterface 85 1 0
    //   81: checkcast 60	java/lang/String
    //   84: aastore
    //   85: aload 9
    //   87: iload_2
    //   88: aload 11
    //   90: invokeinterface 88 1 0
    //   95: checkcast 60	java/lang/String
    //   98: aastore
    //   99: iinc 2 1
    //   102: goto -53 -> 49
    //   105: new 42	com/google/android/gms/internal/ads/zzbjr
    //   108: dup
    //   109: aload_1
    //   110: invokevirtual 92	com/google/android/gms/internal/ads/zzali:zzk	()Ljava/lang/String;
    //   113: aload 8
    //   115: aload 9
    //   117: invokespecial 95	com/google/android/gms/internal/ads/zzbjr:<init>	(Ljava/lang/String;[Ljava/lang/String;[Ljava/lang/String;)V
    //   120: astore 8
    //   122: invokestatic 101	com/google/android/gms/ads/internal/zzt:zzB	()Lcom/google/android/gms/common/util/Clock;
    //   125: invokeinterface 107 1 0
    //   130: lstore 4
    //   132: aconst_null
    //   133: astore_1
    //   134: new 109	com/google/android/gms/internal/ads/zzcal
    //   137: astore 9
    //   139: aload 9
    //   141: invokespecial 110	com/google/android/gms/internal/ads/zzcal:<init>	()V
    //   144: new 112	com/google/android/gms/internal/ads/zzbkb
    //   147: astore 11
    //   149: aload 11
    //   151: aload_0
    //   152: aload 9
    //   154: invokespecial 115	com/google/android/gms/internal/ads/zzbkb:<init>	(Lcom/google/android/gms/internal/ads/zzbkd;Lcom/google/android/gms/internal/ads/zzcal;)V
    //   157: new 117	com/google/android/gms/internal/ads/zzbkc
    //   160: astore 10
    //   162: aload 10
    //   164: aload_0
    //   165: aload 9
    //   167: invokespecial 118	com/google/android/gms/internal/ads/zzbkc:<init>	(Lcom/google/android/gms/internal/ads/zzbkd;Lcom/google/android/gms/internal/ads/zzcal;)V
    //   170: new 25	com/google/android/gms/internal/ads/zzbjq
    //   173: astore 12
    //   175: aload 12
    //   177: aload_0
    //   178: getfield 17	com/google/android/gms/internal/ads/zzbkd:zzb	Landroid/content/Context;
    //   181: invokestatic 122	com/google/android/gms/ads/internal/zzt:zzt	()Lcom/google/android/gms/ads/internal/util/zzbv;
    //   184: invokevirtual 127	com/google/android/gms/ads/internal/util/zzbv:zzb	()Landroid/os/Looper;
    //   187: aload 11
    //   189: aload 10
    //   191: invokespecial 130	com/google/android/gms/internal/ads/zzbjq:<init>	(Landroid/content/Context;Landroid/os/Looper;Lcom/google/android/gms/common/internal/BaseGmsClient$BaseConnectionCallbacks;Lcom/google/android/gms/common/internal/BaseGmsClient$BaseOnConnectionFailedListener;)V
    //   194: aload_0
    //   195: aload 12
    //   197: putfield 21	com/google/android/gms/internal/ads/zzbkd:zza	Lcom/google/android/gms/internal/ads/zzbjq;
    //   200: aload_0
    //   201: getfield 21	com/google/android/gms/internal/ads/zzbkd:zza	Lcom/google/android/gms/internal/ads/zzbjq;
    //   204: invokevirtual 133	com/google/android/gms/internal/ads/zzbjq:checkAvailabilityAndConnect	()V
    //   207: new 135	com/google/android/gms/internal/ads/zzbjz
    //   210: astore 10
    //   212: aload 10
    //   214: aload_0
    //   215: aload 8
    //   217: invokespecial 138	com/google/android/gms/internal/ads/zzbjz:<init>	(Lcom/google/android/gms/internal/ads/zzbkd;Lcom/google/android/gms/internal/ads/zzbjr;)V
    //   220: aload 9
    //   222: aload 10
    //   224: getstatic 143	com/google/android/gms/internal/ads/zzcag:zza	Lcom/google/android/gms/internal/ads/zzfwc;
    //   227: invokestatic 149	com/google/android/gms/internal/ads/zzfvr:zzm	(Lcom/google/android/gms/internal/ads/zzfwb;Lcom/google/android/gms/internal/ads/zzfuy;Ljava/util/concurrent/Executor;)Lcom/google/android/gms/internal/ads/zzfwb;
    //   230: astore 9
    //   232: getstatic 155	com/google/android/gms/internal/ads/zzbbk:zzei	Lcom/google/android/gms/internal/ads/zzbbc;
    //   235: astore 8
    //   237: aload 9
    //   239: invokestatic 160	com/google/android/gms/ads/internal/client/zzba:zzc	()Lcom/google/android/gms/internal/ads/zzbbi;
    //   242: aload 8
    //   244: invokevirtual 165	com/google/android/gms/internal/ads/zzbbi:zzb	(Lcom/google/android/gms/internal/ads/zzbbc;)Ljava/lang/Object;
    //   247: checkcast 167	java/lang/Integer
    //   250: invokevirtual 170	java/lang/Integer:intValue	()I
    //   253: i2l
    //   254: getstatic 176	java/util/concurrent/TimeUnit:MILLISECONDS	Ljava/util/concurrent/TimeUnit;
    //   257: getstatic 180	com/google/android/gms/internal/ads/zzcag:zzd	Ljava/util/concurrent/ScheduledExecutorService;
    //   260: invokestatic 184	com/google/android/gms/internal/ads/zzfvr:zzn	(Lcom/google/android/gms/internal/ads/zzfwb;JLjava/util/concurrent/TimeUnit;Ljava/util/concurrent/ScheduledExecutorService;)Lcom/google/android/gms/internal/ads/zzfwb;
    //   263: astore 9
    //   265: new 186	com/google/android/gms/internal/ads/zzbka
    //   268: astore 8
    //   270: aload 8
    //   272: aload_0
    //   273: invokespecial 188	com/google/android/gms/internal/ads/zzbka:<init>	(Lcom/google/android/gms/internal/ads/zzbkd;)V
    //   276: aload 9
    //   278: aload 8
    //   280: getstatic 143	com/google/android/gms/internal/ads/zzcag:zza	Lcom/google/android/gms/internal/ads/zzfwc;
    //   283: invokeinterface 193 3 0
    //   288: aload 9
    //   290: invokeinterface 196 1 0
    //   295: checkcast 198	android/os/ParcelFileDescriptor
    //   298: astore 9
    //   300: invokestatic 101	com/google/android/gms/ads/internal/zzt:zzB	()Lcom/google/android/gms/common/util/Clock;
    //   303: invokeinterface 107 1 0
    //   308: lstore 6
    //   310: new 200	java/lang/StringBuilder
    //   313: dup
    //   314: invokespecial 201	java/lang/StringBuilder:<init>	()V
    //   317: astore 8
    //   319: aload 8
    //   321: ldc -53
    //   323: invokevirtual 207	java/lang/StringBuilder:append	(Ljava/lang/String;)Ljava/lang/StringBuilder;
    //   326: pop
    //   327: aload 8
    //   329: lload 6
    //   331: lload 4
    //   333: lsub
    //   334: invokevirtual 210	java/lang/StringBuilder:append	(J)Ljava/lang/StringBuilder;
    //   337: pop
    //   338: aload 8
    //   340: ldc -44
    //   342: invokevirtual 207	java/lang/StringBuilder:append	(Ljava/lang/String;)Ljava/lang/StringBuilder;
    //   345: pop
    //   346: aload 8
    //   348: invokevirtual 215	java/lang/StringBuilder:toString	()Ljava/lang/String;
    //   351: invokestatic 220	com/google/android/gms/ads/internal/util/zze:zza	(Ljava/lang/String;)V
    //   354: new 222	com/google/android/gms/internal/ads/zzbue
    //   357: dup
    //   358: aload 9
    //   360: invokespecial 225	com/google/android/gms/internal/ads/zzbue:<init>	(Landroid/os/ParcelFileDescriptor;)V
    //   363: getstatic 228	com/google/android/gms/internal/ads/zzbjt:CREATOR	Landroid/os/Parcelable$Creator;
    //   366: invokevirtual 231	com/google/android/gms/internal/ads/zzbue:zza	(Landroid/os/Parcelable$Creator;)Lcom/google/android/gms/common/internal/safeparcel/SafeParcelable;
    //   369: checkcast 227	com/google/android/gms/internal/ads/zzbjt
    //   372: astore 8
    //   374: aload 8
    //   376: ifnonnull +5 -> 381
    //   379: aconst_null
    //   380: areturn
    //   381: aload 8
    //   383: getfield 234	com/google/android/gms/internal/ads/zzbjt:zza	Z
    //   386: ifne +98 -> 484
    //   389: aload 8
    //   391: getfield 238	com/google/android/gms/internal/ads/zzbjt:zze	[Ljava/lang/String;
    //   394: arraylength
    //   395: aload 8
    //   397: getfield 241	com/google/android/gms/internal/ads/zzbjt:zzf	[Ljava/lang/String;
    //   400: arraylength
    //   401: if_icmpeq +6 -> 407
    //   404: goto +78 -> 482
    //   407: new 243	java/util/HashMap
    //   410: dup
    //   411: invokespecial 244	java/util/HashMap:<init>	()V
    //   414: astore 9
    //   416: iload_3
    //   417: istore_2
    //   418: aload 8
    //   420: getfield 238	com/google/android/gms/internal/ads/zzbjt:zze	[Ljava/lang/String;
    //   423: astore_1
    //   424: iload_2
    //   425: aload_1
    //   426: arraylength
    //   427: if_icmpge +25 -> 452
    //   430: aload 9
    //   432: aload_1
    //   433: iload_2
    //   434: aaload
    //   435: aload 8
    //   437: getfield 241	com/google/android/gms/internal/ads/zzbjt:zzf	[Ljava/lang/String;
    //   440: iload_2
    //   441: aaload
    //   442: invokevirtual 248	java/util/HashMap:put	(Ljava/lang/Object;Ljava/lang/Object;)Ljava/lang/Object;
    //   445: pop
    //   446: iinc 2 1
    //   449: goto -31 -> 418
    //   452: new 250	com/google/android/gms/internal/ads/zzale
    //   455: dup
    //   456: aload 8
    //   458: getfield 253	com/google/android/gms/internal/ads/zzbjt:zzc	I
    //   461: aload 8
    //   463: getfield 256	com/google/android/gms/internal/ads/zzbjt:zzd	[B
    //   466: aload 9
    //   468: aload 8
    //   470: getfield 259	com/google/android/gms/internal/ads/zzbjt:zzg	Z
    //   473: aload 8
    //   475: getfield 263	com/google/android/gms/internal/ads/zzbjt:zzh	J
    //   478: invokespecial 266	com/google/android/gms/internal/ads/zzale:<init>	(I[BLjava/util/Map;ZJ)V
    //   481: astore_1
    //   482: aload_1
    //   483: areturn
    //   484: new 36	com/google/android/gms/internal/ads/zzalr
    //   487: dup
    //   488: aload 8
    //   490: getfield 269	com/google/android/gms/internal/ads/zzbjt:zzb	Ljava/lang/String;
    //   493: invokespecial 271	com/google/android/gms/internal/ads/zzalr:<init>	(Ljava/lang/String;)V
    //   496: athrow
    //   497: astore 8
    //   499: invokestatic 101	com/google/android/gms/ads/internal/zzt:zzB	()Lcom/google/android/gms/common/util/Clock;
    //   502: invokeinterface 107 1 0
    //   507: lstore 6
    //   509: new 200	java/lang/StringBuilder
    //   512: dup
    //   513: invokespecial 201	java/lang/StringBuilder:<init>	()V
    //   516: astore_1
    //   517: aload_1
    //   518: ldc -53
    //   520: invokevirtual 207	java/lang/StringBuilder:append	(Ljava/lang/String;)Ljava/lang/StringBuilder;
    //   523: pop
    //   524: aload_1
    //   525: lload 6
    //   527: lload 4
    //   529: lsub
    //   530: invokevirtual 210	java/lang/StringBuilder:append	(J)Ljava/lang/StringBuilder;
    //   533: pop
    //   534: aload_1
    //   535: ldc -44
    //   537: invokevirtual 207	java/lang/StringBuilder:append	(Ljava/lang/String;)Ljava/lang/StringBuilder;
    //   540: pop
    //   541: aload_1
    //   542: invokevirtual 215	java/lang/StringBuilder:toString	()Ljava/lang/String;
    //   545: invokestatic 220	com/google/android/gms/ads/internal/util/zze:zza	(Ljava/lang/String;)V
    //   548: aload 8
    //   550: athrow
    //   551: astore_1
    //   552: invokestatic 101	com/google/android/gms/ads/internal/zzt:zzB	()Lcom/google/android/gms/common/util/Clock;
    //   555: invokeinterface 107 1 0
    //   560: lstore 6
    //   562: new 200	java/lang/StringBuilder
    //   565: dup
    //   566: invokespecial 201	java/lang/StringBuilder:<init>	()V
    //   569: astore_1
    //   570: aload_1
    //   571: ldc -53
    //   573: invokevirtual 207	java/lang/StringBuilder:append	(Ljava/lang/String;)Ljava/lang/StringBuilder;
    //   576: pop
    //   577: aload_1
    //   578: lload 6
    //   580: lload 4
    //   582: lsub
    //   583: invokevirtual 210	java/lang/StringBuilder:append	(J)Ljava/lang/StringBuilder;
    //   586: pop
    //   587: aload_1
    //   588: ldc -44
    //   590: invokevirtual 207	java/lang/StringBuilder:append	(Ljava/lang/String;)Ljava/lang/StringBuilder;
    //   593: pop
    //   594: aload_1
    //   595: invokevirtual 215	java/lang/StringBuilder:toString	()Ljava/lang/String;
    //   598: invokestatic 220	com/google/android/gms/ads/internal/util/zze:zza	(Ljava/lang/String;)V
    //   601: aconst_null
    //   602: areturn
    // Local variable table:
    //   start	length	slot	name	signature
    //   0	603	0	this	zzbkd
    //   0	603	1	paramzzali	zzali
    //   18	429	2	i	int
    //   46	371	3	j	int
    //   130	451	4	l1	long
    //   308	271	6	l2	long
    //   3	486	8	localObject1	Object
    //   497	52	8	localObject2	Object
    //   29	438	9	localObject3	Object
    //   9	214	10	localObject4	Object
    //   69	119	11	localObject5	Object
    //   173	23	12	localzzbjq	zzbjq
    // Exception table:
    //   from	to	target	type
    //   134	300	497	finally
    //   134	300	551	java/lang/InterruptedException
    //   134	300	551	java/util/concurrent/ExecutionException
  }
}


/* Location:              C:\Users\Ria\Documents\slope apk\dex-tools-v2.4\classes-dex2jar.jar!\com\google\android\gms\internal\ads\zzbkd.class
 * Java compiler version: 6 (50.0)
 * JD-Core Version:       0.7.1
 */