package com.google.android.gms.internal.ads;

final class zzbnb
  implements zzbiv
{
  final zzbnc zza;
  private final zzbme zzb;
  private final zzcal zzc;
  
  public zzbnb(zzbnc paramzzbnc, zzbme paramzzbme, zzcal paramzzcal)
  {
    this.zzb = paramzzbme;
    this.zzc = paramzzcal;
  }
  
  /* Error */
  public final void zza(String paramString)
  {
    // Byte code:
    //   0: aload_1
    //   1: ifnonnull +25 -> 26
    //   4: aload_0
    //   5: getfield 23	com/google/android/gms/internal/ads/zzbnb:zzc	Lcom/google/android/gms/internal/ads/zzcal;
    //   8: astore_2
    //   9: new 29	com/google/android/gms/internal/ads/zzbmn
    //   12: astore_1
    //   13: aload_1
    //   14: invokespecial 30	com/google/android/gms/internal/ads/zzbmn:<init>	()V
    //   17: aload_2
    //   18: aload_1
    //   19: invokevirtual 36	com/google/android/gms/internal/ads/zzcal:zze	(Ljava/lang/Throwable;)Z
    //   22: pop
    //   23: goto +23 -> 46
    //   26: aload_0
    //   27: getfield 23	com/google/android/gms/internal/ads/zzbnb:zzc	Lcom/google/android/gms/internal/ads/zzcal;
    //   30: astore_2
    //   31: new 29	com/google/android/gms/internal/ads/zzbmn
    //   34: astore_3
    //   35: aload_3
    //   36: aload_1
    //   37: invokespecial 38	com/google/android/gms/internal/ads/zzbmn:<init>	(Ljava/lang/String;)V
    //   40: aload_2
    //   41: aload_3
    //   42: invokevirtual 36	com/google/android/gms/internal/ads/zzcal:zze	(Ljava/lang/Throwable;)Z
    //   45: pop
    //   46: aload_0
    //   47: getfield 21	com/google/android/gms/internal/ads/zzbnb:zzb	Lcom/google/android/gms/internal/ads/zzbme;
    //   50: astore_1
    //   51: aload_1
    //   52: invokevirtual 42	com/google/android/gms/internal/ads/zzbme:zzb	()V
    //   55: return
    //   56: astore_1
    //   57: aload_0
    //   58: getfield 21	com/google/android/gms/internal/ads/zzbnb:zzb	Lcom/google/android/gms/internal/ads/zzbme;
    //   61: invokevirtual 42	com/google/android/gms/internal/ads/zzbme:zzb	()V
    //   64: aload_1
    //   65: athrow
    //   66: astore_1
    //   67: aload_0
    //   68: getfield 21	com/google/android/gms/internal/ads/zzbnb:zzb	Lcom/google/android/gms/internal/ads/zzbme;
    //   71: astore_1
    //   72: goto -21 -> 51
    // Local variable table:
    //   start	length	slot	name	signature
    //   0	75	0	this	zzbnb
    //   0	75	1	paramString	String
    //   8	33	2	localzzcal	zzcal
    //   34	8	3	localzzbmn	zzbmn
    // Exception table:
    //   from	to	target	type
    //   4	23	56	finally
    //   26	46	56	finally
    //   4	23	66	java/lang/IllegalStateException
    //   26	46	66	java/lang/IllegalStateException
  }
  
  /* Error */
  public final void zzb(org.json.JSONObject paramJSONObject)
  {
    // Byte code:
    //   0: aload_0
    //   1: getfield 23	com/google/android/gms/internal/ads/zzbnb:zzc	Lcom/google/android/gms/internal/ads/zzcal;
    //   4: aload_0
    //   5: getfield 16	com/google/android/gms/internal/ads/zzbnb:zza	Lcom/google/android/gms/internal/ads/zzbnc;
    //   8: invokestatic 50	com/google/android/gms/internal/ads/zzbnc:zzc	(Lcom/google/android/gms/internal/ads/zzbnc;)Lcom/google/android/gms/internal/ads/zzbmq;
    //   11: aload_1
    //   12: invokeinterface 55 2 0
    //   17: invokevirtual 59	com/google/android/gms/internal/ads/zzcal:zzd	(Ljava/lang/Object;)Z
    //   20: pop
    //   21: aload_0
    //   22: getfield 21	com/google/android/gms/internal/ads/zzbnb:zzb	Lcom/google/android/gms/internal/ads/zzbme;
    //   25: astore_1
    //   26: aload_1
    //   27: invokevirtual 42	com/google/android/gms/internal/ads/zzbme:zzb	()V
    //   30: return
    //   31: astore_1
    //   32: goto +21 -> 53
    //   35: astore_1
    //   36: aload_0
    //   37: getfield 23	com/google/android/gms/internal/ads/zzbnb:zzc	Lcom/google/android/gms/internal/ads/zzcal;
    //   40: aload_1
    //   41: invokevirtual 36	com/google/android/gms/internal/ads/zzcal:zze	(Ljava/lang/Throwable;)Z
    //   44: pop
    //   45: aload_0
    //   46: getfield 21	com/google/android/gms/internal/ads/zzbnb:zzb	Lcom/google/android/gms/internal/ads/zzbme;
    //   49: astore_1
    //   50: goto -24 -> 26
    //   53: aload_0
    //   54: getfield 21	com/google/android/gms/internal/ads/zzbnb:zzb	Lcom/google/android/gms/internal/ads/zzbme;
    //   57: invokevirtual 42	com/google/android/gms/internal/ads/zzbme:zzb	()V
    //   60: aload_1
    //   61: athrow
    //   62: astore_1
    //   63: aload_0
    //   64: getfield 21	com/google/android/gms/internal/ads/zzbnb:zzb	Lcom/google/android/gms/internal/ads/zzbme;
    //   67: astore_1
    //   68: goto -42 -> 26
    // Local variable table:
    //   start	length	slot	name	signature
    //   0	71	0	this	zzbnb
    //   0	71	1	paramJSONObject	org.json.JSONObject
    // Exception table:
    //   from	to	target	type
    //   0	21	31	finally
    //   36	45	31	finally
    //   0	21	35	org/json/JSONException
    //   0	21	62	java/lang/IllegalStateException
  }
}


/* Location:              C:\Users\Ria\Documents\slope apk\dex-tools-v2.4\classes-dex2jar.jar!\com\google\android\gms\internal\ads\zzbnb.class
 * Java compiler version: 6 (50.0)
 * JD-Core Version:       0.7.1
 */