package com.google.android.gms.internal.ads;

import android.content.Context;
import android.os.Looper;
import com.google.android.gms.ads.internal.client.zzba;
import java.io.PrintWriter;
import java.io.StringWriter;
import java.util.WeakHashMap;
import java.util.concurrent.ExecutorService;
import java.util.concurrent.Executors;
import javax.annotation.ParametersAreNonnullByDefault;

@ParametersAreNonnullByDefault
public final class zzbsy
  implements zzbta
{
  static zzbta zza;
  static zzbta zzb;
  private static final Object zzc = new Object();
  private final Object zzd = new Object();
  private final Context zze;
  private final WeakHashMap zzf = new WeakHashMap();
  private final ExecutorService zzg;
  private final zzbzz zzh;
  
  protected zzbsy(Context paramContext, zzbzz paramzzbzz)
  {
    zzflu.zza();
    this.zzg = Executors.unconfigurableExecutorService(Executors.newCachedThreadPool());
    Context localContext = paramContext;
    if (paramContext.getApplicationContext() != null) {
      localContext = paramContext.getApplicationContext();
    }
    this.zze = localContext;
    this.zzh = paramzzbzz;
  }
  
  public static zzbta zza(Context paramContext)
  {
    synchronized (zzc)
    {
      if (zza == null)
      {
        if (((Boolean)zzbdm.zze.zze()).booleanValue())
        {
          Object localObject2 = zzbbk.zzho;
          if (!((Boolean)zzba.zzc().zzb((zzbbc)localObject2)).booleanValue())
          {
            localObject2 = new com/google/android/gms/internal/ads/zzbsy;
            ((zzbsy)localObject2).<init>(paramContext, zzbzz.zza());
            zza = (zzbta)localObject2;
            break label78;
          }
        }
        paramContext = new com/google/android/gms/internal/ads/zzbsz;
        paramContext.<init>();
        zza = paramContext;
      }
      label78:
      return zza;
    }
  }
  
  public static zzbta zzb(Context paramContext, zzbzz arg1)
  {
    synchronized (zzc)
    {
      if (zzb == null)
      {
        if (((Boolean)zzbdm.zze.zze()).booleanValue())
        {
          Object localObject2 = zzbbk.zzho;
          if (!((Boolean)zzba.zzc().zzb((zzbbc)localObject2)).booleanValue())
          {
            localObject2 = new com/google/android/gms/internal/ads/zzbsy;
            ((zzbsy)localObject2).<init>(paramContext, ???);
            paramContext = Looper.getMainLooper().getThread();
            if (paramContext != null) {
              synchronized (((zzbsy)localObject2).zzd)
              {
                ((zzbsy)localObject2).zzf.put(paramContext, Boolean.valueOf(true));
                Thread.UncaughtExceptionHandler localUncaughtExceptionHandler = paramContext.getUncaughtExceptionHandler();
                ??? = new com/google/android/gms/internal/ads/zzbsx;
                ???.<init>((zzbsy)localObject2, localUncaughtExceptionHandler);
                paramContext.setUncaughtExceptionHandler(???);
              }
            }
            paramContext = Thread.getDefaultUncaughtExceptionHandler();
            ??? = new com/google/android/gms/internal/ads/zzbsw;
            ???.<init>((zzbsy)localObject2, paramContext);
            Thread.setDefaultUncaughtExceptionHandler(???);
            zzb = (zzbta)localObject2;
            break label157;
          }
        }
        paramContext = new com/google/android/gms/internal/ads/zzbsz;
        paramContext.<init>();
        zzb = paramContext;
      }
      label157:
      return zzb;
    }
  }
  
  public static String zzc(Throwable paramThrowable)
  {
    StringWriter localStringWriter = new StringWriter();
    paramThrowable.printStackTrace(new PrintWriter(localStringWriter));
    return localStringWriter.toString();
  }
  
  public static String zzd(Throwable paramThrowable)
  {
    return zzfpo.zzc(zzbzm.zzf(zzc(paramThrowable)));
  }
  
  protected final void zze(Thread paramThread, Throwable paramThrowable)
  {
    if (paramThrowable != null)
    {
      paramThread = paramThrowable;
      boolean bool2 = false;
      boolean bool1 = false;
      while (paramThread != null)
      {
        for (StackTraceElement localStackTraceElement : paramThread.getStackTrace())
        {
          bool2 |= zzbzm.zzo(localStackTraceElement.getClassName());
          bool1 |= getClass().getName().equals(localStackTraceElement.getClassName());
        }
        paramThread = paramThread.getCause();
      }
      if ((bool2) && (!bool1)) {
        zzg(paramThrowable, "", 1.0F);
      }
    }
  }
  
  public final void zzf(Throwable paramThrowable, String paramString)
  {
    zzg(paramThrowable, paramString, 1.0F);
  }
  
  /* Error */
  public final void zzg(Throwable paramThrowable, String paramString, float paramFloat)
  {
    // Byte code:
    //   0: getstatic 226	com/google/android/gms/internal/ads/zzbzm:zza	Landroid/os/Handler;
    //   3: astore 13
    //   5: getstatic 228	com/google/android/gms/internal/ads/zzbdm:zzf	Lcom/google/android/gms/internal/ads/zzbcp;
    //   8: invokevirtual 77	com/google/android/gms/internal/ads/zzbcp:zze	()Ljava/lang/Object;
    //   11: checkcast 79	java/lang/Boolean
    //   14: invokevirtual 83	java/lang/Boolean:booleanValue	()Z
    //   17: istore 12
    //   19: iconst_0
    //   20: istore 11
    //   22: iload 12
    //   24: ifeq +9 -> 33
    //   27: aload_1
    //   28: astore 14
    //   30: goto +297 -> 327
    //   33: new 230	java/util/LinkedList
    //   36: dup
    //   37: invokespecial 231	java/util/LinkedList:<init>	()V
    //   40: astore 15
    //   42: aload_1
    //   43: astore 13
    //   45: aload 13
    //   47: ifnull +20 -> 67
    //   50: aload 15
    //   52: aload 13
    //   54: invokevirtual 235	java/util/LinkedList:push	(Ljava/lang/Object;)V
    //   57: aload 13
    //   59: invokevirtual 217	java/lang/Throwable:getCause	()Ljava/lang/Throwable;
    //   62: astore 13
    //   64: goto -19 -> 45
    //   67: aconst_null
    //   68: astore 13
    //   70: aload 13
    //   72: astore 14
    //   74: aload 15
    //   76: invokevirtual 238	java/util/LinkedList:isEmpty	()Z
    //   79: ifne +248 -> 327
    //   82: aload 15
    //   84: invokevirtual 241	java/util/LinkedList:pop	()Ljava/lang/Object;
    //   87: checkcast 165	java/lang/Throwable
    //   90: astore 19
    //   92: aload 19
    //   94: invokevirtual 189	java/lang/Throwable:getStackTrace	()[Ljava/lang/StackTraceElement;
    //   97: astore 18
    //   99: new 243	java/util/ArrayList
    //   102: dup
    //   103: invokespecial 244	java/util/ArrayList:<init>	()V
    //   106: astore 14
    //   108: aload 14
    //   110: new 191	java/lang/StackTraceElement
    //   113: dup
    //   114: aload 19
    //   116: invokevirtual 202	java/lang/Object:getClass	()Ljava/lang/Class;
    //   119: invokevirtual 207	java/lang/Class:getName	()Ljava/lang/String;
    //   122: ldc -10
    //   124: ldc -10
    //   126: iconst_1
    //   127: invokespecial 249	java/lang/StackTraceElement:<init>	(Ljava/lang/String;Ljava/lang/String;Ljava/lang/String;I)V
    //   130: invokevirtual 252	java/util/ArrayList:add	(Ljava/lang/Object;)Z
    //   133: pop
    //   134: aload 18
    //   136: arraylength
    //   137: istore 10
    //   139: iconst_0
    //   140: istore 8
    //   142: iconst_0
    //   143: istore 9
    //   145: iload 8
    //   147: iload 10
    //   149: if_icmpge +115 -> 264
    //   152: aload 18
    //   154: iload 8
    //   156: aaload
    //   157: astore 16
    //   159: aload 16
    //   161: invokevirtual 194	java/lang/StackTraceElement:getClassName	()Ljava/lang/String;
    //   164: invokestatic 198	com/google/android/gms/internal/ads/zzbzm:zzo	(Ljava/lang/String;)Z
    //   167: ifeq +17 -> 184
    //   170: aload 14
    //   172: aload 16
    //   174: invokevirtual 252	java/util/ArrayList:add	(Ljava/lang/Object;)Z
    //   177: pop
    //   178: iconst_1
    //   179: istore 9
    //   181: goto +77 -> 258
    //   184: aload 16
    //   186: invokevirtual 194	java/lang/StackTraceElement:getClassName	()Ljava/lang/String;
    //   189: astore 17
    //   191: aload 17
    //   193: invokestatic 257	android/text/TextUtils:isEmpty	(Ljava/lang/CharSequence;)Z
    //   196: ifeq +6 -> 202
    //   199: goto +28 -> 227
    //   202: aload 17
    //   204: ldc_w 259
    //   207: invokevirtual 262	java/lang/String:startsWith	(Ljava/lang/String;)Z
    //   210: ifne +40 -> 250
    //   213: aload 17
    //   215: ldc_w 264
    //   218: invokevirtual 262	java/lang/String:startsWith	(Ljava/lang/String;)Z
    //   221: ifeq +6 -> 227
    //   224: goto +26 -> 250
    //   227: aload 14
    //   229: new 191	java/lang/StackTraceElement
    //   232: dup
    //   233: ldc -10
    //   235: ldc -10
    //   237: ldc -10
    //   239: iconst_1
    //   240: invokespecial 249	java/lang/StackTraceElement:<init>	(Ljava/lang/String;Ljava/lang/String;Ljava/lang/String;I)V
    //   243: invokevirtual 252	java/util/ArrayList:add	(Ljava/lang/Object;)Z
    //   246: pop
    //   247: goto +11 -> 258
    //   250: aload 14
    //   252: aload 16
    //   254: invokevirtual 252	java/util/ArrayList:add	(Ljava/lang/Object;)Z
    //   257: pop
    //   258: iinc 8 1
    //   261: goto -116 -> 145
    //   264: iload 9
    //   266: ifeq -196 -> 70
    //   269: aload 13
    //   271: ifnonnull +20 -> 291
    //   274: new 165	java/lang/Throwable
    //   277: dup
    //   278: aload 19
    //   280: invokevirtual 267	java/lang/Throwable:getMessage	()Ljava/lang/String;
    //   283: invokespecial 270	java/lang/Throwable:<init>	(Ljava/lang/String;)V
    //   286: astore 13
    //   288: goto +19 -> 307
    //   291: new 165	java/lang/Throwable
    //   294: dup
    //   295: aload 19
    //   297: invokevirtual 267	java/lang/Throwable:getMessage	()Ljava/lang/String;
    //   300: aload 13
    //   302: invokespecial 273	java/lang/Throwable:<init>	(Ljava/lang/String;Ljava/lang/Throwable;)V
    //   305: astore 13
    //   307: aload 13
    //   309: aload 14
    //   311: iconst_0
    //   312: anewarray 191	java/lang/StackTraceElement
    //   315: invokevirtual 277	java/util/ArrayList:toArray	([Ljava/lang/Object;)[Ljava/lang/Object;
    //   318: checkcast 279	[Ljava/lang/StackTraceElement;
    //   321: invokevirtual 283	java/lang/Throwable:setStackTrace	([Ljava/lang/StackTraceElement;)V
    //   324: goto -254 -> 70
    //   327: aload 14
    //   329: ifnonnull +4 -> 333
    //   332: return
    //   333: aload_1
    //   334: invokevirtual 202	java/lang/Object:getClass	()Ljava/lang/Class;
    //   337: invokevirtual 207	java/lang/Class:getName	()Ljava/lang/String;
    //   340: astore 17
    //   342: aload_1
    //   343: invokestatic 175	com/google/android/gms/internal/ads/zzbsy:zzc	(Ljava/lang/Throwable;)Ljava/lang/String;
    //   346: astore 16
    //   348: getstatic 286	com/google/android/gms/internal/ads/zzbbk:zzim	Lcom/google/android/gms/internal/ads/zzbbc;
    //   351: astore 13
    //   353: invokestatic 94	com/google/android/gms/ads/internal/client/zzba:zzc	()Lcom/google/android/gms/internal/ads/zzbbi;
    //   356: aload 13
    //   358: invokevirtual 99	com/google/android/gms/internal/ads/zzbbi:zzb	(Lcom/google/android/gms/internal/ads/zzbbc;)Ljava/lang/Object;
    //   361: checkcast 79	java/lang/Boolean
    //   364: invokevirtual 83	java/lang/Boolean:booleanValue	()Z
    //   367: ifeq +11 -> 378
    //   370: aload_1
    //   371: invokestatic 288	com/google/android/gms/internal/ads/zzbsy:zzd	(Ljava/lang/Throwable;)Ljava/lang/String;
    //   374: astore_1
    //   375: goto +6 -> 381
    //   378: ldc -37
    //   380: astore_1
    //   381: fload_3
    //   382: f2d
    //   383: dstore 6
    //   385: invokestatic 294	java/lang/Math:random	()D
    //   388: dstore 4
    //   390: fload_3
    //   391: fconst_0
    //   392: fcmpl
    //   393: ifle +12 -> 405
    //   396: fconst_1
    //   397: fload_3
    //   398: fdiv
    //   399: f2i
    //   400: istore 8
    //   402: goto +6 -> 408
    //   405: iconst_1
    //   406: istore 8
    //   408: dload 4
    //   410: dload 6
    //   412: dcmpg
    //   413: ifge +446 -> 859
    //   416: new 243	java/util/ArrayList
    //   419: dup
    //   420: invokespecial 244	java/util/ArrayList:<init>	()V
    //   423: astore 15
    //   425: aload_0
    //   426: getfield 62	com/google/android/gms/internal/ads/zzbsy:zze	Landroid/content/Context;
    //   429: invokestatic 300	com/google/android/gms/common/wrappers/Wrappers:packageManager	(Landroid/content/Context;)Lcom/google/android/gms/common/wrappers/PackageManagerWrapper;
    //   432: invokevirtual 305	com/google/android/gms/common/wrappers/PackageManagerWrapper:isCallerInstantApp	()Z
    //   435: istore 12
    //   437: iload 12
    //   439: istore 11
    //   441: goto +13 -> 454
    //   444: astore 13
    //   446: ldc_w 307
    //   449: aload 13
    //   451: invokestatic 311	com/google/android/gms/internal/ads/zzbzt:zzh	(Ljava/lang/String;Ljava/lang/Throwable;)V
    //   454: aload_0
    //   455: getfield 62	com/google/android/gms/internal/ads/zzbsy:zze	Landroid/content/Context;
    //   458: invokevirtual 314	android/content/Context:getPackageName	()Ljava/lang/String;
    //   461: astore 13
    //   463: goto +16 -> 479
    //   466: astore 13
    //   468: ldc_w 316
    //   471: invokestatic 319	com/google/android/gms/internal/ads/zzbzt:zzj	(Ljava/lang/String;)V
    //   474: ldc_w 321
    //   477: astore 13
    //   479: new 323	android/net/Uri$Builder
    //   482: dup
    //   483: invokespecial 324	android/net/Uri$Builder:<init>	()V
    //   486: ldc_w 326
    //   489: invokevirtual 330	android/net/Uri$Builder:scheme	(Ljava/lang/String;)Landroid/net/Uri$Builder;
    //   492: ldc_w 332
    //   495: invokevirtual 335	android/net/Uri$Builder:path	(Ljava/lang/String;)Landroid/net/Uri$Builder;
    //   498: ldc_w 337
    //   501: iload 11
    //   503: invokestatic 340	java/lang/Boolean:toString	(Z)Ljava/lang/String;
    //   506: invokevirtual 344	android/net/Uri$Builder:appendQueryParameter	(Ljava/lang/String;Ljava/lang/String;)Landroid/net/Uri$Builder;
    //   509: ldc_w 346
    //   512: ldc_w 348
    //   515: invokevirtual 344	android/net/Uri$Builder:appendQueryParameter	(Ljava/lang/String;Ljava/lang/String;)Landroid/net/Uri$Builder;
    //   518: ldc_w 350
    //   521: getstatic 356	android/os/Build$VERSION:RELEASE	Ljava/lang/String;
    //   524: invokevirtual 344	android/net/Uri$Builder:appendQueryParameter	(Ljava/lang/String;Ljava/lang/String;)Landroid/net/Uri$Builder;
    //   527: ldc_w 358
    //   530: getstatic 362	android/os/Build$VERSION:SDK_INT	I
    //   533: invokestatic 365	java/lang/String:valueOf	(I)Ljava/lang/String;
    //   536: invokevirtual 344	android/net/Uri$Builder:appendQueryParameter	(Ljava/lang/String;Ljava/lang/String;)Landroid/net/Uri$Builder;
    //   539: astore 18
    //   541: getstatic 370	android/os/Build:MANUFACTURER	Ljava/lang/String;
    //   544: astore 19
    //   546: getstatic 373	android/os/Build:MODEL	Ljava/lang/String;
    //   549: astore 14
    //   551: aload 14
    //   553: aload 19
    //   555: invokevirtual 262	java/lang/String:startsWith	(Ljava/lang/String;)Z
    //   558: ifeq +6 -> 564
    //   561: goto +44 -> 605
    //   564: new 375	java/lang/StringBuilder
    //   567: dup
    //   568: invokespecial 376	java/lang/StringBuilder:<init>	()V
    //   571: astore 20
    //   573: aload 20
    //   575: aload 19
    //   577: invokevirtual 380	java/lang/StringBuilder:append	(Ljava/lang/String;)Ljava/lang/StringBuilder;
    //   580: pop
    //   581: aload 20
    //   583: ldc_w 382
    //   586: invokevirtual 380	java/lang/StringBuilder:append	(Ljava/lang/String;)Ljava/lang/StringBuilder;
    //   589: pop
    //   590: aload 20
    //   592: aload 14
    //   594: invokevirtual 380	java/lang/StringBuilder:append	(Ljava/lang/String;)Ljava/lang/StringBuilder;
    //   597: pop
    //   598: aload 20
    //   600: invokevirtual 383	java/lang/StringBuilder:toString	()Ljava/lang/String;
    //   603: astore 14
    //   605: aload 18
    //   607: ldc_w 385
    //   610: aload 14
    //   612: invokevirtual 344	android/net/Uri$Builder:appendQueryParameter	(Ljava/lang/String;Ljava/lang/String;)Landroid/net/Uri$Builder;
    //   615: ldc_w 387
    //   618: aload_0
    //   619: getfield 64	com/google/android/gms/internal/ads/zzbsy:zzh	Lcom/google/android/gms/internal/ads/zzbzz;
    //   622: getfield 389	com/google/android/gms/internal/ads/zzbzz:zza	Ljava/lang/String;
    //   625: invokevirtual 344	android/net/Uri$Builder:appendQueryParameter	(Ljava/lang/String;Ljava/lang/String;)Landroid/net/Uri$Builder;
    //   628: ldc_w 391
    //   631: aload 13
    //   633: invokevirtual 344	android/net/Uri$Builder:appendQueryParameter	(Ljava/lang/String;Ljava/lang/String;)Landroid/net/Uri$Builder;
    //   636: ldc_w 393
    //   639: aload 17
    //   641: invokevirtual 344	android/net/Uri$Builder:appendQueryParameter	(Ljava/lang/String;Ljava/lang/String;)Landroid/net/Uri$Builder;
    //   644: ldc_w 395
    //   647: aload 16
    //   649: invokevirtual 344	android/net/Uri$Builder:appendQueryParameter	(Ljava/lang/String;Ljava/lang/String;)Landroid/net/Uri$Builder;
    //   652: ldc_w 397
    //   655: ldc_w 399
    //   658: invokestatic 402	com/google/android/gms/ads/internal/client/zzba:zza	()Lcom/google/android/gms/internal/ads/zzbbd;
    //   661: invokevirtual 407	com/google/android/gms/internal/ads/zzbbd:zza	()Ljava/util/List;
    //   664: invokestatic 411	android/text/TextUtils:join	(Ljava/lang/CharSequence;Ljava/lang/Iterable;)Ljava/lang/String;
    //   667: invokevirtual 344	android/net/Uri$Builder:appendQueryParameter	(Ljava/lang/String;Ljava/lang/String;)Landroid/net/Uri$Builder;
    //   670: ldc_w 413
    //   673: aload_2
    //   674: invokevirtual 344	android/net/Uri$Builder:appendQueryParameter	(Ljava/lang/String;Ljava/lang/String;)Landroid/net/Uri$Builder;
    //   677: ldc_w 415
    //   680: ldc_w 417
    //   683: invokevirtual 344	android/net/Uri$Builder:appendQueryParameter	(Ljava/lang/String;Ljava/lang/String;)Landroid/net/Uri$Builder;
    //   686: ldc_w 419
    //   689: ldc_w 421
    //   692: invokevirtual 344	android/net/Uri$Builder:appendQueryParameter	(Ljava/lang/String;Ljava/lang/String;)Landroid/net/Uri$Builder;
    //   695: ldc_w 423
    //   698: iload 8
    //   700: invokestatic 427	java/lang/Integer:toString	(I)Ljava/lang/String;
    //   703: invokevirtual 344	android/net/Uri$Builder:appendQueryParameter	(Ljava/lang/String;Ljava/lang/String;)Landroid/net/Uri$Builder;
    //   706: ldc_w 429
    //   709: getstatic 431	com/google/android/gms/internal/ads/zzbdm:zzc	Lcom/google/android/gms/internal/ads/zzbcp;
    //   712: invokevirtual 77	com/google/android/gms/internal/ads/zzbcp:zze	()Ljava/lang/Object;
    //   715: invokestatic 434	java/lang/String:valueOf	(Ljava/lang/Object;)Ljava/lang/String;
    //   718: invokevirtual 344	android/net/Uri$Builder:appendQueryParameter	(Ljava/lang/String;Ljava/lang/String;)Landroid/net/Uri$Builder;
    //   721: ldc_w 436
    //   724: invokestatic 442	com/google/android/gms/common/GoogleApiAvailabilityLight:getInstance	()Lcom/google/android/gms/common/GoogleApiAvailabilityLight;
    //   727: aload_0
    //   728: getfield 62	com/google/android/gms/internal/ads/zzbsy:zze	Landroid/content/Context;
    //   731: invokevirtual 446	com/google/android/gms/common/GoogleApiAvailabilityLight:getApkVersion	(Landroid/content/Context;)I
    //   734: invokestatic 365	java/lang/String:valueOf	(I)Ljava/lang/String;
    //   737: invokevirtual 344	android/net/Uri$Builder:appendQueryParameter	(Ljava/lang/String;Ljava/lang/String;)Landroid/net/Uri$Builder;
    //   740: astore 13
    //   742: iconst_1
    //   743: aload_0
    //   744: getfield 64	com/google/android/gms/internal/ads/zzbsy:zzh	Lcom/google/android/gms/internal/ads/zzbzz;
    //   747: getfield 449	com/google/android/gms/internal/ads/zzbzz:zze	Z
    //   750: if_icmpeq +10 -> 760
    //   753: ldc_w 451
    //   756: astore_2
    //   757: goto +7 -> 764
    //   760: ldc_w 453
    //   763: astore_2
    //   764: aload 13
    //   766: ldc_w 455
    //   769: aload_2
    //   770: invokevirtual 344	android/net/Uri$Builder:appendQueryParameter	(Ljava/lang/String;Ljava/lang/String;)Landroid/net/Uri$Builder;
    //   773: astore_2
    //   774: aload_1
    //   775: invokestatic 257	android/text/TextUtils:isEmpty	(Ljava/lang/CharSequence;)Z
    //   778: ifne +12 -> 790
    //   781: aload_2
    //   782: ldc_w 457
    //   785: aload_1
    //   786: invokevirtual 344	android/net/Uri$Builder:appendQueryParameter	(Ljava/lang/String;Ljava/lang/String;)Landroid/net/Uri$Builder;
    //   789: pop
    //   790: aload 15
    //   792: aload_2
    //   793: invokevirtual 458	android/net/Uri$Builder:toString	()Ljava/lang/String;
    //   796: invokevirtual 252	java/util/ArrayList:add	(Ljava/lang/Object;)Z
    //   799: pop
    //   800: aload 15
    //   802: invokeinterface 464 1 0
    //   807: astore_1
    //   808: aload_1
    //   809: invokeinterface 469 1 0
    //   814: ifeq +45 -> 859
    //   817: aload_1
    //   818: invokeinterface 472 1 0
    //   823: checkcast 209	java/lang/String
    //   826: astore 13
    //   828: new 474	com/google/android/gms/internal/ads/zzbzy
    //   831: dup
    //   832: aconst_null
    //   833: invokespecial 475	com/google/android/gms/internal/ads/zzbzy:<init>	(Ljava/lang/String;)V
    //   836: astore_2
    //   837: aload_0
    //   838: getfield 54	com/google/android/gms/internal/ads/zzbsy:zzg	Ljava/util/concurrent/ExecutorService;
    //   841: new 477	com/google/android/gms/internal/ads/zzbsv
    //   844: dup
    //   845: aload_2
    //   846: aload 13
    //   848: invokespecial 480	com/google/android/gms/internal/ads/zzbsv:<init>	(Lcom/google/android/gms/internal/ads/zzbzy;Ljava/lang/String;)V
    //   851: invokeinterface 486 2 0
    //   856: goto -48 -> 808
    //   859: return
    // Local variable table:
    //   start	length	slot	name	signature
    //   0	860	0	this	zzbsy
    //   0	860	1	paramThrowable	Throwable
    //   0	860	2	paramString	String
    //   0	860	3	paramFloat	float
    //   388	21	4	d1	double
    //   383	28	6	d2	double
    //   140	559	8	i	int
    //   143	122	9	j	int
    //   137	13	10	k	int
    //   20	482	11	bool1	boolean
    //   17	421	12	bool2	boolean
    //   3	354	13	localObject1	Object
    //   444	6	13	localThrowable	Throwable
    //   461	1	13	str1	String
    //   466	1	13	localObject2	Object
    //   477	370	13	localObject3	Object
    //   28	583	14	localObject4	Object
    //   40	761	15	localObject5	Object
    //   157	491	16	localObject6	Object
    //   189	451	17	str2	String
    //   97	509	18	localObject7	Object
    //   90	486	19	localObject8	Object
    //   571	28	20	localStringBuilder	StringBuilder
    // Exception table:
    //   from	to	target	type
    //   425	437	444	finally
    //   454	463	466	finally
  }
}


/* Location:              C:\Users\Ria\Documents\slope apk\dex-tools-v2.4\classes-dex2jar.jar!\com\google\android\gms\internal\ads\zzbsy.class
 * Java compiler version: 6 (50.0)
 * JD-Core Version:       0.7.1
 */