package com.google.android.gms.internal.ads;

import android.content.Context;
import java.io.File;
import java.text.DecimalFormat;
import java.util.Collections;
import java.util.HashSet;
import java.util.Set;

public final class zzcdq
  extends zzcdn
{
  public static final int zzd = 0;
  private static final Set zze = Collections.synchronizedSet(new HashSet());
  private static final DecimalFormat zzf = new DecimalFormat("#,###");
  private File zzg;
  private boolean zzh;
  
  public zzcdq(zzccc paramzzccc)
  {
    super(paramzzccc);
    paramzzccc = this.zza.getCacheDir();
    if (paramzzccc == null)
    {
      zzbzt.zzj("Context.getCacheDir() returned null");
      return;
    }
    paramzzccc = new File(paramzzccc, "admobVideoStreams");
    this.zzg = paramzzccc;
    if ((!paramzzccc.isDirectory()) && (!this.zzg.mkdirs()))
    {
      zzbzt.zzj("Could not create preload cache directory at ".concat(String.valueOf(this.zzg.getAbsolutePath())));
      this.zzg = null;
      return;
    }
    if ((this.zzg.setReadable(true, false)) && (this.zzg.setExecutable(true, false))) {
      return;
    }
    zzbzt.zzj("Could not set cache file permissions at ".concat(String.valueOf(this.zzg.getAbsolutePath())));
    this.zzg = null;
  }
  
  private final File zza(File paramFile)
  {
    return new File(this.zzg, String.valueOf(paramFile.getName()).concat(".done"));
  }
  
  public final void zzf()
  {
    this.zzh = true;
  }
  
  /* Error */
  public final boolean zzt(String paramString)
  {
    // Byte code:
    //   0: aload_0
    //   1: getfield 69	com/google/android/gms/internal/ads/zzcdq:zzg	Ljava/io/File;
    //   4: astore 14
    //   6: aconst_null
    //   7: astore 18
    //   9: aload 14
    //   11: ifnull +2397 -> 2408
    //   14: aload_0
    //   15: getfield 69	com/google/android/gms/internal/ads/zzcdq:zzg	Ljava/io/File;
    //   18: astore 14
    //   20: aload 14
    //   22: ifnonnull +9 -> 31
    //   25: iconst_0
    //   26: istore 4
    //   28: goto +60 -> 88
    //   31: aload 14
    //   33: invokevirtual 121	java/io/File:listFiles	()[Ljava/io/File;
    //   36: astore 14
    //   38: aload 14
    //   40: arraylength
    //   41: istore 5
    //   43: iconst_0
    //   44: istore_3
    //   45: iconst_0
    //   46: istore_2
    //   47: iload_2
    //   48: istore 4
    //   50: iload_3
    //   51: iload 5
    //   53: if_icmpge +35 -> 88
    //   56: iload_2
    //   57: istore 4
    //   59: aload 14
    //   61: iload_3
    //   62: aaload
    //   63: invokevirtual 105	java/io/File:getName	()Ljava/lang/String;
    //   66: ldc 107
    //   68: invokevirtual 124	java/lang/String:endsWith	(Ljava/lang/String;)Z
    //   71: ifne +8 -> 79
    //   74: iload_2
    //   75: iconst_1
    //   76: iadd
    //   77: istore 4
    //   79: iinc 3 1
    //   82: iload 4
    //   84: istore_2
    //   85: goto -38 -> 47
    //   88: getstatic 130	com/google/android/gms/internal/ads/zzbbk:zzu	Lcom/google/android/gms/internal/ads/zzbbc;
    //   91: astore 14
    //   93: iload 4
    //   95: invokestatic 136	com/google/android/gms/ads/internal/client/zzba:zzc	()Lcom/google/android/gms/internal/ads/zzbbi;
    //   98: aload 14
    //   100: invokevirtual 142	com/google/android/gms/internal/ads/zzbbi:zzb	(Lcom/google/android/gms/internal/ads/zzbbc;)Ljava/lang/Object;
    //   103: checkcast 144	java/lang/Integer
    //   106: invokevirtual 148	java/lang/Integer:intValue	()I
    //   109: if_icmple +184 -> 293
    //   112: aload_0
    //   113: getfield 69	com/google/android/gms/internal/ads/zzcdq:zzg	Ljava/io/File;
    //   116: astore 14
    //   118: aload 14
    //   120: ifnonnull +6 -> 126
    //   123: goto +154 -> 277
    //   126: aload 14
    //   128: invokevirtual 121	java/io/File:listFiles	()[Ljava/io/File;
    //   131: astore 17
    //   133: aload 17
    //   135: arraylength
    //   136: istore_3
    //   137: ldc2_w 149
    //   140: lstore 10
    //   142: aconst_null
    //   143: astore 14
    //   145: iconst_0
    //   146: istore_2
    //   147: iload_2
    //   148: iload_3
    //   149: if_icmpge +75 -> 224
    //   152: aload 17
    //   154: iload_2
    //   155: aaload
    //   156: astore 16
    //   158: lload 10
    //   160: lstore 8
    //   162: aload 14
    //   164: astore 15
    //   166: aload 16
    //   168: invokevirtual 105	java/io/File:getName	()Ljava/lang/String;
    //   171: ldc 107
    //   173: invokevirtual 124	java/lang/String:endsWith	(Ljava/lang/String;)Z
    //   176: ifne +34 -> 210
    //   179: aload 16
    //   181: invokevirtual 154	java/io/File:lastModified	()J
    //   184: lstore 12
    //   186: lload 10
    //   188: lstore 8
    //   190: aload 14
    //   192: astore 15
    //   194: lload 12
    //   196: lload 10
    //   198: lcmp
    //   199: ifge +11 -> 210
    //   202: aload 16
    //   204: astore 15
    //   206: lload 12
    //   208: lstore 8
    //   210: iinc 2 1
    //   213: lload 8
    //   215: lstore 10
    //   217: aload 15
    //   219: astore 14
    //   221: goto -74 -> 147
    //   224: aload 14
    //   226: ifnull +43 -> 269
    //   229: aload 14
    //   231: invokevirtual 157	java/io/File:delete	()Z
    //   234: istore 7
    //   236: aload_0
    //   237: aload 14
    //   239: invokespecial 159	com/google/android/gms/internal/ads/zzcdq:zza	(Ljava/io/File;)Ljava/io/File;
    //   242: astore 14
    //   244: iload 7
    //   246: istore 6
    //   248: aload 14
    //   250: invokevirtual 162	java/io/File:isFile	()Z
    //   253: ifeq +19 -> 272
    //   256: iload 7
    //   258: aload 14
    //   260: invokevirtual 157	java/io/File:delete	()Z
    //   263: iand
    //   264: istore 6
    //   266: goto +6 -> 272
    //   269: iconst_0
    //   270: istore 6
    //   272: iload 6
    //   274: ifne -260 -> 14
    //   277: ldc -92
    //   279: invokestatic 60	com/google/android/gms/internal/ads/zzbzt:zzj	(Ljava/lang/String;)V
    //   282: aload_0
    //   283: aload_1
    //   284: aconst_null
    //   285: ldc -90
    //   287: aconst_null
    //   288: invokevirtual 169	com/google/android/gms/internal/ads/zzcdn:zzg	(Ljava/lang/String;Ljava/lang/String;Ljava/lang/String;Ljava/lang/String;)V
    //   291: iconst_0
    //   292: ireturn
    //   293: aload_1
    //   294: invokestatic 173	com/google/android/gms/internal/ads/zzbzm:zze	(Ljava/lang/String;)Ljava/lang/String;
    //   297: astore 14
    //   299: new 62	java/io/File
    //   302: dup
    //   303: aload_0
    //   304: getfield 69	com/google/android/gms/internal/ads/zzcdq:zzg	Ljava/io/File;
    //   307: aload 14
    //   309: invokespecial 67	java/io/File:<init>	(Ljava/io/File;Ljava/lang/String;)V
    //   312: astore 27
    //   314: aload_0
    //   315: aload 27
    //   317: invokespecial 159	com/google/android/gms/internal/ads/zzcdq:zza	(Ljava/io/File;)Ljava/io/File;
    //   320: astore 28
    //   322: aload 27
    //   324: invokevirtual 162	java/io/File:isFile	()Z
    //   327: ifeq +46 -> 373
    //   330: aload 28
    //   332: invokevirtual 162	java/io/File:isFile	()Z
    //   335: ifne +6 -> 341
    //   338: goto +35 -> 373
    //   341: aload 27
    //   343: invokevirtual 176	java/io/File:length	()J
    //   346: l2i
    //   347: istore_2
    //   348: ldc -78
    //   350: aload_1
    //   351: invokestatic 88	java/lang/String:valueOf	(Ljava/lang/Object;)Ljava/lang/String;
    //   354: invokevirtual 92	java/lang/String:concat	(Ljava/lang/String;)Ljava/lang/String;
    //   357: invokestatic 180	com/google/android/gms/internal/ads/zzbzt:zze	(Ljava/lang/String;)V
    //   360: aload_0
    //   361: aload_1
    //   362: aload 27
    //   364: invokevirtual 82	java/io/File:getAbsolutePath	()Ljava/lang/String;
    //   367: iload_2
    //   368: invokevirtual 183	com/google/android/gms/internal/ads/zzcdn:zzh	(Ljava/lang/String;Ljava/lang/String;I)V
    //   371: iconst_1
    //   372: ireturn
    //   373: aload_0
    //   374: getfield 69	com/google/android/gms/internal/ads/zzcdq:zzg	Ljava/io/File;
    //   377: invokevirtual 82	java/io/File:getAbsolutePath	()Ljava/lang/String;
    //   380: invokestatic 88	java/lang/String:valueOf	(Ljava/lang/Object;)Ljava/lang/String;
    //   383: astore 14
    //   385: aload_1
    //   386: invokestatic 88	java/lang/String:valueOf	(Ljava/lang/Object;)Ljava/lang/String;
    //   389: astore 16
    //   391: getstatic 30	com/google/android/gms/internal/ads/zzcdq:zze	Ljava/util/Set;
    //   394: astore 15
    //   396: aload 14
    //   398: aload 16
    //   400: invokevirtual 92	java/lang/String:concat	(Ljava/lang/String;)Ljava/lang/String;
    //   403: astore 14
    //   405: aload 15
    //   407: monitorenter
    //   408: aload 15
    //   410: aload 14
    //   412: invokeinterface 189 2 0
    //   417: ifeq +54 -> 471
    //   420: new 191	java/lang/StringBuilder
    //   423: astore 14
    //   425: aload 14
    //   427: invokespecial 192	java/lang/StringBuilder:<init>	()V
    //   430: aload 14
    //   432: ldc -62
    //   434: invokevirtual 198	java/lang/StringBuilder:append	(Ljava/lang/String;)Ljava/lang/StringBuilder;
    //   437: pop
    //   438: aload 14
    //   440: aload_1
    //   441: invokevirtual 198	java/lang/StringBuilder:append	(Ljava/lang/String;)Ljava/lang/StringBuilder;
    //   444: pop
    //   445: aload 14
    //   447: invokevirtual 201	java/lang/StringBuilder:toString	()Ljava/lang/String;
    //   450: invokestatic 60	com/google/android/gms/internal/ads/zzbzt:zzj	(Ljava/lang/String;)V
    //   453: aload_0
    //   454: aload_1
    //   455: aload 27
    //   457: invokevirtual 82	java/io/File:getAbsolutePath	()Ljava/lang/String;
    //   460: ldc -53
    //   462: aconst_null
    //   463: invokevirtual 169	com/google/android/gms/internal/ads/zzcdn:zzg	(Ljava/lang/String;Ljava/lang/String;Ljava/lang/String;Ljava/lang/String;)V
    //   466: aload 15
    //   468: monitorexit
    //   469: iconst_0
    //   470: ireturn
    //   471: aload 15
    //   473: aload 14
    //   475: invokeinterface 206 2 0
    //   480: pop
    //   481: aload 15
    //   483: monitorexit
    //   484: ldc -48
    //   486: astore 16
    //   488: invokestatic 213	com/google/android/gms/internal/ads/zzflq:zza	()Lcom/google/android/gms/internal/ads/zzflq;
    //   491: astore 19
    //   493: new 215	com/google/android/gms/internal/ads/zzcdp
    //   496: astore 17
    //   498: aload 17
    //   500: aload_1
    //   501: invokespecial 216	com/google/android/gms/internal/ads/zzcdp:<init>	(Ljava/lang/String;)V
    //   504: aload 19
    //   506: aload 17
    //   508: sipush 265
    //   511: iconst_m1
    //   512: invokevirtual 220	com/google/android/gms/internal/ads/zzflq:zzn	(Lcom/google/android/gms/internal/ads/zzflp;II)Ljava/net/HttpURLConnection;
    //   515: astore 19
    //   517: aload 19
    //   519: instanceof 222
    //   522: ifeq +159 -> 681
    //   525: aload 19
    //   527: invokevirtual 225	java/net/HttpURLConnection:getResponseCode	()I
    //   530: istore_2
    //   531: iload_2
    //   532: sipush 400
    //   535: if_icmpge +6 -> 541
    //   538: goto +143 -> 681
    //   541: ldc -29
    //   543: astore 19
    //   545: iload_2
    //   546: invokestatic 230	java/lang/Integer:toString	(I)Ljava/lang/String;
    //   549: astore 16
    //   551: new 191	java/lang/StringBuilder
    //   554: astore 15
    //   556: aload 15
    //   558: invokespecial 192	java/lang/StringBuilder:<init>	()V
    //   561: aload 15
    //   563: ldc -24
    //   565: invokevirtual 198	java/lang/StringBuilder:append	(Ljava/lang/String;)Ljava/lang/StringBuilder;
    //   568: pop
    //   569: aload 15
    //   571: aload 16
    //   573: invokevirtual 198	java/lang/StringBuilder:append	(Ljava/lang/String;)Ljava/lang/StringBuilder;
    //   576: pop
    //   577: aload 15
    //   579: invokevirtual 201	java/lang/StringBuilder:toString	()Ljava/lang/String;
    //   582: astore 16
    //   584: new 113	java/io/IOException
    //   587: astore 15
    //   589: new 191	java/lang/StringBuilder
    //   592: astore 17
    //   594: aload 17
    //   596: invokespecial 192	java/lang/StringBuilder:<init>	()V
    //   599: aload 17
    //   601: ldc -22
    //   603: invokevirtual 198	java/lang/StringBuilder:append	(Ljava/lang/String;)Ljava/lang/StringBuilder;
    //   606: pop
    //   607: aload 17
    //   609: iload_2
    //   610: invokevirtual 237	java/lang/StringBuilder:append	(I)Ljava/lang/StringBuilder;
    //   613: pop
    //   614: aload 17
    //   616: ldc -17
    //   618: invokevirtual 198	java/lang/StringBuilder:append	(Ljava/lang/String;)Ljava/lang/StringBuilder;
    //   621: pop
    //   622: aload 17
    //   624: aload_1
    //   625: invokevirtual 198	java/lang/StringBuilder:append	(Ljava/lang/String;)Ljava/lang/StringBuilder;
    //   628: pop
    //   629: aload 15
    //   631: aload 17
    //   633: invokevirtual 201	java/lang/StringBuilder:toString	()Ljava/lang/String;
    //   636: invokespecial 240	java/io/IOException:<init>	(Ljava/lang/String;)V
    //   639: aload 15
    //   641: athrow
    //   642: astore 15
    //   644: goto +5 -> 649
    //   647: astore 15
    //   649: goto +13 -> 662
    //   652: astore 15
    //   654: goto +5 -> 659
    //   657: astore 15
    //   659: aconst_null
    //   660: astore 16
    //   662: aload 14
    //   664: astore 17
    //   666: aload 15
    //   668: astore 14
    //   670: aload 17
    //   672: astore 15
    //   674: aload 19
    //   676: astore 17
    //   678: goto +1539 -> 2217
    //   681: aload 19
    //   683: invokevirtual 245	java/net/URLConnection:getContentLength	()I
    //   686: istore_2
    //   687: iload_2
    //   688: ifge +61 -> 749
    //   691: new 191	java/lang/StringBuilder
    //   694: astore 16
    //   696: aload 16
    //   698: invokespecial 192	java/lang/StringBuilder:<init>	()V
    //   701: aload 16
    //   703: ldc -9
    //   705: invokevirtual 198	java/lang/StringBuilder:append	(Ljava/lang/String;)Ljava/lang/StringBuilder;
    //   708: pop
    //   709: aload 16
    //   711: aload_1
    //   712: invokevirtual 198	java/lang/StringBuilder:append	(Ljava/lang/String;)Ljava/lang/StringBuilder;
    //   715: pop
    //   716: aload 16
    //   718: invokevirtual 201	java/lang/StringBuilder:toString	()Ljava/lang/String;
    //   721: invokestatic 60	com/google/android/gms/internal/ads/zzbzt:zzj	(Ljava/lang/String;)V
    //   724: aload_0
    //   725: aload_1
    //   726: aload 27
    //   728: invokevirtual 82	java/io/File:getAbsolutePath	()Ljava/lang/String;
    //   731: ldc -7
    //   733: aconst_null
    //   734: invokevirtual 169	com/google/android/gms/internal/ads/zzcdn:zzg	(Ljava/lang/String;Ljava/lang/String;Ljava/lang/String;Ljava/lang/String;)V
    //   737: aload 15
    //   739: aload 14
    //   741: invokeinterface 252 2 0
    //   746: pop
    //   747: iconst_0
    //   748: ireturn
    //   749: getstatic 39	com/google/android/gms/internal/ads/zzcdq:zzf	Ljava/text/DecimalFormat;
    //   752: iload_2
    //   753: i2l
    //   754: invokevirtual 256	java/text/DecimalFormat:format	(J)Ljava/lang/String;
    //   757: astore 17
    //   759: getstatic 259	com/google/android/gms/internal/ads/zzbbk:zzv	Lcom/google/android/gms/internal/ads/zzbbc;
    //   762: astore 18
    //   764: invokestatic 136	com/google/android/gms/ads/internal/client/zzba:zzc	()Lcom/google/android/gms/internal/ads/zzbbi;
    //   767: aload 18
    //   769: invokevirtual 142	com/google/android/gms/internal/ads/zzbbi:zzb	(Lcom/google/android/gms/internal/ads/zzbbc;)Ljava/lang/Object;
    //   772: checkcast 144	java/lang/Integer
    //   775: invokevirtual 148	java/lang/Integer:intValue	()I
    //   778: istore_3
    //   779: iload_2
    //   780: iload_3
    //   781: if_icmple +115 -> 896
    //   784: new 191	java/lang/StringBuilder
    //   787: astore 16
    //   789: aload 16
    //   791: invokespecial 192	java/lang/StringBuilder:<init>	()V
    //   794: aload 16
    //   796: ldc_w 261
    //   799: invokevirtual 198	java/lang/StringBuilder:append	(Ljava/lang/String;)Ljava/lang/StringBuilder;
    //   802: pop
    //   803: aload 16
    //   805: aload 17
    //   807: invokevirtual 198	java/lang/StringBuilder:append	(Ljava/lang/String;)Ljava/lang/StringBuilder;
    //   810: pop
    //   811: aload 16
    //   813: ldc_w 263
    //   816: invokevirtual 198	java/lang/StringBuilder:append	(Ljava/lang/String;)Ljava/lang/StringBuilder;
    //   819: pop
    //   820: aload 16
    //   822: aload_1
    //   823: invokevirtual 198	java/lang/StringBuilder:append	(Ljava/lang/String;)Ljava/lang/StringBuilder;
    //   826: pop
    //   827: aload 16
    //   829: invokevirtual 201	java/lang/StringBuilder:toString	()Ljava/lang/String;
    //   832: invokestatic 60	com/google/android/gms/internal/ads/zzbzt:zzj	(Ljava/lang/String;)V
    //   835: new 191	java/lang/StringBuilder
    //   838: astore 16
    //   840: aload 16
    //   842: invokespecial 192	java/lang/StringBuilder:<init>	()V
    //   845: aload 16
    //   847: ldc_w 265
    //   850: invokevirtual 198	java/lang/StringBuilder:append	(Ljava/lang/String;)Ljava/lang/StringBuilder;
    //   853: pop
    //   854: aload 16
    //   856: aload 17
    //   858: invokevirtual 198	java/lang/StringBuilder:append	(Ljava/lang/String;)Ljava/lang/StringBuilder;
    //   861: pop
    //   862: aload 16
    //   864: invokevirtual 201	java/lang/StringBuilder:toString	()Ljava/lang/String;
    //   867: astore 16
    //   869: aload_0
    //   870: aload_1
    //   871: aload 27
    //   873: invokevirtual 82	java/io/File:getAbsolutePath	()Ljava/lang/String;
    //   876: ldc_w 267
    //   879: aload 16
    //   881: invokevirtual 169	com/google/android/gms/internal/ads/zzcdn:zzg	(Ljava/lang/String;Ljava/lang/String;Ljava/lang/String;Ljava/lang/String;)V
    //   884: aload 15
    //   886: aload 14
    //   888: invokeinterface 252 2 0
    //   893: pop
    //   894: iconst_0
    //   895: ireturn
    //   896: new 191	java/lang/StringBuilder
    //   899: astore 15
    //   901: aload 15
    //   903: invokespecial 192	java/lang/StringBuilder:<init>	()V
    //   906: aload 15
    //   908: ldc_w 269
    //   911: invokevirtual 198	java/lang/StringBuilder:append	(Ljava/lang/String;)Ljava/lang/StringBuilder;
    //   914: pop
    //   915: aload 15
    //   917: aload 17
    //   919: invokevirtual 198	java/lang/StringBuilder:append	(Ljava/lang/String;)Ljava/lang/StringBuilder;
    //   922: pop
    //   923: aload 15
    //   925: ldc_w 271
    //   928: invokevirtual 198	java/lang/StringBuilder:append	(Ljava/lang/String;)Ljava/lang/StringBuilder;
    //   931: pop
    //   932: aload 15
    //   934: aload_1
    //   935: invokevirtual 198	java/lang/StringBuilder:append	(Ljava/lang/String;)Ljava/lang/StringBuilder;
    //   938: pop
    //   939: aload 15
    //   941: invokevirtual 201	java/lang/StringBuilder:toString	()Ljava/lang/String;
    //   944: invokestatic 180	com/google/android/gms/internal/ads/zzbzt:zze	(Ljava/lang/String;)V
    //   947: aload 19
    //   949: invokevirtual 275	java/net/URLConnection:getInputStream	()Ljava/io/InputStream;
    //   952: invokestatic 281	java/nio/channels/Channels:newChannel	(Ljava/io/InputStream;)Ljava/nio/channels/ReadableByteChannel;
    //   955: astore 24
    //   957: new 283	java/io/FileOutputStream
    //   960: dup
    //   961: aload 27
    //   963: invokespecial 286	java/io/FileOutputStream:<init>	(Ljava/io/File;)V
    //   966: astore 15
    //   968: aload 15
    //   970: astore 20
    //   972: aload 14
    //   974: astore 18
    //   976: aload 16
    //   978: astore 17
    //   980: aload 15
    //   982: astore 19
    //   984: aload 14
    //   986: astore 21
    //   988: aload 16
    //   990: astore 22
    //   992: aload 15
    //   994: invokevirtual 290	java/io/FileOutputStream:getChannel	()Ljava/nio/channels/FileChannel;
    //   997: astore 23
    //   999: aload 15
    //   1001: astore 20
    //   1003: aload 14
    //   1005: astore 18
    //   1007: aload 16
    //   1009: astore 17
    //   1011: aload 15
    //   1013: astore 19
    //   1015: aload 14
    //   1017: astore 21
    //   1019: aload 16
    //   1021: astore 22
    //   1023: ldc_w 291
    //   1026: invokestatic 297	java/nio/ByteBuffer:allocate	(I)Ljava/nio/ByteBuffer;
    //   1029: astore 25
    //   1031: aload 15
    //   1033: astore 20
    //   1035: aload 14
    //   1037: astore 18
    //   1039: aload 16
    //   1041: astore 17
    //   1043: aload 15
    //   1045: astore 19
    //   1047: aload 14
    //   1049: astore 21
    //   1051: aload 16
    //   1053: astore 22
    //   1055: invokestatic 303	com/google/android/gms/ads/internal/zzt:zzB	()Lcom/google/android/gms/common/util/Clock;
    //   1058: astore 29
    //   1060: aload 15
    //   1062: astore 20
    //   1064: aload 14
    //   1066: astore 18
    //   1068: aload 16
    //   1070: astore 17
    //   1072: aload 15
    //   1074: astore 19
    //   1076: aload 14
    //   1078: astore 21
    //   1080: aload 16
    //   1082: astore 22
    //   1084: aload 29
    //   1086: invokeinterface 308 1 0
    //   1091: lstore 8
    //   1093: aload 15
    //   1095: astore 20
    //   1097: aload 14
    //   1099: astore 18
    //   1101: aload 16
    //   1103: astore 17
    //   1105: aload 15
    //   1107: astore 19
    //   1109: aload 14
    //   1111: astore 21
    //   1113: aload 16
    //   1115: astore 22
    //   1117: getstatic 311	com/google/android/gms/internal/ads/zzbbk:zzy	Lcom/google/android/gms/internal/ads/zzbbc;
    //   1120: astore 26
    //   1122: aload 15
    //   1124: astore 20
    //   1126: aload 14
    //   1128: astore 18
    //   1130: aload 16
    //   1132: astore 17
    //   1134: aload 15
    //   1136: astore 19
    //   1138: aload 14
    //   1140: astore 21
    //   1142: aload 16
    //   1144: astore 22
    //   1146: invokestatic 136	com/google/android/gms/ads/internal/client/zzba:zzc	()Lcom/google/android/gms/internal/ads/zzbbi;
    //   1149: aload 26
    //   1151: invokevirtual 142	com/google/android/gms/internal/ads/zzbbi:zzb	(Lcom/google/android/gms/internal/ads/zzbbc;)Ljava/lang/Object;
    //   1154: checkcast 313	java/lang/Long
    //   1157: invokevirtual 316	java/lang/Long:longValue	()J
    //   1160: lstore 10
    //   1162: aload 15
    //   1164: astore 20
    //   1166: aload 14
    //   1168: astore 18
    //   1170: aload 16
    //   1172: astore 17
    //   1174: aload 15
    //   1176: astore 19
    //   1178: aload 14
    //   1180: astore 21
    //   1182: aload 16
    //   1184: astore 22
    //   1186: new 318	com/google/android/gms/ads/internal/util/zzbz
    //   1189: astore 26
    //   1191: aload 15
    //   1193: astore 20
    //   1195: aload 14
    //   1197: astore 18
    //   1199: aload 16
    //   1201: astore 17
    //   1203: aload 15
    //   1205: astore 19
    //   1207: aload 14
    //   1209: astore 21
    //   1211: aload 16
    //   1213: astore 22
    //   1215: aload 26
    //   1217: lload 10
    //   1219: invokespecial 321	com/google/android/gms/ads/internal/util/zzbz:<init>	(J)V
    //   1222: aload 15
    //   1224: astore 20
    //   1226: aload 14
    //   1228: astore 18
    //   1230: aload 16
    //   1232: astore 17
    //   1234: aload 15
    //   1236: astore 19
    //   1238: aload 14
    //   1240: astore 21
    //   1242: aload 16
    //   1244: astore 22
    //   1246: getstatic 324	com/google/android/gms/internal/ads/zzbbk:zzx	Lcom/google/android/gms/internal/ads/zzbbc;
    //   1249: astore 30
    //   1251: aload 15
    //   1253: astore 20
    //   1255: aload 14
    //   1257: astore 18
    //   1259: aload 16
    //   1261: astore 17
    //   1263: aload 15
    //   1265: astore 19
    //   1267: aload 14
    //   1269: astore 21
    //   1271: aload 16
    //   1273: astore 22
    //   1275: invokestatic 136	com/google/android/gms/ads/internal/client/zzba:zzc	()Lcom/google/android/gms/internal/ads/zzbbi;
    //   1278: aload 30
    //   1280: invokevirtual 142	com/google/android/gms/internal/ads/zzbbi:zzb	(Lcom/google/android/gms/internal/ads/zzbbc;)Ljava/lang/Object;
    //   1283: checkcast 313	java/lang/Long
    //   1286: invokevirtual 316	java/lang/Long:longValue	()J
    //   1289: lstore 10
    //   1291: iconst_0
    //   1292: istore 4
    //   1294: aload 15
    //   1296: astore 20
    //   1298: aload 14
    //   1300: astore 18
    //   1302: aload 16
    //   1304: astore 17
    //   1306: aload 15
    //   1308: astore 19
    //   1310: aload 14
    //   1312: astore 21
    //   1314: aload 16
    //   1316: astore 22
    //   1318: aload 24
    //   1320: aload 25
    //   1322: invokeinterface 330 2 0
    //   1327: istore 5
    //   1329: iload 5
    //   1331: iflt +615 -> 1946
    //   1334: iload 4
    //   1336: iload 5
    //   1338: iadd
    //   1339: istore 4
    //   1341: iload 4
    //   1343: iload_3
    //   1344: if_icmpgt +360 -> 1704
    //   1347: aload 25
    //   1349: invokevirtual 334	java/nio/ByteBuffer:flip	()Ljava/nio/Buffer;
    //   1352: pop
    //   1353: aload 23
    //   1355: aload 25
    //   1357: invokevirtual 339	java/nio/channels/FileChannel:write	(Ljava/nio/ByteBuffer;)I
    //   1360: ifgt -7 -> 1353
    //   1363: aload 25
    //   1365: invokevirtual 342	java/nio/ByteBuffer:clear	()Ljava/nio/Buffer;
    //   1368: pop
    //   1369: aload 29
    //   1371: invokeinterface 308 1 0
    //   1376: lload 8
    //   1378: lsub
    //   1379: ldc2_w 343
    //   1382: lload 10
    //   1384: lmul
    //   1385: lcmp
    //   1386: ifgt +117 -> 1503
    //   1389: aload_0
    //   1390: getfield 109	com/google/android/gms/internal/ads/zzcdq:zzh	Z
    //   1393: ifne +65 -> 1458
    //   1396: aload 26
    //   1398: invokevirtual 346	com/google/android/gms/ads/internal/util/zzbz:zzb	()Z
    //   1401: ifeq +54 -> 1455
    //   1404: aload 27
    //   1406: invokevirtual 82	java/io/File:getAbsolutePath	()Ljava/lang/String;
    //   1409: astore 19
    //   1411: getstatic 349	com/google/android/gms/internal/ads/zzbzm:zza	Landroid/os/Handler;
    //   1414: astore 17
    //   1416: new 351	com/google/android/gms/internal/ads/zzcdh
    //   1419: astore 18
    //   1421: aload 18
    //   1423: aload_0
    //   1424: aload_1
    //   1425: aload 19
    //   1427: iload 4
    //   1429: iload_2
    //   1430: iconst_0
    //   1431: invokespecial 354	com/google/android/gms/internal/ads/zzcdh:<init>	(Lcom/google/android/gms/internal/ads/zzcdn;Ljava/lang/String;Ljava/lang/String;IIZ)V
    //   1434: aload 17
    //   1436: aload 18
    //   1438: invokevirtual 360	android/os/Handler:post	(Ljava/lang/Runnable;)Z
    //   1441: pop
    //   1442: goto +13 -> 1455
    //   1445: astore 17
    //   1447: goto +5 -> 1452
    //   1450: astore 17
    //   1452: goto +233 -> 1685
    //   1455: goto -161 -> 1294
    //   1458: ldc_w 362
    //   1461: astore 18
    //   1463: aload 18
    //   1465: astore 16
    //   1467: aload 18
    //   1469: astore 17
    //   1471: new 113	java/io/IOException
    //   1474: astore 19
    //   1476: aload 18
    //   1478: astore 16
    //   1480: aload 18
    //   1482: astore 17
    //   1484: aload 19
    //   1486: ldc_w 364
    //   1489: invokespecial 240	java/io/IOException:<init>	(Ljava/lang/String;)V
    //   1492: aload 18
    //   1494: astore 16
    //   1496: aload 18
    //   1498: astore 17
    //   1500: aload 19
    //   1502: athrow
    //   1503: ldc_w 366
    //   1506: astore 18
    //   1508: aload 18
    //   1510: astore 16
    //   1512: aload 18
    //   1514: astore 17
    //   1516: lload 10
    //   1518: invokestatic 368	java/lang/Long:toString	(J)Ljava/lang/String;
    //   1521: astore 19
    //   1523: aload 18
    //   1525: astore 16
    //   1527: aload 18
    //   1529: astore 17
    //   1531: new 191	java/lang/StringBuilder
    //   1534: astore 20
    //   1536: aload 18
    //   1538: astore 16
    //   1540: aload 18
    //   1542: astore 17
    //   1544: aload 20
    //   1546: invokespecial 192	java/lang/StringBuilder:<init>	()V
    //   1549: aload 18
    //   1551: astore 16
    //   1553: aload 18
    //   1555: astore 17
    //   1557: aload 20
    //   1559: ldc_w 370
    //   1562: invokevirtual 198	java/lang/StringBuilder:append	(Ljava/lang/String;)Ljava/lang/StringBuilder;
    //   1565: pop
    //   1566: aload 18
    //   1568: astore 16
    //   1570: aload 18
    //   1572: astore 17
    //   1574: aload 20
    //   1576: aload 19
    //   1578: invokevirtual 198	java/lang/StringBuilder:append	(Ljava/lang/String;)Ljava/lang/StringBuilder;
    //   1581: pop
    //   1582: aload 18
    //   1584: astore 16
    //   1586: aload 18
    //   1588: astore 17
    //   1590: aload 20
    //   1592: ldc_w 372
    //   1595: invokevirtual 198	java/lang/StringBuilder:append	(Ljava/lang/String;)Ljava/lang/StringBuilder;
    //   1598: pop
    //   1599: aload 18
    //   1601: astore 16
    //   1603: aload 18
    //   1605: astore 17
    //   1607: aload 20
    //   1609: invokevirtual 201	java/lang/StringBuilder:toString	()Ljava/lang/String;
    //   1612: astore 21
    //   1614: aload 21
    //   1616: astore 17
    //   1618: aload 18
    //   1620: astore 16
    //   1622: aload 21
    //   1624: astore 19
    //   1626: aload 18
    //   1628: astore 20
    //   1630: new 113	java/io/IOException
    //   1633: astore 22
    //   1635: aload 21
    //   1637: astore 17
    //   1639: aload 18
    //   1641: astore 16
    //   1643: aload 21
    //   1645: astore 19
    //   1647: aload 18
    //   1649: astore 20
    //   1651: aload 22
    //   1653: ldc_w 374
    //   1656: invokespecial 240	java/io/IOException:<init>	(Ljava/lang/String;)V
    //   1659: aload 21
    //   1661: astore 17
    //   1663: aload 18
    //   1665: astore 16
    //   1667: aload 21
    //   1669: astore 19
    //   1671: aload 18
    //   1673: astore 20
    //   1675: aload 22
    //   1677: athrow
    //   1678: astore 17
    //   1680: goto +5 -> 1685
    //   1683: astore 17
    //   1685: aload 15
    //   1687: astore 18
    //   1689: aload 14
    //   1691: astore 15
    //   1693: aload 17
    //   1695: astore 14
    //   1697: aload 18
    //   1699: astore 17
    //   1701: goto +469 -> 2170
    //   1704: ldc_w 267
    //   1707: astore 18
    //   1709: aload 18
    //   1711: astore 16
    //   1713: aload 18
    //   1715: astore 17
    //   1717: iload 4
    //   1719: invokestatic 230	java/lang/Integer:toString	(I)Ljava/lang/String;
    //   1722: astore 19
    //   1724: aload 18
    //   1726: astore 16
    //   1728: aload 18
    //   1730: astore 17
    //   1732: new 191	java/lang/StringBuilder
    //   1735: astore 20
    //   1737: aload 18
    //   1739: astore 16
    //   1741: aload 18
    //   1743: astore 17
    //   1745: aload 20
    //   1747: invokespecial 192	java/lang/StringBuilder:<init>	()V
    //   1750: aload 18
    //   1752: astore 16
    //   1754: aload 18
    //   1756: astore 17
    //   1758: aload 20
    //   1760: ldc_w 265
    //   1763: invokevirtual 198	java/lang/StringBuilder:append	(Ljava/lang/String;)Ljava/lang/StringBuilder;
    //   1766: pop
    //   1767: aload 18
    //   1769: astore 16
    //   1771: aload 18
    //   1773: astore 17
    //   1775: aload 20
    //   1777: aload 19
    //   1779: invokevirtual 198	java/lang/StringBuilder:append	(Ljava/lang/String;)Ljava/lang/StringBuilder;
    //   1782: pop
    //   1783: aload 18
    //   1785: astore 16
    //   1787: aload 18
    //   1789: astore 17
    //   1791: aload 20
    //   1793: invokevirtual 201	java/lang/StringBuilder:toString	()Ljava/lang/String;
    //   1796: astore 21
    //   1798: aload 21
    //   1800: astore 17
    //   1802: aload 18
    //   1804: astore 16
    //   1806: aload 21
    //   1808: astore 19
    //   1810: aload 18
    //   1812: astore 20
    //   1814: new 113	java/io/IOException
    //   1817: astore 22
    //   1819: aload 21
    //   1821: astore 17
    //   1823: aload 18
    //   1825: astore 16
    //   1827: aload 21
    //   1829: astore 19
    //   1831: aload 18
    //   1833: astore 20
    //   1835: aload 22
    //   1837: ldc_w 376
    //   1840: invokespecial 240	java/io/IOException:<init>	(Ljava/lang/String;)V
    //   1843: aload 21
    //   1845: astore 17
    //   1847: aload 18
    //   1849: astore 16
    //   1851: aload 21
    //   1853: astore 19
    //   1855: aload 18
    //   1857: astore 20
    //   1859: aload 22
    //   1861: athrow
    //   1862: astore 18
    //   1864: aload 17
    //   1866: astore 19
    //   1868: aload 16
    //   1870: astore 17
    //   1872: goto +9 -> 1881
    //   1875: astore 18
    //   1877: aload 20
    //   1879: astore 17
    //   1881: aload 19
    //   1883: astore 16
    //   1885: aload 14
    //   1887: astore 20
    //   1889: aload 15
    //   1891: astore 19
    //   1893: aload 18
    //   1895: astore 14
    //   1897: aload 20
    //   1899: astore 15
    //   1901: aload 19
    //   1903: astore 18
    //   1905: goto +312 -> 2217
    //   1908: astore 17
    //   1910: goto +13 -> 1923
    //   1913: astore 18
    //   1915: aload 17
    //   1917: astore 16
    //   1919: aload 18
    //   1921: astore 17
    //   1923: aload 15
    //   1925: astore 18
    //   1927: aload 14
    //   1929: astore 15
    //   1931: aload 17
    //   1933: astore 14
    //   1935: aload 16
    //   1937: astore 17
    //   1939: aload 18
    //   1941: astore 16
    //   1943: goto +239 -> 2182
    //   1946: aload 15
    //   1948: astore 17
    //   1950: aload 16
    //   1952: astore 18
    //   1954: aload 17
    //   1956: invokevirtual 379	java/io/FileOutputStream:close	()V
    //   1959: iconst_3
    //   1960: invokestatic 385	com/google/android/gms/ads/internal/util/zze:zzm	(I)Z
    //   1963: ifeq +65 -> 2028
    //   1966: getstatic 39	com/google/android/gms/internal/ads/zzcdq:zzf	Ljava/text/DecimalFormat;
    //   1969: iload 4
    //   1971: i2l
    //   1972: invokevirtual 256	java/text/DecimalFormat:format	(J)Ljava/lang/String;
    //   1975: astore 20
    //   1977: new 191	java/lang/StringBuilder
    //   1980: astore 19
    //   1982: aload 19
    //   1984: invokespecial 192	java/lang/StringBuilder:<init>	()V
    //   1987: aload 19
    //   1989: ldc_w 387
    //   1992: invokevirtual 198	java/lang/StringBuilder:append	(Ljava/lang/String;)Ljava/lang/StringBuilder;
    //   1995: pop
    //   1996: aload 19
    //   1998: aload 20
    //   2000: invokevirtual 198	java/lang/StringBuilder:append	(Ljava/lang/String;)Ljava/lang/StringBuilder;
    //   2003: pop
    //   2004: aload 19
    //   2006: ldc_w 271
    //   2009: invokevirtual 198	java/lang/StringBuilder:append	(Ljava/lang/String;)Ljava/lang/StringBuilder;
    //   2012: pop
    //   2013: aload 19
    //   2015: aload_1
    //   2016: invokevirtual 198	java/lang/StringBuilder:append	(Ljava/lang/String;)Ljava/lang/StringBuilder;
    //   2019: pop
    //   2020: aload 19
    //   2022: invokevirtual 201	java/lang/StringBuilder:toString	()Ljava/lang/String;
    //   2025: invokestatic 180	com/google/android/gms/internal/ads/zzbzt:zze	(Ljava/lang/String;)V
    //   2028: aload 27
    //   2030: iconst_1
    //   2031: iconst_0
    //   2032: invokevirtual 96	java/io/File:setReadable	(ZZ)Z
    //   2035: pop
    //   2036: aload 28
    //   2038: invokevirtual 162	java/io/File:isFile	()Z
    //   2041: ifeq +15 -> 2056
    //   2044: aload 28
    //   2046: invokestatic 390	java/lang/System:currentTimeMillis	()J
    //   2049: invokevirtual 394	java/io/File:setLastModified	(J)Z
    //   2052: pop
    //   2053: goto +9 -> 2062
    //   2056: aload 28
    //   2058: invokevirtual 397	java/io/File:createNewFile	()Z
    //   2061: pop
    //   2062: aload_0
    //   2063: aload_1
    //   2064: aload 27
    //   2066: invokevirtual 82	java/io/File:getAbsolutePath	()Ljava/lang/String;
    //   2069: iload 4
    //   2071: invokevirtual 183	com/google/android/gms/internal/ads/zzcdn:zzh	(Ljava/lang/String;Ljava/lang/String;I)V
    //   2074: getstatic 30	com/google/android/gms/internal/ads/zzcdq:zze	Ljava/util/Set;
    //   2077: astore 19
    //   2079: aload 14
    //   2081: astore 15
    //   2083: aload 19
    //   2085: aload 15
    //   2087: invokeinterface 252 2 0
    //   2092: pop
    //   2093: iconst_1
    //   2094: ireturn
    //   2095: astore 14
    //   2097: aload 18
    //   2099: astore 16
    //   2101: goto +69 -> 2170
    //   2104: astore 14
    //   2106: aload 18
    //   2108: astore 16
    //   2110: goto +60 -> 2170
    //   2113: astore 17
    //   2115: goto +5 -> 2120
    //   2118: astore 17
    //   2120: aload 15
    //   2122: astore 18
    //   2124: aload 14
    //   2126: astore 15
    //   2128: aload 17
    //   2130: astore 14
    //   2132: aload 18
    //   2134: astore 17
    //   2136: goto +34 -> 2170
    //   2139: astore 14
    //   2141: aload 20
    //   2143: astore 19
    //   2145: goto +13 -> 2158
    //   2148: astore 14
    //   2150: aload 22
    //   2152: astore 17
    //   2154: aload 21
    //   2156: astore 18
    //   2158: aload 18
    //   2160: astore 15
    //   2162: aload 17
    //   2164: astore 16
    //   2166: aload 19
    //   2168: astore 17
    //   2170: aload 16
    //   2172: astore 18
    //   2174: aload 17
    //   2176: astore 16
    //   2178: aload 18
    //   2180: astore 17
    //   2182: aload 16
    //   2184: astore 18
    //   2186: aconst_null
    //   2187: astore 16
    //   2189: goto +28 -> 2217
    //   2192: astore 19
    //   2194: goto +5 -> 2199
    //   2197: astore 19
    //   2199: ldc -48
    //   2201: astore 17
    //   2203: aconst_null
    //   2204: astore 16
    //   2206: aconst_null
    //   2207: astore 18
    //   2209: aload 14
    //   2211: astore 15
    //   2213: aload 19
    //   2215: astore 14
    //   2217: aload 14
    //   2219: instanceof 115
    //   2222: ifeq +14 -> 2236
    //   2225: invokestatic 401	com/google/android/gms/ads/internal/zzt:zzo	()Lcom/google/android/gms/internal/ads/zzbzc;
    //   2228: aload 14
    //   2230: ldc_w 403
    //   2233: invokevirtual 408	com/google/android/gms/internal/ads/zzbzc:zzu	(Ljava/lang/Throwable;Ljava/lang/String;)V
    //   2236: aload 18
    //   2238: invokevirtual 379	java/io/FileOutputStream:close	()V
    //   2241: goto +5 -> 2246
    //   2244: astore 18
    //   2246: aload_0
    //   2247: getfield 109	com/google/android/gms/internal/ads/zzcdq:zzh	Z
    //   2250: ifeq +48 -> 2298
    //   2253: new 191	java/lang/StringBuilder
    //   2256: dup
    //   2257: invokespecial 192	java/lang/StringBuilder:<init>	()V
    //   2260: astore 14
    //   2262: aload 14
    //   2264: ldc_w 410
    //   2267: invokevirtual 198	java/lang/StringBuilder:append	(Ljava/lang/String;)Ljava/lang/StringBuilder;
    //   2270: pop
    //   2271: aload 14
    //   2273: aload_1
    //   2274: invokevirtual 198	java/lang/StringBuilder:append	(Ljava/lang/String;)Ljava/lang/StringBuilder;
    //   2277: pop
    //   2278: aload 14
    //   2280: ldc_w 412
    //   2283: invokevirtual 198	java/lang/StringBuilder:append	(Ljava/lang/String;)Ljava/lang/StringBuilder;
    //   2286: pop
    //   2287: aload 14
    //   2289: invokevirtual 201	java/lang/StringBuilder:toString	()Ljava/lang/String;
    //   2292: invokestatic 415	com/google/android/gms/internal/ads/zzbzt:zzi	(Ljava/lang/String;)V
    //   2295: goto +47 -> 2342
    //   2298: new 191	java/lang/StringBuilder
    //   2301: dup
    //   2302: invokespecial 192	java/lang/StringBuilder:<init>	()V
    //   2305: astore 18
    //   2307: aload 18
    //   2309: ldc_w 417
    //   2312: invokevirtual 198	java/lang/StringBuilder:append	(Ljava/lang/String;)Ljava/lang/StringBuilder;
    //   2315: pop
    //   2316: aload 18
    //   2318: aload_1
    //   2319: invokevirtual 198	java/lang/StringBuilder:append	(Ljava/lang/String;)Ljava/lang/StringBuilder;
    //   2322: pop
    //   2323: aload 18
    //   2325: ldc_w 412
    //   2328: invokevirtual 198	java/lang/StringBuilder:append	(Ljava/lang/String;)Ljava/lang/StringBuilder;
    //   2331: pop
    //   2332: aload 18
    //   2334: invokevirtual 201	java/lang/StringBuilder:toString	()Ljava/lang/String;
    //   2337: aload 14
    //   2339: invokestatic 421	com/google/android/gms/internal/ads/zzbzt:zzk	(Ljava/lang/String;Ljava/lang/Throwable;)V
    //   2342: aload 27
    //   2344: invokevirtual 424	java/io/File:exists	()Z
    //   2347: ifeq +28 -> 2375
    //   2350: aload 27
    //   2352: invokevirtual 157	java/io/File:delete	()Z
    //   2355: ifne +20 -> 2375
    //   2358: ldc_w 426
    //   2361: aload 27
    //   2363: invokevirtual 82	java/io/File:getAbsolutePath	()Ljava/lang/String;
    //   2366: invokestatic 88	java/lang/String:valueOf	(Ljava/lang/Object;)Ljava/lang/String;
    //   2369: invokevirtual 92	java/lang/String:concat	(Ljava/lang/String;)Ljava/lang/String;
    //   2372: invokestatic 60	com/google/android/gms/internal/ads/zzbzt:zzj	(Ljava/lang/String;)V
    //   2375: aload_0
    //   2376: aload_1
    //   2377: aload 27
    //   2379: invokevirtual 82	java/io/File:getAbsolutePath	()Ljava/lang/String;
    //   2382: aload 17
    //   2384: aload 16
    //   2386: invokevirtual 169	com/google/android/gms/internal/ads/zzcdn:zzg	(Ljava/lang/String;Ljava/lang/String;Ljava/lang/String;Ljava/lang/String;)V
    //   2389: getstatic 30	com/google/android/gms/internal/ads/zzcdq:zze	Ljava/util/Set;
    //   2392: aload 15
    //   2394: invokeinterface 252 2 0
    //   2399: pop
    //   2400: iconst_0
    //   2401: ireturn
    //   2402: astore_1
    //   2403: aload 15
    //   2405: monitorexit
    //   2406: aload_1
    //   2407: athrow
    //   2408: aload_0
    //   2409: aload_1
    //   2410: aconst_null
    //   2411: ldc_w 428
    //   2414: aconst_null
    //   2415: invokevirtual 169	com/google/android/gms/internal/ads/zzcdn:zzg	(Ljava/lang/String;Ljava/lang/String;Ljava/lang/String;Ljava/lang/String;)V
    //   2418: goto -18 -> 2400
    //   2421: astore 19
    //   2423: goto -361 -> 2062
    // Local variable table:
    //   start	length	slot	name	signature
    //   0	2426	0	this	zzcdq
    //   0	2426	1	paramString	String
    //   46	1384	2	i	int
    //   44	1301	3	j	int
    //   26	2044	4	k	int
    //   41	1298	5	m	int
    //   246	27	6	bool1	boolean
    //   234	30	7	bool2	boolean
    //   160	1217	8	l1	long
    //   140	1377	10	l2	long
    //   184	23	12	l3	long
    //   4	2076	14	localObject1	Object
    //   2095	1	14	localRuntimeException1	RuntimeException
    //   2104	21	14	localIOException1	java.io.IOException
    //   2130	1	14	localObject2	Object
    //   2139	1	14	localRuntimeException2	RuntimeException
    //   2148	62	14	localIOException2	java.io.IOException
    //   2215	123	14	localObject3	Object
    //   164	476	15	localObject4	Object
    //   642	1	15	localRuntimeException3	RuntimeException
    //   647	1	15	localIOException3	java.io.IOException
    //   652	1	15	localRuntimeException4	RuntimeException
    //   657	10	15	localIOException4	java.io.IOException
    //   672	1732	15	localObject5	Object
    //   156	2229	16	localObject6	Object
    //   131	1304	17	localObject7	Object
    //   1445	1	17	localRuntimeException5	RuntimeException
    //   1450	1	17	localIOException5	java.io.IOException
    //   1469	193	17	localObject8	Object
    //   1678	1	17	localRuntimeException6	RuntimeException
    //   1683	11	17	localIOException6	java.io.IOException
    //   1699	181	17	localObject9	Object
    //   1908	8	17	localRuntimeException7	RuntimeException
    //   1921	34	17	localObject10	Object
    //   2113	1	17	localRuntimeException8	RuntimeException
    //   2118	11	17	localIOException7	java.io.IOException
    //   2134	249	17	localObject11	Object
    //   7	1849	18	localObject12	Object
    //   1862	1	18	localRuntimeException9	RuntimeException
    //   1875	19	18	localIOException8	java.io.IOException
    //   1903	1	18	localObject13	Object
    //   1913	7	18	localIOException9	java.io.IOException
    //   1925	312	18	localObject14	Object
    //   2244	1	18	localIOException10	java.io.IOException
    //   2305	28	18	localStringBuilder	StringBuilder
    //   491	1676	19	localObject15	Object
    //   2192	1	19	localRuntimeException10	RuntimeException
    //   2197	17	19	localIOException11	java.io.IOException
    //   2421	1	19	localIOException12	java.io.IOException
    //   970	1172	20	localObject16	Object
    //   986	1169	21	localObject17	Object
    //   990	1161	22	localObject18	Object
    //   997	357	23	localFileChannel	java.nio.channels.FileChannel
    //   955	364	24	localReadableByteChannel	java.nio.channels.ReadableByteChannel
    //   1029	335	25	localByteBuffer	java.nio.ByteBuffer
    //   1120	277	26	localObject19	Object
    //   312	2066	27	localFile1	File
    //   320	1737	28	localFile2	File
    //   1058	312	29	localClock	com.google.android.gms.common.util.Clock
    //   1249	30	30	localzzbbc	zzbbc
    // Exception table:
    //   from	to	target	type
    //   584	642	642	java/lang/RuntimeException
    //   584	642	647	java/io/IOException
    //   545	584	652	java/lang/RuntimeException
    //   545	584	657	java/io/IOException
    //   1416	1421	1445	java/lang/RuntimeException
    //   1416	1421	1450	java/io/IOException
    //   1347	1353	1678	java/lang/RuntimeException
    //   1353	1416	1678	java/lang/RuntimeException
    //   1347	1353	1683	java/io/IOException
    //   1353	1416	1683	java/io/IOException
    //   1630	1635	1862	java/lang/RuntimeException
    //   1651	1659	1862	java/lang/RuntimeException
    //   1675	1678	1862	java/lang/RuntimeException
    //   1814	1819	1862	java/lang/RuntimeException
    //   1835	1843	1862	java/lang/RuntimeException
    //   1859	1862	1862	java/lang/RuntimeException
    //   1630	1635	1875	java/io/IOException
    //   1651	1659	1875	java/io/IOException
    //   1675	1678	1875	java/io/IOException
    //   1814	1819	1875	java/io/IOException
    //   1835	1843	1875	java/io/IOException
    //   1859	1862	1875	java/io/IOException
    //   1471	1476	1908	java/lang/RuntimeException
    //   1484	1492	1908	java/lang/RuntimeException
    //   1500	1503	1908	java/lang/RuntimeException
    //   1516	1523	1908	java/lang/RuntimeException
    //   1531	1536	1908	java/lang/RuntimeException
    //   1544	1549	1908	java/lang/RuntimeException
    //   1557	1566	1908	java/lang/RuntimeException
    //   1574	1582	1908	java/lang/RuntimeException
    //   1590	1599	1908	java/lang/RuntimeException
    //   1607	1614	1908	java/lang/RuntimeException
    //   1717	1724	1908	java/lang/RuntimeException
    //   1732	1737	1908	java/lang/RuntimeException
    //   1745	1750	1908	java/lang/RuntimeException
    //   1758	1767	1908	java/lang/RuntimeException
    //   1775	1783	1908	java/lang/RuntimeException
    //   1791	1798	1908	java/lang/RuntimeException
    //   1471	1476	1913	java/io/IOException
    //   1484	1492	1913	java/io/IOException
    //   1500	1503	1913	java/io/IOException
    //   1516	1523	1913	java/io/IOException
    //   1531	1536	1913	java/io/IOException
    //   1544	1549	1913	java/io/IOException
    //   1557	1566	1913	java/io/IOException
    //   1574	1582	1913	java/io/IOException
    //   1590	1599	1913	java/io/IOException
    //   1607	1614	1913	java/io/IOException
    //   1717	1724	1913	java/io/IOException
    //   1732	1737	1913	java/io/IOException
    //   1745	1750	1913	java/io/IOException
    //   1758	1767	1913	java/io/IOException
    //   1775	1783	1913	java/io/IOException
    //   1791	1798	1913	java/io/IOException
    //   2083	2093	2095	java/lang/RuntimeException
    //   2083	2093	2104	java/io/IOException
    //   1421	1442	2113	java/lang/RuntimeException
    //   1954	2028	2113	java/lang/RuntimeException
    //   2028	2053	2113	java/lang/RuntimeException
    //   2056	2062	2113	java/lang/RuntimeException
    //   2062	2079	2113	java/lang/RuntimeException
    //   1421	1442	2118	java/io/IOException
    //   1954	2028	2118	java/io/IOException
    //   2028	2053	2118	java/io/IOException
    //   2062	2079	2118	java/io/IOException
    //   992	999	2139	java/lang/RuntimeException
    //   1023	1031	2139	java/lang/RuntimeException
    //   1055	1060	2139	java/lang/RuntimeException
    //   1084	1093	2139	java/lang/RuntimeException
    //   1117	1122	2139	java/lang/RuntimeException
    //   1146	1162	2139	java/lang/RuntimeException
    //   1186	1191	2139	java/lang/RuntimeException
    //   1215	1222	2139	java/lang/RuntimeException
    //   1246	1251	2139	java/lang/RuntimeException
    //   1275	1291	2139	java/lang/RuntimeException
    //   1318	1329	2139	java/lang/RuntimeException
    //   992	999	2148	java/io/IOException
    //   1023	1031	2148	java/io/IOException
    //   1055	1060	2148	java/io/IOException
    //   1084	1093	2148	java/io/IOException
    //   1117	1122	2148	java/io/IOException
    //   1146	1162	2148	java/io/IOException
    //   1186	1191	2148	java/io/IOException
    //   1215	1222	2148	java/io/IOException
    //   1246	1251	2148	java/io/IOException
    //   1275	1291	2148	java/io/IOException
    //   1318	1329	2148	java/io/IOException
    //   488	531	2192	java/lang/RuntimeException
    //   681	687	2192	java/lang/RuntimeException
    //   691	747	2192	java/lang/RuntimeException
    //   749	779	2192	java/lang/RuntimeException
    //   784	894	2192	java/lang/RuntimeException
    //   896	968	2192	java/lang/RuntimeException
    //   488	531	2197	java/io/IOException
    //   681	687	2197	java/io/IOException
    //   691	747	2197	java/io/IOException
    //   749	779	2197	java/io/IOException
    //   784	894	2197	java/io/IOException
    //   896	968	2197	java/io/IOException
    //   2236	2241	2244	java/io/IOException
    //   2236	2241	2244	java/lang/NullPointerException
    //   408	469	2402	finally
    //   471	484	2402	finally
    //   2403	2406	2402	finally
    //   2056	2062	2421	java/io/IOException
  }
}


/* Location:              C:\Users\Ria\Documents\slope apk\dex-tools-v2.4\classes-dex2jar.jar!\com\google\android\gms\internal\ads\zzcdq.class
 * Java compiler version: 6 (50.0)
 * JD-Core Version:       0.7.1
 */