package com.google.android.gms.internal.ads;

import android.net.Uri;
import com.google.android.gms.ads.internal.util.zzs;
import com.google.android.gms.ads.internal.zzt;
import com.google.android.gms.common.util.Clock;
import java.lang.ref.WeakReference;

public final class zzcdw
  extends zzcdn
  implements zzcbs
{
  public static final int zzd = 0;
  private zzcbt zze;
  private String zzf;
  private boolean zzg;
  private boolean zzh;
  private zzcdf zzi;
  private long zzj;
  private long zzk;
  
  public zzcdw(zzccc paramzzccc, zzccb paramzzccb)
  {
    super(paramzzccc);
    paramzzccc = new zzceo(paramzzccc.getContext(), paramzzccb, (zzccc)this.zzc.get(), null);
    zzbzt.zzi("ExoPlayerAdapter initialized.");
    this.zze = paramzzccc;
    paramzzccc.zzL(this);
  }
  
  protected static final String zzc(String paramString)
  {
    return "cache:".concat(String.valueOf(zzbzm.zze(paramString)));
  }
  
  private static String zzd(String paramString, Exception paramException)
  {
    String str = paramException.getClass().getCanonicalName();
    paramException = paramException.getMessage();
    StringBuilder localStringBuilder = new StringBuilder();
    localStringBuilder.append(paramString);
    localStringBuilder.append("/");
    localStringBuilder.append(str);
    localStringBuilder.append(":");
    localStringBuilder.append(paramException);
    return localStringBuilder.toString();
  }
  
  private final void zzx(long paramLong)
  {
    zzs.zza.postDelayed(new zzcdv(this), paramLong);
  }
  
  public final void release()
  {
    zzcbt localzzcbt = this.zze;
    if (localzzcbt != null)
    {
      localzzcbt.zzL(null);
      this.zze.zzH();
    }
  }
  
  public final void zzD(int paramInt1, int paramInt2) {}
  
  public final zzcbt zza()
  {
    try
    {
      this.zzh = true;
      notify();
      this.zze.zzL(null);
      zzcbt localzzcbt = this.zze;
      this.zze = null;
      return localzzcbt;
    }
    finally {}
  }
  
  public final void zzf()
  {
    try
    {
      this.zzg = true;
      notify();
      release();
      String str = this.zzf;
      if (str != null)
      {
        str = zzc(str);
        zzg(this.zzf, str, "externalAbort", "Programmatic precache abort.");
      }
      return;
    }
    finally {}
  }
  
  public final void zzi(boolean paramBoolean, long paramLong)
  {
    zzccc localzzccc = (zzccc)this.zzc.get();
    if (localzzccc != null) {
      zzcag.zze.execute(new zzcdu(localzzccc, paramBoolean, paramLong));
    }
  }
  
  public final void zzk(String paramString, Exception paramException)
  {
    zzbzt.zzk("Precache error", paramException);
    zzt.zzo().zzt(paramException, "VideoStreamExoPlayerCache.onError");
  }
  
  public final void zzl(String paramString, Exception paramException)
  {
    zzbzt.zzk("Precache exception", paramException);
    zzt.zzo().zzt(paramException, "VideoStreamExoPlayerCache.onException");
  }
  
  public final void zzm(int paramInt) {}
  
  public final void zzp(int paramInt)
  {
    this.zze.zzJ(paramInt);
  }
  
  public final void zzq(int paramInt)
  {
    this.zze.zzK(paramInt);
  }
  
  public final void zzr(int paramInt)
  {
    this.zze.zzM(paramInt);
  }
  
  public final void zzs(int paramInt)
  {
    this.zze.zzN(paramInt);
  }
  
  public final boolean zzt(String paramString)
  {
    return zzu(paramString, new String[] { paramString });
  }
  
  /* Error */
  public final boolean zzu(String paramString, String[] paramArrayOfString)
  {
    // Byte code:
    //   0: aload_0
    //   1: astore 25
    //   3: aload_1
    //   4: astore 26
    //   6: aload 25
    //   8: aload 26
    //   10: putfield 147	com/google/android/gms/internal/ads/zzcdw:zzf	Ljava/lang/String;
    //   13: ldc -105
    //   15: astore 32
    //   17: aload_1
    //   18: invokestatic 149	com/google/android/gms/internal/ads/zzcdw:zzc	(Ljava/lang/String;)Ljava/lang/String;
    //   21: astore 30
    //   23: aload 26
    //   25: astore 29
    //   27: aload 30
    //   29: astore 28
    //   31: aload 25
    //   33: astore 27
    //   35: aload_2
    //   36: arraylength
    //   37: anewarray 359	android/net/Uri
    //   40: astore 31
    //   42: iconst_0
    //   43: istore_3
    //   44: aload 26
    //   46: astore 29
    //   48: aload 30
    //   50: astore 28
    //   52: aload 25
    //   54: astore 27
    //   56: iload_3
    //   57: aload_2
    //   58: arraylength
    //   59: if_icmpge +31 -> 90
    //   62: aload 26
    //   64: astore 29
    //   66: aload 30
    //   68: astore 28
    //   70: aload 25
    //   72: astore 27
    //   74: aload 31
    //   76: iload_3
    //   77: aload_2
    //   78: iload_3
    //   79: aaload
    //   80: invokestatic 363	android/net/Uri:parse	(Ljava/lang/String;)Landroid/net/Uri;
    //   83: aastore
    //   84: iinc 3 1
    //   87: goto -43 -> 44
    //   90: aload 26
    //   92: astore 29
    //   94: aload 30
    //   96: astore 28
    //   98: aload 25
    //   100: astore 27
    //   102: aload 25
    //   104: getfield 56	com/google/android/gms/internal/ads/zzcdw:zze	Lcom/google/android/gms/internal/ads/zzcbt;
    //   107: aload 31
    //   109: aload 25
    //   111: getfield 365	com/google/android/gms/internal/ads/zzcdw:zzb	Ljava/lang/String;
    //   114: invokevirtual 369	com/google/android/gms/internal/ads/zzcbt:zzF	([Landroid/net/Uri;Ljava/lang/String;)V
    //   117: aload 26
    //   119: astore 29
    //   121: aload 30
    //   123: astore 28
    //   125: aload 25
    //   127: astore 27
    //   129: aload 25
    //   131: getfield 38	com/google/android/gms/internal/ads/zzcdw:zzc	Ljava/lang/ref/WeakReference;
    //   134: invokevirtual 44	java/lang/ref/WeakReference:get	()Ljava/lang/Object;
    //   137: checkcast 30	com/google/android/gms/internal/ads/zzccc
    //   140: astore_2
    //   141: aload_2
    //   142: ifnull +25 -> 167
    //   145: aload 26
    //   147: astore 29
    //   149: aload 30
    //   151: astore 28
    //   153: aload 25
    //   155: astore 27
    //   157: aload_2
    //   158: aload 30
    //   160: aload 25
    //   162: invokeinterface 372 3 0
    //   167: aload 26
    //   169: astore 29
    //   171: aload 30
    //   173: astore 28
    //   175: aload 25
    //   177: astore 27
    //   179: invokestatic 198	com/google/android/gms/ads/internal/zzt:zzB	()Lcom/google/android/gms/common/util/Clock;
    //   182: astore 34
    //   184: aload 26
    //   186: astore 29
    //   188: aload 30
    //   190: astore 28
    //   192: aload 25
    //   194: astore 27
    //   196: aload 34
    //   198: invokeinterface 203 1 0
    //   203: lstore 21
    //   205: aload 26
    //   207: astore 29
    //   209: aload 30
    //   211: astore 28
    //   213: aload 25
    //   215: astore 27
    //   217: getstatic 245	com/google/android/gms/internal/ads/zzbbk:zzy	Lcom/google/android/gms/internal/ads/zzbbc;
    //   220: astore_2
    //   221: aload 26
    //   223: astore 29
    //   225: aload 30
    //   227: astore 28
    //   229: aload 25
    //   231: astore 27
    //   233: invokestatic 161	com/google/android/gms/ads/internal/client/zzba:zzc	()Lcom/google/android/gms/internal/ads/zzbbi;
    //   236: aload_2
    //   237: invokevirtual 166	com/google/android/gms/internal/ads/zzbbi:zzb	(Lcom/google/android/gms/internal/ads/zzbbc;)Ljava/lang/Object;
    //   240: checkcast 168	java/lang/Long
    //   243: invokevirtual 172	java/lang/Long:longValue	()J
    //   246: lstore 7
    //   248: aload 26
    //   250: astore 29
    //   252: aload 30
    //   254: astore 28
    //   256: aload 25
    //   258: astore 27
    //   260: getstatic 156	com/google/android/gms/internal/ads/zzbbk:zzx	Lcom/google/android/gms/internal/ads/zzbbc;
    //   263: astore_2
    //   264: aload 26
    //   266: astore 29
    //   268: aload 30
    //   270: astore 28
    //   272: aload 25
    //   274: astore 27
    //   276: invokestatic 161	com/google/android/gms/ads/internal/client/zzba:zzc	()Lcom/google/android/gms/internal/ads/zzbbi;
    //   279: aload_2
    //   280: invokevirtual 166	com/google/android/gms/internal/ads/zzbbi:zzb	(Lcom/google/android/gms/internal/ads/zzbbc;)Ljava/lang/Object;
    //   283: checkcast 168	java/lang/Long
    //   286: invokevirtual 172	java/lang/Long:longValue	()J
    //   289: ldc2_w 173
    //   292: lmul
    //   293: lstore 11
    //   295: aload 26
    //   297: astore 29
    //   299: aload 30
    //   301: astore 28
    //   303: aload 25
    //   305: astore 27
    //   307: getstatic 177	com/google/android/gms/internal/ads/zzbbk:zzw	Lcom/google/android/gms/internal/ads/zzbbc;
    //   310: astore_2
    //   311: aload 26
    //   313: astore 29
    //   315: aload 30
    //   317: astore 28
    //   319: aload 25
    //   321: astore 27
    //   323: invokestatic 161	com/google/android/gms/ads/internal/client/zzba:zzc	()Lcom/google/android/gms/internal/ads/zzbbi;
    //   326: aload_2
    //   327: invokevirtual 166	com/google/android/gms/internal/ads/zzbbi:zzb	(Lcom/google/android/gms/internal/ads/zzbbc;)Ljava/lang/Object;
    //   330: checkcast 179	java/lang/Integer
    //   333: invokevirtual 183	java/lang/Integer:intValue	()I
    //   336: i2l
    //   337: lstore 13
    //   339: aload 26
    //   341: astore 29
    //   343: aload 30
    //   345: astore 28
    //   347: aload 25
    //   349: astore 27
    //   351: getstatic 186	com/google/android/gms/internal/ads/zzbbk:zzbJ	Lcom/google/android/gms/internal/ads/zzbbc;
    //   354: astore_2
    //   355: aload 26
    //   357: astore 29
    //   359: aload 30
    //   361: astore 28
    //   363: aload 25
    //   365: astore 27
    //   367: invokestatic 161	com/google/android/gms/ads/internal/client/zzba:zzc	()Lcom/google/android/gms/internal/ads/zzbbi;
    //   370: aload_2
    //   371: invokevirtual 166	com/google/android/gms/internal/ads/zzbbi:zzb	(Lcom/google/android/gms/internal/ads/zzbbc;)Ljava/lang/Object;
    //   374: checkcast 188	java/lang/Boolean
    //   377: invokevirtual 192	java/lang/Boolean:booleanValue	()Z
    //   380: istore 6
    //   382: ldc2_w 222
    //   385: lstore 9
    //   387: aload 30
    //   389: astore_2
    //   390: aload 26
    //   392: astore 29
    //   394: aload_2
    //   395: astore 28
    //   397: aload 25
    //   399: astore 27
    //   401: aload_0
    //   402: monitorenter
    //   403: aload 34
    //   405: invokeinterface 203 1 0
    //   410: lload 21
    //   412: lsub
    //   413: lload 11
    //   415: lcmp
    //   416: ifgt +628 -> 1044
    //   419: aload 25
    //   421: getfield 207	com/google/android/gms/internal/ads/zzcdw:zzg	Z
    //   424: ifne +556 -> 980
    //   427: aload 25
    //   429: getfield 141	com/google/android/gms/internal/ads/zzcdw:zzh	Z
    //   432: ifeq +8 -> 440
    //   435: aload_0
    //   436: monitorexit
    //   437: goto +344 -> 781
    //   440: aload 25
    //   442: getfield 56	com/google/android/gms/internal/ads/zzcdw:zze	Lcom/google/android/gms/internal/ads/zzcbt;
    //   445: invokevirtual 210	com/google/android/gms/internal/ads/zzcbt:zzV	()Z
    //   448: ifeq +470 -> 918
    //   451: aload 25
    //   453: getfield 56	com/google/android/gms/internal/ads/zzcdw:zze	Lcom/google/android/gms/internal/ads/zzcbt;
    //   456: invokevirtual 213	com/google/android/gms/internal/ads/zzcbt:zzz	()J
    //   459: lstore 23
    //   461: lload 23
    //   463: lconst_0
    //   464: lcmp
    //   465: ifle +325 -> 790
    //   468: aload 25
    //   470: getfield 56	com/google/android/gms/internal/ads/zzcdw:zze	Lcom/google/android/gms/internal/ads/zzcbt;
    //   473: invokevirtual 216	com/google/android/gms/internal/ads/zzcbt:zzv	()J
    //   476: lstore 19
    //   478: lload 19
    //   480: lload 9
    //   482: lcmp
    //   483: ifeq +181 -> 664
    //   486: lload 19
    //   488: lconst_0
    //   489: lcmp
    //   490: ifle +9 -> 499
    //   493: iconst_1
    //   494: istore 5
    //   496: goto +6 -> 502
    //   499: iconst_0
    //   500: istore 5
    //   502: iload 6
    //   504: ifeq +16 -> 520
    //   507: aload 25
    //   509: getfield 56	com/google/android/gms/internal/ads/zzcdw:zze	Lcom/google/android/gms/internal/ads/zzcbt;
    //   512: invokevirtual 221	com/google/android/gms/internal/ads/zzcbt:zzA	()J
    //   515: lstore 9
    //   517: goto +8 -> 525
    //   520: ldc2_w 222
    //   523: lstore 9
    //   525: iload 6
    //   527: ifeq +16 -> 543
    //   530: aload 25
    //   532: getfield 56	com/google/android/gms/internal/ads/zzcdw:zze	Lcom/google/android/gms/internal/ads/zzcbt;
    //   535: invokevirtual 225	com/google/android/gms/internal/ads/zzcbt:zzx	()J
    //   538: lstore 15
    //   540: goto +8 -> 548
    //   543: ldc2_w 222
    //   546: lstore 15
    //   548: iload 6
    //   550: ifeq +16 -> 566
    //   553: aload 25
    //   555: getfield 56	com/google/android/gms/internal/ads/zzcdw:zze	Lcom/google/android/gms/internal/ads/zzcbt;
    //   558: invokevirtual 227	com/google/android/gms/internal/ads/zzcbt:zzB	()J
    //   561: lstore 17
    //   563: goto +8 -> 571
    //   566: ldc2_w 222
    //   569: lstore 17
    //   571: invokestatic 230	com/google/android/gms/internal/ads/zzcbt:zzs	()I
    //   574: istore 4
    //   576: invokestatic 233	com/google/android/gms/internal/ads/zzcbt:zzu	()I
    //   579: istore_3
    //   580: aload_0
    //   581: aload_1
    //   582: aload_2
    //   583: lload 19
    //   585: lload 23
    //   587: iload 5
    //   589: lload 9
    //   591: lload 15
    //   593: lload 17
    //   595: iload 4
    //   597: iload_3
    //   598: invokevirtual 237	com/google/android/gms/internal/ads/zzcdn:zzo	(Ljava/lang/String;Ljava/lang/String;JJZJJJII)V
    //   601: lload 19
    //   603: lstore 9
    //   605: goto +59 -> 664
    //   608: astore 26
    //   610: aload_0
    //   611: astore 25
    //   613: aload_1
    //   614: astore 28
    //   616: aload_2
    //   617: astore 27
    //   619: aload 25
    //   621: astore_1
    //   622: aload 28
    //   624: astore_2
    //   625: aload 27
    //   627: astore 25
    //   629: aload 32
    //   631: astore 27
    //   633: goto +631 -> 1264
    //   636: astore 26
    //   638: aload_0
    //   639: astore 27
    //   641: aload_1
    //   642: astore 25
    //   644: aload_2
    //   645: astore 28
    //   647: aload 27
    //   649: astore_1
    //   650: aload 25
    //   652: astore_2
    //   653: aload 28
    //   655: astore 25
    //   657: aload 32
    //   659: astore 27
    //   661: goto +603 -> 1264
    //   664: lload 19
    //   666: lload 23
    //   668: lcmp
    //   669: iflt +48 -> 717
    //   672: aload_0
    //   673: astore 25
    //   675: aload 25
    //   677: astore 31
    //   679: aload_1
    //   680: astore 29
    //   682: aload_2
    //   683: astore 30
    //   685: aload 32
    //   687: astore 33
    //   689: aload 25
    //   691: aload_1
    //   692: aload_2
    //   693: lload 23
    //   695: invokevirtual 240	com/google/android/gms/internal/ads/zzcdn:zzj	(Ljava/lang/String;Ljava/lang/String;J)V
    //   698: aload 25
    //   700: astore 31
    //   702: aload_1
    //   703: astore 29
    //   705: aload_2
    //   706: astore 30
    //   708: aload 32
    //   710: astore 33
    //   712: aload_0
    //   713: monitorexit
    //   714: goto +67 -> 781
    //   717: aload_0
    //   718: astore 28
    //   720: aload_1
    //   721: astore 27
    //   723: aload_2
    //   724: astore 25
    //   726: aload 28
    //   728: astore 31
    //   730: aload 27
    //   732: astore 29
    //   734: aload 25
    //   736: astore 30
    //   738: aload 32
    //   740: astore 33
    //   742: aload 28
    //   744: getfield 56	com/google/android/gms/internal/ads/zzcdw:zze	Lcom/google/android/gms/internal/ads/zzcbt;
    //   747: invokevirtual 242	com/google/android/gms/internal/ads/zzcbt:zzw	()J
    //   750: lload 13
    //   752: lcmp
    //   753: iflt +30 -> 783
    //   756: lload 19
    //   758: lconst_0
    //   759: lcmp
    //   760: ifle +23 -> 783
    //   763: aload 28
    //   765: astore 31
    //   767: aload 27
    //   769: astore 29
    //   771: aload 25
    //   773: astore 30
    //   775: aload 32
    //   777: astore 33
    //   779: aload_0
    //   780: monitorexit
    //   781: iconst_1
    //   782: ireturn
    //   783: lload 7
    //   785: lstore 15
    //   787: goto +18 -> 805
    //   790: aload_2
    //   791: astore 27
    //   793: lload 7
    //   795: lstore 15
    //   797: aload 26
    //   799: astore 27
    //   801: aload 25
    //   803: astore 28
    //   805: aload_2
    //   806: astore 25
    //   808: aload 28
    //   810: astore 31
    //   812: aload 27
    //   814: astore 29
    //   816: aload 25
    //   818: astore 30
    //   820: aload 32
    //   822: astore 33
    //   824: aload 28
    //   826: lload 7
    //   828: invokevirtual 375	java/lang/Object:wait	(J)V
    //   831: aload 28
    //   833: astore 31
    //   835: aload 27
    //   837: astore 29
    //   839: aload 25
    //   841: astore 30
    //   843: aload 32
    //   845: astore 33
    //   847: aload_0
    //   848: monitorexit
    //   849: aload 27
    //   851: astore 26
    //   853: aload 25
    //   855: astore_2
    //   856: aload 28
    //   858: astore 25
    //   860: goto -470 -> 390
    //   863: astore_1
    //   864: ldc_w 377
    //   867: astore 29
    //   869: aload 29
    //   871: astore 26
    //   873: aload 28
    //   875: astore_1
    //   876: aload 27
    //   878: astore 25
    //   880: new 251	java/io/IOException
    //   883: astore 30
    //   885: aload 29
    //   887: astore 26
    //   889: aload 28
    //   891: astore_1
    //   892: aload 27
    //   894: astore 25
    //   896: aload 30
    //   898: ldc_w 379
    //   901: invokespecial 255	java/io/IOException:<init>	(Ljava/lang/String;)V
    //   904: aload 29
    //   906: astore 26
    //   908: aload 28
    //   910: astore_1
    //   911: aload 27
    //   913: astore 25
    //   915: aload 30
    //   917: athrow
    //   918: aload 26
    //   920: astore 27
    //   922: aload_2
    //   923: astore_1
    //   924: aload 25
    //   926: astore 28
    //   928: ldc -7
    //   930: astore 29
    //   932: aload 29
    //   934: astore 26
    //   936: aload 28
    //   938: astore_1
    //   939: aload 27
    //   941: astore 25
    //   943: new 251	java/io/IOException
    //   946: astore 30
    //   948: aload 29
    //   950: astore 26
    //   952: aload 28
    //   954: astore_1
    //   955: aload 27
    //   957: astore 25
    //   959: aload 30
    //   961: ldc -3
    //   963: invokespecial 255	java/io/IOException:<init>	(Ljava/lang/String;)V
    //   966: aload 29
    //   968: astore 26
    //   970: aload 28
    //   972: astore_1
    //   973: aload 27
    //   975: astore 25
    //   977: aload 30
    //   979: athrow
    //   980: aload 26
    //   982: astore 27
    //   984: aload_2
    //   985: astore_1
    //   986: aload 25
    //   988: astore 28
    //   990: ldc_w 257
    //   993: astore 29
    //   995: aload 29
    //   997: astore 26
    //   999: aload 28
    //   1001: astore_1
    //   1002: aload 27
    //   1004: astore 25
    //   1006: new 251	java/io/IOException
    //   1009: astore 30
    //   1011: aload 29
    //   1013: astore 26
    //   1015: aload 28
    //   1017: astore_1
    //   1018: aload 27
    //   1020: astore 25
    //   1022: aload 30
    //   1024: ldc_w 259
    //   1027: invokespecial 255	java/io/IOException:<init>	(Ljava/lang/String;)V
    //   1030: aload 29
    //   1032: astore 26
    //   1034: aload 28
    //   1036: astore_1
    //   1037: aload 27
    //   1039: astore 25
    //   1041: aload 30
    //   1043: athrow
    //   1044: aload 26
    //   1046: astore 27
    //   1048: aload_2
    //   1049: astore_1
    //   1050: aload 25
    //   1052: astore 28
    //   1054: ldc_w 268
    //   1057: astore 29
    //   1059: aload 29
    //   1061: astore 26
    //   1063: aload 28
    //   1065: astore_1
    //   1066: aload 27
    //   1068: astore 25
    //   1070: new 251	java/io/IOException
    //   1073: astore 30
    //   1075: aload 29
    //   1077: astore 26
    //   1079: aload 28
    //   1081: astore_1
    //   1082: aload 27
    //   1084: astore 25
    //   1086: new 99	java/lang/StringBuilder
    //   1089: astore 31
    //   1091: aload 29
    //   1093: astore 26
    //   1095: aload 28
    //   1097: astore_1
    //   1098: aload 27
    //   1100: astore 25
    //   1102: aload 31
    //   1104: invokespecial 102	java/lang/StringBuilder:<init>	()V
    //   1107: aload 29
    //   1109: astore 26
    //   1111: aload 28
    //   1113: astore_1
    //   1114: aload 27
    //   1116: astore 25
    //   1118: aload 31
    //   1120: ldc_w 261
    //   1123: invokevirtual 106	java/lang/StringBuilder:append	(Ljava/lang/String;)Ljava/lang/StringBuilder;
    //   1126: pop
    //   1127: aload 29
    //   1129: astore 26
    //   1131: aload 28
    //   1133: astore_1
    //   1134: aload 27
    //   1136: astore 25
    //   1138: aload 31
    //   1140: lload 11
    //   1142: invokevirtual 264	java/lang/StringBuilder:append	(J)Ljava/lang/StringBuilder;
    //   1145: pop
    //   1146: aload 29
    //   1148: astore 26
    //   1150: aload 28
    //   1152: astore_1
    //   1153: aload 27
    //   1155: astore 25
    //   1157: aload 31
    //   1159: ldc_w 266
    //   1162: invokevirtual 106	java/lang/StringBuilder:append	(Ljava/lang/String;)Ljava/lang/StringBuilder;
    //   1165: pop
    //   1166: aload 29
    //   1168: astore 26
    //   1170: aload 28
    //   1172: astore_1
    //   1173: aload 27
    //   1175: astore 25
    //   1177: aload 30
    //   1179: aload 31
    //   1181: invokevirtual 113	java/lang/StringBuilder:toString	()Ljava/lang/String;
    //   1184: invokespecial 255	java/io/IOException:<init>	(Ljava/lang/String;)V
    //   1187: aload 29
    //   1189: astore 26
    //   1191: aload 28
    //   1193: astore_1
    //   1194: aload 27
    //   1196: astore 25
    //   1198: aload 30
    //   1200: athrow
    //   1201: aload_2
    //   1202: astore 27
    //   1204: astore_2
    //   1205: aload 26
    //   1207: astore 28
    //   1209: aload_2
    //   1210: astore 26
    //   1212: aload 25
    //   1214: astore_2
    //   1215: aload 27
    //   1217: astore 25
    //   1219: aload 28
    //   1221: astore 27
    //   1223: goto +41 -> 1264
    //   1226: astore 26
    //   1228: aload 31
    //   1230: astore_1
    //   1231: aload 29
    //   1233: astore_2
    //   1234: aload 30
    //   1236: astore 25
    //   1238: aload 33
    //   1240: astore 27
    //   1242: goto +22 -> 1264
    //   1245: astore 28
    //   1247: aload 25
    //   1249: astore_1
    //   1250: aload 32
    //   1252: astore 27
    //   1254: aload_2
    //   1255: astore 25
    //   1257: aload 26
    //   1259: astore_2
    //   1260: aload 28
    //   1262: astore 26
    //   1264: aload_1
    //   1265: astore 31
    //   1267: aload_2
    //   1268: astore 29
    //   1270: aload 25
    //   1272: astore 30
    //   1274: aload 27
    //   1276: astore 33
    //   1278: aload_0
    //   1279: monitorexit
    //   1280: aload 26
    //   1282: athrow
    //   1283: astore 26
    //   1285: aload_1
    //   1286: astore 28
    //   1288: goto +22 -> 1310
    //   1291: astore_1
    //   1292: aload 29
    //   1294: astore_2
    //   1295: aload 28
    //   1297: astore 25
    //   1299: aload 27
    //   1301: astore 28
    //   1303: aload 32
    //   1305: astore 27
    //   1307: aload_1
    //   1308: astore 26
    //   1310: aload 26
    //   1312: invokevirtual 97	java/lang/Exception:getMessage	()Ljava/lang/String;
    //   1315: astore 29
    //   1317: new 99	java/lang/StringBuilder
    //   1320: dup
    //   1321: invokespecial 102	java/lang/StringBuilder:<init>	()V
    //   1324: astore_1
    //   1325: aload_1
    //   1326: ldc_w 270
    //   1329: invokevirtual 106	java/lang/StringBuilder:append	(Ljava/lang/String;)Ljava/lang/StringBuilder;
    //   1332: pop
    //   1333: aload_1
    //   1334: aload_2
    //   1335: invokevirtual 106	java/lang/StringBuilder:append	(Ljava/lang/String;)Ljava/lang/StringBuilder;
    //   1338: pop
    //   1339: aload_1
    //   1340: ldc_w 272
    //   1343: invokevirtual 106	java/lang/StringBuilder:append	(Ljava/lang/String;)Ljava/lang/StringBuilder;
    //   1346: pop
    //   1347: aload_1
    //   1348: aload 29
    //   1350: invokevirtual 106	java/lang/StringBuilder:append	(Ljava/lang/String;)Ljava/lang/StringBuilder;
    //   1353: pop
    //   1354: aload_1
    //   1355: invokevirtual 113	java/lang/StringBuilder:toString	()Ljava/lang/String;
    //   1358: invokestatic 274	com/google/android/gms/internal/ads/zzbzt:zzj	(Ljava/lang/String;)V
    //   1361: invokestatic 277	com/google/android/gms/ads/internal/zzt:zzo	()Lcom/google/android/gms/internal/ads/zzbzc;
    //   1364: aload 26
    //   1366: ldc_w 279
    //   1369: invokevirtual 285	com/google/android/gms/internal/ads/zzbzc:zzt	(Ljava/lang/Throwable;Ljava/lang/String;)V
    //   1372: aload_0
    //   1373: invokevirtual 287	com/google/android/gms/internal/ads/zzcdn:release	()V
    //   1376: aload 28
    //   1378: aload_2
    //   1379: aload 25
    //   1381: aload 27
    //   1383: aload 27
    //   1385: aload 26
    //   1387: invokestatic 289	com/google/android/gms/internal/ads/zzcdw:zzd	(Ljava/lang/String;Ljava/lang/Exception;)Ljava/lang/String;
    //   1390: invokevirtual 292	com/google/android/gms/internal/ads/zzcdn:zzg	(Ljava/lang/String;Ljava/lang/String;Ljava/lang/String;Ljava/lang/String;)V
    //   1393: iconst_0
    //   1394: ireturn
    // Local variable table:
    //   start	length	slot	name	signature
    //   0	1395	0	this	zzcdw
    //   0	1395	1	paramString	String
    //   0	1395	2	paramArrayOfString	String[]
    //   43	555	3	i	int
    //   574	22	4	j	int
    //   494	94	5	bool1	boolean
    //   380	169	6	bool2	boolean
    //   246	581	7	l1	long
    //   385	219	9	l2	long
    //   293	848	11	l3	long
    //   337	414	13	l4	long
    //   538	258	15	l5	long
    //   561	33	17	l6	long
    //   476	281	19	l7	long
    //   203	208	21	l8	long
    //   459	235	23	l9	long
    //   1	1379	25	localObject1	Object
    //   4	387	26	str1	String
    //   608	1	26	localObject2	Object
    //   636	162	26	localObject3	Object
    //   851	360	26	localObject4	Object
    //   1226	32	26	localObject5	Object
    //   1262	19	26	localObject6	Object
    //   1283	1	26	localException	Exception
    //   1308	78	26	str2	String
    //   33	1351	27	localObject7	Object
    //   29	1191	28	localObject8	Object
    //   1245	16	28	localObject9	Object
    //   1286	91	28	localObject10	Object
    //   25	1324	29	localObject11	Object
    //   21	1252	30	localObject12	Object
    //   40	1226	31	localObject13	Object
    //   15	1289	32	str3	String
    //   687	590	33	localObject14	Object
    //   182	222	34	localClock	Clock
    // Exception table:
    //   from	to	target	type
    //   580	601	608	finally
    //   571	580	636	finally
    //   824	831	863	java/lang/InterruptedException
    //   880	885	1201	finally
    //   896	904	1201	finally
    //   915	918	1201	finally
    //   943	948	1201	finally
    //   959	966	1201	finally
    //   977	980	1201	finally
    //   1006	1011	1201	finally
    //   1022	1030	1201	finally
    //   1041	1044	1201	finally
    //   1070	1075	1201	finally
    //   1086	1091	1201	finally
    //   1102	1107	1201	finally
    //   1118	1127	1201	finally
    //   1138	1146	1201	finally
    //   1157	1166	1201	finally
    //   1177	1187	1201	finally
    //   1198	1201	1201	finally
    //   689	698	1226	finally
    //   712	714	1226	finally
    //   742	756	1226	finally
    //   779	781	1226	finally
    //   824	831	1226	finally
    //   847	849	1226	finally
    //   1278	1280	1226	finally
    //   403	437	1245	finally
    //   440	461	1245	finally
    //   468	478	1245	finally
    //   507	517	1245	finally
    //   530	540	1245	finally
    //   553	563	1245	finally
    //   1280	1283	1283	java/lang/Exception
    //   35	42	1291	java/lang/Exception
    //   56	62	1291	java/lang/Exception
    //   74	84	1291	java/lang/Exception
    //   102	117	1291	java/lang/Exception
    //   129	141	1291	java/lang/Exception
    //   157	167	1291	java/lang/Exception
    //   179	184	1291	java/lang/Exception
    //   196	205	1291	java/lang/Exception
    //   217	221	1291	java/lang/Exception
    //   233	248	1291	java/lang/Exception
    //   260	264	1291	java/lang/Exception
    //   276	295	1291	java/lang/Exception
    //   307	311	1291	java/lang/Exception
    //   323	339	1291	java/lang/Exception
    //   351	355	1291	java/lang/Exception
    //   367	382	1291	java/lang/Exception
    //   401	403	1291	java/lang/Exception
  }
  
  public final void zzv()
  {
    zzbzt.zzj("Precache onRenderedFirstFrame");
  }
  
  public final boolean zzw(String paramString, String[] paramArrayOfString, zzcdf paramzzcdf)
  {
    this.zzf = paramString;
    this.zzi = paramzzcdf;
    paramzzcdf = zzc(paramString);
    try
    {
      Uri[] arrayOfUri = new Uri[paramArrayOfString.length];
      for (int i = 0; i < paramArrayOfString.length; i++) {
        arrayOfUri[i] = Uri.parse(paramArrayOfString[i]);
      }
      this.zze.zzF(arrayOfUri, this.zzb);
      paramArrayOfString = (zzccc)this.zzc.get();
      if (paramArrayOfString != null) {
        paramArrayOfString.zzt(paramzzcdf, this);
      }
      this.zzj = zzt.zzB().currentTimeMillis();
      this.zzk = -1L;
      zzx(0L);
      return true;
    }
    catch (Exception localException)
    {
      String str = localException.getMessage();
      paramArrayOfString = new StringBuilder();
      paramArrayOfString.append("Failed to preload url ");
      paramArrayOfString.append(paramString);
      paramArrayOfString.append(" Exception: ");
      paramArrayOfString.append(str);
      zzbzt.zzj(paramArrayOfString.toString());
      zzt.zzo().zzt(localException, "VideoStreamExoPlayerCache.preload");
      release();
      zzg(paramString, paramzzcdf, "error", zzd("error", localException));
    }
    return false;
  }
}


/* Location:              C:\Users\Ria\Documents\slope apk\dex-tools-v2.4\classes-dex2jar.jar!\com\google\android\gms\internal\ads\zzcdw.class
 * Java compiler version: 6 (50.0)
 * JD-Core Version:       0.7.1
 */