package com.google.android.gms.internal.ads;

import java.nio.ByteBuffer;

public final class zzcdt
  extends zzcdn
  implements zzgz
{
  private String zzd;
  private final zzccb zze;
  private boolean zzf;
  private final zzcds zzg;
  private final zzccy zzh;
  private ByteBuffer zzi;
  private boolean zzj;
  private final Object zzk;
  private final String zzl;
  private final int zzm;
  private boolean zzn;
  
  public zzcdt(zzccc paramzzccc, zzccb paramzzccb)
  {
    super(paramzzccc);
    this.zze = paramzzccb;
    this.zzg = new zzcds();
    this.zzh = new zzccy();
    this.zzk = new Object();
    if (paramzzccc != null) {
      paramzzccb = paramzzccc.zzbl();
    } else {
      paramzzccb = null;
    }
    this.zzl = ((String)zzfov.zzd(paramzzccb).zzb(""));
    int i;
    if (paramzzccc != null) {
      i = paramzzccc.zzf();
    } else {
      i = 0;
    }
    this.zzm = i;
  }
  
  protected static final String zzm(String paramString)
  {
    return "cache:".concat(String.valueOf(zzbzm.zze(paramString)));
  }
  
  private final void zzv()
  {
    int j = (int)this.zzg.zza();
    int m = (int)this.zzh.zza(this.zzi);
    int i1 = this.zzi.position();
    float f2 = i1;
    float f1 = j;
    int n = Math.round(m * (f2 / f1));
    int i = zzcbt.zzs();
    int k = zzcbt.zzu();
    String str2 = this.zzd;
    String str1 = zzm(str2);
    long l = n;
    boolean bool;
    if (n > 0) {
      bool = true;
    } else {
      bool = false;
    }
    zzn(str2, str1, i1, j, l, m, bool, i, k);
  }
  
  public final void zza(zzfx paramzzfx, zzgc paramzzgc, boolean paramBoolean, int paramInt) {}
  
  public final void zzb(zzfx paramzzfx, zzgc paramzzgc, boolean paramBoolean) {}
  
  public final void zzc(zzfx paramzzfx, zzgc paramzzgc, boolean paramBoolean) {}
  
  public final void zzd(zzfx paramzzfx, zzgc paramzzgc, boolean paramBoolean)
  {
    if ((paramzzfx instanceof zzgk)) {
      this.zzg.zzb((zzgk)paramzzfx);
    }
  }
  
  public final void zzf()
  {
    this.zzf = true;
  }
  
  public final String zzi()
  {
    return this.zzd;
  }
  
  public final ByteBuffer zzk()
  {
    synchronized (this.zzk)
    {
      ByteBuffer localByteBuffer = this.zzi;
      if ((localByteBuffer != null) && (!this.zzj))
      {
        localByteBuffer.flip();
        this.zzj = true;
      }
      this.zzf = true;
      return this.zzi;
    }
  }
  
  public final boolean zzl()
  {
    return this.zzn;
  }
  
  /* Error */
  public final boolean zzt(String paramString)
  {
    // Byte code:
    //   0: aload_0
    //   1: aload_1
    //   2: putfield 121	com/google/android/gms/internal/ads/zzcdt:zzd	Ljava/lang/String;
    //   5: ldc -104
    //   7: astore 15
    //   9: aload_1
    //   10: invokestatic 123	com/google/android/gms/internal/ads/zzcdt:zzm	(Ljava/lang/String;)Ljava/lang/String;
    //   13: astore 19
    //   15: aload 15
    //   17: astore 16
    //   19: new 154	com/google/android/gms/internal/ads/zzgf
    //   22: astore 17
    //   24: aload 15
    //   26: astore 16
    //   28: aload 17
    //   30: invokespecial 155	com/google/android/gms/internal/ads/zzgf:<init>	()V
    //   33: aload 15
    //   35: astore 16
    //   37: aload 17
    //   39: aload_0
    //   40: getfield 157	com/google/android/gms/internal/ads/zzcdt:zzb	Ljava/lang/String;
    //   43: invokevirtual 160	com/google/android/gms/internal/ads/zzgf:zzf	(Ljava/lang/String;)Lcom/google/android/gms/internal/ads/zzgf;
    //   46: pop
    //   47: aload 15
    //   49: astore 16
    //   51: aload 17
    //   53: aload_0
    //   54: getfield 32	com/google/android/gms/internal/ads/zzcdt:zze	Lcom/google/android/gms/internal/ads/zzccb;
    //   57: getfield 164	com/google/android/gms/internal/ads/zzccb:zzd	I
    //   60: invokevirtual 167	com/google/android/gms/internal/ads/zzgf:zzc	(I)Lcom/google/android/gms/internal/ads/zzgf;
    //   63: pop
    //   64: aload 15
    //   66: astore 16
    //   68: aload 17
    //   70: aload_0
    //   71: getfield 32	com/google/android/gms/internal/ads/zzcdt:zze	Lcom/google/android/gms/internal/ads/zzccb;
    //   74: getfield 169	com/google/android/gms/internal/ads/zzccb:zzf	I
    //   77: invokevirtual 171	com/google/android/gms/internal/ads/zzgf:zzd	(I)Lcom/google/android/gms/internal/ads/zzgf;
    //   80: pop
    //   81: aload 15
    //   83: astore 16
    //   85: aload 17
    //   87: iconst_1
    //   88: invokevirtual 174	com/google/android/gms/internal/ads/zzgf:zzb	(Z)Lcom/google/android/gms/internal/ads/zzgf;
    //   91: pop
    //   92: aload 15
    //   94: astore 16
    //   96: aload 17
    //   98: aload_0
    //   99: invokevirtual 177	com/google/android/gms/internal/ads/zzgf:zze	(Lcom/google/android/gms/internal/ads/zzgz;)Lcom/google/android/gms/internal/ads/zzgf;
    //   102: pop
    //   103: aload 15
    //   105: astore 16
    //   107: aload 17
    //   109: invokevirtual 180	com/google/android/gms/internal/ads/zzgf:zzg	()Lcom/google/android/gms/internal/ads/zzgk;
    //   112: astore 18
    //   114: aload 18
    //   116: astore 17
    //   118: aload 15
    //   120: astore 16
    //   122: aload_0
    //   123: getfield 32	com/google/android/gms/internal/ads/zzcdt:zze	Lcom/google/android/gms/internal/ads/zzccb;
    //   126: getfield 181	com/google/android/gms/internal/ads/zzccb:zzj	Z
    //   129: ifeq +37 -> 166
    //   132: aload 15
    //   134: astore 16
    //   136: new 183	com/google/android/gms/internal/ads/zzccw
    //   139: astore 17
    //   141: aload 15
    //   143: astore 16
    //   145: aload 17
    //   147: aload_0
    //   148: getfield 186	com/google/android/gms/internal/ads/zzcdt:zza	Landroid/content/Context;
    //   151: aload 18
    //   153: aload_0
    //   154: getfield 70	com/google/android/gms/internal/ads/zzcdt:zzl	Ljava/lang/String;
    //   157: aload_0
    //   158: getfield 75	com/google/android/gms/internal/ads/zzcdt:zzm	I
    //   161: aconst_null
    //   162: aconst_null
    //   163: invokespecial 189	com/google/android/gms/internal/ads/zzccw:<init>	(Landroid/content/Context;Lcom/google/android/gms/internal/ads/zzfx;Ljava/lang/String;ILcom/google/android/gms/internal/ads/zzgz;Lcom/google/android/gms/internal/ads/zzccv;)V
    //   166: aload 15
    //   168: astore 16
    //   170: aload_1
    //   171: invokestatic 195	android/net/Uri:parse	(Ljava/lang/String;)Landroid/net/Uri;
    //   174: astore 18
    //   176: aload 15
    //   178: astore 16
    //   180: new 197	com/google/android/gms/internal/ads/zzgc
    //   183: astore 20
    //   185: aload 15
    //   187: astore 16
    //   189: aload 20
    //   191: aload 18
    //   193: invokespecial 200	com/google/android/gms/internal/ads/zzgc:<init>	(Landroid/net/Uri;)V
    //   196: aload 15
    //   198: astore 16
    //   200: aload 17
    //   202: aload 20
    //   204: invokeinterface 205 2 0
    //   209: pop2
    //   210: aload 15
    //   212: astore 16
    //   214: aload_0
    //   215: getfield 208	com/google/android/gms/internal/ads/zzcdt:zzc	Ljava/lang/ref/WeakReference;
    //   218: invokevirtual 214	java/lang/ref/WeakReference:get	()Ljava/lang/Object;
    //   221: checkcast 51	com/google/android/gms/internal/ads/zzccc
    //   224: astore 18
    //   226: aload 18
    //   228: ifnull +17 -> 245
    //   231: aload 15
    //   233: astore 16
    //   235: aload 18
    //   237: aload 19
    //   239: aload_0
    //   240: invokeinterface 217 3 0
    //   245: aload 15
    //   247: astore 16
    //   249: invokestatic 223	com/google/android/gms/ads/internal/zzt:zzB	()Lcom/google/android/gms/common/util/Clock;
    //   252: astore 20
    //   254: aload 15
    //   256: astore 16
    //   258: aload 20
    //   260: invokeinterface 228 1 0
    //   265: lstore 7
    //   267: aload 15
    //   269: astore 16
    //   271: getstatic 234	com/google/android/gms/internal/ads/zzbbk:zzy	Lcom/google/android/gms/internal/ads/zzbbc;
    //   274: astore 18
    //   276: aload 15
    //   278: astore 16
    //   280: invokestatic 239	com/google/android/gms/ads/internal/client/zzba:zzc	()Lcom/google/android/gms/internal/ads/zzbbi;
    //   283: aload 18
    //   285: invokevirtual 244	com/google/android/gms/internal/ads/zzbbi:zzb	(Lcom/google/android/gms/internal/ads/zzbbc;)Ljava/lang/Object;
    //   288: checkcast 246	java/lang/Long
    //   291: invokevirtual 249	java/lang/Long:longValue	()J
    //   294: lstore 11
    //   296: aload 15
    //   298: astore 16
    //   300: getstatic 252	com/google/android/gms/internal/ads/zzbbk:zzx	Lcom/google/android/gms/internal/ads/zzbbc;
    //   303: astore 18
    //   305: aload 15
    //   307: astore 16
    //   309: invokestatic 239	com/google/android/gms/ads/internal/client/zzba:zzc	()Lcom/google/android/gms/internal/ads/zzbbi;
    //   312: aload 18
    //   314: invokevirtual 244	com/google/android/gms/internal/ads/zzbbi:zzb	(Lcom/google/android/gms/internal/ads/zzbbc;)Ljava/lang/Object;
    //   317: checkcast 246	java/lang/Long
    //   320: invokevirtual 249	java/lang/Long:longValue	()J
    //   323: lstore 13
    //   325: aload 15
    //   327: astore 16
    //   329: aload_0
    //   330: aload_0
    //   331: getfield 32	com/google/android/gms/internal/ads/zzcdt:zze	Lcom/google/android/gms/internal/ads/zzccb;
    //   334: getfield 254	com/google/android/gms/internal/ads/zzccb:zzc	I
    //   337: invokestatic 258	java/nio/ByteBuffer:allocate	(I)Ljava/nio/ByteBuffer;
    //   340: putfield 97	com/google/android/gms/internal/ads/zzcdt:zzi	Ljava/nio/ByteBuffer;
    //   343: aload 15
    //   345: astore 16
    //   347: sipush 8192
    //   350: newarray <illegal type>
    //   352: astore 21
    //   354: lload 7
    //   356: lstore 5
    //   358: aload 15
    //   360: astore 16
    //   362: aload 17
    //   364: aload 21
    //   366: iconst_0
    //   367: aload_0
    //   368: getfield 97	com/google/android/gms/internal/ads/zzcdt:zzi	Ljava/nio/ByteBuffer;
    //   371: invokevirtual 261	java/nio/ByteBuffer:remaining	()I
    //   374: sipush 8192
    //   377: invokestatic 265	java/lang/Math:min	(II)I
    //   380: invokeinterface 268 4 0
    //   385: istore_2
    //   386: iload_2
    //   387: iconst_m1
    //   388: if_icmpne +39 -> 427
    //   391: aload 15
    //   393: astore 16
    //   395: aload_0
    //   396: iconst_1
    //   397: putfield 146	com/google/android/gms/internal/ads/zzcdt:zzn	Z
    //   400: aload 15
    //   402: astore 16
    //   404: aload_0
    //   405: aload_1
    //   406: aload 19
    //   408: aload_0
    //   409: getfield 44	com/google/android/gms/internal/ads/zzcdt:zzh	Lcom/google/android/gms/internal/ads/zzccy;
    //   412: aload_0
    //   413: getfield 97	com/google/android/gms/internal/ads/zzcdt:zzi	Ljava/nio/ByteBuffer;
    //   416: invokevirtual 100	com/google/android/gms/internal/ads/zzccy:zza	(Ljava/nio/ByteBuffer;)J
    //   419: l2i
    //   420: i2l
    //   421: invokevirtual 271	com/google/android/gms/internal/ads/zzcdn:zzj	(Ljava/lang/String;Ljava/lang/String;J)V
    //   424: goto +82 -> 506
    //   427: aload 15
    //   429: astore 16
    //   431: aload_0
    //   432: getfield 49	com/google/android/gms/internal/ads/zzcdt:zzk	Ljava/lang/Object;
    //   435: astore 18
    //   437: aload 15
    //   439: astore 16
    //   441: aload 18
    //   443: monitorenter
    //   444: aload_0
    //   445: getfield 136	com/google/android/gms/internal/ads/zzcdt:zzf	Z
    //   448: ifne +26 -> 474
    //   451: aload_0
    //   452: getfield 97	com/google/android/gms/internal/ads/zzcdt:zzi	Ljava/nio/ByteBuffer;
    //   455: astore 22
    //   457: aload 15
    //   459: astore 16
    //   461: aload 22
    //   463: aload 21
    //   465: iconst_0
    //   466: iload_2
    //   467: invokevirtual 275	java/nio/ByteBuffer:put	([BII)Ljava/nio/ByteBuffer;
    //   470: pop
    //   471: goto +3 -> 474
    //   474: aload 15
    //   476: astore 16
    //   478: aload 18
    //   480: monitorexit
    //   481: aload 15
    //   483: astore 16
    //   485: aload_0
    //   486: getfield 97	com/google/android/gms/internal/ads/zzcdt:zzi	Ljava/nio/ByteBuffer;
    //   489: invokevirtual 261	java/nio/ByteBuffer:remaining	()I
    //   492: ifgt +16 -> 508
    //   495: aload 15
    //   497: astore 16
    //   499: aload_0
    //   500: invokespecial 277	com/google/android/gms/internal/ads/zzcdt:zzv	()V
    //   503: goto -79 -> 424
    //   506: iconst_1
    //   507: ireturn
    //   508: aload 15
    //   510: astore 16
    //   512: aload_0
    //   513: getfield 136	com/google/android/gms/internal/ads/zzcdt:zzf	Z
    //   516: ifne +170 -> 686
    //   519: aload 15
    //   521: astore 16
    //   523: aload 20
    //   525: invokeinterface 228 1 0
    //   530: lstore 9
    //   532: lload 5
    //   534: lstore_3
    //   535: lload 9
    //   537: lload 5
    //   539: lsub
    //   540: lload 11
    //   542: lcmp
    //   543: iflt +14 -> 557
    //   546: aload 15
    //   548: astore 16
    //   550: aload_0
    //   551: invokespecial 277	com/google/android/gms/internal/ads/zzcdt:zzv	()V
    //   554: lload 9
    //   556: lstore_3
    //   557: lload 9
    //   559: lload 7
    //   561: lsub
    //   562: ldc2_w 278
    //   565: lload 13
    //   567: lmul
    //   568: lcmp
    //   569: ifgt +9 -> 578
    //   572: lload_3
    //   573: lstore 5
    //   575: goto -217 -> 358
    //   578: ldc_w 281
    //   581: astore 16
    //   583: aload 16
    //   585: astore 15
    //   587: new 283	java/lang/StringBuilder
    //   590: astore 17
    //   592: aload 16
    //   594: astore 15
    //   596: aload 17
    //   598: invokespecial 284	java/lang/StringBuilder:<init>	()V
    //   601: aload 16
    //   603: astore 15
    //   605: aload 17
    //   607: ldc_w 286
    //   610: invokevirtual 290	java/lang/StringBuilder:append	(Ljava/lang/String;)Ljava/lang/StringBuilder;
    //   613: pop
    //   614: aload 16
    //   616: astore 15
    //   618: aload 17
    //   620: lload 13
    //   622: invokevirtual 293	java/lang/StringBuilder:append	(J)Ljava/lang/StringBuilder;
    //   625: pop
    //   626: aload 16
    //   628: astore 15
    //   630: aload 17
    //   632: ldc_w 295
    //   635: invokevirtual 290	java/lang/StringBuilder:append	(Ljava/lang/String;)Ljava/lang/StringBuilder;
    //   638: pop
    //   639: aload 16
    //   641: astore 15
    //   643: aload 17
    //   645: invokevirtual 298	java/lang/StringBuilder:toString	()Ljava/lang/String;
    //   648: astore 17
    //   650: aload 16
    //   652: astore 15
    //   654: new 300	java/io/IOException
    //   657: astore 18
    //   659: aload 16
    //   661: astore 15
    //   663: aload 18
    //   665: aload 17
    //   667: invokespecial 303	java/io/IOException:<init>	(Ljava/lang/String;)V
    //   670: aload 16
    //   672: astore 15
    //   674: aload 18
    //   676: athrow
    //   677: astore 17
    //   679: aload 15
    //   681: astore 16
    //   683: goto +145 -> 828
    //   686: ldc_w 305
    //   689: astore 16
    //   691: aload 16
    //   693: astore 15
    //   695: new 300	java/io/IOException
    //   698: astore 18
    //   700: aload 16
    //   702: astore 15
    //   704: aload_0
    //   705: getfield 97	com/google/android/gms/internal/ads/zzcdt:zzi	Ljava/nio/ByteBuffer;
    //   708: invokevirtual 308	java/nio/ByteBuffer:limit	()I
    //   711: istore_2
    //   712: aload 16
    //   714: astore 15
    //   716: new 283	java/lang/StringBuilder
    //   719: astore 17
    //   721: aload 16
    //   723: astore 15
    //   725: aload 17
    //   727: invokespecial 284	java/lang/StringBuilder:<init>	()V
    //   730: aload 16
    //   732: astore 15
    //   734: aload 17
    //   736: ldc_w 310
    //   739: invokevirtual 290	java/lang/StringBuilder:append	(Ljava/lang/String;)Ljava/lang/StringBuilder;
    //   742: pop
    //   743: aload 16
    //   745: astore 15
    //   747: aload 17
    //   749: iload_2
    //   750: invokevirtual 313	java/lang/StringBuilder:append	(I)Ljava/lang/StringBuilder;
    //   753: pop
    //   754: aload 16
    //   756: astore 15
    //   758: aload 17
    //   760: ldc_w 315
    //   763: invokevirtual 290	java/lang/StringBuilder:append	(Ljava/lang/String;)Ljava/lang/StringBuilder;
    //   766: pop
    //   767: aload 16
    //   769: astore 15
    //   771: aload 18
    //   773: aload 17
    //   775: invokevirtual 298	java/lang/StringBuilder:toString	()Ljava/lang/String;
    //   778: invokespecial 303	java/io/IOException:<init>	(Ljava/lang/String;)V
    //   781: aload 16
    //   783: astore 15
    //   785: aload 18
    //   787: athrow
    //   788: astore 15
    //   790: goto +34 -> 824
    //   793: astore 17
    //   795: aload 16
    //   797: astore 15
    //   799: goto +9 -> 808
    //   802: astore 16
    //   804: aload 16
    //   806: astore 17
    //   808: aload 15
    //   810: astore 16
    //   812: aload 18
    //   814: monitorexit
    //   815: aload 15
    //   817: astore 16
    //   819: aload 17
    //   821: athrow
    //   822: astore 15
    //   824: aload 15
    //   826: astore 17
    //   828: aload 17
    //   830: invokevirtual 319	java/lang/Object:getClass	()Ljava/lang/Class;
    //   833: invokevirtual 324	java/lang/Class:getCanonicalName	()Ljava/lang/String;
    //   836: astore 15
    //   838: aload 17
    //   840: invokevirtual 327	java/lang/Exception:getMessage	()Ljava/lang/String;
    //   843: astore 17
    //   845: new 283	java/lang/StringBuilder
    //   848: dup
    //   849: invokespecial 284	java/lang/StringBuilder:<init>	()V
    //   852: astore 18
    //   854: aload 18
    //   856: aload 15
    //   858: invokevirtual 290	java/lang/StringBuilder:append	(Ljava/lang/String;)Ljava/lang/StringBuilder;
    //   861: pop
    //   862: aload 18
    //   864: ldc_w 329
    //   867: invokevirtual 290	java/lang/StringBuilder:append	(Ljava/lang/String;)Ljava/lang/StringBuilder;
    //   870: pop
    //   871: aload 18
    //   873: aload 17
    //   875: invokevirtual 290	java/lang/StringBuilder:append	(Ljava/lang/String;)Ljava/lang/StringBuilder;
    //   878: pop
    //   879: aload 18
    //   881: invokevirtual 298	java/lang/StringBuilder:toString	()Ljava/lang/String;
    //   884: astore 17
    //   886: new 283	java/lang/StringBuilder
    //   889: dup
    //   890: invokespecial 284	java/lang/StringBuilder:<init>	()V
    //   893: astore 15
    //   895: aload 15
    //   897: ldc_w 331
    //   900: invokevirtual 290	java/lang/StringBuilder:append	(Ljava/lang/String;)Ljava/lang/StringBuilder;
    //   903: pop
    //   904: aload 15
    //   906: aload_1
    //   907: invokevirtual 290	java/lang/StringBuilder:append	(Ljava/lang/String;)Ljava/lang/StringBuilder;
    //   910: pop
    //   911: aload 15
    //   913: ldc_w 333
    //   916: invokevirtual 290	java/lang/StringBuilder:append	(Ljava/lang/String;)Ljava/lang/StringBuilder;
    //   919: pop
    //   920: aload 15
    //   922: aload 17
    //   924: invokevirtual 290	java/lang/StringBuilder:append	(Ljava/lang/String;)Ljava/lang/StringBuilder;
    //   927: pop
    //   928: aload 15
    //   930: invokevirtual 298	java/lang/StringBuilder:toString	()Ljava/lang/String;
    //   933: invokestatic 337	com/google/android/gms/internal/ads/zzbzt:zzj	(Ljava/lang/String;)V
    //   936: aload_0
    //   937: aload_1
    //   938: aload 19
    //   940: aload 16
    //   942: aload 17
    //   944: invokevirtual 340	com/google/android/gms/internal/ads/zzcdn:zzg	(Ljava/lang/String;Ljava/lang/String;Ljava/lang/String;Ljava/lang/String;)V
    //   947: iconst_0
    //   948: ireturn
    // Local variable table:
    //   start	length	slot	name	signature
    //   0	949	0	this	zzcdt
    //   0	949	1	paramString	String
    //   385	365	2	i	int
    //   534	39	3	l1	long
    //   356	218	5	l2	long
    //   265	295	7	l3	long
    //   530	28	9	l4	long
    //   294	247	11	l5	long
    //   323	298	13	l6	long
    //   7	777	15	localObject1	Object
    //   788	1	15	localException1	Exception
    //   797	19	15	localObject2	Object
    //   822	3	15	localException2	Exception
    //   836	93	15	localObject3	Object
    //   17	779	16	localObject4	Object
    //   802	3	16	localObject5	Object
    //   810	131	16	localObject6	Object
    //   22	644	17	localObject7	Object
    //   677	1	17	localException3	Exception
    //   719	55	17	localStringBuilder	StringBuilder
    //   793	1	17	localObject8	Object
    //   806	137	17	localObject9	Object
    //   112	768	18	localObject10	Object
    //   13	926	19	str	String
    //   183	341	20	localObject11	Object
    //   352	112	21	arrayOfByte	byte[]
    //   455	7	22	localByteBuffer	ByteBuffer
    // Exception table:
    //   from	to	target	type
    //   587	592	677	java/lang/Exception
    //   596	601	677	java/lang/Exception
    //   605	614	677	java/lang/Exception
    //   618	626	677	java/lang/Exception
    //   630	639	677	java/lang/Exception
    //   643	650	677	java/lang/Exception
    //   654	659	677	java/lang/Exception
    //   663	670	677	java/lang/Exception
    //   674	677	677	java/lang/Exception
    //   695	700	677	java/lang/Exception
    //   704	712	677	java/lang/Exception
    //   716	721	677	java/lang/Exception
    //   725	730	677	java/lang/Exception
    //   734	743	677	java/lang/Exception
    //   747	754	677	java/lang/Exception
    //   758	767	677	java/lang/Exception
    //   771	781	677	java/lang/Exception
    //   785	788	677	java/lang/Exception
    //   485	495	788	java/lang/Exception
    //   499	503	788	java/lang/Exception
    //   512	519	788	java/lang/Exception
    //   523	532	788	java/lang/Exception
    //   550	554	788	java/lang/Exception
    //   819	822	788	java/lang/Exception
    //   461	471	793	finally
    //   478	481	793	finally
    //   812	815	793	finally
    //   444	457	802	finally
    //   19	24	822	java/lang/Exception
    //   28	33	822	java/lang/Exception
    //   37	47	822	java/lang/Exception
    //   51	64	822	java/lang/Exception
    //   68	81	822	java/lang/Exception
    //   85	92	822	java/lang/Exception
    //   96	103	822	java/lang/Exception
    //   107	114	822	java/lang/Exception
    //   122	132	822	java/lang/Exception
    //   136	141	822	java/lang/Exception
    //   145	166	822	java/lang/Exception
    //   170	176	822	java/lang/Exception
    //   180	185	822	java/lang/Exception
    //   189	196	822	java/lang/Exception
    //   200	210	822	java/lang/Exception
    //   214	226	822	java/lang/Exception
    //   235	245	822	java/lang/Exception
    //   249	254	822	java/lang/Exception
    //   258	267	822	java/lang/Exception
    //   271	276	822	java/lang/Exception
    //   280	296	822	java/lang/Exception
    //   300	305	822	java/lang/Exception
    //   309	325	822	java/lang/Exception
    //   329	343	822	java/lang/Exception
    //   347	354	822	java/lang/Exception
    //   362	386	822	java/lang/Exception
    //   395	400	822	java/lang/Exception
    //   404	424	822	java/lang/Exception
    //   431	437	822	java/lang/Exception
    //   441	444	822	java/lang/Exception
  }
}


/* Location:              C:\Users\Ria\Documents\slope apk\dex-tools-v2.4\classes-dex2jar.jar!\com\google\android\gms\internal\ads\zzcdt.class
 * Java compiler version: 6 (50.0)
 * JD-Core Version:       0.7.1
 */