package com.google.android.gms.internal.ads;

import javax.annotation.ParametersAreNonnullByDefault;

@ParametersAreNonnullByDefault
public final class zzcfn
{
  /* Error */
  public static final zzcfb zza(android.content.Context paramContext, zzcgq paramzzcgq, String paramString, boolean paramBoolean1, boolean paramBoolean2, zzaqq paramzzaqq, zzbcm paramzzbcm, zzbzz paramzzbzz, zzbcc paramzzbcc, com.google.android.gms.ads.internal.zzl paramzzl, com.google.android.gms.ads.internal.zza paramzza, zzawx paramzzawx, zzezf paramzzezf, zzezi paramzzezi)
    throws zzcfm
  {
    // Byte code:
    //   0: aload_0
    //   1: invokestatic 19	com/google/android/gms/internal/ads/zzbbk:zza	(Landroid/content/Context;)V
    //   4: new 21	com/google/android/gms/internal/ads/zzcfj
    //   7: astore 8
    //   9: aload 8
    //   11: aload_0
    //   12: aload_1
    //   13: aload_2
    //   14: iload_3
    //   15: iload 4
    //   17: aload 5
    //   19: aload 6
    //   21: aload 7
    //   23: aconst_null
    //   24: aload 9
    //   26: aload 10
    //   28: aload 11
    //   30: aload 12
    //   32: aload 13
    //   34: invokespecial 24	com/google/android/gms/internal/ads/zzcfj:<init>	(Landroid/content/Context;Lcom/google/android/gms/internal/ads/zzcgq;Ljava/lang/String;ZZLcom/google/android/gms/internal/ads/zzaqq;Lcom/google/android/gms/internal/ads/zzbcm;Lcom/google/android/gms/internal/ads/zzbzz;Lcom/google/android/gms/internal/ads/zzbcc;Lcom/google/android/gms/ads/internal/zzl;Lcom/google/android/gms/ads/internal/zza;Lcom/google/android/gms/internal/ads/zzawx;Lcom/google/android/gms/internal/ads/zzezf;Lcom/google/android/gms/internal/ads/zzezi;)V
    //   37: invokestatic 30	android/os/StrictMode:getThreadPolicy	()Landroid/os/StrictMode$ThreadPolicy;
    //   40: astore_0
    //   41: new 32	android/os/StrictMode$ThreadPolicy$Builder
    //   44: astore_1
    //   45: aload_1
    //   46: aload_0
    //   47: invokespecial 35	android/os/StrictMode$ThreadPolicy$Builder:<init>	(Landroid/os/StrictMode$ThreadPolicy;)V
    //   50: aload_1
    //   51: invokevirtual 39	android/os/StrictMode$ThreadPolicy$Builder:permitDiskReads	()Landroid/os/StrictMode$ThreadPolicy$Builder;
    //   54: invokevirtual 42	android/os/StrictMode$ThreadPolicy$Builder:permitDiskWrites	()Landroid/os/StrictMode$ThreadPolicy$Builder;
    //   57: invokevirtual 45	android/os/StrictMode$ThreadPolicy$Builder:build	()Landroid/os/StrictMode$ThreadPolicy;
    //   60: invokestatic 48	android/os/StrictMode:setThreadPolicy	(Landroid/os/StrictMode$ThreadPolicy;)V
    //   63: aload 8
    //   65: invokeinterface 53 1 0
    //   70: astore_1
    //   71: aload_0
    //   72: invokestatic 48	android/os/StrictMode:setThreadPolicy	(Landroid/os/StrictMode$ThreadPolicy;)V
    //   75: aload_1
    //   76: areturn
    //   77: astore_1
    //   78: aload_0
    //   79: invokestatic 48	android/os/StrictMode:setThreadPolicy	(Landroid/os/StrictMode$ThreadPolicy;)V
    //   82: aload_1
    //   83: athrow
    //   84: astore_0
    //   85: new 14	com/google/android/gms/internal/ads/zzcfm
    //   88: dup
    //   89: ldc 55
    //   91: aload_0
    //   92: invokespecial 58	com/google/android/gms/internal/ads/zzcfm:<init>	(Ljava/lang/String;Ljava/lang/Throwable;)V
    //   95: athrow
    // Local variable table:
    //   start	length	slot	name	signature
    //   0	96	0	paramContext	android.content.Context
    //   0	96	1	paramzzcgq	zzcgq
    //   0	96	2	paramString	String
    //   0	96	3	paramBoolean1	boolean
    //   0	96	4	paramBoolean2	boolean
    //   0	96	5	paramzzaqq	zzaqq
    //   0	96	6	paramzzbcm	zzbcm
    //   0	96	7	paramzzbzz	zzbzz
    //   0	96	8	paramzzbcc	zzbcc
    //   0	96	9	paramzzl	com.google.android.gms.ads.internal.zzl
    //   0	96	10	paramzza	com.google.android.gms.ads.internal.zza
    //   0	96	11	paramzzawx	zzawx
    //   0	96	12	paramzzezf	zzezf
    //   0	96	13	paramzzezi	zzezi
    // Exception table:
    //   from	to	target	type
    //   41	71	77	finally
    //   4	41	84	finally
    //   71	75	84	finally
    //   78	84	84	finally
  }
}


/* Location:              C:\Users\Ria\Documents\slope apk\dex-tools-v2.4\classes-dex2jar.jar!\com\google\android\gms\internal\ads\zzcfn.class
 * Java compiler version: 6 (50.0)
 * JD-Core Version:       0.7.1
 */