package com.google.android.gms.internal.ads;

import android.content.Context;
import android.os.RemoteException;
import android.text.TextUtils;
import com.google.android.gms.ads.internal.client.zzba;
import com.google.android.gms.ads.internal.client.zzcn;
import com.google.android.gms.ads.internal.client.zzda;
import com.google.android.gms.ads.internal.client.zzff;
import com.google.android.gms.ads.internal.util.zzab;
import com.google.android.gms.ads.internal.util.zzas;
import com.google.android.gms.ads.internal.util.zzaw;
import com.google.android.gms.ads.internal.util.zzg;
import com.google.android.gms.ads.internal.util.zzs;
import com.google.android.gms.ads.internal.zze;
import com.google.android.gms.ads.internal.zzt;
import com.google.android.gms.dynamic.IObjectWrapper;
import com.google.android.gms.dynamic.ObjectWrapper;
import java.io.IOException;
import java.util.List;

public final class zzcll
  extends zzcn
{
  private final Context zza;
  private final zzbzz zzb;
  private final zzdnx zzc;
  private final zzebx zzd;
  private final zzeib zze;
  private final zzdse zzf;
  private final zzbxy zzg;
  private final zzdoc zzh;
  private final zzdsz zzi;
  private final zzbdx zzj;
  private final zzfft zzk;
  private final zzfat zzl;
  private final zzbbl zzm;
  private boolean zzn;
  
  zzcll(Context paramContext, zzbzz paramzzbzz, zzdnx paramzzdnx, zzebx paramzzebx, zzeib paramzzeib, zzdse paramzzdse, zzbxy paramzzbxy, zzdoc paramzzdoc, zzdsz paramzzdsz, zzbdx paramzzbdx, zzfft paramzzfft, zzfat paramzzfat, zzbbl paramzzbbl)
  {
    this.zza = paramContext;
    this.zzb = paramzzbzz;
    this.zzc = paramzzdnx;
    this.zzd = paramzzebx;
    this.zze = paramzzeib;
    this.zzf = paramzzdse;
    this.zzg = paramzzbxy;
    this.zzh = paramzzdoc;
    this.zzi = paramzzdsz;
    this.zzj = paramzzbdx;
    this.zzk = paramzzfft;
    this.zzl = paramzzfat;
    this.zzm = paramzzbbl;
    this.zzn = false;
  }
  
  final void zzb()
  {
    if (zzt.zzo().zzh().zzO())
    {
      String str = zzt.zzo().zzh().zzl();
      if (!zzt.zzs().zzj(this.zza, str, this.zzb.zza))
      {
        zzt.zzo().zzh().zzB(false);
        zzt.zzo().zzh().zzA("");
      }
    }
  }
  
  /* Error */
  final void zzc(Runnable paramRunnable)
  {
    // Byte code:
    //   0: ldc 115
    //   2: invokestatic 120	com/google/android/gms/common/internal/Preconditions:checkMainThread	(Ljava/lang/String;)V
    //   5: invokestatic 72	com/google/android/gms/ads/internal/zzt:zzo	()Lcom/google/android/gms/internal/ads/zzbzc;
    //   8: invokevirtual 77	com/google/android/gms/internal/ads/zzbzc:zzh	()Lcom/google/android/gms/ads/internal/util/zzg;
    //   11: invokeinterface 123 1 0
    //   16: invokevirtual 128	com/google/android/gms/internal/ads/zzbyw:zze	()Ljava/util/Map;
    //   19: astore_3
    //   20: aload_3
    //   21: invokeinterface 133 1 0
    //   26: ifeq +4 -> 30
    //   29: return
    //   30: aload_1
    //   31: ifnull +20 -> 51
    //   34: aload_1
    //   35: invokeinterface 138 1 0
    //   40: goto +11 -> 51
    //   43: astore_1
    //   44: ldc -116
    //   46: aload_1
    //   47: invokestatic 145	com/google/android/gms/internal/ads/zzbzt:zzk	(Ljava/lang/String;Ljava/lang/Throwable;)V
    //   50: return
    //   51: aload_0
    //   52: getfield 43	com/google/android/gms/internal/ads/zzcll:zzc	Lcom/google/android/gms/internal/ads/zzdnx;
    //   55: invokevirtual 149	com/google/android/gms/internal/ads/zzdnx:zzd	()Z
    //   58: ifne +4 -> 62
    //   61: return
    //   62: new 151	java/util/HashMap
    //   65: dup
    //   66: invokespecial 152	java/util/HashMap:<init>	()V
    //   69: astore_2
    //   70: aload_3
    //   71: invokeinterface 156 1 0
    //   76: invokeinterface 162 1 0
    //   81: astore_1
    //   82: aload_1
    //   83: invokeinterface 167 1 0
    //   88: ifeq +136 -> 224
    //   91: aload_1
    //   92: invokeinterface 171 1 0
    //   97: checkcast 173	com/google/android/gms/internal/ads/zzbnt
    //   100: getfield 176	com/google/android/gms/internal/ads/zzbnt:zza	Ljava/util/List;
    //   103: invokeinterface 179 1 0
    //   108: astore_3
    //   109: aload_3
    //   110: invokeinterface 167 1 0
    //   115: ifeq -33 -> 82
    //   118: aload_3
    //   119: invokeinterface 171 1 0
    //   124: checkcast 181	com/google/android/gms/internal/ads/zzbns
    //   127: astore 5
    //   129: aload 5
    //   131: getfield 183	com/google/android/gms/internal/ads/zzbns:zzk	Ljava/lang/String;
    //   134: astore 4
    //   136: aload 5
    //   138: getfield 185	com/google/android/gms/internal/ads/zzbns:zzc	Ljava/util/List;
    //   141: invokeinterface 179 1 0
    //   146: astore 6
    //   148: aload 6
    //   150: invokeinterface 167 1 0
    //   155: ifeq -46 -> 109
    //   158: aload 6
    //   160: invokeinterface 171 1 0
    //   165: checkcast 187	java/lang/String
    //   168: astore 5
    //   170: aload_2
    //   171: aload 5
    //   173: invokeinterface 191 2 0
    //   178: ifne +19 -> 197
    //   181: aload_2
    //   182: aload 5
    //   184: new 193	java/util/ArrayList
    //   187: dup
    //   188: invokespecial 194	java/util/ArrayList:<init>	()V
    //   191: invokeinterface 198 3 0
    //   196: pop
    //   197: aload 4
    //   199: ifnull -51 -> 148
    //   202: aload_2
    //   203: aload 5
    //   205: invokeinterface 202 2 0
    //   210: checkcast 178	java/util/List
    //   213: aload 4
    //   215: invokeinterface 205 2 0
    //   220: pop
    //   221: goto -73 -> 148
    //   224: new 207	org/json/JSONObject
    //   227: dup
    //   228: invokespecial 208	org/json/JSONObject:<init>	()V
    //   231: astore_1
    //   232: aload_2
    //   233: invokeinterface 212 1 0
    //   238: invokeinterface 215 1 0
    //   243: astore_2
    //   244: aload_2
    //   245: invokeinterface 167 1 0
    //   250: ifeq +189 -> 439
    //   253: aload_2
    //   254: invokeinterface 171 1 0
    //   259: checkcast 217	java/util/Map$Entry
    //   262: astore 5
    //   264: aload 5
    //   266: invokeinterface 220 1 0
    //   271: checkcast 187	java/lang/String
    //   274: astore_3
    //   275: aload_0
    //   276: getfield 45	com/google/android/gms/internal/ads/zzcll:zzd	Lcom/google/android/gms/internal/ads/zzebx;
    //   279: aload_3
    //   280: aload_1
    //   281: invokeinterface 225 3 0
    //   286: astore 6
    //   288: aload 6
    //   290: ifnull -46 -> 244
    //   293: aload 6
    //   295: getfield 230	com/google/android/gms/internal/ads/zzeby:zzb	Ljava/lang/Object;
    //   298: checkcast 232	com/google/android/gms/internal/ads/zzfav
    //   301: astore 4
    //   303: aload 4
    //   305: invokevirtual 235	com/google/android/gms/internal/ads/zzfav:zzC	()Z
    //   308: ifne -64 -> 244
    //   311: aload 4
    //   313: invokevirtual 237	com/google/android/gms/internal/ads/zzfav:zzB	()Z
    //   316: ifeq -72 -> 244
    //   319: aload 6
    //   321: getfield 240	com/google/android/gms/internal/ads/zzeby:zzc	Lcom/google/android/gms/internal/ads/zzcws;
    //   324: checkcast 242	com/google/android/gms/internal/ads/zzeds
    //   327: astore 6
    //   329: aload 5
    //   331: invokeinterface 245 1 0
    //   336: checkcast 178	java/util/List
    //   339: astore 5
    //   341: aload 4
    //   343: aload_0
    //   344: getfield 39	com/google/android/gms/internal/ads/zzcll:zza	Landroid/content/Context;
    //   347: aload 6
    //   349: aload 5
    //   351: invokevirtual 248	com/google/android/gms/internal/ads/zzfav:zzj	(Landroid/content/Context;Lcom/google/android/gms/internal/ads/zzbvh;Ljava/util/List;)V
    //   354: new 250	java/lang/StringBuilder
    //   357: astore 4
    //   359: aload 4
    //   361: invokespecial 251	java/lang/StringBuilder:<init>	()V
    //   364: aload 4
    //   366: ldc -3
    //   368: invokevirtual 257	java/lang/StringBuilder:append	(Ljava/lang/String;)Ljava/lang/StringBuilder;
    //   371: pop
    //   372: aload 4
    //   374: aload_3
    //   375: invokevirtual 257	java/lang/StringBuilder:append	(Ljava/lang/String;)Ljava/lang/StringBuilder;
    //   378: pop
    //   379: aload 4
    //   381: invokevirtual 260	java/lang/StringBuilder:toString	()Ljava/lang/String;
    //   384: invokestatic 262	com/google/android/gms/internal/ads/zzbzt:zze	(Ljava/lang/String;)V
    //   387: goto -143 -> 244
    //   390: astore 4
    //   392: new 250	java/lang/StringBuilder
    //   395: dup
    //   396: invokespecial 251	java/lang/StringBuilder:<init>	()V
    //   399: astore 5
    //   401: aload 5
    //   403: ldc_w 264
    //   406: invokevirtual 257	java/lang/StringBuilder:append	(Ljava/lang/String;)Ljava/lang/StringBuilder;
    //   409: pop
    //   410: aload 5
    //   412: aload_3
    //   413: invokevirtual 257	java/lang/StringBuilder:append	(Ljava/lang/String;)Ljava/lang/StringBuilder;
    //   416: pop
    //   417: aload 5
    //   419: ldc_w 266
    //   422: invokevirtual 257	java/lang/StringBuilder:append	(Ljava/lang/String;)Ljava/lang/StringBuilder;
    //   425: pop
    //   426: aload 5
    //   428: invokevirtual 260	java/lang/StringBuilder:toString	()Ljava/lang/String;
    //   431: aload 4
    //   433: invokestatic 145	com/google/android/gms/internal/ads/zzbzt:zzk	(Ljava/lang/String;Ljava/lang/Throwable;)V
    //   436: goto -192 -> 244
    //   439: return
    // Local variable table:
    //   start	length	slot	name	signature
    //   0	440	0	this	zzcll
    //   0	440	1	paramRunnable	Runnable
    //   69	185	2	localObject1	Object
    //   19	394	3	localObject2	Object
    //   134	246	4	localObject3	Object
    //   390	42	4	localzzfaf	zzfaf
    //   127	300	5	localObject4	Object
    //   146	202	6	localObject5	Object
    // Exception table:
    //   from	to	target	type
    //   34	40	43	finally
    //   275	288	390	com/google/android/gms/internal/ads/zzfaf
    //   293	387	390	com/google/android/gms/internal/ads/zzfaf
  }
  
  public final float zze()
  {
    try
    {
      float f = zzt.zzr().zza();
      return f;
    }
    finally
    {
      localObject = finally;
      throw ((Throwable)localObject);
    }
  }
  
  public final String zzf()
  {
    return this.zzb.zza;
  }
  
  public final List zzg()
    throws RemoteException
  {
    return this.zzf.zzg();
  }
  
  public final void zzh(String paramString)
  {
    this.zze.zzf(paramString);
  }
  
  public final void zzi()
  {
    this.zzf.zzl();
  }
  
  public final void zzj(boolean paramBoolean)
    throws RemoteException
  {
    try
    {
      zzfma.zzi(this.zza).zzn(paramBoolean);
      return;
    }
    catch (IOException localIOException)
    {
      throw new RemoteException(localIOException.getMessage());
    }
  }
  
  public final void zzk()
  {
    try
    {
      if (this.zzn)
      {
        zzbzt.zzj("Mobile ads is initialized already.");
        return;
      }
      zzbbk.zza(this.zza);
      this.zzm.zza();
      zzt.zzo().zzs(this.zza, this.zzb);
      zzt.zzc().zzi(this.zza);
      this.zzn = true;
      this.zzf.zzr();
      this.zze.zzd();
      Object localObject1 = zzbbk.zzdI;
      if (((Boolean)zzba.zzc().zzb((zzbbc)localObject1)).booleanValue()) {
        this.zzh.zzc();
      }
      this.zzi.zzg();
      localObject1 = zzbbk.zziG;
      Object localObject3;
      if (((Boolean)zzba.zzc().zzb((zzbbc)localObject1)).booleanValue())
      {
        localObject3 = zzcag.zza;
        localObject1 = new com/google/android/gms/internal/ads/zzclh;
        ((zzclh)localObject1).<init>(this);
        ((zzfwc)localObject3).execute((Runnable)localObject1);
      }
      localObject1 = zzbbk.zzju;
      if (((Boolean)zzba.zzc().zzb((zzbbc)localObject1)).booleanValue())
      {
        localObject1 = zzcag.zza;
        localObject3 = new com/google/android/gms/internal/ads/zzclg;
        ((zzclg)localObject3).<init>(this);
        ((zzfwc)localObject1).execute((Runnable)localObject3);
      }
      localObject1 = zzbbk.zzcy;
      if (((Boolean)zzba.zzc().zzb((zzbbc)localObject1)).booleanValue())
      {
        localObject3 = zzcag.zza;
        localObject1 = new com/google/android/gms/internal/ads/zzcli;
        ((zzcli)localObject1).<init>(this);
        ((zzfwc)localObject3).execute((Runnable)localObject1);
        return;
      }
      return;
    }
    finally {}
  }
  
  public final void zzl(String paramString, IObjectWrapper paramIObjectWrapper)
  {
    zzbbk.zza(this.zza);
    Object localObject = zzbbk.zzdM;
    if (((Boolean)zzba.zzc().zzb((zzbbc)localObject)).booleanValue())
    {
      zzt.zzp();
      localObject = zzs.zzn(this.zza);
    }
    else
    {
      localObject = "";
    }
    boolean bool1 = TextUtils.isEmpty((CharSequence)localObject);
    int i = 1;
    if (true != bool1) {
      paramString = (String)localObject;
    }
    if (TextUtils.isEmpty(paramString)) {
      return;
    }
    localObject = zzbbk.zzdH;
    bool1 = ((Boolean)zzba.zzc().zzb((zzbbc)localObject)).booleanValue();
    localObject = zzbbk.zzaN;
    boolean bool2 = ((Boolean)zzba.zzc().zzb((zzbbc)localObject)).booleanValue();
    localObject = zzbbk.zzaN;
    if (((Boolean)zzba.zzc().zzb((zzbbc)localObject)).booleanValue())
    {
      paramIObjectWrapper = new zzclj(this, (Runnable)ObjectWrapper.unwrap(paramIObjectWrapper));
    }
    else
    {
      paramIObjectWrapper = null;
      i = bool1 | bool2;
    }
    if (i != 0) {
      zzt.zza().zza(this.zza, this.zzb, paramString, paramIObjectWrapper, this.zzk);
    }
  }
  
  public final void zzm(zzda paramzzda)
    throws RemoteException
  {
    this.zzi.zzh(paramzzda, zzdsy.zzb);
  }
  
  public final void zzn(IObjectWrapper paramIObjectWrapper, String paramString)
  {
    if (paramIObjectWrapper == null)
    {
      zzbzt.zzg("Wrapped context is null. Failed to open debug menu.");
      return;
    }
    paramIObjectWrapper = (Context)ObjectWrapper.unwrap(paramIObjectWrapper);
    if (paramIObjectWrapper == null)
    {
      zzbzt.zzg("Context is null. Failed to open debug menu.");
      return;
    }
    paramIObjectWrapper = new zzas(paramIObjectWrapper);
    paramIObjectWrapper.zzn(paramString);
    paramIObjectWrapper.zzo(this.zzb.zza);
    paramIObjectWrapper.zzr();
  }
  
  public final void zzo(zzbny paramzzbny)
    throws RemoteException
  {
    this.zzl.zze(paramzzbny);
  }
  
  public final void zzp(boolean paramBoolean)
  {
    try
    {
      zzt.zzr().zzc(paramBoolean);
      return;
    }
    finally
    {
      localObject = finally;
      throw ((Throwable)localObject);
    }
  }
  
  public final void zzq(float paramFloat)
  {
    try
    {
      zzt.zzr().zzd(paramFloat);
      return;
    }
    finally
    {
      localObject = finally;
      throw ((Throwable)localObject);
    }
  }
  
  public final void zzr(String paramString)
  {
    try
    {
      zzbbk.zza(this.zza);
      if (!TextUtils.isEmpty(paramString))
      {
        zzbbc localzzbbc = zzbbk.zzdH;
        if (((Boolean)zzba.zzc().zzb(localzzbbc)).booleanValue())
        {
          zzt.zza().zza(this.zza, this.zzb, paramString, null, this.zzk);
          return;
        }
      }
      return;
    }
    finally
    {
      paramString = finally;
      throw paramString;
    }
  }
  
  public final void zzs(zzbkl paramzzbkl)
    throws RemoteException
  {
    this.zzf.zzs(paramzzbkl);
  }
  
  public final void zzt(String paramString)
  {
    zzbbc localzzbbc = zzbbk.zziP;
    if (((Boolean)zzba.zzc().zzb(localzzbbc)).booleanValue()) {
      zzt.zzo().zzw(paramString);
    }
  }
  
  public final void zzu(zzff paramzzff)
    throws RemoteException
  {
    this.zzg.zzq(this.zza, paramzzff);
  }
  
  public final boolean zzv()
  {
    try
    {
      boolean bool = zzt.zzr().zze();
      return bool;
    }
    finally
    {
      localObject = finally;
      throw ((Throwable)localObject);
    }
  }
}


/* Location:              C:\Users\Ria\Documents\slope apk\dex-tools-v2.4\classes-dex2jar.jar!\com\google\android\gms\internal\ads\zzcll.class
 * Java compiler version: 6 (50.0)
 * JD-Core Version:       0.7.1
 */