package com.google.android.gms.internal.ads;

import android.content.Context;

public final class zzdyx
  implements zzfdg
{
  protected final Context zza;
  protected final String zzb;
  protected final zzbus zzc;
  
  public zzdyx(Context paramContext, String paramString, zzbus paramzzbus, int paramInt)
  {
    this.zza = paramContext;
    this.zzb = paramString;
    this.zzc = paramzzbus;
  }
  
  /* Error */
  public final zzdyw zzb(zzdyv paramzzdyv)
    throws zzdtz
  {
    // Byte code:
    //   0: aload_1
    //   1: getfield 39	com/google/android/gms/internal/ads/zzdyv:zza	Ljava/lang/String;
    //   4: astore 7
    //   6: aload_1
    //   7: getfield 42	com/google/android/gms/internal/ads/zzdyv:zzb	I
    //   10: istore_3
    //   11: aload_1
    //   12: getfield 45	com/google/android/gms/internal/ads/zzdyv:zzc	Ljava/util/Map;
    //   15: astore 13
    //   17: aload_1
    //   18: getfield 49	com/google/android/gms/internal/ads/zzdyv:zzd	[B
    //   21: astore 11
    //   23: aload_1
    //   24: getfield 52	com/google/android/gms/internal/ads/zzdyv:zze	Ljava/lang/String;
    //   27: astore 14
    //   29: invokestatic 58	com/google/android/gms/ads/internal/zzt:zzB	()Lcom/google/android/gms/common/util/Clock;
    //   32: invokeinterface 64 1 0
    //   37: lstore 5
    //   39: new 66	com/google/android/gms/internal/ads/zzdyw
    //   42: astore 10
    //   44: aload 10
    //   46: invokespecial 67	com/google/android/gms/internal/ads/zzdyw:<init>	()V
    //   49: aload_0
    //   50: getfield 21	com/google/android/gms/internal/ads/zzdyx:zzb	Ljava/lang/String;
    //   53: astore 8
    //   55: new 69	java/lang/StringBuilder
    //   58: astore_1
    //   59: aload_1
    //   60: invokespecial 70	java/lang/StringBuilder:<init>	()V
    //   63: aload_1
    //   64: ldc 72
    //   66: invokevirtual 76	java/lang/StringBuilder:append	(Ljava/lang/String;)Ljava/lang/StringBuilder;
    //   69: pop
    //   70: aload_1
    //   71: aload 8
    //   73: invokevirtual 76	java/lang/StringBuilder:append	(Ljava/lang/String;)Ljava/lang/StringBuilder;
    //   76: pop
    //   77: aload_1
    //   78: invokevirtual 80	java/lang/StringBuilder:toString	()Ljava/lang/String;
    //   81: invokestatic 86	com/google/android/gms/internal/ads/zzbzt:zzi	(Ljava/lang/String;)V
    //   84: new 69	java/lang/StringBuilder
    //   87: astore_1
    //   88: aload_1
    //   89: invokespecial 70	java/lang/StringBuilder:<init>	()V
    //   92: aload_1
    //   93: ldc 88
    //   95: invokevirtual 76	java/lang/StringBuilder:append	(Ljava/lang/String;)Ljava/lang/StringBuilder;
    //   98: pop
    //   99: aload_1
    //   100: aload 7
    //   102: invokevirtual 76	java/lang/StringBuilder:append	(Ljava/lang/String;)Ljava/lang/StringBuilder;
    //   105: pop
    //   106: aload_1
    //   107: invokevirtual 80	java/lang/StringBuilder:toString	()Ljava/lang/String;
    //   110: invokestatic 90	com/google/android/gms/internal/ads/zzbzt:zze	(Ljava/lang/String;)V
    //   113: new 92	java/net/URL
    //   116: astore_1
    //   117: aload_1
    //   118: aload 7
    //   120: invokespecial 94	java/net/URL:<init>	(Ljava/lang/String;)V
    //   123: new 96	java/util/HashMap
    //   126: astore 15
    //   128: aload 15
    //   130: invokespecial 97	java/util/HashMap:<init>	()V
    //   133: iconst_0
    //   134: istore_2
    //   135: aload_1
    //   136: invokevirtual 101	java/net/URL:openConnection	()Ljava/net/URLConnection;
    //   139: checkcast 103	java/net/HttpURLConnection
    //   142: astore 9
    //   144: invokestatic 107	com/google/android/gms/ads/internal/zzt:zzp	()Lcom/google/android/gms/ads/internal/util/zzs;
    //   147: astore 12
    //   149: aload_0
    //   150: getfield 19	com/google/android/gms/internal/ads/zzdyx:zza	Landroid/content/Context;
    //   153: astore 16
    //   155: aload_0
    //   156: getfield 21	com/google/android/gms/internal/ads/zzdyx:zzb	Ljava/lang/String;
    //   159: astore 17
    //   161: aload 9
    //   163: astore_1
    //   164: aload_1
    //   165: astore 7
    //   167: aload_1
    //   168: astore 8
    //   170: aload 12
    //   172: aload 16
    //   174: aload 17
    //   176: iconst_0
    //   177: aload 9
    //   179: iconst_0
    //   180: iload_3
    //   181: invokevirtual 113	com/google/android/gms/ads/internal/util/zzs:zzf	(Landroid/content/Context;Ljava/lang/String;ZLjava/net/HttpURLConnection;ZI)V
    //   184: aload_1
    //   185: astore 7
    //   187: aload_1
    //   188: astore 8
    //   190: aload 13
    //   192: invokeinterface 119 1 0
    //   197: invokeinterface 125 1 0
    //   202: astore 9
    //   204: aload_1
    //   205: astore 7
    //   207: aload_1
    //   208: astore 8
    //   210: aload 9
    //   212: invokeinterface 131 1 0
    //   217: ifeq +79 -> 296
    //   220: aload_1
    //   221: astore 7
    //   223: aload_1
    //   224: astore 8
    //   226: aload 9
    //   228: invokeinterface 135 1 0
    //   233: checkcast 137	java/util/Map$Entry
    //   236: astore 16
    //   238: aload_1
    //   239: astore 7
    //   241: aload_1
    //   242: astore 8
    //   244: aload 16
    //   246: invokeinterface 140 1 0
    //   251: checkcast 142	java/lang/String
    //   254: astore 12
    //   256: aload_1
    //   257: astore 7
    //   259: aload_1
    //   260: astore 8
    //   262: aload 16
    //   264: invokeinterface 145 1 0
    //   269: checkcast 142	java/lang/String
    //   272: astore 16
    //   274: aload_1
    //   275: astore 7
    //   277: aload 7
    //   279: astore 8
    //   281: aload 7
    //   283: aload 12
    //   285: aload 16
    //   287: invokevirtual 149	java/net/HttpURLConnection:addRequestProperty	(Ljava/lang/String;Ljava/lang/String;)V
    //   290: aload 7
    //   292: astore_1
    //   293: goto -89 -> 204
    //   296: aload_1
    //   297: astore 7
    //   299: aload 7
    //   301: astore 8
    //   303: aload 14
    //   305: invokestatic 155	android/text/TextUtils:isEmpty	(Ljava/lang/CharSequence;)Z
    //   308: ifne +16 -> 324
    //   311: aload 7
    //   313: astore 8
    //   315: aload 7
    //   317: ldc -99
    //   319: aload 14
    //   321: invokevirtual 160	java/net/HttpURLConnection:setRequestProperty	(Ljava/lang/String;Ljava/lang/String;)V
    //   324: aload 7
    //   326: astore 8
    //   328: aload 11
    //   330: arraylength
    //   331: istore 4
    //   333: aconst_null
    //   334: astore 9
    //   336: iload 4
    //   338: ifle +85 -> 423
    //   341: aload 7
    //   343: astore 8
    //   345: aload 7
    //   347: iconst_1
    //   348: invokevirtual 164	java/net/HttpURLConnection:setDoOutput	(Z)V
    //   351: aload 7
    //   353: astore 8
    //   355: aload 7
    //   357: iload 4
    //   359: invokevirtual 168	java/net/HttpURLConnection:setFixedLengthStreamingMode	(I)V
    //   362: new 170	java/io/BufferedOutputStream
    //   365: astore 12
    //   367: aload 12
    //   369: aload 7
    //   371: invokevirtual 174	java/net/HttpURLConnection:getOutputStream	()Ljava/io/OutputStream;
    //   374: invokespecial 177	java/io/BufferedOutputStream:<init>	(Ljava/io/OutputStream;)V
    //   377: aload 12
    //   379: aload 11
    //   381: invokevirtual 181	java/io/BufferedOutputStream:write	([B)V
    //   384: aload 7
    //   386: astore 8
    //   388: aload 12
    //   390: invokestatic 187	com/google/android/gms/common/util/IOUtils:closeQuietly	(Ljava/io/Closeable;)V
    //   393: goto +30 -> 423
    //   396: astore 11
    //   398: aload 12
    //   400: astore 9
    //   402: goto +5 -> 407
    //   405: astore 11
    //   407: aload 7
    //   409: astore 8
    //   411: aload 9
    //   413: invokestatic 187	com/google/android/gms/common/util/IOUtils:closeQuietly	(Ljava/io/Closeable;)V
    //   416: aload 7
    //   418: astore 8
    //   420: aload 11
    //   422: athrow
    //   423: aload 7
    //   425: astore 8
    //   427: new 189	com/google/android/gms/internal/ads/zzbzs
    //   430: astore 9
    //   432: aload 7
    //   434: astore 8
    //   436: aload 9
    //   438: aconst_null
    //   439: invokespecial 190	com/google/android/gms/internal/ads/zzbzs:<init>	(Ljava/lang/String;)V
    //   442: aload 7
    //   444: astore 8
    //   446: aload 9
    //   448: aload 7
    //   450: aload 11
    //   452: invokevirtual 193	com/google/android/gms/internal/ads/zzbzs:zzc	(Ljava/net/HttpURLConnection;[B)V
    //   455: aload 7
    //   457: astore 8
    //   459: aload 7
    //   461: invokevirtual 197	java/net/HttpURLConnection:getResponseCode	()I
    //   464: istore 4
    //   466: aload 7
    //   468: astore 8
    //   470: aload 7
    //   472: invokevirtual 201	java/net/HttpURLConnection:getHeaderFields	()Ljava/util/Map;
    //   475: invokeinterface 119 1 0
    //   480: invokeinterface 125 1 0
    //   485: astore 12
    //   487: aload 7
    //   489: astore 8
    //   491: aload 12
    //   493: invokeinterface 131 1 0
    //   498: ifeq +133 -> 631
    //   501: aload 7
    //   503: astore 8
    //   505: aload 12
    //   507: invokeinterface 135 1 0
    //   512: checkcast 137	java/util/Map$Entry
    //   515: astore 17
    //   517: aload 7
    //   519: astore 8
    //   521: aload 17
    //   523: invokeinterface 140 1 0
    //   528: checkcast 142	java/lang/String
    //   531: astore 16
    //   533: aload 7
    //   535: astore 8
    //   537: aload 17
    //   539: invokeinterface 145 1 0
    //   544: checkcast 203	java/util/List
    //   547: astore 17
    //   549: aload 7
    //   551: astore 8
    //   553: aload 15
    //   555: aload 16
    //   557: invokeinterface 207 2 0
    //   562: ifeq +30 -> 592
    //   565: aload 7
    //   567: astore 8
    //   569: aload 15
    //   571: aload 16
    //   573: invokeinterface 210 2 0
    //   578: checkcast 203	java/util/List
    //   581: aload 17
    //   583: invokeinterface 214 2 0
    //   588: pop
    //   589: goto -102 -> 487
    //   592: aload 7
    //   594: astore 8
    //   596: new 216	java/util/ArrayList
    //   599: astore 18
    //   601: aload 7
    //   603: astore 8
    //   605: aload 18
    //   607: aload 17
    //   609: invokespecial 219	java/util/ArrayList:<init>	(Ljava/util/Collection;)V
    //   612: aload 7
    //   614: astore 8
    //   616: aload 15
    //   618: aload 16
    //   620: aload 18
    //   622: invokeinterface 223 3 0
    //   627: pop
    //   628: goto -141 -> 487
    //   631: aload 7
    //   633: astore 8
    //   635: aload 9
    //   637: aload 7
    //   639: iload 4
    //   641: invokevirtual 226	com/google/android/gms/internal/ads/zzbzs:zze	(Ljava/net/HttpURLConnection;I)V
    //   644: aload 7
    //   646: astore 8
    //   648: aload 10
    //   650: iload 4
    //   652: putfield 228	com/google/android/gms/internal/ads/zzdyw:zza	I
    //   655: aload 7
    //   657: astore 8
    //   659: aload 10
    //   661: aload 15
    //   663: putfield 230	com/google/android/gms/internal/ads/zzdyw:zzb	Ljava/util/Map;
    //   666: aload 7
    //   668: astore 8
    //   670: aload 10
    //   672: ldc -24
    //   674: putfield 234	com/google/android/gms/internal/ads/zzdyw:zzc	Ljava/lang/String;
    //   677: iload 4
    //   679: sipush 200
    //   682: if_icmplt +184 -> 866
    //   685: iload 4
    //   687: sipush 300
    //   690: if_icmpge +176 -> 866
    //   693: new 236	java/io/InputStreamReader
    //   696: astore_1
    //   697: aload_1
    //   698: aload 7
    //   700: invokevirtual 240	java/net/HttpURLConnection:getInputStream	()Ljava/io/InputStream;
    //   703: invokespecial 243	java/io/InputStreamReader:<init>	(Ljava/io/InputStream;)V
    //   706: invokestatic 107	com/google/android/gms/ads/internal/zzt:zzp	()Lcom/google/android/gms/ads/internal/util/zzs;
    //   709: pop
    //   710: aload_1
    //   711: invokestatic 247	com/google/android/gms/ads/internal/util/zzs:zzJ	(Ljava/io/InputStreamReader;)Ljava/lang/String;
    //   714: astore 11
    //   716: aload 7
    //   718: astore 8
    //   720: aload_1
    //   721: invokestatic 187	com/google/android/gms/common/util/IOUtils:closeQuietly	(Ljava/io/Closeable;)V
    //   724: aload 7
    //   726: astore 8
    //   728: aload 9
    //   730: aload 11
    //   732: invokevirtual 250	com/google/android/gms/internal/ads/zzbzs:zzg	(Ljava/lang/String;)V
    //   735: aload 7
    //   737: astore 8
    //   739: aload 10
    //   741: aload 11
    //   743: putfield 234	com/google/android/gms/internal/ads/zzdyw:zzc	Ljava/lang/String;
    //   746: aload 7
    //   748: astore 8
    //   750: aload 11
    //   752: invokestatic 155	android/text/TextUtils:isEmpty	(Ljava/lang/CharSequence;)Z
    //   755: ifeq +57 -> 812
    //   758: aload 7
    //   760: astore 8
    //   762: getstatic 256	com/google/android/gms/internal/ads/zzbbk:zzfh	Lcom/google/android/gms/internal/ads/zzbbc;
    //   765: astore_1
    //   766: aload 7
    //   768: astore 8
    //   770: invokestatic 261	com/google/android/gms/ads/internal/client/zzba:zzc	()Lcom/google/android/gms/internal/ads/zzbbi;
    //   773: aload_1
    //   774: invokevirtual 266	com/google/android/gms/internal/ads/zzbbi:zzb	(Lcom/google/android/gms/internal/ads/zzbbc;)Ljava/lang/Object;
    //   777: checkcast 268	java/lang/Boolean
    //   780: invokevirtual 271	java/lang/Boolean:booleanValue	()Z
    //   783: ifeq +6 -> 789
    //   786: goto +26 -> 812
    //   789: aload 7
    //   791: astore 8
    //   793: new 35	com/google/android/gms/internal/ads/zzdtz
    //   796: astore_1
    //   797: aload 7
    //   799: astore 8
    //   801: aload_1
    //   802: iconst_3
    //   803: invokespecial 273	com/google/android/gms/internal/ads/zzdtz:<init>	(I)V
    //   806: aload 7
    //   808: astore 8
    //   810: aload_1
    //   811: athrow
    //   812: aload 7
    //   814: astore 8
    //   816: aload 10
    //   818: invokestatic 58	com/google/android/gms/ads/internal/zzt:zzB	()Lcom/google/android/gms/common/util/Clock;
    //   821: invokeinterface 64 1 0
    //   826: lload 5
    //   828: lsub
    //   829: putfield 276	com/google/android/gms/internal/ads/zzdyw:zzd	J
    //   832: aload 7
    //   834: astore_1
    //   835: aload_1
    //   836: invokevirtual 279	java/net/HttpURLConnection:disconnect	()V
    //   839: goto +422 -> 1261
    //   842: astore 9
    //   844: goto +7 -> 851
    //   847: astore 9
    //   849: aconst_null
    //   850: astore_1
    //   851: aload 7
    //   853: astore 8
    //   855: aload_1
    //   856: invokestatic 187	com/google/android/gms/common/util/IOUtils:closeQuietly	(Ljava/io/Closeable;)V
    //   859: aload 7
    //   861: astore 8
    //   863: aload 9
    //   865: athrow
    //   866: iload 4
    //   868: sipush 300
    //   871: if_icmplt +173 -> 1044
    //   874: iload 4
    //   876: sipush 400
    //   879: if_icmpge +165 -> 1044
    //   882: aload 7
    //   884: astore 8
    //   886: aload 7
    //   888: ldc_w 281
    //   891: invokevirtual 285	java/net/HttpURLConnection:getHeaderField	(Ljava/lang/String;)Ljava/lang/String;
    //   894: astore 9
    //   896: aload 7
    //   898: astore 8
    //   900: aload 9
    //   902: invokestatic 155	android/text/TextUtils:isEmpty	(Ljava/lang/CharSequence;)Z
    //   905: ifne +103 -> 1008
    //   908: aload 7
    //   910: astore 8
    //   912: new 92	java/net/URL
    //   915: astore_1
    //   916: aload 7
    //   918: astore 8
    //   920: aload_1
    //   921: aload 9
    //   923: invokespecial 94	java/net/URL:<init>	(Ljava/lang/String;)V
    //   926: iinc 2 1
    //   929: aload 7
    //   931: astore 8
    //   933: getstatic 288	com/google/android/gms/internal/ads/zzbbk:zzeJ	Lcom/google/android/gms/internal/ads/zzbbc;
    //   936: astore 9
    //   938: aload 7
    //   940: astore 8
    //   942: invokestatic 261	com/google/android/gms/ads/internal/client/zzba:zzc	()Lcom/google/android/gms/internal/ads/zzbbi;
    //   945: aload 9
    //   947: invokevirtual 266	com/google/android/gms/internal/ads/zzbbi:zzb	(Lcom/google/android/gms/internal/ads/zzbbc;)Ljava/lang/Object;
    //   950: checkcast 290	java/lang/Integer
    //   953: invokevirtual 293	java/lang/Integer:intValue	()I
    //   956: istore 4
    //   958: iload_2
    //   959: iload 4
    //   961: if_icmpgt +11 -> 972
    //   964: aload 7
    //   966: invokevirtual 279	java/net/HttpURLConnection:disconnect	()V
    //   969: goto -834 -> 135
    //   972: aload 7
    //   974: astore 8
    //   976: ldc_w 295
    //   979: invokestatic 298	com/google/android/gms/internal/ads/zzbzt:zzj	(Ljava/lang/String;)V
    //   982: aload 7
    //   984: astore 8
    //   986: new 35	com/google/android/gms/internal/ads/zzdtz
    //   989: astore_1
    //   990: aload 7
    //   992: astore 8
    //   994: aload_1
    //   995: iconst_1
    //   996: ldc_w 300
    //   999: invokespecial 303	com/google/android/gms/internal/ads/zzdtz:<init>	(ILjava/lang/String;)V
    //   1002: aload 7
    //   1004: astore 8
    //   1006: aload_1
    //   1007: athrow
    //   1008: aload 7
    //   1010: astore 8
    //   1012: ldc_w 305
    //   1015: invokestatic 298	com/google/android/gms/internal/ads/zzbzt:zzj	(Ljava/lang/String;)V
    //   1018: aload 7
    //   1020: astore 8
    //   1022: new 35	com/google/android/gms/internal/ads/zzdtz
    //   1025: astore_1
    //   1026: aload 7
    //   1028: astore 8
    //   1030: aload_1
    //   1031: iconst_1
    //   1032: ldc_w 307
    //   1035: invokespecial 303	com/google/android/gms/internal/ads/zzdtz:<init>	(ILjava/lang/String;)V
    //   1038: aload 7
    //   1040: astore 8
    //   1042: aload_1
    //   1043: athrow
    //   1044: aload 7
    //   1046: astore 8
    //   1048: new 69	java/lang/StringBuilder
    //   1051: astore_1
    //   1052: aload 7
    //   1054: astore 8
    //   1056: aload_1
    //   1057: invokespecial 70	java/lang/StringBuilder:<init>	()V
    //   1060: aload 7
    //   1062: astore 8
    //   1064: aload_1
    //   1065: ldc_w 309
    //   1068: invokevirtual 76	java/lang/StringBuilder:append	(Ljava/lang/String;)Ljava/lang/StringBuilder;
    //   1071: pop
    //   1072: aload 7
    //   1074: astore 8
    //   1076: aload_1
    //   1077: iload 4
    //   1079: invokevirtual 312	java/lang/StringBuilder:append	(I)Ljava/lang/StringBuilder;
    //   1082: pop
    //   1083: aload 7
    //   1085: astore 8
    //   1087: aload_1
    //   1088: invokevirtual 80	java/lang/StringBuilder:toString	()Ljava/lang/String;
    //   1091: invokestatic 298	com/google/android/gms/internal/ads/zzbzt:zzj	(Ljava/lang/String;)V
    //   1094: aload 7
    //   1096: astore 8
    //   1098: new 35	com/google/android/gms/internal/ads/zzdtz
    //   1101: astore_1
    //   1102: aload 7
    //   1104: astore 8
    //   1106: new 69	java/lang/StringBuilder
    //   1109: astore 9
    //   1111: aload 7
    //   1113: astore 8
    //   1115: aload 9
    //   1117: invokespecial 70	java/lang/StringBuilder:<init>	()V
    //   1120: aload 7
    //   1122: astore 8
    //   1124: aload 9
    //   1126: ldc_w 309
    //   1129: invokevirtual 76	java/lang/StringBuilder:append	(Ljava/lang/String;)Ljava/lang/StringBuilder;
    //   1132: pop
    //   1133: aload 7
    //   1135: astore 8
    //   1137: aload 9
    //   1139: iload 4
    //   1141: invokevirtual 312	java/lang/StringBuilder:append	(I)Ljava/lang/StringBuilder;
    //   1144: pop
    //   1145: aload 7
    //   1147: astore 8
    //   1149: aload_1
    //   1150: iconst_1
    //   1151: aload 9
    //   1153: invokevirtual 80	java/lang/StringBuilder:toString	()Ljava/lang/String;
    //   1156: invokespecial 303	com/google/android/gms/internal/ads/zzdtz:<init>	(ILjava/lang/String;)V
    //   1159: aload 7
    //   1161: astore 8
    //   1163: aload_1
    //   1164: athrow
    //   1165: astore 9
    //   1167: aload 7
    //   1169: astore_1
    //   1170: goto +41 -> 1211
    //   1173: astore 9
    //   1175: goto +16 -> 1191
    //   1178: astore_1
    //   1179: aload 7
    //   1181: astore 8
    //   1183: goto +88 -> 1271
    //   1186: astore 9
    //   1188: aload 8
    //   1190: astore_1
    //   1191: goto +20 -> 1211
    //   1194: astore_1
    //   1195: aload 9
    //   1197: astore 8
    //   1199: goto +72 -> 1271
    //   1202: astore 7
    //   1204: aload 9
    //   1206: astore_1
    //   1207: aload 7
    //   1209: astore 9
    //   1211: aload_1
    //   1212: astore 8
    //   1214: getstatic 315	com/google/android/gms/internal/ads/zzbbk:zzhP	Lcom/google/android/gms/internal/ads/zzbbc;
    //   1217: astore 7
    //   1219: aload_1
    //   1220: astore 8
    //   1222: invokestatic 261	com/google/android/gms/ads/internal/client/zzba:zzc	()Lcom/google/android/gms/internal/ads/zzbbi;
    //   1225: aload 7
    //   1227: invokevirtual 266	com/google/android/gms/internal/ads/zzbbi:zzb	(Lcom/google/android/gms/internal/ads/zzbbc;)Ljava/lang/Object;
    //   1230: checkcast 268	java/lang/Boolean
    //   1233: invokevirtual 271	java/lang/Boolean:booleanValue	()Z
    //   1236: ifeq +28 -> 1264
    //   1239: aload_1
    //   1240: astore 8
    //   1242: aload 10
    //   1244: invokestatic 58	com/google/android/gms/ads/internal/zzt:zzB	()Lcom/google/android/gms/common/util/Clock;
    //   1247: invokeinterface 64 1 0
    //   1252: lload 5
    //   1254: lsub
    //   1255: putfield 276	com/google/android/gms/internal/ads/zzdyw:zzd	J
    //   1258: goto -423 -> 835
    //   1261: aload 10
    //   1263: areturn
    //   1264: aload_1
    //   1265: astore 8
    //   1267: aload 9
    //   1269: athrow
    //   1270: astore_1
    //   1271: aload 8
    //   1273: invokevirtual 279	java/net/HttpURLConnection:disconnect	()V
    //   1276: aload_1
    //   1277: athrow
    //   1278: astore_1
    //   1279: goto +4 -> 1283
    //   1282: astore_1
    //   1283: ldc_w 317
    //   1286: aload_1
    //   1287: invokevirtual 320	java/io/IOException:getMessage	()Ljava/lang/String;
    //   1290: invokestatic 324	java/lang/String:valueOf	(Ljava/lang/Object;)Ljava/lang/String;
    //   1293: invokevirtual 327	java/lang/String:concat	(Ljava/lang/String;)Ljava/lang/String;
    //   1296: astore 7
    //   1298: aload 7
    //   1300: invokestatic 298	com/google/android/gms/internal/ads/zzbzt:zzj	(Ljava/lang/String;)V
    //   1303: new 35	com/google/android/gms/internal/ads/zzdtz
    //   1306: dup
    //   1307: iconst_1
    //   1308: aload 7
    //   1310: aload_1
    //   1311: invokespecial 330	com/google/android/gms/internal/ads/zzdtz:<init>	(ILjava/lang/String;Ljava/lang/Throwable;)V
    //   1314: athrow
    // Local variable table:
    //   start	length	slot	name	signature
    //   0	1315	0	this	zzdyx
    //   0	1315	1	paramzzdyv	zzdyv
    //   134	828	2	i	int
    //   10	171	3	j	int
    //   331	809	4	k	int
    //   37	1216	5	l	long
    //   4	1176	7	localObject1	Object
    //   1202	6	7	localzzdtz1	zzdtz
    //   1217	92	7	localObject2	Object
    //   53	1219	8	localObject3	Object
    //   142	587	9	localObject4	Object
    //   842	1	9	localObject5	Object
    //   847	17	9	localObject6	Object
    //   894	258	9	localObject7	Object
    //   1165	1	9	localzzdtz2	zzdtz
    //   1173	1	9	localzzdtz3	zzdtz
    //   1186	19	9	localzzdtz4	zzdtz
    //   1209	59	9	localzzdtz5	zzdtz
    //   42	1220	10	localzzdyw	zzdyw
    //   21	359	11	arrayOfByte1	byte[]
    //   396	1	11	localObject8	Object
    //   405	46	11	arrayOfByte2	byte[]
    //   714	37	11	str1	String
    //   147	359	12	localObject9	Object
    //   15	176	13	localMap	java.util.Map
    //   27	293	14	str2	String
    //   126	536	15	localHashMap	java.util.HashMap
    //   153	466	16	localObject10	Object
    //   159	449	17	localObject11	Object
    //   599	22	18	localArrayList	java.util.ArrayList
    // Exception table:
    //   from	to	target	type
    //   377	384	396	finally
    //   362	377	405	finally
    //   706	716	842	finally
    //   693	706	847	finally
    //   648	655	1165	com/google/android/gms/internal/ads/zzdtz
    //   659	666	1165	com/google/android/gms/internal/ads/zzdtz
    //   670	677	1165	com/google/android/gms/internal/ads/zzdtz
    //   720	724	1165	com/google/android/gms/internal/ads/zzdtz
    //   728	735	1165	com/google/android/gms/internal/ads/zzdtz
    //   739	746	1165	com/google/android/gms/internal/ads/zzdtz
    //   750	758	1165	com/google/android/gms/internal/ads/zzdtz
    //   762	766	1165	com/google/android/gms/internal/ads/zzdtz
    //   770	786	1165	com/google/android/gms/internal/ads/zzdtz
    //   793	797	1165	com/google/android/gms/internal/ads/zzdtz
    //   801	806	1165	com/google/android/gms/internal/ads/zzdtz
    //   810	812	1165	com/google/android/gms/internal/ads/zzdtz
    //   816	832	1165	com/google/android/gms/internal/ads/zzdtz
    //   855	859	1165	com/google/android/gms/internal/ads/zzdtz
    //   863	866	1165	com/google/android/gms/internal/ads/zzdtz
    //   886	896	1165	com/google/android/gms/internal/ads/zzdtz
    //   900	908	1165	com/google/android/gms/internal/ads/zzdtz
    //   912	916	1165	com/google/android/gms/internal/ads/zzdtz
    //   920	926	1165	com/google/android/gms/internal/ads/zzdtz
    //   933	938	1165	com/google/android/gms/internal/ads/zzdtz
    //   942	958	1165	com/google/android/gms/internal/ads/zzdtz
    //   976	982	1165	com/google/android/gms/internal/ads/zzdtz
    //   986	990	1165	com/google/android/gms/internal/ads/zzdtz
    //   994	1002	1165	com/google/android/gms/internal/ads/zzdtz
    //   1006	1008	1165	com/google/android/gms/internal/ads/zzdtz
    //   1012	1018	1165	com/google/android/gms/internal/ads/zzdtz
    //   1022	1026	1165	com/google/android/gms/internal/ads/zzdtz
    //   1030	1038	1165	com/google/android/gms/internal/ads/zzdtz
    //   1042	1044	1165	com/google/android/gms/internal/ads/zzdtz
    //   1048	1052	1165	com/google/android/gms/internal/ads/zzdtz
    //   1056	1060	1165	com/google/android/gms/internal/ads/zzdtz
    //   1064	1072	1165	com/google/android/gms/internal/ads/zzdtz
    //   1076	1083	1165	com/google/android/gms/internal/ads/zzdtz
    //   1087	1094	1165	com/google/android/gms/internal/ads/zzdtz
    //   1098	1102	1165	com/google/android/gms/internal/ads/zzdtz
    //   1106	1111	1165	com/google/android/gms/internal/ads/zzdtz
    //   1115	1120	1165	com/google/android/gms/internal/ads/zzdtz
    //   1124	1133	1165	com/google/android/gms/internal/ads/zzdtz
    //   1137	1145	1165	com/google/android/gms/internal/ads/zzdtz
    //   1149	1159	1165	com/google/android/gms/internal/ads/zzdtz
    //   1163	1165	1165	com/google/android/gms/internal/ads/zzdtz
    //   281	290	1173	com/google/android/gms/internal/ads/zzdtz
    //   303	311	1173	com/google/android/gms/internal/ads/zzdtz
    //   315	324	1173	com/google/android/gms/internal/ads/zzdtz
    //   328	333	1173	com/google/android/gms/internal/ads/zzdtz
    //   345	351	1173	com/google/android/gms/internal/ads/zzdtz
    //   355	362	1173	com/google/android/gms/internal/ads/zzdtz
    //   388	393	1173	com/google/android/gms/internal/ads/zzdtz
    //   411	416	1173	com/google/android/gms/internal/ads/zzdtz
    //   420	423	1173	com/google/android/gms/internal/ads/zzdtz
    //   427	432	1173	com/google/android/gms/internal/ads/zzdtz
    //   436	442	1173	com/google/android/gms/internal/ads/zzdtz
    //   446	455	1173	com/google/android/gms/internal/ads/zzdtz
    //   459	466	1173	com/google/android/gms/internal/ads/zzdtz
    //   470	487	1173	com/google/android/gms/internal/ads/zzdtz
    //   491	501	1173	com/google/android/gms/internal/ads/zzdtz
    //   505	517	1173	com/google/android/gms/internal/ads/zzdtz
    //   521	533	1173	com/google/android/gms/internal/ads/zzdtz
    //   537	549	1173	com/google/android/gms/internal/ads/zzdtz
    //   553	565	1173	com/google/android/gms/internal/ads/zzdtz
    //   569	589	1173	com/google/android/gms/internal/ads/zzdtz
    //   596	601	1173	com/google/android/gms/internal/ads/zzdtz
    //   605	612	1173	com/google/android/gms/internal/ads/zzdtz
    //   616	628	1173	com/google/android/gms/internal/ads/zzdtz
    //   635	644	1173	com/google/android/gms/internal/ads/zzdtz
    //   170	184	1178	finally
    //   190	204	1178	finally
    //   210	220	1178	finally
    //   226	238	1178	finally
    //   244	256	1178	finally
    //   262	274	1178	finally
    //   170	184	1186	com/google/android/gms/internal/ads/zzdtz
    //   190	204	1186	com/google/android/gms/internal/ads/zzdtz
    //   210	220	1186	com/google/android/gms/internal/ads/zzdtz
    //   226	238	1186	com/google/android/gms/internal/ads/zzdtz
    //   244	256	1186	com/google/android/gms/internal/ads/zzdtz
    //   262	274	1186	com/google/android/gms/internal/ads/zzdtz
    //   144	161	1194	finally
    //   144	161	1202	com/google/android/gms/internal/ads/zzdtz
    //   281	290	1270	finally
    //   303	311	1270	finally
    //   315	324	1270	finally
    //   328	333	1270	finally
    //   345	351	1270	finally
    //   355	362	1270	finally
    //   388	393	1270	finally
    //   411	416	1270	finally
    //   420	423	1270	finally
    //   427	432	1270	finally
    //   436	442	1270	finally
    //   446	455	1270	finally
    //   459	466	1270	finally
    //   470	487	1270	finally
    //   491	501	1270	finally
    //   505	517	1270	finally
    //   521	533	1270	finally
    //   537	549	1270	finally
    //   553	565	1270	finally
    //   569	589	1270	finally
    //   596	601	1270	finally
    //   605	612	1270	finally
    //   616	628	1270	finally
    //   635	644	1270	finally
    //   648	655	1270	finally
    //   659	666	1270	finally
    //   670	677	1270	finally
    //   720	724	1270	finally
    //   728	735	1270	finally
    //   739	746	1270	finally
    //   750	758	1270	finally
    //   762	766	1270	finally
    //   770	786	1270	finally
    //   793	797	1270	finally
    //   801	806	1270	finally
    //   810	812	1270	finally
    //   816	832	1270	finally
    //   855	859	1270	finally
    //   863	866	1270	finally
    //   886	896	1270	finally
    //   900	908	1270	finally
    //   912	916	1270	finally
    //   920	926	1270	finally
    //   933	938	1270	finally
    //   942	958	1270	finally
    //   976	982	1270	finally
    //   986	990	1270	finally
    //   994	1002	1270	finally
    //   1006	1008	1270	finally
    //   1012	1018	1270	finally
    //   1022	1026	1270	finally
    //   1030	1038	1270	finally
    //   1042	1044	1270	finally
    //   1048	1052	1270	finally
    //   1056	1060	1270	finally
    //   1064	1072	1270	finally
    //   1076	1083	1270	finally
    //   1087	1094	1270	finally
    //   1098	1102	1270	finally
    //   1106	1111	1270	finally
    //   1115	1120	1270	finally
    //   1124	1133	1270	finally
    //   1137	1145	1270	finally
    //   1149	1159	1270	finally
    //   1163	1165	1270	finally
    //   1214	1219	1270	finally
    //   1222	1239	1270	finally
    //   1242	1258	1270	finally
    //   1267	1270	1270	finally
    //   835	839	1278	java/io/IOException
    //   964	969	1278	java/io/IOException
    //   1271	1278	1278	java/io/IOException
    //   39	133	1282	java/io/IOException
    //   135	144	1282	java/io/IOException
  }
}


/* Location:              C:\Users\Ria\Documents\slope apk\dex-tools-v2.4\classes-dex2jar.jar!\com\google\android\gms\internal\ads\zzdyx.class
 * Java compiler version: 6 (50.0)
 * JD-Core Version:       0.7.1
 */