package com.google.android.gms.internal.ads;

import java.util.HashMap;
import java.util.Map;

public final class zzdyw
{
  public int zza = 0;
  public Map zzb = new HashMap();
  public String zzc = "";
  public long zzd = -1L;
  
  /* Error */
  public static zzdyw zza(java.io.Reader paramReader)
    throws zzezj
  {
    // Byte code:
    //   0: new 45	android/util/JsonReader
    //   3: astore 6
    //   5: aload 6
    //   7: aload_0
    //   8: invokespecial 48	android/util/JsonReader:<init>	(Ljava/io/Reader;)V
    //   11: new 20	java/util/HashMap
    //   14: astore 5
    //   16: aload 5
    //   18: invokespecial 21	java/util/HashMap:<init>	()V
    //   21: ldc2_w 28
    //   24: lstore_2
    //   25: ldc 25
    //   27: astore 4
    //   29: aload 6
    //   31: invokevirtual 51	android/util/JsonReader:beginObject	()V
    //   34: iconst_0
    //   35: istore_1
    //   36: aload 6
    //   38: invokevirtual 55	android/util/JsonReader:hasNext	()Z
    //   41: ifeq +138 -> 179
    //   44: aload 6
    //   46: invokevirtual 59	android/util/JsonReader:nextName	()Ljava/lang/String;
    //   49: astore 7
    //   51: ldc 61
    //   53: aload 7
    //   55: invokevirtual 67	java/lang/String:equals	(Ljava/lang/Object;)Z
    //   58: ifeq +12 -> 70
    //   61: aload 6
    //   63: invokevirtual 71	android/util/JsonReader:nextInt	()I
    //   66: istore_1
    //   67: goto -31 -> 36
    //   70: ldc 73
    //   72: aload 7
    //   74: invokevirtual 67	java/lang/String:equals	(Ljava/lang/Object;)Z
    //   77: ifeq +13 -> 90
    //   80: aload 6
    //   82: invokevirtual 76	android/util/JsonReader:nextString	()Ljava/lang/String;
    //   85: astore 4
    //   87: goto -51 -> 36
    //   90: ldc 78
    //   92: aload 7
    //   94: invokevirtual 67	java/lang/String:equals	(Ljava/lang/Object;)Z
    //   97: ifeq +12 -> 109
    //   100: aload 6
    //   102: invokevirtual 82	android/util/JsonReader:nextLong	()J
    //   105: lstore_2
    //   106: goto -70 -> 36
    //   109: ldc 84
    //   111: aload 7
    //   113: invokevirtual 67	java/lang/String:equals	(Ljava/lang/Object;)Z
    //   116: ifeq +55 -> 171
    //   119: new 20	java/util/HashMap
    //   122: astore 5
    //   124: aload 5
    //   126: invokespecial 21	java/util/HashMap:<init>	()V
    //   129: aload 6
    //   131: invokevirtual 51	android/util/JsonReader:beginObject	()V
    //   134: aload 6
    //   136: invokevirtual 55	android/util/JsonReader:hasNext	()Z
    //   139: ifeq +24 -> 163
    //   142: aload 5
    //   144: aload 6
    //   146: invokevirtual 59	android/util/JsonReader:nextName	()Ljava/lang/String;
    //   149: aload 6
    //   151: invokestatic 89	com/google/android/gms/ads/internal/util/zzbu:zzd	(Landroid/util/JsonReader;)Ljava/util/List;
    //   154: invokeinterface 95 3 0
    //   159: pop
    //   160: goto -26 -> 134
    //   163: aload 6
    //   165: invokevirtual 98	android/util/JsonReader:endObject	()V
    //   168: goto -132 -> 36
    //   171: aload 6
    //   173: invokevirtual 101	android/util/JsonReader:skipValue	()V
    //   176: goto -140 -> 36
    //   179: aload 6
    //   181: invokevirtual 98	android/util/JsonReader:endObject	()V
    //   184: new 2	com/google/android/gms/internal/ads/zzdyw
    //   187: astore 6
    //   189: aload 6
    //   191: invokespecial 102	com/google/android/gms/internal/ads/zzdyw:<init>	()V
    //   194: aload 6
    //   196: iload_1
    //   197: putfield 18	com/google/android/gms/internal/ads/zzdyw:zza	I
    //   200: aload 4
    //   202: ifnull +10 -> 212
    //   205: aload 6
    //   207: aload 4
    //   209: putfield 27	com/google/android/gms/internal/ads/zzdyw:zzc	Ljava/lang/String;
    //   212: aload 6
    //   214: lload_2
    //   215: putfield 31	com/google/android/gms/internal/ads/zzdyw:zzd	J
    //   218: aload 6
    //   220: aload 5
    //   222: putfield 23	com/google/android/gms/internal/ads/zzdyw:zzb	Ljava/util/Map;
    //   225: aload_0
    //   226: invokestatic 108	com/google/android/gms/common/util/IOUtils:closeQuietly	(Ljava/io/Closeable;)V
    //   229: aload 6
    //   231: areturn
    //   232: astore 4
    //   234: goto +37 -> 271
    //   237: astore 4
    //   239: goto +15 -> 254
    //   242: astore 4
    //   244: goto +10 -> 254
    //   247: astore 4
    //   249: goto +5 -> 254
    //   252: astore 4
    //   254: new 35	com/google/android/gms/internal/ads/zzezj
    //   257: astore 5
    //   259: aload 5
    //   261: ldc 110
    //   263: aload 4
    //   265: invokespecial 113	com/google/android/gms/internal/ads/zzezj:<init>	(Ljava/lang/String;Ljava/lang/Throwable;)V
    //   268: aload 5
    //   270: athrow
    //   271: aload_0
    //   272: invokestatic 108	com/google/android/gms/common/util/IOUtils:closeQuietly	(Ljava/io/Closeable;)V
    //   275: aload 4
    //   277: athrow
    // Local variable table:
    //   start	length	slot	name	signature
    //   0	278	0	paramReader	java.io.Reader
    //   35	162	1	i	int
    //   24	191	2	l	long
    //   27	181	4	str1	String
    //   232	1	4	localObject1	Object
    //   237	1	4	localAssertionError	AssertionError
    //   242	1	4	localNumberFormatException	NumberFormatException
    //   247	1	4	localIllegalStateException	IllegalStateException
    //   252	24	4	localIOException	java.io.IOException
    //   14	255	5	localObject2	Object
    //   3	227	6	localObject3	Object
    //   49	63	7	str2	String
    // Exception table:
    //   from	to	target	type
    //   0	21	232	finally
    //   29	34	232	finally
    //   36	67	232	finally
    //   70	87	232	finally
    //   90	106	232	finally
    //   109	134	232	finally
    //   134	160	232	finally
    //   163	168	232	finally
    //   171	176	232	finally
    //   179	200	232	finally
    //   205	212	232	finally
    //   212	225	232	finally
    //   254	271	232	finally
    //   0	21	237	java/lang/AssertionError
    //   29	34	237	java/lang/AssertionError
    //   36	67	237	java/lang/AssertionError
    //   70	87	237	java/lang/AssertionError
    //   90	106	237	java/lang/AssertionError
    //   109	134	237	java/lang/AssertionError
    //   134	160	237	java/lang/AssertionError
    //   163	168	237	java/lang/AssertionError
    //   171	176	237	java/lang/AssertionError
    //   179	200	237	java/lang/AssertionError
    //   205	212	237	java/lang/AssertionError
    //   212	225	237	java/lang/AssertionError
    //   0	21	242	java/lang/NumberFormatException
    //   29	34	242	java/lang/NumberFormatException
    //   36	67	242	java/lang/NumberFormatException
    //   70	87	242	java/lang/NumberFormatException
    //   90	106	242	java/lang/NumberFormatException
    //   109	134	242	java/lang/NumberFormatException
    //   134	160	242	java/lang/NumberFormatException
    //   163	168	242	java/lang/NumberFormatException
    //   171	176	242	java/lang/NumberFormatException
    //   179	200	242	java/lang/NumberFormatException
    //   205	212	242	java/lang/NumberFormatException
    //   212	225	242	java/lang/NumberFormatException
    //   0	21	247	java/lang/IllegalStateException
    //   29	34	247	java/lang/IllegalStateException
    //   36	67	247	java/lang/IllegalStateException
    //   70	87	247	java/lang/IllegalStateException
    //   90	106	247	java/lang/IllegalStateException
    //   109	134	247	java/lang/IllegalStateException
    //   134	160	247	java/lang/IllegalStateException
    //   163	168	247	java/lang/IllegalStateException
    //   171	176	247	java/lang/IllegalStateException
    //   179	200	247	java/lang/IllegalStateException
    //   205	212	247	java/lang/IllegalStateException
    //   212	225	247	java/lang/IllegalStateException
    //   0	21	252	java/io/IOException
    //   29	34	252	java/io/IOException
    //   36	67	252	java/io/IOException
    //   70	87	252	java/io/IOException
    //   90	106	252	java/io/IOException
    //   109	134	252	java/io/IOException
    //   134	160	252	java/io/IOException
    //   163	168	252	java/io/IOException
    //   171	176	252	java/io/IOException
    //   179	200	252	java/io/IOException
    //   205	212	252	java/io/IOException
    //   212	225	252	java/io/IOException
  }
}


/* Location:              C:\Users\Ria\Documents\slope apk\dex-tools-v2.4\classes-dex2jar.jar!\com\google\android\gms\internal\ads\zzdyw.class
 * Java compiler version: 6 (50.0)
 * JD-Core Version:       0.7.1
 */