package com.google.android.gms.internal.ads;

public final class zzdzz
{
  private long zza = 0L;
  private int zzb = 0;
  private long zzc = 0L;
  private long zzd = 0L;
  private long zze = 0L;
  private final Object zzf = new Object();
  private final Object zzg = new Object();
  private final Object zzh = new Object();
  private final Object zzi = new Object();
  private final Object zzj = new Object();
  
  public final int zza()
  {
    synchronized (this.zzg)
    {
      int i = this.zzb;
      return i;
    }
  }
  
  /* Error */
  public final long zzb()
  {
    // Byte code:
    //   0: aload_0
    //   1: monitorenter
    //   2: aload_0
    //   3: getfield 41	com/google/android/gms/internal/ads/zzdzz:zzj	Ljava/lang/Object;
    //   6: astore_3
    //   7: aload_3
    //   8: monitorenter
    //   9: aload_0
    //   10: getfield 31	com/google/android/gms/internal/ads/zzdzz:zze	J
    //   13: lstore_1
    //   14: aload_3
    //   15: monitorexit
    //   16: aload_0
    //   17: monitorexit
    //   18: lload_1
    //   19: lreturn
    //   20: astore 4
    //   22: aload_3
    //   23: monitorexit
    //   24: aload 4
    //   26: athrow
    //   27: astore_3
    //   28: aload_0
    //   29: monitorexit
    //   30: aload_3
    //   31: athrow
    // Local variable table:
    //   start	length	slot	name	signature
    //   0	32	0	this	zzdzz
    //   13	6	1	l	long
    //   27	4	3	localObject2	Object
    //   20	5	4	localObject3	Object
    // Exception table:
    //   from	to	target	type
    //   9	16	20	finally
    //   22	24	20	finally
    //   2	9	27	finally
    //   24	27	27	finally
  }
  
  /* Error */
  public final long zzc()
  {
    // Byte code:
    //   0: aload_0
    //   1: monitorenter
    //   2: aload_0
    //   3: getfield 39	com/google/android/gms/internal/ads/zzdzz:zzi	Ljava/lang/Object;
    //   6: astore_3
    //   7: aload_3
    //   8: monitorenter
    //   9: aload_0
    //   10: getfield 29	com/google/android/gms/internal/ads/zzdzz:zzd	J
    //   13: lstore_1
    //   14: aload_3
    //   15: monitorexit
    //   16: aload_0
    //   17: monitorexit
    //   18: lload_1
    //   19: lreturn
    //   20: astore 4
    //   22: aload_3
    //   23: monitorexit
    //   24: aload 4
    //   26: athrow
    //   27: astore_3
    //   28: aload_0
    //   29: monitorexit
    //   30: aload_3
    //   31: athrow
    // Local variable table:
    //   start	length	slot	name	signature
    //   0	32	0	this	zzdzz
    //   13	6	1	l	long
    //   27	4	3	localObject2	Object
    //   20	5	4	localObject3	Object
    // Exception table:
    //   from	to	target	type
    //   9	16	20	finally
    //   22	24	20	finally
    //   2	9	27	finally
    //   24	27	27	finally
  }
  
  /* Error */
  public final long zzd()
  {
    // Byte code:
    //   0: aload_0
    //   1: monitorenter
    //   2: aload_0
    //   3: getfield 33	com/google/android/gms/internal/ads/zzdzz:zzf	Ljava/lang/Object;
    //   6: astore_3
    //   7: aload_3
    //   8: monitorenter
    //   9: aload_0
    //   10: getfield 23	com/google/android/gms/internal/ads/zzdzz:zza	J
    //   13: lstore_1
    //   14: aload_3
    //   15: monitorexit
    //   16: aload_0
    //   17: monitorexit
    //   18: lload_1
    //   19: lreturn
    //   20: astore 4
    //   22: aload_3
    //   23: monitorexit
    //   24: aload 4
    //   26: athrow
    //   27: astore_3
    //   28: aload_0
    //   29: monitorexit
    //   30: aload_3
    //   31: athrow
    // Local variable table:
    //   start	length	slot	name	signature
    //   0	32	0	this	zzdzz
    //   13	6	1	l	long
    //   27	4	3	localObject2	Object
    //   20	5	4	localObject3	Object
    // Exception table:
    //   from	to	target	type
    //   9	16	20	finally
    //   22	24	20	finally
    //   2	9	27	finally
    //   24	27	27	finally
  }
  
  public final long zze()
  {
    synchronized (this.zzh)
    {
      long l = this.zzc;
      return l;
    }
  }
  
  /* Error */
  public final void zzf(long paramLong)
  {
    // Byte code:
    //   0: aload_0
    //   1: monitorenter
    //   2: aload_0
    //   3: getfield 41	com/google/android/gms/internal/ads/zzdzz:zzj	Ljava/lang/Object;
    //   6: astore 4
    //   8: aload 4
    //   10: monitorenter
    //   11: aload_0
    //   12: lload_1
    //   13: putfield 31	com/google/android/gms/internal/ads/zzdzz:zze	J
    //   16: aload 4
    //   18: monitorexit
    //   19: aload_0
    //   20: monitorexit
    //   21: return
    //   22: astore_3
    //   23: aload 4
    //   25: monitorexit
    //   26: aload_3
    //   27: athrow
    //   28: astore_3
    //   29: aload_0
    //   30: monitorexit
    //   31: aload_3
    //   32: athrow
    // Local variable table:
    //   start	length	slot	name	signature
    //   0	33	0	this	zzdzz
    //   0	33	1	paramLong	long
    //   22	5	3	localObject1	Object
    //   28	4	3	localObject2	Object
    // Exception table:
    //   from	to	target	type
    //   11	19	22	finally
    //   23	26	22	finally
    //   2	11	28	finally
    //   26	28	28	finally
  }
  
  /* Error */
  public final void zzg(long paramLong)
  {
    // Byte code:
    //   0: aload_0
    //   1: monitorenter
    //   2: aload_0
    //   3: getfield 39	com/google/android/gms/internal/ads/zzdzz:zzi	Ljava/lang/Object;
    //   6: astore 4
    //   8: aload 4
    //   10: monitorenter
    //   11: aload_0
    //   12: lload_1
    //   13: putfield 29	com/google/android/gms/internal/ads/zzdzz:zzd	J
    //   16: aload 4
    //   18: monitorexit
    //   19: aload_0
    //   20: monitorexit
    //   21: return
    //   22: astore_3
    //   23: aload 4
    //   25: monitorexit
    //   26: aload_3
    //   27: athrow
    //   28: astore_3
    //   29: aload_0
    //   30: monitorexit
    //   31: aload_3
    //   32: athrow
    // Local variable table:
    //   start	length	slot	name	signature
    //   0	33	0	this	zzdzz
    //   0	33	1	paramLong	long
    //   22	5	3	localObject1	Object
    //   28	4	3	localObject2	Object
    // Exception table:
    //   from	to	target	type
    //   11	19	22	finally
    //   23	26	22	finally
    //   2	11	28	finally
    //   26	28	28	finally
  }
  
  /* Error */
  public final void zzh(long paramLong)
  {
    // Byte code:
    //   0: aload_0
    //   1: monitorenter
    //   2: aload_0
    //   3: getfield 33	com/google/android/gms/internal/ads/zzdzz:zzf	Ljava/lang/Object;
    //   6: astore 4
    //   8: aload 4
    //   10: monitorenter
    //   11: aload_0
    //   12: lload_1
    //   13: putfield 23	com/google/android/gms/internal/ads/zzdzz:zza	J
    //   16: aload 4
    //   18: monitorexit
    //   19: aload_0
    //   20: monitorexit
    //   21: return
    //   22: astore_3
    //   23: aload 4
    //   25: monitorexit
    //   26: aload_3
    //   27: athrow
    //   28: astore_3
    //   29: aload_0
    //   30: monitorexit
    //   31: aload_3
    //   32: athrow
    // Local variable table:
    //   start	length	slot	name	signature
    //   0	33	0	this	zzdzz
    //   0	33	1	paramLong	long
    //   22	5	3	localObject1	Object
    //   28	4	3	localObject2	Object
    // Exception table:
    //   from	to	target	type
    //   11	19	22	finally
    //   23	26	22	finally
    //   2	11	28	finally
    //   26	28	28	finally
  }
  
  public final void zzi(int paramInt)
  {
    synchronized (this.zzg)
    {
      this.zzb = paramInt;
      return;
    }
  }
  
  public final void zzj(long paramLong)
  {
    synchronized (this.zzh)
    {
      this.zzc = paramLong;
      return;
    }
  }
}


/* Location:              C:\Users\Ria\Documents\slope apk\dex-tools-v2.4\classes-dex2jar.jar!\com\google\android\gms\internal\ads\zzdzz.class
 * Java compiler version: 6 (50.0)
 * JD-Core Version:       0.7.1
 */