package com.google.android.gms.internal.ads;

import android.os.RemoteException;
import com.google.android.gms.ads.internal.client.zzdn;
import com.google.android.gms.ads.internal.client.zzl;

public final class zzejq
{
  private final zzejv zza;
  private final String zzb;
  private zzdn zzc;
  
  public zzejq(zzejv paramzzejv, String paramString)
  {
    this.zza = paramzzejv;
    this.zzb = paramString;
  }
  
  /* Error */
  public final String zza()
  {
    // Byte code:
    //   0: aload_0
    //   1: monitorenter
    //   2: aconst_null
    //   3: astore_1
    //   4: aload_0
    //   5: getfield 23	com/google/android/gms/internal/ads/zzejq:zzc	Lcom/google/android/gms/ads/internal/client/zzdn;
    //   8: astore_2
    //   9: aload_2
    //   10: ifnull +10 -> 20
    //   13: aload_2
    //   14: invokeinterface 31 1 0
    //   19: astore_1
    //   20: aload_0
    //   21: monitorexit
    //   22: aload_1
    //   23: areturn
    //   24: astore_1
    //   25: goto +14 -> 39
    //   28: astore_1
    //   29: ldc 33
    //   31: aload_1
    //   32: invokestatic 39	com/google/android/gms/internal/ads/zzbzt:zzl	(Ljava/lang/String;Ljava/lang/Throwable;)V
    //   35: aload_0
    //   36: monitorexit
    //   37: aconst_null
    //   38: areturn
    //   39: aload_0
    //   40: monitorexit
    //   41: aload_1
    //   42: athrow
    // Local variable table:
    //   start	length	slot	name	signature
    //   0	43	0	this	zzejq
    //   3	20	1	str	String
    //   24	1	1	localObject	Object
    //   28	14	1	localRemoteException	RemoteException
    //   8	6	2	localzzdn	zzdn
    // Exception table:
    //   from	to	target	type
    //   4	9	24	finally
    //   13	20	24	finally
    //   29	35	24	finally
    //   4	9	28	android/os/RemoteException
    //   13	20	28	android/os/RemoteException
  }
  
  /* Error */
  public final String zzb()
  {
    // Byte code:
    //   0: aload_0
    //   1: monitorenter
    //   2: aconst_null
    //   3: astore_1
    //   4: aload_0
    //   5: getfield 23	com/google/android/gms/internal/ads/zzejq:zzc	Lcom/google/android/gms/ads/internal/client/zzdn;
    //   8: astore_2
    //   9: aload_2
    //   10: ifnull +10 -> 20
    //   13: aload_2
    //   14: invokeinterface 31 1 0
    //   19: astore_1
    //   20: aload_0
    //   21: monitorexit
    //   22: aload_1
    //   23: areturn
    //   24: astore_1
    //   25: goto +14 -> 39
    //   28: astore_1
    //   29: ldc 33
    //   31: aload_1
    //   32: invokestatic 39	com/google/android/gms/internal/ads/zzbzt:zzl	(Ljava/lang/String;Ljava/lang/Throwable;)V
    //   35: aload_0
    //   36: monitorexit
    //   37: aconst_null
    //   38: areturn
    //   39: aload_0
    //   40: monitorexit
    //   41: aload_1
    //   42: athrow
    // Local variable table:
    //   start	length	slot	name	signature
    //   0	43	0	this	zzejq
    //   3	20	1	str	String
    //   24	1	1	localObject	Object
    //   28	14	1	localRemoteException	RemoteException
    //   8	6	2	localzzdn	zzdn
    // Exception table:
    //   from	to	target	type
    //   4	9	24	finally
    //   13	20	24	finally
    //   29	35	24	finally
    //   4	9	28	android/os/RemoteException
    //   13	20	28	android/os/RemoteException
  }
  
  public final void zzd(zzl paramzzl, int paramInt)
    throws RemoteException
  {
    try
    {
      this.zzc = null;
      zzejw localzzejw = new com/google/android/gms/internal/ads/zzejw;
      localzzejw.<init>(paramInt);
      zzejv localzzejv = this.zza;
      String str = this.zzb;
      zzejp localzzejp = new com/google/android/gms/internal/ads/zzejp;
      localzzejp.<init>(this);
      localzzejv.zzb(paramzzl, str, localzzejw, localzzejp);
      return;
    }
    finally
    {
      paramzzl = finally;
      throw paramzzl;
    }
  }
  
  public final boolean zze()
    throws RemoteException
  {
    try
    {
      boolean bool = this.zza.zza();
      return bool;
    }
    finally
    {
      localObject = finally;
      throw ((Throwable)localObject);
    }
  }
}


/* Location:              C:\Users\Ria\Documents\slope apk\dex-tools-v2.4\classes-dex2jar.jar!\com\google\android\gms\internal\ads\zzejq.class
 * Java compiler version: 6 (50.0)
 * JD-Core Version:       0.7.1
 */