package com.google.android.gms.internal.ads;

import java.io.IOException;
import java.lang.reflect.Field;
import java.util.Arrays;
import java.util.List;
import java.util.Map;
import java.util.Objects;
import sun.misc.Unsafe;

final class zzgqj<T>
  implements zzgqz<T>
{
  private static final int[] zza = new int[0];
  private static final Unsafe zzb = zzgsa.zzi();
  private final int[] zzc;
  private final Object[] zzd;
  private final int zze;
  private final int zzf;
  private final zzgqg zzg;
  private final boolean zzh;
  private final boolean zzi;
  private final boolean zzj;
  private final int[] zzk;
  private final int zzl;
  private final int zzm;
  private final zzgpu zzn;
  private final zzgrq zzo;
  private final zzgoj zzp;
  private final zzgql zzq;
  private final zzgqb zzr;
  
  private zzgqj(int[] paramArrayOfInt1, Object[] paramArrayOfObject, int paramInt1, int paramInt2, zzgqg paramzzgqg, boolean paramBoolean1, boolean paramBoolean2, int[] paramArrayOfInt2, int paramInt3, int paramInt4, zzgql paramzzgql, zzgpu paramzzgpu, zzgrq paramzzgrq, zzgoj paramzzgoj, zzgqb paramzzgqb)
  {
    this.zzc = paramArrayOfInt1;
    this.zzd = paramArrayOfObject;
    this.zze = paramInt1;
    this.zzf = paramInt2;
    this.zzi = (paramzzgqg instanceof zzgow);
    this.zzj = paramBoolean1;
    paramBoolean2 = false;
    paramBoolean1 = paramBoolean2;
    if (paramzzgoj != null)
    {
      paramBoolean1 = paramBoolean2;
      if (paramzzgoj.zzh(paramzzgqg)) {
        paramBoolean1 = true;
      }
    }
    this.zzh = paramBoolean1;
    this.zzk = paramArrayOfInt2;
    this.zzl = paramInt3;
    this.zzm = paramInt4;
    this.zzq = paramzzgql;
    this.zzn = paramzzgpu;
    this.zzo = paramzzgrq;
    this.zzp = paramzzgoj;
    this.zzg = paramzzgqg;
    this.zzr = paramzzgqb;
  }
  
  private static long zzA(Object paramObject, long paramLong)
  {
    return ((Long)zzgsa.zzh(paramObject, paramLong)).longValue();
  }
  
  private final zzgpa zzB(int paramInt)
  {
    paramInt /= 3;
    return (zzgpa)this.zzd[(paramInt + paramInt + 1)];
  }
  
  private final zzgqz zzC(int paramInt)
  {
    Object localObject = this.zzd;
    paramInt /= 3;
    paramInt += paramInt;
    localObject = (zzgqz)localObject[paramInt];
    if (localObject != null) {
      return (zzgqz)localObject;
    }
    localObject = zzgqo.zza().zzb((Class)this.zzd[(paramInt + 1)]);
    this.zzd[paramInt] = localObject;
    return (zzgqz)localObject;
  }
  
  private final Object zzD(Object paramObject1, int paramInt, Object paramObject2, zzgrq paramzzgrq, Object paramObject3)
  {
    int i = this.zzc[paramInt];
    paramObject1 = zzgsa.zzh(paramObject1, zzz(paramInt) & 0xFFFFF);
    if (paramObject1 == null) {
      return paramObject2;
    }
    if (zzB(paramInt) == null) {
      return paramObject2;
    }
    paramObject1 = (zzgqa)paramObject1;
    paramObject1 = (zzgpz)zzE(paramInt);
    throw null;
  }
  
  private final Object zzE(int paramInt)
  {
    paramInt /= 3;
    return this.zzd[(paramInt + paramInt)];
  }
  
  private final Object zzF(Object paramObject, int paramInt)
  {
    zzgqz localzzgqz = zzC(paramInt);
    int i = zzz(paramInt);
    if (!zzS(paramObject, paramInt)) {
      return localzzgqz.zze();
    }
    long l = i & 0xFFFFF;
    paramObject = zzb.getObject(paramObject, l);
    if (zzV(paramObject)) {
      return paramObject;
    }
    Object localObject = localzzgqz.zze();
    if (paramObject != null) {
      localzzgqz.zzg(localObject, paramObject);
    }
    return localObject;
  }
  
  private final Object zzG(Object paramObject, int paramInt1, int paramInt2)
  {
    zzgqz localzzgqz = zzC(paramInt2);
    if (!zzW(paramObject, paramInt1, paramInt2)) {
      return localzzgqz.zze();
    }
    paramObject = zzb.getObject(paramObject, zzz(paramInt2) & 0xFFFFF);
    if (zzV(paramObject)) {
      return paramObject;
    }
    Object localObject = localzzgqz.zze();
    if (paramObject != null) {
      localzzgqz.zzg(localObject, paramObject);
    }
    return localObject;
  }
  
  private static Field zzH(Class paramClass, String paramString)
  {
    try
    {
      Field localField = paramClass.getDeclaredField(paramString);
      return localField;
    }
    catch (NoSuchFieldException localNoSuchFieldException)
    {
      for (localObject2 : paramClass.getDeclaredFields()) {
        if (paramString.equals(((Field)localObject2).getName())) {
          return (Field)localObject2;
        }
      }
      paramClass = paramClass.getName();
      Object localObject2 = Arrays.toString((Object[])???);
      ??? = new StringBuilder();
      ((StringBuilder)???).append("Field ");
      ((StringBuilder)???).append(paramString);
      ((StringBuilder)???).append(" for ");
      ((StringBuilder)???).append(paramClass);
      ((StringBuilder)???).append(" not found. Known fields are ");
      ((StringBuilder)???).append((String)localObject2);
      throw new RuntimeException(((StringBuilder)???).toString());
    }
  }
  
  private static void zzI(Object paramObject)
  {
    if (zzV(paramObject)) {
      return;
    }
    throw new IllegalArgumentException("Mutating immutable message: ".concat(String.valueOf(String.valueOf(paramObject))));
  }
  
  private final void zzJ(Object paramObject1, Object paramObject2, int paramInt)
  {
    if (!zzS(paramObject2, paramInt)) {
      return;
    }
    int i = zzz(paramInt);
    Unsafe localUnsafe = zzb;
    long l = i & 0xFFFFF;
    Object localObject2 = localUnsafe.getObject(paramObject2, l);
    if (localObject2 != null)
    {
      zzgqz localzzgqz = zzC(paramInt);
      if (!zzS(paramObject1, paramInt))
      {
        if (!zzV(localObject2))
        {
          localUnsafe.putObject(paramObject1, l, localObject2);
        }
        else
        {
          paramObject2 = localzzgqz.zze();
          localzzgqz.zzg(paramObject2, localObject2);
          localUnsafe.putObject(paramObject1, l, paramObject2);
        }
        zzM(paramObject1, paramInt);
        return;
      }
      Object localObject1 = localUnsafe.getObject(paramObject1, l);
      paramObject2 = localObject1;
      if (!zzV(localObject1))
      {
        paramObject2 = localzzgqz.zze();
        localzzgqz.zzg(paramObject2, localObject1);
        localUnsafe.putObject(paramObject1, l, paramObject2);
      }
      localzzgqz.zzg(paramObject2, localObject2);
      return;
    }
    paramInt = this.zzc[paramInt];
    paramObject2 = paramObject2.toString();
    paramObject1 = new StringBuilder();
    ((StringBuilder)paramObject1).append("Source subfield ");
    ((StringBuilder)paramObject1).append(paramInt);
    ((StringBuilder)paramObject1).append(" is present but null: ");
    ((StringBuilder)paramObject1).append((String)paramObject2);
    throw new IllegalStateException(((StringBuilder)paramObject1).toString());
  }
  
  private final void zzK(Object paramObject1, Object paramObject2, int paramInt)
  {
    int j = this.zzc[paramInt];
    if (!zzW(paramObject2, j, paramInt)) {
      return;
    }
    int i = zzz(paramInt);
    Unsafe localUnsafe = zzb;
    long l = i & 0xFFFFF;
    Object localObject2 = localUnsafe.getObject(paramObject2, l);
    if (localObject2 != null)
    {
      zzgqz localzzgqz = zzC(paramInt);
      if (!zzW(paramObject1, j, paramInt))
      {
        if (!zzV(localObject2))
        {
          localUnsafe.putObject(paramObject1, l, localObject2);
        }
        else
        {
          paramObject2 = localzzgqz.zze();
          localzzgqz.zzg(paramObject2, localObject2);
          localUnsafe.putObject(paramObject1, l, paramObject2);
        }
        zzN(paramObject1, j, paramInt);
        return;
      }
      Object localObject1 = localUnsafe.getObject(paramObject1, l);
      paramObject2 = localObject1;
      if (!zzV(localObject1))
      {
        paramObject2 = localzzgqz.zze();
        localzzgqz.zzg(paramObject2, localObject1);
        localUnsafe.putObject(paramObject1, l, paramObject2);
      }
      localzzgqz.zzg(paramObject2, localObject2);
      return;
    }
    paramInt = this.zzc[paramInt];
    paramObject2 = paramObject2.toString();
    paramObject1 = new StringBuilder();
    ((StringBuilder)paramObject1).append("Source subfield ");
    ((StringBuilder)paramObject1).append(paramInt);
    ((StringBuilder)paramObject1).append(" is present but null: ");
    ((StringBuilder)paramObject1).append((String)paramObject2);
    throw new IllegalStateException(((StringBuilder)paramObject1).toString());
  }
  
  private final void zzL(Object paramObject, int paramInt, zzgqr paramzzgqr)
    throws IOException
  {
    if (zzR(paramInt))
    {
      paramzzgqr = paramzzgqr.zzs();
      zzgsa.zzv(paramObject, paramInt & 0xFFFFF, paramzzgqr);
      return;
    }
    if (this.zzi)
    {
      paramzzgqr = paramzzgqr.zzr();
      zzgsa.zzv(paramObject, paramInt & 0xFFFFF, paramzzgqr);
      return;
    }
    paramzzgqr = paramzzgqr.zzp();
    zzgsa.zzv(paramObject, paramInt & 0xFFFFF, paramzzgqr);
  }
  
  private final void zzM(Object paramObject, int paramInt)
  {
    paramInt = zzw(paramInt);
    long l = 0xFFFFF & paramInt;
    if (l == 1048575L) {
      return;
    }
    zzgsa.zzt(paramObject, l, 1 << (paramInt >>> 20) | zzgsa.zzd(paramObject, l));
  }
  
  private final void zzN(Object paramObject, int paramInt1, int paramInt2)
  {
    zzgsa.zzt(paramObject, zzw(paramInt2) & 0xFFFFF, paramInt1);
  }
  
  private final void zzO(Object paramObject1, int paramInt, Object paramObject2)
  {
    zzb.putObject(paramObject1, zzz(paramInt) & 0xFFFFF, paramObject2);
    zzM(paramObject1, paramInt);
  }
  
  private final void zzP(Object paramObject1, int paramInt1, int paramInt2, Object paramObject2)
  {
    zzb.putObject(paramObject1, zzz(paramInt2) & 0xFFFFF, paramObject2);
    zzN(paramObject1, paramInt1, paramInt2);
  }
  
  private final boolean zzQ(Object paramObject1, Object paramObject2, int paramInt)
  {
    return zzS(paramObject1, paramInt) == zzS(paramObject2, paramInt);
  }
  
  private static boolean zzR(int paramInt)
  {
    return (paramInt & 0x20000000) != 0;
  }
  
  private final boolean zzS(Object paramObject, int paramInt)
  {
    int i = zzw(paramInt);
    long l = i & 0xFFFFF;
    if (l == 1048575L)
    {
      paramInt = zzz(paramInt);
      i = zzy(paramInt);
      l = paramInt & 0xFFFFF;
      switch (i)
      {
      default: 
        throw new IllegalArgumentException();
      case 17: 
        return zzgsa.zzh(paramObject, l) != null;
      case 16: 
        return zzgsa.zzf(paramObject, l) != 0L;
      case 15: 
        return zzgsa.zzd(paramObject, l) != 0;
      case 14: 
        return zzgsa.zzf(paramObject, l) != 0L;
      case 13: 
        return zzgsa.zzd(paramObject, l) != 0;
      case 12: 
        return zzgsa.zzd(paramObject, l) != 0;
      case 11: 
        return zzgsa.zzd(paramObject, l) != 0;
      case 10: 
        return !zzgno.zzb.equals(zzgsa.zzh(paramObject, l));
      case 9: 
        return zzgsa.zzh(paramObject, l) != null;
      case 8: 
        paramObject = zzgsa.zzh(paramObject, l);
        if ((paramObject instanceof String)) {
          return !((String)paramObject).isEmpty();
        }
        if ((paramObject instanceof zzgno)) {
          return !zzgno.zzb.equals(paramObject);
        }
        throw new IllegalArgumentException();
      case 7: 
        return zzgsa.zzz(paramObject, l);
      case 6: 
        return zzgsa.zzd(paramObject, l) != 0;
      case 5: 
        return zzgsa.zzf(paramObject, l) != 0L;
      case 4: 
        return zzgsa.zzd(paramObject, l) != 0;
      case 3: 
        return zzgsa.zzf(paramObject, l) != 0L;
      case 2: 
        return zzgsa.zzf(paramObject, l) != 0L;
      case 1: 
        return Float.floatToRawIntBits(zzgsa.zzc(paramObject, l)) != 0;
      }
      return Double.doubleToRawLongBits(zzgsa.zzb(paramObject, l)) != 0L;
    }
    return (zzgsa.zzd(paramObject, l) & 1 << (i >>> 20)) != 0;
  }
  
  private final boolean zzT(Object paramObject, int paramInt1, int paramInt2, int paramInt3, int paramInt4)
  {
    if (paramInt2 == 1048575) {
      return zzS(paramObject, paramInt1);
    }
    return (paramInt3 & paramInt4) != 0;
  }
  
  private static boolean zzU(Object paramObject, int paramInt, zzgqz paramzzgqz)
  {
    return paramzzgqz.zzk(zzgsa.zzh(paramObject, paramInt & 0xFFFFF));
  }
  
  private static boolean zzV(Object paramObject)
  {
    if (paramObject == null) {
      return false;
    }
    if ((paramObject instanceof zzgow)) {
      return ((zzgow)paramObject).zzaY();
    }
    return true;
  }
  
  private final boolean zzW(Object paramObject, int paramInt1, int paramInt2)
  {
    return zzgsa.zzd(paramObject, zzw(paramInt2) & 0xFFFFF) == paramInt1;
  }
  
  private static boolean zzX(Object paramObject, long paramLong)
  {
    return ((Boolean)zzgsa.zzh(paramObject, paramLong)).booleanValue();
  }
  
  private final void zzY(zzgoe paramzzgoe, int paramInt1, Object paramObject, int paramInt2)
    throws IOException
  {
    if (paramObject == null) {
      return;
    }
    paramzzgoe = (zzgpz)zzE(paramInt2);
    throw null;
  }
  
  private static final void zzZ(int paramInt, Object paramObject, zzgoe paramzzgoe)
    throws IOException
  {
    if ((paramObject instanceof String))
    {
      paramzzgoe.zzF(paramInt, (String)paramObject);
      return;
    }
    paramzzgoe.zzd(paramInt, (zzgno)paramObject);
  }
  
  static zzgrr zzd(Object paramObject)
  {
    zzgow localzzgow = (zzgow)paramObject;
    zzgrr localzzgrr = localzzgow.zzc;
    paramObject = localzzgrr;
    if (localzzgrr == zzgrr.zzc())
    {
      paramObject = zzgrr.zzf();
      localzzgow.zzc = ((zzgrr)paramObject);
    }
    return (zzgrr)paramObject;
  }
  
  static zzgqj zzl(Class paramClass, zzgqd paramzzgqd, zzgql paramzzgql, zzgpu paramzzgpu, zzgrq paramzzgrq, zzgoj paramzzgoj, zzgqb paramzzgqb)
  {
    if ((paramzzgqd instanceof zzgqq))
    {
      zzgqq localzzgqq = (zzgqq)paramzzgqd;
      int i9 = localzzgqq.zzc();
      String str = localzzgqq.zzd();
      int i7 = str.length();
      int i5 = 0;
      if (str.charAt(0) >= 55296) {
        for (i = 1;; i = k)
        {
          k = i + 1;
          j = k;
          if (str.charAt(i) < 55296) {
            break;
          }
        }
      }
      int j = 1;
      int i = j + 1;
      int m = str.charAt(j);
      j = i;
      int k = m;
      if (m >= 55296)
      {
        k = m & 0x1FFF;
        j = 13;
        for (m = i;; m = i)
        {
          i = m + 1;
          m = str.charAt(m);
          if (m < 55296) {
            break;
          }
          k |= (m & 0x1FFF) << j;
          j += 13;
        }
        k |= m << j;
        j = i;
      }
      int i1;
      int i4;
      if (k == 0)
      {
        paramClass = zza;
        i = 0;
        i1 = 0;
        m = 0;
        n = 0;
        i2 = 0;
        k = 0;
      }
      else
      {
        k = j + 1;
        j = str.charAt(j);
        i = j;
        m = k;
        if (j >= 55296)
        {
          j &= 0x1FFF;
          i = 13;
          m = k;
          k = j;
          for (;;)
          {
            j = m + 1;
            m = str.charAt(m);
            if (m < 55296) {
              break;
            }
            k |= (m & 0x1FFF) << i;
            i += 13;
            m = j;
          }
          i = k | m << i;
          m = j;
        }
        j = m + 1;
        k = str.charAt(m);
        i3 = k;
        m = j;
        if (k >= 55296)
        {
          m = k & 0x1FFF;
          k = 13;
          for (n = j;; n = j)
          {
            j = n + 1;
            n = str.charAt(n);
            if (n < 55296) {
              break;
            }
            m |= (n & 0x1FFF) << k;
            k += 13;
          }
          i3 = m | n << k;
          m = j;
        }
        k = m + 1;
        m = str.charAt(m);
        j = m;
        n = k;
        if (m >= 55296)
        {
          m &= 0x1FFF;
          j = 13;
          for (n = k;; n = k)
          {
            k = n + 1;
            n = str.charAt(n);
            if (n < 55296) {
              break;
            }
            m |= (n & 0x1FFF) << j;
            j += 13;
          }
          j = m | n << j;
          n = k;
        }
        m = n + 1;
        n = str.charAt(n);
        k = n;
        i1 = m;
        if (n >= 55296)
        {
          k = n & 0x1FFF;
          n = 13;
          i1 = m;
          m = k;
          for (;;)
          {
            k = i1 + 1;
            i1 = str.charAt(i1);
            if (i1 < 55296) {
              break;
            }
            m |= (i1 & 0x1FFF) << n;
            n += 13;
            i1 = k;
          }
          m |= i1 << n;
          i1 = k;
          k = m;
        }
        n = i1 + 1;
        i1 = str.charAt(i1);
        m = i1;
        i2 = n;
        if (i1 >= 55296)
        {
          i1 &= 0x1FFF;
          m = 13;
          for (i2 = n;; i2 = n)
          {
            n = i2 + 1;
            i2 = str.charAt(i2);
            if (i2 < 55296) {
              break;
            }
            i1 |= (i2 & 0x1FFF) << m;
            m += 13;
          }
          m = i1 | i2 << m;
          i2 = n;
        }
        i1 = i2 + 1;
        i2 = str.charAt(i2);
        n = i2;
        i4 = i1;
        if (i2 >= 55296)
        {
          n = i2 & 0x1FFF;
          i2 = 13;
          i4 = i1;
          i1 = n;
          for (;;)
          {
            n = i4 + 1;
            i4 = str.charAt(i4);
            if (i4 < 55296) {
              break;
            }
            i1 |= (i4 & 0x1FFF) << i2;
            i2 += 13;
            i4 = n;
          }
          i1 |= i4 << i2;
          i4 = n;
          n = i1;
        }
        i2 = i4 + 1;
        i5 = str.charAt(i4);
        i4 = i5;
        i1 = i2;
        if (i5 >= 55296)
        {
          i4 = i5 & 0x1FFF;
          i1 = 13;
          for (i5 = i2;; i5 = i2)
          {
            i2 = i5 + 1;
            i5 = str.charAt(i5);
            if (i5 < 55296) {
              break;
            }
            i4 |= (i5 & 0x1FFF) << i1;
            i1 += 13;
          }
          i4 |= i5 << i1;
          i1 = i2;
        }
        i5 = i1 + 1;
        i6 = str.charAt(i1);
        i2 = i6;
        i1 = i5;
        if (i6 >= 55296)
        {
          i1 = i6 & 0x1FFF;
          i6 = i5;
          i2 = 13;
          i5 = i1;
          for (;;)
          {
            i1 = i6 + 1;
            i6 = str.charAt(i6);
            if (i6 < 55296) {
              break;
            }
            i5 |= (i6 & 0x1FFF) << i2;
            i2 += 13;
            i6 = i1;
          }
          i2 = i5 | i6 << i2;
        }
        paramClass = new int[i2 + n + i4];
        i5 = i;
        i4 = i + i + i3;
        i3 = i1;
        i = k;
        k = i2;
        i2 = i;
        i1 = i4;
        i = j;
        j = i3;
      }
      Unsafe localUnsafe = zzb;
      paramzzgqd = localzzgqq.zze();
      Class localClass = localzzgqq.zza().getClass();
      int i16 = k + n;
      int[] arrayOfInt = new int[m * 3];
      Object[] arrayOfObject = new Object[m + m];
      int n = k;
      m = i16;
      int i3 = 0;
      int i8 = 0;
      int i6 = i2;
      int i2 = j;
      j = i9;
      boolean bool;
      for (;;)
      {
        if (j == 2) {
          bool = true;
        } else {
          bool = false;
        }
        if (i2 >= i7) {
          break;
        }
        i4 = i2 + 1;
        i9 = str.charAt(i2);
        if (i9 >= 55296)
        {
          i9 &= 0x1FFF;
          i2 = 13;
          i10 = i4;
          i4 = i9;
          for (;;)
          {
            i9 = i10 + 1;
            i10 = str.charAt(i10);
            if (i10 < 55296) {
              break;
            }
            i4 |= (i10 & 0x1FFF) << i2;
            i2 += 13;
            i10 = i9;
          }
          i4 |= i10 << i2;
          i2 = i9;
          i9 = i4;
        }
        else
        {
          i2 = i4;
        }
        i4 = i2 + 1;
        int i10 = str.charAt(i2);
        int i11 = i10;
        i2 = i4;
        if (i10 >= 55296)
        {
          i2 = i10 & 0x1FFF;
          i10 = 13;
          i11 = i4;
          i4 = i2;
          for (;;)
          {
            i2 = i11 + 1;
            i11 = str.charAt(i11);
            if (i11 < 55296) {
              break;
            }
            i4 |= (i11 & 0x1FFF) << i10;
            i10 += 13;
            i11 = i2;
          }
          i11 = i4 | i11 << i10;
        }
        i10 = i3;
        if ((i11 & 0x400) != 0)
        {
          paramClass[i3] = i8;
          i10 = i3 + 1;
        }
        int i17 = i11 & 0xFF;
        int i12;
        label1735:
        Field localField1;
        int i13;
        if (i17 >= 51)
        {
          i3 = i2 + 1;
          i4 = str.charAt(i2);
          if (i4 >= 55296)
          {
            i4 &= 0x1FFF;
            i2 = 13;
            for (i12 = i3;; i12 = i3)
            {
              i3 = i12 + 1;
              i12 = str.charAt(i12);
              if (i12 < 55296) {
                break;
              }
              i4 |= (i12 & 0x1FFF) << i2;
              i2 += 13;
            }
            i4 |= i12 << i2;
            i2 = i3;
          }
          else
          {
            i2 = i3;
          }
          i12 = i17 - 51;
          if ((i12 != 9) && (i12 != 17))
          {
            i3 = i1;
            if (i12 != 12) {
              break label1735;
            }
            i3 = i1;
            if (bool) {
              break label1735;
            }
            i12 = i8 / 3;
            i3 = i1 + 1;
            arrayOfObject[(i12 + i12 + 1)] = paramzzgqd[i1];
            i1 = i3;
          }
          else
          {
            i12 = i8 / 3;
            i3 = i1 + 1;
            arrayOfObject[(i12 + i12 + 1)] = paramzzgqd[i1];
            i1 = i3;
          }
          i3 = i1;
          i1 = i4 + i4;
          localField1 = paramzzgqd[i1];
          if ((localField1 instanceof Field))
          {
            localField1 = (Field)localField1;
          }
          else
          {
            localField1 = zzH(localClass, (String)localField1);
            paramzzgqd[i1] = localField1;
          }
          i13 = (int)localUnsafe.objectFieldOffset(localField1);
          i1++;
          localField1 = paramzzgqd[i1];
          if ((localField1 instanceof Field))
          {
            localField1 = (Field)localField1;
          }
          else
          {
            localField1 = zzH(localClass, (String)localField1);
            paramzzgqd[i1] = localField1;
          }
          i12 = (int)localUnsafe.objectFieldOffset(localField1);
          i14 = i2;
          i2 = 0;
          i1 = i3;
          i4 = m;
          m = i14;
        }
        else
        {
          i12 = i;
          i3 = i1 + 1;
          Field localField2 = zzH(localClass, (String)paramzzgqd[i1]);
          if ((i17 != 9) && (i17 != 17))
          {
            if ((i17 != 27) && (i17 != 49))
            {
              if ((i17 != 12) && (i17 != 30) && (i17 != 44))
              {
                if (i17 == 50)
                {
                  i = n + 1;
                  paramClass[n] = i8;
                  n = i8 / 3;
                  i1 = i3 + 1;
                  localField1 = paramzzgqd[i3];
                  n += n;
                  arrayOfObject[n] = localField1;
                  if ((i11 & 0x800) != 0)
                  {
                    i3 = i1 + 1;
                    arrayOfObject[(n + 1)] = paramzzgqd[i1];
                    n = i;
                    i = i3;
                    break label2147;
                  }
                  n = i;
                  i = i1;
                  break label2147;
                }
              }
              else if (!bool)
              {
                i1 = i8 / 3;
                i = i3 + 1;
                arrayOfObject[(i1 + i1 + 1)] = paramzzgqd[i3];
                break label2119;
              }
              i = i3;
              break label2147;
            }
            else
            {
              i1 = i8 / 3;
              i = i3 + 1;
              arrayOfObject[(i1 + i1 + 1)] = paramzzgqd[i3];
            }
          }
          else
          {
            label2119:
            i = i8 / 3;
            arrayOfObject[(i + i + 1)] = localField2.getType();
            i = i3;
          }
          label2147:
          i14 = (int)localUnsafe.objectFieldOffset(localField2);
          i4 = 1048575;
          if (((i11 & 0x1000) == 4096) && (i17 <= 17))
          {
            i4 = i2 + 1;
            i2 = str.charAt(i2);
            if (i2 >= 55296)
            {
              i3 = i2 & 0x1FFF;
              i2 = 13;
              for (;;)
              {
                i1 = i4 + 1;
                i4 = str.charAt(i4);
                if (i4 < 55296) {
                  break;
                }
                i3 |= (i4 & 0x1FFF) << i2;
                i2 += 13;
                i4 = i1;
              }
              i2 = i3 | i4 << i2;
            }
            else
            {
              i1 = i4;
            }
            i3 = i5 + i5 + i2 / 32;
            localField1 = paramzzgqd[i3];
            if ((localField1 instanceof Field))
            {
              localField1 = (Field)localField1;
            }
            else
            {
              localField1 = zzH(localClass, (String)localField1);
              paramzzgqd[i3] = localField1;
            }
            i4 = (int)localUnsafe.objectFieldOffset(localField1);
            i2 %= 32;
          }
          else
          {
            i1 = i2;
            i2 = 0;
          }
          i3 = m;
          if (i17 >= 18)
          {
            i3 = m;
            if (i17 <= 49)
            {
              paramClass[m] = i14;
              i3 = m + 1;
            }
          }
          i13 = i;
          int i15 = i4;
          i = i12;
          m = i1;
          i4 = i3;
          i1 = i13;
          i13 = i14;
          i12 = i15;
        }
        int i14 = i8 + 1;
        arrayOfInt[i8] = i9;
        i9 = i14 + 1;
        if ((i11 & 0x200) != 0) {
          i3 = 536870912;
        } else {
          i3 = 0;
        }
        if ((i11 & 0x100) != 0) {
          i8 = 268435456;
        } else {
          i8 = 0;
        }
        arrayOfInt[i14] = (i8 | i3 | i17 << 20 | i13);
        i8 = i9 + 1;
        arrayOfInt[i9] = (i2 << 20 | i12);
        i2 = m;
        i3 = i10;
        m = i4;
      }
      return new zzgqj(arrayOfInt, arrayOfObject, i, i6, localzzgqq.zza(), bool, false, paramClass, k, i16, paramzzgql, paramzzgpu, paramzzgrq, paramzzgoj, paramzzgqb);
    }
    paramClass = (zzgrn)paramzzgqd;
    throw null;
  }
  
  private static double zzn(Object paramObject, long paramLong)
  {
    return ((Double)zzgsa.zzh(paramObject, paramLong)).doubleValue();
  }
  
  private static float zzo(Object paramObject, long paramLong)
  {
    return ((Float)zzgsa.zzh(paramObject, paramLong)).floatValue();
  }
  
  private final int zzp(Object paramObject)
  {
    Object localObject1 = zzb;
    int n = 0;
    int m = 0;
    int i = 1048575;
    int i2;
    for (int j = 0; n < this.zzc.length; j = i2)
    {
      int i3 = zzz(n);
      Object localObject2 = this.zzc;
      int i4 = localObject2[n];
      int i5 = zzy(i3);
      int i1;
      int k;
      if (i5 <= 17)
      {
        i2 = localObject2[(n + 2)];
        i1 = i2 & 0xFFFFF;
        k = i;
        if (i1 != i)
        {
          j = ((Unsafe)localObject1).getInt(paramObject, i1);
          k = i1;
        }
        i = 1 << (i2 >>> 20);
        i1 = k;
        i2 = j;
        k = i;
      }
      else
      {
        k = 0;
        i2 = j;
        i1 = i;
      }
      long l = i3 & 0xFFFFF;
      switch (i5)
      {
      default: 
        i = m;
        break;
      case 68: 
        i = m;
        if (zzW(paramObject, i4, n)) {
          i = zzgod.zzw(i4, (zzgqg)((Unsafe)localObject1).getObject(paramObject, l), zzC(n));
        }
        break;
      case 67: 
        i = m;
        if (zzW(paramObject, i4, n))
        {
          l = zzA(paramObject, l);
          i = m + (zzgod.zzA(i4 << 3) + zzgod.zzB(l >> 63 ^ l + l));
        }
        break;
      case 66: 
        i = m;
        if (zzW(paramObject, i4, n))
        {
          i = zzq(paramObject, l);
          j = zzgod.zzA(i4 << 3);
          i = zzgod.zzA(i >> 31 ^ i + i);
        }
        break;
      case 65: 
        i = m;
        if (zzW(paramObject, i4, n)) {
          i = zzgod.zzA(i4 << 3);
        }
        break;
      case 64: 
        i = m;
        if (zzW(paramObject, i4, n)) {
          i = zzgod.zzA(i4 << 3);
        }
        break;
      case 63: 
        i = m;
        if (zzW(paramObject, i4, n))
        {
          i = zzgod.zzx(zzq(paramObject, l));
          j = zzgod.zzA(i4 << 3);
        }
        break;
      case 62: 
        i = m;
        if (zzW(paramObject, i4, n))
        {
          i = zzgod.zzA(zzq(paramObject, l));
          j = zzgod.zzA(i4 << 3);
        }
        break;
      case 61: 
        i = m;
        if (zzW(paramObject, i4, n))
        {
          localObject2 = (zzgno)((Unsafe)localObject1).getObject(paramObject, l);
          i = zzgod.zzf;
          i = ((zzgno)localObject2).zzd();
          i = zzgod.zzA(i) + i;
        }
      case 60: 
      case 59: 
        for (j = zzgod.zzA(i4 << 3);; j = zzgod.zzA(i4 << 3))
        {
          i = j + i;
          break label2025;
          i = m;
          if (!zzW(paramObject, i4, n)) {
            break label2030;
          }
          i = zzgrb.zzn(i4, ((Unsafe)localObject1).getObject(paramObject, l), zzC(n));
          break label2025;
          i = m;
          if (!zzW(paramObject, i4, n)) {
            break label2030;
          }
          localObject2 = ((Unsafe)localObject1).getObject(paramObject, l);
          if (!(localObject2 instanceof zzgno)) {
            break;
          }
          localObject2 = (zzgno)localObject2;
          i = zzgod.zzf;
          i = ((zzgno)localObject2).zzd();
          i = zzgod.zzA(i) + i;
        }
        i = zzgod.zzz((String)localObject2);
        j = zzgod.zzA(i4 << 3);
        break;
      case 58: 
        i = m;
        if (zzW(paramObject, i4, n)) {
          i = zzgod.zzA(i4 << 3) + 1;
        }
        break;
      case 57: 
        i = m;
        if (zzW(paramObject, i4, n)) {
          i = zzgod.zzA(i4 << 3);
        }
        break;
      case 56: 
        i = m;
        if (zzW(paramObject, i4, n)) {
          i = zzgod.zzA(i4 << 3);
        }
        break;
      case 55: 
        i = m;
        if (zzW(paramObject, i4, n))
        {
          i = zzgod.zzx(zzq(paramObject, l));
          j = zzgod.zzA(i4 << 3);
        }
        break;
      case 54: 
        i = m;
        if (zzW(paramObject, i4, n))
        {
          i = zzgod.zzB(zzA(paramObject, l));
          j = zzgod.zzA(i4 << 3);
        }
        break;
      case 53: 
        i = m;
        if (zzW(paramObject, i4, n))
        {
          i = zzgod.zzB(zzA(paramObject, l));
          j = zzgod.zzA(i4 << 3);
        }
        break;
      case 52: 
        i = m;
        if (zzW(paramObject, i4, n))
        {
          i = zzgod.zzA(i4 << 3);
          i += 4;
        }
        break;
      case 51: 
        i = m;
        if (zzW(paramObject, i4, n))
        {
          i = zzgod.zzA(i4 << 3);
          i += 8;
        }
        break;
      case 50: 
        zzgqb.zza(i4, ((Unsafe)localObject1).getObject(paramObject, l), zzE(n));
        i = m;
        break;
      case 49: 
        i = zzgrb.zzi(i4, (List)((Unsafe)localObject1).getObject(paramObject, l), zzC(n));
        break;
      case 48: 
        j = zzgrb.zzs((List)((Unsafe)localObject1).getObject(paramObject, l));
        i = m;
        if (j > 0)
        {
          k = zzgod.zzA(j);
          i3 = zzgod.zzA(i4 << 3);
          i = j;
          j = i3;
        }
        break;
      case 47: 
        j = zzgrb.zzq((List)((Unsafe)localObject1).getObject(paramObject, l));
        i = m;
        if (j > 0)
        {
          k = zzgod.zzA(j);
          i3 = zzgod.zzA(i4 << 3);
          i = j;
          j = i3;
        }
        break;
      case 46: 
        j = zzgrb.zzh((List)((Unsafe)localObject1).getObject(paramObject, l));
        i = m;
        if (j > 0)
        {
          k = zzgod.zzA(j);
          i3 = zzgod.zzA(i4 << 3);
          i = j;
          j = i3;
        }
        break;
      case 45: 
        j = zzgrb.zzf((List)((Unsafe)localObject1).getObject(paramObject, l));
        i = m;
        if (j > 0)
        {
          k = zzgod.zzA(j);
          i3 = zzgod.zzA(i4 << 3);
          i = j;
          j = i3;
        }
        break;
      case 44: 
        j = zzgrb.zzd((List)((Unsafe)localObject1).getObject(paramObject, l));
        i = m;
        if (j > 0)
        {
          k = zzgod.zzA(j);
          i3 = zzgod.zzA(i4 << 3);
          i = j;
          j = i3;
        }
        break;
      case 43: 
        j = zzgrb.zzv((List)((Unsafe)localObject1).getObject(paramObject, l));
        i = m;
        if (j > 0)
        {
          k = zzgod.zzA(j);
          i3 = zzgod.zzA(i4 << 3);
          i = j;
          j = i3;
        }
        break;
      case 42: 
        localObject2 = (List)((Unsafe)localObject1).getObject(paramObject, l);
        i = zzgrb.zza;
        j = ((List)localObject2).size();
        i = m;
        if (j > 0)
        {
          k = zzgod.zzA(j);
          i3 = zzgod.zzA(i4 << 3);
          i = j;
          j = i3;
        }
        break;
      case 41: 
        j = zzgrb.zzf((List)((Unsafe)localObject1).getObject(paramObject, l));
        i = m;
        if (j > 0)
        {
          k = zzgod.zzA(j);
          i3 = zzgod.zzA(i4 << 3);
          i = j;
          j = i3;
        }
        break;
      case 40: 
        j = zzgrb.zzh((List)((Unsafe)localObject1).getObject(paramObject, l));
        i = m;
        if (j > 0)
        {
          k = zzgod.zzA(j);
          i3 = zzgod.zzA(i4 << 3);
          i = j;
          j = i3;
        }
        break;
      case 39: 
        j = zzgrb.zzk((List)((Unsafe)localObject1).getObject(paramObject, l));
        i = m;
        if (j > 0)
        {
          k = zzgod.zzA(j);
          i3 = zzgod.zzA(i4 << 3);
          i = j;
          j = i3;
        }
        break;
      case 38: 
        j = zzgrb.zzx((List)((Unsafe)localObject1).getObject(paramObject, l));
        i = m;
        if (j > 0)
        {
          k = zzgod.zzA(j);
          i3 = zzgod.zzA(i4 << 3);
          i = j;
          j = i3;
        }
        break;
      case 37: 
        j = zzgrb.zzm((List)((Unsafe)localObject1).getObject(paramObject, l));
        i = m;
        if (j > 0)
        {
          k = zzgod.zzA(j);
          i3 = zzgod.zzA(i4 << 3);
          i = j;
          j = i3;
        }
        break;
      case 36: 
        j = zzgrb.zzf((List)((Unsafe)localObject1).getObject(paramObject, l));
        i = m;
        if (j > 0)
        {
          k = zzgod.zzA(j);
          i3 = zzgod.zzA(i4 << 3);
          i = j;
          j = i3;
        }
        break;
      case 35: 
        i3 = zzgrb.zzh((List)((Unsafe)localObject1).getObject(paramObject, l));
        i = m;
        if (i3 > 0)
        {
          k = zzgod.zzA(i3);
          j = zzgod.zzA(i4 << 3);
          i = i3;
          j += k;
          i = m + (j + i);
        }
        break;
      case 34: 
        i = zzgrb.zzr(i4, (List)((Unsafe)localObject1).getObject(paramObject, l), false);
        break;
      case 33: 
        i = zzgrb.zzp(i4, (List)((Unsafe)localObject1).getObject(paramObject, l), false);
        break;
      case 32: 
        i = zzgrb.zzg(i4, (List)((Unsafe)localObject1).getObject(paramObject, l), false);
        break;
      case 31: 
        i = zzgrb.zze(i4, (List)((Unsafe)localObject1).getObject(paramObject, l), false);
        break;
      case 30: 
        i = zzgrb.zzc(i4, (List)((Unsafe)localObject1).getObject(paramObject, l), false);
        break;
      case 29: 
        i = zzgrb.zzu(i4, (List)((Unsafe)localObject1).getObject(paramObject, l), false);
        break;
      case 28: 
        i = zzgrb.zzb(i4, (List)((Unsafe)localObject1).getObject(paramObject, l));
        break;
      case 27: 
        i = zzgrb.zzo(i4, (List)((Unsafe)localObject1).getObject(paramObject, l), zzC(n));
        break;
      case 26: 
        i = zzgrb.zzt(i4, (List)((Unsafe)localObject1).getObject(paramObject, l));
        i = m + i;
        break;
      case 25: 
        i = zzgrb.zza(i4, (List)((Unsafe)localObject1).getObject(paramObject, l), false);
        break;
      case 24: 
        i = zzgrb.zze(i4, (List)((Unsafe)localObject1).getObject(paramObject, l), false);
        break;
      case 23: 
        i = zzgrb.zzg(i4, (List)((Unsafe)localObject1).getObject(paramObject, l), false);
        break;
      case 22: 
        i = zzgrb.zzj(i4, (List)((Unsafe)localObject1).getObject(paramObject, l), false);
        break;
      case 21: 
        i = zzgrb.zzw(i4, (List)((Unsafe)localObject1).getObject(paramObject, l), false);
        break;
      case 20: 
        i = zzgrb.zzl(i4, (List)((Unsafe)localObject1).getObject(paramObject, l), false);
        break;
      case 19: 
        i = zzgrb.zze(i4, (List)((Unsafe)localObject1).getObject(paramObject, l), false);
        break;
      case 18: 
        label2025:
        label2030:
        i = zzgrb.zzg(i4, (List)((Unsafe)localObject1).getObject(paramObject, l), false);
      }
      for (;;)
      {
        i = m + i;
        break;
        i = m;
        if ((i2 & k) == 0) {
          break;
        }
        i = zzgod.zzw(i4, (zzgqg)((Unsafe)localObject1).getObject(paramObject, l), zzC(n));
        continue;
        i = m;
        if ((k & i2) == 0) {
          break;
        }
        l = ((Unsafe)localObject1).getLong(paramObject, l);
        i = m + (zzgod.zzA(i4 << 3) + zzgod.zzB(l >> 63 ^ l + l));
        break;
        i = m;
        if ((i2 & k) == 0) {
          break;
        }
        i = ((Unsafe)localObject1).getInt(paramObject, l);
        j = zzgod.zzA(i4 << 3);
        i = zzgod.zzA(i >> 31 ^ i + i);
        break label2789;
        i = m;
        if ((i2 & k) == 0) {
          break;
        }
        i = zzgod.zzA(i4 << 3);
        break label2843;
        i = m;
        if ((i2 & k) == 0) {
          break;
        }
        i = zzgod.zzA(i4 << 3);
        break label2818;
        i = m;
        if ((i2 & k) == 0) {
          break;
        }
        i = zzgod.zzx(((Unsafe)localObject1).getInt(paramObject, l));
        j = zzgod.zzA(i4 << 3);
        break label2789;
        i = m;
        if ((i2 & k) == 0) {
          break;
        }
        i = zzgod.zzA(((Unsafe)localObject1).getInt(paramObject, l));
        j = zzgod.zzA(i4 << 3);
        break label2789;
        i = m;
        if ((i2 & k) == 0) {
          break;
        }
        localObject2 = (zzgno)((Unsafe)localObject1).getObject(paramObject, l);
        i = zzgod.zzf;
        i = ((zzgno)localObject2).zzd();
        j = zzgod.zzA(i) + i;
        for (i = zzgod.zzA(i4 << 3);; i = zzgod.zzA(i4 << 3))
        {
          i += j;
          break;
          i = m;
          if ((i2 & k) == 0) {
            break label2849;
          }
          i = zzgrb.zzn(i4, ((Unsafe)localObject1).getObject(paramObject, l), zzC(n));
          break;
          i = m;
          if ((i2 & k) == 0) {
            break label2849;
          }
          localObject2 = ((Unsafe)localObject1).getObject(paramObject, l);
          if (!(localObject2 instanceof zzgno)) {
            break label2602;
          }
          localObject2 = (zzgno)localObject2;
          i = zzgod.zzf;
          i = ((zzgno)localObject2).zzd();
          j = zzgod.zzA(i) + i;
        }
        label2602:
        i = zzgod.zzz((String)localObject2);
        j = zzgod.zzA(i4 << 3);
        break label2789;
        i = m;
        if ((i2 & k) == 0) {
          break;
        }
        i = zzgod.zzA(i4 << 3) + 1;
        continue;
        i = m;
        if ((i2 & k) == 0) {
          break;
        }
        i = zzgod.zzA(i4 << 3);
        break label2818;
        i = m;
        if ((i2 & k) == 0) {
          break;
        }
        i = zzgod.zzA(i4 << 3);
        break label2843;
        i = m;
        if ((i2 & k) == 0) {
          break;
        }
        i = zzgod.zzx(((Unsafe)localObject1).getInt(paramObject, l));
        j = zzgod.zzA(i4 << 3);
        break label2789;
        i = m;
        if ((i2 & k) == 0) {
          break;
        }
        i = zzgod.zzB(((Unsafe)localObject1).getLong(paramObject, l));
        j = zzgod.zzA(i4 << 3);
        break label2789;
        i = m;
        if ((i2 & k) == 0) {
          break;
        }
        i = zzgod.zzB(((Unsafe)localObject1).getLong(paramObject, l));
        j = zzgod.zzA(i4 << 3);
        label2789:
        i = m + (j + i);
        break;
        i = m;
        if ((i2 & k) == 0) {
          break;
        }
        i = zzgod.zzA(i4 << 3);
        label2818:
        i += 4;
        continue;
        i = m;
        if ((i2 & k) == 0) {
          break;
        }
        i = zzgod.zzA(i4 << 3);
        label2843:
        i += 8;
      }
      label2849:
      n += 3;
      m = i;
      i = i1;
    }
    localObject1 = this.zzo;
    i = ((zzgrq)localObject1).zza(((zzgrq)localObject1).zzd(paramObject));
    if (!this.zzh) {
      return m + i;
    }
    this.zzp.zza(paramObject);
    throw null;
  }
  
  private static int zzq(Object paramObject, long paramLong)
  {
    return ((Integer)zzgsa.zzh(paramObject, paramLong)).intValue();
  }
  
  private final int zzr(Object paramObject, byte[] paramArrayOfByte, int paramInt1, int paramInt2, int paramInt3, long paramLong, zzgna paramzzgna)
    throws IOException
  {
    Unsafe localUnsafe = zzb;
    paramzzgna = zzE(paramInt3);
    paramArrayOfByte = localUnsafe.getObject(paramObject, paramLong);
    if (zzgqb.zzb(paramArrayOfByte))
    {
      zzgqa localzzgqa = zzgqa.zza().zzb();
      zzgqb.zzc(localzzgqa, paramArrayOfByte);
      localUnsafe.putObject(paramObject, paramLong, localzzgqa);
    }
    paramObject = (zzgpz)paramzzgna;
    throw null;
  }
  
  private final int zzs(Object paramObject, byte[] paramArrayOfByte, int paramInt1, int paramInt2, int paramInt3, int paramInt4, int paramInt5, int paramInt6, int paramInt7, long paramLong, int paramInt8, zzgna paramzzgna)
    throws IOException
  {
    Object localObject = zzb;
    long l = this.zzc[(paramInt8 + 2)] & 0xFFFFF;
    switch (paramInt7)
    {
    default: 
      break;
    case 68: 
      if (paramInt5 == 3)
      {
        localObject = zzG(paramObject, paramInt4, paramInt8);
        paramInt1 = zzgnb.zzn(localObject, zzC(paramInt8), paramArrayOfByte, paramInt1, paramInt2, paramInt3 & 0xFFFFFFF8 | 0x4, paramzzgna);
        zzP(paramObject, paramInt4, paramInt8, localObject);
        return paramInt1;
      }
      break;
    case 67: 
      if (paramInt5 == 0)
      {
        paramInt1 = zzgnb.zzm(paramArrayOfByte, paramInt1, paramzzgna);
        ((Unsafe)localObject).putObject(paramObject, paramLong, Long.valueOf(zzgnw.zzG(paramzzgna.zzb)));
        ((Unsafe)localObject).putInt(paramObject, l, paramInt4);
        return paramInt1;
      }
      break;
    case 66: 
      if (paramInt5 == 0)
      {
        paramInt1 = zzgnb.zzj(paramArrayOfByte, paramInt1, paramzzgna);
        ((Unsafe)localObject).putObject(paramObject, paramLong, Integer.valueOf(zzgnw.zzF(paramzzgna.zza)));
        ((Unsafe)localObject).putInt(paramObject, l, paramInt4);
        return paramInt1;
      }
      break;
    case 63: 
      if (paramInt5 == 0)
      {
        paramInt1 = zzgnb.zzj(paramArrayOfByte, paramInt1, paramzzgna);
        paramInt2 = paramzzgna.zza;
        paramArrayOfByte = zzB(paramInt8);
        if ((paramArrayOfByte != null) && (!paramArrayOfByte.zza(paramInt2)))
        {
          zzd(paramObject).zzj(paramInt3, Long.valueOf(paramInt2));
        }
        else
        {
          ((Unsafe)localObject).putObject(paramObject, paramLong, Integer.valueOf(paramInt2));
          ((Unsafe)localObject).putInt(paramObject, l, paramInt4);
        }
      }
      break;
    case 61: 
      if (paramInt5 == 2)
      {
        paramInt1 = zzgnb.zza(paramArrayOfByte, paramInt1, paramzzgna);
        ((Unsafe)localObject).putObject(paramObject, paramLong, paramzzgna.zzc);
        ((Unsafe)localObject).putInt(paramObject, l, paramInt4);
        return paramInt1;
      }
      break;
    case 60: 
      if (paramInt5 == 2)
      {
        localObject = zzG(paramObject, paramInt4, paramInt8);
        paramInt1 = zzgnb.zzo(localObject, zzC(paramInt8), paramArrayOfByte, paramInt1, paramInt2, paramzzgna);
        zzP(paramObject, paramInt4, paramInt8, localObject);
        return paramInt1;
      }
      break;
    case 59: 
      if (paramInt5 == 2)
      {
        paramInt1 = zzgnb.zzj(paramArrayOfByte, paramInt1, paramzzgna);
        paramInt2 = paramzzgna.zza;
        if (paramInt2 == 0)
        {
          ((Unsafe)localObject).putObject(paramObject, paramLong, "");
        }
        else
        {
          if (((paramInt6 & 0x20000000) != 0) && (!zzgsf.zzj(paramArrayOfByte, paramInt1, paramInt1 + paramInt2))) {
            throw zzgpi.zzd();
          }
          ((Unsafe)localObject).putObject(paramObject, paramLong, new String(paramArrayOfByte, paramInt1, paramInt2, zzgpg.zzb));
          paramInt1 += paramInt2;
        }
        ((Unsafe)localObject).putInt(paramObject, l, paramInt4);
      }
      break;
    case 58: 
      if (paramInt5 == 0)
      {
        paramInt1 = zzgnb.zzm(paramArrayOfByte, paramInt1, paramzzgna);
        boolean bool;
        if (paramzzgna.zzb != 0L) {
          bool = true;
        } else {
          bool = false;
        }
        ((Unsafe)localObject).putObject(paramObject, paramLong, Boolean.valueOf(bool));
        ((Unsafe)localObject).putInt(paramObject, l, paramInt4);
        return paramInt1;
      }
      break;
    case 57: 
    case 64: 
      if (paramInt5 == 5)
      {
        ((Unsafe)localObject).putObject(paramObject, paramLong, Integer.valueOf(zzgnb.zzb(paramArrayOfByte, paramInt1)));
        ((Unsafe)localObject).putInt(paramObject, l, paramInt4);
        return paramInt1 + 4;
      }
      break;
    case 56: 
    case 65: 
      if (paramInt5 == 1)
      {
        ((Unsafe)localObject).putObject(paramObject, paramLong, Long.valueOf(zzgnb.zzp(paramArrayOfByte, paramInt1)));
        ((Unsafe)localObject).putInt(paramObject, l, paramInt4);
        return paramInt1 + 8;
      }
      break;
    case 55: 
    case 62: 
      if (paramInt5 == 0)
      {
        paramInt1 = zzgnb.zzj(paramArrayOfByte, paramInt1, paramzzgna);
        ((Unsafe)localObject).putObject(paramObject, paramLong, Integer.valueOf(paramzzgna.zza));
        ((Unsafe)localObject).putInt(paramObject, l, paramInt4);
        return paramInt1;
      }
      break;
    case 53: 
    case 54: 
      if (paramInt5 == 0)
      {
        paramInt1 = zzgnb.zzm(paramArrayOfByte, paramInt1, paramzzgna);
        ((Unsafe)localObject).putObject(paramObject, paramLong, Long.valueOf(paramzzgna.zzb));
        ((Unsafe)localObject).putInt(paramObject, l, paramInt4);
        return paramInt1;
      }
      break;
    case 52: 
      if (paramInt5 == 5)
      {
        ((Unsafe)localObject).putObject(paramObject, paramLong, Float.valueOf(Float.intBitsToFloat(zzgnb.zzb(paramArrayOfByte, paramInt1))));
        ((Unsafe)localObject).putInt(paramObject, l, paramInt4);
        return paramInt1 + 4;
      }
      break;
    case 51: 
      if (paramInt5 == 1)
      {
        ((Unsafe)localObject).putObject(paramObject, paramLong, Double.valueOf(Double.longBitsToDouble(zzgnb.zzp(paramArrayOfByte, paramInt1))));
        ((Unsafe)localObject).putInt(paramObject, l, paramInt4);
        return paramInt1 + 8;
      }
      break;
    }
    return paramInt1;
  }
  
  private final int zzt(Object paramObject, byte[] paramArrayOfByte, int paramInt1, int paramInt2, int paramInt3, int paramInt4, int paramInt5, int paramInt6, long paramLong1, int paramInt7, long paramLong2, zzgna paramzzgna)
    throws IOException
  {
    int i = paramInt1;
    Unsafe localUnsafe = zzb;
    zzgpf localzzgpf2 = (zzgpf)localUnsafe.getObject(paramObject, paramLong2);
    zzgpf localzzgpf1 = localzzgpf2;
    if (!localzzgpf2.zzc())
    {
      int j = localzzgpf2.size();
      if (j == 0) {
        j = 10;
      } else {
        j += j;
      }
      localzzgpf1 = localzzgpf2.zzd(j);
      localUnsafe.putObject(paramObject, paramLong2, localzzgpf1);
    }
    switch (paramInt7)
    {
    default: 
      paramInt7 = i;
      if (paramInt5 != 3) {
        break label2329;
      }
      paramObject = zzC(paramInt6);
      paramInt4 = paramInt3 & 0xFFFFFFF8 | 0x4;
      paramInt1 = zzgnb.zzc((zzgqz)paramObject, paramArrayOfByte, paramInt1, paramInt2, paramInt4, paramzzgna);
      localzzgpf1.add(paramzzgna.zzc);
      break;
    case 34: 
    case 48: 
      if (paramInt5 == 2)
      {
        paramObject = (zzgpv)localzzgpf1;
        paramInt1 = zzgnb.zzj(paramArrayOfByte, i, paramzzgna);
        paramInt2 = paramzzgna.zza + paramInt1;
        while (paramInt1 < paramInt2)
        {
          paramInt1 = zzgnb.zzm(paramArrayOfByte, paramInt1, paramzzgna);
          ((zzgpv)paramObject).zzg(zzgnw.zzG(paramzzgna.zzb));
        }
        if (paramInt1 == paramInt2) {
          return paramInt1;
        }
        throw zzgpi.zzj();
      }
      paramInt7 = i;
      if (paramInt5 != 0) {
        break label2329;
      }
      paramObject = (zzgpv)localzzgpf1;
      paramInt1 = zzgnb.zzm(paramArrayOfByte, i, paramzzgna);
      ((zzgpv)paramObject).zzg(zzgnw.zzG(paramzzgna.zzb));
      while (paramInt1 < paramInt2)
      {
        paramInt4 = zzgnb.zzj(paramArrayOfByte, paramInt1, paramzzgna);
        if (paramInt3 != paramzzgna.zza) {
          break;
        }
        paramInt1 = zzgnb.zzm(paramArrayOfByte, paramInt4, paramzzgna);
        ((zzgpv)paramObject).zzg(zzgnw.zzG(paramzzgna.zzb));
      }
      return paramInt1;
    case 33: 
    case 47: 
      if (paramInt5 == 2)
      {
        paramObject = (zzgox)localzzgpf1;
        paramInt1 = zzgnb.zzj(paramArrayOfByte, i, paramzzgna);
        paramInt2 = paramzzgna.zza + paramInt1;
        while (paramInt1 < paramInt2)
        {
          paramInt1 = zzgnb.zzj(paramArrayOfByte, paramInt1, paramzzgna);
          ((zzgox)paramObject).zzh(zzgnw.zzF(paramzzgna.zza));
        }
        if (paramInt1 == paramInt2) {
          return paramInt1;
        }
        throw zzgpi.zzj();
      }
      paramInt7 = i;
      if (paramInt5 != 0) {
        break label2329;
      }
      paramObject = (zzgox)localzzgpf1;
      paramInt1 = zzgnb.zzj(paramArrayOfByte, i, paramzzgna);
      ((zzgox)paramObject).zzh(zzgnw.zzF(paramzzgna.zza));
      while (paramInt1 < paramInt2)
      {
        paramInt4 = zzgnb.zzj(paramArrayOfByte, paramInt1, paramzzgna);
        if (paramInt3 != paramzzgna.zza) {
          break;
        }
        paramInt1 = zzgnb.zzj(paramArrayOfByte, paramInt4, paramzzgna);
        ((zzgox)paramObject).zzh(zzgnw.zzF(paramzzgna.zza));
      }
      return paramInt1;
    case 30: 
    case 44: 
      if (paramInt5 == 2)
      {
        paramInt1 = zzgnb.zzf(paramArrayOfByte, i, localzzgpf1, paramzzgna);
      }
      else
      {
        paramInt7 = i;
        if (paramInt5 != 0) {
          break label2329;
        }
        paramInt1 = zzgnb.zzl(paramInt3, paramArrayOfByte, paramInt1, paramInt2, localzzgpf1, paramzzgna);
      }
      zzgrb.zzA(paramObject, paramInt4, localzzgpf1, zzB(paramInt6), null, this.zzo);
    case 28: 
    case 27: 
    case 26: 
    case 25: 
    case 42: 
      boolean bool;
      do
      {
        return paramInt1;
        paramInt7 = i;
        if (paramInt5 != 2) {
          break label2329;
        }
        paramInt4 = zzgnb.zzj(paramArrayOfByte, i, paramzzgna);
        paramInt1 = paramzzgna.zza;
        if (paramInt1 >= 0)
        {
          if (paramInt1 <= paramArrayOfByte.length - paramInt4)
          {
            if (paramInt1 == 0)
            {
              localzzgpf1.add(zzgno.zzb);
              paramInt1 = paramInt4;
            }
            else
            {
              localzzgpf1.add(zzgno.zzv(paramArrayOfByte, paramInt4, paramInt1));
            }
            for (;;)
            {
              paramInt1 = paramInt4 + paramInt1;
              for (;;)
              {
                if (paramInt1 >= paramInt2) {
                  break label858;
                }
                paramInt4 = zzgnb.zzj(paramArrayOfByte, paramInt1, paramzzgna);
                if (paramInt3 != paramzzgna.zza) {
                  break label858;
                }
                paramInt1 = zzgnb.zzj(paramArrayOfByte, paramInt4, paramzzgna);
                paramInt5 = paramzzgna.zza;
                if (paramInt5 < 0) {
                  break label854;
                }
                if (paramInt5 > paramArrayOfByte.length - paramInt1) {
                  break label850;
                }
                if (paramInt5 != 0) {
                  break;
                }
                localzzgpf1.add(zzgno.zzb);
              }
              localzzgpf1.add(zzgno.zzv(paramArrayOfByte, paramInt1, paramInt5));
              paramInt4 = paramInt1;
              paramInt1 = paramInt5;
            }
            throw zzgpi.zzj();
            throw zzgpi.zzf();
            return paramInt1;
          }
          throw zzgpi.zzj();
        }
        throw zzgpi.zzf();
        paramInt7 = i;
        if (paramInt5 != 2) {
          break label2329;
        }
        return zzgnb.zze(zzC(paramInt6), paramInt3, paramArrayOfByte, paramInt1, paramInt2, localzzgpf1, paramzzgna);
        paramInt7 = i;
        if (paramInt5 != 2) {
          break label2329;
        }
        if ((paramLong1 & 0x20000000) == 0L)
        {
          paramInt1 = zzgnb.zzj(paramArrayOfByte, i, paramzzgna);
          paramInt4 = paramzzgna.zza;
          if (paramInt4 >= 0)
          {
            if (paramInt4 == 0) {
              localzzgpf1.add("");
            } else {
              localzzgpf1.add(new String(paramArrayOfByte, paramInt1, paramInt4, zzgpg.zzb));
            }
            for (;;)
            {
              paramInt1 += paramInt4;
              for (;;)
              {
                paramInt7 = paramInt1;
                if (paramInt1 >= paramInt2) {
                  break label2329;
                }
                paramInt4 = zzgnb.zzj(paramArrayOfByte, paramInt1, paramzzgna);
                paramInt7 = paramInt1;
                if (paramInt3 != paramzzgna.zza) {
                  break label2329;
                }
                paramInt1 = zzgnb.zzj(paramArrayOfByte, paramInt4, paramzzgna);
                paramInt4 = paramzzgna.zza;
                if (paramInt4 < 0) {
                  break label1082;
                }
                if (paramInt4 != 0) {
                  break;
                }
                localzzgpf1.add("");
              }
              localzzgpf1.add(new String(paramArrayOfByte, paramInt1, paramInt4, zzgpg.zzb));
            }
            throw zzgpi.zzf();
          }
          throw zzgpi.zzf();
        }
        paramInt1 = zzgnb.zzj(paramArrayOfByte, i, paramzzgna);
        paramInt5 = paramzzgna.zza;
        if (paramInt5 >= 0)
        {
          if (paramInt5 == 0)
          {
            localzzgpf1.add("");
          }
          else
          {
            paramInt4 = paramInt1 + paramInt5;
            if (!zzgsf.zzj(paramArrayOfByte, paramInt1, paramInt4)) {
              break label1296;
            }
            localzzgpf1.add(new String(paramArrayOfByte, paramInt1, paramInt5, zzgpg.zzb));
            paramInt1 = paramInt4;
          }
          for (;;)
          {
            paramInt7 = paramInt1;
            if (paramInt1 >= paramInt2) {
              break label2329;
            }
            paramInt4 = zzgnb.zzj(paramArrayOfByte, paramInt1, paramzzgna);
            paramInt7 = paramInt1;
            if (paramInt3 != paramzzgna.zza) {
              break label2329;
            }
            paramInt4 = zzgnb.zzj(paramArrayOfByte, paramInt4, paramzzgna);
            paramInt5 = paramzzgna.zza;
            if (paramInt5 < 0) {
              break label1292;
            }
            if (paramInt5 == 0)
            {
              localzzgpf1.add("");
              paramInt1 = paramInt4;
            }
            else
            {
              paramInt1 = paramInt4 + paramInt5;
              if (!zzgsf.zzj(paramArrayOfByte, paramInt4, paramInt1)) {
                break;
              }
              localzzgpf1.add(new String(paramArrayOfByte, paramInt4, paramInt5, zzgpg.zzb));
            }
          }
          throw zzgpi.zzd();
          throw zzgpi.zzf();
          throw zzgpi.zzd();
        }
        throw zzgpi.zzf();
        if (paramInt5 != 2) {
          break;
        }
        paramObject = (zzgnc)localzzgpf1;
        paramInt1 = zzgnb.zzj(paramArrayOfByte, i, paramzzgna);
        paramInt2 = paramzzgna.zza + paramInt1;
        while (paramInt1 < paramInt2)
        {
          paramInt1 = zzgnb.zzm(paramArrayOfByte, paramInt1, paramzzgna);
          if (paramzzgna.zzb != 0L) {
            bool = true;
          } else {
            bool = false;
          }
          ((zzgnc)paramObject).zze(bool);
        }
      } while (paramInt1 == paramInt2);
      throw zzgpi.zzj();
      paramInt7 = i;
      if (paramInt5 != 0) {
        break label2329;
      }
      paramObject = (zzgnc)localzzgpf1;
      paramInt1 = zzgnb.zzm(paramArrayOfByte, i, paramzzgna);
      if (paramzzgna.zzb != 0L) {
        bool = true;
      } else {
        bool = false;
      }
      ((zzgnc)paramObject).zze(bool);
      while (paramInt1 < paramInt2)
      {
        paramInt4 = zzgnb.zzj(paramArrayOfByte, paramInt1, paramzzgna);
        if (paramInt3 != paramzzgna.zza) {
          break;
        }
        paramInt1 = zzgnb.zzm(paramArrayOfByte, paramInt4, paramzzgna);
        if (paramzzgna.zzb != 0L) {
          bool = true;
        } else {
          bool = false;
        }
        ((zzgnc)paramObject).zze(bool);
      }
      return paramInt1;
    case 24: 
    case 31: 
    case 41: 
    case 45: 
      if (paramInt5 == 2)
      {
        paramObject = (zzgox)localzzgpf1;
        paramInt1 = zzgnb.zzj(paramArrayOfByte, i, paramzzgna);
        paramInt2 = paramzzgna.zza + paramInt1;
        while (paramInt1 < paramInt2)
        {
          ((zzgox)paramObject).zzh(zzgnb.zzb(paramArrayOfByte, paramInt1));
          paramInt1 += 4;
        }
        if (paramInt1 == paramInt2) {
          return paramInt1;
        }
        throw zzgpi.zzj();
      }
      paramInt7 = i;
      if (paramInt5 != 5) {
        break label2329;
      }
      paramObject = (zzgox)localzzgpf1;
      ((zzgox)paramObject).zzh(zzgnb.zzb(paramArrayOfByte, paramInt1));
      for (;;)
      {
        paramInt1 = i + 4;
        if (paramInt1 >= paramInt2) {
          break;
        }
        i = zzgnb.zzj(paramArrayOfByte, paramInt1, paramzzgna);
        if (paramInt3 != paramzzgna.zza) {
          break;
        }
        ((zzgox)paramObject).zzh(zzgnb.zzb(paramArrayOfByte, i));
      }
      return paramInt1;
    case 23: 
    case 32: 
    case 40: 
    case 46: 
      if (paramInt5 == 2)
      {
        paramObject = (zzgpv)localzzgpf1;
        paramInt1 = zzgnb.zzj(paramArrayOfByte, i, paramzzgna);
        paramInt2 = paramzzgna.zza + paramInt1;
        while (paramInt1 < paramInt2)
        {
          ((zzgpv)paramObject).zzg(zzgnb.zzp(paramArrayOfByte, paramInt1));
          paramInt1 += 8;
        }
        if (paramInt1 == paramInt2) {
          return paramInt1;
        }
        throw zzgpi.zzj();
      }
      paramInt7 = i;
      if (paramInt5 != 1) {
        break label2329;
      }
      paramObject = (zzgpv)localzzgpf1;
      ((zzgpv)paramObject).zzg(zzgnb.zzp(paramArrayOfByte, paramInt1));
      for (;;)
      {
        paramInt1 = i + 8;
        if (paramInt1 >= paramInt2) {
          break;
        }
        i = zzgnb.zzj(paramArrayOfByte, paramInt1, paramzzgna);
        if (paramInt3 != paramzzgna.zza) {
          break;
        }
        ((zzgpv)paramObject).zzg(zzgnb.zzp(paramArrayOfByte, i));
      }
      return paramInt1;
    case 22: 
    case 29: 
    case 39: 
    case 43: 
      if (paramInt5 == 2) {
        return zzgnb.zzf(paramArrayOfByte, i, localzzgpf1, paramzzgna);
      }
      paramInt7 = i;
      if (paramInt5 != 0) {
        break label2329;
      }
      return zzgnb.zzl(paramInt3, paramArrayOfByte, paramInt1, paramInt2, localzzgpf1, paramzzgna);
    case 20: 
    case 21: 
    case 37: 
    case 38: 
      if (paramInt5 == 2)
      {
        paramObject = (zzgpv)localzzgpf1;
        paramInt1 = zzgnb.zzj(paramArrayOfByte, i, paramzzgna);
        paramInt2 = paramzzgna.zza + paramInt1;
        while (paramInt1 < paramInt2)
        {
          paramInt1 = zzgnb.zzm(paramArrayOfByte, paramInt1, paramzzgna);
          ((zzgpv)paramObject).zzg(paramzzgna.zzb);
        }
        if (paramInt1 == paramInt2) {
          return paramInt1;
        }
        throw zzgpi.zzj();
      }
      paramInt7 = i;
      if (paramInt5 != 0) {
        break label2329;
      }
      paramObject = (zzgpv)localzzgpf1;
      paramInt1 = zzgnb.zzm(paramArrayOfByte, i, paramzzgna);
      ((zzgpv)paramObject).zzg(paramzzgna.zzb);
      while (paramInt1 < paramInt2)
      {
        paramInt4 = zzgnb.zzj(paramArrayOfByte, paramInt1, paramzzgna);
        if (paramInt3 != paramzzgna.zza) {
          break;
        }
        paramInt1 = zzgnb.zzm(paramArrayOfByte, paramInt4, paramzzgna);
        ((zzgpv)paramObject).zzg(paramzzgna.zzb);
      }
      return paramInt1;
    case 19: 
    case 36: 
      if (paramInt5 == 2)
      {
        paramObject = (zzgop)localzzgpf1;
        paramInt1 = zzgnb.zzj(paramArrayOfByte, i, paramzzgna);
        paramInt2 = paramzzgna.zza + paramInt1;
        while (paramInt1 < paramInt2)
        {
          ((zzgop)paramObject).zze(Float.intBitsToFloat(zzgnb.zzb(paramArrayOfByte, paramInt1)));
          paramInt1 += 4;
        }
        if (paramInt1 == paramInt2) {
          return paramInt1;
        }
        throw zzgpi.zzj();
      }
      paramInt7 = i;
      if (paramInt5 != 5) {
        break label2329;
      }
      paramObject = (zzgop)localzzgpf1;
      ((zzgop)paramObject).zze(Float.intBitsToFloat(zzgnb.zzb(paramArrayOfByte, paramInt1)));
      for (;;)
      {
        paramInt1 = i + 4;
        if (paramInt1 >= paramInt2) {
          break;
        }
        i = zzgnb.zzj(paramArrayOfByte, paramInt1, paramzzgna);
        if (paramInt3 != paramzzgna.zza) {
          break;
        }
        ((zzgop)paramObject).zze(Float.intBitsToFloat(zzgnb.zzb(paramArrayOfByte, i)));
      }
      return paramInt1;
    case 18: 
    case 35: 
      label850:
      label854:
      label858:
      label1082:
      label1292:
      label1296:
      if (paramInt5 == 2)
      {
        paramObject = (zzgof)localzzgpf1;
        paramInt1 = zzgnb.zzj(paramArrayOfByte, i, paramzzgna);
        paramInt2 = paramzzgna.zza + paramInt1;
        while (paramInt1 < paramInt2)
        {
          ((zzgof)paramObject).zze(Double.longBitsToDouble(zzgnb.zzp(paramArrayOfByte, paramInt1)));
          paramInt1 += 8;
        }
        if (paramInt1 == paramInt2) {
          return paramInt1;
        }
        throw zzgpi.zzj();
      }
      paramInt7 = i;
      if (paramInt5 != 1) {
        break label2329;
      }
      paramObject = (zzgof)localzzgpf1;
      ((zzgof)paramObject).zze(Double.longBitsToDouble(zzgnb.zzp(paramArrayOfByte, paramInt1)));
      for (;;)
      {
        paramInt1 = i + 8;
        if (paramInt1 >= paramInt2) {
          break;
        }
        i = zzgnb.zzj(paramArrayOfByte, paramInt1, paramzzgna);
        if (paramInt3 != paramzzgna.zza) {
          break;
        }
        ((zzgof)paramObject).zze(Double.longBitsToDouble(zzgnb.zzp(paramArrayOfByte, i)));
      }
      return paramInt1;
    }
    while (paramInt1 < paramInt2)
    {
      paramInt5 = zzgnb.zzj(paramArrayOfByte, paramInt1, paramzzgna);
      if (paramInt3 != paramzzgna.zza) {
        break;
      }
      paramInt1 = zzgnb.zzc((zzgqz)paramObject, paramArrayOfByte, paramInt5, paramInt2, paramInt4, paramzzgna);
      localzzgpf1.add(paramzzgna.zzc);
    }
    return paramInt1;
    label2329:
    paramInt1 = paramInt7;
    return paramInt1;
  }
  
  private final int zzu(int paramInt)
  {
    if ((paramInt >= this.zze) && (paramInt <= this.zzf)) {
      return zzx(paramInt, 0);
    }
    return -1;
  }
  
  private final int zzv(int paramInt1, int paramInt2)
  {
    if ((paramInt1 >= this.zze) && (paramInt1 <= this.zzf)) {
      return zzx(paramInt1, paramInt2);
    }
    return -1;
  }
  
  private final int zzw(int paramInt)
  {
    return this.zzc[(paramInt + 2)];
  }
  
  private final int zzx(int paramInt1, int paramInt2)
  {
    int i = this.zzc.length / 3 - 1;
    while (paramInt2 <= i)
    {
      int m = i + paramInt2 >>> 1;
      int j = m * 3;
      int k = this.zzc[j];
      if (paramInt1 == k) {
        return j;
      }
      if (paramInt1 < k) {
        i = m - 1;
      } else {
        paramInt2 = m + 1;
      }
    }
    return -1;
  }
  
  private static int zzy(int paramInt)
  {
    return paramInt >>> 20 & 0xFF;
  }
  
  private final int zzz(int paramInt)
  {
    return this.zzc[(paramInt + 1)];
  }
  
  public final int zza(Object paramObject)
  {
    int i;
    if (this.zzj)
    {
      Object localObject1 = zzb;
      int m = 0;
      for (int n = 0; m < this.zzc.length; n = i)
      {
        int k = zzz(m);
        int j = zzy(k);
        int i2 = this.zzc[m];
        if ((j >= zzgoo.zzJ.zza()) && (j <= zzgoo.zzW.zza())) {
          i = this.zzc[(m + 2)];
        }
        long l = k & 0xFFFFF;
        Object localObject2;
        int i1;
        switch (j)
        {
        default: 
          i = n;
          break;
        case 68: 
          i = n;
          if (!zzW(paramObject, i2, m)) {
            break label2740;
          }
          i = zzgod.zzw(i2, (zzgqg)zzgsa.zzh(paramObject, l), zzC(m));
          break;
        case 67: 
          i = n;
          if (!zzW(paramObject, i2, m)) {
            break label2740;
          }
          l = zzA(paramObject, l);
          j = zzgod.zzA(i2 << 3);
          i = zzgod.zzB(l + l ^ l >> 63);
          break;
        case 66: 
          i = n;
          if (!zzW(paramObject, i2, m)) {
            break label2740;
          }
          i = zzq(paramObject, l);
          j = zzgod.zzA(i2 << 3);
          i = zzgod.zzA(i >> 31 ^ i + i);
          break;
        case 65: 
          i = n;
          if (!zzW(paramObject, i2, m)) {
            break label2740;
          }
          i = zzgod.zzA(i2 << 3);
          break;
        case 64: 
          i = n;
          if (!zzW(paramObject, i2, m)) {
            break label2740;
          }
          i = zzgod.zzA(i2 << 3);
          break;
        case 63: 
          i = n;
          if (!zzW(paramObject, i2, m)) {
            break label2740;
          }
          i = zzgod.zzx(zzq(paramObject, l));
          j = zzgod.zzA(i2 << 3);
          break;
        case 62: 
          i = n;
          if (!zzW(paramObject, i2, m)) {
            break label2740;
          }
          i = zzgod.zzA(zzq(paramObject, l));
          j = zzgod.zzA(i2 << 3);
          break;
        case 61: 
          i = n;
          if (!zzW(paramObject, i2, m)) {
            break label2740;
          }
          localObject2 = (zzgno)zzgsa.zzh(paramObject, l);
          i = zzgod.zzf;
          i = ((zzgno)localObject2).zzd();
          j = zzgod.zzA(i) + i;
          i = zzgod.zzA(i2 << 3);
          break;
        case 60: 
          i = n;
          if (!zzW(paramObject, i2, m)) {
            break label2740;
          }
          i = zzgrb.zzn(i2, zzgsa.zzh(paramObject, l), zzC(m));
          break;
        case 59: 
          i = n;
          if (!zzW(paramObject, i2, m)) {
            break label2740;
          }
          localObject2 = zzgsa.zzh(paramObject, l);
          if ((localObject2 instanceof zzgno))
          {
            localObject2 = (zzgno)localObject2;
            i = zzgod.zzf;
            i = ((zzgno)localObject2).zzd();
            j = zzgod.zzA(i) + i;
            i = zzgod.zzA(i2 << 3);
          }
          else
          {
            i = zzgod.zzz((String)localObject2);
            j = zzgod.zzA(i2 << 3);
          }
          break;
        case 58: 
          i = n;
          if (!zzW(paramObject, i2, m)) {
            break label2740;
          }
          i = zzgod.zzA(i2 << 3);
          break;
        case 57: 
          i = n;
          if (!zzW(paramObject, i2, m)) {
            break label2740;
          }
          i = zzgod.zzA(i2 << 3);
          break;
        case 56: 
          i = n;
          if (!zzW(paramObject, i2, m)) {
            break label2740;
          }
          i = zzgod.zzA(i2 << 3);
          break;
        case 55: 
          i = n;
          if (!zzW(paramObject, i2, m)) {
            break label2740;
          }
          i = zzgod.zzx(zzq(paramObject, l));
          j = zzgod.zzA(i2 << 3);
          break;
        case 54: 
          i = n;
          if (!zzW(paramObject, i2, m)) {
            break label2740;
          }
          i = zzgod.zzB(zzA(paramObject, l));
          j = zzgod.zzA(i2 << 3);
          break;
        case 53: 
          i = n;
          if (!zzW(paramObject, i2, m)) {
            break label2740;
          }
          i = zzgod.zzB(zzA(paramObject, l));
          j = zzgod.zzA(i2 << 3);
          break;
        case 52: 
          i = n;
          if (!zzW(paramObject, i2, m)) {
            break label2740;
          }
          i = zzgod.zzA(i2 << 3);
          break;
        case 51: 
          i = n;
          if (!zzW(paramObject, i2, m)) {
            break label2740;
          }
          i = zzgod.zzA(i2 << 3);
          break;
        case 50: 
          zzgqb.zza(i2, zzgsa.zzh(paramObject, l), zzE(m));
          i = n;
          break;
        case 49: 
          i = zzgrb.zzi(i2, (List)zzgsa.zzh(paramObject, l), zzC(m));
          break;
        case 48: 
          j = zzgrb.zzs((List)((Unsafe)localObject1).getObject(paramObject, l));
          i = n;
          if (j <= 0) {
            break label2740;
          }
          k = zzgod.zzA(j);
          i1 = zzgod.zzA(i2 << 3);
          i = j;
          j = i1;
          break;
        case 47: 
          j = zzgrb.zzq((List)((Unsafe)localObject1).getObject(paramObject, l));
          i = n;
          if (j <= 0) {
            break label2740;
          }
          k = zzgod.zzA(j);
          i1 = zzgod.zzA(i2 << 3);
          i = j;
          j = i1;
          break;
        case 46: 
          j = zzgrb.zzh((List)((Unsafe)localObject1).getObject(paramObject, l));
          i = n;
          if (j <= 0) {
            break label2740;
          }
          k = zzgod.zzA(j);
          i1 = zzgod.zzA(i2 << 3);
          i = j;
          j = i1;
          break;
        case 45: 
          j = zzgrb.zzf((List)((Unsafe)localObject1).getObject(paramObject, l));
          i = n;
          if (j <= 0) {
            break label2740;
          }
          k = zzgod.zzA(j);
          i1 = zzgod.zzA(i2 << 3);
          i = j;
          j = i1;
          break;
        case 44: 
          j = zzgrb.zzd((List)((Unsafe)localObject1).getObject(paramObject, l));
          i = n;
          if (j <= 0) {
            break label2740;
          }
          k = zzgod.zzA(j);
          i1 = zzgod.zzA(i2 << 3);
          i = j;
          j = i1;
          break;
        case 43: 
          j = zzgrb.zzv((List)((Unsafe)localObject1).getObject(paramObject, l));
          i = n;
          if (j <= 0) {
            break label2740;
          }
          k = zzgod.zzA(j);
          i1 = zzgod.zzA(i2 << 3);
          i = j;
          j = i1;
          break;
        case 42: 
          localObject2 = (List)((Unsafe)localObject1).getObject(paramObject, l);
          i = zzgrb.zza;
          j = ((List)localObject2).size();
          i = n;
          if (j <= 0) {
            break label2740;
          }
          k = zzgod.zzA(j);
          i1 = zzgod.zzA(i2 << 3);
          i = j;
          j = i1;
          break;
        case 41: 
          j = zzgrb.zzf((List)((Unsafe)localObject1).getObject(paramObject, l));
          i = n;
          if (j <= 0) {
            break label2740;
          }
          k = zzgod.zzA(j);
          i1 = zzgod.zzA(i2 << 3);
          i = j;
          j = i1;
          break;
        case 40: 
          j = zzgrb.zzh((List)((Unsafe)localObject1).getObject(paramObject, l));
          i = n;
          if (j <= 0) {
            break label2740;
          }
          k = zzgod.zzA(j);
          i1 = zzgod.zzA(i2 << 3);
          i = j;
          j = i1;
          break;
        case 39: 
          j = zzgrb.zzk((List)((Unsafe)localObject1).getObject(paramObject, l));
          i = n;
          if (j <= 0) {
            break label2740;
          }
          k = zzgod.zzA(j);
          i1 = zzgod.zzA(i2 << 3);
          i = j;
          j = i1;
          break;
        case 38: 
          j = zzgrb.zzx((List)((Unsafe)localObject1).getObject(paramObject, l));
          i = n;
          if (j <= 0) {
            break label2740;
          }
          k = zzgod.zzA(j);
          i1 = zzgod.zzA(i2 << 3);
          i = j;
          j = i1;
          break;
        case 37: 
          j = zzgrb.zzm((List)((Unsafe)localObject1).getObject(paramObject, l));
          i = n;
          if (j <= 0) {
            break label2740;
          }
          k = zzgod.zzA(j);
          i1 = zzgod.zzA(i2 << 3);
          i = j;
          j = i1;
          break;
        case 36: 
          j = zzgrb.zzf((List)((Unsafe)localObject1).getObject(paramObject, l));
          i = n;
          if (j <= 0) {
            break label2740;
          }
          k = zzgod.zzA(j);
          i1 = zzgod.zzA(i2 << 3);
          i = j;
          j = i1;
          break;
        case 35: 
          i1 = zzgrb.zzh((List)((Unsafe)localObject1).getObject(paramObject, l));
          i = n;
          if (i1 <= 0) {
            break label2740;
          }
          k = zzgod.zzA(i1);
          j = zzgod.zzA(i2 << 3);
          i = i1;
          j += k;
          break;
        case 34: 
          i = zzgrb.zzr(i2, (List)zzgsa.zzh(paramObject, l), false);
          break;
        case 33: 
          i = zzgrb.zzp(i2, (List)zzgsa.zzh(paramObject, l), false);
          break;
        case 32: 
          i = zzgrb.zzg(i2, (List)zzgsa.zzh(paramObject, l), false);
          break;
        case 31: 
          i = zzgrb.zze(i2, (List)zzgsa.zzh(paramObject, l), false);
          break;
        case 30: 
          i = zzgrb.zzc(i2, (List)zzgsa.zzh(paramObject, l), false);
          break;
        case 29: 
          i = zzgrb.zzu(i2, (List)zzgsa.zzh(paramObject, l), false);
          break;
        case 28: 
          i = zzgrb.zzb(i2, (List)zzgsa.zzh(paramObject, l));
          break;
        case 27: 
          i = zzgrb.zzo(i2, (List)zzgsa.zzh(paramObject, l), zzC(m));
          break;
        case 26: 
          i = zzgrb.zzt(i2, (List)zzgsa.zzh(paramObject, l));
          break;
        case 25: 
          i = zzgrb.zza(i2, (List)zzgsa.zzh(paramObject, l), false);
          break;
        case 24: 
          i = zzgrb.zze(i2, (List)zzgsa.zzh(paramObject, l), false);
          break;
        case 23: 
          i = zzgrb.zzg(i2, (List)zzgsa.zzh(paramObject, l), false);
          break;
        case 22: 
          i = zzgrb.zzj(i2, (List)zzgsa.zzh(paramObject, l), false);
          break;
        case 21: 
          i = zzgrb.zzw(i2, (List)zzgsa.zzh(paramObject, l), false);
          break;
        case 20: 
          i = zzgrb.zzl(i2, (List)zzgsa.zzh(paramObject, l), false);
          break;
        case 19: 
          i = zzgrb.zze(i2, (List)zzgsa.zzh(paramObject, l), false);
          break;
        case 18: 
          i = zzgrb.zzg(i2, (List)zzgsa.zzh(paramObject, l), false);
        }
        for (;;)
        {
          i = n + i;
          break;
          i = n;
          if (!zzS(paramObject, m)) {
            break;
          }
          i = zzgod.zzw(i2, (zzgqg)zzgsa.zzh(paramObject, l), zzC(m));
          continue;
          i = n;
          if (!zzS(paramObject, m)) {
            break;
          }
          l = zzgsa.zzf(paramObject, l);
          j = zzgod.zzA(i2 << 3);
          i = zzgod.zzB(l + l ^ l >> 63);
          i = j + i;
          continue;
          i = n;
          if (!zzS(paramObject, m)) {
            break;
          }
          i = zzgsa.zzd(paramObject, l);
          j = zzgod.zzA(i2 << 3);
          i = zzgod.zzA(i >> 31 ^ i + i);
          break label2676;
          i = n;
          if (!zzS(paramObject, m)) {
            break;
          }
          i = zzgod.zzA(i2 << 3);
          break label2734;
          i = n;
          if (!zzS(paramObject, m)) {
            break;
          }
          i = zzgod.zzA(i2 << 3);
          break label2707;
          i = n;
          if (!zzS(paramObject, m)) {
            break;
          }
          i = zzgod.zzx(zzgsa.zzd(paramObject, l));
          j = zzgod.zzA(i2 << 3);
          break label2676;
          i = n;
          if (!zzS(paramObject, m)) {
            break;
          }
          i = zzgod.zzA(zzgsa.zzd(paramObject, l));
          j = zzgod.zzA(i2 << 3);
          break label2676;
          i = n;
          if (!zzS(paramObject, m)) {
            break;
          }
          localObject2 = (zzgno)zzgsa.zzh(paramObject, l);
          i = zzgod.zzf;
          i = ((zzgno)localObject2).zzd();
          j = zzgod.zzA(i) + i;
          for (i = zzgod.zzA(i2 << 3);; i = zzgod.zzA(i2 << 3))
          {
            i += j;
            break;
            i = n;
            if (!zzS(paramObject, m)) {
              break label2740;
            }
            i = zzgrb.zzn(i2, zzgsa.zzh(paramObject, l), zzC(m));
            break;
            i = n;
            if (!zzS(paramObject, m)) {
              break label2740;
            }
            localObject2 = zzgsa.zzh(paramObject, l);
            if (!(localObject2 instanceof zzgno)) {
              break label2482;
            }
            localObject2 = (zzgno)localObject2;
            i = zzgod.zzf;
            i = ((zzgno)localObject2).zzd();
            j = zzgod.zzA(i) + i;
          }
          label2482:
          i = zzgod.zzz((String)localObject2);
          j = zzgod.zzA(i2 << 3);
          break label2676;
          i = n;
          if (!zzS(paramObject, m)) {
            break;
          }
          i = zzgod.zzA(i2 << 3);
          i++;
          continue;
          i = n;
          if (!zzS(paramObject, m)) {
            break;
          }
          i = zzgod.zzA(i2 << 3);
          break label2707;
          i = n;
          if (!zzS(paramObject, m)) {
            break;
          }
          i = zzgod.zzA(i2 << 3);
          break label2734;
          i = n;
          if (!zzS(paramObject, m)) {
            break;
          }
          i = zzgod.zzx(zzgsa.zzd(paramObject, l));
          j = zzgod.zzA(i2 << 3);
          break label2676;
          i = n;
          if (!zzS(paramObject, m)) {
            break;
          }
          i = zzgod.zzB(zzgsa.zzf(paramObject, l));
          j = zzgod.zzA(i2 << 3);
          break label2676;
          i = n;
          if (!zzS(paramObject, m)) {
            break;
          }
          i = zzgod.zzB(zzgsa.zzf(paramObject, l));
          j = zzgod.zzA(i2 << 3);
          label2676:
          i = n + (j + i);
          break;
          i = n;
          if (!zzS(paramObject, m)) {
            break;
          }
          i = zzgod.zzA(i2 << 3);
          label2707:
          i += 4;
          continue;
          i = n;
          if (!zzS(paramObject, m)) {
            break;
          }
          i = zzgod.zzA(i2 << 3);
          label2734:
          i += 8;
        }
        label2740:
        m += 3;
      }
      localObject1 = this.zzo;
      i = n + ((zzgrq)localObject1).zza(((zzgrq)localObject1).zzd(paramObject));
    }
    else
    {
      i = zzp(paramObject);
    }
    return i;
  }
  
  public final int zzb(Object paramObject)
  {
    int m = this.zzc.length;
    int k = 0;
    for (int j = 0; k < m; j = i)
    {
      i = zzz(k);
      int n = this.zzc[k];
      int i1 = zzy(i);
      long l = 0xFFFFF & i;
      i = 37;
      switch (i1)
      {
      default: 
        i = j;
        break;
      case 68: 
        i = j;
        if (!zzW(paramObject, n, k)) {
          break label1333;
        }
        localObject = zzgsa.zzh(paramObject, l);
        i = j * 53;
        j = localObject.hashCode();
        break;
      case 67: 
        i = j;
        if (!zzW(paramObject, n, k)) {
          break label1333;
        }
        i = j * 53;
        l = zzA(paramObject, l);
        localObject = zzgpg.zzd;
        break;
      case 66: 
        i = j;
        if (!zzW(paramObject, n, k)) {
          break label1333;
        }
        i = j * 53;
        j = zzq(paramObject, l);
        break;
      case 65: 
        i = j;
        if (!zzW(paramObject, n, k)) {
          break label1333;
        }
        i = j * 53;
        l = zzA(paramObject, l);
        localObject = zzgpg.zzd;
        break;
      case 64: 
        i = j;
        if (!zzW(paramObject, n, k)) {
          break label1333;
        }
        i = j * 53;
        j = zzq(paramObject, l);
        break;
      case 63: 
        i = j;
        if (!zzW(paramObject, n, k)) {
          break label1333;
        }
        i = j * 53;
        j = zzq(paramObject, l);
        break;
      case 62: 
        i = j;
        if (!zzW(paramObject, n, k)) {
          break label1333;
        }
        i = j * 53;
        j = zzq(paramObject, l);
        break;
      case 61: 
        i = j;
        if (!zzW(paramObject, n, k)) {
          break label1333;
        }
        i = j * 53;
        j = zzgsa.zzh(paramObject, l).hashCode();
        break;
      case 60: 
        i = j;
        if (!zzW(paramObject, n, k)) {
          break label1333;
        }
        localObject = zzgsa.zzh(paramObject, l);
        i = j * 53;
        j = localObject.hashCode();
        break;
      case 59: 
        i = j;
        if (!zzW(paramObject, n, k)) {
          break label1333;
        }
        i = j * 53;
        j = ((String)zzgsa.zzh(paramObject, l)).hashCode();
        break;
      case 58: 
        i = j;
        if (!zzW(paramObject, n, k)) {
          break label1333;
        }
        i = j * 53;
        j = zzgpg.zza(zzX(paramObject, l));
        break;
      case 57: 
        i = j;
        if (!zzW(paramObject, n, k)) {
          break label1333;
        }
        i = j * 53;
        j = zzq(paramObject, l);
        break;
      case 56: 
        i = j;
        if (!zzW(paramObject, n, k)) {
          break label1333;
        }
        i = j * 53;
        l = zzA(paramObject, l);
        localObject = zzgpg.zzd;
        break;
      case 55: 
        i = j;
        if (!zzW(paramObject, n, k)) {
          break label1333;
        }
        i = j * 53;
        j = zzq(paramObject, l);
        break;
      case 54: 
        i = j;
        if (!zzW(paramObject, n, k)) {
          break label1333;
        }
        i = j * 53;
        l = zzA(paramObject, l);
        localObject = zzgpg.zzd;
        break;
      case 53: 
        i = j;
        if (!zzW(paramObject, n, k)) {
          break label1333;
        }
        i = j * 53;
        l = zzA(paramObject, l);
        localObject = zzgpg.zzd;
        break;
      case 52: 
        i = j;
        if (!zzW(paramObject, n, k)) {
          break label1333;
        }
        i = j * 53;
        j = Float.floatToIntBits(zzo(paramObject, l));
        break;
      case 51: 
        i = j;
        if (!zzW(paramObject, n, k)) {
          break label1333;
        }
        i = j * 53;
        l = Double.doubleToLongBits(zzn(paramObject, l));
        localObject = zzgpg.zzd;
        break;
      case 50: 
        i = j * 53;
        j = zzgsa.zzh(paramObject, l).hashCode();
        break;
      case 18: 
      case 19: 
      case 20: 
      case 21: 
      case 22: 
      case 23: 
      case 24: 
      case 25: 
      case 26: 
      case 27: 
      case 28: 
      case 29: 
      case 30: 
      case 31: 
      case 32: 
      case 33: 
      case 34: 
      case 35: 
      case 36: 
      case 37: 
      case 38: 
      case 39: 
      case 40: 
      case 41: 
      case 42: 
      case 43: 
      case 44: 
      case 45: 
      case 46: 
      case 47: 
      case 48: 
      case 49: 
        i = j * 53;
        j = zzgsa.zzh(paramObject, l).hashCode();
        break;
      case 17: 
        localObject = zzgsa.zzh(paramObject, l);
        if (localObject != null) {
          i = localObject.hashCode();
        }
        break;
      case 16: 
        i = j * 53;
        l = zzgsa.zzf(paramObject, l);
        localObject = zzgpg.zzd;
        break;
      case 15: 
        i = j * 53;
        j = zzgsa.zzd(paramObject, l);
        break;
      case 14: 
        i = j * 53;
        l = zzgsa.zzf(paramObject, l);
        localObject = zzgpg.zzd;
        break;
      case 13: 
        i = j * 53;
        j = zzgsa.zzd(paramObject, l);
        break;
      case 12: 
        i = j * 53;
        j = zzgsa.zzd(paramObject, l);
        break;
      case 11: 
        i = j * 53;
        j = zzgsa.zzd(paramObject, l);
        break;
      case 10: 
        i = j * 53;
        j = zzgsa.zzh(paramObject, l).hashCode();
        break;
      case 9: 
        localObject = zzgsa.zzh(paramObject, l);
        if (localObject != null) {
          i = localObject.hashCode();
        }
        i = j * 53 + i;
        break;
      case 8: 
        i = j * 53;
        j = ((String)zzgsa.zzh(paramObject, l)).hashCode();
        break;
      case 7: 
        i = j * 53;
        j = zzgpg.zza(zzgsa.zzz(paramObject, l));
        break;
      case 6: 
        i = j * 53;
        j = zzgsa.zzd(paramObject, l);
        break;
      case 5: 
        i = j * 53;
        l = zzgsa.zzf(paramObject, l);
        localObject = zzgpg.zzd;
        break;
      case 4: 
        i = j * 53;
        j = zzgsa.zzd(paramObject, l);
        break;
      case 3: 
        i = j * 53;
        l = zzgsa.zzf(paramObject, l);
        localObject = zzgpg.zzd;
        break;
      case 2: 
        i = j * 53;
        l = zzgsa.zzf(paramObject, l);
        localObject = zzgpg.zzd;
        break;
      case 1: 
        i = j * 53;
        j = Float.floatToIntBits(zzgsa.zzc(paramObject, l));
        i += j;
        break;
      }
      i = j * 53;
      l = Double.doubleToLongBits(zzgsa.zzb(paramObject, l));
      Object localObject = zzgpg.zzd;
      i += (int)(l ^ l >>> 32);
      label1333:
      k += 3;
    }
    int i = this.zzo.zzd(paramObject).hashCode();
    if (!this.zzh) {
      return j * 53 + i;
    }
    this.zzp.zza(paramObject);
    throw null;
  }
  
  final int zzc(Object paramObject, byte[] paramArrayOfByte, int paramInt1, int paramInt2, int paramInt3, zzgna paramzzgna)
    throws IOException
  {
    Object localObject1 = paramObject;
    localObject1 = paramArrayOfByte;
    int i1 = paramInt3;
    Object localObject2 = paramzzgna;
    zzI(paramObject);
    localObject2 = zzb;
    int i2 = -1;
    int i3 = 0;
    int i = 0;
    int m = 0;
    int n = 1048575;
    Object localObject3;
    for (;;)
    {
      localObject3 = paramObject;
      Object localObject4 = paramzzgna;
      if (paramInt1 >= paramInt2) {
        break;
      }
      j = paramInt1 + 1;
      int k = localObject1[paramInt1];
      if (k < 0)
      {
        j = zzgnb.zzk(k, (byte[])localObject1, j, (zzgna)localObject4);
        k = ((zzgna)localObject4).zza;
      }
      i = k >>> 3;
      if (i > i2) {
        paramInt1 = zzv(i, i3 / 3);
      } else {
        paramInt1 = zzu(i);
      }
      if (paramInt1 == -1)
      {
        paramInt1 = i;
        i2 = j;
        j = k;
        k = m;
        paramInt1 = i1;
        i1 = 0;
        m = i2;
      }
      else
      {
        int i4 = k & 0x7;
        int[] arrayOfInt = this.zzc;
        int i6 = arrayOfInt[(paramInt1 + 1)];
        int i5 = zzy(i6);
        i1 = k;
        long l = i6 & 0xFFFFF;
        if (i5 <= 17)
        {
          i2 = arrayOfInt[(paramInt1 + 2)];
          i3 = 1 << (i2 >>> 20);
          i2 &= 0xFFFFF;
          if (i2 != n)
          {
            if (n != 1048575) {
              ((Unsafe)localObject2).putInt(localObject3, n, m);
            }
            n = ((Unsafe)localObject2).getInt(localObject3, i2);
            m = i2;
          }
          else
          {
            i2 = m;
            m = n;
            n = i2;
          }
          switch (i5)
          {
          default: 
            i2 = j;
            if (i4 != 3) {
              break label1125;
            }
            localObject1 = zzF(localObject3, paramInt1);
            j = zzgnb.zzn(localObject1, zzC(paramInt1), paramArrayOfByte, i2, paramInt2, i << 3 | 0x4, paramzzgna);
            zzO(localObject3, paramInt1, localObject1);
            n |= i3;
            i2 = i;
            i2 = paramInt1;
            localObject1 = paramArrayOfByte;
            break;
          case 16: 
            if (i4 == 0)
            {
              j = zzgnb.zzm((byte[])localObject1, j, (zzgna)localObject4);
              ((Unsafe)localObject2).putLong(paramObject, l, zzgnw.zzG(((zzgna)localObject4).zzb));
              n |= i3;
              i2 = paramInt1;
              i2 = i;
            }
            else
            {
              i1 = paramInt1;
              i1 = j;
            }
            break;
          case 15: 
            if (i4 == 0)
            {
              j = zzgnb.zzj((byte[])localObject1, j, (zzgna)localObject4);
              ((Unsafe)localObject2).putInt(localObject3, l, zzgnw.zzF(((zzgna)localObject4).zza));
            }
            break;
          case 12: 
            if (i4 == 0)
            {
              j = zzgnb.zzj((byte[])localObject1, j, (zzgna)localObject4);
              i2 = ((zzgna)localObject4).zza;
              localObject4 = zzB(paramInt1);
              if ((localObject4 != null) && (!((zzgpa)localObject4).zza(i2)))
              {
                zzd(paramObject).zzj(i1, Long.valueOf(i2));
                i1 = paramInt1;
              }
              else
              {
                ((Unsafe)localObject2).putInt(localObject3, l, i2);
              }
            }
            break;
          case 10: 
            if (i4 == 2)
            {
              j = zzgnb.zza((byte[])localObject1, j, (zzgna)localObject4);
              ((Unsafe)localObject2).putObject(localObject3, l, ((zzgna)localObject4).zzc);
              i1 = n | i3;
              n = paramInt1;
              n = i1;
              i1 = paramInt1;
              i1 = i;
              i1 = k;
            }
            else
            {
              i1 = paramInt1;
              i1 = k;
              i1 = j;
            }
            break;
          case 9: 
            if (i4 == 2)
            {
              localObject4 = zzF(localObject3, paramInt1);
              j = zzgnb.zzo(localObject4, zzC(paramInt1), paramArrayOfByte, j, paramInt2, paramzzgna);
              zzO(localObject3, paramInt1, localObject4);
              break label1074;
            }
            break;
          case 8: 
            if (i4 == 2)
            {
              if ((i6 & 0x20000000) == 0) {
                j = zzgnb.zzg((byte[])localObject1, j, (zzgna)localObject4);
              } else {
                j = zzgnb.zzh((byte[])localObject1, j, (zzgna)localObject4);
              }
              ((Unsafe)localObject2).putObject(localObject3, l, ((zzgna)localObject4).zzc);
            }
            break;
          case 7: 
            if (i4 == 0)
            {
              j = zzgnb.zzm((byte[])localObject1, j, (zzgna)localObject4);
              boolean bool;
              if (((zzgna)localObject4).zzb != 0L) {
                bool = true;
              } else {
                bool = false;
              }
              zzgsa.zzp(localObject3, l, bool);
            }
            break;
          case 6: 
          case 13: 
            if (i4 == 5)
            {
              ((Unsafe)localObject2).putInt(localObject3, l, zzgnb.zzb((byte[])localObject1, j));
              j += 4;
            }
            break;
          case 5: 
          case 14: 
            if (i4 == 1)
            {
              ((Unsafe)localObject2).putLong(paramObject, l, zzgnb.zzp((byte[])localObject1, j));
              break label1071;
            }
            i1 = j;
            break;
          case 4: 
          case 11: 
            i1 = j;
            if (i4 != 0) {
              break label1125;
            }
            j = zzgnb.zzj((byte[])localObject1, i1, (zzgna)localObject4);
            ((Unsafe)localObject2).putInt(localObject3, l, ((zzgna)localObject4).zza);
            break;
          case 2: 
          case 3: 
            i2 = j;
            if (i4 != 0) {
              break label1125;
            }
            j = zzgnb.zzm((byte[])localObject1, i2, (zzgna)localObject4);
            ((Unsafe)localObject2).putLong(paramObject, l, ((zzgna)localObject4).zzb);
            n |= i3;
            i2 = paramInt1;
            i2 = i;
            i1 = k;
            i1 = paramInt1;
            i1 = i;
            break;
          case 1: 
            i1 = j;
            if (i4 != 5) {
              break label1125;
            }
            zzgsa.zzs(localObject3, l, Float.intBitsToFloat(zzgnb.zzb((byte[])localObject1, i1)));
            j = i1 + 4;
            break;
          }
          i1 = j;
          if (i4 == 1)
          {
            zzgsa.zzr(localObject3, l, Double.longBitsToDouble(zzgnb.zzp((byte[])localObject1, i1)));
            label1071:
            j += 8;
            label1074:
            n |= i3;
            i1 = paramInt1;
            i1 = i;
            i1 = k;
            i3 = paramInt1;
            i4 = m;
            i1 = paramInt3;
            paramInt1 = j;
            i2 = i;
            i = k;
            m = n;
            n = i4;
            continue;
          }
          label1125:
          i1 = j;
          i1 = k;
          i1 = paramInt1;
          i2 = k;
          i1 = paramInt1;
          paramInt1 = paramInt3;
          k = n;
          n = i;
          n = j;
          j = i2;
          i2 = m;
          m = n;
          n = i2;
        }
        else
        {
          if (i5 == 27)
          {
            if (i4 == 2)
            {
              localObject4 = (zzgpf)((Unsafe)localObject2).getObject(localObject3, l);
              localObject1 = localObject4;
              if (!((zzgpf)localObject4).zzc())
              {
                k = ((zzgpf)localObject4).size();
                if (k == 0) {
                  k = 10;
                } else {
                  k += k;
                }
                localObject1 = ((zzgpf)localObject4).zzd(k);
                ((Unsafe)localObject2).putObject(localObject3, l, localObject1);
              }
              k = zzgnb.zze(zzC(paramInt1), i1, paramArrayOfByte, j, paramInt2, (zzgpf)localObject1, paramzzgna);
              j = paramInt3;
              i3 = paramInt1;
              localObject1 = paramArrayOfByte;
              paramInt1 = k;
              i2 = i;
              i = i1;
              i1 = j;
              continue;
            }
          }
          else
          {
            i2 = m;
            if (i5 <= 49)
            {
              m = zzt(paramObject, paramArrayOfByte, j, paramInt2, i1, i, i4, paramInt1, i6, i5, l, paramzzgna);
              k = m;
              if (m != j) {
                j = m;
              }
            }
          }
          for (;;)
          {
            localObject1 = paramObject;
            localObject1 = paramArrayOfByte;
            i3 = i;
            k = paramInt3;
            localObject3 = paramzzgna;
            m = i2;
            i = i1;
            i1 = paramInt1;
            paramInt1 = j;
            i2 = i3;
            i3 = i1;
            i1 = k;
            break;
            label1527:
            do
            {
              do
              {
                j = i;
                i3 = paramInt1;
                j = i1;
                paramInt1 = paramInt3;
                m = k;
                k = i2;
                i1 = i3;
                break label1572;
                if (i5 != 50) {
                  break label1527;
                }
                if (i4 != 2) {
                  break;
                }
                m = zzr(paramObject, paramArrayOfByte, j, paramInt2, paramInt1, l, paramzzgna);
                k = m;
              } while (m == j);
              j = m;
              break;
              k = i;
              i2 = paramInt1;
              k = m;
              paramInt1 = paramInt3;
              m = j;
              j = i1;
              i1 = i2;
              break label1572;
              m = zzs(paramObject, paramArrayOfByte, j, paramInt2, i1, i, i4, i6, i5, l, paramInt1, paramzzgna);
              k = m;
            } while (m == j);
            j = m;
          }
        }
      }
      label1572:
      i2 = i;
      if ((j == paramInt1) && (paramInt1 != 0))
      {
        paramArrayOfByte = this;
        localObject3 = paramObject;
        paramInt3 = m;
        m = k;
        break label1730;
      }
      if (this.zzh)
      {
        localObject1 = paramzzgna.zzd;
        if (localObject1 != zzgoi.zza)
        {
          if (((zzgoi)localObject1).zzc(this.zzg, i2) == null)
          {
            i = zzgnb.zzi(j, paramArrayOfByte, m, paramInt2, zzd(paramObject), paramzzgna);
            break label1687;
          }
          paramObject = (zzgot)paramObject;
          throw null;
        }
      }
      i = zzgnb.zzi(j, paramArrayOfByte, m, paramInt2, zzd(paramObject), paramzzgna);
      label1687:
      localObject1 = paramObject;
      i3 = i1;
      localObject1 = paramArrayOfByte;
      i1 = paramInt1;
      localObject3 = paramzzgna;
      paramInt1 = i;
      i = j;
      m = k;
    }
    paramArrayOfByte = this;
    paramInt3 = paramInt1;
    paramInt1 = i1;
    int j = i;
    label1730:
    paramArrayOfByte = this;
    if (n != 1048575) {
      ((Unsafe)localObject2).putInt(localObject3, n, m);
    }
    for (i = paramArrayOfByte.zzl; i < paramArrayOfByte.zzm; i++) {
      zzD(paramObject, paramArrayOfByte.zzk[i], null, paramArrayOfByte.zzo, paramObject);
    }
    if (paramInt1 == 0)
    {
      if (paramInt3 != paramInt2) {
        throw zzgpi.zzg();
      }
    }
    else {
      if ((paramInt3 > paramInt2) || (j != paramInt1)) {
        break label1825;
      }
    }
    return paramInt3;
    label1825:
    throw zzgpi.zzg();
  }
  
  public final Object zze()
  {
    return ((zzgow)this.zzg).zzaD();
  }
  
  public final void zzf(Object paramObject)
  {
    if (!zzV(paramObject)) {
      return;
    }
    boolean bool = paramObject instanceof zzgow;
    int i = 0;
    Object localObject;
    if (bool)
    {
      localObject = (zzgow)paramObject;
      ((zzgow)localObject).zzaV(Integer.MAX_VALUE);
      ((zzgow)localObject).zza = 0;
      ((zzgow)localObject).zzaT();
    }
    int j = this.zzc.length;
    while (i < j)
    {
      int m = zzz(i);
      int k = zzy(m);
      long l = 0xFFFFF & m;
      if (k != 9)
      {
        if ((k != 60) && (k != 68)) {}
        switch (k)
        {
        default: 
          break;
        case 50: 
          Unsafe localUnsafe = zzb;
          localObject = localUnsafe.getObject(paramObject, l);
          if (localObject == null) {
            break;
          }
          ((zzgqa)localObject).zzc();
          localUnsafe.putObject(paramObject, l, localObject);
          break;
        case 18: 
        case 19: 
        case 20: 
        case 21: 
        case 22: 
        case 23: 
        case 24: 
        case 25: 
        case 26: 
        case 27: 
        case 28: 
        case 29: 
        case 30: 
        case 31: 
        case 32: 
        case 33: 
        case 34: 
        case 35: 
        case 36: 
        case 37: 
        case 38: 
        case 39: 
        case 40: 
        case 41: 
        case 42: 
        case 43: 
        case 44: 
        case 45: 
        case 46: 
        case 47: 
        case 48: 
        case 49: 
          this.zzn.zzb(paramObject, l);
          break;
          if (!zzW(paramObject, this.zzc[i], i)) {
            break;
          }
          zzC(i).zzf(zzb.getObject(paramObject, l));
          break;
        }
      }
      else if (zzS(paramObject, i))
      {
        zzC(i).zzf(zzb.getObject(paramObject, l));
      }
      i += 3;
    }
    this.zzo.zzm(paramObject);
    if (this.zzh) {
      this.zzp.zze(paramObject);
    }
  }
  
  public final void zzg(Object paramObject1, Object paramObject2)
  {
    zzI(paramObject1);
    Objects.requireNonNull(paramObject2);
    for (int i = 0; i < this.zzc.length; i += 3)
    {
      int j = zzz(i);
      int k = this.zzc[i];
      int m = zzy(j);
      long l = 0xFFFFF & j;
      switch (m)
      {
      default: 
        break;
      case 68: 
        zzK(paramObject1, paramObject2, i);
        break;
      case 61: 
      case 62: 
      case 63: 
      case 64: 
      case 65: 
      case 66: 
      case 67: 
        if (zzW(paramObject2, k, i))
        {
          zzgsa.zzv(paramObject1, l, zzgsa.zzh(paramObject2, l));
          zzN(paramObject1, k, i);
        }
        break;
      case 60: 
        zzK(paramObject1, paramObject2, i);
        break;
      case 51: 
      case 52: 
      case 53: 
      case 54: 
      case 55: 
      case 56: 
      case 57: 
      case 58: 
      case 59: 
        if (zzW(paramObject2, k, i))
        {
          zzgsa.zzv(paramObject1, l, zzgsa.zzh(paramObject2, l));
          zzN(paramObject1, k, i);
        }
        break;
      case 50: 
        j = zzgrb.zza;
        zzgsa.zzv(paramObject1, l, zzgqb.zzc(zzgsa.zzh(paramObject1, l), zzgsa.zzh(paramObject2, l)));
        break;
      case 18: 
      case 19: 
      case 20: 
      case 21: 
      case 22: 
      case 23: 
      case 24: 
      case 25: 
      case 26: 
      case 27: 
      case 28: 
      case 29: 
      case 30: 
      case 31: 
      case 32: 
      case 33: 
      case 34: 
      case 35: 
      case 36: 
      case 37: 
      case 38: 
      case 39: 
      case 40: 
      case 41: 
      case 42: 
      case 43: 
      case 44: 
      case 45: 
      case 46: 
      case 47: 
      case 48: 
      case 49: 
        this.zzn.zzc(paramObject1, paramObject2, l);
        break;
      case 17: 
        zzJ(paramObject1, paramObject2, i);
        break;
      case 16: 
        if (zzS(paramObject2, i))
        {
          zzgsa.zzu(paramObject1, l, zzgsa.zzf(paramObject2, l));
          zzM(paramObject1, i);
        }
        break;
      case 15: 
        if (zzS(paramObject2, i))
        {
          zzgsa.zzt(paramObject1, l, zzgsa.zzd(paramObject2, l));
          zzM(paramObject1, i);
        }
        break;
      case 14: 
        if (zzS(paramObject2, i))
        {
          zzgsa.zzu(paramObject1, l, zzgsa.zzf(paramObject2, l));
          zzM(paramObject1, i);
        }
        break;
      case 13: 
        if (zzS(paramObject2, i))
        {
          zzgsa.zzt(paramObject1, l, zzgsa.zzd(paramObject2, l));
          zzM(paramObject1, i);
        }
        break;
      case 12: 
        if (zzS(paramObject2, i))
        {
          zzgsa.zzt(paramObject1, l, zzgsa.zzd(paramObject2, l));
          zzM(paramObject1, i);
        }
        break;
      case 11: 
        if (zzS(paramObject2, i))
        {
          zzgsa.zzt(paramObject1, l, zzgsa.zzd(paramObject2, l));
          zzM(paramObject1, i);
        }
        break;
      case 10: 
        if (zzS(paramObject2, i))
        {
          zzgsa.zzv(paramObject1, l, zzgsa.zzh(paramObject2, l));
          zzM(paramObject1, i);
        }
        break;
      case 9: 
        zzJ(paramObject1, paramObject2, i);
        break;
      case 8: 
        if (zzS(paramObject2, i))
        {
          zzgsa.zzv(paramObject1, l, zzgsa.zzh(paramObject2, l));
          zzM(paramObject1, i);
        }
        break;
      case 7: 
        if (zzS(paramObject2, i))
        {
          zzgsa.zzp(paramObject1, l, zzgsa.zzz(paramObject2, l));
          zzM(paramObject1, i);
        }
        break;
      case 6: 
        if (zzS(paramObject2, i))
        {
          zzgsa.zzt(paramObject1, l, zzgsa.zzd(paramObject2, l));
          zzM(paramObject1, i);
        }
        break;
      case 5: 
        if (zzS(paramObject2, i))
        {
          zzgsa.zzu(paramObject1, l, zzgsa.zzf(paramObject2, l));
          zzM(paramObject1, i);
        }
        break;
      case 4: 
        if (zzS(paramObject2, i))
        {
          zzgsa.zzt(paramObject1, l, zzgsa.zzd(paramObject2, l));
          zzM(paramObject1, i);
        }
        break;
      case 3: 
        if (zzS(paramObject2, i))
        {
          zzgsa.zzu(paramObject1, l, zzgsa.zzf(paramObject2, l));
          zzM(paramObject1, i);
        }
        break;
      case 2: 
        if (zzS(paramObject2, i))
        {
          zzgsa.zzu(paramObject1, l, zzgsa.zzf(paramObject2, l));
          zzM(paramObject1, i);
        }
        break;
      case 1: 
        if (zzS(paramObject2, i))
        {
          zzgsa.zzs(paramObject1, l, zzgsa.zzc(paramObject2, l));
          zzM(paramObject1, i);
        }
        break;
      case 0: 
        if (zzS(paramObject2, i))
        {
          zzgsa.zzr(paramObject1, l, zzgsa.zzb(paramObject2, l));
          zzM(paramObject1, i);
        }
        break;
      }
    }
    zzgrb.zzC(this.zzo, paramObject1, paramObject2);
    if (!this.zzh) {
      return;
    }
    this.zzp.zza(paramObject2);
    throw null;
  }
  
  /* Error */
  public final void zzh(Object paramObject, zzgqr paramzzgqr, zzgoi paramzzgoi)
    throws IOException
  {
    // Byte code:
    //   0: aload_1
    //   1: astore 14
    //   3: aload_3
    //   4: astore 20
    //   6: aload_3
    //   7: invokestatic 823	java/util/Objects:requireNonNull	(Ljava/lang/Object;)Ljava/lang/Object;
    //   10: pop
    //   11: aload_1
    //   12: invokestatic 740	com/google/android/gms/internal/ads/zzgqj:zzI	(Ljava/lang/Object;)V
    //   15: aload_0
    //   16: getfield 85	com/google/android/gms/internal/ads/zzgqj:zzo	Lcom/google/android/gms/internal/ads/zzgrq;
    //   19: astore 15
    //   21: aload_0
    //   22: getfield 87	com/google/android/gms/internal/ads/zzgqj:zzp	Lcom/google/android/gms/internal/ads/zzgoj;
    //   25: astore 17
    //   27: aconst_null
    //   28: astore 16
    //   30: aconst_null
    //   31: astore 21
    //   33: aload_2
    //   34: invokeinterface 839 1 0
    //   39: istore 9
    //   41: aload_0
    //   42: iload 9
    //   44: invokespecial 747	com/google/android/gms/internal/ads/zzgqj:zzu	(I)I
    //   47: istore 7
    //   49: iload 7
    //   51: ifge +277 -> 328
    //   54: iload 9
    //   56: ldc_w 798
    //   59: if_icmpne +58 -> 117
    //   62: aload_0
    //   63: getfield 77	com/google/android/gms/internal/ads/zzgqj:zzl	I
    //   66: istore 7
    //   68: iload 7
    //   70: aload_0
    //   71: getfield 79	com/google/android/gms/internal/ads/zzgqj:zzm	I
    //   74: if_icmpge +28 -> 102
    //   77: aload_0
    //   78: aload_1
    //   79: aload_0
    //   80: getfield 75	com/google/android/gms/internal/ads/zzgqj:zzk	[I
    //   83: iload 7
    //   85: iaload
    //   86: aload 16
    //   88: aload 15
    //   90: aload_1
    //   91: invokespecial 791	com/google/android/gms/internal/ads/zzgqj:zzD	(Ljava/lang/Object;ILjava/lang/Object;Lcom/google/android/gms/internal/ads/zzgrq;Ljava/lang/Object;)Ljava/lang/Object;
    //   94: astore 16
    //   96: iinc 7 1
    //   99: goto -31 -> 68
    //   102: aload 16
    //   104: ifnull +3139 -> 3243
    //   107: aload 15
    //   109: aload 14
    //   111: aload 16
    //   113: invokevirtual 841	com/google/android/gms/internal/ads/zzgrq:zzn	(Ljava/lang/Object;Ljava/lang/Object;)V
    //   116: return
    //   117: aload_0
    //   118: getfield 73	com/google/android/gms/internal/ads/zzgqj:zzh	Z
    //   121: ifne +9 -> 130
    //   124: aconst_null
    //   125: astore 19
    //   127: goto +18 -> 145
    //   130: aload 17
    //   132: aload 20
    //   134: aload_0
    //   135: getfield 89	com/google/android/gms/internal/ads/zzgqj:zzg	Lcom/google/android/gms/internal/ads/zzgqg;
    //   138: iload 9
    //   140: invokevirtual 844	com/google/android/gms/internal/ads/zzgoj:zzc	(Lcom/google/android/gms/internal/ads/zzgoi;Lcom/google/android/gms/internal/ads/zzgqg;I)Ljava/lang/Object;
    //   143: astore 19
    //   145: aload 19
    //   147: ifnull +50 -> 197
    //   150: aload 21
    //   152: astore 18
    //   154: aload 21
    //   156: ifnonnull +12 -> 168
    //   159: aload 17
    //   161: aload 14
    //   163: invokevirtual 846	com/google/android/gms/internal/ads/zzgoj:zzb	(Ljava/lang/Object;)Lcom/google/android/gms/internal/ads/zzgon;
    //   166: astore 18
    //   168: aload 17
    //   170: aload_1
    //   171: aload_2
    //   172: aload 19
    //   174: aload_3
    //   175: aload 18
    //   177: aload 16
    //   179: aload 15
    //   181: invokevirtual 849	com/google/android/gms/internal/ads/zzgoj:zzd	(Ljava/lang/Object;Lcom/google/android/gms/internal/ads/zzgqr;Ljava/lang/Object;Lcom/google/android/gms/internal/ads/zzgoi;Lcom/google/android/gms/internal/ads/zzgon;Ljava/lang/Object;Lcom/google/android/gms/internal/ads/zzgrq;)Ljava/lang/Object;
    //   184: astore 19
    //   186: aload 18
    //   188: astore 21
    //   190: aload 19
    //   192: astore 16
    //   194: goto -161 -> 33
    //   197: aload 15
    //   199: astore 19
    //   201: aload 14
    //   203: astore 22
    //   205: aload 19
    //   207: aload_2
    //   208: invokevirtual 852	com/google/android/gms/internal/ads/zzgrq:zzq	(Lcom/google/android/gms/internal/ads/zzgqr;)Z
    //   211: pop
    //   212: aload 16
    //   214: astore 18
    //   216: aload 16
    //   218: ifnonnull +12 -> 230
    //   221: aload 19
    //   223: aload 22
    //   225: invokevirtual 854	com/google/android/gms/internal/ads/zzgrq:zzc	(Ljava/lang/Object;)Ljava/lang/Object;
    //   228: astore 18
    //   230: aload 19
    //   232: aload 18
    //   234: aload_2
    //   235: invokevirtual 857	com/google/android/gms/internal/ads/zzgrq:zzp	(Ljava/lang/Object;Lcom/google/android/gms/internal/ads/zzgqr;)Z
    //   238: istore 11
    //   240: aload 18
    //   242: astore 16
    //   244: iload 11
    //   246: ifne -52 -> 194
    //   249: aload_0
    //   250: getfield 77	com/google/android/gms/internal/ads/zzgqj:zzl	I
    //   253: istore 7
    //   255: iload 7
    //   257: aload_0
    //   258: getfield 79	com/google/android/gms/internal/ads/zzgqj:zzm	I
    //   261: if_icmpge +28 -> 289
    //   264: aload_0
    //   265: aload_1
    //   266: aload_0
    //   267: getfield 75	com/google/android/gms/internal/ads/zzgqj:zzk	[I
    //   270: iload 7
    //   272: iaload
    //   273: aload 18
    //   275: aload 19
    //   277: aload_1
    //   278: invokespecial 791	com/google/android/gms/internal/ads/zzgqj:zzD	(Ljava/lang/Object;ILjava/lang/Object;Lcom/google/android/gms/internal/ads/zzgrq;Ljava/lang/Object;)Ljava/lang/Object;
    //   281: astore 18
    //   283: iinc 7 1
    //   286: goto -31 -> 255
    //   289: aload 18
    //   291: ifnull +2952 -> 3243
    //   294: aload 19
    //   296: aload 22
    //   298: aload 18
    //   300: invokevirtual 841	com/google/android/gms/internal/ads/zzgrq:zzn	(Ljava/lang/Object;Ljava/lang/Object;)V
    //   303: return
    //   304: astore_2
    //   305: goto +2966 -> 3271
    //   308: astore_2
    //   309: aload 14
    //   311: astore_3
    //   312: aload 15
    //   314: astore_3
    //   315: goto +2930 -> 3245
    //   318: astore_2
    //   319: aload 15
    //   321: astore_3
    //   322: aload 14
    //   324: astore_3
    //   325: goto +2920 -> 3245
    //   328: aload 15
    //   330: astore 22
    //   332: aload 14
    //   334: astore 23
    //   336: aload_0
    //   337: iload 7
    //   339: invokespecial 124	com/google/android/gms/internal/ads/zzgqj:zzz	(I)I
    //   342: istore 8
    //   344: iload 8
    //   346: invokestatic 299	com/google/android/gms/internal/ads/zzgqj:zzy	(I)I
    //   349: istore 10
    //   351: iload 10
    //   353: tableswitch	default:+291->644, 0:+2637->2990, 1:+2605->2958, 2:+2573->2926, 3:+2541->2894, 4:+2509->2862, 5:+2477->2830, 6:+2445->2798, 7:+2413->2766, 8:+2389->2742, 9:+2347->2700, 10:+2315->2668, 11:+2283->2636, 12:+2201->2554, 13:+2169->2522, 14:+2137->2490, 15:+2105->2458, 16:+2073->2426, 17:+2031->2384, 18:+2007->2360, 19:+1983->2336, 20:+1959->2312, 21:+1935->2288, 22:+1911->2264, 23:+1887->2240, 24:+1863->2216, 25:+1839->2192, 26:+1771->2124, 27:+1735->2088, 28:+1711->2064, 29:+1687->2040, 30:+1635->1988, 31:+1611->1964, 32:+1587->1940, 33:+1563->1916, 34:+1539->1892, 35:+1515->1868, 36:+1491->1844, 37:+1467->1820, 38:+1443->1796, 39:+1419->1772, 40:+1395->1748, 41:+1371->1724, 42:+1347->1700, 43:+1323->1676, 44:+1267->1620, 45:+1243->1596, 46:+1219->1572, 47:+1195->1548, 48:+1171->1524, 49:+1135->1488, 50:+1028->1381, 51:+991->1344, 52:+954->1307, 53:+917->1270, 54:+880->1233, 55:+843->1196, 56:+806->1159, 57:+769->1122, 58:+732->1085, 59:+710->1063, 60:+664->1017, 61:+630->983, 62:+593->946, 63:+506->859, 64:+469->822, 65:+432->785, 66:+395->748, 67:+358->711, 68:+312->665
    //   644: aload 16
    //   646: ifnonnull +2392 -> 3038
    //   649: aload 22
    //   651: aload 23
    //   653: invokevirtual 854	com/google/android/gms/internal/ads/zzgrq:zzc	(Ljava/lang/Object;)Ljava/lang/Object;
    //   656: astore 18
    //   658: aload 18
    //   660: astore 16
    //   662: goto +2376 -> 3038
    //   665: aload_0
    //   666: aload 23
    //   668: iload 9
    //   670: iload 7
    //   672: invokespecial 548	com/google/android/gms/internal/ads/zzgqj:zzG	(Ljava/lang/Object;II)Ljava/lang/Object;
    //   675: checkcast 425	com/google/android/gms/internal/ads/zzgqg
    //   678: astore 18
    //   680: aload_2
    //   681: aload 18
    //   683: aload_0
    //   684: iload 7
    //   686: invokespecial 139	com/google/android/gms/internal/ads/zzgqj:zzC	(I)Lcom/google/android/gms/internal/ads/zzgqz;
    //   689: aload 20
    //   691: invokeinterface 860 4 0
    //   696: aload_0
    //   697: aload 23
    //   699: iload 9
    //   701: iload 7
    //   703: aload 18
    //   705: invokespecial 555	com/google/android/gms/internal/ads/zzgqj:zzP	(Ljava/lang/Object;IILjava/lang/Object;)V
    //   708: goto +374 -> 1082
    //   711: aload_2
    //   712: invokeinterface 862 1 0
    //   717: lstore 12
    //   719: aload 23
    //   721: iload 8
    //   723: ldc 125
    //   725: iand
    //   726: i2l
    //   727: lload 12
    //   729: invokestatic 571	java/lang/Long:valueOf	(J)Ljava/lang/Long;
    //   732: invokestatic 271	com/google/android/gms/internal/ads/zzgsa:zzv	(Ljava/lang/Object;JLjava/lang/Object;)V
    //   735: aload_0
    //   736: aload 23
    //   738: iload 9
    //   740: iload 7
    //   742: invokespecial 255	com/google/android/gms/internal/ads/zzgqj:zzN	(Ljava/lang/Object;II)V
    //   745: goto +337 -> 1082
    //   748: aload_2
    //   749: invokeinterface 864 1 0
    //   754: istore 10
    //   756: aload 23
    //   758: iload 8
    //   760: ldc 125
    //   762: iand
    //   763: i2l
    //   764: iload 10
    //   766: invokestatic 582	java/lang/Integer:valueOf	(I)Ljava/lang/Integer;
    //   769: invokestatic 271	com/google/android/gms/internal/ads/zzgsa:zzv	(Ljava/lang/Object;JLjava/lang/Object;)V
    //   772: aload_0
    //   773: aload 23
    //   775: iload 9
    //   777: iload 7
    //   779: invokespecial 255	com/google/android/gms/internal/ads/zzgqj:zzN	(Ljava/lang/Object;II)V
    //   782: goto +300 -> 1082
    //   785: aload_2
    //   786: invokeinterface 866 1 0
    //   791: lstore 12
    //   793: aload 23
    //   795: iload 8
    //   797: ldc 125
    //   799: iand
    //   800: i2l
    //   801: lload 12
    //   803: invokestatic 571	java/lang/Long:valueOf	(J)Ljava/lang/Long;
    //   806: invokestatic 271	com/google/android/gms/internal/ads/zzgsa:zzv	(Ljava/lang/Object;JLjava/lang/Object;)V
    //   809: aload_0
    //   810: aload 23
    //   812: iload 9
    //   814: iload 7
    //   816: invokespecial 255	com/google/android/gms/internal/ads/zzgqj:zzN	(Ljava/lang/Object;II)V
    //   819: goto +263 -> 1082
    //   822: aload_2
    //   823: invokeinterface 868 1 0
    //   828: istore 10
    //   830: aload 23
    //   832: iload 8
    //   834: ldc 125
    //   836: iand
    //   837: i2l
    //   838: iload 10
    //   840: invokestatic 582	java/lang/Integer:valueOf	(I)Ljava/lang/Integer;
    //   843: invokestatic 271	com/google/android/gms/internal/ads/zzgsa:zzv	(Ljava/lang/Object;JLjava/lang/Object;)V
    //   846: aload_0
    //   847: aload 23
    //   849: iload 9
    //   851: iload 7
    //   853: invokespecial 255	com/google/android/gms/internal/ads/zzgqj:zzN	(Ljava/lang/Object;II)V
    //   856: goto +226 -> 1082
    //   859: aload_2
    //   860: invokeinterface 870 1 0
    //   865: istore 10
    //   867: aload_0
    //   868: iload 7
    //   870: invokespecial 127	com/google/android/gms/internal/ads/zzgqj:zzB	(I)Lcom/google/android/gms/internal/ads/zzgpa;
    //   873: astore 18
    //   875: aload 18
    //   877: ifnull +40 -> 917
    //   880: aload 18
    //   882: iload 10
    //   884: invokeinterface 584 2 0
    //   889: ifeq +6 -> 895
    //   892: goto +25 -> 917
    //   895: aload 23
    //   897: iload 9
    //   899: iload 10
    //   901: aload 16
    //   903: aload 22
    //   905: invokestatic 873	com/google/android/gms/internal/ads/zzgrb:zzB	(Ljava/lang/Object;IILjava/lang/Object;Lcom/google/android/gms/internal/ads/zzgrq;)Ljava/lang/Object;
    //   908: astore 18
    //   910: aload 18
    //   912: astore 16
    //   914: goto +2117 -> 3031
    //   917: aload 23
    //   919: iload 8
    //   921: ldc 125
    //   923: iand
    //   924: i2l
    //   925: iload 10
    //   927: invokestatic 582	java/lang/Integer:valueOf	(I)Ljava/lang/Integer;
    //   930: invokestatic 271	com/google/android/gms/internal/ads/zzgsa:zzv	(Ljava/lang/Object;JLjava/lang/Object;)V
    //   933: aload_0
    //   934: aload 23
    //   936: iload 9
    //   938: iload 7
    //   940: invokespecial 255	com/google/android/gms/internal/ads/zzgqj:zzN	(Ljava/lang/Object;II)V
    //   943: goto +139 -> 1082
    //   946: aload_2
    //   947: invokeinterface 875 1 0
    //   952: istore 10
    //   954: aload 23
    //   956: iload 8
    //   958: ldc 125
    //   960: iand
    //   961: i2l
    //   962: iload 10
    //   964: invokestatic 582	java/lang/Integer:valueOf	(I)Ljava/lang/Integer;
    //   967: invokestatic 271	com/google/android/gms/internal/ads/zzgsa:zzv	(Ljava/lang/Object;JLjava/lang/Object;)V
    //   970: aload_0
    //   971: aload 23
    //   973: iload 9
    //   975: iload 7
    //   977: invokespecial 255	com/google/android/gms/internal/ads/zzgqj:zzN	(Ljava/lang/Object;II)V
    //   980: goto +102 -> 1082
    //   983: aload_2
    //   984: invokeinterface 276 1 0
    //   989: astore 18
    //   991: aload 23
    //   993: iload 8
    //   995: ldc 125
    //   997: iand
    //   998: i2l
    //   999: aload 18
    //   1001: invokestatic 271	com/google/android/gms/internal/ads/zzgsa:zzv	(Ljava/lang/Object;JLjava/lang/Object;)V
    //   1004: aload_0
    //   1005: aload 23
    //   1007: iload 9
    //   1009: iload 7
    //   1011: invokespecial 255	com/google/android/gms/internal/ads/zzgqj:zzN	(Ljava/lang/Object;II)V
    //   1014: goto +68 -> 1082
    //   1017: aload_0
    //   1018: aload 23
    //   1020: iload 9
    //   1022: iload 7
    //   1024: invokespecial 548	com/google/android/gms/internal/ads/zzgqj:zzG	(Ljava/lang/Object;II)Ljava/lang/Object;
    //   1027: checkcast 425	com/google/android/gms/internal/ads/zzgqg
    //   1030: astore 18
    //   1032: aload_2
    //   1033: aload 18
    //   1035: aload_0
    //   1036: iload 7
    //   1038: invokespecial 139	com/google/android/gms/internal/ads/zzgqj:zzC	(I)Lcom/google/android/gms/internal/ads/zzgqz;
    //   1041: aload 20
    //   1043: invokeinterface 877 4 0
    //   1048: aload_0
    //   1049: aload 23
    //   1051: iload 9
    //   1053: iload 7
    //   1055: aload 18
    //   1057: invokespecial 555	com/google/android/gms/internal/ads/zzgqj:zzP	(Ljava/lang/Object;IILjava/lang/Object;)V
    //   1060: goto +22 -> 1082
    //   1063: aload_0
    //   1064: aload 23
    //   1066: iload 8
    //   1068: aload_2
    //   1069: invokespecial 879	com/google/android/gms/internal/ads/zzgqj:zzL	(Ljava/lang/Object;ILcom/google/android/gms/internal/ads/zzgqr;)V
    //   1072: aload_0
    //   1073: aload 23
    //   1075: iload 9
    //   1077: iload 7
    //   1079: invokespecial 255	com/google/android/gms/internal/ads/zzgqj:zzN	(Ljava/lang/Object;II)V
    //   1082: goto +1937 -> 3019
    //   1085: aload_2
    //   1086: invokeinterface 881 1 0
    //   1091: istore 11
    //   1093: aload 23
    //   1095: iload 8
    //   1097: ldc 125
    //   1099: iand
    //   1100: i2l
    //   1101: iload 11
    //   1103: invokestatic 620	java/lang/Boolean:valueOf	(Z)Ljava/lang/Boolean;
    //   1106: invokestatic 271	com/google/android/gms/internal/ads/zzgsa:zzv	(Ljava/lang/Object;JLjava/lang/Object;)V
    //   1109: aload_0
    //   1110: aload 23
    //   1112: iload 9
    //   1114: iload 7
    //   1116: invokespecial 255	com/google/android/gms/internal/ads/zzgqj:zzN	(Ljava/lang/Object;II)V
    //   1119: goto -37 -> 1082
    //   1122: aload_2
    //   1123: invokeinterface 883 1 0
    //   1128: istore 10
    //   1130: aload 23
    //   1132: iload 8
    //   1134: ldc 125
    //   1136: iand
    //   1137: i2l
    //   1138: iload 10
    //   1140: invokestatic 582	java/lang/Integer:valueOf	(I)Ljava/lang/Integer;
    //   1143: invokestatic 271	com/google/android/gms/internal/ads/zzgsa:zzv	(Ljava/lang/Object;JLjava/lang/Object;)V
    //   1146: aload_0
    //   1147: aload 23
    //   1149: iload 9
    //   1151: iload 7
    //   1153: invokespecial 255	com/google/android/gms/internal/ads/zzgqj:zzN	(Ljava/lang/Object;II)V
    //   1156: goto -74 -> 1082
    //   1159: aload_2
    //   1160: invokeinterface 885 1 0
    //   1165: lstore 12
    //   1167: aload 23
    //   1169: iload 8
    //   1171: ldc 125
    //   1173: iand
    //   1174: i2l
    //   1175: lload 12
    //   1177: invokestatic 571	java/lang/Long:valueOf	(J)Ljava/lang/Long;
    //   1180: invokestatic 271	com/google/android/gms/internal/ads/zzgsa:zzv	(Ljava/lang/Object;JLjava/lang/Object;)V
    //   1183: aload_0
    //   1184: aload 23
    //   1186: iload 9
    //   1188: iload 7
    //   1190: invokespecial 255	com/google/android/gms/internal/ads/zzgqj:zzN	(Ljava/lang/Object;II)V
    //   1193: goto -111 -> 1082
    //   1196: aload_2
    //   1197: invokeinterface 887 1 0
    //   1202: istore 10
    //   1204: aload 23
    //   1206: iload 8
    //   1208: ldc 125
    //   1210: iand
    //   1211: i2l
    //   1212: iload 10
    //   1214: invokestatic 582	java/lang/Integer:valueOf	(I)Ljava/lang/Integer;
    //   1217: invokestatic 271	com/google/android/gms/internal/ads/zzgsa:zzv	(Ljava/lang/Object;JLjava/lang/Object;)V
    //   1220: aload_0
    //   1221: aload 23
    //   1223: iload 9
    //   1225: iload 7
    //   1227: invokespecial 255	com/google/android/gms/internal/ads/zzgqj:zzN	(Ljava/lang/Object;II)V
    //   1230: goto -148 -> 1082
    //   1233: aload_2
    //   1234: invokeinterface 889 1 0
    //   1239: lstore 12
    //   1241: aload 23
    //   1243: iload 8
    //   1245: ldc 125
    //   1247: iand
    //   1248: i2l
    //   1249: lload 12
    //   1251: invokestatic 571	java/lang/Long:valueOf	(J)Ljava/lang/Long;
    //   1254: invokestatic 271	com/google/android/gms/internal/ads/zzgsa:zzv	(Ljava/lang/Object;JLjava/lang/Object;)V
    //   1257: aload_0
    //   1258: aload 23
    //   1260: iload 9
    //   1262: iload 7
    //   1264: invokespecial 255	com/google/android/gms/internal/ads/zzgqj:zzN	(Ljava/lang/Object;II)V
    //   1267: goto -185 -> 1082
    //   1270: aload_2
    //   1271: invokeinterface 891 1 0
    //   1276: lstore 12
    //   1278: aload 23
    //   1280: iload 8
    //   1282: ldc 125
    //   1284: iand
    //   1285: i2l
    //   1286: lload 12
    //   1288: invokestatic 571	java/lang/Long:valueOf	(J)Ljava/lang/Long;
    //   1291: invokestatic 271	com/google/android/gms/internal/ads/zzgsa:zzv	(Ljava/lang/Object;JLjava/lang/Object;)V
    //   1294: aload_0
    //   1295: aload 23
    //   1297: iload 9
    //   1299: iload 7
    //   1301: invokespecial 255	com/google/android/gms/internal/ads/zzgqj:zzN	(Ljava/lang/Object;II)V
    //   1304: goto -222 -> 1082
    //   1307: aload_2
    //   1308: invokeinterface 893 1 0
    //   1313: fstore 6
    //   1315: aload 23
    //   1317: iload 8
    //   1319: ldc 125
    //   1321: iand
    //   1322: i2l
    //   1323: fload 6
    //   1325: invokestatic 633	java/lang/Float:valueOf	(F)Ljava/lang/Float;
    //   1328: invokestatic 271	com/google/android/gms/internal/ads/zzgsa:zzv	(Ljava/lang/Object;JLjava/lang/Object;)V
    //   1331: aload_0
    //   1332: aload 23
    //   1334: iload 9
    //   1336: iload 7
    //   1338: invokespecial 255	com/google/android/gms/internal/ads/zzgqj:zzN	(Ljava/lang/Object;II)V
    //   1341: goto -259 -> 1082
    //   1344: aload_2
    //   1345: invokeinterface 895 1 0
    //   1350: dstore 4
    //   1352: aload 23
    //   1354: iload 8
    //   1356: ldc 125
    //   1358: iand
    //   1359: i2l
    //   1360: dload 4
    //   1362: invokestatic 640	java/lang/Double:valueOf	(D)Ljava/lang/Double;
    //   1365: invokestatic 271	com/google/android/gms/internal/ads/zzgsa:zzv	(Ljava/lang/Object;JLjava/lang/Object;)V
    //   1368: aload_0
    //   1369: aload 23
    //   1371: iload 9
    //   1373: iload 7
    //   1375: invokespecial 255	com/google/android/gms/internal/ads/zzgqj:zzN	(Ljava/lang/Object;II)V
    //   1378: goto -296 -> 1082
    //   1381: aload_0
    //   1382: iload 7
    //   1384: invokespecial 133	com/google/android/gms/internal/ads/zzgqj:zzE	(I)Ljava/lang/Object;
    //   1387: astore 24
    //   1389: aload_0
    //   1390: iload 7
    //   1392: invokespecial 124	com/google/android/gms/internal/ads/zzgqj:zzz	(I)I
    //   1395: ldc 125
    //   1397: iand
    //   1398: i2l
    //   1399: lstore 12
    //   1401: aload 23
    //   1403: lload 12
    //   1405: invokestatic 96	com/google/android/gms/internal/ads/zzgsa:zzh	(Ljava/lang/Object;J)Ljava/lang/Object;
    //   1408: astore 19
    //   1410: aload 19
    //   1412: ifnull +43 -> 1455
    //   1415: aload 19
    //   1417: astore 18
    //   1419: aload 19
    //   1421: invokestatic 537	com/google/android/gms/internal/ads/zzgqb:zzb	(Ljava/lang/Object;)Z
    //   1424: ifeq +48 -> 1472
    //   1427: invokestatic 540	com/google/android/gms/internal/ads/zzgqa:zza	()Lcom/google/android/gms/internal/ads/zzgqa;
    //   1430: invokevirtual 542	com/google/android/gms/internal/ads/zzgqa:zzb	()Lcom/google/android/gms/internal/ads/zzgqa;
    //   1433: astore 18
    //   1435: aload 18
    //   1437: aload 19
    //   1439: invokestatic 545	com/google/android/gms/internal/ads/zzgqb:zzc	(Ljava/lang/Object;Ljava/lang/Object;)Ljava/lang/Object;
    //   1442: pop
    //   1443: aload 23
    //   1445: lload 12
    //   1447: aload 18
    //   1449: invokestatic 271	com/google/android/gms/internal/ads/zzgsa:zzv	(Ljava/lang/Object;JLjava/lang/Object;)V
    //   1452: goto +20 -> 1472
    //   1455: invokestatic 540	com/google/android/gms/internal/ads/zzgqa:zza	()Lcom/google/android/gms/internal/ads/zzgqa;
    //   1458: invokevirtual 542	com/google/android/gms/internal/ads/zzgqa:zzb	()Lcom/google/android/gms/internal/ads/zzgqa;
    //   1461: astore 18
    //   1463: aload 23
    //   1465: lload 12
    //   1467: aload 18
    //   1469: invokestatic 271	com/google/android/gms/internal/ads/zzgsa:zzv	(Ljava/lang/Object;JLjava/lang/Object;)V
    //   1472: aload 18
    //   1474: checkcast 129	com/google/android/gms/internal/ads/zzgqa
    //   1477: astore 18
    //   1479: aload 24
    //   1481: checkcast 135	com/google/android/gms/internal/ads/zzgpz
    //   1484: astore 18
    //   1486: aconst_null
    //   1487: athrow
    //   1488: aload_0
    //   1489: iload 7
    //   1491: invokespecial 139	com/google/android/gms/internal/ads/zzgqj:zzC	(I)Lcom/google/android/gms/internal/ads/zzgqz;
    //   1494: astore 18
    //   1496: aload_2
    //   1497: aload_0
    //   1498: getfield 83	com/google/android/gms/internal/ads/zzgqj:zzn	Lcom/google/android/gms/internal/ads/zzgpu;
    //   1501: aload 23
    //   1503: iload 8
    //   1505: ldc 125
    //   1507: iand
    //   1508: i2l
    //   1509: invokevirtual 898	com/google/android/gms/internal/ads/zzgpu:zza	(Ljava/lang/Object;J)Ljava/util/List;
    //   1512: aload 18
    //   1514: aload 20
    //   1516: invokeinterface 901 4 0
    //   1521: goto -439 -> 1082
    //   1524: aload_2
    //   1525: aload_0
    //   1526: getfield 83	com/google/android/gms/internal/ads/zzgqj:zzn	Lcom/google/android/gms/internal/ads/zzgpu;
    //   1529: aload 23
    //   1531: iload 8
    //   1533: ldc 125
    //   1535: iand
    //   1536: i2l
    //   1537: invokevirtual 898	com/google/android/gms/internal/ads/zzgpu:zza	(Ljava/lang/Object;J)Ljava/util/List;
    //   1540: invokeinterface 904 2 0
    //   1545: goto -463 -> 1082
    //   1548: aload_2
    //   1549: aload_0
    //   1550: getfield 83	com/google/android/gms/internal/ads/zzgqj:zzn	Lcom/google/android/gms/internal/ads/zzgpu;
    //   1553: aload 23
    //   1555: iload 8
    //   1557: ldc 125
    //   1559: iand
    //   1560: i2l
    //   1561: invokevirtual 898	com/google/android/gms/internal/ads/zzgpu:zza	(Ljava/lang/Object;J)Ljava/util/List;
    //   1564: invokeinterface 906 2 0
    //   1569: goto -487 -> 1082
    //   1572: aload_2
    //   1573: aload_0
    //   1574: getfield 83	com/google/android/gms/internal/ads/zzgqj:zzn	Lcom/google/android/gms/internal/ads/zzgpu;
    //   1577: aload 23
    //   1579: iload 8
    //   1581: ldc 125
    //   1583: iand
    //   1584: i2l
    //   1585: invokevirtual 898	com/google/android/gms/internal/ads/zzgpu:zza	(Ljava/lang/Object;J)Ljava/util/List;
    //   1588: invokeinterface 908 2 0
    //   1593: goto -511 -> 1082
    //   1596: aload_2
    //   1597: aload_0
    //   1598: getfield 83	com/google/android/gms/internal/ads/zzgqj:zzn	Lcom/google/android/gms/internal/ads/zzgpu;
    //   1601: aload 23
    //   1603: iload 8
    //   1605: ldc 125
    //   1607: iand
    //   1608: i2l
    //   1609: invokevirtual 898	com/google/android/gms/internal/ads/zzgpu:zza	(Ljava/lang/Object;J)Ljava/util/List;
    //   1612: invokeinterface 910 2 0
    //   1617: goto -535 -> 1082
    //   1620: aload_0
    //   1621: getfield 83	com/google/android/gms/internal/ads/zzgqj:zzn	Lcom/google/android/gms/internal/ads/zzgpu;
    //   1624: aload 23
    //   1626: iload 8
    //   1628: ldc 125
    //   1630: iand
    //   1631: i2l
    //   1632: invokevirtual 898	com/google/android/gms/internal/ads/zzgpu:zza	(Ljava/lang/Object;J)Ljava/util/List;
    //   1635: astore 19
    //   1637: aload_2
    //   1638: aload 19
    //   1640: invokeinterface 912 2 0
    //   1645: aload_0
    //   1646: iload 7
    //   1648: invokespecial 127	com/google/android/gms/internal/ads/zzgqj:zzB	(I)Lcom/google/android/gms/internal/ads/zzgpa;
    //   1651: astore 18
    //   1653: aload_1
    //   1654: iload 9
    //   1656: aload 19
    //   1658: aload 18
    //   1660: aload 16
    //   1662: aload 22
    //   1664: invokestatic 676	com/google/android/gms/internal/ads/zzgrb:zzA	(Ljava/lang/Object;ILjava/util/List;Lcom/google/android/gms/internal/ads/zzgpa;Ljava/lang/Object;Lcom/google/android/gms/internal/ads/zzgrq;)Ljava/lang/Object;
    //   1667: astore 18
    //   1669: aload 18
    //   1671: astore 15
    //   1673: goto +1443 -> 3116
    //   1676: aload_2
    //   1677: aload_0
    //   1678: getfield 83	com/google/android/gms/internal/ads/zzgqj:zzn	Lcom/google/android/gms/internal/ads/zzgpu;
    //   1681: aload 23
    //   1683: iload 8
    //   1685: ldc 125
    //   1687: iand
    //   1688: i2l
    //   1689: invokevirtual 898	com/google/android/gms/internal/ads/zzgpu:zza	(Ljava/lang/Object;J)Ljava/util/List;
    //   1692: invokeinterface 914 2 0
    //   1697: goto +1322 -> 3019
    //   1700: aload_2
    //   1701: aload_0
    //   1702: getfield 83	com/google/android/gms/internal/ads/zzgqj:zzn	Lcom/google/android/gms/internal/ads/zzgpu;
    //   1705: aload 23
    //   1707: iload 8
    //   1709: ldc 125
    //   1711: iand
    //   1712: i2l
    //   1713: invokevirtual 898	com/google/android/gms/internal/ads/zzgpu:zza	(Ljava/lang/Object;J)Ljava/util/List;
    //   1716: invokeinterface 916 2 0
    //   1721: goto +1298 -> 3019
    //   1724: aload_2
    //   1725: aload_0
    //   1726: getfield 83	com/google/android/gms/internal/ads/zzgqj:zzn	Lcom/google/android/gms/internal/ads/zzgpu;
    //   1729: aload 23
    //   1731: iload 8
    //   1733: ldc 125
    //   1735: iand
    //   1736: i2l
    //   1737: invokevirtual 898	com/google/android/gms/internal/ads/zzgpu:zza	(Ljava/lang/Object;J)Ljava/util/List;
    //   1740: invokeinterface 918 2 0
    //   1745: goto +1274 -> 3019
    //   1748: aload_2
    //   1749: aload_0
    //   1750: getfield 83	com/google/android/gms/internal/ads/zzgqj:zzn	Lcom/google/android/gms/internal/ads/zzgpu;
    //   1753: aload 23
    //   1755: iload 8
    //   1757: ldc 125
    //   1759: iand
    //   1760: i2l
    //   1761: invokevirtual 898	com/google/android/gms/internal/ads/zzgpu:zza	(Ljava/lang/Object;J)Ljava/util/List;
    //   1764: invokeinterface 920 2 0
    //   1769: goto +1250 -> 3019
    //   1772: aload_2
    //   1773: aload_0
    //   1774: getfield 83	com/google/android/gms/internal/ads/zzgqj:zzn	Lcom/google/android/gms/internal/ads/zzgpu;
    //   1777: aload 23
    //   1779: iload 8
    //   1781: ldc 125
    //   1783: iand
    //   1784: i2l
    //   1785: invokevirtual 898	com/google/android/gms/internal/ads/zzgpu:zza	(Ljava/lang/Object;J)Ljava/util/List;
    //   1788: invokeinterface 922 2 0
    //   1793: goto +1226 -> 3019
    //   1796: aload_2
    //   1797: aload_0
    //   1798: getfield 83	com/google/android/gms/internal/ads/zzgqj:zzn	Lcom/google/android/gms/internal/ads/zzgpu;
    //   1801: aload 23
    //   1803: iload 8
    //   1805: ldc 125
    //   1807: iand
    //   1808: i2l
    //   1809: invokevirtual 898	com/google/android/gms/internal/ads/zzgpu:zza	(Ljava/lang/Object;J)Ljava/util/List;
    //   1812: invokeinterface 924 2 0
    //   1817: goto +1202 -> 3019
    //   1820: aload_2
    //   1821: aload_0
    //   1822: getfield 83	com/google/android/gms/internal/ads/zzgqj:zzn	Lcom/google/android/gms/internal/ads/zzgpu;
    //   1825: aload 23
    //   1827: iload 8
    //   1829: ldc 125
    //   1831: iand
    //   1832: i2l
    //   1833: invokevirtual 898	com/google/android/gms/internal/ads/zzgpu:zza	(Ljava/lang/Object;J)Ljava/util/List;
    //   1836: invokeinterface 926 2 0
    //   1841: goto +1178 -> 3019
    //   1844: aload_2
    //   1845: aload_0
    //   1846: getfield 83	com/google/android/gms/internal/ads/zzgqj:zzn	Lcom/google/android/gms/internal/ads/zzgpu;
    //   1849: aload 23
    //   1851: iload 8
    //   1853: ldc 125
    //   1855: iand
    //   1856: i2l
    //   1857: invokevirtual 898	com/google/android/gms/internal/ads/zzgpu:zza	(Ljava/lang/Object;J)Ljava/util/List;
    //   1860: invokeinterface 928 2 0
    //   1865: goto +1154 -> 3019
    //   1868: aload_2
    //   1869: aload_0
    //   1870: getfield 83	com/google/android/gms/internal/ads/zzgqj:zzn	Lcom/google/android/gms/internal/ads/zzgpu;
    //   1873: aload 23
    //   1875: iload 8
    //   1877: ldc 125
    //   1879: iand
    //   1880: i2l
    //   1881: invokevirtual 898	com/google/android/gms/internal/ads/zzgpu:zza	(Ljava/lang/Object;J)Ljava/util/List;
    //   1884: invokeinterface 930 2 0
    //   1889: goto +1130 -> 3019
    //   1892: aload_2
    //   1893: aload_0
    //   1894: getfield 83	com/google/android/gms/internal/ads/zzgqj:zzn	Lcom/google/android/gms/internal/ads/zzgpu;
    //   1897: aload 23
    //   1899: iload 8
    //   1901: ldc 125
    //   1903: iand
    //   1904: i2l
    //   1905: invokevirtual 898	com/google/android/gms/internal/ads/zzgpu:zza	(Ljava/lang/Object;J)Ljava/util/List;
    //   1908: invokeinterface 904 2 0
    //   1913: goto +1106 -> 3019
    //   1916: aload_2
    //   1917: aload_0
    //   1918: getfield 83	com/google/android/gms/internal/ads/zzgqj:zzn	Lcom/google/android/gms/internal/ads/zzgpu;
    //   1921: aload 23
    //   1923: iload 8
    //   1925: ldc 125
    //   1927: iand
    //   1928: i2l
    //   1929: invokevirtual 898	com/google/android/gms/internal/ads/zzgpu:zza	(Ljava/lang/Object;J)Ljava/util/List;
    //   1932: invokeinterface 906 2 0
    //   1937: goto +1082 -> 3019
    //   1940: aload_2
    //   1941: aload_0
    //   1942: getfield 83	com/google/android/gms/internal/ads/zzgqj:zzn	Lcom/google/android/gms/internal/ads/zzgpu;
    //   1945: aload 23
    //   1947: iload 8
    //   1949: ldc 125
    //   1951: iand
    //   1952: i2l
    //   1953: invokevirtual 898	com/google/android/gms/internal/ads/zzgpu:zza	(Ljava/lang/Object;J)Ljava/util/List;
    //   1956: invokeinterface 908 2 0
    //   1961: goto +1058 -> 3019
    //   1964: aload_2
    //   1965: aload_0
    //   1966: getfield 83	com/google/android/gms/internal/ads/zzgqj:zzn	Lcom/google/android/gms/internal/ads/zzgpu;
    //   1969: aload 23
    //   1971: iload 8
    //   1973: ldc 125
    //   1975: iand
    //   1976: i2l
    //   1977: invokevirtual 898	com/google/android/gms/internal/ads/zzgpu:zza	(Ljava/lang/Object;J)Ljava/util/List;
    //   1980: invokeinterface 910 2 0
    //   1985: goto +1034 -> 3019
    //   1988: aload_0
    //   1989: getfield 83	com/google/android/gms/internal/ads/zzgqj:zzn	Lcom/google/android/gms/internal/ads/zzgpu;
    //   1992: aload 23
    //   1994: iload 8
    //   1996: ldc 125
    //   1998: iand
    //   1999: i2l
    //   2000: invokevirtual 898	com/google/android/gms/internal/ads/zzgpu:zza	(Ljava/lang/Object;J)Ljava/util/List;
    //   2003: astore 18
    //   2005: aload_2
    //   2006: aload 18
    //   2008: invokeinterface 912 2 0
    //   2013: aload_1
    //   2014: iload 9
    //   2016: aload 18
    //   2018: aload_0
    //   2019: iload 7
    //   2021: invokespecial 127	com/google/android/gms/internal/ads/zzgqj:zzB	(I)Lcom/google/android/gms/internal/ads/zzgpa;
    //   2024: aload 16
    //   2026: aload 22
    //   2028: invokestatic 676	com/google/android/gms/internal/ads/zzgrb:zzA	(Ljava/lang/Object;ILjava/util/List;Lcom/google/android/gms/internal/ads/zzgpa;Ljava/lang/Object;Lcom/google/android/gms/internal/ads/zzgrq;)Ljava/lang/Object;
    //   2031: astore 18
    //   2033: aload 18
    //   2035: astore 15
    //   2037: goto +1079 -> 3116
    //   2040: aload_2
    //   2041: aload_0
    //   2042: getfield 83	com/google/android/gms/internal/ads/zzgqj:zzn	Lcom/google/android/gms/internal/ads/zzgpu;
    //   2045: aload 23
    //   2047: iload 8
    //   2049: ldc 125
    //   2051: iand
    //   2052: i2l
    //   2053: invokevirtual 898	com/google/android/gms/internal/ads/zzgpu:zza	(Ljava/lang/Object;J)Ljava/util/List;
    //   2056: invokeinterface 914 2 0
    //   2061: goto +958 -> 3019
    //   2064: aload_2
    //   2065: aload_0
    //   2066: getfield 83	com/google/android/gms/internal/ads/zzgqj:zzn	Lcom/google/android/gms/internal/ads/zzgpu;
    //   2069: aload 23
    //   2071: iload 8
    //   2073: ldc 125
    //   2075: iand
    //   2076: i2l
    //   2077: invokevirtual 898	com/google/android/gms/internal/ads/zzgpu:zza	(Ljava/lang/Object;J)Ljava/util/List;
    //   2080: invokeinterface 932 2 0
    //   2085: goto +934 -> 3019
    //   2088: aload_0
    //   2089: iload 7
    //   2091: invokespecial 139	com/google/android/gms/internal/ads/zzgqj:zzC	(I)Lcom/google/android/gms/internal/ads/zzgqz;
    //   2094: astore 18
    //   2096: aload_2
    //   2097: aload_0
    //   2098: getfield 83	com/google/android/gms/internal/ads/zzgqj:zzn	Lcom/google/android/gms/internal/ads/zzgpu;
    //   2101: aload 23
    //   2103: iload 8
    //   2105: ldc 125
    //   2107: iand
    //   2108: i2l
    //   2109: invokevirtual 898	com/google/android/gms/internal/ads/zzgpu:zza	(Ljava/lang/Object;J)Ljava/util/List;
    //   2112: aload 18
    //   2114: aload 20
    //   2116: invokeinterface 934 4 0
    //   2121: goto +898 -> 3019
    //   2124: iload 8
    //   2126: invokestatic 263	com/google/android/gms/internal/ads/zzgqj:zzR	(I)Z
    //   2129: ifeq +33 -> 2162
    //   2132: aload_0
    //   2133: getfield 83	com/google/android/gms/internal/ads/zzgqj:zzn	Lcom/google/android/gms/internal/ads/zzgpu;
    //   2136: aload 23
    //   2138: iload 8
    //   2140: ldc 125
    //   2142: iand
    //   2143: i2l
    //   2144: invokevirtual 898	com/google/android/gms/internal/ads/zzgpu:zza	(Ljava/lang/Object;J)Ljava/util/List;
    //   2147: astore 18
    //   2149: aload_2
    //   2150: checkcast 936	com/google/android/gms/internal/ads/zzgnx
    //   2153: aload 18
    //   2155: iconst_1
    //   2156: invokevirtual 939	com/google/android/gms/internal/ads/zzgnx:zzK	(Ljava/util/List;Z)V
    //   2159: goto +860 -> 3019
    //   2162: aload_0
    //   2163: getfield 83	com/google/android/gms/internal/ads/zzgqj:zzn	Lcom/google/android/gms/internal/ads/zzgpu;
    //   2166: aload 23
    //   2168: iload 8
    //   2170: ldc 125
    //   2172: iand
    //   2173: i2l
    //   2174: invokevirtual 898	com/google/android/gms/internal/ads/zzgpu:zza	(Ljava/lang/Object;J)Ljava/util/List;
    //   2177: astore 18
    //   2179: aload_2
    //   2180: checkcast 936	com/google/android/gms/internal/ads/zzgnx
    //   2183: aload 18
    //   2185: iconst_0
    //   2186: invokevirtual 939	com/google/android/gms/internal/ads/zzgnx:zzK	(Ljava/util/List;Z)V
    //   2189: goto +830 -> 3019
    //   2192: aload_2
    //   2193: aload_0
    //   2194: getfield 83	com/google/android/gms/internal/ads/zzgqj:zzn	Lcom/google/android/gms/internal/ads/zzgpu;
    //   2197: aload 23
    //   2199: iload 8
    //   2201: ldc 125
    //   2203: iand
    //   2204: i2l
    //   2205: invokevirtual 898	com/google/android/gms/internal/ads/zzgpu:zza	(Ljava/lang/Object;J)Ljava/util/List;
    //   2208: invokeinterface 916 2 0
    //   2213: goto +806 -> 3019
    //   2216: aload_2
    //   2217: aload_0
    //   2218: getfield 83	com/google/android/gms/internal/ads/zzgqj:zzn	Lcom/google/android/gms/internal/ads/zzgpu;
    //   2221: aload 23
    //   2223: iload 8
    //   2225: ldc 125
    //   2227: iand
    //   2228: i2l
    //   2229: invokevirtual 898	com/google/android/gms/internal/ads/zzgpu:zza	(Ljava/lang/Object;J)Ljava/util/List;
    //   2232: invokeinterface 918 2 0
    //   2237: goto +782 -> 3019
    //   2240: aload_2
    //   2241: aload_0
    //   2242: getfield 83	com/google/android/gms/internal/ads/zzgqj:zzn	Lcom/google/android/gms/internal/ads/zzgpu;
    //   2245: aload 23
    //   2247: iload 8
    //   2249: ldc 125
    //   2251: iand
    //   2252: i2l
    //   2253: invokevirtual 898	com/google/android/gms/internal/ads/zzgpu:zza	(Ljava/lang/Object;J)Ljava/util/List;
    //   2256: invokeinterface 920 2 0
    //   2261: goto +758 -> 3019
    //   2264: aload_2
    //   2265: aload_0
    //   2266: getfield 83	com/google/android/gms/internal/ads/zzgqj:zzn	Lcom/google/android/gms/internal/ads/zzgpu;
    //   2269: aload 23
    //   2271: iload 8
    //   2273: ldc 125
    //   2275: iand
    //   2276: i2l
    //   2277: invokevirtual 898	com/google/android/gms/internal/ads/zzgpu:zza	(Ljava/lang/Object;J)Ljava/util/List;
    //   2280: invokeinterface 922 2 0
    //   2285: goto +734 -> 3019
    //   2288: aload_2
    //   2289: aload_0
    //   2290: getfield 83	com/google/android/gms/internal/ads/zzgqj:zzn	Lcom/google/android/gms/internal/ads/zzgpu;
    //   2293: aload 23
    //   2295: iload 8
    //   2297: ldc 125
    //   2299: iand
    //   2300: i2l
    //   2301: invokevirtual 898	com/google/android/gms/internal/ads/zzgpu:zza	(Ljava/lang/Object;J)Ljava/util/List;
    //   2304: invokeinterface 924 2 0
    //   2309: goto +710 -> 3019
    //   2312: aload_2
    //   2313: aload_0
    //   2314: getfield 83	com/google/android/gms/internal/ads/zzgqj:zzn	Lcom/google/android/gms/internal/ads/zzgpu;
    //   2317: aload 23
    //   2319: iload 8
    //   2321: ldc 125
    //   2323: iand
    //   2324: i2l
    //   2325: invokevirtual 898	com/google/android/gms/internal/ads/zzgpu:zza	(Ljava/lang/Object;J)Ljava/util/List;
    //   2328: invokeinterface 926 2 0
    //   2333: goto +686 -> 3019
    //   2336: aload_2
    //   2337: aload_0
    //   2338: getfield 83	com/google/android/gms/internal/ads/zzgqj:zzn	Lcom/google/android/gms/internal/ads/zzgpu;
    //   2341: aload 23
    //   2343: iload 8
    //   2345: ldc 125
    //   2347: iand
    //   2348: i2l
    //   2349: invokevirtual 898	com/google/android/gms/internal/ads/zzgpu:zza	(Ljava/lang/Object;J)Ljava/util/List;
    //   2352: invokeinterface 928 2 0
    //   2357: goto +662 -> 3019
    //   2360: aload_2
    //   2361: aload_0
    //   2362: getfield 83	com/google/android/gms/internal/ads/zzgqj:zzn	Lcom/google/android/gms/internal/ads/zzgpu;
    //   2365: aload 23
    //   2367: iload 8
    //   2369: ldc 125
    //   2371: iand
    //   2372: i2l
    //   2373: invokevirtual 898	com/google/android/gms/internal/ads/zzgpu:zza	(Ljava/lang/Object;J)Ljava/util/List;
    //   2376: invokeinterface 930 2 0
    //   2381: goto +638 -> 3019
    //   2384: aload_0
    //   2385: aload 23
    //   2387: iload 7
    //   2389: invokespecial 749	com/google/android/gms/internal/ads/zzgqj:zzF	(Ljava/lang/Object;I)Ljava/lang/Object;
    //   2392: checkcast 425	com/google/android/gms/internal/ads/zzgqg
    //   2395: astore 18
    //   2397: aload_2
    //   2398: aload 18
    //   2400: aload_0
    //   2401: iload 7
    //   2403: invokespecial 139	com/google/android/gms/internal/ads/zzgqj:zzC	(I)Lcom/google/android/gms/internal/ads/zzgqz;
    //   2406: aload 20
    //   2408: invokeinterface 860 4 0
    //   2413: aload_0
    //   2414: aload 23
    //   2416: iload 7
    //   2418: aload 18
    //   2420: invokespecial 751	com/google/android/gms/internal/ads/zzgqj:zzO	(Ljava/lang/Object;ILjava/lang/Object;)V
    //   2423: goto +596 -> 3019
    //   2426: aload_2
    //   2427: invokeinterface 862 1 0
    //   2432: lstore 12
    //   2434: aload 23
    //   2436: iload 8
    //   2438: ldc 125
    //   2440: iand
    //   2441: i2l
    //   2442: lload 12
    //   2444: invokestatic 832	com/google/android/gms/internal/ads/zzgsa:zzu	(Ljava/lang/Object;JJ)V
    //   2447: aload_0
    //   2448: aload 23
    //   2450: iload 7
    //   2452: invokespecial 239	com/google/android/gms/internal/ads/zzgqj:zzM	(Ljava/lang/Object;I)V
    //   2455: goto +564 -> 3019
    //   2458: aload_2
    //   2459: invokeinterface 864 1 0
    //   2464: istore 9
    //   2466: aload 23
    //   2468: iload 8
    //   2470: ldc 125
    //   2472: iand
    //   2473: i2l
    //   2474: iload 9
    //   2476: invokestatic 289	com/google/android/gms/internal/ads/zzgsa:zzt	(Ljava/lang/Object;JI)V
    //   2479: aload_0
    //   2480: aload 23
    //   2482: iload 7
    //   2484: invokespecial 239	com/google/android/gms/internal/ads/zzgqj:zzM	(Ljava/lang/Object;I)V
    //   2487: goto +532 -> 3019
    //   2490: aload_2
    //   2491: invokeinterface 866 1 0
    //   2496: lstore 12
    //   2498: aload 23
    //   2500: iload 8
    //   2502: ldc 125
    //   2504: iand
    //   2505: i2l
    //   2506: lload 12
    //   2508: invokestatic 832	com/google/android/gms/internal/ads/zzgsa:zzu	(Ljava/lang/Object;JJ)V
    //   2511: aload_0
    //   2512: aload 23
    //   2514: iload 7
    //   2516: invokespecial 239	com/google/android/gms/internal/ads/zzgqj:zzM	(Ljava/lang/Object;I)V
    //   2519: goto +500 -> 3019
    //   2522: aload_2
    //   2523: invokeinterface 868 1 0
    //   2528: istore 9
    //   2530: aload 23
    //   2532: iload 8
    //   2534: ldc 125
    //   2536: iand
    //   2537: i2l
    //   2538: iload 9
    //   2540: invokestatic 289	com/google/android/gms/internal/ads/zzgsa:zzt	(Ljava/lang/Object;JI)V
    //   2543: aload_0
    //   2544: aload 23
    //   2546: iload 7
    //   2548: invokespecial 239	com/google/android/gms/internal/ads/zzgqj:zzM	(Ljava/lang/Object;I)V
    //   2551: goto +468 -> 3019
    //   2554: aload_2
    //   2555: invokeinterface 870 1 0
    //   2560: istore 10
    //   2562: aload_0
    //   2563: iload 7
    //   2565: invokespecial 127	com/google/android/gms/internal/ads/zzgqj:zzB	(I)Lcom/google/android/gms/internal/ads/zzgpa;
    //   2568: astore 18
    //   2570: aload 18
    //   2572: ifnull +40 -> 2612
    //   2575: aload 18
    //   2577: iload 10
    //   2579: invokeinterface 584 2 0
    //   2584: ifeq +6 -> 2590
    //   2587: goto +25 -> 2612
    //   2590: aload 23
    //   2592: iload 9
    //   2594: iload 10
    //   2596: aload 16
    //   2598: aload 22
    //   2600: invokestatic 873	com/google/android/gms/internal/ads/zzgrb:zzB	(Ljava/lang/Object;IILjava/lang/Object;Lcom/google/android/gms/internal/ads/zzgrq;)Ljava/lang/Object;
    //   2603: astore 18
    //   2605: aload 18
    //   2607: astore 15
    //   2609: goto +507 -> 3116
    //   2612: aload 23
    //   2614: iload 8
    //   2616: ldc 125
    //   2618: iand
    //   2619: i2l
    //   2620: iload 10
    //   2622: invokestatic 289	com/google/android/gms/internal/ads/zzgsa:zzt	(Ljava/lang/Object;JI)V
    //   2625: aload_0
    //   2626: aload 23
    //   2628: iload 7
    //   2630: invokespecial 239	com/google/android/gms/internal/ads/zzgqj:zzM	(Ljava/lang/Object;I)V
    //   2633: goto +386 -> 3019
    //   2636: aload_2
    //   2637: invokeinterface 875 1 0
    //   2642: istore 9
    //   2644: aload 23
    //   2646: iload 8
    //   2648: ldc 125
    //   2650: iand
    //   2651: i2l
    //   2652: iload 9
    //   2654: invokestatic 289	com/google/android/gms/internal/ads/zzgsa:zzt	(Ljava/lang/Object;JI)V
    //   2657: aload_0
    //   2658: aload 23
    //   2660: iload 7
    //   2662: invokespecial 239	com/google/android/gms/internal/ads/zzgqj:zzM	(Ljava/lang/Object;I)V
    //   2665: goto +354 -> 3019
    //   2668: aload_2
    //   2669: invokeinterface 276 1 0
    //   2674: astore 18
    //   2676: aload 23
    //   2678: iload 8
    //   2680: ldc 125
    //   2682: iand
    //   2683: i2l
    //   2684: aload 18
    //   2686: invokestatic 271	com/google/android/gms/internal/ads/zzgsa:zzv	(Ljava/lang/Object;JLjava/lang/Object;)V
    //   2689: aload_0
    //   2690: aload 23
    //   2692: iload 7
    //   2694: invokespecial 239	com/google/android/gms/internal/ads/zzgqj:zzM	(Ljava/lang/Object;I)V
    //   2697: goto +322 -> 3019
    //   2700: aload_0
    //   2701: aload 23
    //   2703: iload 7
    //   2705: invokespecial 749	com/google/android/gms/internal/ads/zzgqj:zzF	(Ljava/lang/Object;I)Ljava/lang/Object;
    //   2708: checkcast 425	com/google/android/gms/internal/ads/zzgqg
    //   2711: astore 18
    //   2713: aload_2
    //   2714: aload 18
    //   2716: aload_0
    //   2717: iload 7
    //   2719: invokespecial 139	com/google/android/gms/internal/ads/zzgqj:zzC	(I)Lcom/google/android/gms/internal/ads/zzgqz;
    //   2722: aload 20
    //   2724: invokeinterface 877 4 0
    //   2729: aload_0
    //   2730: aload 23
    //   2732: iload 7
    //   2734: aload 18
    //   2736: invokespecial 751	com/google/android/gms/internal/ads/zzgqj:zzO	(Ljava/lang/Object;ILjava/lang/Object;)V
    //   2739: goto +280 -> 3019
    //   2742: aload_0
    //   2743: aload 23
    //   2745: iload 8
    //   2747: aload_2
    //   2748: invokespecial 879	com/google/android/gms/internal/ads/zzgqj:zzL	(Ljava/lang/Object;ILcom/google/android/gms/internal/ads/zzgqr;)V
    //   2751: aload_0
    //   2752: aload 23
    //   2754: iload 7
    //   2756: invokespecial 239	com/google/android/gms/internal/ads/zzgqj:zzM	(Ljava/lang/Object;I)V
    //   2759: goto +260 -> 3019
    //   2762: astore_2
    //   2763: goto +498 -> 3261
    //   2766: aload_2
    //   2767: invokeinterface 881 1 0
    //   2772: istore 11
    //   2774: aload 23
    //   2776: iload 8
    //   2778: ldc 125
    //   2780: iand
    //   2781: i2l
    //   2782: iload 11
    //   2784: invokestatic 762	com/google/android/gms/internal/ads/zzgsa:zzp	(Ljava/lang/Object;JZ)V
    //   2787: aload_0
    //   2788: aload 23
    //   2790: iload 7
    //   2792: invokespecial 239	com/google/android/gms/internal/ads/zzgqj:zzM	(Ljava/lang/Object;I)V
    //   2795: goto +224 -> 3019
    //   2798: aload_2
    //   2799: invokeinterface 883 1 0
    //   2804: istore 9
    //   2806: aload 23
    //   2808: iload 8
    //   2810: ldc 125
    //   2812: iand
    //   2813: i2l
    //   2814: iload 9
    //   2816: invokestatic 289	com/google/android/gms/internal/ads/zzgsa:zzt	(Ljava/lang/Object;JI)V
    //   2819: aload_0
    //   2820: aload 23
    //   2822: iload 7
    //   2824: invokespecial 239	com/google/android/gms/internal/ads/zzgqj:zzM	(Ljava/lang/Object;I)V
    //   2827: goto +192 -> 3019
    //   2830: aload_2
    //   2831: invokeinterface 885 1 0
    //   2836: lstore 12
    //   2838: aload 23
    //   2840: iload 8
    //   2842: ldc 125
    //   2844: iand
    //   2845: i2l
    //   2846: lload 12
    //   2848: invokestatic 832	com/google/android/gms/internal/ads/zzgsa:zzu	(Ljava/lang/Object;JJ)V
    //   2851: aload_0
    //   2852: aload 23
    //   2854: iload 7
    //   2856: invokespecial 239	com/google/android/gms/internal/ads/zzgqj:zzM	(Ljava/lang/Object;I)V
    //   2859: goto +160 -> 3019
    //   2862: aload_2
    //   2863: invokeinterface 887 1 0
    //   2868: istore 9
    //   2870: aload 23
    //   2872: iload 8
    //   2874: ldc 125
    //   2876: iand
    //   2877: i2l
    //   2878: iload 9
    //   2880: invokestatic 289	com/google/android/gms/internal/ads/zzgsa:zzt	(Ljava/lang/Object;JI)V
    //   2883: aload_0
    //   2884: aload 23
    //   2886: iload 7
    //   2888: invokespecial 239	com/google/android/gms/internal/ads/zzgqj:zzM	(Ljava/lang/Object;I)V
    //   2891: goto +128 -> 3019
    //   2894: aload_2
    //   2895: invokeinterface 889 1 0
    //   2900: lstore 12
    //   2902: aload 23
    //   2904: iload 8
    //   2906: ldc 125
    //   2908: iand
    //   2909: i2l
    //   2910: lload 12
    //   2912: invokestatic 832	com/google/android/gms/internal/ads/zzgsa:zzu	(Ljava/lang/Object;JJ)V
    //   2915: aload_0
    //   2916: aload 23
    //   2918: iload 7
    //   2920: invokespecial 239	com/google/android/gms/internal/ads/zzgqj:zzM	(Ljava/lang/Object;I)V
    //   2923: goto +96 -> 3019
    //   2926: aload_2
    //   2927: invokeinterface 891 1 0
    //   2932: lstore 12
    //   2934: aload 23
    //   2936: iload 8
    //   2938: ldc 125
    //   2940: iand
    //   2941: i2l
    //   2942: lload 12
    //   2944: invokestatic 832	com/google/android/gms/internal/ads/zzgsa:zzu	(Ljava/lang/Object;JJ)V
    //   2947: aload_0
    //   2948: aload 23
    //   2950: iload 7
    //   2952: invokespecial 239	com/google/android/gms/internal/ads/zzgqj:zzM	(Ljava/lang/Object;I)V
    //   2955: goto +64 -> 3019
    //   2958: aload_2
    //   2959: invokeinterface 893 1 0
    //   2964: fstore 6
    //   2966: aload 23
    //   2968: iload 8
    //   2970: ldc 125
    //   2972: iand
    //   2973: i2l
    //   2974: fload 6
    //   2976: invokestatic 765	com/google/android/gms/internal/ads/zzgsa:zzs	(Ljava/lang/Object;JF)V
    //   2979: aload_0
    //   2980: aload 23
    //   2982: iload 7
    //   2984: invokespecial 239	com/google/android/gms/internal/ads/zzgqj:zzM	(Ljava/lang/Object;I)V
    //   2987: goto +32 -> 3019
    //   2990: aload_2
    //   2991: invokeinterface 895 1 0
    //   2996: dstore 4
    //   2998: aload 23
    //   3000: iload 8
    //   3002: ldc 125
    //   3004: iand
    //   3005: i2l
    //   3006: dload 4
    //   3008: invokestatic 768	com/google/android/gms/internal/ads/zzgsa:zzr	(Ljava/lang/Object;JD)V
    //   3011: aload_0
    //   3012: aload 23
    //   3014: iload 7
    //   3016: invokespecial 239	com/google/android/gms/internal/ads/zzgqj:zzM	(Ljava/lang/Object;I)V
    //   3019: aload 17
    //   3021: astore 15
    //   3023: aload 16
    //   3025: astore 15
    //   3027: aload 15
    //   3029: astore 16
    //   3031: aload 22
    //   3033: astore 15
    //   3035: goto -3002 -> 33
    //   3038: aload 16
    //   3040: astore 18
    //   3042: aload 22
    //   3044: aload 16
    //   3046: aload_2
    //   3047: invokevirtual 857	com/google/android/gms/internal/ads/zzgrq:zzp	(Ljava/lang/Object;Lcom/google/android/gms/internal/ads/zzgqr;)Z
    //   3050: istore 11
    //   3052: aload 16
    //   3054: astore 15
    //   3056: iload 11
    //   3058: ifne +58 -> 3116
    //   3061: aload_0
    //   3062: getfield 77	com/google/android/gms/internal/ads/zzgqj:zzl	I
    //   3065: istore 7
    //   3067: iload 7
    //   3069: aload_0
    //   3070: getfield 79	com/google/android/gms/internal/ads/zzgqj:zzm	I
    //   3073: if_icmpge +28 -> 3101
    //   3076: aload_0
    //   3077: aload_1
    //   3078: aload_0
    //   3079: getfield 75	com/google/android/gms/internal/ads/zzgqj:zzk	[I
    //   3082: iload 7
    //   3084: iaload
    //   3085: aload 16
    //   3087: aload 22
    //   3089: aload_1
    //   3090: invokespecial 791	com/google/android/gms/internal/ads/zzgqj:zzD	(Ljava/lang/Object;ILjava/lang/Object;Lcom/google/android/gms/internal/ads/zzgrq;Ljava/lang/Object;)Ljava/lang/Object;
    //   3093: astore 16
    //   3095: iinc 7 1
    //   3098: goto -31 -> 3067
    //   3101: aload 16
    //   3103: ifnull +140 -> 3243
    //   3106: aload 22
    //   3108: aload 23
    //   3110: aload 16
    //   3112: invokevirtual 841	com/google/android/gms/internal/ads/zzgrq:zzn	(Ljava/lang/Object;Ljava/lang/Object;)V
    //   3115: return
    //   3116: aload 17
    //   3118: astore 16
    //   3120: goto -93 -> 3027
    //   3123: astore_2
    //   3124: goto +147 -> 3271
    //   3127: astore 18
    //   3129: aload 16
    //   3131: astore 19
    //   3133: aload 19
    //   3135: astore 18
    //   3137: aload 22
    //   3139: aload_2
    //   3140: invokevirtual 852	com/google/android/gms/internal/ads/zzgrq:zzq	(Lcom/google/android/gms/internal/ads/zzgqr;)Z
    //   3143: pop
    //   3144: aload 19
    //   3146: astore 16
    //   3148: aload 19
    //   3150: ifnonnull +16 -> 3166
    //   3153: aload 19
    //   3155: astore 18
    //   3157: aload 22
    //   3159: aload 23
    //   3161: invokevirtual 854	com/google/android/gms/internal/ads/zzgrq:zzc	(Ljava/lang/Object;)Ljava/lang/Object;
    //   3164: astore 16
    //   3166: aload 16
    //   3168: astore 18
    //   3170: aload 22
    //   3172: aload 16
    //   3174: aload_2
    //   3175: invokevirtual 857	com/google/android/gms/internal/ads/zzgrq:zzp	(Ljava/lang/Object;Lcom/google/android/gms/internal/ads/zzgqr;)Z
    //   3178: istore 11
    //   3180: aload 16
    //   3182: astore 15
    //   3184: iload 11
    //   3186: ifne -70 -> 3116
    //   3189: aload_0
    //   3190: getfield 77	com/google/android/gms/internal/ads/zzgqj:zzl	I
    //   3193: istore 7
    //   3195: iload 7
    //   3197: aload_0
    //   3198: getfield 79	com/google/android/gms/internal/ads/zzgqj:zzm	I
    //   3201: if_icmpge +28 -> 3229
    //   3204: aload_0
    //   3205: aload_1
    //   3206: aload_0
    //   3207: getfield 75	com/google/android/gms/internal/ads/zzgqj:zzk	[I
    //   3210: iload 7
    //   3212: iaload
    //   3213: aload 16
    //   3215: aload 22
    //   3217: aload_1
    //   3218: invokespecial 791	com/google/android/gms/internal/ads/zzgqj:zzD	(Ljava/lang/Object;ILjava/lang/Object;Lcom/google/android/gms/internal/ads/zzgrq;Ljava/lang/Object;)Ljava/lang/Object;
    //   3221: astore 16
    //   3223: iinc 7 1
    //   3226: goto -31 -> 3195
    //   3229: aload 16
    //   3231: ifnull +12 -> 3243
    //   3234: aload 22
    //   3236: aload 23
    //   3238: aload 16
    //   3240: invokevirtual 841	com/google/android/gms/internal/ads/zzgrq:zzn	(Ljava/lang/Object;Ljava/lang/Object;)V
    //   3243: return
    //   3244: astore_2
    //   3245: aload 15
    //   3247: astore_3
    //   3248: aload 14
    //   3250: astore_3
    //   3251: goto +10 -> 3261
    //   3254: astore_2
    //   3255: aload 15
    //   3257: astore_3
    //   3258: aload 14
    //   3260: astore_3
    //   3261: aload 15
    //   3263: astore_3
    //   3264: aload 14
    //   3266: astore_3
    //   3267: aload 16
    //   3269: astore 18
    //   3271: aload_0
    //   3272: getfield 77	com/google/android/gms/internal/ads/zzgqj:zzl	I
    //   3275: istore 7
    //   3277: iload 7
    //   3279: aload_0
    //   3280: getfield 79	com/google/android/gms/internal/ads/zzgqj:zzm	I
    //   3283: if_icmpge +28 -> 3311
    //   3286: aload_0
    //   3287: aload_1
    //   3288: aload_0
    //   3289: getfield 75	com/google/android/gms/internal/ads/zzgqj:zzk	[I
    //   3292: iload 7
    //   3294: iaload
    //   3295: aload 18
    //   3297: aload 15
    //   3299: aload_1
    //   3300: invokespecial 791	com/google/android/gms/internal/ads/zzgqj:zzD	(Ljava/lang/Object;ILjava/lang/Object;Lcom/google/android/gms/internal/ads/zzgrq;Ljava/lang/Object;)Ljava/lang/Object;
    //   3303: astore 18
    //   3305: iinc 7 1
    //   3308: goto -31 -> 3277
    //   3311: aload 18
    //   3313: ifnull +12 -> 3325
    //   3316: aload 15
    //   3318: aload 14
    //   3320: aload 18
    //   3322: invokevirtual 841	com/google/android/gms/internal/ads/zzgrq:zzn	(Ljava/lang/Object;Ljava/lang/Object;)V
    //   3325: aload_2
    //   3326: athrow
    //   3327: astore 18
    //   3329: goto -200 -> 3129
    //   3332: astore 18
    //   3334: aload 16
    //   3336: astore 19
    //   3338: goto -205 -> 3133
    // Local variable table:
    //   start	length	slot	name	signature
    //   0	3341	0	this	zzgqj
    //   0	3341	1	paramObject	Object
    //   0	3341	2	paramzzgqr	zzgqr
    //   0	3341	3	paramzzgoi	zzgoi
    //   1350	1657	4	d	double
    //   1313	1662	6	f	float
    //   47	3259	7	i	int
    //   342	2663	8	j	int
    //   39	2840	9	k	int
    //   349	2272	10	m	int
    //   238	2947	11	bool	boolean
    //   717	2226	12	l	long
    //   1	3318	14	localObject1	Object
    //   19	3298	15	localObject2	Object
    //   28	3307	16	localObject3	Object
    //   25	3092	17	localzzgoj	zzgoj
    //   152	2889	18	localObject4	Object
    //   3127	1	18	localzzgph1	zzgph
    //   3135	186	18	localObject5	Object
    //   3327	1	18	localzzgph2	zzgph
    //   3332	1	18	localzzgph3	zzgph
    //   125	3212	19	localObject6	Object
    //   4	2719	20	localzzgoi	zzgoi
    //   31	158	21	localObject7	Object
    //   203	3032	22	localObject8	Object
    //   334	2903	23	localObject9	Object
    //   1387	93	24	localObject10	Object
    // Exception table:
    //   from	to	target	type
    //   230	240	304	finally
    //   168	186	308	finally
    //   205	212	308	finally
    //   221	230	308	finally
    //   117	124	318	finally
    //   130	145	318	finally
    //   649	658	2762	finally
    //   1653	1669	2762	finally
    //   1676	1697	2762	finally
    //   1700	1721	2762	finally
    //   1724	1745	2762	finally
    //   1748	1769	2762	finally
    //   1772	1793	2762	finally
    //   1796	1817	2762	finally
    //   1820	1841	2762	finally
    //   1844	1865	2762	finally
    //   1868	1889	2762	finally
    //   1892	1913	2762	finally
    //   1916	1937	2762	finally
    //   1940	1961	2762	finally
    //   1964	1985	2762	finally
    //   1988	2033	2762	finally
    //   2040	2061	2762	finally
    //   2064	2085	2762	finally
    //   2088	2121	2762	finally
    //   2124	2159	2762	finally
    //   2162	2189	2762	finally
    //   2192	2213	2762	finally
    //   2216	2237	2762	finally
    //   2240	2261	2762	finally
    //   2264	2285	2762	finally
    //   2288	2309	2762	finally
    //   2312	2333	2762	finally
    //   2336	2357	2762	finally
    //   2360	2381	2762	finally
    //   2384	2423	2762	finally
    //   2426	2455	2762	finally
    //   2458	2487	2762	finally
    //   2490	2519	2762	finally
    //   2522	2551	2762	finally
    //   2554	2570	2762	finally
    //   2575	2587	2762	finally
    //   2590	2605	2762	finally
    //   2612	2633	2762	finally
    //   2636	2665	2762	finally
    //   2668	2697	2762	finally
    //   2700	2739	2762	finally
    //   2742	2759	2762	finally
    //   2766	2795	2762	finally
    //   2798	2827	2762	finally
    //   2830	2859	2762	finally
    //   2862	2891	2762	finally
    //   2894	2923	2762	finally
    //   2926	2955	2762	finally
    //   2958	2987	2762	finally
    //   2990	3019	2762	finally
    //   3042	3052	3123	finally
    //   3137	3144	3123	finally
    //   3157	3166	3123	finally
    //   3170	3180	3123	finally
    //   344	351	3127	com/google/android/gms/internal/ads/zzgph
    //   665	708	3127	com/google/android/gms/internal/ads/zzgph
    //   711	745	3127	com/google/android/gms/internal/ads/zzgph
    //   748	782	3127	com/google/android/gms/internal/ads/zzgph
    //   785	819	3127	com/google/android/gms/internal/ads/zzgph
    //   822	856	3127	com/google/android/gms/internal/ads/zzgph
    //   859	875	3127	com/google/android/gms/internal/ads/zzgph
    //   880	892	3127	com/google/android/gms/internal/ads/zzgph
    //   895	910	3127	com/google/android/gms/internal/ads/zzgph
    //   917	943	3127	com/google/android/gms/internal/ads/zzgph
    //   946	980	3127	com/google/android/gms/internal/ads/zzgph
    //   983	1014	3127	com/google/android/gms/internal/ads/zzgph
    //   1017	1060	3127	com/google/android/gms/internal/ads/zzgph
    //   1063	1082	3127	com/google/android/gms/internal/ads/zzgph
    //   1085	1119	3127	com/google/android/gms/internal/ads/zzgph
    //   1122	1156	3127	com/google/android/gms/internal/ads/zzgph
    //   1159	1193	3127	com/google/android/gms/internal/ads/zzgph
    //   1196	1230	3127	com/google/android/gms/internal/ads/zzgph
    //   1233	1267	3127	com/google/android/gms/internal/ads/zzgph
    //   1270	1304	3127	com/google/android/gms/internal/ads/zzgph
    //   1307	1341	3127	com/google/android/gms/internal/ads/zzgph
    //   1344	1378	3127	com/google/android/gms/internal/ads/zzgph
    //   1381	1410	3127	com/google/android/gms/internal/ads/zzgph
    //   1419	1452	3127	com/google/android/gms/internal/ads/zzgph
    //   1455	1472	3127	com/google/android/gms/internal/ads/zzgph
    //   1472	1488	3127	com/google/android/gms/internal/ads/zzgph
    //   1488	1521	3127	com/google/android/gms/internal/ads/zzgph
    //   1524	1545	3127	com/google/android/gms/internal/ads/zzgph
    //   1548	1569	3127	com/google/android/gms/internal/ads/zzgph
    //   1572	1593	3127	com/google/android/gms/internal/ads/zzgph
    //   1596	1617	3127	com/google/android/gms/internal/ads/zzgph
    //   1620	1653	3127	com/google/android/gms/internal/ads/zzgph
    //   336	344	3244	finally
    //   344	351	3244	finally
    //   665	708	3244	finally
    //   711	745	3244	finally
    //   748	782	3244	finally
    //   785	819	3244	finally
    //   822	856	3244	finally
    //   859	875	3244	finally
    //   880	892	3244	finally
    //   895	910	3244	finally
    //   917	943	3244	finally
    //   946	980	3244	finally
    //   983	1014	3244	finally
    //   1017	1060	3244	finally
    //   1063	1082	3244	finally
    //   1085	1119	3244	finally
    //   1122	1156	3244	finally
    //   1159	1193	3244	finally
    //   1196	1230	3244	finally
    //   1233	1267	3244	finally
    //   1270	1304	3244	finally
    //   1307	1341	3244	finally
    //   1344	1378	3244	finally
    //   1381	1410	3244	finally
    //   1419	1452	3244	finally
    //   1455	1472	3244	finally
    //   1472	1488	3244	finally
    //   1488	1521	3244	finally
    //   1524	1545	3244	finally
    //   1548	1569	3244	finally
    //   1572	1593	3244	finally
    //   1596	1617	3244	finally
    //   1620	1653	3244	finally
    //   33	49	3254	finally
    //   159	168	3254	finally
    //   649	658	3327	com/google/android/gms/internal/ads/zzgph
    //   1653	1669	3327	com/google/android/gms/internal/ads/zzgph
    //   1676	1697	3327	com/google/android/gms/internal/ads/zzgph
    //   1700	1721	3327	com/google/android/gms/internal/ads/zzgph
    //   1724	1745	3327	com/google/android/gms/internal/ads/zzgph
    //   1748	1769	3327	com/google/android/gms/internal/ads/zzgph
    //   1772	1793	3327	com/google/android/gms/internal/ads/zzgph
    //   1796	1817	3327	com/google/android/gms/internal/ads/zzgph
    //   1820	1841	3327	com/google/android/gms/internal/ads/zzgph
    //   1844	1865	3327	com/google/android/gms/internal/ads/zzgph
    //   1868	1889	3327	com/google/android/gms/internal/ads/zzgph
    //   1892	1913	3327	com/google/android/gms/internal/ads/zzgph
    //   1916	1937	3327	com/google/android/gms/internal/ads/zzgph
    //   1940	1961	3327	com/google/android/gms/internal/ads/zzgph
    //   1964	1985	3327	com/google/android/gms/internal/ads/zzgph
    //   1988	2033	3327	com/google/android/gms/internal/ads/zzgph
    //   2040	2061	3327	com/google/android/gms/internal/ads/zzgph
    //   2064	2085	3327	com/google/android/gms/internal/ads/zzgph
    //   2088	2121	3327	com/google/android/gms/internal/ads/zzgph
    //   2124	2159	3327	com/google/android/gms/internal/ads/zzgph
    //   2162	2189	3327	com/google/android/gms/internal/ads/zzgph
    //   2192	2213	3327	com/google/android/gms/internal/ads/zzgph
    //   2216	2237	3327	com/google/android/gms/internal/ads/zzgph
    //   2240	2261	3327	com/google/android/gms/internal/ads/zzgph
    //   2264	2285	3327	com/google/android/gms/internal/ads/zzgph
    //   2288	2309	3327	com/google/android/gms/internal/ads/zzgph
    //   2312	2333	3327	com/google/android/gms/internal/ads/zzgph
    //   2336	2357	3327	com/google/android/gms/internal/ads/zzgph
    //   2360	2381	3327	com/google/android/gms/internal/ads/zzgph
    //   2384	2423	3327	com/google/android/gms/internal/ads/zzgph
    //   2426	2455	3327	com/google/android/gms/internal/ads/zzgph
    //   2458	2487	3327	com/google/android/gms/internal/ads/zzgph
    //   2490	2519	3327	com/google/android/gms/internal/ads/zzgph
    //   2522	2551	3327	com/google/android/gms/internal/ads/zzgph
    //   2554	2570	3327	com/google/android/gms/internal/ads/zzgph
    //   2575	2587	3327	com/google/android/gms/internal/ads/zzgph
    //   2590	2605	3327	com/google/android/gms/internal/ads/zzgph
    //   2612	2633	3327	com/google/android/gms/internal/ads/zzgph
    //   2636	2665	3327	com/google/android/gms/internal/ads/zzgph
    //   2668	2697	3327	com/google/android/gms/internal/ads/zzgph
    //   2700	2739	3327	com/google/android/gms/internal/ads/zzgph
    //   2742	2759	3327	com/google/android/gms/internal/ads/zzgph
    //   2766	2795	3327	com/google/android/gms/internal/ads/zzgph
    //   2798	2827	3327	com/google/android/gms/internal/ads/zzgph
    //   2830	2859	3327	com/google/android/gms/internal/ads/zzgph
    //   2862	2891	3327	com/google/android/gms/internal/ads/zzgph
    //   2894	2923	3327	com/google/android/gms/internal/ads/zzgph
    //   2926	2955	3327	com/google/android/gms/internal/ads/zzgph
    //   2958	2987	3327	com/google/android/gms/internal/ads/zzgph
    //   2990	3019	3327	com/google/android/gms/internal/ads/zzgph
    //   3042	3052	3332	com/google/android/gms/internal/ads/zzgph
  }
  
  public final void zzi(Object paramObject, byte[] paramArrayOfByte, int paramInt1, int paramInt2, zzgna paramzzgna)
    throws IOException
  {
    Object localObject1 = this;
    Object localObject2 = paramObject;
    byte[] arrayOfByte = paramArrayOfByte;
    zzgna localzzgna = paramzzgna;
    if (((zzgqj)localObject1).zzj)
    {
      zzI(paramObject);
      Unsafe localUnsafe = zzb;
      int i = paramInt1;
      paramInt1 = -1;
      int n = 0;
      int j = 0;
      int k = 1048575;
      while (i < paramInt2)
      {
        int m = i + 1;
        int i1 = arrayOfByte[i];
        if (i1 < 0)
        {
          m = zzgnb.zzk(i1, arrayOfByte, m, localzzgna);
          i1 = localzzgna.zza;
        }
        i = i1 >>> 3;
        if (i > paramInt1) {
          paramInt1 = ((zzgqj)localObject1).zzv(i, n / 3);
        } else {
          paramInt1 = ((zzgqj)localObject1).zzu(i);
        }
        if (paramInt1 == -1) {
          paramInt1 = 0;
        }
        for (;;)
        {
          break label1257;
          int i3 = i1 & 0x7;
          Object localObject3 = ((zzgqj)localObject1).zzc;
          int i4 = localObject3[(paramInt1 + 1)];
          int i5 = zzy(i4);
          long l = i4 & 0xFFFFF;
          int i2;
          if (i5 <= 17)
          {
            n = localObject3[(paramInt1 + 2)];
            boolean bool = true;
            i2 = 1 << (n >>> 20);
            n &= 0xFFFFF;
            if (n != k)
            {
              if (k != 1048575) {
                localUnsafe.putInt(localObject2, k, j);
              }
              if (n != 1048575) {
                j = localUnsafe.getInt(localObject2, n);
              }
              localObject1 = localUnsafe;
              k = n;
              n = j;
            }
            else
            {
              localObject1 = localUnsafe;
              n = j;
            }
            switch (i5)
            {
            default: 
              break;
            case 16: 
              if (i3 == 0)
              {
                m = zzgnb.zzm(arrayOfByte, m, localzzgna);
                localUnsafe.putLong(paramObject, l, zzgnw.zzG(localzzgna.zzb));
                j = n | i2;
                localObject1 = localUnsafe;
                n = paramInt1;
                n = k;
                n = i;
                localObject1 = this;
                break label942;
              }
              break;
            case 15: 
              if (i3 == 0)
              {
                j = zzgnb.zzj(arrayOfByte, m, localzzgna);
                localUnsafe.putInt(localObject2, l, zzgnw.zzF(localzzgna.zza));
              }
              break;
            case 12: 
              if (i3 == 0)
              {
                j = zzgnb.zzj(arrayOfByte, m, localzzgna);
                localUnsafe.putInt(localObject2, l, localzzgna.zza);
              }
              break;
            case 10: 
              if (i3 == 2)
              {
                j = zzgnb.zza(arrayOfByte, m, localzzgna);
                localUnsafe.putObject(localObject2, l, localzzgna.zzc);
                i1 = n | i2;
                m = i;
                m = j;
                n = paramInt1;
                j = i1;
              }
              break;
            case 9: 
              if (i3 == 2)
              {
                localObject1 = zzF(localObject2, paramInt1);
                j = zzgnb.zzo(localObject1, zzC(paramInt1), paramArrayOfByte, m, paramInt2, paramzzgna);
                zzO(localObject2, paramInt1, localObject1);
                break label902;
              }
              break;
            case 8: 
              if (i3 != 2) {
                break label958;
              }
              if ((i4 & 0x20000000) == 0) {
                j = zzgnb.zzg(arrayOfByte, m, localzzgna);
              } else {
                j = zzgnb.zzh(arrayOfByte, m, localzzgna);
              }
              localUnsafe.putObject(localObject2, l, localzzgna.zzc);
              break;
            case 7: 
              if (i3 != 0) {
                break label958;
              }
              j = zzgnb.zzm(arrayOfByte, m, localzzgna);
              if (localzzgna.zzb == 0L) {
                bool = false;
              }
              zzgsa.zzp(localObject2, l, bool);
              break;
            case 6: 
            case 13: 
              if (i3 != 5) {
                break label958;
              }
              localUnsafe.putInt(localObject2, l, zzgnb.zzb(arrayOfByte, m));
              break;
            case 5: 
            case 14: 
              if (i3 != 1) {
                break label958;
              }
              localUnsafe.putLong(paramObject, l, zzgnb.zzp(arrayOfByte, m));
              j = m + 8;
              break;
            case 4: 
            case 11: 
              if (i3 != 0) {
                break label958;
              }
              j = zzgnb.zzj(arrayOfByte, m, localzzgna);
              localUnsafe.putInt(localObject2, l, localzzgna.zza);
              break;
            case 2: 
            case 3: 
              if (i3 != 0) {
                break label958;
              }
              m = zzgnb.zzm(arrayOfByte, m, localzzgna);
              localUnsafe.putLong(paramObject, l, localzzgna.zzb);
              n |= i2;
              localObject1 = localUnsafe;
              j = paramInt1;
              break;
            case 1: 
              if (i3 != 5) {
                break label958;
              }
              zzgsa.zzs(localObject2, l, Float.intBitsToFloat(zzgnb.zzb(arrayOfByte, m)));
              j = m + 4;
              break;
            }
            if (i3 == 1)
            {
              zzgsa.zzr(localObject2, l, Double.longBitsToDouble(zzgnb.zzp(arrayOfByte, m)));
              j = m + 8;
              label902:
              n |= i2;
              localObject1 = localUnsafe;
              m = paramInt1;
              m = j;
              localObject1 = localUnsafe;
              j = paramInt1;
              j = k;
              j = i;
              localObject1 = this;
              j = n;
              label942:
              localObject1 = this;
              n = paramInt1;
              paramInt1 = i;
              i = m;
              break;
            }
            label958:
            j = n;
            continue;
          }
          if (i5 == 27)
          {
            if (i3 == 2)
            {
              zzgpf localzzgpf = (zzgpf)localUnsafe.getObject(localObject2, l);
              localObject3 = localzzgpf;
              if (!localzzgpf.zzc())
              {
                n = localzzgpf.size();
                if (n == 0) {
                  n = 10;
                } else {
                  n += n;
                }
                localObject3 = localzzgpf.zzd(n);
                localUnsafe.putObject(localObject2, l, localObject3);
              }
              m = zzgnb.zze(((zzgqj)localObject1).zzC(paramInt1), i1, paramArrayOfByte, m, paramInt2, (zzgpf)localObject3, paramzzgna);
              n = paramInt1;
              paramInt1 = i;
              i = m;
              break;
            }
            break label1209;
          }
          if (i5 <= 49)
          {
            i2 = zzt(paramObject, paramArrayOfByte, m, paramInt2, i1, i, i3, paramInt1, i4, i5, l, paramzzgna);
            n = i2;
            if (i2 != m) {
              m = i2;
            }
          }
          for (;;)
          {
            n = i;
            n = paramInt1;
            break label1282;
            label1209:
            label1212:
            do
            {
              do
              {
                m = n;
                break;
                if (i5 != 50) {
                  break label1212;
                }
                if (i3 != 2) {
                  break;
                }
                i2 = zzr(paramObject, paramArrayOfByte, m, paramInt2, paramInt1, l, paramzzgna);
                n = i2;
              } while (i2 == m);
              m = i2;
              break;
              break label1257;
              i2 = zzs(paramObject, paramArrayOfByte, m, paramInt2, i1, i, i3, i4, i5, l, paramInt1, paramzzgna);
              n = i2;
            } while (i2 == m);
            m = i2;
          }
        }
        label1257:
        m = zzgnb.zzi(i1, paramArrayOfByte, m, paramInt2, zzd(paramObject), paramzzgna);
        n = i;
        n = paramInt1;
        label1282:
        paramInt1 = i;
        localObject2 = paramObject;
        arrayOfByte = paramArrayOfByte;
        localzzgna = paramzzgna;
        paramInt1 = i;
        localObject1 = this;
        i = m;
      }
      if (k != 1048575) {
        localUnsafe.putInt(paramObject, k, j);
      }
      if (i == paramInt2) {
        return;
      }
      throw zzgpi.zzg();
    }
    zzc(paramObject, paramArrayOfByte, paramInt1, paramInt2, 0, paramzzgna);
  }
  
  /* Error */
  public final boolean zzj(Object paramObject1, Object paramObject2)
  {
    // Byte code:
    //   0: aload_0
    //   1: getfield 54	com/google/android/gms/internal/ads/zzgqj:zzc	[I
    //   4: arraylength
    //   5: istore 4
    //   7: iconst_0
    //   8: istore_3
    //   9: iload_3
    //   10: iload 4
    //   12: if_icmpge +953 -> 965
    //   15: aload_0
    //   16: iload_3
    //   17: invokespecial 124	com/google/android/gms/internal/ads/zzgqj:zzz	(I)I
    //   20: istore 6
    //   22: iload 6
    //   24: invokestatic 299	com/google/android/gms/internal/ads/zzgqj:zzy	(I)I
    //   27: istore 5
    //   29: iload 6
    //   31: ldc 125
    //   33: iand
    //   34: i2l
    //   35: lstore 8
    //   37: iload 5
    //   39: tableswitch	default:+289->328, 0:+883->922, 1:+849->888, 2:+820->859, 3:+791->830, 4:+763->802, 5:+734->773, 6:+706->745, 7:+678->717, 8:+647->686, 9:+616->655, 10:+585->624, 11:+557->596, 12:+529->568, 13:+501->540, 14:+472->511, 15:+444->483, 16:+415->454, 17:+384->423, 18:+359->398, 19:+359->398, 20:+359->398, 21:+359->398, 22:+359->398, 23:+359->398, 24:+359->398, 25:+359->398, 26:+359->398, 27:+359->398, 28:+359->398, 29:+359->398, 30:+359->398, 31:+359->398, 32:+359->398, 33:+359->398, 34:+359->398, 35:+359->398, 36:+359->398, 37:+359->398, 38:+359->398, 39:+359->398, 40:+359->398, 41:+359->398, 42:+359->398, 43:+359->398, 44:+359->398, 45:+359->398, 46:+359->398, 47:+359->398, 48:+359->398, 49:+359->398, 50:+339->378, 51:+292->331, 52:+292->331, 53:+292->331, 54:+292->331, 55:+292->331, 56:+292->331, 57:+292->331, 58:+292->331, 59:+292->331, 60:+292->331, 61:+292->331, 62:+292->331, 63:+292->331, 64:+292->331, 65:+292->331, 66:+292->331, 67:+292->331, 68:+292->331
    //   328: goto +631 -> 959
    //   331: aload_0
    //   332: iload_3
    //   333: invokespecial 280	com/google/android/gms/internal/ads/zzgqj:zzw	(I)I
    //   336: ldc 125
    //   338: iand
    //   339: i2l
    //   340: lstore 10
    //   342: aload_1
    //   343: lload 10
    //   345: invokestatic 285	com/google/android/gms/internal/ads/zzgsa:zzd	(Ljava/lang/Object;J)I
    //   348: aload_2
    //   349: lload 10
    //   351: invokestatic 285	com/google/android/gms/internal/ads/zzgsa:zzd	(Ljava/lang/Object;J)I
    //   354: if_icmpne +603 -> 957
    //   357: aload_1
    //   358: lload 8
    //   360: invokestatic 96	com/google/android/gms/internal/ads/zzgsa:zzh	(Ljava/lang/Object;J)Ljava/lang/Object;
    //   363: aload_2
    //   364: lload 8
    //   366: invokestatic 96	com/google/android/gms/internal/ads/zzgsa:zzh	(Ljava/lang/Object;J)Ljava/lang/Object;
    //   369: invokestatic 945	com/google/android/gms/internal/ads/zzgrb:zzE	(Ljava/lang/Object;Ljava/lang/Object;)Z
    //   372: ifne +587 -> 959
    //   375: goto +582 -> 957
    //   378: aload_1
    //   379: lload 8
    //   381: invokestatic 96	com/google/android/gms/internal/ads/zzgsa:zzh	(Ljava/lang/Object;J)Ljava/lang/Object;
    //   384: aload_2
    //   385: lload 8
    //   387: invokestatic 96	com/google/android/gms/internal/ads/zzgsa:zzh	(Ljava/lang/Object;J)Ljava/lang/Object;
    //   390: invokestatic 945	com/google/android/gms/internal/ads/zzgrb:zzE	(Ljava/lang/Object;Ljava/lang/Object;)Z
    //   393: istore 7
    //   395: goto +20 -> 415
    //   398: aload_1
    //   399: lload 8
    //   401: invokestatic 96	com/google/android/gms/internal/ads/zzgsa:zzh	(Ljava/lang/Object;J)Ljava/lang/Object;
    //   404: aload_2
    //   405: lload 8
    //   407: invokestatic 96	com/google/android/gms/internal/ads/zzgsa:zzh	(Ljava/lang/Object;J)Ljava/lang/Object;
    //   410: invokestatic 945	com/google/android/gms/internal/ads/zzgrb:zzE	(Ljava/lang/Object;Ljava/lang/Object;)Z
    //   413: istore 7
    //   415: iload 7
    //   417: ifne +542 -> 959
    //   420: goto +537 -> 957
    //   423: aload_0
    //   424: aload_1
    //   425: aload_2
    //   426: iload_3
    //   427: invokespecial 947	com/google/android/gms/internal/ads/zzgqj:zzQ	(Ljava/lang/Object;Ljava/lang/Object;I)Z
    //   430: ifeq +527 -> 957
    //   433: aload_1
    //   434: lload 8
    //   436: invokestatic 96	com/google/android/gms/internal/ads/zzgsa:zzh	(Ljava/lang/Object;J)Ljava/lang/Object;
    //   439: aload_2
    //   440: lload 8
    //   442: invokestatic 96	com/google/android/gms/internal/ads/zzgsa:zzh	(Ljava/lang/Object;J)Ljava/lang/Object;
    //   445: invokestatic 945	com/google/android/gms/internal/ads/zzgrb:zzE	(Ljava/lang/Object;Ljava/lang/Object;)Z
    //   448: ifeq +509 -> 957
    //   451: goto +508 -> 959
    //   454: aload_0
    //   455: aload_1
    //   456: aload_2
    //   457: iload_3
    //   458: invokespecial 947	com/google/android/gms/internal/ads/zzgqj:zzQ	(Ljava/lang/Object;Ljava/lang/Object;I)Z
    //   461: ifeq +496 -> 957
    //   464: aload_1
    //   465: lload 8
    //   467: invokestatic 302	com/google/android/gms/internal/ads/zzgsa:zzf	(Ljava/lang/Object;J)J
    //   470: aload_2
    //   471: lload 8
    //   473: invokestatic 302	com/google/android/gms/internal/ads/zzgsa:zzf	(Ljava/lang/Object;J)J
    //   476: lcmp
    //   477: ifne +480 -> 957
    //   480: goto +479 -> 959
    //   483: aload_0
    //   484: aload_1
    //   485: aload_2
    //   486: iload_3
    //   487: invokespecial 947	com/google/android/gms/internal/ads/zzgqj:zzQ	(Ljava/lang/Object;Ljava/lang/Object;I)Z
    //   490: ifeq +467 -> 957
    //   493: aload_1
    //   494: lload 8
    //   496: invokestatic 285	com/google/android/gms/internal/ads/zzgsa:zzd	(Ljava/lang/Object;J)I
    //   499: aload_2
    //   500: lload 8
    //   502: invokestatic 285	com/google/android/gms/internal/ads/zzgsa:zzd	(Ljava/lang/Object;J)I
    //   505: if_icmpne +452 -> 957
    //   508: goto +451 -> 959
    //   511: aload_0
    //   512: aload_1
    //   513: aload_2
    //   514: iload_3
    //   515: invokespecial 947	com/google/android/gms/internal/ads/zzgqj:zzQ	(Ljava/lang/Object;Ljava/lang/Object;I)Z
    //   518: ifeq +439 -> 957
    //   521: aload_1
    //   522: lload 8
    //   524: invokestatic 302	com/google/android/gms/internal/ads/zzgsa:zzf	(Ljava/lang/Object;J)J
    //   527: aload_2
    //   528: lload 8
    //   530: invokestatic 302	com/google/android/gms/internal/ads/zzgsa:zzf	(Ljava/lang/Object;J)J
    //   533: lcmp
    //   534: ifne +423 -> 957
    //   537: goto +422 -> 959
    //   540: aload_0
    //   541: aload_1
    //   542: aload_2
    //   543: iload_3
    //   544: invokespecial 947	com/google/android/gms/internal/ads/zzgqj:zzQ	(Ljava/lang/Object;Ljava/lang/Object;I)Z
    //   547: ifeq +410 -> 957
    //   550: aload_1
    //   551: lload 8
    //   553: invokestatic 285	com/google/android/gms/internal/ads/zzgsa:zzd	(Ljava/lang/Object;J)I
    //   556: aload_2
    //   557: lload 8
    //   559: invokestatic 285	com/google/android/gms/internal/ads/zzgsa:zzd	(Ljava/lang/Object;J)I
    //   562: if_icmpne +395 -> 957
    //   565: goto +394 -> 959
    //   568: aload_0
    //   569: aload_1
    //   570: aload_2
    //   571: iload_3
    //   572: invokespecial 947	com/google/android/gms/internal/ads/zzgqj:zzQ	(Ljava/lang/Object;Ljava/lang/Object;I)Z
    //   575: ifeq +382 -> 957
    //   578: aload_1
    //   579: lload 8
    //   581: invokestatic 285	com/google/android/gms/internal/ads/zzgsa:zzd	(Ljava/lang/Object;J)I
    //   584: aload_2
    //   585: lload 8
    //   587: invokestatic 285	com/google/android/gms/internal/ads/zzgsa:zzd	(Ljava/lang/Object;J)I
    //   590: if_icmpne +367 -> 957
    //   593: goto +366 -> 959
    //   596: aload_0
    //   597: aload_1
    //   598: aload_2
    //   599: iload_3
    //   600: invokespecial 947	com/google/android/gms/internal/ads/zzgqj:zzQ	(Ljava/lang/Object;Ljava/lang/Object;I)Z
    //   603: ifeq +354 -> 957
    //   606: aload_1
    //   607: lload 8
    //   609: invokestatic 285	com/google/android/gms/internal/ads/zzgsa:zzd	(Ljava/lang/Object;J)I
    //   612: aload_2
    //   613: lload 8
    //   615: invokestatic 285	com/google/android/gms/internal/ads/zzgsa:zzd	(Ljava/lang/Object;J)I
    //   618: if_icmpne +339 -> 957
    //   621: goto +338 -> 959
    //   624: aload_0
    //   625: aload_1
    //   626: aload_2
    //   627: iload_3
    //   628: invokespecial 947	com/google/android/gms/internal/ads/zzgqj:zzQ	(Ljava/lang/Object;Ljava/lang/Object;I)Z
    //   631: ifeq +326 -> 957
    //   634: aload_1
    //   635: lload 8
    //   637: invokestatic 96	com/google/android/gms/internal/ads/zzgsa:zzh	(Ljava/lang/Object;J)Ljava/lang/Object;
    //   640: aload_2
    //   641: lload 8
    //   643: invokestatic 96	com/google/android/gms/internal/ads/zzgsa:zzh	(Ljava/lang/Object;J)Ljava/lang/Object;
    //   646: invokestatic 945	com/google/android/gms/internal/ads/zzgrb:zzE	(Ljava/lang/Object;Ljava/lang/Object;)Z
    //   649: ifeq +308 -> 957
    //   652: goto +307 -> 959
    //   655: aload_0
    //   656: aload_1
    //   657: aload_2
    //   658: iload_3
    //   659: invokespecial 947	com/google/android/gms/internal/ads/zzgqj:zzQ	(Ljava/lang/Object;Ljava/lang/Object;I)Z
    //   662: ifeq +295 -> 957
    //   665: aload_1
    //   666: lload 8
    //   668: invokestatic 96	com/google/android/gms/internal/ads/zzgsa:zzh	(Ljava/lang/Object;J)Ljava/lang/Object;
    //   671: aload_2
    //   672: lload 8
    //   674: invokestatic 96	com/google/android/gms/internal/ads/zzgsa:zzh	(Ljava/lang/Object;J)Ljava/lang/Object;
    //   677: invokestatic 945	com/google/android/gms/internal/ads/zzgrb:zzE	(Ljava/lang/Object;Ljava/lang/Object;)Z
    //   680: ifeq +277 -> 957
    //   683: goto +276 -> 959
    //   686: aload_0
    //   687: aload_1
    //   688: aload_2
    //   689: iload_3
    //   690: invokespecial 947	com/google/android/gms/internal/ads/zzgqj:zzQ	(Ljava/lang/Object;Ljava/lang/Object;I)Z
    //   693: ifeq +264 -> 957
    //   696: aload_1
    //   697: lload 8
    //   699: invokestatic 96	com/google/android/gms/internal/ads/zzgsa:zzh	(Ljava/lang/Object;J)Ljava/lang/Object;
    //   702: aload_2
    //   703: lload 8
    //   705: invokestatic 96	com/google/android/gms/internal/ads/zzgsa:zzh	(Ljava/lang/Object;J)Ljava/lang/Object;
    //   708: invokestatic 945	com/google/android/gms/internal/ads/zzgrb:zzE	(Ljava/lang/Object;Ljava/lang/Object;)Z
    //   711: ifeq +246 -> 957
    //   714: goto +245 -> 959
    //   717: aload_0
    //   718: aload_1
    //   719: aload_2
    //   720: iload_3
    //   721: invokespecial 947	com/google/android/gms/internal/ads/zzgqj:zzQ	(Ljava/lang/Object;Ljava/lang/Object;I)Z
    //   724: ifeq +233 -> 957
    //   727: aload_1
    //   728: lload 8
    //   730: invokestatic 315	com/google/android/gms/internal/ads/zzgsa:zzz	(Ljava/lang/Object;J)Z
    //   733: aload_2
    //   734: lload 8
    //   736: invokestatic 315	com/google/android/gms/internal/ads/zzgsa:zzz	(Ljava/lang/Object;J)Z
    //   739: if_icmpne +218 -> 957
    //   742: goto +217 -> 959
    //   745: aload_0
    //   746: aload_1
    //   747: aload_2
    //   748: iload_3
    //   749: invokespecial 947	com/google/android/gms/internal/ads/zzgqj:zzQ	(Ljava/lang/Object;Ljava/lang/Object;I)Z
    //   752: ifeq +205 -> 957
    //   755: aload_1
    //   756: lload 8
    //   758: invokestatic 285	com/google/android/gms/internal/ads/zzgsa:zzd	(Ljava/lang/Object;J)I
    //   761: aload_2
    //   762: lload 8
    //   764: invokestatic 285	com/google/android/gms/internal/ads/zzgsa:zzd	(Ljava/lang/Object;J)I
    //   767: if_icmpne +190 -> 957
    //   770: goto +189 -> 959
    //   773: aload_0
    //   774: aload_1
    //   775: aload_2
    //   776: iload_3
    //   777: invokespecial 947	com/google/android/gms/internal/ads/zzgqj:zzQ	(Ljava/lang/Object;Ljava/lang/Object;I)Z
    //   780: ifeq +177 -> 957
    //   783: aload_1
    //   784: lload 8
    //   786: invokestatic 302	com/google/android/gms/internal/ads/zzgsa:zzf	(Ljava/lang/Object;J)J
    //   789: aload_2
    //   790: lload 8
    //   792: invokestatic 302	com/google/android/gms/internal/ads/zzgsa:zzf	(Ljava/lang/Object;J)J
    //   795: lcmp
    //   796: ifne +161 -> 957
    //   799: goto +160 -> 959
    //   802: aload_0
    //   803: aload_1
    //   804: aload_2
    //   805: iload_3
    //   806: invokespecial 947	com/google/android/gms/internal/ads/zzgqj:zzQ	(Ljava/lang/Object;Ljava/lang/Object;I)Z
    //   809: ifeq +148 -> 957
    //   812: aload_1
    //   813: lload 8
    //   815: invokestatic 285	com/google/android/gms/internal/ads/zzgsa:zzd	(Ljava/lang/Object;J)I
    //   818: aload_2
    //   819: lload 8
    //   821: invokestatic 285	com/google/android/gms/internal/ads/zzgsa:zzd	(Ljava/lang/Object;J)I
    //   824: if_icmpne +133 -> 957
    //   827: goto +132 -> 959
    //   830: aload_0
    //   831: aload_1
    //   832: aload_2
    //   833: iload_3
    //   834: invokespecial 947	com/google/android/gms/internal/ads/zzgqj:zzQ	(Ljava/lang/Object;Ljava/lang/Object;I)Z
    //   837: ifeq +120 -> 957
    //   840: aload_1
    //   841: lload 8
    //   843: invokestatic 302	com/google/android/gms/internal/ads/zzgsa:zzf	(Ljava/lang/Object;J)J
    //   846: aload_2
    //   847: lload 8
    //   849: invokestatic 302	com/google/android/gms/internal/ads/zzgsa:zzf	(Ljava/lang/Object;J)J
    //   852: lcmp
    //   853: ifne +104 -> 957
    //   856: goto +103 -> 959
    //   859: aload_0
    //   860: aload_1
    //   861: aload_2
    //   862: iload_3
    //   863: invokespecial 947	com/google/android/gms/internal/ads/zzgqj:zzQ	(Ljava/lang/Object;Ljava/lang/Object;I)Z
    //   866: ifeq +91 -> 957
    //   869: aload_1
    //   870: lload 8
    //   872: invokestatic 302	com/google/android/gms/internal/ads/zzgsa:zzf	(Ljava/lang/Object;J)J
    //   875: aload_2
    //   876: lload 8
    //   878: invokestatic 302	com/google/android/gms/internal/ads/zzgsa:zzf	(Ljava/lang/Object;J)J
    //   881: lcmp
    //   882: ifne +75 -> 957
    //   885: goto +74 -> 959
    //   888: aload_0
    //   889: aload_1
    //   890: aload_2
    //   891: iload_3
    //   892: invokespecial 947	com/google/android/gms/internal/ads/zzgqj:zzQ	(Ljava/lang/Object;Ljava/lang/Object;I)Z
    //   895: ifeq +62 -> 957
    //   898: aload_1
    //   899: lload 8
    //   901: invokestatic 318	com/google/android/gms/internal/ads/zzgsa:zzc	(Ljava/lang/Object;J)F
    //   904: invokestatic 732	java/lang/Float:floatToIntBits	(F)I
    //   907: aload_2
    //   908: lload 8
    //   910: invokestatic 318	com/google/android/gms/internal/ads/zzgsa:zzc	(Ljava/lang/Object;J)F
    //   913: invokestatic 732	java/lang/Float:floatToIntBits	(F)I
    //   916: if_icmpne +41 -> 957
    //   919: goto +40 -> 959
    //   922: aload_0
    //   923: aload_1
    //   924: aload_2
    //   925: iload_3
    //   926: invokespecial 947	com/google/android/gms/internal/ads/zzgqj:zzQ	(Ljava/lang/Object;Ljava/lang/Object;I)Z
    //   929: ifeq +28 -> 957
    //   932: aload_1
    //   933: lload 8
    //   935: invokestatic 327	com/google/android/gms/internal/ads/zzgsa:zzb	(Ljava/lang/Object;J)D
    //   938: invokestatic 737	java/lang/Double:doubleToLongBits	(D)J
    //   941: aload_2
    //   942: lload 8
    //   944: invokestatic 327	com/google/android/gms/internal/ads/zzgsa:zzb	(Ljava/lang/Object;J)D
    //   947: invokestatic 737	java/lang/Double:doubleToLongBits	(D)J
    //   950: lcmp
    //   951: ifne +6 -> 957
    //   954: goto +5 -> 959
    //   957: iconst_0
    //   958: ireturn
    //   959: iinc 3 3
    //   962: goto -953 -> 9
    //   965: aload_0
    //   966: getfield 85	com/google/android/gms/internal/ads/zzgqj:zzo	Lcom/google/android/gms/internal/ads/zzgrq;
    //   969: aload_1
    //   970: invokevirtual 524	com/google/android/gms/internal/ads/zzgrq:zzd	(Ljava/lang/Object;)Ljava/lang/Object;
    //   973: aload_0
    //   974: getfield 85	com/google/android/gms/internal/ads/zzgqj:zzo	Lcom/google/android/gms/internal/ads/zzgrq;
    //   977: aload_2
    //   978: invokevirtual 524	com/google/android/gms/internal/ads/zzgrq:zzd	(Ljava/lang/Object;)Ljava/lang/Object;
    //   981: invokevirtual 948	java/lang/Object:equals	(Ljava/lang/Object;)Z
    //   984: ifne +5 -> 989
    //   987: iconst_0
    //   988: ireturn
    //   989: aload_0
    //   990: getfield 73	com/google/android/gms/internal/ads/zzgqj:zzh	Z
    //   993: ifne +5 -> 998
    //   996: iconst_1
    //   997: ireturn
    //   998: aload_0
    //   999: getfield 87	com/google/android/gms/internal/ads/zzgqj:zzp	Lcom/google/android/gms/internal/ads/zzgoj;
    //   1002: aload_1
    //   1003: invokevirtual 529	com/google/android/gms/internal/ads/zzgoj:zza	(Ljava/lang/Object;)Lcom/google/android/gms/internal/ads/zzgon;
    //   1006: pop
    //   1007: aload_0
    //   1008: getfield 87	com/google/android/gms/internal/ads/zzgqj:zzp	Lcom/google/android/gms/internal/ads/zzgoj;
    //   1011: aload_2
    //   1012: invokevirtual 529	com/google/android/gms/internal/ads/zzgoj:zza	(Ljava/lang/Object;)Lcom/google/android/gms/internal/ads/zzgon;
    //   1015: pop
    //   1016: aconst_null
    //   1017: athrow
    // Local variable table:
    //   start	length	slot	name	signature
    //   0	1018	0	this	zzgqj
    //   0	1018	1	paramObject1	Object
    //   0	1018	2	paramObject2	Object
    //   8	952	3	i	int
    //   5	8	4	j	int
    //   27	11	5	k	int
    //   20	14	6	m	int
    //   393	23	7	bool	boolean
    //   35	908	8	l1	long
    //   340	10	10	l2	long
  }
  
  public final boolean zzk(Object paramObject)
  {
    int j = 1048575;
    int i = 0;
    for (int k = 0; k < this.zzl; k++)
    {
      int i2 = this.zzk[k];
      int i1 = this.zzc[i2];
      int n = zzz(i2);
      int i3 = this.zzc[(i2 + 2)];
      int m = i3 & 0xFFFFF;
      i3 = 1 << (i3 >>> 20);
      if (m != j)
      {
        if (m != 1048575)
        {
          long l = m;
          i = zzb.getInt(paramObject, l);
        }
        j = m;
      }
      if (((0x10000000 & n) != 0) && (!zzT(paramObject, i2, j, i, i3))) {
        return false;
      }
      m = zzy(n);
      List localList;
      zzgqz localzzgqz;
      if ((m != 9) && (m != 17))
      {
        if (m != 27) {
          if ((m != 60) && (m != 68))
          {
            if (m != 49)
            {
              if ((m != 50) || (((zzgqa)zzgsa.zzh(paramObject, n & 0xFFFFF)).isEmpty())) {
                continue;
              }
              paramObject = (zzgpz)zzE(i2);
              throw null;
            }
          }
          else
          {
            if ((!zzW(paramObject, i1, i2)) || (zzU(paramObject, n, zzC(i2)))) {
              continue;
            }
            return false;
          }
        }
        localList = (List)zzgsa.zzh(paramObject, n & 0xFFFFF);
        if (!localList.isEmpty())
        {
          localzzgqz = zzC(i2);
          m = 0;
        }
      }
      else
      {
        while (m < localList.size())
        {
          if (!localzzgqz.zzk(localList.get(m))) {
            return false;
          }
          m++;
          continue;
          if ((zzT(paramObject, i2, j, i, i3)) && (!zzU(paramObject, n, zzC(i2)))) {
            return false;
          }
        }
      }
    }
    if (!this.zzh) {
      return true;
    }
    this.zzp.zza(paramObject);
    throw null;
  }
  
  public final void zzm(Object paramObject, zzgoe paramzzgoe)
    throws IOException
  {
    int j;
    int i;
    int m;
    int k;
    Object localObject;
    if (this.zzj)
    {
      if (!this.zzh)
      {
        j = this.zzc.length;
        for (i = 0; i < j; i += 3)
        {
          m = zzz(i);
          k = this.zzc[i];
          switch (zzy(m))
          {
          default: 
            break;
          case 68: 
            if (zzW(paramObject, k, i)) {
              paramzzgoe.zzq(k, zzgsa.zzh(paramObject, m & 0xFFFFF), zzC(i));
            }
            break;
          case 67: 
            if (zzW(paramObject, k, i)) {
              paramzzgoe.zzC(k, zzA(paramObject, m & 0xFFFFF));
            }
            break;
          case 66: 
            if (zzW(paramObject, k, i)) {
              paramzzgoe.zzA(k, zzq(paramObject, m & 0xFFFFF));
            }
            break;
          case 65: 
            if (zzW(paramObject, k, i)) {
              paramzzgoe.zzy(k, zzA(paramObject, m & 0xFFFFF));
            }
            break;
          case 64: 
            if (zzW(paramObject, k, i)) {
              paramzzgoe.zzw(k, zzq(paramObject, m & 0xFFFFF));
            }
            break;
          case 63: 
            if (zzW(paramObject, k, i)) {
              paramzzgoe.zzi(k, zzq(paramObject, m & 0xFFFFF));
            }
            break;
          case 62: 
            if (zzW(paramObject, k, i)) {
              paramzzgoe.zzH(k, zzq(paramObject, m & 0xFFFFF));
            }
            break;
          case 61: 
            if (zzW(paramObject, k, i)) {
              paramzzgoe.zzd(k, (zzgno)zzgsa.zzh(paramObject, m & 0xFFFFF));
            }
            break;
          case 60: 
            if (zzW(paramObject, k, i)) {
              paramzzgoe.zzv(k, zzgsa.zzh(paramObject, m & 0xFFFFF), zzC(i));
            }
            break;
          case 59: 
            if (zzW(paramObject, k, i)) {
              zzZ(k, zzgsa.zzh(paramObject, m & 0xFFFFF), paramzzgoe);
            }
            break;
          case 58: 
            if (zzW(paramObject, k, i)) {
              paramzzgoe.zzb(k, zzX(paramObject, m & 0xFFFFF));
            }
            break;
          case 57: 
            if (zzW(paramObject, k, i)) {
              paramzzgoe.zzk(k, zzq(paramObject, m & 0xFFFFF));
            }
            break;
          case 56: 
            if (zzW(paramObject, k, i)) {
              paramzzgoe.zzm(k, zzA(paramObject, m & 0xFFFFF));
            }
            break;
          case 55: 
            if (zzW(paramObject, k, i)) {
              paramzzgoe.zzr(k, zzq(paramObject, m & 0xFFFFF));
            }
            break;
          case 54: 
            if (zzW(paramObject, k, i)) {
              paramzzgoe.zzJ(k, zzA(paramObject, m & 0xFFFFF));
            }
            break;
          case 53: 
            if (zzW(paramObject, k, i)) {
              paramzzgoe.zzt(k, zzA(paramObject, m & 0xFFFFF));
            }
            break;
          case 52: 
            if (zzW(paramObject, k, i)) {
              paramzzgoe.zzo(k, zzo(paramObject, m & 0xFFFFF));
            }
            break;
          case 51: 
            if (zzW(paramObject, k, i)) {
              paramzzgoe.zzf(k, zzn(paramObject, m & 0xFFFFF));
            }
            break;
          case 50: 
            zzY(paramzzgoe, k, zzgsa.zzh(paramObject, m & 0xFFFFF), i);
            break;
          case 49: 
            zzgrb.zzM(k, (List)zzgsa.zzh(paramObject, m & 0xFFFFF), paramzzgoe, zzC(i));
            break;
          case 48: 
            zzgrb.zzT(k, (List)zzgsa.zzh(paramObject, m & 0xFFFFF), paramzzgoe, true);
            break;
          case 47: 
            zzgrb.zzS(k, (List)zzgsa.zzh(paramObject, m & 0xFFFFF), paramzzgoe, true);
            break;
          case 46: 
            zzgrb.zzR(k, (List)zzgsa.zzh(paramObject, m & 0xFFFFF), paramzzgoe, true);
            break;
          case 45: 
            zzgrb.zzQ(k, (List)zzgsa.zzh(paramObject, m & 0xFFFFF), paramzzgoe, true);
            break;
          case 44: 
            zzgrb.zzI(k, (List)zzgsa.zzh(paramObject, m & 0xFFFFF), paramzzgoe, true);
            break;
          case 43: 
            zzgrb.zzV(k, (List)zzgsa.zzh(paramObject, m & 0xFFFFF), paramzzgoe, true);
            break;
          case 42: 
            zzgrb.zzF(k, (List)zzgsa.zzh(paramObject, m & 0xFFFFF), paramzzgoe, true);
            break;
          case 41: 
            zzgrb.zzJ(k, (List)zzgsa.zzh(paramObject, m & 0xFFFFF), paramzzgoe, true);
            break;
          case 40: 
            zzgrb.zzK(k, (List)zzgsa.zzh(paramObject, m & 0xFFFFF), paramzzgoe, true);
            break;
          case 39: 
            zzgrb.zzN(k, (List)zzgsa.zzh(paramObject, m & 0xFFFFF), paramzzgoe, true);
            break;
          case 38: 
            zzgrb.zzW(k, (List)zzgsa.zzh(paramObject, m & 0xFFFFF), paramzzgoe, true);
            break;
          case 37: 
            zzgrb.zzO(k, (List)zzgsa.zzh(paramObject, m & 0xFFFFF), paramzzgoe, true);
            break;
          case 36: 
            zzgrb.zzL(k, (List)zzgsa.zzh(paramObject, m & 0xFFFFF), paramzzgoe, true);
            break;
          case 35: 
            zzgrb.zzH(k, (List)zzgsa.zzh(paramObject, m & 0xFFFFF), paramzzgoe, true);
            break;
          case 34: 
            zzgrb.zzT(k, (List)zzgsa.zzh(paramObject, m & 0xFFFFF), paramzzgoe, false);
            break;
          case 33: 
            zzgrb.zzS(k, (List)zzgsa.zzh(paramObject, m & 0xFFFFF), paramzzgoe, false);
            break;
          case 32: 
            zzgrb.zzR(k, (List)zzgsa.zzh(paramObject, m & 0xFFFFF), paramzzgoe, false);
            break;
          case 31: 
            zzgrb.zzQ(k, (List)zzgsa.zzh(paramObject, m & 0xFFFFF), paramzzgoe, false);
            break;
          case 30: 
            zzgrb.zzI(k, (List)zzgsa.zzh(paramObject, m & 0xFFFFF), paramzzgoe, false);
            break;
          case 29: 
            zzgrb.zzV(k, (List)zzgsa.zzh(paramObject, m & 0xFFFFF), paramzzgoe, false);
            break;
          case 28: 
            zzgrb.zzG(k, (List)zzgsa.zzh(paramObject, m & 0xFFFFF), paramzzgoe);
            break;
          case 27: 
            zzgrb.zzP(k, (List)zzgsa.zzh(paramObject, m & 0xFFFFF), paramzzgoe, zzC(i));
            break;
          case 26: 
            zzgrb.zzU(k, (List)zzgsa.zzh(paramObject, m & 0xFFFFF), paramzzgoe);
            break;
          case 25: 
            zzgrb.zzF(k, (List)zzgsa.zzh(paramObject, m & 0xFFFFF), paramzzgoe, false);
            break;
          case 24: 
            zzgrb.zzJ(k, (List)zzgsa.zzh(paramObject, m & 0xFFFFF), paramzzgoe, false);
            break;
          case 23: 
            zzgrb.zzK(k, (List)zzgsa.zzh(paramObject, m & 0xFFFFF), paramzzgoe, false);
            break;
          case 22: 
            zzgrb.zzN(k, (List)zzgsa.zzh(paramObject, m & 0xFFFFF), paramzzgoe, false);
            break;
          case 21: 
            zzgrb.zzW(k, (List)zzgsa.zzh(paramObject, m & 0xFFFFF), paramzzgoe, false);
            break;
          case 20: 
            zzgrb.zzO(k, (List)zzgsa.zzh(paramObject, m & 0xFFFFF), paramzzgoe, false);
            break;
          case 19: 
            zzgrb.zzL(k, (List)zzgsa.zzh(paramObject, m & 0xFFFFF), paramzzgoe, false);
            break;
          case 18: 
            zzgrb.zzH(k, (List)zzgsa.zzh(paramObject, m & 0xFFFFF), paramzzgoe, false);
            break;
          case 17: 
            if (zzS(paramObject, i)) {
              paramzzgoe.zzq(k, zzgsa.zzh(paramObject, m & 0xFFFFF), zzC(i));
            }
            break;
          case 16: 
            if (zzS(paramObject, i)) {
              paramzzgoe.zzC(k, zzgsa.zzf(paramObject, m & 0xFFFFF));
            }
            break;
          case 15: 
            if (zzS(paramObject, i)) {
              paramzzgoe.zzA(k, zzgsa.zzd(paramObject, m & 0xFFFFF));
            }
            break;
          case 14: 
            if (zzS(paramObject, i)) {
              paramzzgoe.zzy(k, zzgsa.zzf(paramObject, m & 0xFFFFF));
            }
            break;
          case 13: 
            if (zzS(paramObject, i)) {
              paramzzgoe.zzw(k, zzgsa.zzd(paramObject, m & 0xFFFFF));
            }
            break;
          case 12: 
            if (zzS(paramObject, i)) {
              paramzzgoe.zzi(k, zzgsa.zzd(paramObject, m & 0xFFFFF));
            }
            break;
          case 11: 
            if (zzS(paramObject, i)) {
              paramzzgoe.zzH(k, zzgsa.zzd(paramObject, m & 0xFFFFF));
            }
            break;
          case 10: 
            if (zzS(paramObject, i)) {
              paramzzgoe.zzd(k, (zzgno)zzgsa.zzh(paramObject, m & 0xFFFFF));
            }
            break;
          case 9: 
            if (zzS(paramObject, i)) {
              paramzzgoe.zzv(k, zzgsa.zzh(paramObject, m & 0xFFFFF), zzC(i));
            }
            break;
          case 8: 
            if (zzS(paramObject, i)) {
              zzZ(k, zzgsa.zzh(paramObject, m & 0xFFFFF), paramzzgoe);
            }
            break;
          case 7: 
            if (zzS(paramObject, i)) {
              paramzzgoe.zzb(k, zzgsa.zzz(paramObject, m & 0xFFFFF));
            }
            break;
          case 6: 
            if (zzS(paramObject, i)) {
              paramzzgoe.zzk(k, zzgsa.zzd(paramObject, m & 0xFFFFF));
            }
            break;
          case 5: 
            if (zzS(paramObject, i)) {
              paramzzgoe.zzm(k, zzgsa.zzf(paramObject, m & 0xFFFFF));
            }
            break;
          case 4: 
            if (zzS(paramObject, i)) {
              paramzzgoe.zzr(k, zzgsa.zzd(paramObject, m & 0xFFFFF));
            }
            break;
          case 3: 
            if (zzS(paramObject, i)) {
              paramzzgoe.zzJ(k, zzgsa.zzf(paramObject, m & 0xFFFFF));
            }
            break;
          case 2: 
            if (zzS(paramObject, i)) {
              paramzzgoe.zzt(k, zzgsa.zzf(paramObject, m & 0xFFFFF));
            }
            break;
          case 1: 
            if (zzS(paramObject, i)) {
              paramzzgoe.zzo(k, zzgsa.zzc(paramObject, m & 0xFFFFF));
            }
            break;
          case 0: 
            if (zzS(paramObject, i)) {
              paramzzgoe.zzf(k, zzgsa.zzb(paramObject, m & 0xFFFFF));
            }
            break;
          }
        }
        localObject = this.zzo;
        ((zzgrq)localObject).zzr(((zzgrq)localObject).zzd(paramObject), paramzzgoe);
        return;
      }
      this.zzp.zza(paramObject);
      throw null;
    }
    if (!this.zzh)
    {
      int i1 = this.zzc.length;
      localObject = zzb;
      m = 0;
      i = 1048575;
      j = 0;
      while (m < i1)
      {
        int i4 = zzz(m);
        int[] arrayOfInt = this.zzc;
        int i2 = arrayOfInt[m];
        int i3 = zzy(i4);
        if (i3 <= 17)
        {
          int i5 = arrayOfInt[(m + 2)];
          int n = i5 & 0xFFFFF;
          k = i;
          if (n != i)
          {
            j = ((Unsafe)localObject).getInt(paramObject, n);
            k = n;
          }
          n = 1 << (i5 >>> 20);
          i = k;
          k = n;
        }
        else
        {
          k = 0;
        }
        long l = i4 & 0xFFFFF;
        switch (i3)
        {
        }
        for (;;)
        {
          break;
          if (zzW(paramObject, i2, m))
          {
            paramzzgoe.zzq(i2, ((Unsafe)localObject).getObject(paramObject, l), zzC(m));
            continue;
            if (zzW(paramObject, i2, m))
            {
              paramzzgoe.zzC(i2, zzA(paramObject, l));
              continue;
              if (zzW(paramObject, i2, m))
              {
                paramzzgoe.zzA(i2, zzq(paramObject, l));
                continue;
                if (zzW(paramObject, i2, m))
                {
                  paramzzgoe.zzy(i2, zzA(paramObject, l));
                  continue;
                  if (zzW(paramObject, i2, m))
                  {
                    paramzzgoe.zzw(i2, zzq(paramObject, l));
                    continue;
                    if (zzW(paramObject, i2, m))
                    {
                      paramzzgoe.zzi(i2, zzq(paramObject, l));
                      continue;
                      if (zzW(paramObject, i2, m))
                      {
                        paramzzgoe.zzH(i2, zzq(paramObject, l));
                        continue;
                        if (zzW(paramObject, i2, m))
                        {
                          paramzzgoe.zzd(i2, (zzgno)((Unsafe)localObject).getObject(paramObject, l));
                          continue;
                          if (zzW(paramObject, i2, m))
                          {
                            paramzzgoe.zzv(i2, ((Unsafe)localObject).getObject(paramObject, l), zzC(m));
                            continue;
                            if (zzW(paramObject, i2, m))
                            {
                              zzZ(i2, ((Unsafe)localObject).getObject(paramObject, l), paramzzgoe);
                              continue;
                              if (zzW(paramObject, i2, m))
                              {
                                paramzzgoe.zzb(i2, zzX(paramObject, l));
                                continue;
                                if (zzW(paramObject, i2, m))
                                {
                                  paramzzgoe.zzk(i2, zzq(paramObject, l));
                                  continue;
                                  if (zzW(paramObject, i2, m))
                                  {
                                    paramzzgoe.zzm(i2, zzA(paramObject, l));
                                    continue;
                                    if (zzW(paramObject, i2, m))
                                    {
                                      paramzzgoe.zzr(i2, zzq(paramObject, l));
                                      continue;
                                      if (zzW(paramObject, i2, m))
                                      {
                                        paramzzgoe.zzJ(i2, zzA(paramObject, l));
                                        continue;
                                        if (zzW(paramObject, i2, m))
                                        {
                                          paramzzgoe.zzt(i2, zzA(paramObject, l));
                                          continue;
                                          if (zzW(paramObject, i2, m))
                                          {
                                            paramzzgoe.zzo(i2, zzo(paramObject, l));
                                            continue;
                                            if (zzW(paramObject, i2, m))
                                            {
                                              paramzzgoe.zzf(i2, zzn(paramObject, l));
                                              continue;
                                              zzY(paramzzgoe, i2, ((Unsafe)localObject).getObject(paramObject, l), m);
                                              continue;
                                              zzgrb.zzM(this.zzc[m], (List)((Unsafe)localObject).getObject(paramObject, l), paramzzgoe, zzC(m));
                                              continue;
                                              zzgrb.zzT(this.zzc[m], (List)((Unsafe)localObject).getObject(paramObject, l), paramzzgoe, true);
                                              continue;
                                              zzgrb.zzS(this.zzc[m], (List)((Unsafe)localObject).getObject(paramObject, l), paramzzgoe, true);
                                              continue;
                                              zzgrb.zzR(this.zzc[m], (List)((Unsafe)localObject).getObject(paramObject, l), paramzzgoe, true);
                                              continue;
                                              zzgrb.zzQ(this.zzc[m], (List)((Unsafe)localObject).getObject(paramObject, l), paramzzgoe, true);
                                              continue;
                                              zzgrb.zzI(this.zzc[m], (List)((Unsafe)localObject).getObject(paramObject, l), paramzzgoe, true);
                                              continue;
                                              zzgrb.zzV(this.zzc[m], (List)((Unsafe)localObject).getObject(paramObject, l), paramzzgoe, true);
                                              continue;
                                              zzgrb.zzF(this.zzc[m], (List)((Unsafe)localObject).getObject(paramObject, l), paramzzgoe, true);
                                              continue;
                                              zzgrb.zzJ(this.zzc[m], (List)((Unsafe)localObject).getObject(paramObject, l), paramzzgoe, true);
                                              continue;
                                              zzgrb.zzK(this.zzc[m], (List)((Unsafe)localObject).getObject(paramObject, l), paramzzgoe, true);
                                              continue;
                                              zzgrb.zzN(this.zzc[m], (List)((Unsafe)localObject).getObject(paramObject, l), paramzzgoe, true);
                                              continue;
                                              zzgrb.zzW(this.zzc[m], (List)((Unsafe)localObject).getObject(paramObject, l), paramzzgoe, true);
                                              continue;
                                              zzgrb.zzO(this.zzc[m], (List)((Unsafe)localObject).getObject(paramObject, l), paramzzgoe, true);
                                              continue;
                                              zzgrb.zzL(this.zzc[m], (List)((Unsafe)localObject).getObject(paramObject, l), paramzzgoe, true);
                                              continue;
                                              zzgrb.zzH(this.zzc[m], (List)((Unsafe)localObject).getObject(paramObject, l), paramzzgoe, true);
                                              continue;
                                              zzgrb.zzT(this.zzc[m], (List)((Unsafe)localObject).getObject(paramObject, l), paramzzgoe, false);
                                              continue;
                                              zzgrb.zzS(this.zzc[m], (List)((Unsafe)localObject).getObject(paramObject, l), paramzzgoe, false);
                                              continue;
                                              zzgrb.zzR(this.zzc[m], (List)((Unsafe)localObject).getObject(paramObject, l), paramzzgoe, false);
                                              continue;
                                              zzgrb.zzQ(this.zzc[m], (List)((Unsafe)localObject).getObject(paramObject, l), paramzzgoe, false);
                                              continue;
                                              zzgrb.zzI(this.zzc[m], (List)((Unsafe)localObject).getObject(paramObject, l), paramzzgoe, false);
                                              continue;
                                              zzgrb.zzV(this.zzc[m], (List)((Unsafe)localObject).getObject(paramObject, l), paramzzgoe, false);
                                              continue;
                                              zzgrb.zzG(this.zzc[m], (List)((Unsafe)localObject).getObject(paramObject, l), paramzzgoe);
                                              continue;
                                              zzgrb.zzP(this.zzc[m], (List)((Unsafe)localObject).getObject(paramObject, l), paramzzgoe, zzC(m));
                                              continue;
                                              zzgrb.zzU(this.zzc[m], (List)((Unsafe)localObject).getObject(paramObject, l), paramzzgoe);
                                              continue;
                                              zzgrb.zzF(this.zzc[m], (List)((Unsafe)localObject).getObject(paramObject, l), paramzzgoe, false);
                                              break;
                                              zzgrb.zzJ(this.zzc[m], (List)((Unsafe)localObject).getObject(paramObject, l), paramzzgoe, false);
                                              break;
                                              zzgrb.zzK(this.zzc[m], (List)((Unsafe)localObject).getObject(paramObject, l), paramzzgoe, false);
                                              break;
                                              zzgrb.zzN(this.zzc[m], (List)((Unsafe)localObject).getObject(paramObject, l), paramzzgoe, false);
                                              break;
                                              zzgrb.zzW(this.zzc[m], (List)((Unsafe)localObject).getObject(paramObject, l), paramzzgoe, false);
                                              break;
                                              zzgrb.zzO(this.zzc[m], (List)((Unsafe)localObject).getObject(paramObject, l), paramzzgoe, false);
                                              break;
                                              zzgrb.zzL(this.zzc[m], (List)((Unsafe)localObject).getObject(paramObject, l), paramzzgoe, false);
                                              break;
                                              zzgrb.zzH(this.zzc[m], (List)((Unsafe)localObject).getObject(paramObject, l), paramzzgoe, false);
                                              break;
                                              if ((j & k) != 0)
                                              {
                                                paramzzgoe.zzq(i2, ((Unsafe)localObject).getObject(paramObject, l), zzC(m));
                                                break;
                                                if ((j & k) != 0)
                                                {
                                                  paramzzgoe.zzC(i2, ((Unsafe)localObject).getLong(paramObject, l));
                                                  break;
                                                  if ((j & k) != 0)
                                                  {
                                                    paramzzgoe.zzA(i2, ((Unsafe)localObject).getInt(paramObject, l));
                                                    break;
                                                    if ((j & k) != 0)
                                                    {
                                                      paramzzgoe.zzy(i2, ((Unsafe)localObject).getLong(paramObject, l));
                                                      break;
                                                      if ((j & k) != 0)
                                                      {
                                                        paramzzgoe.zzw(i2, ((Unsafe)localObject).getInt(paramObject, l));
                                                        break;
                                                        if ((j & k) != 0)
                                                        {
                                                          paramzzgoe.zzi(i2, ((Unsafe)localObject).getInt(paramObject, l));
                                                          break;
                                                          if ((j & k) != 0)
                                                          {
                                                            paramzzgoe.zzH(i2, ((Unsafe)localObject).getInt(paramObject, l));
                                                            break;
                                                            if ((j & k) != 0)
                                                            {
                                                              paramzzgoe.zzd(i2, (zzgno)((Unsafe)localObject).getObject(paramObject, l));
                                                              break;
                                                              if ((j & k) != 0)
                                                              {
                                                                paramzzgoe.zzv(i2, ((Unsafe)localObject).getObject(paramObject, l), zzC(m));
                                                                break;
                                                                if ((j & k) != 0)
                                                                {
                                                                  zzZ(i2, ((Unsafe)localObject).getObject(paramObject, l), paramzzgoe);
                                                                  break;
                                                                  if ((j & k) != 0)
                                                                  {
                                                                    paramzzgoe.zzb(i2, zzgsa.zzz(paramObject, l));
                                                                    break;
                                                                    if ((j & k) != 0)
                                                                    {
                                                                      paramzzgoe.zzk(i2, ((Unsafe)localObject).getInt(paramObject, l));
                                                                      break;
                                                                      if ((j & k) != 0)
                                                                      {
                                                                        paramzzgoe.zzm(i2, ((Unsafe)localObject).getLong(paramObject, l));
                                                                        break;
                                                                        if ((j & k) != 0)
                                                                        {
                                                                          paramzzgoe.zzr(i2, ((Unsafe)localObject).getInt(paramObject, l));
                                                                          break;
                                                                          if ((j & k) != 0)
                                                                          {
                                                                            paramzzgoe.zzJ(i2, ((Unsafe)localObject).getLong(paramObject, l));
                                                                            break;
                                                                            if ((j & k) != 0)
                                                                            {
                                                                              paramzzgoe.zzt(i2, ((Unsafe)localObject).getLong(paramObject, l));
                                                                              break;
                                                                              if ((j & k) != 0)
                                                                              {
                                                                                paramzzgoe.zzo(i2, zzgsa.zzc(paramObject, l));
                                                                                break;
                                                                                if ((j & k) != 0) {
                                                                                  paramzzgoe.zzf(i2, zzgsa.zzb(paramObject, l));
                                                                                }
                                                                              }
                                                                            }
                                                                          }
                                                                        }
                                                                      }
                                                                    }
                                                                  }
                                                                }
                                                              }
                                                            }
                                                          }
                                                        }
                                                      }
                                                    }
                                                  }
                                                }
                                              }
                                            }
                                          }
                                        }
                                      }
                                    }
                                  }
                                }
                              }
                            }
                          }
                        }
                      }
                    }
                  }
                }
              }
            }
          }
        }
        m += 3;
      }
      localObject = this.zzo;
      ((zzgrq)localObject).zzr(((zzgrq)localObject).zzd(paramObject), paramzzgoe);
      return;
    }
    this.zzp.zza(paramObject);
    throw null;
  }
}


/* Location:              C:\Users\Ria\Documents\slope apk\dex-tools-v2.4\classes-dex2jar.jar!\com\google\android\gms\internal\ads\zzgqj.class
 * Java compiler version: 6 (50.0)
 * JD-Core Version:       0.7.1
 */