package com.google.android.gms.internal.ads;

import android.content.Context;
import android.content.res.AssetFileDescriptor;
import android.content.res.Resources;
import android.net.Uri;
import java.io.EOFException;
import java.io.IOException;
import java.io.InputStream;

public final class zzgx
  extends zzfr
{
  private final Resources zza;
  private final String zzb;
  private Uri zzc;
  private AssetFileDescriptor zzd;
  private InputStream zze;
  private long zzf;
  private boolean zzg;
  
  public zzgx(Context paramContext)
  {
    super(false);
    this.zza = paramContext.getResources();
    this.zzb = paramContext.getPackageName();
  }
  
  public static Uri buildRawResourceUri(int paramInt)
  {
    StringBuilder localStringBuilder = new StringBuilder();
    localStringBuilder.append("rawresource:///");
    localStringBuilder.append(paramInt);
    return Uri.parse(localStringBuilder.toString());
  }
  
  public final int zza(byte[] paramArrayOfByte, int paramInt1, int paramInt2)
    throws zzgw
  {
    if (paramInt2 == 0) {
      return 0;
    }
    long l2 = this.zzf;
    if (l2 != 0L)
    {
      int i = paramInt2;
      long l1;
      if (l2 != -1L) {
        l1 = paramInt2;
      }
      try
      {
        i = (int)Math.min(l2, l1);
        InputStream localInputStream = this.zze;
        paramInt2 = zzfn.zza;
        paramInt1 = localInputStream.read(paramArrayOfByte, paramInt1, i);
        if (paramInt1 == -1)
        {
          if (this.zzf == -1L) {
            return -1;
          }
          throw new zzgw("End of stream reached having not read sufficient data.", new EOFException(), 2000);
        }
        l1 = this.zzf;
        if (l1 != -1L) {
          this.zzf = (l1 - paramInt1);
        }
        zzg(paramInt1);
        return paramInt1;
      }
      catch (IOException paramArrayOfByte)
      {
        throw new zzgw(null, paramArrayOfByte, 2000);
      }
    }
    return -1;
  }
  
  /* Error */
  public final long zzb(zzgc paramzzgc)
    throws zzgw
  {
    // Byte code:
    //   0: aload_1
    //   1: getfield 111	com/google/android/gms/internal/ads/zzgc:zza	Landroid/net/Uri;
    //   4: astore 9
    //   6: aload_0
    //   7: aload 9
    //   9: putfield 113	com/google/android/gms/internal/ads/zzgx:zzc	Landroid/net/Uri;
    //   12: ldc 115
    //   14: aload 9
    //   16: invokevirtual 118	android/net/Uri:getScheme	()Ljava/lang/String;
    //   19: invokestatic 124	android/text/TextUtils:equals	(Ljava/lang/CharSequence;Ljava/lang/CharSequence;)Z
    //   22: ifne +209 -> 231
    //   25: ldc 126
    //   27: aload 9
    //   29: invokevirtual 118	android/net/Uri:getScheme	()Ljava/lang/String;
    //   32: invokestatic 124	android/text/TextUtils:equals	(Ljava/lang/CharSequence;Ljava/lang/CharSequence;)Z
    //   35: ifeq +43 -> 78
    //   38: aload 9
    //   40: invokevirtual 130	android/net/Uri:getPathSegments	()Ljava/util/List;
    //   43: invokeinterface 136 1 0
    //   48: iconst_1
    //   49: if_icmpne +29 -> 78
    //   52: aload 9
    //   54: invokevirtual 139	android/net/Uri:getLastPathSegment	()Ljava/lang/String;
    //   57: astore 7
    //   59: aload 7
    //   61: invokestatic 145	java/util/Objects:requireNonNull	(Ljava/lang/Object;)Ljava/lang/Object;
    //   64: pop
    //   65: aload 7
    //   67: ldc -109
    //   69: invokevirtual 153	java/lang/String:matches	(Ljava/lang/String;)Z
    //   72: ifeq +6 -> 78
    //   75: goto +156 -> 231
    //   78: ldc 126
    //   80: aload 9
    //   82: invokevirtual 118	android/net/Uri:getScheme	()Ljava/lang/String;
    //   85: invokestatic 124	android/text/TextUtils:equals	(Ljava/lang/CharSequence;Ljava/lang/CharSequence;)Z
    //   88: ifeq +129 -> 217
    //   91: aload 9
    //   93: invokevirtual 156	android/net/Uri:getPath	()Ljava/lang/String;
    //   96: astore 8
    //   98: aload 8
    //   100: invokestatic 145	java/util/Objects:requireNonNull	(Ljava/lang/Object;)Ljava/lang/Object;
    //   103: pop
    //   104: aload 8
    //   106: astore 7
    //   108: aload 8
    //   110: ldc -98
    //   112: invokevirtual 161	java/lang/String:startsWith	(Ljava/lang/String;)Z
    //   115: ifeq +11 -> 126
    //   118: aload 8
    //   120: iconst_1
    //   121: invokevirtual 165	java/lang/String:substring	(I)Ljava/lang/String;
    //   124: astore 7
    //   126: aload 9
    //   128: invokevirtual 168	android/net/Uri:getHost	()Ljava/lang/String;
    //   131: astore 8
    //   133: aload 8
    //   135: invokestatic 172	android/text/TextUtils:isEmpty	(Ljava/lang/CharSequence;)Z
    //   138: ifeq +10 -> 148
    //   141: ldc -82
    //   143: astore 8
    //   145: goto +15 -> 160
    //   148: aload 8
    //   150: invokestatic 178	java/lang/String:valueOf	(Ljava/lang/Object;)Ljava/lang/String;
    //   153: ldc -76
    //   155: invokevirtual 184	java/lang/String:concat	(Ljava/lang/String;)Ljava/lang/String;
    //   158: astore 8
    //   160: aload 7
    //   162: invokestatic 178	java/lang/String:valueOf	(Ljava/lang/Object;)Ljava/lang/String;
    //   165: astore 11
    //   167: aload_0
    //   168: getfield 31	com/google/android/gms/internal/ads/zzgx:zza	Landroid/content/res/Resources;
    //   171: astore 7
    //   173: aload_0
    //   174: getfield 37	com/google/android/gms/internal/ads/zzgx:zzb	Ljava/lang/String;
    //   177: astore 10
    //   179: aload 7
    //   181: aload 8
    //   183: aload 11
    //   185: invokevirtual 184	java/lang/String:concat	(Ljava/lang/String;)Ljava/lang/String;
    //   188: ldc -70
    //   190: aload 10
    //   192: invokevirtual 192	android/content/res/Resources:getIdentifier	(Ljava/lang/String;Ljava/lang/String;Ljava/lang/String;)I
    //   195: istore_2
    //   196: iload_2
    //   197: ifeq +6 -> 203
    //   200: goto +50 -> 250
    //   203: new 66	com/google/android/gms/internal/ads/zzgw
    //   206: dup
    //   207: ldc -62
    //   209: aconst_null
    //   210: sipush 2005
    //   213: invokespecial 98	com/google/android/gms/internal/ads/zzgw:<init>	(Ljava/lang/String;Ljava/lang/Throwable;I)V
    //   216: athrow
    //   217: new 66	com/google/android/gms/internal/ads/zzgw
    //   220: dup
    //   221: ldc -60
    //   223: aconst_null
    //   224: sipush 1004
    //   227: invokespecial 98	com/google/android/gms/internal/ads/zzgw:<init>	(Ljava/lang/String;Ljava/lang/Throwable;I)V
    //   230: athrow
    //   231: aload 9
    //   233: invokevirtual 139	android/net/Uri:getLastPathSegment	()Ljava/lang/String;
    //   236: astore 7
    //   238: aload 7
    //   240: invokestatic 145	java/util/Objects:requireNonNull	(Ljava/lang/Object;)Ljava/lang/Object;
    //   243: pop
    //   244: aload 7
    //   246: invokestatic 202	java/lang/Integer:parseInt	(Ljava/lang/String;)I
    //   249: istore_2
    //   250: aload_0
    //   251: aload_1
    //   252: invokevirtual 206	com/google/android/gms/internal/ads/zzfr:zzi	(Lcom/google/android/gms/internal/ads/zzgc;)V
    //   255: aload_0
    //   256: getfield 31	com/google/android/gms/internal/ads/zzgx:zza	Landroid/content/res/Resources;
    //   259: iload_2
    //   260: invokevirtual 210	android/content/res/Resources:openRawResourceFd	(I)Landroid/content/res/AssetFileDescriptor;
    //   263: astore 7
    //   265: aload_0
    //   266: aload 7
    //   268: putfield 212	com/google/android/gms/internal/ads/zzgx:zzd	Landroid/content/res/AssetFileDescriptor;
    //   271: aload 7
    //   273: ifnull +308 -> 581
    //   276: aload 7
    //   278: invokevirtual 218	android/content/res/AssetFileDescriptor:getLength	()J
    //   281: lstore_3
    //   282: new 220	java/io/FileInputStream
    //   285: dup
    //   286: aload 7
    //   288: invokevirtual 224	android/content/res/AssetFileDescriptor:getFileDescriptor	()Ljava/io/FileDescriptor;
    //   291: invokespecial 227	java/io/FileInputStream:<init>	(Ljava/io/FileDescriptor;)V
    //   294: astore 8
    //   296: aload_0
    //   297: aload 8
    //   299: putfield 80	com/google/android/gms/internal/ads/zzgx:zze	Ljava/io/InputStream;
    //   302: lload_3
    //   303: ldc2_w 71
    //   306: lcmp
    //   307: istore_2
    //   308: iload_2
    //   309: ifeq +30 -> 339
    //   312: aload_1
    //   313: getfield 228	com/google/android/gms/internal/ads/zzgc:zzf	J
    //   316: lload_3
    //   317: lcmp
    //   318: ifgt +6 -> 324
    //   321: goto +18 -> 339
    //   324: new 66	com/google/android/gms/internal/ads/zzgw
    //   327: astore_1
    //   328: aload_1
    //   329: aconst_null
    //   330: aconst_null
    //   331: sipush 2008
    //   334: invokespecial 98	com/google/android/gms/internal/ads/zzgw:<init>	(Ljava/lang/String;Ljava/lang/Throwable;I)V
    //   337: aload_1
    //   338: athrow
    //   339: aload 7
    //   341: invokevirtual 231	android/content/res/AssetFileDescriptor:getStartOffset	()J
    //   344: lstore 5
    //   346: aload 8
    //   348: aload_1
    //   349: getfield 228	com/google/android/gms/internal/ads/zzgc:zzf	J
    //   352: lload 5
    //   354: ladd
    //   355: invokevirtual 235	java/io/FileInputStream:skip	(J)J
    //   358: lload 5
    //   360: lsub
    //   361: lstore 5
    //   363: lload 5
    //   365: aload_1
    //   366: getfield 228	com/google/android/gms/internal/ads/zzgc:zzf	J
    //   369: lcmp
    //   370: ifne +179 -> 549
    //   373: iload_2
    //   374: ifne +75 -> 449
    //   377: aload 8
    //   379: invokevirtual 239	java/io/FileInputStream:getChannel	()Ljava/nio/channels/FileChannel;
    //   382: astore 7
    //   384: aload 7
    //   386: invokevirtual 243	java/nio/channels/FileChannel:size	()J
    //   389: lconst_0
    //   390: lcmp
    //   391: ifne +17 -> 408
    //   394: aload_0
    //   395: ldc2_w 71
    //   398: putfield 70	com/google/android/gms/internal/ads/zzgx:zzf	J
    //   401: ldc2_w 71
    //   404: lstore_3
    //   405: goto +60 -> 465
    //   408: aload 7
    //   410: invokevirtual 243	java/nio/channels/FileChannel:size	()J
    //   413: aload 7
    //   415: invokevirtual 246	java/nio/channels/FileChannel:position	()J
    //   418: lsub
    //   419: lstore_3
    //   420: aload_0
    //   421: lload_3
    //   422: putfield 70	com/google/android/gms/internal/ads/zzgx:zzf	J
    //   425: lload_3
    //   426: lconst_0
    //   427: lcmp
    //   428: iflt +6 -> 434
    //   431: goto +34 -> 465
    //   434: new 66	com/google/android/gms/internal/ads/zzgw
    //   437: astore_1
    //   438: aload_1
    //   439: aconst_null
    //   440: aconst_null
    //   441: sipush 2008
    //   444: invokespecial 98	com/google/android/gms/internal/ads/zzgw:<init>	(Ljava/lang/String;Ljava/lang/Throwable;I)V
    //   447: aload_1
    //   448: athrow
    //   449: lload_3
    //   450: lload 5
    //   452: lsub
    //   453: lstore_3
    //   454: aload_0
    //   455: lload_3
    //   456: putfield 70	com/google/android/gms/internal/ads/zzgx:zzf	J
    //   459: lload_3
    //   460: lconst_0
    //   461: lcmp
    //   462: iflt +74 -> 536
    //   465: aload_1
    //   466: getfield 248	com/google/android/gms/internal/ads/zzgc:zzg	J
    //   469: lstore 5
    //   471: lload 5
    //   473: ldc2_w 71
    //   476: lcmp
    //   477: ifeq +29 -> 506
    //   480: lload_3
    //   481: ldc2_w 71
    //   484: lcmp
    //   485: ifne +9 -> 494
    //   488: lload 5
    //   490: lstore_3
    //   491: goto +10 -> 501
    //   494: lload_3
    //   495: lload 5
    //   497: invokestatic 78	java/lang/Math:min	(JJ)J
    //   500: lstore_3
    //   501: aload_0
    //   502: lload_3
    //   503: putfield 70	com/google/android/gms/internal/ads/zzgx:zzf	J
    //   506: aload_0
    //   507: iconst_1
    //   508: putfield 250	com/google/android/gms/internal/ads/zzgx:zzg	Z
    //   511: aload_0
    //   512: aload_1
    //   513: invokevirtual 253	com/google/android/gms/internal/ads/zzfr:zzj	(Lcom/google/android/gms/internal/ads/zzgc;)V
    //   516: aload_1
    //   517: getfield 248	com/google/android/gms/internal/ads/zzgc:zzg	J
    //   520: lstore_3
    //   521: lload_3
    //   522: ldc2_w 71
    //   525: lcmp
    //   526: ifeq +5 -> 531
    //   529: lload_3
    //   530: lreturn
    //   531: aload_0
    //   532: getfield 70	com/google/android/gms/internal/ads/zzgx:zzf	J
    //   535: lreturn
    //   536: new 255	com/google/android/gms/internal/ads/zzfy
    //   539: astore_1
    //   540: aload_1
    //   541: sipush 2008
    //   544: invokespecial 257	com/google/android/gms/internal/ads/zzfy:<init>	(I)V
    //   547: aload_1
    //   548: athrow
    //   549: new 66	com/google/android/gms/internal/ads/zzgw
    //   552: astore_1
    //   553: aload_1
    //   554: aconst_null
    //   555: aconst_null
    //   556: sipush 2008
    //   559: invokespecial 98	com/google/android/gms/internal/ads/zzgw:<init>	(Ljava/lang/String;Ljava/lang/Throwable;I)V
    //   562: aload_1
    //   563: athrow
    //   564: astore_1
    //   565: new 66	com/google/android/gms/internal/ads/zzgw
    //   568: dup
    //   569: aconst_null
    //   570: aload_1
    //   571: sipush 2000
    //   574: invokespecial 98	com/google/android/gms/internal/ads/zzgw:<init>	(Ljava/lang/String;Ljava/lang/Throwable;I)V
    //   577: athrow
    //   578: astore_1
    //   579: aload_1
    //   580: athrow
    //   581: new 66	com/google/android/gms/internal/ads/zzgw
    //   584: dup
    //   585: ldc_w 259
    //   588: aload 9
    //   590: invokestatic 178	java/lang/String:valueOf	(Ljava/lang/Object;)Ljava/lang/String;
    //   593: invokestatic 178	java/lang/String:valueOf	(Ljava/lang/Object;)Ljava/lang/String;
    //   596: invokevirtual 184	java/lang/String:concat	(Ljava/lang/String;)Ljava/lang/String;
    //   599: aconst_null
    //   600: sipush 2000
    //   603: invokespecial 98	com/google/android/gms/internal/ads/zzgw:<init>	(Ljava/lang/String;Ljava/lang/Throwable;I)V
    //   606: athrow
    //   607: astore_1
    //   608: new 66	com/google/android/gms/internal/ads/zzgw
    //   611: dup
    //   612: aconst_null
    //   613: aload_1
    //   614: sipush 2005
    //   617: invokespecial 98	com/google/android/gms/internal/ads/zzgw:<init>	(Ljava/lang/String;Ljava/lang/Throwable;I)V
    //   620: athrow
    //   621: astore_1
    //   622: new 66	com/google/android/gms/internal/ads/zzgw
    //   625: dup
    //   626: ldc_w 261
    //   629: aconst_null
    //   630: sipush 1004
    //   633: invokespecial 98	com/google/android/gms/internal/ads/zzgw:<init>	(Ljava/lang/String;Ljava/lang/Throwable;I)V
    //   636: athrow
    // Local variable table:
    //   start	length	slot	name	signature
    //   0	637	0	this	zzgx
    //   0	637	1	paramzzgc	zzgc
    //   195	65	2	i	int
    //   307	67	2	bool	boolean
    //   281	249	3	l1	long
    //   344	152	5	l2	long
    //   57	357	7	localObject1	Object
    //   96	282	8	localObject2	Object
    //   4	585	9	localUri	Uri
    //   177	14	10	str1	String
    //   165	19	11	str2	String
    // Exception table:
    //   from	to	target	type
    //   312	321	564	java/io/IOException
    //   324	339	564	java/io/IOException
    //   339	373	564	java/io/IOException
    //   377	401	564	java/io/IOException
    //   408	425	564	java/io/IOException
    //   434	449	564	java/io/IOException
    //   454	459	564	java/io/IOException
    //   536	549	564	java/io/IOException
    //   549	564	564	java/io/IOException
    //   312	321	578	com/google/android/gms/internal/ads/zzgw
    //   324	339	578	com/google/android/gms/internal/ads/zzgw
    //   339	373	578	com/google/android/gms/internal/ads/zzgw
    //   377	401	578	com/google/android/gms/internal/ads/zzgw
    //   408	425	578	com/google/android/gms/internal/ads/zzgw
    //   434	449	578	com/google/android/gms/internal/ads/zzgw
    //   454	459	578	com/google/android/gms/internal/ads/zzgw
    //   536	549	578	com/google/android/gms/internal/ads/zzgw
    //   549	564	578	com/google/android/gms/internal/ads/zzgw
    //   255	265	607	android/content/res/Resources$NotFoundException
    //   231	238	621	java/lang/NumberFormatException
    //   244	250	621	java/lang/NumberFormatException
  }
  
  public final Uri zzc()
  {
    return this.zzc;
  }
  
  /* Error */
  public final void zzd()
    throws zzgw
  {
    // Byte code:
    //   0: aload_0
    //   1: aconst_null
    //   2: putfield 113	com/google/android/gms/internal/ads/zzgx:zzc	Landroid/net/Uri;
    //   5: aload_0
    //   6: getfield 80	com/google/android/gms/internal/ads/zzgx:zze	Ljava/io/InputStream;
    //   9: astore_1
    //   10: aload_1
    //   11: ifnull +7 -> 18
    //   14: aload_1
    //   15: invokevirtual 265	java/io/InputStream:close	()V
    //   18: aload_0
    //   19: aconst_null
    //   20: putfield 80	com/google/android/gms/internal/ads/zzgx:zze	Ljava/io/InputStream;
    //   23: aload_0
    //   24: getfield 212	com/google/android/gms/internal/ads/zzgx:zzd	Landroid/content/res/AssetFileDescriptor;
    //   27: astore_1
    //   28: aload_1
    //   29: ifnull +7 -> 36
    //   32: aload_1
    //   33: invokevirtual 266	android/content/res/AssetFileDescriptor:close	()V
    //   36: aload_0
    //   37: aconst_null
    //   38: putfield 212	com/google/android/gms/internal/ads/zzgx:zzd	Landroid/content/res/AssetFileDescriptor;
    //   41: aload_0
    //   42: getfield 250	com/google/android/gms/internal/ads/zzgx:zzg	Z
    //   45: ifeq +12 -> 57
    //   48: aload_0
    //   49: iconst_0
    //   50: putfield 250	com/google/android/gms/internal/ads/zzgx:zzg	Z
    //   53: aload_0
    //   54: invokevirtual 269	com/google/android/gms/internal/ads/zzfr:zzh	()V
    //   57: return
    //   58: astore_1
    //   59: goto +19 -> 78
    //   62: astore_1
    //   63: new 66	com/google/android/gms/internal/ads/zzgw
    //   66: astore_2
    //   67: aload_2
    //   68: aconst_null
    //   69: aload_1
    //   70: sipush 2000
    //   73: invokespecial 98	com/google/android/gms/internal/ads/zzgw:<init>	(Ljava/lang/String;Ljava/lang/Throwable;I)V
    //   76: aload_2
    //   77: athrow
    //   78: aload_0
    //   79: aconst_null
    //   80: putfield 212	com/google/android/gms/internal/ads/zzgx:zzd	Landroid/content/res/AssetFileDescriptor;
    //   83: aload_0
    //   84: getfield 250	com/google/android/gms/internal/ads/zzgx:zzg	Z
    //   87: ifeq +12 -> 99
    //   90: aload_0
    //   91: iconst_0
    //   92: putfield 250	com/google/android/gms/internal/ads/zzgx:zzg	Z
    //   95: aload_0
    //   96: invokevirtual 269	com/google/android/gms/internal/ads/zzfr:zzh	()V
    //   99: aload_1
    //   100: athrow
    //   101: astore_2
    //   102: goto +19 -> 121
    //   105: astore_2
    //   106: new 66	com/google/android/gms/internal/ads/zzgw
    //   109: astore_1
    //   110: aload_1
    //   111: aconst_null
    //   112: aload_2
    //   113: sipush 2000
    //   116: invokespecial 98	com/google/android/gms/internal/ads/zzgw:<init>	(Ljava/lang/String;Ljava/lang/Throwable;I)V
    //   119: aload_1
    //   120: athrow
    //   121: aload_0
    //   122: aconst_null
    //   123: putfield 80	com/google/android/gms/internal/ads/zzgx:zze	Ljava/io/InputStream;
    //   126: aload_0
    //   127: getfield 212	com/google/android/gms/internal/ads/zzgx:zzd	Landroid/content/res/AssetFileDescriptor;
    //   130: astore_1
    //   131: aload_1
    //   132: ifnull +7 -> 139
    //   135: aload_1
    //   136: invokevirtual 266	android/content/res/AssetFileDescriptor:close	()V
    //   139: aload_0
    //   140: aconst_null
    //   141: putfield 212	com/google/android/gms/internal/ads/zzgx:zzd	Landroid/content/res/AssetFileDescriptor;
    //   144: aload_0
    //   145: getfield 250	com/google/android/gms/internal/ads/zzgx:zzg	Z
    //   148: ifeq +12 -> 160
    //   151: aload_0
    //   152: iconst_0
    //   153: putfield 250	com/google/android/gms/internal/ads/zzgx:zzg	Z
    //   156: aload_0
    //   157: invokevirtual 269	com/google/android/gms/internal/ads/zzfr:zzh	()V
    //   160: aload_2
    //   161: athrow
    //   162: astore_1
    //   163: goto +19 -> 182
    //   166: astore_2
    //   167: new 66	com/google/android/gms/internal/ads/zzgw
    //   170: astore_1
    //   171: aload_1
    //   172: aconst_null
    //   173: aload_2
    //   174: sipush 2000
    //   177: invokespecial 98	com/google/android/gms/internal/ads/zzgw:<init>	(Ljava/lang/String;Ljava/lang/Throwable;I)V
    //   180: aload_1
    //   181: athrow
    //   182: aload_0
    //   183: aconst_null
    //   184: putfield 212	com/google/android/gms/internal/ads/zzgx:zzd	Landroid/content/res/AssetFileDescriptor;
    //   187: aload_0
    //   188: getfield 250	com/google/android/gms/internal/ads/zzgx:zzg	Z
    //   191: ifne +6 -> 197
    //   194: goto +12 -> 206
    //   197: aload_0
    //   198: iconst_0
    //   199: putfield 250	com/google/android/gms/internal/ads/zzgx:zzg	Z
    //   202: aload_0
    //   203: invokevirtual 269	com/google/android/gms/internal/ads/zzfr:zzh	()V
    //   206: aload_1
    //   207: athrow
    // Local variable table:
    //   start	length	slot	name	signature
    //   0	208	0	this	zzgx
    //   9	24	1	localObject1	Object
    //   58	1	1	localObject2	Object
    //   62	38	1	localIOException1	IOException
    //   109	27	1	localObject3	Object
    //   162	1	1	localObject4	Object
    //   170	37	1	localzzgw1	zzgw
    //   66	11	2	localzzgw2	zzgw
    //   101	1	2	localObject5	Object
    //   105	56	2	localIOException2	IOException
    //   166	8	2	localIOException3	IOException
    // Exception table:
    //   from	to	target	type
    //   23	28	58	finally
    //   32	36	58	finally
    //   63	78	58	finally
    //   23	28	62	java/io/IOException
    //   32	36	62	java/io/IOException
    //   5	10	101	finally
    //   14	18	101	finally
    //   106	121	101	finally
    //   5	10	105	java/io/IOException
    //   14	18	105	java/io/IOException
    //   126	131	162	finally
    //   135	139	162	finally
    //   167	182	162	finally
    //   126	131	166	java/io/IOException
    //   135	139	166	java/io/IOException
  }
}


/* Location:              C:\Users\Ria\Documents\slope apk\dex-tools-v2.4\classes-dex2jar.jar!\com\google\android\gms\internal\ads\zzgx.class
 * Java compiler version: 6 (50.0)
 * JD-Core Version:       0.7.1
 */