package com.google.android.gms.internal.ads;

import android.os.Handler.Callback;
import android.os.HandlerThread;
import android.os.Looper;
import android.os.SystemClock;
import android.util.Pair;
import java.io.IOException;
import java.util.ArrayList;
import java.util.Collections;
import java.util.IdentityHashMap;
import java.util.List;
import java.util.Set;

final class zzkd
  implements Handler.Callback, zzti, zzxc, zzkw, zzhx, zzkz
{
  private boolean zzA;
  private int zzB;
  private boolean zzC;
  private boolean zzD;
  private boolean zzE;
  private boolean zzF;
  private int zzG;
  private zzkc zzH;
  private long zzI;
  private int zzJ;
  private boolean zzK;
  private zzia zzL;
  private long zzM;
  private final zzjg zzN;
  private final zzhv zzO;
  private final zzle[] zza;
  private final Set zzb;
  private final zzlf[] zzc;
  private final zzxd zzd;
  private final zzxe zze;
  private final zzkg zzf;
  private final zzxl zzg;
  private final zzei zzh;
  private final HandlerThread zzi;
  private final Looper zzj;
  private final zzcw zzk;
  private final zzcu zzl;
  private final long zzm;
  private final zzhy zzn;
  private final ArrayList zzo;
  private final zzdz zzp;
  private final zzkl zzq;
  private final zzkx zzr;
  private final long zzs;
  private zzlh zzt;
  private zzky zzu;
  private zzkb zzv;
  private boolean zzw;
  private boolean zzx;
  private boolean zzy;
  private boolean zzz;
  
  public zzkd(zzle[] paramArrayOfzzle, zzxd paramzzxd, zzxe paramzzxe, zzkg paramzzkg, zzxl paramzzxl, int paramInt, boolean paramBoolean1, zzls paramzzls, zzlh paramzzlh, zzhv paramzzhv, long paramLong, boolean paramBoolean2, Looper paramLooper1, zzdz paramzzdz, zzjg paramzzjg, zzof paramzzof, Looper paramLooper2)
  {
    this.zzN = paramzzjg;
    this.zza = paramArrayOfzzle;
    this.zzd = paramzzxd;
    this.zze = paramzzxe;
    this.zzf = paramzzkg;
    this.zzg = paramzzxl;
    paramInt = 0;
    this.zzB = 0;
    this.zzC = false;
    this.zzt = paramzzlh;
    this.zzO = paramzzhv;
    this.zzs = paramLong;
    this.zzx = false;
    this.zzp = paramzzdz;
    this.zzM = -9223372036854775807L;
    this.zzm = paramzzkg.zza();
    paramzzkg.zzf();
    paramzzxe = zzky.zzi(paramzzxe);
    this.zzu = paramzzxe;
    this.zzv = new zzkb(paramzzxe);
    int i = paramArrayOfzzle.length;
    this.zzc = new zzlf[2];
    for (;;)
    {
      i = paramArrayOfzzle.length;
      if (paramInt >= 2) {
        break;
      }
      paramArrayOfzzle[paramInt].zzr(paramInt, paramzzof);
      this.zzc[paramInt] = paramArrayOfzzle[paramInt].zzj();
      paramInt++;
    }
    this.zzn = new zzhy(this, paramzzdz);
    this.zzo = new ArrayList();
    this.zzb = Collections.newSetFromMap(new IdentityHashMap());
    this.zzk = new zzcw();
    this.zzl = new zzcu();
    paramzzxd.zzq(this, paramzzxl);
    this.zzK = true;
    paramArrayOfzzle = paramzzdz.zzb(paramLooper1, null);
    this.zzq = new zzkl(paramzzls, paramArrayOfzzle);
    this.zzr = new zzkx(this, paramzzls, paramArrayOfzzle, paramzzof);
    paramArrayOfzzle = new HandlerThread("ExoPlayer:Playback", -16);
    this.zzi = paramArrayOfzzle;
    paramArrayOfzzle.start();
    paramArrayOfzzle = paramArrayOfzzle.getLooper();
    this.zzj = paramArrayOfzzle;
    this.zzh = paramzzdz.zzb(paramArrayOfzzle, this);
  }
  
  private final void zzA(zzle paramzzle)
    throws zzia
  {
    if (!zzad(paramzzle)) {
      return;
    }
    this.zzn.zzd(paramzzle);
    zzak(paramzzle);
    paramzzle.zzo();
    this.zzG -= 1;
  }
  
  private final void zzB()
    throws zzia
  {
    int i = this.zza.length;
    zzC(new boolean[2]);
  }
  
  private final void zzC(boolean[] paramArrayOfBoolean)
    throws zzia
  {
    zzki localzzki1 = this.zzq.zze();
    zzxe localzzxe = localzzki1.zzi();
    int j;
    for (int i = 0;; i++)
    {
      j = this.zza.length;
      if (i >= 2) {
        break;
      }
      if ((!localzzxe.zzb(i)) && (this.zzb.remove(this.zza[i]))) {
        this.zza[i].zzC();
      }
    }
    for (i = 0;; i++)
    {
      j = this.zza.length;
      if (i >= 2) {
        break;
      }
      if (localzzxe.zzb(i))
      {
        int k = paramArrayOfBoolean[i];
        zzle localzzle = this.zza[i];
        if (!zzad(localzzle))
        {
          zzki localzzki2 = this.zzq.zze();
          boolean bool;
          if (localzzki2 == this.zzq.zzd()) {
            bool = true;
          } else {
            bool = false;
          }
          Object localObject = localzzki2.zzi();
          zzlg localzzlg = localObject.zzb[i];
          localObject = zzai(localObject.zzc[i]);
          if ((zzag()) && (this.zzu.zze == 3)) {
            j = 1;
          } else {
            j = 0;
          }
          if ((k == 0) && (j != 0)) {
            k = 1;
          } else {
            k = 0;
          }
          this.zzG += 1;
          this.zzb.add(localzzle);
          localzzle.zzp(localzzlg, (zzam[])localObject, localzzki2.zzc[i], this.zzI, k, bool, localzzki2.zzf(), localzzki2.zze());
          localzzle.zzq(11, new zzjw(this));
          this.zzn.zze(localzzle);
          if (j != 0) {
            localzzle.zzG();
          }
        }
      }
    }
    localzzki1.zzg = true;
  }
  
  private final void zzD(IOException paramIOException, int paramInt)
  {
    zzia localzzia = zzia.zzc(paramIOException, paramInt);
    zzki localzzki = this.zzq.zzd();
    paramIOException = localzzia;
    if (localzzki != null) {
      paramIOException = localzzia.zza(localzzki.zzf.zza);
    }
    zzer.zzc("ExoPlayerImplInternal", "Playback error", paramIOException);
    zzV(false, false);
    this.zzu = this.zzu.zzf(paramIOException);
  }
  
  private final void zzE(boolean paramBoolean)
  {
    zzki localzzki = this.zzq.zzc();
    if (localzzki == null) {
      localObject = this.zzu.zzb;
    } else {
      localObject = localzzki.zzf.zza;
    }
    boolean bool = this.zzu.zzk.equals(localObject) ^ true;
    if (bool) {
      this.zzu = this.zzu.zzc((zztl)localObject);
    }
    Object localObject = this.zzu;
    long l;
    if (localzzki == null) {
      l = ((zzky)localObject).zzr;
    } else {
      l = localzzki.zzc();
    }
    ((zzky)localObject).zzp = l;
    this.zzu.zzq = zzt();
    if (((bool) || (paramBoolean)) && (localzzki != null) && (localzzki.zzd)) {
      zzY(localzzki.zzf.zza, localzzki.zzh(), localzzki.zzi());
    }
  }
  
  /* Error */
  private final void zzF(zzcx paramzzcx, boolean paramBoolean)
    throws zzia
  {
    // Byte code:
    //   0: aload_0
    //   1: getfield 136	com/google/android/gms/internal/ads/zzkd:zzu	Lcom/google/android/gms/internal/ads/zzky;
    //   4: astore 26
    //   6: aload_0
    //   7: getfield 390	com/google/android/gms/internal/ads/zzkd:zzH	Lcom/google/android/gms/internal/ads/zzkc;
    //   10: astore 29
    //   12: aload_0
    //   13: getfield 207	com/google/android/gms/internal/ads/zzkd:zzq	Lcom/google/android/gms/internal/ads/zzkl;
    //   16: astore 24
    //   18: aload_0
    //   19: getfield 103	com/google/android/gms/internal/ads/zzkd:zzB	I
    //   22: istore_3
    //   23: aload_0
    //   24: getfield 105	com/google/android/gms/internal/ads/zzkd:zzC	Z
    //   27: istore 8
    //   29: aload_0
    //   30: getfield 183	com/google/android/gms/internal/ads/zzkd:zzk	Lcom/google/android/gms/internal/ads/zzcw;
    //   33: astore 27
    //   35: aload_0
    //   36: getfield 188	com/google/android/gms/internal/ads/zzkd:zzl	Lcom/google/android/gms/internal/ads/zzcu;
    //   39: astore 25
    //   41: aload_1
    //   42: invokevirtual 394	com/google/android/gms/internal/ads/zzcx:zzo	()Z
    //   45: istore 9
    //   47: ldc2_w 116
    //   50: lstore 18
    //   52: iconst_1
    //   53: istore 6
    //   55: iload 9
    //   57: ifeq +24 -> 81
    //   60: invokestatic 397	com/google/android/gms/internal/ads/zzky:zzj	()Lcom/google/android/gms/internal/ads/zztl;
    //   63: astore 23
    //   65: ldc2_w 116
    //   68: lstore 16
    //   70: iconst_0
    //   71: istore 8
    //   73: iconst_0
    //   74: istore_3
    //   75: lconst_0
    //   76: lstore 10
    //   78: goto +808 -> 886
    //   81: aload 26
    //   83: getfield 358	com/google/android/gms/internal/ads/zzky:zzb	Lcom/google/android/gms/internal/ads/zztl;
    //   86: astore 23
    //   88: aload 23
    //   90: getfield 402	com/google/android/gms/internal/ads/zztl:zza	Ljava/lang/Object;
    //   93: astore 22
    //   95: aload 26
    //   97: aload 25
    //   99: invokestatic 406	com/google/android/gms/internal/ads/zzkd:zzaf	(Lcom/google/android/gms/internal/ads/zzky;Lcom/google/android/gms/internal/ads/zzcu;)Z
    //   102: istore 9
    //   104: aload 26
    //   106: getfield 358	com/google/android/gms/internal/ads/zzky:zzb	Lcom/google/android/gms/internal/ads/zztl;
    //   109: invokevirtual 408	com/google/android/gms/internal/ads/zzbx:zzb	()Z
    //   112: ifne +21 -> 133
    //   115: iload 9
    //   117: ifeq +6 -> 123
    //   120: goto +13 -> 133
    //   123: aload 26
    //   125: getfield 370	com/google/android/gms/internal/ads/zzky:zzr	J
    //   128: lstore 10
    //   130: goto +10 -> 140
    //   133: aload 26
    //   135: getfield 410	com/google/android/gms/internal/ads/zzky:zzc	J
    //   138: lstore 10
    //   140: aload 29
    //   142: ifnull +139 -> 281
    //   145: aload_1
    //   146: aload 29
    //   148: iconst_1
    //   149: iload_3
    //   150: iload 8
    //   152: aload 27
    //   154: aload 25
    //   156: invokestatic 413	com/google/android/gms/internal/ads/zzkd:zzy	(Lcom/google/android/gms/internal/ads/zzcx;Lcom/google/android/gms/internal/ads/zzkc;ZIZLcom/google/android/gms/internal/ads/zzcw;Lcom/google/android/gms/internal/ads/zzcu;)Landroid/util/Pair;
    //   159: astore 28
    //   161: aload 28
    //   163: ifnonnull +26 -> 189
    //   166: aload_1
    //   167: iload 8
    //   169: invokevirtual 416	com/google/android/gms/internal/ads/zzcx:zzg	(Z)I
    //   172: istore 5
    //   174: lload 10
    //   176: lstore 12
    //   178: iconst_1
    //   179: istore_3
    //   180: iconst_0
    //   181: istore 8
    //   183: iconst_0
    //   184: istore 4
    //   186: goto +92 -> 278
    //   189: aload 29
    //   191: getfield 419	com/google/android/gms/internal/ads/zzkc:zzc	J
    //   194: ldc2_w 116
    //   197: lcmp
    //   198: ifne +28 -> 226
    //   201: aload_1
    //   202: aload 28
    //   204: getfield 424	android/util/Pair:first	Ljava/lang/Object;
    //   207: aload 25
    //   209: invokevirtual 427	com/google/android/gms/internal/ads/zzcx:zzn	(Ljava/lang/Object;Lcom/google/android/gms/internal/ads/zzcu;)Lcom/google/android/gms/internal/ads/zzcu;
    //   212: getfield 429	com/google/android/gms/internal/ads/zzcu:zzd	I
    //   215: istore_3
    //   216: lload 10
    //   218: lstore 12
    //   220: iconst_0
    //   221: istore 4
    //   223: goto +28 -> 251
    //   226: aload 28
    //   228: getfield 424	android/util/Pair:first	Ljava/lang/Object;
    //   231: astore 22
    //   233: aload 28
    //   235: getfield 432	android/util/Pair:second	Ljava/lang/Object;
    //   238: checkcast 434	java/lang/Long
    //   241: invokevirtual 437	java/lang/Long:longValue	()J
    //   244: lstore 12
    //   246: iconst_1
    //   247: istore 4
    //   249: iconst_m1
    //   250: istore_3
    //   251: aload 26
    //   253: getfield 293	com/google/android/gms/internal/ads/zzky:zze	I
    //   256: iconst_4
    //   257: if_icmpne +9 -> 266
    //   260: iconst_1
    //   261: istore 8
    //   263: goto +6 -> 269
    //   266: iconst_0
    //   267: istore 8
    //   269: iconst_0
    //   270: istore 6
    //   272: iload_3
    //   273: istore 5
    //   275: iload 6
    //   277: istore_3
    //   278: goto +273 -> 551
    //   281: aload 26
    //   283: getfield 440	com/google/android/gms/internal/ads/zzky:zza	Lcom/google/android/gms/internal/ads/zzcx;
    //   286: invokevirtual 394	com/google/android/gms/internal/ads/zzcx:zzo	()Z
    //   289: ifeq +28 -> 317
    //   292: aload_1
    //   293: iload 8
    //   295: invokevirtual 416	com/google/android/gms/internal/ads/zzcx:zzg	(Z)I
    //   298: istore_3
    //   299: iload_3
    //   300: istore 5
    //   302: lload 10
    //   304: lstore 12
    //   306: iconst_0
    //   307: istore 8
    //   309: iconst_0
    //   310: istore_3
    //   311: iconst_0
    //   312: istore 4
    //   314: goto +237 -> 551
    //   317: aload_1
    //   318: aload 22
    //   320: invokevirtual 443	com/google/android/gms/internal/ads/zzcx:zza	(Ljava/lang/Object;)I
    //   323: iconst_m1
    //   324: if_icmpne +77 -> 401
    //   327: aload 27
    //   329: aload 25
    //   331: iload_3
    //   332: iload 8
    //   334: aload 22
    //   336: aload 26
    //   338: getfield 440	com/google/android/gms/internal/ads/zzky:zza	Lcom/google/android/gms/internal/ads/zzcx;
    //   341: aload_1
    //   342: invokestatic 446	com/google/android/gms/internal/ads/zzkd:zze	(Lcom/google/android/gms/internal/ads/zzcw;Lcom/google/android/gms/internal/ads/zzcu;IZLjava/lang/Object;Lcom/google/android/gms/internal/ads/zzcx;Lcom/google/android/gms/internal/ads/zzcx;)Ljava/lang/Object;
    //   345: astore 28
    //   347: aload 28
    //   349: ifnonnull +16 -> 365
    //   352: aload_1
    //   353: iload 8
    //   355: invokevirtual 416	com/google/android/gms/internal/ads/zzcx:zzg	(Z)I
    //   358: istore 4
    //   360: iconst_1
    //   361: istore_3
    //   362: goto +18 -> 380
    //   365: aload_1
    //   366: aload 28
    //   368: aload 25
    //   370: invokevirtual 427	com/google/android/gms/internal/ads/zzcx:zzn	(Ljava/lang/Object;Lcom/google/android/gms/internal/ads/zzcu;)Lcom/google/android/gms/internal/ads/zzcu;
    //   373: getfield 429	com/google/android/gms/internal/ads/zzcu:zzd	I
    //   376: istore 4
    //   378: iconst_0
    //   379: istore_3
    //   380: lload 10
    //   382: lstore 12
    //   384: iconst_0
    //   385: istore 8
    //   387: iconst_0
    //   388: istore 6
    //   390: iload 4
    //   392: istore 5
    //   394: iload 6
    //   396: istore 4
    //   398: goto -120 -> 278
    //   401: lload 10
    //   403: ldc2_w 116
    //   406: lcmp
    //   407: ifne +18 -> 425
    //   410: aload_1
    //   411: aload 22
    //   413: aload 25
    //   415: invokevirtual 427	com/google/android/gms/internal/ads/zzcx:zzn	(Ljava/lang/Object;Lcom/google/android/gms/internal/ads/zzcu;)Lcom/google/android/gms/internal/ads/zzcu;
    //   418: getfield 429	com/google/android/gms/internal/ads/zzcu:zzd	I
    //   421: istore_3
    //   422: goto -123 -> 299
    //   425: iload 9
    //   427: ifeq +118 -> 545
    //   430: aload 26
    //   432: getfield 440	com/google/android/gms/internal/ads/zzky:zza	Lcom/google/android/gms/internal/ads/zzcx;
    //   435: aload 23
    //   437: getfield 402	com/google/android/gms/internal/ads/zztl:zza	Ljava/lang/Object;
    //   440: aload 25
    //   442: invokevirtual 427	com/google/android/gms/internal/ads/zzcx:zzn	(Ljava/lang/Object;Lcom/google/android/gms/internal/ads/zzcu;)Lcom/google/android/gms/internal/ads/zzcu;
    //   445: pop
    //   446: aload 26
    //   448: getfield 440	com/google/android/gms/internal/ads/zzky:zza	Lcom/google/android/gms/internal/ads/zzcx;
    //   451: aload 25
    //   453: getfield 429	com/google/android/gms/internal/ads/zzcu:zzd	I
    //   456: aload 27
    //   458: lconst_0
    //   459: invokevirtual 449	com/google/android/gms/internal/ads/zzcx:zze	(ILcom/google/android/gms/internal/ads/zzcw;J)Lcom/google/android/gms/internal/ads/zzcw;
    //   462: getfield 451	com/google/android/gms/internal/ads/zzcw:zzo	I
    //   465: aload 26
    //   467: getfield 440	com/google/android/gms/internal/ads/zzky:zza	Lcom/google/android/gms/internal/ads/zzcx;
    //   470: aload 23
    //   472: getfield 402	com/google/android/gms/internal/ads/zztl:zza	Ljava/lang/Object;
    //   475: invokevirtual 443	com/google/android/gms/internal/ads/zzcx:zza	(Ljava/lang/Object;)I
    //   478: if_icmpne +49 -> 527
    //   481: aload_1
    //   482: aload 27
    //   484: aload 25
    //   486: aload_1
    //   487: aload 22
    //   489: aload 25
    //   491: invokevirtual 427	com/google/android/gms/internal/ads/zzcx:zzn	(Ljava/lang/Object;Lcom/google/android/gms/internal/ads/zzcu;)Lcom/google/android/gms/internal/ads/zzcu;
    //   494: getfield 429	com/google/android/gms/internal/ads/zzcu:zzd	I
    //   497: lload 10
    //   499: invokevirtual 454	com/google/android/gms/internal/ads/zzcx:zzl	(Lcom/google/android/gms/internal/ads/zzcw;Lcom/google/android/gms/internal/ads/zzcu;IJ)Landroid/util/Pair;
    //   502: astore 28
    //   504: aload 28
    //   506: getfield 424	android/util/Pair:first	Ljava/lang/Object;
    //   509: astore 22
    //   511: aload 28
    //   513: getfield 432	android/util/Pair:second	Ljava/lang/Object;
    //   516: checkcast 434	java/lang/Long
    //   519: invokevirtual 437	java/lang/Long:longValue	()J
    //   522: lstore 12
    //   524: goto +7 -> 531
    //   527: lload 10
    //   529: lstore 12
    //   531: iconst_m1
    //   532: istore 5
    //   534: iconst_0
    //   535: istore 8
    //   537: iconst_0
    //   538: istore_3
    //   539: iconst_1
    //   540: istore 4
    //   542: goto +9 -> 551
    //   545: iconst_m1
    //   546: istore 5
    //   548: goto -246 -> 302
    //   551: iload 5
    //   553: iconst_m1
    //   554: if_icmpeq +46 -> 600
    //   557: aload_1
    //   558: aload 27
    //   560: aload 25
    //   562: iload 5
    //   564: ldc2_w 116
    //   567: invokevirtual 454	com/google/android/gms/internal/ads/zzcx:zzl	(Lcom/google/android/gms/internal/ads/zzcw;Lcom/google/android/gms/internal/ads/zzcu;IJ)Landroid/util/Pair;
    //   570: astore 27
    //   572: aload 27
    //   574: getfield 424	android/util/Pair:first	Ljava/lang/Object;
    //   577: astore 22
    //   579: aload 27
    //   581: getfield 432	android/util/Pair:second	Ljava/lang/Object;
    //   584: checkcast 434	java/lang/Long
    //   587: invokevirtual 437	java/lang/Long:longValue	()J
    //   590: lstore 14
    //   592: ldc2_w 116
    //   595: lstore 12
    //   597: goto +7 -> 604
    //   600: lload 12
    //   602: lstore 14
    //   604: aload 24
    //   606: aload_1
    //   607: aload 22
    //   609: lload 14
    //   611: invokevirtual 457	com/google/android/gms/internal/ads/zzkl:zzh	(Lcom/google/android/gms/internal/ads/zzcx;Ljava/lang/Object;J)Lcom/google/android/gms/internal/ads/zztl;
    //   614: astore 24
    //   616: aload 24
    //   618: getfield 458	com/google/android/gms/internal/ads/zztl:zze	I
    //   621: istore 6
    //   623: iload 6
    //   625: iconst_m1
    //   626: if_icmpeq +32 -> 658
    //   629: aload 23
    //   631: getfield 458	com/google/android/gms/internal/ads/zztl:zze	I
    //   634: istore 5
    //   636: iload 5
    //   638: iconst_m1
    //   639: if_icmpeq +13 -> 652
    //   642: iload 6
    //   644: iload 5
    //   646: if_icmplt +6 -> 652
    //   649: goto +9 -> 658
    //   652: iconst_0
    //   653: istore 5
    //   655: goto +6 -> 661
    //   658: iconst_1
    //   659: istore 5
    //   661: aload 23
    //   663: getfield 402	com/google/android/gms/internal/ads/zztl:zza	Ljava/lang/Object;
    //   666: aload 22
    //   668: invokevirtual 459	java/lang/Object:equals	(Ljava/lang/Object;)Z
    //   671: ifeq +30 -> 701
    //   674: aload 23
    //   676: invokevirtual 408	com/google/android/gms/internal/ads/zzbx:zzb	()Z
    //   679: ifne +22 -> 701
    //   682: aload 24
    //   684: invokevirtual 408	com/google/android/gms/internal/ads/zzbx:zzb	()Z
    //   687: ifne +14 -> 701
    //   690: iload 5
    //   692: ifeq +9 -> 701
    //   695: iconst_1
    //   696: istore 5
    //   698: goto +6 -> 704
    //   701: iconst_0
    //   702: istore 5
    //   704: aload_1
    //   705: aload 22
    //   707: aload 25
    //   709: invokevirtual 427	com/google/android/gms/internal/ads/zzcx:zzn	(Ljava/lang/Object;Lcom/google/android/gms/internal/ads/zzcu;)Lcom/google/android/gms/internal/ads/zzcu;
    //   712: astore 22
    //   714: iload 9
    //   716: ifne +68 -> 784
    //   719: lload 10
    //   721: lload 12
    //   723: lcmp
    //   724: ifne +60 -> 784
    //   727: aload 23
    //   729: getfield 402	com/google/android/gms/internal/ads/zztl:zza	Ljava/lang/Object;
    //   732: aload 24
    //   734: getfield 402	com/google/android/gms/internal/ads/zztl:zza	Ljava/lang/Object;
    //   737: invokevirtual 459	java/lang/Object:equals	(Ljava/lang/Object;)Z
    //   740: ifne +6 -> 746
    //   743: goto +41 -> 784
    //   746: aload 23
    //   748: invokevirtual 408	com/google/android/gms/internal/ads/zzbx:zzb	()Z
    //   751: ifeq +14 -> 765
    //   754: aload 22
    //   756: aload 23
    //   758: getfield 461	com/google/android/gms/internal/ads/zztl:zzb	I
    //   761: invokevirtual 463	com/google/android/gms/internal/ads/zzcu:zzn	(I)Z
    //   764: pop
    //   765: aload 24
    //   767: invokevirtual 408	com/google/android/gms/internal/ads/zzbx:zzb	()Z
    //   770: ifeq +14 -> 784
    //   773: aload 22
    //   775: aload 24
    //   777: getfield 461	com/google/android/gms/internal/ads/zztl:zzb	I
    //   780: invokevirtual 463	com/google/android/gms/internal/ads/zzcu:zzn	(I)Z
    //   783: pop
    //   784: iconst_1
    //   785: iload 5
    //   787: if_icmpeq +10 -> 797
    //   790: aload 24
    //   792: astore 22
    //   794: goto +7 -> 801
    //   797: aload 23
    //   799: astore 22
    //   801: lload 14
    //   803: lstore 10
    //   805: aload 22
    //   807: invokevirtual 408	com/google/android/gms/internal/ads/zzbx:zzb	()Z
    //   810: ifeq +62 -> 872
    //   813: aload 22
    //   815: aload 23
    //   817: invokevirtual 365	com/google/android/gms/internal/ads/zzbx:equals	(Ljava/lang/Object;)Z
    //   820: ifeq +13 -> 833
    //   823: aload 26
    //   825: getfield 370	com/google/android/gms/internal/ads/zzky:zzr	J
    //   828: lstore 10
    //   830: goto +42 -> 872
    //   833: aload_1
    //   834: aload 22
    //   836: getfield 402	com/google/android/gms/internal/ads/zztl:zza	Ljava/lang/Object;
    //   839: aload 25
    //   841: invokevirtual 427	com/google/android/gms/internal/ads/zzcx:zzn	(Ljava/lang/Object;Lcom/google/android/gms/internal/ads/zzcu;)Lcom/google/android/gms/internal/ads/zzcu;
    //   844: pop
    //   845: aload 22
    //   847: getfield 465	com/google/android/gms/internal/ads/zztl:zzc	I
    //   850: aload 25
    //   852: aload 22
    //   854: getfield 461	com/google/android/gms/internal/ads/zztl:zzb	I
    //   857: invokevirtual 468	com/google/android/gms/internal/ads/zzcu:zze	(I)I
    //   860: if_icmpne +9 -> 869
    //   863: aload 25
    //   865: invokevirtual 470	com/google/android/gms/internal/ads/zzcu:zzj	()J
    //   868: pop2
    //   869: lconst_0
    //   870: lstore 10
    //   872: iload_3
    //   873: istore 6
    //   875: iload 4
    //   877: istore_3
    //   878: lload 12
    //   880: lstore 16
    //   882: aload 22
    //   884: astore 23
    //   886: aload_0
    //   887: getfield 136	com/google/android/gms/internal/ads/zzkd:zzu	Lcom/google/android/gms/internal/ads/zzky;
    //   890: getfield 358	com/google/android/gms/internal/ads/zzky:zzb	Lcom/google/android/gms/internal/ads/zztl;
    //   893: aload 23
    //   895: invokevirtual 365	com/google/android/gms/internal/ads/zzbx:equals	(Ljava/lang/Object;)Z
    //   898: ifeq +25 -> 923
    //   901: lload 10
    //   903: aload_0
    //   904: getfield 136	com/google/android/gms/internal/ads/zzkd:zzu	Lcom/google/android/gms/internal/ads/zzky;
    //   907: getfield 370	com/google/android/gms/internal/ads/zzky:zzr	J
    //   910: lcmp
    //   911: ifeq +6 -> 917
    //   914: goto +9 -> 923
    //   917: iconst_0
    //   918: istore 4
    //   920: goto +6 -> 926
    //   923: iconst_1
    //   924: istore 4
    //   926: iconst_3
    //   927: istore 5
    //   929: iload 6
    //   931: ifeq +38 -> 969
    //   934: aload_0
    //   935: getfield 136	com/google/android/gms/internal/ads/zzkd:zzu	Lcom/google/android/gms/internal/ads/zzky;
    //   938: getfield 293	com/google/android/gms/internal/ads/zzky:zze	I
    //   941: iconst_1
    //   942: if_icmpeq +11 -> 953
    //   945: aload_0
    //   946: iconst_4
    //   947: invokespecial 474	com/google/android/gms/internal/ads/zzkd:zzT	(I)V
    //   950: goto +3 -> 953
    //   953: aload_0
    //   954: iconst_0
    //   955: iconst_0
    //   956: iconst_0
    //   957: iconst_1
    //   958: invokespecial 477	com/google/android/gms/internal/ads/zzkd:zzL	(ZZZZ)V
    //   961: goto +8 -> 969
    //   964: astore 22
    //   966: goto +525 -> 1491
    //   969: iload 4
    //   971: ifne +209 -> 1180
    //   974: aload_0
    //   975: getfield 207	com/google/android/gms/internal/ads/zzkd:zzq	Lcom/google/android/gms/internal/ads/zzkl;
    //   978: astore 25
    //   980: aload_0
    //   981: getfield 301	com/google/android/gms/internal/ads/zzkd:zzI	J
    //   984: lstore 20
    //   986: aload 25
    //   988: invokevirtual 258	com/google/android/gms/internal/ads/zzkl:zze	()Lcom/google/android/gms/internal/ads/zzki;
    //   991: astore 22
    //   993: aload 22
    //   995: ifnonnull +9 -> 1004
    //   998: lconst_0
    //   999: lstore 12
    //   1001: goto +145 -> 1146
    //   1004: aload 22
    //   1006: invokevirtual 305	com/google/android/gms/internal/ads/zzki:zze	()J
    //   1009: lstore 14
    //   1011: aload 22
    //   1013: getfield 380	com/google/android/gms/internal/ads/zzki:zzd	Z
    //   1016: istore 8
    //   1018: lload 14
    //   1020: lstore 12
    //   1022: iload 8
    //   1024: ifeq +122 -> 1146
    //   1027: iconst_0
    //   1028: istore 6
    //   1030: aload_0
    //   1031: getfield 93	com/google/android/gms/internal/ads/zzkd:zza	[Lcom/google/android/gms/internal/ads/zzle;
    //   1034: astore 24
    //   1036: aload 24
    //   1038: arraylength
    //   1039: istore 7
    //   1041: lload 14
    //   1043: lstore 12
    //   1045: iload 6
    //   1047: iconst_2
    //   1048: if_icmpge +98 -> 1146
    //   1051: lload 14
    //   1053: lstore 12
    //   1055: aload 24
    //   1057: iload 6
    //   1059: aaload
    //   1060: invokestatic 242	com/google/android/gms/internal/ads/zzkd:zzad	(Lcom/google/android/gms/internal/ads/zzle;)Z
    //   1063: ifeq +73 -> 1136
    //   1066: aload_0
    //   1067: getfield 93	com/google/android/gms/internal/ads/zzkd:zza	[Lcom/google/android/gms/internal/ads/zzle;
    //   1070: iload 6
    //   1072: aaload
    //   1073: invokeinterface 480 1 0
    //   1078: aload 22
    //   1080: getfield 299	com/google/android/gms/internal/ads/zzki:zzc	[Lcom/google/android/gms/internal/ads/zzvc;
    //   1083: iload 6
    //   1085: aaload
    //   1086: if_acmpeq +10 -> 1096
    //   1089: lload 14
    //   1091: lstore 12
    //   1093: goto +43 -> 1136
    //   1096: aload_0
    //   1097: getfield 93	com/google/android/gms/internal/ads/zzkd:zza	[Lcom/google/android/gms/internal/ads/zzle;
    //   1100: iload 6
    //   1102: aaload
    //   1103: invokeinterface 481 1 0
    //   1108: lstore 12
    //   1110: lload 12
    //   1112: ldc2_w 482
    //   1115: lcmp
    //   1116: ifne +11 -> 1127
    //   1119: ldc2_w 482
    //   1122: lstore 12
    //   1124: goto +22 -> 1146
    //   1127: lload 12
    //   1129: lload 14
    //   1131: invokestatic 489	java/lang/Math:max	(JJ)J
    //   1134: lstore 12
    //   1136: iinc 6 1
    //   1139: lload 12
    //   1141: lstore 14
    //   1143: goto -113 -> 1030
    //   1146: lload 10
    //   1148: lstore 14
    //   1150: aload 25
    //   1152: aload_1
    //   1153: lload 20
    //   1155: lload 12
    //   1157: invokevirtual 492	com/google/android/gms/internal/ads/zzkl:zzo	(Lcom/google/android/gms/internal/ads/zzcx;JJ)Z
    //   1160: ifne +106 -> 1266
    //   1163: aload_0
    //   1164: iconst_0
    //   1165: invokespecial 495	com/google/android/gms/internal/ads/zzkd:zzQ	(Z)V
    //   1168: lload 10
    //   1170: lstore 14
    //   1172: goto +94 -> 1266
    //   1175: astore 22
    //   1177: goto -211 -> 966
    //   1180: lload 10
    //   1182: lstore 14
    //   1184: aload_1
    //   1185: invokevirtual 394	com/google/android/gms/internal/ads/zzcx:zzo	()Z
    //   1188: ifne +78 -> 1266
    //   1191: aload_0
    //   1192: getfield 207	com/google/android/gms/internal/ads/zzkd:zzq	Lcom/google/android/gms/internal/ads/zzkl;
    //   1195: invokevirtual 278	com/google/android/gms/internal/ads/zzkl:zzd	()Lcom/google/android/gms/internal/ads/zzki;
    //   1198: astore 22
    //   1200: aload 22
    //   1202: ifnull +52 -> 1254
    //   1205: aload 22
    //   1207: getfield 329	com/google/android/gms/internal/ads/zzki:zzf	Lcom/google/android/gms/internal/ads/zzkj;
    //   1210: getfield 334	com/google/android/gms/internal/ads/zzkj:zza	Lcom/google/android/gms/internal/ads/zztl;
    //   1213: aload 23
    //   1215: invokevirtual 365	com/google/android/gms/internal/ads/zzbx:equals	(Ljava/lang/Object;)Z
    //   1218: ifeq +26 -> 1244
    //   1221: aload 22
    //   1223: aload_0
    //   1224: getfield 207	com/google/android/gms/internal/ads/zzkd:zzq	Lcom/google/android/gms/internal/ads/zzkl;
    //   1227: aload_1
    //   1228: aload 22
    //   1230: getfield 329	com/google/android/gms/internal/ads/zzki:zzf	Lcom/google/android/gms/internal/ads/zzkj;
    //   1233: invokevirtual 498	com/google/android/gms/internal/ads/zzkl:zzg	(Lcom/google/android/gms/internal/ads/zzcx;Lcom/google/android/gms/internal/ads/zzkj;)Lcom/google/android/gms/internal/ads/zzkj;
    //   1236: putfield 329	com/google/android/gms/internal/ads/zzki:zzf	Lcom/google/android/gms/internal/ads/zzkj;
    //   1239: aload 22
    //   1241: invokevirtual 500	com/google/android/gms/internal/ads/zzki:zzq	()V
    //   1244: aload 22
    //   1246: invokevirtual 502	com/google/android/gms/internal/ads/zzki:zzg	()Lcom/google/android/gms/internal/ads/zzki;
    //   1249: astore 22
    //   1251: goto -51 -> 1200
    //   1254: aload_0
    //   1255: aload 23
    //   1257: lload 10
    //   1259: iload 8
    //   1261: invokespecial 505	com/google/android/gms/internal/ads/zzkd:zzv	(Lcom/google/android/gms/internal/ads/zztl;JZ)J
    //   1264: lstore 14
    //   1266: aload_0
    //   1267: getfield 136	com/google/android/gms/internal/ads/zzkd:zzu	Lcom/google/android/gms/internal/ads/zzky;
    //   1270: astore 24
    //   1272: aload 24
    //   1274: getfield 440	com/google/android/gms/internal/ads/zzky:zza	Lcom/google/android/gms/internal/ads/zzcx;
    //   1277: astore 22
    //   1279: aload 24
    //   1281: getfield 358	com/google/android/gms/internal/ads/zzky:zzb	Lcom/google/android/gms/internal/ads/zztl;
    //   1284: astore 24
    //   1286: iconst_1
    //   1287: iload_3
    //   1288: if_icmpeq +11 -> 1299
    //   1291: ldc2_w 116
    //   1294: lstore 10
    //   1296: goto +7 -> 1303
    //   1299: lload 14
    //   1301: lstore 10
    //   1303: aload_0
    //   1304: aload_1
    //   1305: aload 23
    //   1307: aload 22
    //   1309: aload 24
    //   1311: lload 10
    //   1313: iconst_0
    //   1314: invokespecial 509	com/google/android/gms/internal/ads/zzkd:zzaa	(Lcom/google/android/gms/internal/ads/zzcx;Lcom/google/android/gms/internal/ads/zztl;Lcom/google/android/gms/internal/ads/zzcx;Lcom/google/android/gms/internal/ads/zztl;JZ)V
    //   1317: iload 4
    //   1319: ifne +16 -> 1335
    //   1322: lload 16
    //   1324: aload_0
    //   1325: getfield 136	com/google/android/gms/internal/ads/zzkd:zzu	Lcom/google/android/gms/internal/ads/zzky;
    //   1328: getfield 410	com/google/android/gms/internal/ads/zzky:zzc	J
    //   1331: lcmp
    //   1332: ifeq +108 -> 1440
    //   1335: aload_0
    //   1336: getfield 136	com/google/android/gms/internal/ads/zzkd:zzu	Lcom/google/android/gms/internal/ads/zzky;
    //   1339: astore 24
    //   1341: aload 24
    //   1343: getfield 358	com/google/android/gms/internal/ads/zzky:zzb	Lcom/google/android/gms/internal/ads/zztl;
    //   1346: getfield 402	com/google/android/gms/internal/ads/zztl:zza	Ljava/lang/Object;
    //   1349: astore 22
    //   1351: aload 24
    //   1353: getfield 440	com/google/android/gms/internal/ads/zzky:zza	Lcom/google/android/gms/internal/ads/zzcx;
    //   1356: astore 24
    //   1358: iload 4
    //   1360: ifeq +37 -> 1397
    //   1363: iload_2
    //   1364: ifeq +33 -> 1397
    //   1367: aload 24
    //   1369: invokevirtual 394	com/google/android/gms/internal/ads/zzcx:zzo	()Z
    //   1372: ifne +25 -> 1397
    //   1375: aload 24
    //   1377: aload 22
    //   1379: aload_0
    //   1380: getfield 188	com/google/android/gms/internal/ads/zzkd:zzl	Lcom/google/android/gms/internal/ads/zzcu;
    //   1383: invokevirtual 427	com/google/android/gms/internal/ads/zzcx:zzn	(Ljava/lang/Object;Lcom/google/android/gms/internal/ads/zzcu;)Lcom/google/android/gms/internal/ads/zzcu;
    //   1386: getfield 510	com/google/android/gms/internal/ads/zzcu:zzg	Z
    //   1389: ifne +8 -> 1397
    //   1392: iconst_1
    //   1393: istore_2
    //   1394: goto +5 -> 1399
    //   1397: iconst_0
    //   1398: istore_2
    //   1399: aload_0
    //   1400: getfield 136	com/google/android/gms/internal/ads/zzkd:zzu	Lcom/google/android/gms/internal/ads/zzky;
    //   1403: getfield 512	com/google/android/gms/internal/ads/zzky:zzd	J
    //   1406: lstore 10
    //   1408: aload_1
    //   1409: aload 22
    //   1411: invokevirtual 443	com/google/android/gms/internal/ads/zzcx:zza	(Ljava/lang/Object;)I
    //   1414: iconst_m1
    //   1415: if_icmpne +6 -> 1421
    //   1418: iconst_4
    //   1419: istore 5
    //   1421: aload_0
    //   1422: aload_0
    //   1423: aload 23
    //   1425: lload 14
    //   1427: lload 16
    //   1429: lload 10
    //   1431: iload_2
    //   1432: iload 5
    //   1434: invokespecial 515	com/google/android/gms/internal/ads/zzkd:zzz	(Lcom/google/android/gms/internal/ads/zztl;JJJZI)Lcom/google/android/gms/internal/ads/zzky;
    //   1437: putfield 136	com/google/android/gms/internal/ads/zzkd:zzu	Lcom/google/android/gms/internal/ads/zzky;
    //   1440: aload_0
    //   1441: invokespecial 517	com/google/android/gms/internal/ads/zzkd:zzM	()V
    //   1444: aload_0
    //   1445: aload_1
    //   1446: aload_0
    //   1447: getfield 136	com/google/android/gms/internal/ads/zzkd:zzu	Lcom/google/android/gms/internal/ads/zzky;
    //   1450: getfield 440	com/google/android/gms/internal/ads/zzky:zza	Lcom/google/android/gms/internal/ads/zzcx;
    //   1453: invokespecial 520	com/google/android/gms/internal/ads/zzkd:zzO	(Lcom/google/android/gms/internal/ads/zzcx;Lcom/google/android/gms/internal/ads/zzcx;)V
    //   1456: aload_0
    //   1457: aload_0
    //   1458: getfield 136	com/google/android/gms/internal/ads/zzkd:zzu	Lcom/google/android/gms/internal/ads/zzky;
    //   1461: aload_1
    //   1462: invokevirtual 523	com/google/android/gms/internal/ads/zzky:zzh	(Lcom/google/android/gms/internal/ads/zzcx;)Lcom/google/android/gms/internal/ads/zzky;
    //   1465: putfield 136	com/google/android/gms/internal/ads/zzkd:zzu	Lcom/google/android/gms/internal/ads/zzky;
    //   1468: aload_1
    //   1469: invokevirtual 394	com/google/android/gms/internal/ads/zzcx:zzo	()Z
    //   1472: ifne +8 -> 1480
    //   1475: aload_0
    //   1476: aconst_null
    //   1477: putfield 390	com/google/android/gms/internal/ads/zzkd:zzH	Lcom/google/android/gms/internal/ads/zzkc;
    //   1480: aload_0
    //   1481: iconst_0
    //   1482: invokespecial 525	com/google/android/gms/internal/ads/zzkd:zzE	(Z)V
    //   1485: return
    //   1486: astore 22
    //   1488: goto -522 -> 966
    //   1491: aload_0
    //   1492: getfield 136	com/google/android/gms/internal/ads/zzkd:zzu	Lcom/google/android/gms/internal/ads/zzky;
    //   1495: astore 25
    //   1497: aload 25
    //   1499: getfield 440	com/google/android/gms/internal/ads/zzky:zza	Lcom/google/android/gms/internal/ads/zzcx;
    //   1502: astore 24
    //   1504: aload 25
    //   1506: getfield 358	com/google/android/gms/internal/ads/zzky:zzb	Lcom/google/android/gms/internal/ads/zztl;
    //   1509: astore 25
    //   1511: iconst_1
    //   1512: iload_3
    //   1513: if_icmpeq +10 -> 1523
    //   1516: lload 18
    //   1518: lstore 12
    //   1520: goto +7 -> 1527
    //   1523: lload 10
    //   1525: lstore 12
    //   1527: iconst_1
    //   1528: istore 8
    //   1530: aload_0
    //   1531: aload_1
    //   1532: aload 23
    //   1534: aload 24
    //   1536: aload 25
    //   1538: lload 12
    //   1540: iconst_0
    //   1541: invokespecial 509	com/google/android/gms/internal/ads/zzkd:zzaa	(Lcom/google/android/gms/internal/ads/zzcx;Lcom/google/android/gms/internal/ads/zztl;Lcom/google/android/gms/internal/ads/zzcx;Lcom/google/android/gms/internal/ads/zztl;JZ)V
    //   1544: iload 4
    //   1546: ifne +16 -> 1562
    //   1549: lload 16
    //   1551: aload_0
    //   1552: getfield 136	com/google/android/gms/internal/ads/zzkd:zzu	Lcom/google/android/gms/internal/ads/zzky;
    //   1555: getfield 410	com/google/android/gms/internal/ads/zzky:zzc	J
    //   1558: lcmp
    //   1559: ifeq +109 -> 1668
    //   1562: aload_0
    //   1563: getfield 136	com/google/android/gms/internal/ads/zzkd:zzu	Lcom/google/android/gms/internal/ads/zzky;
    //   1566: astore 25
    //   1568: aload 25
    //   1570: getfield 358	com/google/android/gms/internal/ads/zzky:zzb	Lcom/google/android/gms/internal/ads/zztl;
    //   1573: getfield 402	com/google/android/gms/internal/ads/zztl:zza	Ljava/lang/Object;
    //   1576: astore 24
    //   1578: aload 25
    //   1580: getfield 440	com/google/android/gms/internal/ads/zzky:zza	Lcom/google/android/gms/internal/ads/zzcx;
    //   1583: astore 25
    //   1585: iload 4
    //   1587: ifeq +38 -> 1625
    //   1590: iload_2
    //   1591: ifeq +34 -> 1625
    //   1594: aload 25
    //   1596: invokevirtual 394	com/google/android/gms/internal/ads/zzcx:zzo	()Z
    //   1599: ifne +26 -> 1625
    //   1602: aload 25
    //   1604: aload 24
    //   1606: aload_0
    //   1607: getfield 188	com/google/android/gms/internal/ads/zzkd:zzl	Lcom/google/android/gms/internal/ads/zzcu;
    //   1610: invokevirtual 427	com/google/android/gms/internal/ads/zzcx:zzn	(Ljava/lang/Object;Lcom/google/android/gms/internal/ads/zzcu;)Lcom/google/android/gms/internal/ads/zzcu;
    //   1613: getfield 510	com/google/android/gms/internal/ads/zzcu:zzg	Z
    //   1616: ifne +9 -> 1625
    //   1619: iload 8
    //   1621: istore_2
    //   1622: goto +5 -> 1627
    //   1625: iconst_0
    //   1626: istore_2
    //   1627: aload_0
    //   1628: getfield 136	com/google/android/gms/internal/ads/zzkd:zzu	Lcom/google/android/gms/internal/ads/zzky;
    //   1631: getfield 512	com/google/android/gms/internal/ads/zzky:zzd	J
    //   1634: lstore 12
    //   1636: aload_1
    //   1637: aload 24
    //   1639: invokevirtual 443	com/google/android/gms/internal/ads/zzcx:zza	(Ljava/lang/Object;)I
    //   1642: iconst_m1
    //   1643: if_icmpne +6 -> 1649
    //   1646: iconst_4
    //   1647: istore 5
    //   1649: aload_0
    //   1650: aload_0
    //   1651: aload 23
    //   1653: lload 10
    //   1655: lload 16
    //   1657: lload 12
    //   1659: iload_2
    //   1660: iload 5
    //   1662: invokespecial 515	com/google/android/gms/internal/ads/zzkd:zzz	(Lcom/google/android/gms/internal/ads/zztl;JJJZI)Lcom/google/android/gms/internal/ads/zzky;
    //   1665: putfield 136	com/google/android/gms/internal/ads/zzkd:zzu	Lcom/google/android/gms/internal/ads/zzky;
    //   1668: aload_0
    //   1669: invokespecial 517	com/google/android/gms/internal/ads/zzkd:zzM	()V
    //   1672: aload_0
    //   1673: aload_1
    //   1674: aload_0
    //   1675: getfield 136	com/google/android/gms/internal/ads/zzkd:zzu	Lcom/google/android/gms/internal/ads/zzky;
    //   1678: getfield 440	com/google/android/gms/internal/ads/zzky:zza	Lcom/google/android/gms/internal/ads/zzcx;
    //   1681: invokespecial 520	com/google/android/gms/internal/ads/zzkd:zzO	(Lcom/google/android/gms/internal/ads/zzcx;Lcom/google/android/gms/internal/ads/zzcx;)V
    //   1684: aload_0
    //   1685: aload_0
    //   1686: getfield 136	com/google/android/gms/internal/ads/zzkd:zzu	Lcom/google/android/gms/internal/ads/zzky;
    //   1689: aload_1
    //   1690: invokevirtual 523	com/google/android/gms/internal/ads/zzky:zzh	(Lcom/google/android/gms/internal/ads/zzcx;)Lcom/google/android/gms/internal/ads/zzky;
    //   1693: putfield 136	com/google/android/gms/internal/ads/zzkd:zzu	Lcom/google/android/gms/internal/ads/zzky;
    //   1696: aload_1
    //   1697: invokevirtual 394	com/google/android/gms/internal/ads/zzcx:zzo	()Z
    //   1700: ifne +8 -> 1708
    //   1703: aload_0
    //   1704: aconst_null
    //   1705: putfield 390	com/google/android/gms/internal/ads/zzkd:zzH	Lcom/google/android/gms/internal/ads/zzkc;
    //   1708: aload_0
    //   1709: iconst_0
    //   1710: invokespecial 525	com/google/android/gms/internal/ads/zzkd:zzE	(Z)V
    //   1713: aload 22
    //   1715: athrow
    // Local variable table:
    //   start	length	slot	name	signature
    //   0	1716	0	this	zzkd
    //   0	1716	1	paramzzcx	zzcx
    //   0	1716	2	paramBoolean	boolean
    //   22	1492	3	i	int
    //   184	1402	4	j	int
    //   172	1489	5	k	int
    //   53	1084	6	m	int
    //   1039	1	7	n	int
    //   27	1593	8	bool1	boolean
    //   45	670	9	bool2	boolean
    //   76	1578	10	l1	long
    //   176	1482	12	l2	long
    //   590	836	14	l3	long
    //   68	1588	16	l4	long
    //   50	1467	18	l5	long
    //   984	170	20	l6	long
    //   93	790	22	localObject1	Object
    //   964	1	22	localObject2	Object
    //   991	88	22	localzzki	zzki
    //   1175	1	22	localObject3	Object
    //   1198	212	22	localObject4	Object
    //   1486	228	22	localObject5	Object
    //   63	1589	23	localObject6	Object
    //   16	1622	24	localObject7	Object
    //   39	1564	25	localObject8	Object
    //   4	820	26	localzzky	zzky
    //   33	547	27	localObject9	Object
    //   159	353	28	localObject10	Object
    //   10	180	29	localzzkc	zzkc
    // Exception table:
    //   from	to	target	type
    //   934	950	964	finally
    //   953	961	964	finally
    //   1030	1041	964	finally
    //   1055	1089	964	finally
    //   1096	1110	964	finally
    //   1127	1136	964	finally
    //   974	993	1175	finally
    //   1004	1018	1175	finally
    //   1150	1168	1486	finally
    //   1184	1200	1486	finally
    //   1205	1244	1486	finally
    //   1244	1251	1486	finally
    //   1254	1266	1486	finally
  }
  
  private final void zzG(zzci paramzzci, boolean paramBoolean)
    throws zzia
  {
    zzH(paramzzci, paramzzci.zzc, true, paramBoolean);
  }
  
  private final void zzH(zzci paramzzci, float paramFloat, boolean paramBoolean1, boolean paramBoolean2)
    throws zzia
  {
    if (paramBoolean1)
    {
      if (paramBoolean2) {
        this.zzv.zza(1);
      }
      localObject = this.zzu;
      this.zzu = new zzky(((zzky)localObject).zza, ((zzky)localObject).zzb, ((zzky)localObject).zzc, ((zzky)localObject).zzd, ((zzky)localObject).zze, ((zzky)localObject).zzf, ((zzky)localObject).zzg, ((zzky)localObject).zzh, ((zzky)localObject).zzi, ((zzky)localObject).zzj, ((zzky)localObject).zzk, ((zzky)localObject).zzl, ((zzky)localObject).zzm, paramzzci, ((zzky)localObject).zzp, ((zzky)localObject).zzq, ((zzky)localObject).zzr, ((zzky)localObject).zzs, ((zzky)localObject).zzo);
    }
    float f = paramzzci.zzc;
    int j;
    zzwx localzzwx;
    for (Object localObject = this.zzq.zzd();; localObject = ((zzki)localObject).zzg())
    {
      j = 0;
      i = 0;
      if (localObject == null) {
        break;
      }
      zzwx[] arrayOfzzwx = ((zzki)localObject).zzi().zzc;
      j = arrayOfzzwx.length;
      while (i < j)
      {
        localzzwx = arrayOfzzwx[i];
        i++;
      }
    }
    localObject = this.zza;
    int i = localObject.length;
    for (i = j; i < 2; i++)
    {
      localzzwx = localObject[i];
      if (localzzwx != null) {
        localzzwx.zzF(paramFloat, paramzzci.zzc);
      }
    }
  }
  
  private final void zzI()
  {
    boolean bool2 = zzac();
    boolean bool1 = false;
    if (bool2)
    {
      zzki localzzki = this.zzq.zzc();
      long l3 = zzu(localzzki.zzd());
      long l2;
      if (localzzki == this.zzq.zzd())
      {
        l2 = this.zzI;
        l1 = localzzki.zze();
      }
      else
      {
        l2 = this.zzI - localzzki.zze();
        l1 = localzzki.zzf.zzb;
      }
      long l1 = l2 - l1;
      bool1 = this.zzf.zzg(l1, l3, this.zzn.zzc().zzc);
      if ((!bool1) && (l3 < 500000L) && (this.zzm > 0L))
      {
        this.zzq.zzd().zza.zzj(this.zzu.zzr, false);
        bool1 = this.zzf.zzg(l1, l3, this.zzn.zzc().zzc);
      }
    }
    this.zzA = bool1;
    if (bool1) {
      this.zzq.zzc().zzk(this.zzI);
    }
    zzX();
  }
  
  private final void zzJ()
  {
    this.zzv.zzc(this.zzu);
    if (zzkb.zze(this.zzv))
    {
      zzjg localzzjg = this.zzN;
      zzkb localzzkb = this.zzv;
      localzzjg.zza.zzY(localzzkb);
      this.zzv = new zzkb(this.zzu);
    }
  }
  
  private final void zzK()
    throws zzia
  {
    float f = this.zzn.zzc().zzc;
    zzki localzzki = this.zzq.zzd();
    Object localObject1 = this.zzq.zze();
    int i = 1;
    while ((localzzki != null) && (localzzki.zzd))
    {
      Object localObject2 = localzzki.zzj(f, this.zzu.zza);
      Object localObject3 = localzzki.zzi();
      int k = 0;
      int j;
      if ((localObject3 != null) && (((zzxe)localObject3).zzc.length == ((zzxe)localObject2).zzc.length))
      {
        for (j = 0; j < ((zzxe)localObject2).zzc.length; j++) {
          if (!((zzxe)localObject2).zza((zzxe)localObject3, j)) {
            break label153;
          }
        }
        if (localzzki == localObject1) {
          j = k;
        } else {
          j = 1;
        }
        i &= j;
        localzzki = localzzki.zzg();
      }
      else
      {
        label153:
        if (i != 0)
        {
          localzzki = this.zzq.zzd();
          boolean bool = this.zzq.zzm(localzzki);
          i = this.zza.length;
          localObject1 = new boolean[2];
          long l = localzzki.zzb((zzxe)localObject2, this.zzu.zzr, bool, (boolean[])localObject1);
          localObject2 = this.zzu;
          if ((((zzky)localObject2).zze != 4) && (l != ((zzky)localObject2).zzr)) {
            bool = true;
          } else {
            bool = false;
          }
          localObject2 = this.zzu;
          this.zzu = zzz(((zzky)localObject2).zzb, l, ((zzky)localObject2).zzc, ((zzky)localObject2).zzd, bool, 5);
          if (bool) {
            zzN(l);
          }
          i = this.zza.length;
          localObject2 = new boolean[2];
          for (i = 0;; i++)
          {
            localObject3 = this.zza;
            j = localObject3.length;
            if (i >= 2) {
              break;
            }
            localObject3 = localObject3[i];
            bool = zzad((zzle)localObject3);
            localObject2[i] = bool;
            zzvc localzzvc = localzzki.zzc[i];
            if (bool) {
              if (localzzvc != ((zzle)localObject3).zzm()) {
                zzA((zzle)localObject3);
              } else if (localObject1[i] != 0) {
                ((zzle)localObject3).zzD(this.zzI);
              }
            }
          }
          zzC((boolean[])localObject2);
        }
        else
        {
          this.zzq.zzm(localzzki);
          if (localzzki.zzd) {
            localzzki.zza((zzxe)localObject2, Math.max(localzzki.zzf.zzb, this.zzI - localzzki.zze()), false);
          }
        }
        zzE(true);
        if (this.zzu.zze != 4)
        {
          zzI();
          zzZ();
          this.zzh.zzi(2);
        }
      }
    }
  }
  
  private final void zzL(boolean paramBoolean1, boolean paramBoolean2, boolean paramBoolean3, boolean paramBoolean4)
  {
    this.zzh.zzf(2);
    zzia localzzia2 = null;
    this.zzL = null;
    this.zzz = false;
    this.zzn.zzi();
    this.zzI = 1000000000000L;
    zzle[] arrayOfzzle = this.zza;
    int i = arrayOfzzle.length;
    for (i = 0; i < 2; i++)
    {
      zzle localzzle = arrayOfzzle[i];
      try
      {
        zzA(localzzle);
      }
      catch (RuntimeException localRuntimeException1) {}catch (zzia localzzia1) {}
      zzer.zzc("ExoPlayerImplInternal", "Disable failed.", localzzia1);
    }
    if (paramBoolean1)
    {
      localObject1 = this.zza;
      i = localObject1.length;
      for (i = 0; i < 2; i++)
      {
        arrayOfzzle = localObject1[i];
        if (this.zzb.remove(arrayOfzzle)) {
          try
          {
            arrayOfzzle.zzC();
          }
          catch (RuntimeException localRuntimeException2)
          {
            zzer.zzc("ExoPlayerImplInternal", "Reset failed.", localRuntimeException2);
          }
        }
      }
    }
    this.zzG = 0;
    Object localObject2 = this.zzu;
    Object localObject1 = ((zzky)localObject2).zzb;
    long l2 = ((zzky)localObject2).zzr;
    long l1;
    if ((!this.zzu.zzb.zzb()) && (!zzaf(this.zzu, this.zzl))) {
      l1 = this.zzu.zzr;
    } else {
      l1 = this.zzu.zzc;
    }
    if (paramBoolean2)
    {
      this.zzH = null;
      localObject2 = zzx(this.zzu.zza);
      localObject1 = (zztl)((Pair)localObject2).first;
      l2 = ((Long)((Pair)localObject2).second).longValue();
      if (!((zzbx)localObject1).equals(this.zzu.zzb))
      {
        i = 1;
        l1 = -9223372036854775807L;
        break label329;
      }
      l1 = -9223372036854775807L;
    }
    i = 0;
    label329:
    this.zzq.zzi();
    this.zzA = false;
    localObject2 = this.zzu;
    zzcx localzzcx = ((zzky)localObject2).zza;
    int j = ((zzky)localObject2).zze;
    if (!paramBoolean4) {
      localzzia2 = ((zzky)localObject2).zzf;
    }
    if (i != 0) {
      localObject2 = zzvk.zza;
    } else {
      localObject2 = ((zzky)localObject2).zzh;
    }
    zzxe localzzxe;
    if (i != 0) {
      localzzxe = this.zze;
    } else {
      localzzxe = this.zzu.zzi;
    }
    Object localObject3;
    if (i != 0) {
      localObject3 = zzfrr.zzl();
    } else {
      localObject3 = this.zzu.zzj;
    }
    zzky localzzky = this.zzu;
    this.zzu = new zzky(localzzcx, (zztl)localObject1, l1, l2, j, localzzia2, false, (zzvk)localObject2, localzzxe, (List)localObject3, (zztl)localObject1, localzzky.zzl, localzzky.zzm, localzzky.zzn, l2, 0L, l2, 0L, false);
    if (paramBoolean3) {
      this.zzr.zzg();
    }
  }
  
  private final void zzM()
  {
    zzki localzzki = this.zzq.zzd();
    boolean bool2 = false;
    boolean bool1 = bool2;
    if (localzzki != null)
    {
      bool1 = bool2;
      if (localzzki.zzf.zzh)
      {
        bool1 = bool2;
        if (this.zzx) {
          bool1 = true;
        }
      }
    }
    this.zzy = bool1;
  }
  
  private final void zzN(long paramLong)
    throws zzia
  {
    zzki localzzki = this.zzq.zzd();
    long l;
    if (localzzki == null) {
      l = 1000000000000L;
    } else {
      l = localzzki.zze();
    }
    paramLong += l;
    this.zzI = paramLong;
    this.zzn.zzf(paramLong);
    Object localObject1 = this.zza;
    int i = localObject1.length;
    for (i = 0; i < 2; i++)
    {
      localzzki = localObject1[i];
      if (zzad(localzzki)) {
        localzzki.zzD(this.zzI);
      }
    }
    for (localzzki = this.zzq.zzd(); localzzki != null; localzzki = localzzki.zzg()) {
      for (Object localObject2 : localzzki.zzi().zzc) {}
    }
  }
  
  private final void zzO(zzcx paramzzcx1, zzcx paramzzcx2)
  {
    if ((paramzzcx1.zzo()) && (paramzzcx2.zzo())) {
      return;
    }
    int i = this.zzo.size() - 1;
    if (i < 0)
    {
      Collections.sort(this.zzo);
      return;
    }
    paramzzcx1 = (zzka)this.zzo.get(i);
    paramzzcx2 = paramzzcx1.zzb;
    paramzzcx2 = paramzzcx1.zza;
    i = zzfn.zza;
    paramzzcx1 = paramzzcx1.zza;
    throw null;
  }
  
  private final void zzP(long paramLong1, long paramLong2)
  {
    this.zzh.zzj(2, paramLong1 + paramLong2);
  }
  
  private final void zzQ(boolean paramBoolean)
    throws zzia
  {
    zztl localzztl = this.zzq.zzd().zzf.zza;
    long l = zzw(localzztl, this.zzu.zzr, true, false);
    if (l != this.zzu.zzr)
    {
      zzky localzzky = this.zzu;
      this.zzu = zzz(localzztl, l, localzzky.zzc, localzzky.zzd, paramBoolean, 5);
    }
  }
  
  private final void zzR(zzci paramzzci)
  {
    this.zzh.zzf(16);
    this.zzn.zzg(paramzzci);
  }
  
  private final void zzS(boolean paramBoolean1, int paramInt1, boolean paramBoolean2, int paramInt2)
    throws zzia
  {
    this.zzv.zza(paramBoolean2);
    this.zzv.zzb(paramInt2);
    this.zzu = this.zzu.zze(paramBoolean1, paramInt1);
    this.zzz = false;
    for (zzki localzzki = this.zzq.zzd(); localzzki != null; localzzki = localzzki.zzg()) {
      for (zzwx localzzwx : localzzki.zzi().zzc) {}
    }
    if (!zzag())
    {
      zzW();
      zzZ();
      return;
    }
    paramInt1 = this.zzu.zze;
    if (paramInt1 == 3)
    {
      zzU();
      this.zzh.zzi(2);
      return;
    }
    if (paramInt1 == 2) {
      this.zzh.zzi(2);
    }
  }
  
  private final void zzT(int paramInt)
  {
    zzky localzzky = this.zzu;
    if (localzzky.zze != paramInt)
    {
      if (paramInt != 2) {
        this.zzM = -9223372036854775807L;
      }
      this.zzu = localzzky.zzg(paramInt);
    }
  }
  
  private final void zzU()
    throws zzia
  {
    int i = 0;
    this.zzz = false;
    this.zzn.zzh();
    zzle[] arrayOfzzle = this.zza;
    int j = arrayOfzzle.length;
    while (i < 2)
    {
      zzle localzzle = arrayOfzzle[i];
      if (zzad(localzzle)) {
        localzzle.zzG();
      }
      i++;
    }
  }
  
  private final void zzV(boolean paramBoolean1, boolean paramBoolean2)
  {
    if ((!paramBoolean1) && (this.zzD)) {
      paramBoolean1 = false;
    } else {
      paramBoolean1 = true;
    }
    zzL(paramBoolean1, false, true, false);
    this.zzv.zza(paramBoolean2);
    this.zzf.zzd();
    zzT(1);
  }
  
  private final void zzW()
    throws zzia
  {
    this.zzn.zzi();
    zzle[] arrayOfzzle = this.zza;
    int i = arrayOfzzle.length;
    for (i = 0; i < 2; i++)
    {
      zzle localzzle = arrayOfzzle[i];
      if (zzad(localzzle)) {
        zzak(localzzle);
      }
    }
  }
  
  private final void zzX()
  {
    Object localObject = this.zzq.zzc();
    boolean bool;
    if ((!this.zzA) && ((localObject == null) || (!((zzki)localObject).zza.zzp()))) {
      bool = false;
    } else {
      bool = true;
    }
    localObject = this.zzu;
    if (bool != ((zzky)localObject).zzg) {
      this.zzu = new zzky(((zzky)localObject).zza, ((zzky)localObject).zzb, ((zzky)localObject).zzc, ((zzky)localObject).zzd, ((zzky)localObject).zze, ((zzky)localObject).zzf, bool, ((zzky)localObject).zzh, ((zzky)localObject).zzi, ((zzky)localObject).zzj, ((zzky)localObject).zzk, ((zzky)localObject).zzl, ((zzky)localObject).zzm, ((zzky)localObject).zzn, ((zzky)localObject).zzp, ((zzky)localObject).zzq, ((zzky)localObject).zzr, ((zzky)localObject).zzs, ((zzky)localObject).zzo);
    }
  }
  
  private final void zzY(zztl paramzztl, zzvk paramzzvk, zzxe paramzzxe)
  {
    this.zzf.zze(this.zzu.zza, paramzztl, this.zza, paramzzvk, paramzzxe.zzc);
  }
  
  private final void zzZ()
    throws zzia
  {
    zzki localzzki = this.zzq.zzd();
    if (localzzki == null) {
      return;
    }
    long l1;
    if (localzzki.zzd) {
      l1 = localzzki.zza.zzd();
    } else {
      l1 = -9223372036854775807L;
    }
    if (l1 != -9223372036854775807L)
    {
      zzN(l1);
      if (l1 != this.zzu.zzr)
      {
        localObject = this.zzu;
        this.zzu = zzz(((zzky)localObject).zzb, l1, ((zzky)localObject).zzc, l1, true, 5);
      }
    }
    else
    {
      localObject = this.zzn;
      boolean bool;
      if (localzzki != this.zzq.zze()) {
        bool = true;
      } else {
        bool = false;
      }
      long l3 = ((zzhy)localObject).zzb(bool);
      this.zzI = l3;
      long l4 = localzzki.zze();
      long l2 = this.zzu.zzr;
      if ((!this.zzo.isEmpty()) && (!this.zzu.zzb.zzb()))
      {
        l1 = l2;
        if (this.zzK)
        {
          l1 = l2 - 1L;
          this.zzK = false;
        }
        localObject = this.zzu;
        int k = ((zzky)localObject).zza.zza(((zzky)localObject).zzb.zza);
        int j = Math.min(this.zzJ, this.zzo.size());
        l2 = l1;
        int i = j;
        if (j > 0)
        {
          localObject = (zzka)this.zzo.get(j - 1);
          i = j;
        }
        while ((localObject != null) && ((k < 0) || ((k == 0) && (l1 < 0L))))
        {
          j = i - 1;
          l2 = l1;
          i = j;
          if (j > 0)
          {
            localObject = (zzka)this.zzo.get(j - 1);
            i = j;
          }
          else
          {
            localObject = null;
            l1 = l2;
          }
        }
        if (i < this.zzo.size()) {
          localObject = (zzka)this.zzo.get(i);
        }
        this.zzJ = i;
      }
      localObject = this.zzu;
      ((zzky)localObject).zzr = (l3 - l4);
      ((zzky)localObject).zzs = SystemClock.elapsedRealtime();
    }
    Object localObject = this.zzq.zzc();
    this.zzu.zzp = ((zzki)localObject).zzc();
    this.zzu.zzq = zzt();
    localObject = this.zzu;
    if ((((zzky)localObject).zzl) && (((zzky)localObject).zze == 3) && (zzah(((zzky)localObject).zza, ((zzky)localObject).zzb)))
    {
      localObject = this.zzu;
      if (((zzky)localObject).zzn.zzc == 1.0F)
      {
        float f = this.zzO.zza(zzs(((zzky)localObject).zza, ((zzky)localObject).zzb.zza, ((zzky)localObject).zzr), zzt());
        if (this.zzn.zzc().zzc != f)
        {
          zzR(new zzci(f, this.zzu.zzn.zzd));
          zzH(this.zzu.zzn, this.zzn.zzc().zzc, false, false);
        }
      }
    }
  }
  
  private final void zzaa(zzcx paramzzcx1, zztl paramzztl1, zzcx paramzzcx2, zztl paramzztl2, long paramLong, boolean paramBoolean)
    throws zzia
  {
    if (!zzah(paramzzcx1, paramzztl1))
    {
      if (paramzztl1.zzb()) {
        paramzzcx1 = zzci.zza;
      } else {
        paramzzcx1 = this.zzu.zzn;
      }
      if (!this.zzn.zzc().equals(paramzzcx1))
      {
        zzR(paramzzcx1);
        zzH(this.zzu.zzn, paramzzcx1.zzc, false, false);
      }
      return;
    }
    paramzzcx1.zze(paramzzcx1.zzn(paramzztl1.zza, this.zzl).zzd, this.zzk, 0L);
    zzhv localzzhv = this.zzO;
    zzbg localzzbg = this.zzk.zzk;
    int i = zzfn.zza;
    localzzhv.zzd(localzzbg);
    if (paramLong != -9223372036854775807L)
    {
      this.zzO.zze(zzs(paramzzcx1, paramzztl1.zza, paramLong));
      return;
    }
    paramzztl1 = this.zzk.zzc;
    if (!paramzzcx2.zzo()) {
      paramzzcx1 = paramzzcx2.zze(paramzzcx2.zzn(paramzztl2.zza, this.zzl).zzd, this.zzk, 0L).zzc;
    } else {
      paramzzcx1 = null;
    }
    if ((zzfn.zzB(paramzzcx1, paramzztl1)) && (!paramBoolean)) {
      return;
    }
    this.zzO.zze(-9223372036854775807L);
  }
  
  private final void zzab(zzfpp paramzzfpp, long paramLong)
  {
    try
    {
      long l2 = SystemClock.elapsedRealtime();
      int i = 0;
      for (long l1 = paramLong;; l1 = l2 + paramLong - SystemClock.elapsedRealtime())
      {
        boolean bool = Boolean.valueOf(((zzju)paramzzfpp).zza.zzw).booleanValue();
        if ((bool) || (l1 <= 0L)) {
          break;
        }
        try
        {
          wait(l1);
        }
        catch (InterruptedException localInterruptedException)
        {
          i = 1;
        }
      }
      if (i != 0)
      {
        Thread.currentThread().interrupt();
        return;
      }
      return;
    }
    finally {}
  }
  
  private final boolean zzac()
  {
    zzki localzzki = this.zzq.zzc();
    if (localzzki == null) {
      return false;
    }
    return localzzki.zzd() != Long.MIN_VALUE;
  }
  
  private static boolean zzad(zzle paramzzle)
  {
    return paramzzle.zzbc() != 0;
  }
  
  private final boolean zzae()
  {
    zzki localzzki = this.zzq.zzd();
    long l = localzzki.zzf.zze;
    boolean bool3 = localzzki.zzd;
    boolean bool2 = false;
    boolean bool1 = bool2;
    if (bool3) {
      if ((l != -9223372036854775807L) && (this.zzu.zzr >= l))
      {
        if (zzag()) {
          bool1 = bool2;
        } else {
          return true;
        }
      }
      else {
        bool1 = true;
      }
    }
    return bool1;
  }
  
  private static boolean zzaf(zzky paramzzky, zzcu paramzzcu)
  {
    zztl localzztl = paramzzky.zzb;
    paramzzky = paramzzky.zza;
    return (paramzzky.zzo()) || (paramzzky.zzn(localzztl.zza, paramzzcu).zzg);
  }
  
  private final boolean zzag()
  {
    zzky localzzky = this.zzu;
    return (localzzky.zzl) && (localzzky.zzm == 0);
  }
  
  private final boolean zzah(zzcx paramzzcx, zztl paramzztl)
  {
    if ((!paramzztl.zzb()) && (!paramzzcx.zzo()))
    {
      paramzzcx.zze(paramzzcx.zzn(paramzztl.zza, this.zzl).zzd, this.zzk, 0L);
      if (this.zzk.zzb())
      {
        paramzzcx = this.zzk;
        if ((paramzzcx.zzi) && (paramzzcx.zzf != -9223372036854775807L)) {
          return true;
        }
      }
    }
    return false;
  }
  
  private static zzam[] zzai(zzwx paramzzwx)
  {
    int j = 0;
    int i;
    if (paramzzwx != null) {
      i = paramzzwx.zzc();
    } else {
      i = 0;
    }
    zzam[] arrayOfzzam = new zzam[i];
    while (j < i)
    {
      arrayOfzzam[j] = paramzzwx.zzd(j);
      j++;
    }
    return arrayOfzzam;
  }
  
  private static final void zzaj(zzlb paramzzlb)
    throws zzia
  {
    paramzzlb.zzj();
    try
    {
      paramzzlb.zzc().zzq(paramzzlb.zza(), paramzzlb.zzg());
      return;
    }
    finally
    {
      paramzzlb.zzh(true);
    }
  }
  
  private static final void zzak(zzle paramzzle)
  {
    if (paramzzle.zzbc() == 2) {
      paramzzle.zzH();
    }
  }
  
  private static final void zzal(zzle paramzzle, long paramLong)
  {
    paramzzle.zzE();
    if (!(paramzzle instanceof zzvo)) {
      return;
    }
    paramzzle = (zzvo)paramzzle;
    throw null;
  }
  
  static Object zze(zzcw paramzzcw, zzcu paramzzcu, int paramInt, boolean paramBoolean, Object paramObject, zzcx paramzzcx1, zzcx paramzzcx2)
  {
    int j = paramzzcx1.zza(paramObject);
    int n = paramzzcx1.zzb();
    int k = 0;
    int i = -1;
    int m;
    for (;;)
    {
      m = i;
      if (k >= n) {
        break;
      }
      m = i;
      if (i != -1) {
        break;
      }
      j = paramzzcx1.zzi(j, paramzzcu, paramzzcw, paramInt, paramBoolean);
      if (j == -1)
      {
        m = -1;
        break;
      }
      i = paramzzcx2.zza(paramzzcx1.zzf(j));
      k++;
    }
    if (m == -1) {
      return null;
    }
    return paramzzcx2.zzf(m);
  }
  
  private final long zzs(zzcx paramzzcx, Object paramObject, long paramLong)
  {
    paramzzcx.zze(paramzzcx.zzn(paramObject, this.zzl).zzd, this.zzk, 0L);
    paramzzcx = this.zzk;
    if ((paramzzcx.zzf != -9223372036854775807L) && (paramzzcx.zzb()))
    {
      paramzzcx = this.zzk;
      if (paramzzcx.zzi)
      {
        long l = paramzzcx.zzg;
        if (l == -9223372036854775807L) {
          l = System.currentTimeMillis();
        } else {
          l += SystemClock.elapsedRealtime();
        }
        return zzfn.zzo(l - this.zzk.zzf) - paramLong;
      }
    }
    return -9223372036854775807L;
  }
  
  private final long zzt()
  {
    return zzu(this.zzu.zzp);
  }
  
  private final long zzu(long paramLong)
  {
    zzki localzzki = this.zzq.zzc();
    if (localzzki == null) {
      return 0L;
    }
    return Math.max(0L, paramLong - (this.zzI - localzzki.zze()));
  }
  
  private final long zzv(zztl paramzztl, long paramLong, boolean paramBoolean)
    throws zzia
  {
    boolean bool;
    if (this.zzq.zzd() != this.zzq.zze()) {
      bool = true;
    } else {
      bool = false;
    }
    return zzw(paramzztl, paramLong, bool, paramBoolean);
  }
  
  private final long zzw(zztl paramzztl, long paramLong, boolean paramBoolean1, boolean paramBoolean2)
    throws zzia
  {
    zzW();
    this.zzz = false;
    if ((paramBoolean2) || (this.zzu.zze == 3)) {
      zzT(2);
    }
    zzki localzzki2 = this.zzq.zzd();
    for (zzki localzzki1 = localzzki2; (localzzki1 != null) && (!paramzztl.equals(localzzki1.zzf.zza)); localzzki1 = localzzki1.zzg()) {}
    if ((paramBoolean1) || (localzzki2 != localzzki1) || ((localzzki1 != null) && (localzzki1.zze() + paramLong < 0L)))
    {
      paramzztl = this.zza;
      int i = paramzztl.length;
      for (i = 0; i < 2; i++) {
        zzA(paramzztl[i]);
      }
      if (localzzki1 != null)
      {
        while (this.zzq.zzd() != localzzki1) {
          this.zzq.zza();
        }
        this.zzq.zzm(localzzki1);
        localzzki1.zzp(1000000000000L);
        zzB();
      }
    }
    if (localzzki1 != null)
    {
      this.zzq.zzm(localzzki1);
      long l;
      if (!localzzki1.zzd)
      {
        localzzki1.zzf = localzzki1.zzf.zzb(paramLong);
        l = paramLong;
      }
      else
      {
        l = paramLong;
        if (localzzki1.zze)
        {
          l = localzzki1.zza.zze(paramLong);
          localzzki1.zza.zzj(l - this.zzm, false);
        }
      }
      zzN(l);
      zzI();
      paramLong = l;
    }
    else
    {
      this.zzq.zzi();
      zzN(paramLong);
    }
    zzE(false);
    this.zzh.zzi(2);
    return paramLong;
  }
  
  private final Pair zzx(zzcx paramzzcx)
  {
    boolean bool = paramzzcx.zzo();
    long l2 = 0L;
    if (bool) {
      return Pair.create(zzky.zzj(), Long.valueOf(0L));
    }
    int i = paramzzcx.zzg(this.zzC);
    Pair localPair = paramzzcx.zzl(this.zzk, this.zzl, i, -9223372036854775807L);
    zztl localzztl = this.zzq.zzh(paramzzcx, localPair.first, 0L);
    long l1 = ((Long)localPair.second).longValue();
    if (localzztl.zzb())
    {
      paramzzcx.zzn(localzztl.zza, this.zzl);
      l1 = l2;
      if (localzztl.zzc == this.zzl.zze(localzztl.zzb))
      {
        this.zzl.zzj();
        l1 = l2;
      }
    }
    return Pair.create(localzztl, Long.valueOf(l1));
  }
  
  private static Pair zzy(zzcx paramzzcx, zzkc paramzzkc, boolean paramBoolean1, int paramInt, boolean paramBoolean2, zzcw paramzzcw, zzcu paramzzcu)
  {
    zzcx localzzcx = paramzzkc.zza;
    if (paramzzcx.zzo()) {
      return null;
    }
    if (true == localzzcx.zzo()) {
      localzzcx = paramzzcx;
    }
    try
    {
      Pair localPair = localzzcx.zzl(paramzzcw, paramzzcu, paramzzkc.zzb, paramzzkc.zzc);
      if (paramzzcx.equals(localzzcx)) {
        return localPair;
      }
      if (paramzzcx.zza(localPair.first) != -1)
      {
        if ((localzzcx.zzn(localPair.first, paramzzcu).zzg) && (localzzcx.zze(paramzzcu.zzd, paramzzcw, 0L).zzo == localzzcx.zza(localPair.first))) {
          return paramzzcx.zzl(paramzzcw, paramzzcu, paramzzcx.zzn(localPair.first, paramzzcu).zzd, paramzzkc.zzc);
        }
        return localPair;
      }
      paramzzkc = zze(paramzzcw, paramzzcu, paramInt, paramBoolean2, localPair.first, localzzcx, paramzzcx);
      if (paramzzkc != null) {
        return paramzzcx.zzl(paramzzcw, paramzzcu, paramzzcx.zzn(paramzzkc, paramzzcu).zzd, -9223372036854775807L);
      }
    }
    catch (IndexOutOfBoundsException paramzzcx)
    {
      for (;;) {}
    }
    return null;
  }
  
  private final zzky zzz(zztl paramzztl, long paramLong1, long paramLong2, long paramLong3, boolean paramBoolean, int paramInt)
  {
    boolean bool;
    if ((!this.zzK) && (paramLong1 == this.zzu.zzr) && (paramzztl.equals(this.zzu.zzb))) {
      bool = false;
    } else {
      bool = true;
    }
    this.zzK = bool;
    zzM();
    Object localObject1 = this.zzu;
    Object localObject3 = ((zzky)localObject1).zzh;
    Object localObject2 = ((zzky)localObject1).zzi;
    localObject1 = ((zzky)localObject1).zzj;
    if (this.zzr.zzi())
    {
      localObject4 = this.zzq.zzd();
      if (localObject4 == null) {
        localObject1 = zzvk.zza;
      } else {
        localObject1 = ((zzki)localObject4).zzh();
      }
      if (localObject4 == null) {
        localObject2 = this.zze;
      } else {
        localObject2 = ((zzki)localObject4).zzi();
      }
      Object localObject5 = ((zzxe)localObject2).zzc;
      localObject3 = new zzfro();
      int m = localObject5.length;
      int i = 0;
      int j;
      for (int k = 0; i < m; k = j)
      {
        zzca localzzca = localObject5[i];
        j = k;
        if (localzzca != null)
        {
          localzzca = localzzca.zzd(0).zzk;
          if (localzzca == null)
          {
            ((zzfro)localObject3).zzf(new zzca(-9223372036854775807L, new zzbz[0]));
            j = k;
          }
          else
          {
            ((zzfro)localObject3).zzf(localzzca);
            j = 1;
          }
        }
        i++;
      }
      if (k != 0) {
        localObject3 = ((zzfro)localObject3).zzi();
      } else {
        localObject3 = zzfrr.zzl();
      }
      if (localObject4 != null)
      {
        localObject5 = ((zzki)localObject4).zzf;
        if (((zzkj)localObject5).zzc != paramLong2) {
          ((zzki)localObject4).zzf = ((zzkj)localObject5).zza(paramLong2);
        }
      }
      localObject4 = localObject3;
      localObject3 = localObject1;
      localObject1 = localObject4;
    }
    else if (!paramzztl.equals(this.zzu.zzb))
    {
      localObject3 = zzvk.zza;
      localObject1 = this.zze;
      localObject2 = zzfrr.zzl();
      break label376;
    }
    Object localObject4 = localObject2;
    localObject2 = localObject1;
    localObject1 = localObject4;
    label376:
    if (paramBoolean) {
      this.zzv.zzd(paramInt);
    }
    return this.zzu.zzd(paramzztl, paramLong1, paramLong2, paramLong3, zzt(), (zzvk)localObject3, (zzxe)localObject1, (List)localObject2);
  }
  
  /* Error */
  public final boolean handleMessage(android.os.Message paramMessage)
  {
    // Byte code:
    //   0: aload_1
    //   1: getfield 971	android/os/Message:what	I
    //   4: tableswitch	default:+120->124, 0:+4282->4286, 1:+4251->4255, 2:+1929->1933, 3:+1297->1301, 4:+1271->1275, 5:+1257->1261, 6:+1248->1252, 7:+1151->1155, 8:+1002->1006, 9:+965->969, 10:+958->962, 11:+917->921, 12:+863->867, 13:+736->740, 14:+661->665, 15:+580->584, 16:+565->569, 17:+474->478, 18:+412->416, 19:+349->353, 20:+305->309, 21:+273->277, 22:+258->262, 23:+195->199, 24:+134->138, 25:+122->126
    //   124: iconst_0
    //   125: ireturn
    //   126: aload_0
    //   127: invokespecial 973	com/google/android/gms/internal/ads/zzkd:zzK	()V
    //   130: aload_0
    //   131: iconst_1
    //   132: invokespecial 495	com/google/android/gms/internal/ads/zzkd:zzQ	(Z)V
    //   135: goto +4384 -> 4519
    //   138: aload_1
    //   139: getfield 976	android/os/Message:arg1	I
    //   142: iconst_1
    //   143: if_icmpne +9 -> 152
    //   146: iconst_1
    //   147: istore 18
    //   149: goto +6 -> 155
    //   152: iconst_0
    //   153: istore 18
    //   155: iload 18
    //   157: aload_0
    //   158: getfield 978	com/google/android/gms/internal/ads/zzkd:zzF	Z
    //   161: if_icmpeq +4358 -> 4519
    //   164: aload_0
    //   165: iload 18
    //   167: putfield 978	com/google/android/gms/internal/ads/zzkd:zzF	Z
    //   170: iload 18
    //   172: ifne +4347 -> 4519
    //   175: aload_0
    //   176: getfield 136	com/google/android/gms/internal/ads/zzkd:zzu	Lcom/google/android/gms/internal/ads/zzky;
    //   179: getfield 554	com/google/android/gms/internal/ads/zzky:zzo	Z
    //   182: ifeq +4337 -> 4519
    //   185: aload_0
    //   186: getfield 234	com/google/android/gms/internal/ads/zzkd:zzh	Lcom/google/android/gms/internal/ads/zzei;
    //   189: iconst_2
    //   190: invokeinterface 639 2 0
    //   195: pop
    //   196: goto +4323 -> 4519
    //   199: aload_1
    //   200: getfield 976	android/os/Message:arg1	I
    //   203: ifeq +9 -> 212
    //   206: iconst_1
    //   207: istore 18
    //   209: goto +6 -> 215
    //   212: iconst_0
    //   213: istore 18
    //   215: aload_0
    //   216: iload 18
    //   218: putfield 113	com/google/android/gms/internal/ads/zzkd:zzx	Z
    //   221: aload_0
    //   222: invokespecial 517	com/google/android/gms/internal/ads/zzkd:zzM	()V
    //   225: aload_0
    //   226: getfield 677	com/google/android/gms/internal/ads/zzkd:zzy	Z
    //   229: ifeq +4290 -> 4519
    //   232: aload_0
    //   233: getfield 207	com/google/android/gms/internal/ads/zzkd:zzq	Lcom/google/android/gms/internal/ads/zzkl;
    //   236: invokevirtual 258	com/google/android/gms/internal/ads/zzkl:zze	()Lcom/google/android/gms/internal/ads/zzki;
    //   239: aload_0
    //   240: getfield 207	com/google/android/gms/internal/ads/zzkd:zzq	Lcom/google/android/gms/internal/ads/zzkl;
    //   243: invokevirtual 278	com/google/android/gms/internal/ads/zzkl:zzd	()Lcom/google/android/gms/internal/ads/zzki;
    //   246: if_acmpeq +4273 -> 4519
    //   249: aload_0
    //   250: iconst_1
    //   251: invokespecial 495	com/google/android/gms/internal/ads/zzkd:zzQ	(Z)V
    //   254: aload_0
    //   255: iconst_0
    //   256: invokespecial 525	com/google/android/gms/internal/ads/zzkd:zzE	(Z)V
    //   259: goto +4260 -> 4519
    //   262: aload_0
    //   263: aload_0
    //   264: getfield 214	com/google/android/gms/internal/ads/zzkd:zzr	Lcom/google/android/gms/internal/ads/zzkx;
    //   267: invokevirtual 981	com/google/android/gms/internal/ads/zzkx:zzb	()Lcom/google/android/gms/internal/ads/zzcx;
    //   270: iconst_1
    //   271: invokespecial 983	com/google/android/gms/internal/ads/zzkd:zzF	(Lcom/google/android/gms/internal/ads/zzcx;Z)V
    //   274: goto +4245 -> 4519
    //   277: aload_1
    //   278: getfield 986	android/os/Message:obj	Ljava/lang/Object;
    //   281: checkcast 988	com/google/android/gms/internal/ads/zzvf
    //   284: astore_1
    //   285: aload_0
    //   286: getfield 143	com/google/android/gms/internal/ads/zzkd:zzv	Lcom/google/android/gms/internal/ads/zzkb;
    //   289: iconst_1
    //   290: invokevirtual 536	com/google/android/gms/internal/ads/zzkb:zza	(I)V
    //   293: aload_0
    //   294: aload_0
    //   295: getfield 214	com/google/android/gms/internal/ads/zzkd:zzr	Lcom/google/android/gms/internal/ads/zzkx;
    //   298: aload_1
    //   299: invokevirtual 991	com/google/android/gms/internal/ads/zzkx:zzn	(Lcom/google/android/gms/internal/ads/zzvf;)Lcom/google/android/gms/internal/ads/zzcx;
    //   302: iconst_0
    //   303: invokespecial 983	com/google/android/gms/internal/ads/zzkd:zzF	(Lcom/google/android/gms/internal/ads/zzcx;Z)V
    //   306: goto +4213 -> 4519
    //   309: aload_1
    //   310: getfield 976	android/os/Message:arg1	I
    //   313: istore_2
    //   314: aload_1
    //   315: getfield 994	android/os/Message:arg2	I
    //   318: istore_3
    //   319: aload_1
    //   320: getfield 986	android/os/Message:obj	Ljava/lang/Object;
    //   323: checkcast 988	com/google/android/gms/internal/ads/zzvf
    //   326: astore_1
    //   327: aload_0
    //   328: getfield 143	com/google/android/gms/internal/ads/zzkd:zzv	Lcom/google/android/gms/internal/ads/zzkb;
    //   331: iconst_1
    //   332: invokevirtual 536	com/google/android/gms/internal/ads/zzkb:zza	(I)V
    //   335: aload_0
    //   336: aload_0
    //   337: getfield 214	com/google/android/gms/internal/ads/zzkd:zzr	Lcom/google/android/gms/internal/ads/zzkx;
    //   340: iload_2
    //   341: iload_3
    //   342: aload_1
    //   343: invokevirtual 997	com/google/android/gms/internal/ads/zzkx:zzl	(IILcom/google/android/gms/internal/ads/zzvf;)Lcom/google/android/gms/internal/ads/zzcx;
    //   346: iconst_0
    //   347: invokespecial 983	com/google/android/gms/internal/ads/zzkd:zzF	(Lcom/google/android/gms/internal/ads/zzcx;Z)V
    //   350: goto +4169 -> 4519
    //   353: aload_1
    //   354: getfield 986	android/os/Message:obj	Ljava/lang/Object;
    //   357: checkcast 999	com/google/android/gms/internal/ads/zzjz
    //   360: astore 20
    //   362: aload_0
    //   363: getfield 143	com/google/android/gms/internal/ads/zzkd:zzv	Lcom/google/android/gms/internal/ads/zzkb;
    //   366: iconst_1
    //   367: invokevirtual 536	com/google/android/gms/internal/ads/zzkb:zza	(I)V
    //   370: aload_0
    //   371: getfield 214	com/google/android/gms/internal/ads/zzkd:zzr	Lcom/google/android/gms/internal/ads/zzkx;
    //   374: astore_1
    //   375: aload 20
    //   377: getfield 1000	com/google/android/gms/internal/ads/zzjz:zza	I
    //   380: istore_2
    //   381: aload 20
    //   383: getfield 1001	com/google/android/gms/internal/ads/zzjz:zzb	I
    //   386: istore_2
    //   387: aload 20
    //   389: getfield 1002	com/google/android/gms/internal/ads/zzjz:zzc	I
    //   392: istore_2
    //   393: aload 20
    //   395: getfield 1005	com/google/android/gms/internal/ads/zzjz:zzd	Lcom/google/android/gms/internal/ads/zzvf;
    //   398: astore 20
    //   400: aload_0
    //   401: aload_1
    //   402: iconst_0
    //   403: iconst_0
    //   404: iconst_0
    //   405: aconst_null
    //   406: invokevirtual 1008	com/google/android/gms/internal/ads/zzkx:zzk	(IIILcom/google/android/gms/internal/ads/zzvf;)Lcom/google/android/gms/internal/ads/zzcx;
    //   409: iconst_0
    //   410: invokespecial 983	com/google/android/gms/internal/ads/zzkd:zzF	(Lcom/google/android/gms/internal/ads/zzcx;Z)V
    //   413: goto +4106 -> 4519
    //   416: aload_1
    //   417: getfield 986	android/os/Message:obj	Ljava/lang/Object;
    //   420: checkcast 1010	com/google/android/gms/internal/ads/zzjy
    //   423: astore 20
    //   425: aload_1
    //   426: getfield 976	android/os/Message:arg1	I
    //   429: istore_3
    //   430: aload_0
    //   431: getfield 143	com/google/android/gms/internal/ads/zzkd:zzv	Lcom/google/android/gms/internal/ads/zzkb;
    //   434: iconst_1
    //   435: invokevirtual 536	com/google/android/gms/internal/ads/zzkb:zza	(I)V
    //   438: aload_0
    //   439: getfield 214	com/google/android/gms/internal/ads/zzkd:zzr	Lcom/google/android/gms/internal/ads/zzkx;
    //   442: astore_1
    //   443: iload_3
    //   444: istore_2
    //   445: iload_3
    //   446: iconst_m1
    //   447: if_icmpne +8 -> 455
    //   450: aload_1
    //   451: invokevirtual 1011	com/google/android/gms/internal/ads/zzkx:zza	()I
    //   454: istore_2
    //   455: aload_0
    //   456: aload_1
    //   457: iload_2
    //   458: aload 20
    //   460: invokestatic 1014	com/google/android/gms/internal/ads/zzjy:zzc	(Lcom/google/android/gms/internal/ads/zzjy;)Ljava/util/List;
    //   463: aload 20
    //   465: invokestatic 1017	com/google/android/gms/internal/ads/zzjy:zzd	(Lcom/google/android/gms/internal/ads/zzjy;)Lcom/google/android/gms/internal/ads/zzvf;
    //   468: invokevirtual 1020	com/google/android/gms/internal/ads/zzkx:zzj	(ILjava/util/List;Lcom/google/android/gms/internal/ads/zzvf;)Lcom/google/android/gms/internal/ads/zzcx;
    //   471: iconst_0
    //   472: invokespecial 983	com/google/android/gms/internal/ads/zzkd:zzF	(Lcom/google/android/gms/internal/ads/zzcx;Z)V
    //   475: goto +4044 -> 4519
    //   478: aload_1
    //   479: getfield 986	android/os/Message:obj	Ljava/lang/Object;
    //   482: checkcast 1010	com/google/android/gms/internal/ads/zzjy
    //   485: astore_1
    //   486: aload_0
    //   487: getfield 143	com/google/android/gms/internal/ads/zzkd:zzv	Lcom/google/android/gms/internal/ads/zzkb;
    //   490: iconst_1
    //   491: invokevirtual 536	com/google/android/gms/internal/ads/zzkb:zza	(I)V
    //   494: aload_1
    //   495: invokestatic 1023	com/google/android/gms/internal/ads/zzjy:zza	(Lcom/google/android/gms/internal/ads/zzjy;)I
    //   498: iconst_m1
    //   499: if_icmpeq +47 -> 546
    //   502: new 418	com/google/android/gms/internal/ads/zzkc
    //   505: astore 20
    //   507: new 1025	com/google/android/gms/internal/ads/zzlc
    //   510: astore 21
    //   512: aload 21
    //   514: aload_1
    //   515: invokestatic 1014	com/google/android/gms/internal/ads/zzjy:zzc	(Lcom/google/android/gms/internal/ads/zzjy;)Ljava/util/List;
    //   518: aload_1
    //   519: invokestatic 1017	com/google/android/gms/internal/ads/zzjy:zzd	(Lcom/google/android/gms/internal/ads/zzjy;)Lcom/google/android/gms/internal/ads/zzvf;
    //   522: invokespecial 1028	com/google/android/gms/internal/ads/zzlc:<init>	(Ljava/util/Collection;Lcom/google/android/gms/internal/ads/zzvf;)V
    //   525: aload 20
    //   527: aload 21
    //   529: aload_1
    //   530: invokestatic 1023	com/google/android/gms/internal/ads/zzjy:zza	(Lcom/google/android/gms/internal/ads/zzjy;)I
    //   533: aload_1
    //   534: invokestatic 1031	com/google/android/gms/internal/ads/zzjy:zzb	(Lcom/google/android/gms/internal/ads/zzjy;)J
    //   537: invokespecial 1034	com/google/android/gms/internal/ads/zzkc:<init>	(Lcom/google/android/gms/internal/ads/zzcx;IJ)V
    //   540: aload_0
    //   541: aload 20
    //   543: putfield 390	com/google/android/gms/internal/ads/zzkd:zzH	Lcom/google/android/gms/internal/ads/zzkc;
    //   546: aload_0
    //   547: aload_0
    //   548: getfield 214	com/google/android/gms/internal/ads/zzkd:zzr	Lcom/google/android/gms/internal/ads/zzkx;
    //   551: aload_1
    //   552: invokestatic 1014	com/google/android/gms/internal/ads/zzjy:zzc	(Lcom/google/android/gms/internal/ads/zzjy;)Ljava/util/List;
    //   555: aload_1
    //   556: invokestatic 1017	com/google/android/gms/internal/ads/zzjy:zzd	(Lcom/google/android/gms/internal/ads/zzjy;)Lcom/google/android/gms/internal/ads/zzvf;
    //   559: invokevirtual 1037	com/google/android/gms/internal/ads/zzkx:zzm	(Ljava/util/List;Lcom/google/android/gms/internal/ads/zzvf;)Lcom/google/android/gms/internal/ads/zzcx;
    //   562: iconst_0
    //   563: invokespecial 983	com/google/android/gms/internal/ads/zzkd:zzF	(Lcom/google/android/gms/internal/ads/zzcx;Z)V
    //   566: goto +3953 -> 4519
    //   569: aload_0
    //   570: aload_1
    //   571: getfield 986	android/os/Message:obj	Ljava/lang/Object;
    //   574: checkcast 528	com/google/android/gms/internal/ads/zzci
    //   577: iconst_0
    //   578: invokespecial 1039	com/google/android/gms/internal/ads/zzkd:zzG	(Lcom/google/android/gms/internal/ads/zzci;Z)V
    //   581: goto +3938 -> 4519
    //   584: aload_1
    //   585: getfield 986	android/os/Message:obj	Ljava/lang/Object;
    //   588: checkcast 849	com/google/android/gms/internal/ads/zzlb
    //   591: astore_1
    //   592: aload_1
    //   593: invokevirtual 1041	com/google/android/gms/internal/ads/zzlb:zzb	()Landroid/os/Looper;
    //   596: astore 20
    //   598: aload 20
    //   600: invokevirtual 1046	android/os/Looper:getThread	()Ljava/lang/Thread;
    //   603: invokevirtual 1049	java/lang/Thread:isAlive	()Z
    //   606: ifne +20 -> 626
    //   609: ldc_w 1051
    //   612: ldc_w 1053
    //   615: invokestatic 1056	com/google/android/gms/internal/ads/zzer:zze	(Ljava/lang/String;Ljava/lang/String;)V
    //   618: aload_1
    //   619: iconst_0
    //   620: invokevirtual 864	com/google/android/gms/internal/ads/zzlb:zzh	(Z)V
    //   623: goto +3896 -> 4519
    //   626: aload_0
    //   627: getfield 115	com/google/android/gms/internal/ads/zzkd:zzp	Lcom/google/android/gms/internal/ads/zzdz;
    //   630: aload 20
    //   632: aconst_null
    //   633: invokeinterface 200 3 0
    //   638: astore 21
    //   640: new 1058	com/google/android/gms/internal/ads/zzjv
    //   643: astore 20
    //   645: aload 20
    //   647: aload_0
    //   648: aload_1
    //   649: invokespecial 1061	com/google/android/gms/internal/ads/zzjv:<init>	(Lcom/google/android/gms/internal/ads/zzkd;Lcom/google/android/gms/internal/ads/zzlb;)V
    //   652: aload 21
    //   654: aload 20
    //   656: invokeinterface 1064 2 0
    //   661: pop
    //   662: goto +3857 -> 4519
    //   665: aload_1
    //   666: getfield 986	android/os/Message:obj	Ljava/lang/Object;
    //   669: checkcast 849	com/google/android/gms/internal/ads/zzlb
    //   672: astore_1
    //   673: aload_1
    //   674: invokevirtual 1041	com/google/android/gms/internal/ads/zzlb:zzb	()Landroid/os/Looper;
    //   677: aload_0
    //   678: getfield 232	com/google/android/gms/internal/ads/zzkd:zzj	Landroid/os/Looper;
    //   681: if_acmpne +39 -> 720
    //   684: aload_1
    //   685: invokestatic 885	com/google/android/gms/internal/ads/zzkd:zzaj	(Lcom/google/android/gms/internal/ads/zzlb;)V
    //   688: aload_0
    //   689: getfield 136	com/google/android/gms/internal/ads/zzkd:zzu	Lcom/google/android/gms/internal/ads/zzky;
    //   692: getfield 293	com/google/android/gms/internal/ads/zzky:zze	I
    //   695: istore_2
    //   696: iload_2
    //   697: iconst_3
    //   698: if_icmpeq +8 -> 706
    //   701: iload_2
    //   702: iconst_2
    //   703: if_icmpne +3816 -> 4519
    //   706: aload_0
    //   707: getfield 234	com/google/android/gms/internal/ads/zzkd:zzh	Lcom/google/android/gms/internal/ads/zzei;
    //   710: iconst_2
    //   711: invokeinterface 639 2 0
    //   716: pop
    //   717: goto +3802 -> 4519
    //   720: aload_0
    //   721: getfield 234	com/google/android/gms/internal/ads/zzkd:zzh	Lcom/google/android/gms/internal/ads/zzei;
    //   724: bipush 15
    //   726: aload_1
    //   727: invokeinterface 1067 3 0
    //   732: invokeinterface 1071 1 0
    //   737: goto +3782 -> 4519
    //   740: aload_1
    //   741: getfield 976	android/os/Message:arg1	I
    //   744: ifeq +9 -> 753
    //   747: iconst_1
    //   748: istore 18
    //   750: goto +6 -> 756
    //   753: iconst_0
    //   754: istore 18
    //   756: aload_1
    //   757: getfield 986	android/os/Message:obj	Ljava/lang/Object;
    //   760: checkcast 1073	java/util/concurrent/atomic/AtomicBoolean
    //   763: astore_1
    //   764: aload_0
    //   765: getfield 734	com/google/android/gms/internal/ads/zzkd:zzD	Z
    //   768: iload 18
    //   770: if_icmpeq +72 -> 842
    //   773: aload_0
    //   774: iload 18
    //   776: putfield 734	com/google/android/gms/internal/ads/zzkd:zzD	Z
    //   779: iload 18
    //   781: ifne +61 -> 842
    //   784: aload_0
    //   785: getfield 93	com/google/android/gms/internal/ads/zzkd:zza	[Lcom/google/android/gms/internal/ads/zzle;
    //   788: astore 20
    //   790: aload 20
    //   792: arraylength
    //   793: istore_2
    //   794: iconst_0
    //   795: istore_2
    //   796: iload_2
    //   797: iconst_2
    //   798: if_icmpge +44 -> 842
    //   801: aload 20
    //   803: iload_2
    //   804: aaload
    //   805: astore 21
    //   807: aload 21
    //   809: invokestatic 242	com/google/android/gms/internal/ads/zzkd:zzad	(Lcom/google/android/gms/internal/ads/zzle;)Z
    //   812: ifne +24 -> 836
    //   815: aload_0
    //   816: getfield 178	com/google/android/gms/internal/ads/zzkd:zzb	Ljava/util/Set;
    //   819: aload 21
    //   821: invokeinterface 274 2 0
    //   826: ifeq +10 -> 836
    //   829: aload 21
    //   831: invokeinterface 276 1 0
    //   836: iinc 2 1
    //   839: goto -43 -> 796
    //   842: aload_1
    //   843: ifnull +3676 -> 4519
    //   846: aload_0
    //   847: monitorenter
    //   848: aload_1
    //   849: iconst_1
    //   850: invokevirtual 1076	java/util/concurrent/atomic/AtomicBoolean:set	(Z)V
    //   853: aload_0
    //   854: invokevirtual 1079	java/lang/Object:notifyAll	()V
    //   857: aload_0
    //   858: monitorexit
    //   859: goto +3660 -> 4519
    //   862: astore_1
    //   863: aload_0
    //   864: monitorexit
    //   865: aload_1
    //   866: athrow
    //   867: aload_1
    //   868: getfield 976	android/os/Message:arg1	I
    //   871: ifeq +9 -> 880
    //   874: iconst_1
    //   875: istore 18
    //   877: goto +6 -> 883
    //   880: iconst_0
    //   881: istore 18
    //   883: aload_0
    //   884: iload 18
    //   886: putfield 105	com/google/android/gms/internal/ads/zzkd:zzC	Z
    //   889: aload_0
    //   890: getfield 207	com/google/android/gms/internal/ads/zzkd:zzq	Lcom/google/android/gms/internal/ads/zzkl;
    //   893: aload_0
    //   894: getfield 136	com/google/android/gms/internal/ads/zzkd:zzu	Lcom/google/android/gms/internal/ads/zzky;
    //   897: getfield 440	com/google/android/gms/internal/ads/zzky:zza	Lcom/google/android/gms/internal/ads/zzcx;
    //   900: iload 18
    //   902: invokevirtual 1082	com/google/android/gms/internal/ads/zzkl:zzq	(Lcom/google/android/gms/internal/ads/zzcx;Z)Z
    //   905: ifne +8 -> 913
    //   908: aload_0
    //   909: iconst_1
    //   910: invokespecial 495	com/google/android/gms/internal/ads/zzkd:zzQ	(Z)V
    //   913: aload_0
    //   914: iconst_0
    //   915: invokespecial 525	com/google/android/gms/internal/ads/zzkd:zzE	(Z)V
    //   918: goto +3601 -> 4519
    //   921: aload_1
    //   922: getfield 976	android/os/Message:arg1	I
    //   925: istore_2
    //   926: aload_0
    //   927: iload_2
    //   928: putfield 103	com/google/android/gms/internal/ads/zzkd:zzB	I
    //   931: aload_0
    //   932: getfield 207	com/google/android/gms/internal/ads/zzkd:zzq	Lcom/google/android/gms/internal/ads/zzkl;
    //   935: aload_0
    //   936: getfield 136	com/google/android/gms/internal/ads/zzkd:zzu	Lcom/google/android/gms/internal/ads/zzky;
    //   939: getfield 440	com/google/android/gms/internal/ads/zzky:zza	Lcom/google/android/gms/internal/ads/zzcx;
    //   942: iload_2
    //   943: invokevirtual 1085	com/google/android/gms/internal/ads/zzkl:zzp	(Lcom/google/android/gms/internal/ads/zzcx;I)Z
    //   946: ifne +8 -> 954
    //   949: aload_0
    //   950: iconst_1
    //   951: invokespecial 495	com/google/android/gms/internal/ads/zzkd:zzQ	(Z)V
    //   954: aload_0
    //   955: iconst_0
    //   956: invokespecial 525	com/google/android/gms/internal/ads/zzkd:zzE	(Z)V
    //   959: goto +3560 -> 4519
    //   962: aload_0
    //   963: invokespecial 973	com/google/android/gms/internal/ads/zzkd:zzK	()V
    //   966: goto +3553 -> 4519
    //   969: aload_1
    //   970: getfield 986	android/os/Message:obj	Ljava/lang/Object;
    //   973: checkcast 583	com/google/android/gms/internal/ads/zztj
    //   976: astore_1
    //   977: aload_0
    //   978: getfield 207	com/google/android/gms/internal/ads/zzkd:zzq	Lcom/google/android/gms/internal/ads/zzkl;
    //   981: aload_1
    //   982: invokevirtual 1088	com/google/android/gms/internal/ads/zzkl:zzl	(Lcom/google/android/gms/internal/ads/zztj;)Z
    //   985: ifeq +3534 -> 4519
    //   988: aload_0
    //   989: getfield 207	com/google/android/gms/internal/ads/zzkd:zzq	Lcom/google/android/gms/internal/ads/zzkl;
    //   992: aload_0
    //   993: getfield 301	com/google/android/gms/internal/ads/zzkd:zzI	J
    //   996: invokevirtual 1089	com/google/android/gms/internal/ads/zzkl:zzk	(J)V
    //   999: aload_0
    //   1000: invokespecial 632	com/google/android/gms/internal/ads/zzkd:zzI	()V
    //   1003: goto +3516 -> 4519
    //   1006: aload_1
    //   1007: getfield 986	android/os/Message:obj	Ljava/lang/Object;
    //   1010: checkcast 583	com/google/android/gms/internal/ads/zztj
    //   1013: astore_1
    //   1014: aload_0
    //   1015: getfield 207	com/google/android/gms/internal/ads/zzkd:zzq	Lcom/google/android/gms/internal/ads/zzkl;
    //   1018: aload_1
    //   1019: invokevirtual 1088	com/google/android/gms/internal/ads/zzkl:zzl	(Lcom/google/android/gms/internal/ads/zztj;)Z
    //   1022: ifeq +3497 -> 4519
    //   1025: aload_0
    //   1026: getfield 207	com/google/android/gms/internal/ads/zzkd:zzq	Lcom/google/android/gms/internal/ads/zzkl;
    //   1029: invokevirtual 356	com/google/android/gms/internal/ads/zzkl:zzc	()Lcom/google/android/gms/internal/ads/zzki;
    //   1032: astore 20
    //   1034: aload 20
    //   1036: aload_0
    //   1037: getfield 162	com/google/android/gms/internal/ads/zzkd:zzn	Lcom/google/android/gms/internal/ads/zzhy;
    //   1040: invokevirtual 573	com/google/android/gms/internal/ads/zzhy:zzc	()Lcom/google/android/gms/internal/ads/zzci;
    //   1043: getfield 531	com/google/android/gms/internal/ads/zzci:zzc	F
    //   1046: aload_0
    //   1047: getfield 136	com/google/android/gms/internal/ads/zzkd:zzu	Lcom/google/android/gms/internal/ads/zzky;
    //   1050: getfield 440	com/google/android/gms/internal/ads/zzky:zza	Lcom/google/android/gms/internal/ads/zzcx;
    //   1053: invokevirtual 1092	com/google/android/gms/internal/ads/zzki:zzl	(FLcom/google/android/gms/internal/ads/zzcx;)V
    //   1056: aload_0
    //   1057: aload 20
    //   1059: getfield 329	com/google/android/gms/internal/ads/zzki:zzf	Lcom/google/android/gms/internal/ads/zzkj;
    //   1062: getfield 334	com/google/android/gms/internal/ads/zzkj:zza	Lcom/google/android/gms/internal/ads/zztl;
    //   1065: aload 20
    //   1067: invokevirtual 383	com/google/android/gms/internal/ads/zzki:zzh	()Lcom/google/android/gms/internal/ads/zzvk;
    //   1070: aload 20
    //   1072: invokevirtual 263	com/google/android/gms/internal/ads/zzki:zzi	()Lcom/google/android/gms/internal/ads/zzxe;
    //   1075: invokespecial 387	com/google/android/gms/internal/ads/zzkd:zzY	(Lcom/google/android/gms/internal/ads/zztl;Lcom/google/android/gms/internal/ads/zzvk;Lcom/google/android/gms/internal/ads/zzxe;)V
    //   1078: aload 20
    //   1080: aload_0
    //   1081: getfield 207	com/google/android/gms/internal/ads/zzkd:zzq	Lcom/google/android/gms/internal/ads/zzkl;
    //   1084: invokevirtual 278	com/google/android/gms/internal/ads/zzkl:zzd	()Lcom/google/android/gms/internal/ads/zzki;
    //   1087: if_acmpne +61 -> 1148
    //   1090: aload_0
    //   1091: aload 20
    //   1093: getfield 329	com/google/android/gms/internal/ads/zzki:zzf	Lcom/google/android/gms/internal/ads/zzkj;
    //   1096: getfield 570	com/google/android/gms/internal/ads/zzkj:zzb	J
    //   1099: invokespecial 623	com/google/android/gms/internal/ads/zzkd:zzN	(J)V
    //   1102: aload_0
    //   1103: invokespecial 905	com/google/android/gms/internal/ads/zzkd:zzB	()V
    //   1106: aload_0
    //   1107: getfield 136	com/google/android/gms/internal/ads/zzkd:zzu	Lcom/google/android/gms/internal/ads/zzky;
    //   1110: astore 21
    //   1112: aload 21
    //   1114: getfield 358	com/google/android/gms/internal/ads/zzky:zzb	Lcom/google/android/gms/internal/ads/zztl;
    //   1117: astore_1
    //   1118: aload 20
    //   1120: getfield 329	com/google/android/gms/internal/ads/zzki:zzf	Lcom/google/android/gms/internal/ads/zzkj;
    //   1123: getfield 570	com/google/android/gms/internal/ads/zzkj:zzb	J
    //   1126: lstore 8
    //   1128: aload_0
    //   1129: aload_0
    //   1130: aload_1
    //   1131: lload 8
    //   1133: aload 21
    //   1135: getfield 410	com/google/android/gms/internal/ads/zzky:zzc	J
    //   1138: lload 8
    //   1140: iconst_0
    //   1141: iconst_5
    //   1142: invokespecial 515	com/google/android/gms/internal/ads/zzkd:zzz	(Lcom/google/android/gms/internal/ads/zztl;JJJZI)Lcom/google/android/gms/internal/ads/zzky;
    //   1145: putfield 136	com/google/android/gms/internal/ads/zzkd:zzu	Lcom/google/android/gms/internal/ads/zzky;
    //   1148: aload_0
    //   1149: invokespecial 632	com/google/android/gms/internal/ads/zzkd:zzI	()V
    //   1152: goto +3367 -> 4519
    //   1155: aload_0
    //   1156: iconst_1
    //   1157: iconst_0
    //   1158: iconst_1
    //   1159: iconst_0
    //   1160: invokespecial 477	com/google/android/gms/internal/ads/zzkd:zzL	(ZZZZ)V
    //   1163: iconst_0
    //   1164: istore_2
    //   1165: aload_0
    //   1166: getfield 93	com/google/android/gms/internal/ads/zzkd:zza	[Lcom/google/android/gms/internal/ads/zzle;
    //   1169: arraylength
    //   1170: istore_3
    //   1171: iload_2
    //   1172: iconst_2
    //   1173: if_icmpge +31 -> 1204
    //   1176: aload_0
    //   1177: getfield 147	com/google/android/gms/internal/ads/zzkd:zzc	[Lcom/google/android/gms/internal/ads/zzlf;
    //   1180: iload_2
    //   1181: aaload
    //   1182: invokeinterface 1094 1 0
    //   1187: aload_0
    //   1188: getfield 93	com/google/android/gms/internal/ads/zzkd:zza	[Lcom/google/android/gms/internal/ads/zzle;
    //   1191: iload_2
    //   1192: aaload
    //   1193: invokeinterface 1096 1 0
    //   1198: iinc 2 1
    //   1201: goto -36 -> 1165
    //   1204: aload_0
    //   1205: getfield 99	com/google/android/gms/internal/ads/zzkd:zzf	Lcom/google/android/gms/internal/ads/zzkg;
    //   1208: invokeinterface 1098 1 0
    //   1213: aload_0
    //   1214: iconst_1
    //   1215: invokespecial 474	com/google/android/gms/internal/ads/zzkd:zzT	(I)V
    //   1218: aload_0
    //   1219: getfield 223	com/google/android/gms/internal/ads/zzkd:zzi	Landroid/os/HandlerThread;
    //   1222: astore_1
    //   1223: aload_1
    //   1224: ifnull +8 -> 1232
    //   1227: aload_1
    //   1228: invokevirtual 1101	android/os/HandlerThread:quit	()Z
    //   1231: pop
    //   1232: aload_0
    //   1233: monitorenter
    //   1234: aload_0
    //   1235: iconst_1
    //   1236: putfield 804	com/google/android/gms/internal/ads/zzkd:zzw	Z
    //   1239: aload_0
    //   1240: invokevirtual 1079	java/lang/Object:notifyAll	()V
    //   1243: aload_0
    //   1244: monitorexit
    //   1245: iconst_1
    //   1246: ireturn
    //   1247: astore_1
    //   1248: aload_0
    //   1249: monitorexit
    //   1250: aload_1
    //   1251: athrow
    //   1252: aload_0
    //   1253: iconst_0
    //   1254: iconst_1
    //   1255: invokespecial 350	com/google/android/gms/internal/ads/zzkd:zzV	(ZZ)V
    //   1258: goto +3261 -> 4519
    //   1261: aload_0
    //   1262: aload_1
    //   1263: getfield 986	android/os/Message:obj	Ljava/lang/Object;
    //   1266: checkcast 1103	com/google/android/gms/internal/ads/zzlh
    //   1269: putfield 107	com/google/android/gms/internal/ads/zzkd:zzt	Lcom/google/android/gms/internal/ads/zzlh;
    //   1272: goto +3247 -> 4519
    //   1275: aload_0
    //   1276: aload_1
    //   1277: getfield 986	android/os/Message:obj	Ljava/lang/Object;
    //   1280: checkcast 528	com/google/android/gms/internal/ads/zzci
    //   1283: invokespecial 777	com/google/android/gms/internal/ads/zzkd:zzR	(Lcom/google/android/gms/internal/ads/zzci;)V
    //   1286: aload_0
    //   1287: aload_0
    //   1288: getfield 162	com/google/android/gms/internal/ads/zzkd:zzn	Lcom/google/android/gms/internal/ads/zzhy;
    //   1291: invokevirtual 573	com/google/android/gms/internal/ads/zzhy:zzc	()Lcom/google/android/gms/internal/ads/zzci;
    //   1294: iconst_1
    //   1295: invokespecial 1039	com/google/android/gms/internal/ads/zzkd:zzG	(Lcom/google/android/gms/internal/ads/zzci;Z)V
    //   1298: goto +3221 -> 4519
    //   1301: aload_1
    //   1302: getfield 986	android/os/Message:obj	Ljava/lang/Object;
    //   1305: checkcast 418	com/google/android/gms/internal/ads/zzkc
    //   1308: astore 20
    //   1310: aload_0
    //   1311: getfield 143	com/google/android/gms/internal/ads/zzkd:zzv	Lcom/google/android/gms/internal/ads/zzkb;
    //   1314: iconst_1
    //   1315: invokevirtual 536	com/google/android/gms/internal/ads/zzkb:zza	(I)V
    //   1318: aload_0
    //   1319: getfield 136	com/google/android/gms/internal/ads/zzkd:zzu	Lcom/google/android/gms/internal/ads/zzky;
    //   1322: getfield 440	com/google/android/gms/internal/ads/zzky:zza	Lcom/google/android/gms/internal/ads/zzcx;
    //   1325: aload 20
    //   1327: iconst_1
    //   1328: aload_0
    //   1329: getfield 103	com/google/android/gms/internal/ads/zzkd:zzB	I
    //   1332: aload_0
    //   1333: getfield 105	com/google/android/gms/internal/ads/zzkd:zzC	Z
    //   1336: aload_0
    //   1337: getfield 183	com/google/android/gms/internal/ads/zzkd:zzk	Lcom/google/android/gms/internal/ads/zzcw;
    //   1340: aload_0
    //   1341: getfield 188	com/google/android/gms/internal/ads/zzkd:zzl	Lcom/google/android/gms/internal/ads/zzcu;
    //   1344: invokestatic 413	com/google/android/gms/internal/ads/zzkd:zzy	(Lcom/google/android/gms/internal/ads/zzcx;Lcom/google/android/gms/internal/ads/zzkc;ZIZLcom/google/android/gms/internal/ads/zzcw;Lcom/google/android/gms/internal/ads/zzcu;)Landroid/util/Pair;
    //   1347: astore 21
    //   1349: aload 21
    //   1351: ifnonnull +64 -> 1415
    //   1354: aload_0
    //   1355: aload_0
    //   1356: getfield 136	com/google/android/gms/internal/ads/zzkd:zzu	Lcom/google/android/gms/internal/ads/zzky;
    //   1359: getfield 440	com/google/android/gms/internal/ads/zzky:zza	Lcom/google/android/gms/internal/ads/zzcx;
    //   1362: invokespecial 658	com/google/android/gms/internal/ads/zzkd:zzx	(Lcom/google/android/gms/internal/ads/zzcx;)Landroid/util/Pair;
    //   1365: astore 22
    //   1367: aload 22
    //   1369: getfield 424	android/util/Pair:first	Ljava/lang/Object;
    //   1372: checkcast 399	com/google/android/gms/internal/ads/zztl
    //   1375: astore_1
    //   1376: aload 22
    //   1378: getfield 432	android/util/Pair:second	Ljava/lang/Object;
    //   1381: checkcast 434	java/lang/Long
    //   1384: invokevirtual 437	java/lang/Long:longValue	()J
    //   1387: lstore 8
    //   1389: aload_0
    //   1390: getfield 136	com/google/android/gms/internal/ads/zzkd:zzu	Lcom/google/android/gms/internal/ads/zzky;
    //   1393: getfield 440	com/google/android/gms/internal/ads/zzky:zza	Lcom/google/android/gms/internal/ads/zzcx;
    //   1396: invokevirtual 394	com/google/android/gms/internal/ads/zzcx:zzo	()Z
    //   1399: istore 18
    //   1401: ldc2_w 116
    //   1404: lstore 12
    //   1406: iload 18
    //   1408: iconst_1
    //   1409: ixor
    //   1410: istore 18
    //   1412: goto +158 -> 1570
    //   1415: aload 21
    //   1417: getfield 424	android/util/Pair:first	Ljava/lang/Object;
    //   1420: astore_1
    //   1421: aload 21
    //   1423: getfield 432	android/util/Pair:second	Ljava/lang/Object;
    //   1426: checkcast 434	java/lang/Long
    //   1429: invokevirtual 437	java/lang/Long:longValue	()J
    //   1432: lstore 8
    //   1434: aload 20
    //   1436: getfield 419	com/google/android/gms/internal/ads/zzkc:zzc	J
    //   1439: ldc2_w 116
    //   1442: lcmp
    //   1443: ifne +11 -> 1454
    //   1446: ldc2_w 116
    //   1449: lstore 10
    //   1451: goto +7 -> 1458
    //   1454: lload 8
    //   1456: lstore 10
    //   1458: aload_0
    //   1459: getfield 207	com/google/android/gms/internal/ads/zzkd:zzq	Lcom/google/android/gms/internal/ads/zzkl;
    //   1462: aload_0
    //   1463: getfield 136	com/google/android/gms/internal/ads/zzkd:zzu	Lcom/google/android/gms/internal/ads/zzky;
    //   1466: getfield 440	com/google/android/gms/internal/ads/zzky:zza	Lcom/google/android/gms/internal/ads/zzcx;
    //   1469: aload_1
    //   1470: lload 8
    //   1472: invokevirtual 457	com/google/android/gms/internal/ads/zzkl:zzh	(Lcom/google/android/gms/internal/ads/zzcx;Ljava/lang/Object;J)Lcom/google/android/gms/internal/ads/zztl;
    //   1475: astore_1
    //   1476: aload_1
    //   1477: invokevirtual 408	com/google/android/gms/internal/ads/zzbx:zzb	()Z
    //   1480: ifeq +61 -> 1541
    //   1483: aload_0
    //   1484: getfield 136	com/google/android/gms/internal/ads/zzkd:zzu	Lcom/google/android/gms/internal/ads/zzky;
    //   1487: getfield 440	com/google/android/gms/internal/ads/zzky:zza	Lcom/google/android/gms/internal/ads/zzcx;
    //   1490: aload_1
    //   1491: getfield 402	com/google/android/gms/internal/ads/zztl:zza	Ljava/lang/Object;
    //   1494: aload_0
    //   1495: getfield 188	com/google/android/gms/internal/ads/zzkd:zzl	Lcom/google/android/gms/internal/ads/zzcu;
    //   1498: invokevirtual 427	com/google/android/gms/internal/ads/zzcx:zzn	(Ljava/lang/Object;Lcom/google/android/gms/internal/ads/zzcu;)Lcom/google/android/gms/internal/ads/zzcu;
    //   1501: pop
    //   1502: aload_0
    //   1503: getfield 188	com/google/android/gms/internal/ads/zzkd:zzl	Lcom/google/android/gms/internal/ads/zzcu;
    //   1506: aload_1
    //   1507: getfield 461	com/google/android/gms/internal/ads/zztl:zzb	I
    //   1510: invokevirtual 468	com/google/android/gms/internal/ads/zzcu:zze	(I)I
    //   1513: aload_1
    //   1514: getfield 465	com/google/android/gms/internal/ads/zztl:zzc	I
    //   1517: if_icmpne +11 -> 1528
    //   1520: aload_0
    //   1521: getfield 188	com/google/android/gms/internal/ads/zzkd:zzl	Lcom/google/android/gms/internal/ads/zzcu;
    //   1524: invokevirtual 470	com/google/android/gms/internal/ads/zzcu:zzj	()J
    //   1527: pop2
    //   1528: lconst_0
    //   1529: lstore 8
    //   1531: iconst_1
    //   1532: istore 18
    //   1534: lload 10
    //   1536: lstore 12
    //   1538: goto +32 -> 1570
    //   1541: aload 20
    //   1543: getfield 419	com/google/android/gms/internal/ads/zzkc:zzc	J
    //   1546: lstore 12
    //   1548: lload 12
    //   1550: ldc2_w 116
    //   1553: lcmp
    //   1554: ifne +9 -> 1563
    //   1557: iconst_1
    //   1558: istore 18
    //   1560: goto +6 -> 1566
    //   1563: iconst_0
    //   1564: istore 18
    //   1566: lload 10
    //   1568: lstore 12
    //   1570: aload_0
    //   1571: getfield 136	com/google/android/gms/internal/ads/zzkd:zzu	Lcom/google/android/gms/internal/ads/zzky;
    //   1574: getfield 440	com/google/android/gms/internal/ads/zzky:zza	Lcom/google/android/gms/internal/ads/zzcx;
    //   1577: invokevirtual 394	com/google/android/gms/internal/ads/zzcx:zzo	()Z
    //   1580: istore 19
    //   1582: iload 19
    //   1584: ifeq +17 -> 1601
    //   1587: aload_0
    //   1588: aload 20
    //   1590: putfield 390	com/google/android/gms/internal/ads/zzkd:zzH	Lcom/google/android/gms/internal/ads/zzkc;
    //   1593: goto +37 -> 1630
    //   1596: astore 20
    //   1598: goto +314 -> 1912
    //   1601: aload 21
    //   1603: ifnonnull +30 -> 1633
    //   1606: aload_0
    //   1607: getfield 136	com/google/android/gms/internal/ads/zzkd:zzu	Lcom/google/android/gms/internal/ads/zzky;
    //   1610: getfield 293	com/google/android/gms/internal/ads/zzky:zze	I
    //   1613: iconst_1
    //   1614: if_icmpeq +8 -> 1622
    //   1617: aload_0
    //   1618: iconst_4
    //   1619: invokespecial 474	com/google/android/gms/internal/ads/zzkd:zzT	(I)V
    //   1622: aload_0
    //   1623: iconst_0
    //   1624: iconst_1
    //   1625: iconst_0
    //   1626: iconst_1
    //   1627: invokespecial 477	com/google/android/gms/internal/ads/zzkd:zzL	(ZZZZ)V
    //   1630: goto +248 -> 1878
    //   1633: aload_1
    //   1634: aload_0
    //   1635: getfield 136	com/google/android/gms/internal/ads/zzkd:zzu	Lcom/google/android/gms/internal/ads/zzky;
    //   1638: getfield 358	com/google/android/gms/internal/ads/zzky:zzb	Lcom/google/android/gms/internal/ads/zztl;
    //   1641: invokevirtual 365	com/google/android/gms/internal/ads/zzbx:equals	(Ljava/lang/Object;)Z
    //   1644: ifeq +144 -> 1788
    //   1647: aload_0
    //   1648: getfield 207	com/google/android/gms/internal/ads/zzkd:zzq	Lcom/google/android/gms/internal/ads/zzkl;
    //   1651: invokevirtual 278	com/google/android/gms/internal/ads/zzkl:zzd	()Lcom/google/android/gms/internal/ads/zzki;
    //   1654: astore 20
    //   1656: aload 20
    //   1658: ifnull +39 -> 1697
    //   1661: aload 20
    //   1663: getfield 380	com/google/android/gms/internal/ads/zzki:zzd	Z
    //   1666: ifeq +31 -> 1697
    //   1669: lload 8
    //   1671: lconst_0
    //   1672: lcmp
    //   1673: ifeq +24 -> 1697
    //   1676: aload 20
    //   1678: getfield 581	com/google/android/gms/internal/ads/zzki:zza	Lcom/google/android/gms/internal/ads/zztj;
    //   1681: lload 8
    //   1683: aload_0
    //   1684: getfield 107	com/google/android/gms/internal/ads/zzkd:zzt	Lcom/google/android/gms/internal/ads/zzlh;
    //   1687: invokeinterface 1106 4 0
    //   1692: lstore 10
    //   1694: goto +7 -> 1701
    //   1697: lload 8
    //   1699: lstore 10
    //   1701: lload 10
    //   1703: invokestatic 1108	com/google/android/gms/internal/ads/zzfn:zzq	(J)J
    //   1706: lstore 16
    //   1708: aload_0
    //   1709: getfield 136	com/google/android/gms/internal/ads/zzkd:zzu	Lcom/google/android/gms/internal/ads/zzky;
    //   1712: astore 20
    //   1714: lload 10
    //   1716: lstore 14
    //   1718: lload 16
    //   1720: aload 20
    //   1722: getfield 370	com/google/android/gms/internal/ads/zzky:zzr	J
    //   1725: invokestatic 1108	com/google/android/gms/internal/ads/zzfn:zzq	(J)J
    //   1728: lcmp
    //   1729: ifne +63 -> 1792
    //   1732: aload_0
    //   1733: getfield 136	com/google/android/gms/internal/ads/zzkd:zzu	Lcom/google/android/gms/internal/ads/zzky;
    //   1736: astore 20
    //   1738: aload 20
    //   1740: getfield 293	com/google/android/gms/internal/ads/zzky:zze	I
    //   1743: istore_2
    //   1744: iload_2
    //   1745: iconst_2
    //   1746: if_icmpeq +12 -> 1758
    //   1749: lload 10
    //   1751: lstore 14
    //   1753: iload_2
    //   1754: iconst_3
    //   1755: if_icmpne +37 -> 1792
    //   1758: aload 20
    //   1760: getfield 370	com/google/android/gms/internal/ads/zzky:zzr	J
    //   1763: lstore 10
    //   1765: aload_0
    //   1766: aload_1
    //   1767: lload 10
    //   1769: lload 12
    //   1771: lload 10
    //   1773: iload 18
    //   1775: iconst_2
    //   1776: invokespecial 515	com/google/android/gms/internal/ads/zzkd:zzz	(Lcom/google/android/gms/internal/ads/zztl;JJJZI)Lcom/google/android/gms/internal/ads/zzky;
    //   1779: astore_1
    //   1780: aload_0
    //   1781: aload_1
    //   1782: putfield 136	com/google/android/gms/internal/ads/zzkd:zzu	Lcom/google/android/gms/internal/ads/zzky;
    //   1785: goto +2734 -> 4519
    //   1788: lload 8
    //   1790: lstore 14
    //   1792: aload_0
    //   1793: getfield 136	com/google/android/gms/internal/ads/zzkd:zzu	Lcom/google/android/gms/internal/ads/zzky;
    //   1796: getfield 293	com/google/android/gms/internal/ads/zzky:zze	I
    //   1799: iconst_4
    //   1800: if_icmpne +9 -> 1809
    //   1803: iconst_1
    //   1804: istore 19
    //   1806: goto +6 -> 1812
    //   1809: iconst_0
    //   1810: istore 19
    //   1812: aload_0
    //   1813: aload_1
    //   1814: lload 14
    //   1816: iload 19
    //   1818: invokespecial 505	com/google/android/gms/internal/ads/zzkd:zzv	(Lcom/google/android/gms/internal/ads/zztl;JZ)J
    //   1821: lstore 10
    //   1823: lload 8
    //   1825: lload 10
    //   1827: lcmp
    //   1828: ifeq +8 -> 1836
    //   1831: iconst_1
    //   1832: istore_2
    //   1833: goto +5 -> 1838
    //   1836: iconst_0
    //   1837: istore_2
    //   1838: iload 18
    //   1840: iload_2
    //   1841: ior
    //   1842: istore 18
    //   1844: aload_0
    //   1845: getfield 136	com/google/android/gms/internal/ads/zzkd:zzu	Lcom/google/android/gms/internal/ads/zzky;
    //   1848: astore 20
    //   1850: aload 20
    //   1852: getfield 440	com/google/android/gms/internal/ads/zzky:zza	Lcom/google/android/gms/internal/ads/zzcx;
    //   1855: astore 21
    //   1857: aload_0
    //   1858: aload 21
    //   1860: aload_1
    //   1861: aload 21
    //   1863: aload 20
    //   1865: getfield 358	com/google/android/gms/internal/ads/zzky:zzb	Lcom/google/android/gms/internal/ads/zztl;
    //   1868: lload 12
    //   1870: iconst_1
    //   1871: invokespecial 509	com/google/android/gms/internal/ads/zzkd:zzaa	(Lcom/google/android/gms/internal/ads/zzcx;Lcom/google/android/gms/internal/ads/zztl;Lcom/google/android/gms/internal/ads/zzcx;Lcom/google/android/gms/internal/ads/zztl;JZ)V
    //   1874: lload 10
    //   1876: lstore 8
    //   1878: aload_0
    //   1879: aload_1
    //   1880: lload 8
    //   1882: lload 12
    //   1884: lload 8
    //   1886: iload 18
    //   1888: iconst_2
    //   1889: invokespecial 515	com/google/android/gms/internal/ads/zzkd:zzz	(Lcom/google/android/gms/internal/ads/zztl;JJJZI)Lcom/google/android/gms/internal/ads/zzky;
    //   1892: astore_1
    //   1893: goto -113 -> 1780
    //   1896: astore 20
    //   1898: lload 10
    //   1900: lstore 8
    //   1902: goto +10 -> 1912
    //   1905: astore 20
    //   1907: goto +5 -> 1912
    //   1910: astore 20
    //   1912: aload_0
    //   1913: aload_0
    //   1914: aload_1
    //   1915: lload 8
    //   1917: lload 12
    //   1919: lload 8
    //   1921: iload 18
    //   1923: iconst_2
    //   1924: invokespecial 515	com/google/android/gms/internal/ads/zzkd:zzz	(Lcom/google/android/gms/internal/ads/zztl;JJJZI)Lcom/google/android/gms/internal/ads/zzky;
    //   1927: putfield 136	com/google/android/gms/internal/ads/zzkd:zzu	Lcom/google/android/gms/internal/ads/zzky;
    //   1930: aload 20
    //   1932: athrow
    //   1933: invokestatic 1111	android/os/SystemClock:uptimeMillis	()J
    //   1936: lstore 10
    //   1938: aload_0
    //   1939: getfield 234	com/google/android/gms/internal/ads/zzkd:zzh	Lcom/google/android/gms/internal/ads/zzei;
    //   1942: iconst_2
    //   1943: invokeinterface 643 2 0
    //   1948: aload_0
    //   1949: getfield 136	com/google/android/gms/internal/ads/zzkd:zzu	Lcom/google/android/gms/internal/ads/zzky;
    //   1952: getfield 440	com/google/android/gms/internal/ads/zzky:zza	Lcom/google/android/gms/internal/ads/zzcx;
    //   1955: invokevirtual 394	com/google/android/gms/internal/ads/zzcx:zzo	()Z
    //   1958: ifne +1120 -> 3078
    //   1961: aload_0
    //   1962: getfield 214	com/google/android/gms/internal/ads/zzkd:zzr	Lcom/google/android/gms/internal/ads/zzkx;
    //   1965: invokevirtual 926	com/google/android/gms/internal/ads/zzkx:zzi	()Z
    //   1968: ifne +6 -> 1974
    //   1971: goto +1107 -> 3078
    //   1974: aload_0
    //   1975: getfield 207	com/google/android/gms/internal/ads/zzkd:zzq	Lcom/google/android/gms/internal/ads/zzkl;
    //   1978: aload_0
    //   1979: getfield 301	com/google/android/gms/internal/ads/zzkd:zzI	J
    //   1982: invokevirtual 1089	com/google/android/gms/internal/ads/zzkl:zzk	(J)V
    //   1985: aload_0
    //   1986: getfield 207	com/google/android/gms/internal/ads/zzkd:zzq	Lcom/google/android/gms/internal/ads/zzkl;
    //   1989: invokevirtual 1113	com/google/android/gms/internal/ads/zzkl:zzn	()Z
    //   1992: ifeq +98 -> 2090
    //   1995: aload_0
    //   1996: getfield 207	com/google/android/gms/internal/ads/zzkd:zzq	Lcom/google/android/gms/internal/ads/zzkl;
    //   1999: aload_0
    //   2000: getfield 301	com/google/android/gms/internal/ads/zzkd:zzI	J
    //   2003: aload_0
    //   2004: getfield 136	com/google/android/gms/internal/ads/zzkd:zzu	Lcom/google/android/gms/internal/ads/zzky;
    //   2007: invokevirtual 1116	com/google/android/gms/internal/ads/zzkl:zzf	(JLcom/google/android/gms/internal/ads/zzky;)Lcom/google/android/gms/internal/ads/zzkj;
    //   2010: astore_1
    //   2011: aload_1
    //   2012: ifnull +78 -> 2090
    //   2015: aload_0
    //   2016: getfield 207	com/google/android/gms/internal/ads/zzkd:zzq	Lcom/google/android/gms/internal/ads/zzkl;
    //   2019: aload_0
    //   2020: getfield 147	com/google/android/gms/internal/ads/zzkd:zzc	[Lcom/google/android/gms/internal/ads/zzlf;
    //   2023: aload_0
    //   2024: getfield 95	com/google/android/gms/internal/ads/zzkd:zzd	Lcom/google/android/gms/internal/ads/zzxd;
    //   2027: aload_0
    //   2028: getfield 99	com/google/android/gms/internal/ads/zzkd:zzf	Lcom/google/android/gms/internal/ads/zzkg;
    //   2031: invokeinterface 1119 1 0
    //   2036: aload_0
    //   2037: getfield 214	com/google/android/gms/internal/ads/zzkd:zzr	Lcom/google/android/gms/internal/ads/zzkx;
    //   2040: aload_1
    //   2041: aload_0
    //   2042: getfield 97	com/google/android/gms/internal/ads/zzkd:zze	Lcom/google/android/gms/internal/ads/zzxe;
    //   2045: invokevirtual 1122	com/google/android/gms/internal/ads/zzkl:zzr	([Lcom/google/android/gms/internal/ads/zzlf;Lcom/google/android/gms/internal/ads/zzxd;Lcom/google/android/gms/internal/ads/zzxm;Lcom/google/android/gms/internal/ads/zzkx;Lcom/google/android/gms/internal/ads/zzkj;Lcom/google/android/gms/internal/ads/zzxe;)Lcom/google/android/gms/internal/ads/zzki;
    //   2048: astore 20
    //   2050: aload 20
    //   2052: getfield 581	com/google/android/gms/internal/ads/zzki:zza	Lcom/google/android/gms/internal/ads/zztj;
    //   2055: aload_0
    //   2056: aload_1
    //   2057: getfield 570	com/google/android/gms/internal/ads/zzkj:zzb	J
    //   2060: invokeinterface 1125 4 0
    //   2065: aload_0
    //   2066: getfield 207	com/google/android/gms/internal/ads/zzkd:zzq	Lcom/google/android/gms/internal/ads/zzkl;
    //   2069: invokevirtual 278	com/google/android/gms/internal/ads/zzkl:zzd	()Lcom/google/android/gms/internal/ads/zzki;
    //   2072: aload 20
    //   2074: if_acmpne +11 -> 2085
    //   2077: aload_0
    //   2078: aload_1
    //   2079: getfield 570	com/google/android/gms/internal/ads/zzkj:zzb	J
    //   2082: invokespecial 623	com/google/android/gms/internal/ads/zzkd:zzN	(J)V
    //   2085: aload_0
    //   2086: iconst_0
    //   2087: invokespecial 525	com/google/android/gms/internal/ads/zzkd:zzE	(Z)V
    //   2090: aload_0
    //   2091: getfield 588	com/google/android/gms/internal/ads/zzkd:zzA	Z
    //   2094: ifeq +18 -> 2112
    //   2097: aload_0
    //   2098: aload_0
    //   2099: invokespecial 563	com/google/android/gms/internal/ads/zzkd:zzac	()Z
    //   2102: putfield 588	com/google/android/gms/internal/ads/zzkd:zzA	Z
    //   2105: aload_0
    //   2106: invokespecial 594	com/google/android/gms/internal/ads/zzkd:zzX	()V
    //   2109: goto +7 -> 2116
    //   2112: aload_0
    //   2113: invokespecial 632	com/google/android/gms/internal/ads/zzkd:zzI	()V
    //   2116: aload_0
    //   2117: getfield 207	com/google/android/gms/internal/ads/zzkd:zzq	Lcom/google/android/gms/internal/ads/zzkl;
    //   2120: invokevirtual 258	com/google/android/gms/internal/ads/zzkl:zze	()Lcom/google/android/gms/internal/ads/zzki;
    //   2123: astore 20
    //   2125: aload 20
    //   2127: ifnonnull +6 -> 2133
    //   2130: goto +526 -> 2656
    //   2133: aload 20
    //   2135: invokevirtual 502	com/google/android/gms/internal/ads/zzki:zzg	()Lcom/google/android/gms/internal/ads/zzki;
    //   2138: ifnull +389 -> 2527
    //   2141: aload_0
    //   2142: getfield 677	com/google/android/gms/internal/ads/zzkd:zzy	Z
    //   2145: ifeq +6 -> 2151
    //   2148: goto +379 -> 2527
    //   2151: aload_0
    //   2152: getfield 207	com/google/android/gms/internal/ads/zzkd:zzq	Lcom/google/android/gms/internal/ads/zzkl;
    //   2155: invokevirtual 258	com/google/android/gms/internal/ads/zzkl:zze	()Lcom/google/android/gms/internal/ads/zzki;
    //   2158: astore_1
    //   2159: aload_1
    //   2160: getfield 380	com/google/android/gms/internal/ads/zzki:zzd	Z
    //   2163: ifeq -33 -> 2130
    //   2166: iconst_0
    //   2167: istore_2
    //   2168: aload_0
    //   2169: getfield 93	com/google/android/gms/internal/ads/zzkd:zza	[Lcom/google/android/gms/internal/ads/zzle;
    //   2172: astore 21
    //   2174: aload 21
    //   2176: arraylength
    //   2177: istore_3
    //   2178: iload_2
    //   2179: iconst_2
    //   2180: if_icmpge +67 -> 2247
    //   2183: aload 21
    //   2185: iload_2
    //   2186: aaload
    //   2187: astore 21
    //   2189: aload_1
    //   2190: getfield 299	com/google/android/gms/internal/ads/zzki:zzc	[Lcom/google/android/gms/internal/ads/zzvc;
    //   2193: iload_2
    //   2194: aaload
    //   2195: astore 22
    //   2197: aload 21
    //   2199: invokeinterface 480 1 0
    //   2204: aload 22
    //   2206: if_acmpne -76 -> 2130
    //   2209: aload 22
    //   2211: ifnull +30 -> 2241
    //   2214: aload 21
    //   2216: invokeinterface 1127 1 0
    //   2221: ifne +20 -> 2241
    //   2224: aload_1
    //   2225: invokevirtual 502	com/google/android/gms/internal/ads/zzki:zzg	()Lcom/google/android/gms/internal/ads/zzki;
    //   2228: pop
    //   2229: aload_1
    //   2230: getfield 329	com/google/android/gms/internal/ads/zzki:zzf	Lcom/google/android/gms/internal/ads/zzkj;
    //   2233: getfield 1129	com/google/android/gms/internal/ads/zzkj:zzf	Z
    //   2236: istore 18
    //   2238: goto -108 -> 2130
    //   2241: iinc 2 1
    //   2244: goto -76 -> 2168
    //   2247: aload 20
    //   2249: invokevirtual 502	com/google/android/gms/internal/ads/zzki:zzg	()Lcom/google/android/gms/internal/ads/zzki;
    //   2252: getfield 380	com/google/android/gms/internal/ads/zzki:zzd	Z
    //   2255: ifne +19 -> 2274
    //   2258: aload_0
    //   2259: getfield 301	com/google/android/gms/internal/ads/zzkd:zzI	J
    //   2262: aload 20
    //   2264: invokevirtual 502	com/google/android/gms/internal/ads/zzki:zzg	()Lcom/google/android/gms/internal/ads/zzki;
    //   2267: invokevirtual 303	com/google/android/gms/internal/ads/zzki:zzf	()J
    //   2270: lcmp
    //   2271: iflt -141 -> 2130
    //   2274: aload 20
    //   2276: invokevirtual 263	com/google/android/gms/internal/ads/zzki:zzi	()Lcom/google/android/gms/internal/ads/zzxe;
    //   2279: astore 21
    //   2281: aload_0
    //   2282: getfield 207	com/google/android/gms/internal/ads/zzkd:zzq	Lcom/google/android/gms/internal/ads/zzkl;
    //   2285: invokevirtual 1131	com/google/android/gms/internal/ads/zzkl:zzb	()Lcom/google/android/gms/internal/ads/zzki;
    //   2288: astore 22
    //   2290: aload 22
    //   2292: invokevirtual 263	com/google/android/gms/internal/ads/zzki:zzi	()Lcom/google/android/gms/internal/ads/zzxe;
    //   2295: astore_1
    //   2296: aload_0
    //   2297: getfield 136	com/google/android/gms/internal/ads/zzkd:zzu	Lcom/google/android/gms/internal/ads/zzky;
    //   2300: getfield 440	com/google/android/gms/internal/ads/zzky:zza	Lcom/google/android/gms/internal/ads/zzcx;
    //   2303: astore 24
    //   2305: aload 22
    //   2307: getfield 329	com/google/android/gms/internal/ads/zzki:zzf	Lcom/google/android/gms/internal/ads/zzkj;
    //   2310: getfield 334	com/google/android/gms/internal/ads/zzkj:zza	Lcom/google/android/gms/internal/ads/zztl;
    //   2313: astore 23
    //   2315: aload 20
    //   2317: getfield 329	com/google/android/gms/internal/ads/zzki:zzf	Lcom/google/android/gms/internal/ads/zzkj;
    //   2320: getfield 334	com/google/android/gms/internal/ads/zzkj:zza	Lcom/google/android/gms/internal/ads/zztl;
    //   2323: astore 20
    //   2325: aload_0
    //   2326: aload 24
    //   2328: aload 23
    //   2330: aload 24
    //   2332: aload 20
    //   2334: ldc2_w 116
    //   2337: iconst_0
    //   2338: invokespecial 509	com/google/android/gms/internal/ads/zzkd:zzaa	(Lcom/google/android/gms/internal/ads/zzcx;Lcom/google/android/gms/internal/ads/zztl;Lcom/google/android/gms/internal/ads/zzcx;Lcom/google/android/gms/internal/ads/zztl;JZ)V
    //   2341: aload 22
    //   2343: getfield 380	com/google/android/gms/internal/ads/zzki:zzd	Z
    //   2346: ifeq +70 -> 2416
    //   2349: aload 22
    //   2351: getfield 581	com/google/android/gms/internal/ads/zzki:zza	Lcom/google/android/gms/internal/ads/zztj;
    //   2354: invokeinterface 742 1 0
    //   2359: ldc2_w 116
    //   2362: lcmp
    //   2363: ifeq +53 -> 2416
    //   2366: aload 22
    //   2368: invokevirtual 303	com/google/android/gms/internal/ads/zzki:zzf	()J
    //   2371: lstore 8
    //   2373: aload_0
    //   2374: getfield 93	com/google/android/gms/internal/ads/zzkd:zza	[Lcom/google/android/gms/internal/ads/zzle;
    //   2377: astore 20
    //   2379: aload 20
    //   2381: arraylength
    //   2382: istore_2
    //   2383: iconst_0
    //   2384: istore_2
    //   2385: iload_2
    //   2386: iconst_2
    //   2387: if_icmpge +269 -> 2656
    //   2390: aload 20
    //   2392: iload_2
    //   2393: aaload
    //   2394: astore_1
    //   2395: aload_1
    //   2396: invokeinterface 480 1 0
    //   2401: ifnull +9 -> 2410
    //   2404: aload_1
    //   2405: lload 8
    //   2407: invokestatic 1133	com/google/android/gms/internal/ads/zzkd:zzal	(Lcom/google/android/gms/internal/ads/zzle;J)V
    //   2410: iinc 2 1
    //   2413: goto -28 -> 2385
    //   2416: iconst_0
    //   2417: istore_2
    //   2418: aload_0
    //   2419: getfield 93	com/google/android/gms/internal/ads/zzkd:zza	[Lcom/google/android/gms/internal/ads/zzle;
    //   2422: arraylength
    //   2423: istore_3
    //   2424: iload_2
    //   2425: iconst_2
    //   2426: if_icmpge +230 -> 2656
    //   2429: aload 21
    //   2431: iload_2
    //   2432: invokevirtual 268	com/google/android/gms/internal/ads/zzxe:zzb	(I)Z
    //   2435: istore 18
    //   2437: aload_1
    //   2438: iload_2
    //   2439: invokevirtual 268	com/google/android/gms/internal/ads/zzxe:zzb	(I)Z
    //   2442: istore 19
    //   2444: iload 18
    //   2446: ifeq +75 -> 2521
    //   2449: aload_0
    //   2450: getfield 93	com/google/android/gms/internal/ads/zzkd:zza	[Lcom/google/android/gms/internal/ads/zzle;
    //   2453: iload_2
    //   2454: aaload
    //   2455: invokeinterface 1135 1 0
    //   2460: ifne +61 -> 2521
    //   2463: aload_0
    //   2464: getfield 147	com/google/android/gms/internal/ads/zzkd:zzc	[Lcom/google/android/gms/internal/ads/zzlf;
    //   2467: iload_2
    //   2468: aaload
    //   2469: invokeinterface 1136 1 0
    //   2474: pop
    //   2475: aload 21
    //   2477: getfield 281	com/google/android/gms/internal/ads/zzxe:zzb	[Lcom/google/android/gms/internal/ads/zzlg;
    //   2480: iload_2
    //   2481: aaload
    //   2482: astore 23
    //   2484: aload_1
    //   2485: getfield 281	com/google/android/gms/internal/ads/zzxe:zzb	[Lcom/google/android/gms/internal/ads/zzlg;
    //   2488: iload_2
    //   2489: aaload
    //   2490: astore 20
    //   2492: iload 19
    //   2494: ifeq +13 -> 2507
    //   2497: aload 20
    //   2499: aload 23
    //   2501: invokevirtual 1139	com/google/android/gms/internal/ads/zzlg:equals	(Ljava/lang/Object;)Z
    //   2504: ifne +17 -> 2521
    //   2507: aload_0
    //   2508: getfield 93	com/google/android/gms/internal/ads/zzkd:zza	[Lcom/google/android/gms/internal/ads/zzle;
    //   2511: iload_2
    //   2512: aaload
    //   2513: aload 22
    //   2515: invokevirtual 303	com/google/android/gms/internal/ads/zzki:zzf	()J
    //   2518: invokestatic 1133	com/google/android/gms/internal/ads/zzkd:zzal	(Lcom/google/android/gms/internal/ads/zzle;J)V
    //   2521: iinc 2 1
    //   2524: goto -106 -> 2418
    //   2527: aload 20
    //   2529: getfield 329	com/google/android/gms/internal/ads/zzki:zzf	Lcom/google/android/gms/internal/ads/zzkj;
    //   2532: getfield 1140	com/google/android/gms/internal/ads/zzkj:zzi	Z
    //   2535: ifne +10 -> 2545
    //   2538: aload_0
    //   2539: getfield 677	com/google/android/gms/internal/ads/zzkd:zzy	Z
    //   2542: ifeq +114 -> 2656
    //   2545: iconst_0
    //   2546: istore_2
    //   2547: aload_0
    //   2548: getfield 93	com/google/android/gms/internal/ads/zzkd:zza	[Lcom/google/android/gms/internal/ads/zzle;
    //   2551: astore_1
    //   2552: aload_1
    //   2553: arraylength
    //   2554: istore_3
    //   2555: iload_2
    //   2556: iconst_2
    //   2557: if_icmpge +99 -> 2656
    //   2560: aload_1
    //   2561: iload_2
    //   2562: aaload
    //   2563: astore_1
    //   2564: aload 20
    //   2566: getfield 299	com/google/android/gms/internal/ads/zzki:zzc	[Lcom/google/android/gms/internal/ads/zzvc;
    //   2569: iload_2
    //   2570: aaload
    //   2571: astore 21
    //   2573: aload 21
    //   2575: ifnull +75 -> 2650
    //   2578: aload_1
    //   2579: invokeinterface 480 1 0
    //   2584: aload 21
    //   2586: if_acmpne +64 -> 2650
    //   2589: aload_1
    //   2590: invokeinterface 1127 1 0
    //   2595: ifeq +55 -> 2650
    //   2598: aload 20
    //   2600: getfield 329	com/google/android/gms/internal/ads/zzki:zzf	Lcom/google/android/gms/internal/ads/zzkj;
    //   2603: getfield 831	com/google/android/gms/internal/ads/zzkj:zze	J
    //   2606: lstore 8
    //   2608: lload 8
    //   2610: ldc2_w 116
    //   2613: lcmp
    //   2614: ifeq +25 -> 2639
    //   2617: lload 8
    //   2619: ldc2_w 482
    //   2622: lcmp
    //   2623: ifeq +16 -> 2639
    //   2626: aload 20
    //   2628: invokevirtual 305	com/google/android/gms/internal/ads/zzki:zze	()J
    //   2631: lload 8
    //   2633: ladd
    //   2634: lstore 8
    //   2636: goto +8 -> 2644
    //   2639: ldc2_w 116
    //   2642: lstore 8
    //   2644: aload_1
    //   2645: lload 8
    //   2647: invokestatic 1133	com/google/android/gms/internal/ads/zzkd:zzal	(Lcom/google/android/gms/internal/ads/zzle;J)V
    //   2650: iinc 2 1
    //   2653: goto -106 -> 2547
    //   2656: aload_0
    //   2657: getfield 207	com/google/android/gms/internal/ads/zzkd:zzq	Lcom/google/android/gms/internal/ads/zzkl;
    //   2660: invokevirtual 258	com/google/android/gms/internal/ads/zzkl:zze	()Lcom/google/android/gms/internal/ads/zzki;
    //   2663: astore_1
    //   2664: aload_1
    //   2665: ifnull +200 -> 2865
    //   2668: aload_0
    //   2669: getfield 207	com/google/android/gms/internal/ads/zzkd:zzq	Lcom/google/android/gms/internal/ads/zzkl;
    //   2672: invokevirtual 278	com/google/android/gms/internal/ads/zzkl:zzd	()Lcom/google/android/gms/internal/ads/zzki;
    //   2675: aload_1
    //   2676: if_acmpeq +189 -> 2865
    //   2679: aload_1
    //   2680: getfield 322	com/google/android/gms/internal/ads/zzki:zzg	Z
    //   2683: ifeq +6 -> 2689
    //   2686: goto +179 -> 2865
    //   2689: aload_0
    //   2690: getfield 207	com/google/android/gms/internal/ads/zzkd:zzq	Lcom/google/android/gms/internal/ads/zzkl;
    //   2693: invokevirtual 258	com/google/android/gms/internal/ads/zzkl:zze	()Lcom/google/android/gms/internal/ads/zzki;
    //   2696: astore_1
    //   2697: aload_1
    //   2698: invokevirtual 263	com/google/android/gms/internal/ads/zzki:zzi	()Lcom/google/android/gms/internal/ads/zzxe;
    //   2701: astore 20
    //   2703: iconst_0
    //   2704: istore_2
    //   2705: iconst_0
    //   2706: istore_3
    //   2707: aload_0
    //   2708: getfield 93	com/google/android/gms/internal/ads/zzkd:zza	[Lcom/google/android/gms/internal/ads/zzle;
    //   2711: astore 21
    //   2713: aload 21
    //   2715: arraylength
    //   2716: istore 4
    //   2718: iload_2
    //   2719: iconst_2
    //   2720: if_icmpge +137 -> 2857
    //   2723: aload 21
    //   2725: iload_2
    //   2726: aaload
    //   2727: astore 22
    //   2729: iload_3
    //   2730: istore 4
    //   2732: aload 22
    //   2734: invokestatic 242	com/google/android/gms/internal/ads/zzkd:zzad	(Lcom/google/android/gms/internal/ads/zzle;)Z
    //   2737: ifeq +111 -> 2848
    //   2740: aload 22
    //   2742: invokeinterface 480 1 0
    //   2747: astore 21
    //   2749: aload_1
    //   2750: getfield 299	com/google/android/gms/internal/ads/zzki:zzc	[Lcom/google/android/gms/internal/ads/zzvc;
    //   2753: iload_2
    //   2754: aaload
    //   2755: astore 23
    //   2757: aload 20
    //   2759: iload_2
    //   2760: invokevirtual 268	com/google/android/gms/internal/ads/zzxe:zzb	(I)Z
    //   2763: ifeq +13 -> 2776
    //   2766: iload_3
    //   2767: istore 4
    //   2769: aload 21
    //   2771: aload 23
    //   2773: if_acmpeq +75 -> 2848
    //   2776: aload 22
    //   2778: invokeinterface 1135 1 0
    //   2783: ifne +40 -> 2823
    //   2786: aload 22
    //   2788: aload 20
    //   2790: getfield 284	com/google/android/gms/internal/ads/zzxe:zzc	[Lcom/google/android/gms/internal/ads/zzwx;
    //   2793: iload_2
    //   2794: aaload
    //   2795: invokestatic 288	com/google/android/gms/internal/ads/zzkd:zzai	(Lcom/google/android/gms/internal/ads/zzwx;)[Lcom/google/android/gms/internal/ads/zzam;
    //   2798: aload_1
    //   2799: getfield 299	com/google/android/gms/internal/ads/zzki:zzc	[Lcom/google/android/gms/internal/ads/zzvc;
    //   2802: iload_2
    //   2803: aaload
    //   2804: aload_1
    //   2805: invokevirtual 303	com/google/android/gms/internal/ads/zzki:zzf	()J
    //   2808: aload_1
    //   2809: invokevirtual 305	com/google/android/gms/internal/ads/zzki:zze	()J
    //   2812: invokeinterface 1143 7 0
    //   2817: iload_3
    //   2818: istore 4
    //   2820: goto +28 -> 2848
    //   2823: aload 22
    //   2825: invokeinterface 1145 1 0
    //   2830: ifeq +15 -> 2845
    //   2833: aload_0
    //   2834: aload 22
    //   2836: invokespecial 625	com/google/android/gms/internal/ads/zzkd:zzA	(Lcom/google/android/gms/internal/ads/zzle;)V
    //   2839: iload_3
    //   2840: istore 4
    //   2842: goto +6 -> 2848
    //   2845: iconst_1
    //   2846: istore 4
    //   2848: iinc 2 1
    //   2851: iload 4
    //   2853: istore_3
    //   2854: goto -147 -> 2707
    //   2857: iload_3
    //   2858: ifne +7 -> 2865
    //   2861: aload_0
    //   2862: invokespecial 905	com/google/android/gms/internal/ads/zzkd:zzB	()V
    //   2865: iconst_0
    //   2866: istore_2
    //   2867: aload_0
    //   2868: invokespecial 291	com/google/android/gms/internal/ads/zzkd:zzag	()Z
    //   2871: ifeq +207 -> 3078
    //   2874: aload_0
    //   2875: getfield 677	com/google/android/gms/internal/ads/zzkd:zzy	Z
    //   2878: ifne +200 -> 3078
    //   2881: aload_0
    //   2882: getfield 207	com/google/android/gms/internal/ads/zzkd:zzq	Lcom/google/android/gms/internal/ads/zzkl;
    //   2885: invokevirtual 278	com/google/android/gms/internal/ads/zzkl:zzd	()Lcom/google/android/gms/internal/ads/zzki;
    //   2888: astore_1
    //   2889: aload_1
    //   2890: ifnull +188 -> 3078
    //   2893: aload_1
    //   2894: invokevirtual 502	com/google/android/gms/internal/ads/zzki:zzg	()Lcom/google/android/gms/internal/ads/zzki;
    //   2897: astore_1
    //   2898: aload_1
    //   2899: ifnull +179 -> 3078
    //   2902: aload_0
    //   2903: getfield 301	com/google/android/gms/internal/ads/zzkd:zzI	J
    //   2906: aload_1
    //   2907: invokevirtual 303	com/google/android/gms/internal/ads/zzki:zzf	()J
    //   2910: lcmp
    //   2911: iflt +167 -> 3078
    //   2914: aload_1
    //   2915: getfield 322	com/google/android/gms/internal/ads/zzki:zzg	Z
    //   2918: ifeq +160 -> 3078
    //   2921: iload_2
    //   2922: ifeq +7 -> 2929
    //   2925: aload_0
    //   2926: invokespecial 1147	com/google/android/gms/internal/ads/zzkd:zzJ	()V
    //   2929: aload_0
    //   2930: getfield 207	com/google/android/gms/internal/ads/zzkd:zzq	Lcom/google/android/gms/internal/ads/zzkl;
    //   2933: invokevirtual 901	com/google/android/gms/internal/ads/zzkl:zza	()Lcom/google/android/gms/internal/ads/zzki;
    //   2936: astore_1
    //   2937: aload_1
    //   2938: invokestatic 1153	java/util/Objects:requireNonNull	(Ljava/lang/Object;)Ljava/lang/Object;
    //   2941: pop
    //   2942: aload_0
    //   2943: getfield 136	com/google/android/gms/internal/ads/zzkd:zzu	Lcom/google/android/gms/internal/ads/zzky;
    //   2946: getfield 358	com/google/android/gms/internal/ads/zzky:zzb	Lcom/google/android/gms/internal/ads/zztl;
    //   2949: getfield 402	com/google/android/gms/internal/ads/zztl:zza	Ljava/lang/Object;
    //   2952: aload_1
    //   2953: getfield 329	com/google/android/gms/internal/ads/zzki:zzf	Lcom/google/android/gms/internal/ads/zzkj;
    //   2956: getfield 334	com/google/android/gms/internal/ads/zzkj:zza	Lcom/google/android/gms/internal/ads/zztl;
    //   2959: getfield 402	com/google/android/gms/internal/ads/zztl:zza	Ljava/lang/Object;
    //   2962: invokevirtual 459	java/lang/Object:equals	(Ljava/lang/Object;)Z
    //   2965: ifeq +57 -> 3022
    //   2968: aload_0
    //   2969: getfield 136	com/google/android/gms/internal/ads/zzkd:zzu	Lcom/google/android/gms/internal/ads/zzky;
    //   2972: getfield 358	com/google/android/gms/internal/ads/zzky:zzb	Lcom/google/android/gms/internal/ads/zztl;
    //   2975: astore 20
    //   2977: aload 20
    //   2979: getfield 461	com/google/android/gms/internal/ads/zztl:zzb	I
    //   2982: iconst_m1
    //   2983: if_icmpne +39 -> 3022
    //   2986: aload_1
    //   2987: getfield 329	com/google/android/gms/internal/ads/zzki:zzf	Lcom/google/android/gms/internal/ads/zzkj;
    //   2990: getfield 334	com/google/android/gms/internal/ads/zzkj:zza	Lcom/google/android/gms/internal/ads/zztl;
    //   2993: astore 21
    //   2995: aload 21
    //   2997: getfield 461	com/google/android/gms/internal/ads/zztl:zzb	I
    //   3000: iconst_m1
    //   3001: if_icmpne +21 -> 3022
    //   3004: aload 20
    //   3006: getfield 458	com/google/android/gms/internal/ads/zztl:zze	I
    //   3009: aload 21
    //   3011: getfield 458	com/google/android/gms/internal/ads/zztl:zze	I
    //   3014: if_icmpeq +8 -> 3022
    //   3017: iconst_1
    //   3018: istore_2
    //   3019: goto +5 -> 3024
    //   3022: iconst_0
    //   3023: istore_2
    //   3024: aload_1
    //   3025: getfield 329	com/google/android/gms/internal/ads/zzki:zzf	Lcom/google/android/gms/internal/ads/zzkj;
    //   3028: astore 20
    //   3030: aload 20
    //   3032: getfield 334	com/google/android/gms/internal/ads/zzkj:zza	Lcom/google/android/gms/internal/ads/zztl;
    //   3035: astore_1
    //   3036: aload 20
    //   3038: getfield 570	com/google/android/gms/internal/ads/zzkj:zzb	J
    //   3041: lstore 8
    //   3043: aload_0
    //   3044: aload_0
    //   3045: aload_1
    //   3046: lload 8
    //   3048: aload 20
    //   3050: getfield 945	com/google/android/gms/internal/ads/zzkj:zzc	J
    //   3053: lload 8
    //   3055: iload_2
    //   3056: iconst_1
    //   3057: ixor
    //   3058: iconst_0
    //   3059: invokespecial 515	com/google/android/gms/internal/ads/zzkd:zzz	(Lcom/google/android/gms/internal/ads/zztl;JJJZI)Lcom/google/android/gms/internal/ads/zzky;
    //   3062: putfield 136	com/google/android/gms/internal/ads/zzkd:zzu	Lcom/google/android/gms/internal/ads/zzky;
    //   3065: aload_0
    //   3066: invokespecial 517	com/google/android/gms/internal/ads/zzkd:zzM	()V
    //   3069: aload_0
    //   3070: invokespecial 635	com/google/android/gms/internal/ads/zzkd:zzZ	()V
    //   3073: iconst_1
    //   3074: istore_2
    //   3075: goto -208 -> 2867
    //   3078: aload_0
    //   3079: getfield 136	com/google/android/gms/internal/ads/zzkd:zzu	Lcom/google/android/gms/internal/ads/zzky;
    //   3082: getfield 293	com/google/android/gms/internal/ads/zzky:zze	I
    //   3085: istore_2
    //   3086: iload_2
    //   3087: iconst_1
    //   3088: if_icmpeq +1725 -> 4813
    //   3091: iload_2
    //   3092: iconst_4
    //   3093: if_icmpne +6 -> 3099
    //   3096: goto +1423 -> 4519
    //   3099: aload_0
    //   3100: getfield 207	com/google/android/gms/internal/ads/zzkd:zzq	Lcom/google/android/gms/internal/ads/zzkl;
    //   3103: invokevirtual 278	com/google/android/gms/internal/ads/zzkl:zzd	()Lcom/google/android/gms/internal/ads/zzki;
    //   3106: astore 20
    //   3108: aload 20
    //   3110: ifnonnull +15 -> 3125
    //   3113: aload_0
    //   3114: lload 10
    //   3116: ldc2_w 1154
    //   3119: invokespecial 1157	com/google/android/gms/internal/ads/zzkd:zzP	(JJ)V
    //   3122: goto +1397 -> 4519
    //   3125: getstatic 702	com/google/android/gms/internal/ads/zzfn:zza	I
    //   3128: istore_2
    //   3129: ldc_w 1159
    //   3132: invokestatic 1165	android/os/Trace:beginSection	(Ljava/lang/String;)V
    //   3135: aload_0
    //   3136: invokespecial 635	com/google/android/gms/internal/ads/zzkd:zzZ	()V
    //   3139: aload 20
    //   3141: getfield 380	com/google/android/gms/internal/ads/zzki:zzd	Z
    //   3144: ifeq +253 -> 3397
    //   3147: invokestatic 759	android/os/SystemClock:elapsedRealtime	()J
    //   3150: lstore 8
    //   3152: aload 20
    //   3154: getfield 581	com/google/android/gms/internal/ads/zzki:zza	Lcom/google/android/gms/internal/ads/zztj;
    //   3157: aload_0
    //   3158: getfield 136	com/google/android/gms/internal/ads/zzkd:zzu	Lcom/google/android/gms/internal/ads/zzky;
    //   3161: getfield 370	com/google/android/gms/internal/ads/zzky:zzr	J
    //   3164: aload_0
    //   3165: getfield 126	com/google/android/gms/internal/ads/zzkd:zzm	J
    //   3168: lsub
    //   3169: iconst_0
    //   3170: invokeinterface 586 4 0
    //   3175: iconst_1
    //   3176: istore_3
    //   3177: iconst_1
    //   3178: istore_2
    //   3179: iconst_0
    //   3180: istore 4
    //   3182: aload_0
    //   3183: getfield 93	com/google/android/gms/internal/ads/zzkd:zza	[Lcom/google/android/gms/internal/ads/zzle;
    //   3186: astore_1
    //   3187: aload_1
    //   3188: arraylength
    //   3189: istore 5
    //   3191: iload_3
    //   3192: istore 6
    //   3194: iload_2
    //   3195: istore 5
    //   3197: iload 4
    //   3199: iconst_2
    //   3200: if_icmpge +213 -> 3413
    //   3203: aload_1
    //   3204: iload 4
    //   3206: aaload
    //   3207: astore_1
    //   3208: iload_3
    //   3209: istore 5
    //   3211: iload_2
    //   3212: istore 7
    //   3214: aload_1
    //   3215: invokestatic 242	com/google/android/gms/internal/ads/zzkd:zzad	(Lcom/google/android/gms/internal/ads/zzle;)Z
    //   3218: ifeq +167 -> 3385
    //   3221: aload_1
    //   3222: aload_0
    //   3223: getfield 301	com/google/android/gms/internal/ads/zzkd:zzI	J
    //   3226: lload 8
    //   3228: ldc2_w 1166
    //   3231: lmul
    //   3232: invokeinterface 1169 5 0
    //   3237: iload_3
    //   3238: ifeq +17 -> 3255
    //   3241: aload_1
    //   3242: invokeinterface 1145 1 0
    //   3247: ifeq +8 -> 3255
    //   3250: iconst_1
    //   3251: istore_3
    //   3252: goto +5 -> 3257
    //   3255: iconst_0
    //   3256: istore_3
    //   3257: aload 20
    //   3259: getfield 299	com/google/android/gms/internal/ads/zzki:zzc	[Lcom/google/android/gms/internal/ads/zzvc;
    //   3262: iload 4
    //   3264: aaload
    //   3265: aload_1
    //   3266: invokeinterface 480 1 0
    //   3271: if_acmpeq +9 -> 3280
    //   3274: iconst_1
    //   3275: istore 5
    //   3277: goto +6 -> 3283
    //   3280: iconst_0
    //   3281: istore 5
    //   3283: iload 5
    //   3285: ifne +18 -> 3303
    //   3288: aload_1
    //   3289: invokeinterface 1127 1 0
    //   3294: ifeq +9 -> 3303
    //   3297: iconst_1
    //   3298: istore 6
    //   3300: goto +6 -> 3306
    //   3303: iconst_0
    //   3304: istore 6
    //   3306: iload 5
    //   3308: ifne +35 -> 3343
    //   3311: iload 6
    //   3313: ifne +30 -> 3343
    //   3316: aload_1
    //   3317: invokeinterface 1171 1 0
    //   3322: ifne +21 -> 3343
    //   3325: aload_1
    //   3326: invokeinterface 1145 1 0
    //   3331: ifeq +6 -> 3337
    //   3334: goto +9 -> 3343
    //   3337: iconst_0
    //   3338: istore 6
    //   3340: goto +6 -> 3346
    //   3343: iconst_1
    //   3344: istore 6
    //   3346: iload_2
    //   3347: ifeq +13 -> 3360
    //   3350: iload 6
    //   3352: ifeq +8 -> 3360
    //   3355: iconst_1
    //   3356: istore_2
    //   3357: goto +5 -> 3362
    //   3360: iconst_0
    //   3361: istore_2
    //   3362: iload_3
    //   3363: istore 5
    //   3365: iload_2
    //   3366: istore 7
    //   3368: iload 6
    //   3370: ifne +15 -> 3385
    //   3373: aload_1
    //   3374: invokeinterface 1173 1 0
    //   3379: iload_2
    //   3380: istore 7
    //   3382: iload_3
    //   3383: istore 5
    //   3385: iinc 4 1
    //   3388: iload 5
    //   3390: istore_3
    //   3391: iload 7
    //   3393: istore_2
    //   3394: goto -212 -> 3182
    //   3397: aload 20
    //   3399: getfield 581	com/google/android/gms/internal/ads/zzki:zza	Lcom/google/android/gms/internal/ads/zztj;
    //   3402: invokeinterface 1175 1 0
    //   3407: iconst_1
    //   3408: istore 6
    //   3410: iconst_1
    //   3411: istore 5
    //   3413: aload 20
    //   3415: getfield 329	com/google/android/gms/internal/ads/zzki:zzf	Lcom/google/android/gms/internal/ads/zzkj;
    //   3418: getfield 831	com/google/android/gms/internal/ads/zzkj:zze	J
    //   3421: lstore 8
    //   3423: iload 6
    //   3425: ifeq +82 -> 3507
    //   3428: aload 20
    //   3430: getfield 380	com/google/android/gms/internal/ads/zzki:zzd	Z
    //   3433: ifeq +74 -> 3507
    //   3436: lload 8
    //   3438: ldc2_w 116
    //   3441: lcmp
    //   3442: ifeq +16 -> 3458
    //   3445: lload 8
    //   3447: aload_0
    //   3448: getfield 136	com/google/android/gms/internal/ads/zzkd:zzu	Lcom/google/android/gms/internal/ads/zzky;
    //   3451: getfield 370	com/google/android/gms/internal/ads/zzky:zzr	J
    //   3454: lcmp
    //   3455: ifgt +52 -> 3507
    //   3458: aload_0
    //   3459: getfield 677	com/google/android/gms/internal/ads/zzkd:zzy	Z
    //   3462: ifeq +22 -> 3484
    //   3465: aload_0
    //   3466: iconst_0
    //   3467: putfield 677	com/google/android/gms/internal/ads/zzkd:zzy	Z
    //   3470: aload_0
    //   3471: iconst_0
    //   3472: aload_0
    //   3473: getfield 136	com/google/android/gms/internal/ads/zzkd:zzu	Lcom/google/android/gms/internal/ads/zzky;
    //   3476: getfield 551	com/google/android/gms/internal/ads/zzky:zzm	I
    //   3479: iconst_0
    //   3480: iconst_5
    //   3481: invokespecial 1177	com/google/android/gms/internal/ads/zzkd:zzS	(ZIZI)V
    //   3484: aload 20
    //   3486: getfield 329	com/google/android/gms/internal/ads/zzki:zzf	Lcom/google/android/gms/internal/ads/zzkj;
    //   3489: getfield 1140	com/google/android/gms/internal/ads/zzkj:zzi	Z
    //   3492: ifeq +15 -> 3507
    //   3495: aload_0
    //   3496: iconst_4
    //   3497: invokespecial 474	com/google/android/gms/internal/ads/zzkd:zzT	(I)V
    //   3500: aload_0
    //   3501: invokespecial 724	com/google/android/gms/internal/ads/zzkd:zzW	()V
    //   3504: goto +353 -> 3857
    //   3507: aload_0
    //   3508: getfield 136	com/google/android/gms/internal/ads/zzkd:zzu	Lcom/google/android/gms/internal/ads/zzky;
    //   3511: astore_1
    //   3512: aload_1
    //   3513: getfield 293	com/google/android/gms/internal/ads/zzky:zze	I
    //   3516: iconst_2
    //   3517: if_icmpeq +6 -> 3523
    //   3520: goto +221 -> 3741
    //   3523: aload_0
    //   3524: getfield 251	com/google/android/gms/internal/ads/zzkd:zzG	I
    //   3527: ifne +13 -> 3540
    //   3530: aload_0
    //   3531: invokespecial 1179	com/google/android/gms/internal/ads/zzkd:zzae	()Z
    //   3534: ifeq -14 -> 3520
    //   3537: goto +180 -> 3717
    //   3540: iload 5
    //   3542: ifeq -22 -> 3520
    //   3545: aload_1
    //   3546: getfield 539	com/google/android/gms/internal/ads/zzky:zzg	Z
    //   3549: ifeq -12 -> 3537
    //   3552: aload_0
    //   3553: getfield 207	com/google/android/gms/internal/ads/zzkd:zzq	Lcom/google/android/gms/internal/ads/zzkl;
    //   3556: invokevirtual 278	com/google/android/gms/internal/ads/zzkl:zzd	()Lcom/google/android/gms/internal/ads/zzki;
    //   3559: astore 21
    //   3561: aload_0
    //   3562: aload_0
    //   3563: getfield 136	com/google/android/gms/internal/ads/zzkd:zzu	Lcom/google/android/gms/internal/ads/zzky;
    //   3566: getfield 440	com/google/android/gms/internal/ads/zzky:zza	Lcom/google/android/gms/internal/ads/zzcx;
    //   3569: aload 21
    //   3571: getfield 329	com/google/android/gms/internal/ads/zzki:zzf	Lcom/google/android/gms/internal/ads/zzkj;
    //   3574: getfield 334	com/google/android/gms/internal/ads/zzkj:zza	Lcom/google/android/gms/internal/ads/zztl;
    //   3577: invokespecial 763	com/google/android/gms/internal/ads/zzkd:zzah	(Lcom/google/android/gms/internal/ads/zzcx;Lcom/google/android/gms/internal/ads/zztl;)Z
    //   3580: ifeq +15 -> 3595
    //   3583: aload_0
    //   3584: getfield 109	com/google/android/gms/internal/ads/zzkd:zzO	Lcom/google/android/gms/internal/ads/zzhv;
    //   3587: invokevirtual 1181	com/google/android/gms/internal/ads/zzhv:zzb	()J
    //   3590: lstore 8
    //   3592: goto +8 -> 3600
    //   3595: ldc2_w 116
    //   3598: lstore 8
    //   3600: aload_0
    //   3601: getfield 207	com/google/android/gms/internal/ads/zzkd:zzq	Lcom/google/android/gms/internal/ads/zzkl;
    //   3604: invokevirtual 356	com/google/android/gms/internal/ads/zzkl:zzc	()Lcom/google/android/gms/internal/ads/zzki;
    //   3607: astore_1
    //   3608: aload_1
    //   3609: invokevirtual 1183	com/google/android/gms/internal/ads/zzki:zzr	()Z
    //   3612: ifeq +18 -> 3630
    //   3615: aload_1
    //   3616: getfield 329	com/google/android/gms/internal/ads/zzki:zzf	Lcom/google/android/gms/internal/ads/zzkj;
    //   3619: getfield 1140	com/google/android/gms/internal/ads/zzkj:zzi	Z
    //   3622: ifeq +8 -> 3630
    //   3625: iconst_1
    //   3626: istore_2
    //   3627: goto +5 -> 3632
    //   3630: iconst_0
    //   3631: istore_2
    //   3632: aload_1
    //   3633: getfield 329	com/google/android/gms/internal/ads/zzki:zzf	Lcom/google/android/gms/internal/ads/zzkj;
    //   3636: getfield 334	com/google/android/gms/internal/ads/zzkj:zza	Lcom/google/android/gms/internal/ads/zztl;
    //   3639: invokevirtual 408	com/google/android/gms/internal/ads/zzbx:zzb	()Z
    //   3642: ifeq +15 -> 3657
    //   3645: aload_1
    //   3646: getfield 380	com/google/android/gms/internal/ads/zzki:zzd	Z
    //   3649: ifne +8 -> 3657
    //   3652: iconst_1
    //   3653: istore_3
    //   3654: goto +5 -> 3659
    //   3657: iconst_0
    //   3658: istore_3
    //   3659: iload_2
    //   3660: ifne -123 -> 3537
    //   3663: iload_3
    //   3664: ifne -127 -> 3537
    //   3667: aload_0
    //   3668: getfield 99	com/google/android/gms/internal/ads/zzkd:zzf	Lcom/google/android/gms/internal/ads/zzkg;
    //   3671: aload_0
    //   3672: getfield 136	com/google/android/gms/internal/ads/zzkd:zzu	Lcom/google/android/gms/internal/ads/zzky;
    //   3675: getfield 440	com/google/android/gms/internal/ads/zzky:zza	Lcom/google/android/gms/internal/ads/zzcx;
    //   3678: aload 21
    //   3680: getfield 329	com/google/android/gms/internal/ads/zzki:zzf	Lcom/google/android/gms/internal/ads/zzkj;
    //   3683: getfield 334	com/google/android/gms/internal/ads/zzkj:zza	Lcom/google/android/gms/internal/ads/zztl;
    //   3686: aload_0
    //   3687: invokespecial 376	com/google/android/gms/internal/ads/zzkd:zzt	()J
    //   3690: aload_0
    //   3691: getfield 162	com/google/android/gms/internal/ads/zzkd:zzn	Lcom/google/android/gms/internal/ads/zzhy;
    //   3694: invokevirtual 573	com/google/android/gms/internal/ads/zzhy:zzc	()Lcom/google/android/gms/internal/ads/zzci;
    //   3697: getfield 531	com/google/android/gms/internal/ads/zzci:zzc	F
    //   3700: aload_0
    //   3701: getfield 647	com/google/android/gms/internal/ads/zzkd:zzz	Z
    //   3704: lload 8
    //   3706: invokeinterface 1186 9 0
    //   3711: ifeq -191 -> 3520
    //   3714: goto -177 -> 3537
    //   3717: aload_0
    //   3718: iconst_3
    //   3719: invokespecial 474	com/google/android/gms/internal/ads/zzkd:zzT	(I)V
    //   3722: aload_0
    //   3723: aconst_null
    //   3724: putfield 645	com/google/android/gms/internal/ads/zzkd:zzL	Lcom/google/android/gms/internal/ads/zzia;
    //   3727: aload_0
    //   3728: invokespecial 291	com/google/android/gms/internal/ads/zzkd:zzag	()Z
    //   3731: ifeq +126 -> 3857
    //   3734: aload_0
    //   3735: invokespecial 727	com/google/android/gms/internal/ads/zzkd:zzU	()V
    //   3738: goto +119 -> 3857
    //   3741: aload_0
    //   3742: getfield 136	com/google/android/gms/internal/ads/zzkd:zzu	Lcom/google/android/gms/internal/ads/zzky;
    //   3745: getfield 293	com/google/android/gms/internal/ads/zzky:zze	I
    //   3748: iconst_3
    //   3749: if_icmpne +108 -> 3857
    //   3752: aload_0
    //   3753: getfield 251	com/google/android/gms/internal/ads/zzkd:zzG	I
    //   3756: ifne +13 -> 3769
    //   3759: aload_0
    //   3760: invokespecial 1179	com/google/android/gms/internal/ads/zzkd:zzae	()Z
    //   3763: ifne +94 -> 3857
    //   3766: goto +8 -> 3774
    //   3769: iload 5
    //   3771: ifne +86 -> 3857
    //   3774: aload_0
    //   3775: aload_0
    //   3776: invokespecial 291	com/google/android/gms/internal/ads/zzkd:zzag	()Z
    //   3779: putfield 647	com/google/android/gms/internal/ads/zzkd:zzz	Z
    //   3782: aload_0
    //   3783: iconst_2
    //   3784: invokespecial 474	com/google/android/gms/internal/ads/zzkd:zzT	(I)V
    //   3787: aload_0
    //   3788: getfield 647	com/google/android/gms/internal/ads/zzkd:zzz	Z
    //   3791: ifeq +62 -> 3853
    //   3794: aload_0
    //   3795: getfield 207	com/google/android/gms/internal/ads/zzkd:zzq	Lcom/google/android/gms/internal/ads/zzkl;
    //   3798: invokevirtual 278	com/google/android/gms/internal/ads/zzkl:zzd	()Lcom/google/android/gms/internal/ads/zzki;
    //   3801: astore_1
    //   3802: aload_1
    //   3803: ifnull +43 -> 3846
    //   3806: aload_1
    //   3807: invokevirtual 263	com/google/android/gms/internal/ads/zzki:zzi	()Lcom/google/android/gms/internal/ads/zzxe;
    //   3810: getfield 284	com/google/android/gms/internal/ads/zzxe:zzc	[Lcom/google/android/gms/internal/ads/zzwx;
    //   3813: astore 21
    //   3815: aload 21
    //   3817: arraylength
    //   3818: istore_3
    //   3819: iconst_0
    //   3820: istore_2
    //   3821: iload_2
    //   3822: iload_3
    //   3823: if_icmpge +15 -> 3838
    //   3826: aload 21
    //   3828: iload_2
    //   3829: aaload
    //   3830: astore 22
    //   3832: iinc 2 1
    //   3835: goto -14 -> 3821
    //   3838: aload_1
    //   3839: invokevirtual 502	com/google/android/gms/internal/ads/zzki:zzg	()Lcom/google/android/gms/internal/ads/zzki;
    //   3842: astore_1
    //   3843: goto -41 -> 3802
    //   3846: aload_0
    //   3847: getfield 109	com/google/android/gms/internal/ads/zzkd:zzO	Lcom/google/android/gms/internal/ads/zzhv;
    //   3850: invokevirtual 1187	com/google/android/gms/internal/ads/zzhv:zzc	()V
    //   3853: aload_0
    //   3854: invokespecial 724	com/google/android/gms/internal/ads/zzkd:zzW	()V
    //   3857: aload_0
    //   3858: getfield 136	com/google/android/gms/internal/ads/zzkd:zzu	Lcom/google/android/gms/internal/ads/zzky;
    //   3861: getfield 293	com/google/android/gms/internal/ads/zzky:zze	I
    //   3864: iconst_2
    //   3865: if_icmpne +147 -> 4012
    //   3868: iconst_0
    //   3869: istore_2
    //   3870: aload_0
    //   3871: getfield 93	com/google/android/gms/internal/ads/zzkd:zza	[Lcom/google/android/gms/internal/ads/zzle;
    //   3874: astore_1
    //   3875: aload_1
    //   3876: arraylength
    //   3877: istore_3
    //   3878: iload_2
    //   3879: iconst_2
    //   3880: if_icmpge +50 -> 3930
    //   3883: aload_1
    //   3884: iload_2
    //   3885: aaload
    //   3886: invokestatic 242	com/google/android/gms/internal/ads/zzkd:zzad	(Lcom/google/android/gms/internal/ads/zzle;)Z
    //   3889: ifeq +35 -> 3924
    //   3892: aload_0
    //   3893: getfield 93	com/google/android/gms/internal/ads/zzkd:zza	[Lcom/google/android/gms/internal/ads/zzle;
    //   3896: iload_2
    //   3897: aaload
    //   3898: invokeinterface 480 1 0
    //   3903: aload 20
    //   3905: getfield 299	com/google/android/gms/internal/ads/zzki:zzc	[Lcom/google/android/gms/internal/ads/zzvc;
    //   3908: iload_2
    //   3909: aaload
    //   3910: if_acmpne +14 -> 3924
    //   3913: aload_0
    //   3914: getfield 93	com/google/android/gms/internal/ads/zzkd:zza	[Lcom/google/android/gms/internal/ads/zzle;
    //   3917: iload_2
    //   3918: aaload
    //   3919: invokeinterface 1173 1 0
    //   3924: iinc 2 1
    //   3927: goto -57 -> 3870
    //   3930: aload_0
    //   3931: getfield 136	com/google/android/gms/internal/ads/zzkd:zzu	Lcom/google/android/gms/internal/ads/zzky;
    //   3934: astore_1
    //   3935: aload_1
    //   3936: getfield 539	com/google/android/gms/internal/ads/zzky:zzg	Z
    //   3939: ifne +73 -> 4012
    //   3942: aload_1
    //   3943: getfield 378	com/google/android/gms/internal/ads/zzky:zzq	J
    //   3946: ldc2_w 577
    //   3949: lcmp
    //   3950: ifge +62 -> 4012
    //   3953: aload_0
    //   3954: invokespecial 563	com/google/android/gms/internal/ads/zzkd:zzac	()Z
    //   3957: ifeq +55 -> 4012
    //   3960: aload_0
    //   3961: getfield 119	com/google/android/gms/internal/ads/zzkd:zzM	J
    //   3964: ldc2_w 116
    //   3967: lcmp
    //   3968: ifne +13 -> 3981
    //   3971: aload_0
    //   3972: invokestatic 759	android/os/SystemClock:elapsedRealtime	()J
    //   3975: putfield 119	com/google/android/gms/internal/ads/zzkd:zzM	J
    //   3978: goto +41 -> 4019
    //   3981: invokestatic 759	android/os/SystemClock:elapsedRealtime	()J
    //   3984: aload_0
    //   3985: getfield 119	com/google/android/gms/internal/ads/zzkd:zzM	J
    //   3988: lsub
    //   3989: ldc2_w 1188
    //   3992: lcmp
    //   3993: ifge +6 -> 3999
    //   3996: goto +23 -> 4019
    //   3999: new 1191	java/lang/IllegalStateException
    //   4002: astore_1
    //   4003: aload_1
    //   4004: ldc_w 1193
    //   4007: invokespecial 1195	java/lang/IllegalStateException:<init>	(Ljava/lang/String;)V
    //   4010: aload_1
    //   4011: athrow
    //   4012: aload_0
    //   4013: ldc2_w 116
    //   4016: putfield 119	com/google/android/gms/internal/ads/zzkd:zzM	J
    //   4019: aload_0
    //   4020: invokespecial 291	com/google/android/gms/internal/ads/zzkd:zzag	()Z
    //   4023: ifeq +19 -> 4042
    //   4026: aload_0
    //   4027: getfield 136	com/google/android/gms/internal/ads/zzkd:zzu	Lcom/google/android/gms/internal/ads/zzky;
    //   4030: getfield 293	com/google/android/gms/internal/ads/zzky:zze	I
    //   4033: iconst_3
    //   4034: if_icmpne +8 -> 4042
    //   4037: iconst_1
    //   4038: istore_2
    //   4039: goto +5 -> 4044
    //   4042: iconst_0
    //   4043: istore_2
    //   4044: aload_0
    //   4045: getfield 978	com/google/android/gms/internal/ads/zzkd:zzF	Z
    //   4048: ifeq +20 -> 4068
    //   4051: aload_0
    //   4052: getfield 883	com/google/android/gms/internal/ads/zzkd:zzE	Z
    //   4055: ifeq +13 -> 4068
    //   4058: iload_2
    //   4059: ifeq +9 -> 4068
    //   4062: iconst_1
    //   4063: istore 18
    //   4065: goto +6 -> 4071
    //   4068: iconst_0
    //   4069: istore 18
    //   4071: aload_0
    //   4072: getfield 136	com/google/android/gms/internal/ads/zzkd:zzu	Lcom/google/android/gms/internal/ads/zzky;
    //   4075: astore_1
    //   4076: aload_1
    //   4077: getfield 554	com/google/android/gms/internal/ads/zzky:zzo	Z
    //   4080: iload 18
    //   4082: if_icmpeq +96 -> 4178
    //   4085: new 131	com/google/android/gms/internal/ads/zzky
    //   4088: astore 20
    //   4090: aload 20
    //   4092: aload_1
    //   4093: getfield 440	com/google/android/gms/internal/ads/zzky:zza	Lcom/google/android/gms/internal/ads/zzcx;
    //   4096: aload_1
    //   4097: getfield 358	com/google/android/gms/internal/ads/zzky:zzb	Lcom/google/android/gms/internal/ads/zztl;
    //   4100: aload_1
    //   4101: getfield 410	com/google/android/gms/internal/ads/zzky:zzc	J
    //   4104: aload_1
    //   4105: getfield 512	com/google/android/gms/internal/ads/zzky:zzd	J
    //   4108: aload_1
    //   4109: getfield 293	com/google/android/gms/internal/ads/zzky:zze	I
    //   4112: aload_1
    //   4113: getfield 538	com/google/android/gms/internal/ads/zzky:zzf	Lcom/google/android/gms/internal/ads/zzia;
    //   4116: aload_1
    //   4117: getfield 539	com/google/android/gms/internal/ads/zzky:zzg	Z
    //   4120: aload_1
    //   4121: getfield 542	com/google/android/gms/internal/ads/zzky:zzh	Lcom/google/android/gms/internal/ads/zzvk;
    //   4124: aload_1
    //   4125: getfield 544	com/google/android/gms/internal/ads/zzky:zzi	Lcom/google/android/gms/internal/ads/zzxe;
    //   4128: aload_1
    //   4129: getfield 547	com/google/android/gms/internal/ads/zzky:zzj	Ljava/util/List;
    //   4132: aload_1
    //   4133: getfield 360	com/google/android/gms/internal/ads/zzky:zzk	Lcom/google/android/gms/internal/ads/zztl;
    //   4136: aload_1
    //   4137: getfield 549	com/google/android/gms/internal/ads/zzky:zzl	Z
    //   4140: aload_1
    //   4141: getfield 551	com/google/android/gms/internal/ads/zzky:zzm	I
    //   4144: aload_1
    //   4145: getfield 671	com/google/android/gms/internal/ads/zzky:zzn	Lcom/google/android/gms/internal/ads/zzci;
    //   4148: aload_1
    //   4149: getfield 374	com/google/android/gms/internal/ads/zzky:zzp	J
    //   4152: aload_1
    //   4153: getfield 378	com/google/android/gms/internal/ads/zzky:zzq	J
    //   4156: aload_1
    //   4157: getfield 370	com/google/android/gms/internal/ads/zzky:zzr	J
    //   4160: aload_1
    //   4161: getfield 552	com/google/android/gms/internal/ads/zzky:zzs	J
    //   4164: iload 18
    //   4166: invokespecial 557	com/google/android/gms/internal/ads/zzky:<init>	(Lcom/google/android/gms/internal/ads/zzcx;Lcom/google/android/gms/internal/ads/zztl;JJILcom/google/android/gms/internal/ads/zzia;ZLcom/google/android/gms/internal/ads/zzvk;Lcom/google/android/gms/internal/ads/zzxe;Ljava/util/List;Lcom/google/android/gms/internal/ads/zztl;ZILcom/google/android/gms/internal/ads/zzci;JJJJZ)V
    //   4169: aload_0
    //   4170: aload 20
    //   4172: putfield 136	com/google/android/gms/internal/ads/zzkd:zzu	Lcom/google/android/gms/internal/ads/zzky;
    //   4175: goto +3 -> 4178
    //   4178: aload_0
    //   4179: iconst_0
    //   4180: putfield 883	com/google/android/gms/internal/ads/zzkd:zzE	Z
    //   4183: iload 18
    //   4185: ifne +64 -> 4249
    //   4188: aload_0
    //   4189: getfield 136	com/google/android/gms/internal/ads/zzkd:zzu	Lcom/google/android/gms/internal/ads/zzky;
    //   4192: getfield 293	com/google/android/gms/internal/ads/zzky:zze	I
    //   4195: istore_3
    //   4196: iload_3
    //   4197: iconst_4
    //   4198: if_icmpne +6 -> 4204
    //   4201: goto +48 -> 4249
    //   4204: iload_2
    //   4205: ifne +35 -> 4240
    //   4208: iload_3
    //   4209: iconst_2
    //   4210: if_icmpne +6 -> 4216
    //   4213: goto +27 -> 4240
    //   4216: iload_3
    //   4217: iconst_3
    //   4218: if_icmpne +31 -> 4249
    //   4221: aload_0
    //   4222: getfield 251	com/google/android/gms/internal/ads/zzkd:zzG	I
    //   4225: ifeq +24 -> 4249
    //   4228: aload_0
    //   4229: lload 10
    //   4231: ldc2_w 1166
    //   4234: invokespecial 1157	com/google/android/gms/internal/ads/zzkd:zzP	(JJ)V
    //   4237: goto +12 -> 4249
    //   4240: aload_0
    //   4241: lload 10
    //   4243: ldc2_w 1154
    //   4246: invokespecial 1157	com/google/android/gms/internal/ads/zzkd:zzP	(JJ)V
    //   4249: invokestatic 1198	android/os/Trace:endSection	()V
    //   4252: goto +267 -> 4519
    //   4255: aload_1
    //   4256: getfield 976	android/os/Message:arg1	I
    //   4259: ifeq +9 -> 4268
    //   4262: iconst_1
    //   4263: istore 18
    //   4265: goto +6 -> 4271
    //   4268: iconst_0
    //   4269: istore 18
    //   4271: aload_0
    //   4272: iload 18
    //   4274: aload_1
    //   4275: getfield 994	android/os/Message:arg2	I
    //   4278: iconst_1
    //   4279: iconst_1
    //   4280: invokespecial 1177	com/google/android/gms/internal/ads/zzkd:zzS	(ZIZI)V
    //   4283: goto +236 -> 4519
    //   4286: aload_0
    //   4287: getfield 143	com/google/android/gms/internal/ads/zzkd:zzv	Lcom/google/android/gms/internal/ads/zzkb;
    //   4290: iconst_1
    //   4291: invokevirtual 536	com/google/android/gms/internal/ads/zzkb:zza	(I)V
    //   4294: aload_0
    //   4295: iconst_0
    //   4296: iconst_0
    //   4297: iconst_0
    //   4298: iconst_1
    //   4299: invokespecial 477	com/google/android/gms/internal/ads/zzkd:zzL	(ZZZZ)V
    //   4302: aload_0
    //   4303: getfield 99	com/google/android/gms/internal/ads/zzkd:zzf	Lcom/google/android/gms/internal/ads/zzkg;
    //   4306: invokeinterface 1200 1 0
    //   4311: iconst_1
    //   4312: aload_0
    //   4313: getfield 136	com/google/android/gms/internal/ads/zzkd:zzu	Lcom/google/android/gms/internal/ads/zzky;
    //   4316: getfield 440	com/google/android/gms/internal/ads/zzky:zza	Lcom/google/android/gms/internal/ads/zzcx;
    //   4319: invokevirtual 394	com/google/android/gms/internal/ads/zzcx:zzo	()Z
    //   4322: if_icmpeq +8 -> 4330
    //   4325: iconst_2
    //   4326: istore_2
    //   4327: goto +5 -> 4332
    //   4330: iconst_4
    //   4331: istore_2
    //   4332: aload_0
    //   4333: iload_2
    //   4334: invokespecial 474	com/google/android/gms/internal/ads/zzkd:zzT	(I)V
    //   4337: aload_0
    //   4338: getfield 214	com/google/android/gms/internal/ads/zzkd:zzr	Lcom/google/android/gms/internal/ads/zzkx;
    //   4341: aload_0
    //   4342: getfield 101	com/google/android/gms/internal/ads/zzkd:zzg	Lcom/google/android/gms/internal/ads/zzxl;
    //   4345: invokevirtual 1203	com/google/android/gms/internal/ads/zzkx:zzf	(Lcom/google/android/gms/internal/ads/zzgz;)V
    //   4348: aload_0
    //   4349: getfield 234	com/google/android/gms/internal/ads/zzkd:zzh	Lcom/google/android/gms/internal/ads/zzei;
    //   4352: iconst_2
    //   4353: invokeinterface 639 2 0
    //   4358: pop
    //   4359: goto +160 -> 4519
    //   4362: astore_1
    //   4363: aload_1
    //   4364: instanceof 1191
    //   4367: ifne +20 -> 4387
    //   4370: aload_1
    //   4371: instanceof 1205
    //   4374: ifeq +6 -> 4380
    //   4377: goto +10 -> 4387
    //   4380: sipush 1000
    //   4383: istore_2
    //   4384: goto +7 -> 4391
    //   4387: sipush 1004
    //   4390: istore_2
    //   4391: aload_1
    //   4392: iload_2
    //   4393: invokestatic 1208	com/google/android/gms/internal/ads/zzia:zzd	(Ljava/lang/RuntimeException;I)Lcom/google/android/gms/internal/ads/zzia;
    //   4396: astore_1
    //   4397: ldc_w 339
    //   4400: ldc_w 341
    //   4403: aload_1
    //   4404: invokestatic 346	com/google/android/gms/internal/ads/zzer:zzc	(Ljava/lang/String;Ljava/lang/String;Ljava/lang/Throwable;)V
    //   4407: aload_0
    //   4408: iconst_1
    //   4409: iconst_0
    //   4410: invokespecial 350	com/google/android/gms/internal/ads/zzkd:zzV	(ZZ)V
    //   4413: aload_0
    //   4414: aload_0
    //   4415: getfield 136	com/google/android/gms/internal/ads/zzkd:zzu	Lcom/google/android/gms/internal/ads/zzky;
    //   4418: aload_1
    //   4419: invokevirtual 353	com/google/android/gms/internal/ads/zzky:zzf	(Lcom/google/android/gms/internal/ads/zzia;)Lcom/google/android/gms/internal/ads/zzky;
    //   4422: putfield 136	com/google/android/gms/internal/ads/zzkd:zzu	Lcom/google/android/gms/internal/ads/zzky;
    //   4425: goto +94 -> 4519
    //   4428: astore_1
    //   4429: aload_0
    //   4430: aload_1
    //   4431: sipush 2000
    //   4434: invokespecial 1210	com/google/android/gms/internal/ads/zzkd:zzD	(Ljava/io/IOException;I)V
    //   4437: goto +82 -> 4519
    //   4440: astore_1
    //   4441: aload_0
    //   4442: aload_1
    //   4443: sipush 1002
    //   4446: invokespecial 1210	com/google/android/gms/internal/ads/zzkd:zzD	(Ljava/io/IOException;I)V
    //   4449: goto +70 -> 4519
    //   4452: astore_1
    //   4453: aload_0
    //   4454: aload_1
    //   4455: aload_1
    //   4456: getfield 1211	com/google/android/gms/internal/ads/zzfy:zza	I
    //   4459: invokespecial 1210	com/google/android/gms/internal/ads/zzkd:zzD	(Ljava/io/IOException;I)V
    //   4462: goto +57 -> 4519
    //   4465: astore_1
    //   4466: aload_1
    //   4467: getfield 1212	com/google/android/gms/internal/ads/zzce:zzb	I
    //   4470: iconst_1
    //   4471: if_icmpne +25 -> 4496
    //   4474: iconst_1
    //   4475: aload_1
    //   4476: getfield 1214	com/google/android/gms/internal/ads/zzce:zza	Z
    //   4479: if_icmpeq +10 -> 4489
    //   4482: sipush 3003
    //   4485: istore_2
    //   4486: goto +14 -> 4500
    //   4489: sipush 3001
    //   4492: istore_2
    //   4493: goto +7 -> 4500
    //   4496: sipush 1000
    //   4499: istore_2
    //   4500: aload_0
    //   4501: aload_1
    //   4502: iload_2
    //   4503: invokespecial 1210	com/google/android/gms/internal/ads/zzkd:zzD	(Ljava/io/IOException;I)V
    //   4506: goto +13 -> 4519
    //   4509: astore_1
    //   4510: aload_0
    //   4511: aload_1
    //   4512: aload_1
    //   4513: getfield 1215	com/google/android/gms/internal/ads/zzqj:zza	I
    //   4516: invokespecial 1210	com/google/android/gms/internal/ads/zzkd:zzD	(Ljava/io/IOException;I)V
    //   4519: goto +294 -> 4813
    //   4522: astore 20
    //   4524: aload 20
    //   4526: astore_1
    //   4527: aload 20
    //   4529: getfield 1216	com/google/android/gms/internal/ads/zzia:zze	I
    //   4532: iconst_1
    //   4533: if_icmpne +34 -> 4567
    //   4536: aload_0
    //   4537: getfield 207	com/google/android/gms/internal/ads/zzkd:zzq	Lcom/google/android/gms/internal/ads/zzkl;
    //   4540: invokevirtual 258	com/google/android/gms/internal/ads/zzkl:zze	()Lcom/google/android/gms/internal/ads/zzki;
    //   4543: astore 21
    //   4545: aload 20
    //   4547: astore_1
    //   4548: aload 21
    //   4550: ifnull +17 -> 4567
    //   4553: aload 20
    //   4555: aload 21
    //   4557: getfield 329	com/google/android/gms/internal/ads/zzki:zzf	Lcom/google/android/gms/internal/ads/zzkj;
    //   4560: getfield 334	com/google/android/gms/internal/ads/zzkj:zza	Lcom/google/android/gms/internal/ads/zztl;
    //   4563: invokevirtual 337	com/google/android/gms/internal/ads/zzia:zza	(Lcom/google/android/gms/internal/ads/zzbx;)Lcom/google/android/gms/internal/ads/zzia;
    //   4566: astore_1
    //   4567: aload_1
    //   4568: getfield 1218	com/google/android/gms/internal/ads/zzia:zzk	Z
    //   4571: ifeq +52 -> 4623
    //   4574: aload_0
    //   4575: getfield 645	com/google/android/gms/internal/ads/zzkd:zzL	Lcom/google/android/gms/internal/ads/zzia;
    //   4578: ifnonnull +45 -> 4623
    //   4581: ldc_w 339
    //   4584: ldc_w 1220
    //   4587: aload_1
    //   4588: invokestatic 1222	com/google/android/gms/internal/ads/zzer:zzf	(Ljava/lang/String;Ljava/lang/String;Ljava/lang/Throwable;)V
    //   4591: aload_0
    //   4592: aload_1
    //   4593: putfield 645	com/google/android/gms/internal/ads/zzkd:zzL	Lcom/google/android/gms/internal/ads/zzia;
    //   4596: aload_0
    //   4597: getfield 234	com/google/android/gms/internal/ads/zzkd:zzh	Lcom/google/android/gms/internal/ads/zzei;
    //   4600: astore 20
    //   4602: aload 20
    //   4604: aload 20
    //   4606: bipush 25
    //   4608: aload_1
    //   4609: invokeinterface 1067 3 0
    //   4614: invokeinterface 1225 2 0
    //   4619: pop
    //   4620: goto -101 -> 4519
    //   4623: aload_0
    //   4624: getfield 645	com/google/android/gms/internal/ads/zzkd:zzL	Lcom/google/android/gms/internal/ads/zzia;
    //   4627: astore 21
    //   4629: aload_1
    //   4630: astore 20
    //   4632: aload 21
    //   4634: ifnull +42 -> 4676
    //   4637: ldc_w 1227
    //   4640: ldc_w 1229
    //   4643: iconst_1
    //   4644: anewarray 1231	java/lang/Class
    //   4647: dup
    //   4648: iconst_0
    //   4649: ldc_w 1227
    //   4652: aastore
    //   4653: invokevirtual 1235	java/lang/Class:getDeclaredMethod	(Ljava/lang/String;[Ljava/lang/Class;)Ljava/lang/reflect/Method;
    //   4656: aload 21
    //   4658: iconst_1
    //   4659: anewarray 4	java/lang/Object
    //   4662: dup
    //   4663: iconst_0
    //   4664: aload_1
    //   4665: aastore
    //   4666: invokevirtual 1241	java/lang/reflect/Method:invoke	(Ljava/lang/Object;[Ljava/lang/Object;)Ljava/lang/Object;
    //   4669: pop
    //   4670: aload_0
    //   4671: getfield 645	com/google/android/gms/internal/ads/zzkd:zzL	Lcom/google/android/gms/internal/ads/zzia;
    //   4674: astore 20
    //   4676: ldc_w 339
    //   4679: ldc_w 341
    //   4682: aload 20
    //   4684: invokestatic 346	com/google/android/gms/internal/ads/zzer:zzc	(Ljava/lang/String;Ljava/lang/String;Ljava/lang/Throwable;)V
    //   4687: aload 20
    //   4689: getfield 1216	com/google/android/gms/internal/ads/zzia:zze	I
    //   4692: iconst_1
    //   4693: if_icmpne +101 -> 4794
    //   4696: aload_0
    //   4697: getfield 207	com/google/android/gms/internal/ads/zzkd:zzq	Lcom/google/android/gms/internal/ads/zzkl;
    //   4700: invokevirtual 278	com/google/android/gms/internal/ads/zzkl:zzd	()Lcom/google/android/gms/internal/ads/zzki;
    //   4703: aload_0
    //   4704: getfield 207	com/google/android/gms/internal/ads/zzkd:zzq	Lcom/google/android/gms/internal/ads/zzkl;
    //   4707: invokevirtual 258	com/google/android/gms/internal/ads/zzkl:zze	()Lcom/google/android/gms/internal/ads/zzki;
    //   4710: if_acmpeq +81 -> 4791
    //   4713: aload_0
    //   4714: getfield 207	com/google/android/gms/internal/ads/zzkd:zzq	Lcom/google/android/gms/internal/ads/zzkl;
    //   4717: invokevirtual 278	com/google/android/gms/internal/ads/zzkl:zzd	()Lcom/google/android/gms/internal/ads/zzki;
    //   4720: aload_0
    //   4721: getfield 207	com/google/android/gms/internal/ads/zzkd:zzq	Lcom/google/android/gms/internal/ads/zzkl;
    //   4724: invokevirtual 258	com/google/android/gms/internal/ads/zzkl:zze	()Lcom/google/android/gms/internal/ads/zzki;
    //   4727: if_acmpeq +14 -> 4741
    //   4730: aload_0
    //   4731: getfield 207	com/google/android/gms/internal/ads/zzkd:zzq	Lcom/google/android/gms/internal/ads/zzkl;
    //   4734: invokevirtual 901	com/google/android/gms/internal/ads/zzkl:zza	()Lcom/google/android/gms/internal/ads/zzki;
    //   4737: pop
    //   4738: goto -25 -> 4713
    //   4741: aload_0
    //   4742: getfield 207	com/google/android/gms/internal/ads/zzkd:zzq	Lcom/google/android/gms/internal/ads/zzkl;
    //   4745: invokevirtual 278	com/google/android/gms/internal/ads/zzkl:zzd	()Lcom/google/android/gms/internal/ads/zzki;
    //   4748: astore_1
    //   4749: aload_1
    //   4750: invokestatic 1153	java/util/Objects:requireNonNull	(Ljava/lang/Object;)Ljava/lang/Object;
    //   4753: pop
    //   4754: aload_1
    //   4755: getfield 329	com/google/android/gms/internal/ads/zzki:zzf	Lcom/google/android/gms/internal/ads/zzkj;
    //   4758: astore_1
    //   4759: aload_1
    //   4760: getfield 334	com/google/android/gms/internal/ads/zzkj:zza	Lcom/google/android/gms/internal/ads/zztl;
    //   4763: astore 21
    //   4765: aload_1
    //   4766: getfield 570	com/google/android/gms/internal/ads/zzkj:zzb	J
    //   4769: lstore 8
    //   4771: aload_0
    //   4772: aload_0
    //   4773: aload 21
    //   4775: lload 8
    //   4777: aload_1
    //   4778: getfield 945	com/google/android/gms/internal/ads/zzkj:zzc	J
    //   4781: lload 8
    //   4783: iconst_1
    //   4784: iconst_0
    //   4785: invokespecial 515	com/google/android/gms/internal/ads/zzkd:zzz	(Lcom/google/android/gms/internal/ads/zztl;JJJZI)Lcom/google/android/gms/internal/ads/zzky;
    //   4788: putfield 136	com/google/android/gms/internal/ads/zzkd:zzu	Lcom/google/android/gms/internal/ads/zzky;
    //   4791: goto +3 -> 4794
    //   4794: aload_0
    //   4795: iconst_1
    //   4796: iconst_0
    //   4797: invokespecial 350	com/google/android/gms/internal/ads/zzkd:zzV	(ZZ)V
    //   4800: aload_0
    //   4801: aload_0
    //   4802: getfield 136	com/google/android/gms/internal/ads/zzkd:zzu	Lcom/google/android/gms/internal/ads/zzky;
    //   4805: aload 20
    //   4807: invokevirtual 353	com/google/android/gms/internal/ads/zzky:zzf	(Lcom/google/android/gms/internal/ads/zzia;)Lcom/google/android/gms/internal/ads/zzky;
    //   4810: putfield 136	com/google/android/gms/internal/ads/zzkd:zzu	Lcom/google/android/gms/internal/ads/zzky;
    //   4813: aload_0
    //   4814: invokespecial 1147	com/google/android/gms/internal/ads/zzkd:zzJ	()V
    //   4817: iconst_1
    //   4818: ireturn
    //   4819: astore_1
    //   4820: goto -150 -> 4670
    // Local variable table:
    //   start	length	slot	name	signature
    //   0	4823	0	this	zzkd
    //   0	4823	1	paramMessage	android.os.Message
    //   313	1529	2	i	int
    //   2167	2336	2	j	int
    //   318	3901	3	k	int
    //   2716	670	4	m	int
    //   3189	581	5	n	int
    //   3192	232	6	i1	int
    //   3212	180	7	i2	int
    //   1126	3656	8	l1	long
    //   1449	2793	10	l2	long
    //   1404	514	12	l3	long
    //   1716	99	14	l4	long
    //   1706	13	16	l5	long
    //   147	4126	18	i3	int
    //   1580	913	19	bool	boolean
    //   360	1229	20	localObject1	Object
    //   1596	1	20	localObject2	Object
    //   1654	210	20	localObject3	Object
    //   1896	1	20	localObject4	Object
    //   1905	1	20	localObject5	Object
    //   1910	21	20	localObject6	Object
    //   2048	2123	20	localObject7	Object
    //   4522	32	20	localzzia	zzia
    //   4600	206	20	localObject8	Object
    //   510	4264	21	localObject9	Object
    //   1365	2466	22	localObject10	Object
    //   2313	459	23	localObject11	Object
    //   2303	28	24	localzzcx	zzcx
    // Exception table:
    //   from	to	target	type
    //   848	859	862	finally
    //   863	865	862	finally
    //   1234	1245	1247	finally
    //   1248	1250	1247	finally
    //   1587	1593	1596	finally
    //   1606	1622	1596	finally
    //   1622	1630	1596	finally
    //   1661	1669	1596	finally
    //   1676	1694	1596	finally
    //   1844	1874	1896	finally
    //   1718	1744	1905	finally
    //   1758	1765	1905	finally
    //   1792	1803	1905	finally
    //   1812	1823	1905	finally
    //   1570	1582	1910	finally
    //   1633	1656	1910	finally
    //   1701	1714	1910	finally
    //   0	124	4362	java/lang/RuntimeException
    //   126	135	4362	java/lang/RuntimeException
    //   138	146	4362	java/lang/RuntimeException
    //   155	170	4362	java/lang/RuntimeException
    //   175	196	4362	java/lang/RuntimeException
    //   199	206	4362	java/lang/RuntimeException
    //   215	259	4362	java/lang/RuntimeException
    //   262	274	4362	java/lang/RuntimeException
    //   277	306	4362	java/lang/RuntimeException
    //   309	350	4362	java/lang/RuntimeException
    //   353	413	4362	java/lang/RuntimeException
    //   416	443	4362	java/lang/RuntimeException
    //   450	455	4362	java/lang/RuntimeException
    //   455	475	4362	java/lang/RuntimeException
    //   478	546	4362	java/lang/RuntimeException
    //   546	566	4362	java/lang/RuntimeException
    //   569	581	4362	java/lang/RuntimeException
    //   584	623	4362	java/lang/RuntimeException
    //   626	662	4362	java/lang/RuntimeException
    //   665	696	4362	java/lang/RuntimeException
    //   706	717	4362	java/lang/RuntimeException
    //   720	737	4362	java/lang/RuntimeException
    //   740	747	4362	java/lang/RuntimeException
    //   756	779	4362	java/lang/RuntimeException
    //   784	794	4362	java/lang/RuntimeException
    //   807	836	4362	java/lang/RuntimeException
    //   846	848	4362	java/lang/RuntimeException
    //   865	867	4362	java/lang/RuntimeException
    //   867	874	4362	java/lang/RuntimeException
    //   883	913	4362	java/lang/RuntimeException
    //   913	918	4362	java/lang/RuntimeException
    //   921	954	4362	java/lang/RuntimeException
    //   954	959	4362	java/lang/RuntimeException
    //   962	966	4362	java/lang/RuntimeException
    //   969	1003	4362	java/lang/RuntimeException
    //   1006	1148	4362	java/lang/RuntimeException
    //   1148	1152	4362	java/lang/RuntimeException
    //   1155	1163	4362	java/lang/RuntimeException
    //   1165	1171	4362	java/lang/RuntimeException
    //   1176	1198	4362	java/lang/RuntimeException
    //   1204	1223	4362	java/lang/RuntimeException
    //   1227	1232	4362	java/lang/RuntimeException
    //   1232	1234	4362	java/lang/RuntimeException
    //   1250	1252	4362	java/lang/RuntimeException
    //   1252	1258	4362	java/lang/RuntimeException
    //   1261	1272	4362	java/lang/RuntimeException
    //   1275	1298	4362	java/lang/RuntimeException
    //   1301	1349	4362	java/lang/RuntimeException
    //   1354	1401	4362	java/lang/RuntimeException
    //   1415	1446	4362	java/lang/RuntimeException
    //   1458	1528	4362	java/lang/RuntimeException
    //   1541	1548	4362	java/lang/RuntimeException
    //   1765	1780	4362	java/lang/RuntimeException
    //   1780	1785	4362	java/lang/RuntimeException
    //   1878	1893	4362	java/lang/RuntimeException
    //   1912	1933	4362	java/lang/RuntimeException
    //   1933	1971	4362	java/lang/RuntimeException
    //   1974	2011	4362	java/lang/RuntimeException
    //   2015	2085	4362	java/lang/RuntimeException
    //   2085	2090	4362	java/lang/RuntimeException
    //   2090	2109	4362	java/lang/RuntimeException
    //   2112	2116	4362	java/lang/RuntimeException
    //   2116	2125	4362	java/lang/RuntimeException
    //   2133	2148	4362	java/lang/RuntimeException
    //   2151	2166	4362	java/lang/RuntimeException
    //   2168	2178	4362	java/lang/RuntimeException
    //   2189	2209	4362	java/lang/RuntimeException
    //   2214	2238	4362	java/lang/RuntimeException
    //   2247	2274	4362	java/lang/RuntimeException
    //   2274	2325	4362	java/lang/RuntimeException
    //   2325	2383	4362	java/lang/RuntimeException
    //   2395	2410	4362	java/lang/RuntimeException
    //   2418	2424	4362	java/lang/RuntimeException
    //   2429	2444	4362	java/lang/RuntimeException
    //   2449	2492	4362	java/lang/RuntimeException
    //   2497	2507	4362	java/lang/RuntimeException
    //   2507	2521	4362	java/lang/RuntimeException
    //   2527	2545	4362	java/lang/RuntimeException
    //   2547	2555	4362	java/lang/RuntimeException
    //   2564	2573	4362	java/lang/RuntimeException
    //   2578	2608	4362	java/lang/RuntimeException
    //   2626	2636	4362	java/lang/RuntimeException
    //   2644	2650	4362	java/lang/RuntimeException
    //   2656	2664	4362	java/lang/RuntimeException
    //   2668	2686	4362	java/lang/RuntimeException
    //   2689	2703	4362	java/lang/RuntimeException
    //   2707	2718	4362	java/lang/RuntimeException
    //   2732	2766	4362	java/lang/RuntimeException
    //   2776	2817	4362	java/lang/RuntimeException
    //   2823	2839	4362	java/lang/RuntimeException
    //   2861	2865	4362	java/lang/RuntimeException
    //   2867	2889	4362	java/lang/RuntimeException
    //   2893	2898	4362	java/lang/RuntimeException
    //   2902	2921	4362	java/lang/RuntimeException
    //   2925	2929	4362	java/lang/RuntimeException
    //   2929	2937	4362	java/lang/RuntimeException
    //   2942	3017	4362	java/lang/RuntimeException
    //   3024	3073	4362	java/lang/RuntimeException
    //   3078	3086	4362	java/lang/RuntimeException
    //   3099	3108	4362	java/lang/RuntimeException
    //   3113	3122	4362	java/lang/RuntimeException
    //   3125	3175	4362	java/lang/RuntimeException
    //   3182	3191	4362	java/lang/RuntimeException
    //   3214	3237	4362	java/lang/RuntimeException
    //   3241	3250	4362	java/lang/RuntimeException
    //   3257	3274	4362	java/lang/RuntimeException
    //   3288	3297	4362	java/lang/RuntimeException
    //   3316	3334	4362	java/lang/RuntimeException
    //   3373	3379	4362	java/lang/RuntimeException
    //   3397	3407	4362	java/lang/RuntimeException
    //   3413	3423	4362	java/lang/RuntimeException
    //   3428	3436	4362	java/lang/RuntimeException
    //   3445	3458	4362	java/lang/RuntimeException
    //   3458	3484	4362	java/lang/RuntimeException
    //   3484	3504	4362	java/lang/RuntimeException
    //   3507	3520	4362	java/lang/RuntimeException
    //   3523	3537	4362	java/lang/RuntimeException
    //   3545	3592	4362	java/lang/RuntimeException
    //   3600	3625	4362	java/lang/RuntimeException
    //   3632	3652	4362	java/lang/RuntimeException
    //   3667	3714	4362	java/lang/RuntimeException
    //   3717	3738	4362	java/lang/RuntimeException
    //   3741	3766	4362	java/lang/RuntimeException
    //   3774	3802	4362	java/lang/RuntimeException
    //   3806	3819	4362	java/lang/RuntimeException
    //   3838	3843	4362	java/lang/RuntimeException
    //   3846	3853	4362	java/lang/RuntimeException
    //   3853	3857	4362	java/lang/RuntimeException
    //   3857	3868	4362	java/lang/RuntimeException
    //   3870	3878	4362	java/lang/RuntimeException
    //   3883	3924	4362	java/lang/RuntimeException
    //   3930	3978	4362	java/lang/RuntimeException
    //   3981	3996	4362	java/lang/RuntimeException
    //   3999	4012	4362	java/lang/RuntimeException
    //   4012	4019	4362	java/lang/RuntimeException
    //   4019	4037	4362	java/lang/RuntimeException
    //   4044	4058	4362	java/lang/RuntimeException
    //   4071	4175	4362	java/lang/RuntimeException
    //   4178	4183	4362	java/lang/RuntimeException
    //   4188	4196	4362	java/lang/RuntimeException
    //   4221	4237	4362	java/lang/RuntimeException
    //   4240	4249	4362	java/lang/RuntimeException
    //   4249	4252	4362	java/lang/RuntimeException
    //   4255	4262	4362	java/lang/RuntimeException
    //   4271	4283	4362	java/lang/RuntimeException
    //   4286	4325	4362	java/lang/RuntimeException
    //   4332	4359	4362	java/lang/RuntimeException
    //   0	124	4428	java/io/IOException
    //   126	135	4428	java/io/IOException
    //   138	146	4428	java/io/IOException
    //   155	170	4428	java/io/IOException
    //   175	196	4428	java/io/IOException
    //   199	206	4428	java/io/IOException
    //   215	259	4428	java/io/IOException
    //   262	274	4428	java/io/IOException
    //   277	306	4428	java/io/IOException
    //   309	350	4428	java/io/IOException
    //   353	413	4428	java/io/IOException
    //   416	443	4428	java/io/IOException
    //   450	455	4428	java/io/IOException
    //   455	475	4428	java/io/IOException
    //   478	546	4428	java/io/IOException
    //   546	566	4428	java/io/IOException
    //   569	581	4428	java/io/IOException
    //   584	623	4428	java/io/IOException
    //   626	662	4428	java/io/IOException
    //   665	696	4428	java/io/IOException
    //   706	717	4428	java/io/IOException
    //   720	737	4428	java/io/IOException
    //   740	747	4428	java/io/IOException
    //   756	779	4428	java/io/IOException
    //   784	794	4428	java/io/IOException
    //   807	836	4428	java/io/IOException
    //   846	848	4428	java/io/IOException
    //   865	867	4428	java/io/IOException
    //   867	874	4428	java/io/IOException
    //   883	913	4428	java/io/IOException
    //   913	918	4428	java/io/IOException
    //   921	954	4428	java/io/IOException
    //   954	959	4428	java/io/IOException
    //   962	966	4428	java/io/IOException
    //   969	1003	4428	java/io/IOException
    //   1006	1148	4428	java/io/IOException
    //   1148	1152	4428	java/io/IOException
    //   1155	1163	4428	java/io/IOException
    //   1165	1171	4428	java/io/IOException
    //   1176	1198	4428	java/io/IOException
    //   1204	1223	4428	java/io/IOException
    //   1227	1232	4428	java/io/IOException
    //   1232	1234	4428	java/io/IOException
    //   1250	1252	4428	java/io/IOException
    //   1252	1258	4428	java/io/IOException
    //   1261	1272	4428	java/io/IOException
    //   1275	1298	4428	java/io/IOException
    //   1301	1349	4428	java/io/IOException
    //   1354	1401	4428	java/io/IOException
    //   1415	1446	4428	java/io/IOException
    //   1458	1528	4428	java/io/IOException
    //   1541	1548	4428	java/io/IOException
    //   1765	1780	4428	java/io/IOException
    //   1780	1785	4428	java/io/IOException
    //   1878	1893	4428	java/io/IOException
    //   1912	1933	4428	java/io/IOException
    //   1933	1971	4428	java/io/IOException
    //   1974	2011	4428	java/io/IOException
    //   2015	2085	4428	java/io/IOException
    //   2085	2090	4428	java/io/IOException
    //   2090	2109	4428	java/io/IOException
    //   2112	2116	4428	java/io/IOException
    //   2116	2125	4428	java/io/IOException
    //   2133	2148	4428	java/io/IOException
    //   2151	2166	4428	java/io/IOException
    //   2168	2178	4428	java/io/IOException
    //   2189	2209	4428	java/io/IOException
    //   2214	2238	4428	java/io/IOException
    //   2247	2274	4428	java/io/IOException
    //   2274	2325	4428	java/io/IOException
    //   2325	2383	4428	java/io/IOException
    //   2395	2410	4428	java/io/IOException
    //   2418	2424	4428	java/io/IOException
    //   2429	2444	4428	java/io/IOException
    //   2449	2492	4428	java/io/IOException
    //   2497	2507	4428	java/io/IOException
    //   2507	2521	4428	java/io/IOException
    //   2527	2545	4428	java/io/IOException
    //   2547	2555	4428	java/io/IOException
    //   2564	2573	4428	java/io/IOException
    //   2578	2608	4428	java/io/IOException
    //   2626	2636	4428	java/io/IOException
    //   2644	2650	4428	java/io/IOException
    //   2656	2664	4428	java/io/IOException
    //   2668	2686	4428	java/io/IOException
    //   2689	2703	4428	java/io/IOException
    //   2707	2718	4428	java/io/IOException
    //   2732	2766	4428	java/io/IOException
    //   2776	2817	4428	java/io/IOException
    //   2823	2839	4428	java/io/IOException
    //   2861	2865	4428	java/io/IOException
    //   2867	2889	4428	java/io/IOException
    //   2893	2898	4428	java/io/IOException
    //   2902	2921	4428	java/io/IOException
    //   2925	2929	4428	java/io/IOException
    //   2929	2937	4428	java/io/IOException
    //   2942	3017	4428	java/io/IOException
    //   3024	3073	4428	java/io/IOException
    //   3078	3086	4428	java/io/IOException
    //   3099	3108	4428	java/io/IOException
    //   3113	3122	4428	java/io/IOException
    //   3125	3175	4428	java/io/IOException
    //   3182	3191	4428	java/io/IOException
    //   3214	3237	4428	java/io/IOException
    //   3241	3250	4428	java/io/IOException
    //   3257	3274	4428	java/io/IOException
    //   3288	3297	4428	java/io/IOException
    //   3316	3334	4428	java/io/IOException
    //   3373	3379	4428	java/io/IOException
    //   3397	3407	4428	java/io/IOException
    //   3413	3423	4428	java/io/IOException
    //   3428	3436	4428	java/io/IOException
    //   3445	3458	4428	java/io/IOException
    //   3458	3484	4428	java/io/IOException
    //   3484	3504	4428	java/io/IOException
    //   3507	3520	4428	java/io/IOException
    //   3523	3537	4428	java/io/IOException
    //   3545	3592	4428	java/io/IOException
    //   3600	3625	4428	java/io/IOException
    //   3632	3652	4428	java/io/IOException
    //   3667	3714	4428	java/io/IOException
    //   3717	3738	4428	java/io/IOException
    //   3741	3766	4428	java/io/IOException
    //   3774	3802	4428	java/io/IOException
    //   3806	3819	4428	java/io/IOException
    //   3838	3843	4428	java/io/IOException
    //   3846	3853	4428	java/io/IOException
    //   3853	3857	4428	java/io/IOException
    //   3857	3868	4428	java/io/IOException
    //   3870	3878	4428	java/io/IOException
    //   3883	3924	4428	java/io/IOException
    //   3930	3978	4428	java/io/IOException
    //   3981	3996	4428	java/io/IOException
    //   3999	4012	4428	java/io/IOException
    //   4012	4019	4428	java/io/IOException
    //   4019	4037	4428	java/io/IOException
    //   4044	4058	4428	java/io/IOException
    //   4071	4175	4428	java/io/IOException
    //   4178	4183	4428	java/io/IOException
    //   4188	4196	4428	java/io/IOException
    //   4221	4237	4428	java/io/IOException
    //   4240	4249	4428	java/io/IOException
    //   4249	4252	4428	java/io/IOException
    //   4255	4262	4428	java/io/IOException
    //   4271	4283	4428	java/io/IOException
    //   4286	4325	4428	java/io/IOException
    //   4332	4359	4428	java/io/IOException
    //   0	124	4440	com/google/android/gms/internal/ads/zzsn
    //   126	135	4440	com/google/android/gms/internal/ads/zzsn
    //   138	146	4440	com/google/android/gms/internal/ads/zzsn
    //   155	170	4440	com/google/android/gms/internal/ads/zzsn
    //   175	196	4440	com/google/android/gms/internal/ads/zzsn
    //   199	206	4440	com/google/android/gms/internal/ads/zzsn
    //   215	259	4440	com/google/android/gms/internal/ads/zzsn
    //   262	274	4440	com/google/android/gms/internal/ads/zzsn
    //   277	306	4440	com/google/android/gms/internal/ads/zzsn
    //   309	350	4440	com/google/android/gms/internal/ads/zzsn
    //   353	413	4440	com/google/android/gms/internal/ads/zzsn
    //   416	443	4440	com/google/android/gms/internal/ads/zzsn
    //   450	455	4440	com/google/android/gms/internal/ads/zzsn
    //   455	475	4440	com/google/android/gms/internal/ads/zzsn
    //   478	546	4440	com/google/android/gms/internal/ads/zzsn
    //   546	566	4440	com/google/android/gms/internal/ads/zzsn
    //   569	581	4440	com/google/android/gms/internal/ads/zzsn
    //   584	623	4440	com/google/android/gms/internal/ads/zzsn
    //   626	662	4440	com/google/android/gms/internal/ads/zzsn
    //   665	696	4440	com/google/android/gms/internal/ads/zzsn
    //   706	717	4440	com/google/android/gms/internal/ads/zzsn
    //   720	737	4440	com/google/android/gms/internal/ads/zzsn
    //   740	747	4440	com/google/android/gms/internal/ads/zzsn
    //   756	779	4440	com/google/android/gms/internal/ads/zzsn
    //   784	794	4440	com/google/android/gms/internal/ads/zzsn
    //   807	836	4440	com/google/android/gms/internal/ads/zzsn
    //   846	848	4440	com/google/android/gms/internal/ads/zzsn
    //   865	867	4440	com/google/android/gms/internal/ads/zzsn
    //   867	874	4440	com/google/android/gms/internal/ads/zzsn
    //   883	913	4440	com/google/android/gms/internal/ads/zzsn
    //   913	918	4440	com/google/android/gms/internal/ads/zzsn
    //   921	954	4440	com/google/android/gms/internal/ads/zzsn
    //   954	959	4440	com/google/android/gms/internal/ads/zzsn
    //   962	966	4440	com/google/android/gms/internal/ads/zzsn
    //   969	1003	4440	com/google/android/gms/internal/ads/zzsn
    //   1006	1148	4440	com/google/android/gms/internal/ads/zzsn
    //   1148	1152	4440	com/google/android/gms/internal/ads/zzsn
    //   1155	1163	4440	com/google/android/gms/internal/ads/zzsn
    //   1165	1171	4440	com/google/android/gms/internal/ads/zzsn
    //   1176	1198	4440	com/google/android/gms/internal/ads/zzsn
    //   1204	1223	4440	com/google/android/gms/internal/ads/zzsn
    //   1227	1232	4440	com/google/android/gms/internal/ads/zzsn
    //   1232	1234	4440	com/google/android/gms/internal/ads/zzsn
    //   1250	1252	4440	com/google/android/gms/internal/ads/zzsn
    //   1252	1258	4440	com/google/android/gms/internal/ads/zzsn
    //   1261	1272	4440	com/google/android/gms/internal/ads/zzsn
    //   1275	1298	4440	com/google/android/gms/internal/ads/zzsn
    //   1301	1349	4440	com/google/android/gms/internal/ads/zzsn
    //   1354	1401	4440	com/google/android/gms/internal/ads/zzsn
    //   1415	1446	4440	com/google/android/gms/internal/ads/zzsn
    //   1458	1528	4440	com/google/android/gms/internal/ads/zzsn
    //   1541	1548	4440	com/google/android/gms/internal/ads/zzsn
    //   1765	1780	4440	com/google/android/gms/internal/ads/zzsn
    //   1780	1785	4440	com/google/android/gms/internal/ads/zzsn
    //   1878	1893	4440	com/google/android/gms/internal/ads/zzsn
    //   1912	1933	4440	com/google/android/gms/internal/ads/zzsn
    //   1933	1971	4440	com/google/android/gms/internal/ads/zzsn
    //   1974	2011	4440	com/google/android/gms/internal/ads/zzsn
    //   2015	2085	4440	com/google/android/gms/internal/ads/zzsn
    //   2085	2090	4440	com/google/android/gms/internal/ads/zzsn
    //   2090	2109	4440	com/google/android/gms/internal/ads/zzsn
    //   2112	2116	4440	com/google/android/gms/internal/ads/zzsn
    //   2116	2125	4440	com/google/android/gms/internal/ads/zzsn
    //   2133	2148	4440	com/google/android/gms/internal/ads/zzsn
    //   2151	2166	4440	com/google/android/gms/internal/ads/zzsn
    //   2168	2178	4440	com/google/android/gms/internal/ads/zzsn
    //   2189	2209	4440	com/google/android/gms/internal/ads/zzsn
    //   2214	2238	4440	com/google/android/gms/internal/ads/zzsn
    //   2247	2274	4440	com/google/android/gms/internal/ads/zzsn
    //   2274	2325	4440	com/google/android/gms/internal/ads/zzsn
    //   2325	2383	4440	com/google/android/gms/internal/ads/zzsn
    //   2395	2410	4440	com/google/android/gms/internal/ads/zzsn
    //   2418	2424	4440	com/google/android/gms/internal/ads/zzsn
    //   2429	2444	4440	com/google/android/gms/internal/ads/zzsn
    //   2449	2492	4440	com/google/android/gms/internal/ads/zzsn
    //   2497	2507	4440	com/google/android/gms/internal/ads/zzsn
    //   2507	2521	4440	com/google/android/gms/internal/ads/zzsn
    //   2527	2545	4440	com/google/android/gms/internal/ads/zzsn
    //   2547	2555	4440	com/google/android/gms/internal/ads/zzsn
    //   2564	2573	4440	com/google/android/gms/internal/ads/zzsn
    //   2578	2608	4440	com/google/android/gms/internal/ads/zzsn
    //   2626	2636	4440	com/google/android/gms/internal/ads/zzsn
    //   2644	2650	4440	com/google/android/gms/internal/ads/zzsn
    //   2656	2664	4440	com/google/android/gms/internal/ads/zzsn
    //   2668	2686	4440	com/google/android/gms/internal/ads/zzsn
    //   2689	2703	4440	com/google/android/gms/internal/ads/zzsn
    //   2707	2718	4440	com/google/android/gms/internal/ads/zzsn
    //   2732	2766	4440	com/google/android/gms/internal/ads/zzsn
    //   2776	2817	4440	com/google/android/gms/internal/ads/zzsn
    //   2823	2839	4440	com/google/android/gms/internal/ads/zzsn
    //   2861	2865	4440	com/google/android/gms/internal/ads/zzsn
    //   2867	2889	4440	com/google/android/gms/internal/ads/zzsn
    //   2893	2898	4440	com/google/android/gms/internal/ads/zzsn
    //   2902	2921	4440	com/google/android/gms/internal/ads/zzsn
    //   2925	2929	4440	com/google/android/gms/internal/ads/zzsn
    //   2929	2937	4440	com/google/android/gms/internal/ads/zzsn
    //   2942	3017	4440	com/google/android/gms/internal/ads/zzsn
    //   3024	3073	4440	com/google/android/gms/internal/ads/zzsn
    //   3078	3086	4440	com/google/android/gms/internal/ads/zzsn
    //   3099	3108	4440	com/google/android/gms/internal/ads/zzsn
    //   3113	3122	4440	com/google/android/gms/internal/ads/zzsn
    //   3125	3175	4440	com/google/android/gms/internal/ads/zzsn
    //   3182	3191	4440	com/google/android/gms/internal/ads/zzsn
    //   3214	3237	4440	com/google/android/gms/internal/ads/zzsn
    //   3241	3250	4440	com/google/android/gms/internal/ads/zzsn
    //   3257	3274	4440	com/google/android/gms/internal/ads/zzsn
    //   3288	3297	4440	com/google/android/gms/internal/ads/zzsn
    //   3316	3334	4440	com/google/android/gms/internal/ads/zzsn
    //   3373	3379	4440	com/google/android/gms/internal/ads/zzsn
    //   3397	3407	4440	com/google/android/gms/internal/ads/zzsn
    //   3413	3423	4440	com/google/android/gms/internal/ads/zzsn
    //   3428	3436	4440	com/google/android/gms/internal/ads/zzsn
    //   3445	3458	4440	com/google/android/gms/internal/ads/zzsn
    //   3458	3484	4440	com/google/android/gms/internal/ads/zzsn
    //   3484	3504	4440	com/google/android/gms/internal/ads/zzsn
    //   3507	3520	4440	com/google/android/gms/internal/ads/zzsn
    //   3523	3537	4440	com/google/android/gms/internal/ads/zzsn
    //   3545	3592	4440	com/google/android/gms/internal/ads/zzsn
    //   3600	3625	4440	com/google/android/gms/internal/ads/zzsn
    //   3632	3652	4440	com/google/android/gms/internal/ads/zzsn
    //   3667	3714	4440	com/google/android/gms/internal/ads/zzsn
    //   3717	3738	4440	com/google/android/gms/internal/ads/zzsn
    //   3741	3766	4440	com/google/android/gms/internal/ads/zzsn
    //   3774	3802	4440	com/google/android/gms/internal/ads/zzsn
    //   3806	3819	4440	com/google/android/gms/internal/ads/zzsn
    //   3838	3843	4440	com/google/android/gms/internal/ads/zzsn
    //   3846	3853	4440	com/google/android/gms/internal/ads/zzsn
    //   3853	3857	4440	com/google/android/gms/internal/ads/zzsn
    //   3857	3868	4440	com/google/android/gms/internal/ads/zzsn
    //   3870	3878	4440	com/google/android/gms/internal/ads/zzsn
    //   3883	3924	4440	com/google/android/gms/internal/ads/zzsn
    //   3930	3978	4440	com/google/android/gms/internal/ads/zzsn
    //   3981	3996	4440	com/google/android/gms/internal/ads/zzsn
    //   3999	4012	4440	com/google/android/gms/internal/ads/zzsn
    //   4012	4019	4440	com/google/android/gms/internal/ads/zzsn
    //   4019	4037	4440	com/google/android/gms/internal/ads/zzsn
    //   4044	4058	4440	com/google/android/gms/internal/ads/zzsn
    //   4071	4175	4440	com/google/android/gms/internal/ads/zzsn
    //   4178	4183	4440	com/google/android/gms/internal/ads/zzsn
    //   4188	4196	4440	com/google/android/gms/internal/ads/zzsn
    //   4221	4237	4440	com/google/android/gms/internal/ads/zzsn
    //   4240	4249	4440	com/google/android/gms/internal/ads/zzsn
    //   4249	4252	4440	com/google/android/gms/internal/ads/zzsn
    //   4255	4262	4440	com/google/android/gms/internal/ads/zzsn
    //   4271	4283	4440	com/google/android/gms/internal/ads/zzsn
    //   4286	4325	4440	com/google/android/gms/internal/ads/zzsn
    //   4332	4359	4440	com/google/android/gms/internal/ads/zzsn
    //   0	124	4452	com/google/android/gms/internal/ads/zzfy
    //   126	135	4452	com/google/android/gms/internal/ads/zzfy
    //   138	146	4452	com/google/android/gms/internal/ads/zzfy
    //   155	170	4452	com/google/android/gms/internal/ads/zzfy
    //   175	196	4452	com/google/android/gms/internal/ads/zzfy
    //   199	206	4452	com/google/android/gms/internal/ads/zzfy
    //   215	259	4452	com/google/android/gms/internal/ads/zzfy
    //   262	274	4452	com/google/android/gms/internal/ads/zzfy
    //   277	306	4452	com/google/android/gms/internal/ads/zzfy
    //   309	350	4452	com/google/android/gms/internal/ads/zzfy
    //   353	413	4452	com/google/android/gms/internal/ads/zzfy
    //   416	443	4452	com/google/android/gms/internal/ads/zzfy
    //   450	455	4452	com/google/android/gms/internal/ads/zzfy
    //   455	475	4452	com/google/android/gms/internal/ads/zzfy
    //   478	546	4452	com/google/android/gms/internal/ads/zzfy
    //   546	566	4452	com/google/android/gms/internal/ads/zzfy
    //   569	581	4452	com/google/android/gms/internal/ads/zzfy
    //   584	623	4452	com/google/android/gms/internal/ads/zzfy
    //   626	662	4452	com/google/android/gms/internal/ads/zzfy
    //   665	696	4452	com/google/android/gms/internal/ads/zzfy
    //   706	717	4452	com/google/android/gms/internal/ads/zzfy
    //   720	737	4452	com/google/android/gms/internal/ads/zzfy
    //   740	747	4452	com/google/android/gms/internal/ads/zzfy
    //   756	779	4452	com/google/android/gms/internal/ads/zzfy
    //   784	794	4452	com/google/android/gms/internal/ads/zzfy
    //   807	836	4452	com/google/android/gms/internal/ads/zzfy
    //   846	848	4452	com/google/android/gms/internal/ads/zzfy
    //   865	867	4452	com/google/android/gms/internal/ads/zzfy
    //   867	874	4452	com/google/android/gms/internal/ads/zzfy
    //   883	913	4452	com/google/android/gms/internal/ads/zzfy
    //   913	918	4452	com/google/android/gms/internal/ads/zzfy
    //   921	954	4452	com/google/android/gms/internal/ads/zzfy
    //   954	959	4452	com/google/android/gms/internal/ads/zzfy
    //   962	966	4452	com/google/android/gms/internal/ads/zzfy
    //   969	1003	4452	com/google/android/gms/internal/ads/zzfy
    //   1006	1148	4452	com/google/android/gms/internal/ads/zzfy
    //   1148	1152	4452	com/google/android/gms/internal/ads/zzfy
    //   1155	1163	4452	com/google/android/gms/internal/ads/zzfy
    //   1165	1171	4452	com/google/android/gms/internal/ads/zzfy
    //   1176	1198	4452	com/google/android/gms/internal/ads/zzfy
    //   1204	1223	4452	com/google/android/gms/internal/ads/zzfy
    //   1227	1232	4452	com/google/android/gms/internal/ads/zzfy
    //   1232	1234	4452	com/google/android/gms/internal/ads/zzfy
    //   1250	1252	4452	com/google/android/gms/internal/ads/zzfy
    //   1252	1258	4452	com/google/android/gms/internal/ads/zzfy
    //   1261	1272	4452	com/google/android/gms/internal/ads/zzfy
    //   1275	1298	4452	com/google/android/gms/internal/ads/zzfy
    //   1301	1349	4452	com/google/android/gms/internal/ads/zzfy
    //   1354	1401	4452	com/google/android/gms/internal/ads/zzfy
    //   1415	1446	4452	com/google/android/gms/internal/ads/zzfy
    //   1458	1528	4452	com/google/android/gms/internal/ads/zzfy
    //   1541	1548	4452	com/google/android/gms/internal/ads/zzfy
    //   1765	1780	4452	com/google/android/gms/internal/ads/zzfy
    //   1780	1785	4452	com/google/android/gms/internal/ads/zzfy
    //   1878	1893	4452	com/google/android/gms/internal/ads/zzfy
    //   1912	1933	4452	com/google/android/gms/internal/ads/zzfy
    //   1933	1971	4452	com/google/android/gms/internal/ads/zzfy
    //   1974	2011	4452	com/google/android/gms/internal/ads/zzfy
    //   2015	2085	4452	com/google/android/gms/internal/ads/zzfy
    //   2085	2090	4452	com/google/android/gms/internal/ads/zzfy
    //   2090	2109	4452	com/google/android/gms/internal/ads/zzfy
    //   2112	2116	4452	com/google/android/gms/internal/ads/zzfy
    //   2116	2125	4452	com/google/android/gms/internal/ads/zzfy
    //   2133	2148	4452	com/google/android/gms/internal/ads/zzfy
    //   2151	2166	4452	com/google/android/gms/internal/ads/zzfy
    //   2168	2178	4452	com/google/android/gms/internal/ads/zzfy
    //   2189	2209	4452	com/google/android/gms/internal/ads/zzfy
    //   2214	2238	4452	com/google/android/gms/internal/ads/zzfy
    //   2247	2274	4452	com/google/android/gms/internal/ads/zzfy
    //   2274	2325	4452	com/google/android/gms/internal/ads/zzfy
    //   2325	2383	4452	com/google/android/gms/internal/ads/zzfy
    //   2395	2410	4452	com/google/android/gms/internal/ads/zzfy
    //   2418	2424	4452	com/google/android/gms/internal/ads/zzfy
    //   2429	2444	4452	com/google/android/gms/internal/ads/zzfy
    //   2449	2492	4452	com/google/android/gms/internal/ads/zzfy
    //   2497	2507	4452	com/google/android/gms/internal/ads/zzfy
    //   2507	2521	4452	com/google/android/gms/internal/ads/zzfy
    //   2527	2545	4452	com/google/android/gms/internal/ads/zzfy
    //   2547	2555	4452	com/google/android/gms/internal/ads/zzfy
    //   2564	2573	4452	com/google/android/gms/internal/ads/zzfy
    //   2578	2608	4452	com/google/android/gms/internal/ads/zzfy
    //   2626	2636	4452	com/google/android/gms/internal/ads/zzfy
    //   2644	2650	4452	com/google/android/gms/internal/ads/zzfy
    //   2656	2664	4452	com/google/android/gms/internal/ads/zzfy
    //   2668	2686	4452	com/google/android/gms/internal/ads/zzfy
    //   2689	2703	4452	com/google/android/gms/internal/ads/zzfy
    //   2707	2718	4452	com/google/android/gms/internal/ads/zzfy
    //   2732	2766	4452	com/google/android/gms/internal/ads/zzfy
    //   2776	2817	4452	com/google/android/gms/internal/ads/zzfy
    //   2823	2839	4452	com/google/android/gms/internal/ads/zzfy
    //   2861	2865	4452	com/google/android/gms/internal/ads/zzfy
    //   2867	2889	4452	com/google/android/gms/internal/ads/zzfy
    //   2893	2898	4452	com/google/android/gms/internal/ads/zzfy
    //   2902	2921	4452	com/google/android/gms/internal/ads/zzfy
    //   2925	2929	4452	com/google/android/gms/internal/ads/zzfy
    //   2929	2937	4452	com/google/android/gms/internal/ads/zzfy
    //   2942	3017	4452	com/google/android/gms/internal/ads/zzfy
    //   3024	3073	4452	com/google/android/gms/internal/ads/zzfy
    //   3078	3086	4452	com/google/android/gms/internal/ads/zzfy
    //   3099	3108	4452	com/google/android/gms/internal/ads/zzfy
    //   3113	3122	4452	com/google/android/gms/internal/ads/zzfy
    //   3125	3175	4452	com/google/android/gms/internal/ads/zzfy
    //   3182	3191	4452	com/google/android/gms/internal/ads/zzfy
    //   3214	3237	4452	com/google/android/gms/internal/ads/zzfy
    //   3241	3250	4452	com/google/android/gms/internal/ads/zzfy
    //   3257	3274	4452	com/google/android/gms/internal/ads/zzfy
    //   3288	3297	4452	com/google/android/gms/internal/ads/zzfy
    //   3316	3334	4452	com/google/android/gms/internal/ads/zzfy
    //   3373	3379	4452	com/google/android/gms/internal/ads/zzfy
    //   3397	3407	4452	com/google/android/gms/internal/ads/zzfy
    //   3413	3423	4452	com/google/android/gms/internal/ads/zzfy
    //   3428	3436	4452	com/google/android/gms/internal/ads/zzfy
    //   3445	3458	4452	com/google/android/gms/internal/ads/zzfy
    //   3458	3484	4452	com/google/android/gms/internal/ads/zzfy
    //   3484	3504	4452	com/google/android/gms/internal/ads/zzfy
    //   3507	3520	4452	com/google/android/gms/internal/ads/zzfy
    //   3523	3537	4452	com/google/android/gms/internal/ads/zzfy
    //   3545	3592	4452	com/google/android/gms/internal/ads/zzfy
    //   3600	3625	4452	com/google/android/gms/internal/ads/zzfy
    //   3632	3652	4452	com/google/android/gms/internal/ads/zzfy
    //   3667	3714	4452	com/google/android/gms/internal/ads/zzfy
    //   3717	3738	4452	com/google/android/gms/internal/ads/zzfy
    //   3741	3766	4452	com/google/android/gms/internal/ads/zzfy
    //   3774	3802	4452	com/google/android/gms/internal/ads/zzfy
    //   3806	3819	4452	com/google/android/gms/internal/ads/zzfy
    //   3838	3843	4452	com/google/android/gms/internal/ads/zzfy
    //   3846	3853	4452	com/google/android/gms/internal/ads/zzfy
    //   3853	3857	4452	com/google/android/gms/internal/ads/zzfy
    //   3857	3868	4452	com/google/android/gms/internal/ads/zzfy
    //   3870	3878	4452	com/google/android/gms/internal/ads/zzfy
    //   3883	3924	4452	com/google/android/gms/internal/ads/zzfy
    //   3930	3978	4452	com/google/android/gms/internal/ads/zzfy
    //   3981	3996	4452	com/google/android/gms/internal/ads/zzfy
    //   3999	4012	4452	com/google/android/gms/internal/ads/zzfy
    //   4012	4019	4452	com/google/android/gms/internal/ads/zzfy
    //   4019	4037	4452	com/google/android/gms/internal/ads/zzfy
    //   4044	4058	4452	com/google/android/gms/internal/ads/zzfy
    //   4071	4175	4452	com/google/android/gms/internal/ads/zzfy
    //   4178	4183	4452	com/google/android/gms/internal/ads/zzfy
    //   4188	4196	4452	com/google/android/gms/internal/ads/zzfy
    //   4221	4237	4452	com/google/android/gms/internal/ads/zzfy
    //   4240	4249	4452	com/google/android/gms/internal/ads/zzfy
    //   4249	4252	4452	com/google/android/gms/internal/ads/zzfy
    //   4255	4262	4452	com/google/android/gms/internal/ads/zzfy
    //   4271	4283	4452	com/google/android/gms/internal/ads/zzfy
    //   4286	4325	4452	com/google/android/gms/internal/ads/zzfy
    //   4332	4359	4452	com/google/android/gms/internal/ads/zzfy
    //   0	124	4465	com/google/android/gms/internal/ads/zzce
    //   126	135	4465	com/google/android/gms/internal/ads/zzce
    //   138	146	4465	com/google/android/gms/internal/ads/zzce
    //   155	170	4465	com/google/android/gms/internal/ads/zzce
    //   175	196	4465	com/google/android/gms/internal/ads/zzce
    //   199	206	4465	com/google/android/gms/internal/ads/zzce
    //   215	259	4465	com/google/android/gms/internal/ads/zzce
    //   262	274	4465	com/google/android/gms/internal/ads/zzce
    //   277	306	4465	com/google/android/gms/internal/ads/zzce
    //   309	350	4465	com/google/android/gms/internal/ads/zzce
    //   353	413	4465	com/google/android/gms/internal/ads/zzce
    //   416	443	4465	com/google/android/gms/internal/ads/zzce
    //   450	455	4465	com/google/android/gms/internal/ads/zzce
    //   455	475	4465	com/google/android/gms/internal/ads/zzce
    //   478	546	4465	com/google/android/gms/internal/ads/zzce
    //   546	566	4465	com/google/android/gms/internal/ads/zzce
    //   569	581	4465	com/google/android/gms/internal/ads/zzce
    //   584	623	4465	com/google/android/gms/internal/ads/zzce
    //   626	662	4465	com/google/android/gms/internal/ads/zzce
    //   665	696	4465	com/google/android/gms/internal/ads/zzce
    //   706	717	4465	com/google/android/gms/internal/ads/zzce
    //   720	737	4465	com/google/android/gms/internal/ads/zzce
    //   740	747	4465	com/google/android/gms/internal/ads/zzce
    //   756	779	4465	com/google/android/gms/internal/ads/zzce
    //   784	794	4465	com/google/android/gms/internal/ads/zzce
    //   807	836	4465	com/google/android/gms/internal/ads/zzce
    //   846	848	4465	com/google/android/gms/internal/ads/zzce
    //   865	867	4465	com/google/android/gms/internal/ads/zzce
    //   867	874	4465	com/google/android/gms/internal/ads/zzce
    //   883	913	4465	com/google/android/gms/internal/ads/zzce
    //   913	918	4465	com/google/android/gms/internal/ads/zzce
    //   921	954	4465	com/google/android/gms/internal/ads/zzce
    //   954	959	4465	com/google/android/gms/internal/ads/zzce
    //   962	966	4465	com/google/android/gms/internal/ads/zzce
    //   969	1003	4465	com/google/android/gms/internal/ads/zzce
    //   1006	1148	4465	com/google/android/gms/internal/ads/zzce
    //   1148	1152	4465	com/google/android/gms/internal/ads/zzce
    //   1155	1163	4465	com/google/android/gms/internal/ads/zzce
    //   1165	1171	4465	com/google/android/gms/internal/ads/zzce
    //   1176	1198	4465	com/google/android/gms/internal/ads/zzce
    //   1204	1223	4465	com/google/android/gms/internal/ads/zzce
    //   1227	1232	4465	com/google/android/gms/internal/ads/zzce
    //   1232	1234	4465	com/google/android/gms/internal/ads/zzce
    //   1250	1252	4465	com/google/android/gms/internal/ads/zzce
    //   1252	1258	4465	com/google/android/gms/internal/ads/zzce
    //   1261	1272	4465	com/google/android/gms/internal/ads/zzce
    //   1275	1298	4465	com/google/android/gms/internal/ads/zzce
    //   1301	1349	4465	com/google/android/gms/internal/ads/zzce
    //   1354	1401	4465	com/google/android/gms/internal/ads/zzce
    //   1415	1446	4465	com/google/android/gms/internal/ads/zzce
    //   1458	1528	4465	com/google/android/gms/internal/ads/zzce
    //   1541	1548	4465	com/google/android/gms/internal/ads/zzce
    //   1765	1780	4465	com/google/android/gms/internal/ads/zzce
    //   1780	1785	4465	com/google/android/gms/internal/ads/zzce
    //   1878	1893	4465	com/google/android/gms/internal/ads/zzce
    //   1912	1933	4465	com/google/android/gms/internal/ads/zzce
    //   1933	1971	4465	com/google/android/gms/internal/ads/zzce
    //   1974	2011	4465	com/google/android/gms/internal/ads/zzce
    //   2015	2085	4465	com/google/android/gms/internal/ads/zzce
    //   2085	2090	4465	com/google/android/gms/internal/ads/zzce
    //   2090	2109	4465	com/google/android/gms/internal/ads/zzce
    //   2112	2116	4465	com/google/android/gms/internal/ads/zzce
    //   2116	2125	4465	com/google/android/gms/internal/ads/zzce
    //   2133	2148	4465	com/google/android/gms/internal/ads/zzce
    //   2151	2166	4465	com/google/android/gms/internal/ads/zzce
    //   2168	2178	4465	com/google/android/gms/internal/ads/zzce
    //   2189	2209	4465	com/google/android/gms/internal/ads/zzce
    //   2214	2238	4465	com/google/android/gms/internal/ads/zzce
    //   2247	2274	4465	com/google/android/gms/internal/ads/zzce
    //   2274	2325	4465	com/google/android/gms/internal/ads/zzce
    //   2325	2383	4465	com/google/android/gms/internal/ads/zzce
    //   2395	2410	4465	com/google/android/gms/internal/ads/zzce
    //   2418	2424	4465	com/google/android/gms/internal/ads/zzce
    //   2429	2444	4465	com/google/android/gms/internal/ads/zzce
    //   2449	2492	4465	com/google/android/gms/internal/ads/zzce
    //   2497	2507	4465	com/google/android/gms/internal/ads/zzce
    //   2507	2521	4465	com/google/android/gms/internal/ads/zzce
    //   2527	2545	4465	com/google/android/gms/internal/ads/zzce
    //   2547	2555	4465	com/google/android/gms/internal/ads/zzce
    //   2564	2573	4465	com/google/android/gms/internal/ads/zzce
    //   2578	2608	4465	com/google/android/gms/internal/ads/zzce
    //   2626	2636	4465	com/google/android/gms/internal/ads/zzce
    //   2644	2650	4465	com/google/android/gms/internal/ads/zzce
    //   2656	2664	4465	com/google/android/gms/internal/ads/zzce
    //   2668	2686	4465	com/google/android/gms/internal/ads/zzce
    //   2689	2703	4465	com/google/android/gms/internal/ads/zzce
    //   2707	2718	4465	com/google/android/gms/internal/ads/zzce
    //   2732	2766	4465	com/google/android/gms/internal/ads/zzce
    //   2776	2817	4465	com/google/android/gms/internal/ads/zzce
    //   2823	2839	4465	com/google/android/gms/internal/ads/zzce
    //   2861	2865	4465	com/google/android/gms/internal/ads/zzce
    //   2867	2889	4465	com/google/android/gms/internal/ads/zzce
    //   2893	2898	4465	com/google/android/gms/internal/ads/zzce
    //   2902	2921	4465	com/google/android/gms/internal/ads/zzce
    //   2925	2929	4465	com/google/android/gms/internal/ads/zzce
    //   2929	2937	4465	com/google/android/gms/internal/ads/zzce
    //   2942	3017	4465	com/google/android/gms/internal/ads/zzce
    //   3024	3073	4465	com/google/android/gms/internal/ads/zzce
    //   3078	3086	4465	com/google/android/gms/internal/ads/zzce
    //   3099	3108	4465	com/google/android/gms/internal/ads/zzce
    //   3113	3122	4465	com/google/android/gms/internal/ads/zzce
    //   3125	3175	4465	com/google/android/gms/internal/ads/zzce
    //   3182	3191	4465	com/google/android/gms/internal/ads/zzce
    //   3214	3237	4465	com/google/android/gms/internal/ads/zzce
    //   3241	3250	4465	com/google/android/gms/internal/ads/zzce
    //   3257	3274	4465	com/google/android/gms/internal/ads/zzce
    //   3288	3297	4465	com/google/android/gms/internal/ads/zzce
    //   3316	3334	4465	com/google/android/gms/internal/ads/zzce
    //   3373	3379	4465	com/google/android/gms/internal/ads/zzce
    //   3397	3407	4465	com/google/android/gms/internal/ads/zzce
    //   3413	3423	4465	com/google/android/gms/internal/ads/zzce
    //   3428	3436	4465	com/google/android/gms/internal/ads/zzce
    //   3445	3458	4465	com/google/android/gms/internal/ads/zzce
    //   3458	3484	4465	com/google/android/gms/internal/ads/zzce
    //   3484	3504	4465	com/google/android/gms/internal/ads/zzce
    //   3507	3520	4465	com/google/android/gms/internal/ads/zzce
    //   3523	3537	4465	com/google/android/gms/internal/ads/zzce
    //   3545	3592	4465	com/google/android/gms/internal/ads/zzce
    //   3600	3625	4465	com/google/android/gms/internal/ads/zzce
    //   3632	3652	4465	com/google/android/gms/internal/ads/zzce
    //   3667	3714	4465	com/google/android/gms/internal/ads/zzce
    //   3717	3738	4465	com/google/android/gms/internal/ads/zzce
    //   3741	3766	4465	com/google/android/gms/internal/ads/zzce
    //   3774	3802	4465	com/google/android/gms/internal/ads/zzce
    //   3806	3819	4465	com/google/android/gms/internal/ads/zzce
    //   3838	3843	4465	com/google/android/gms/internal/ads/zzce
    //   3846	3853	4465	com/google/android/gms/internal/ads/zzce
    //   3853	3857	4465	com/google/android/gms/internal/ads/zzce
    //   3857	3868	4465	com/google/android/gms/internal/ads/zzce
    //   3870	3878	4465	com/google/android/gms/internal/ads/zzce
    //   3883	3924	4465	com/google/android/gms/internal/ads/zzce
    //   3930	3978	4465	com/google/android/gms/internal/ads/zzce
    //   3981	3996	4465	com/google/android/gms/internal/ads/zzce
    //   3999	4012	4465	com/google/android/gms/internal/ads/zzce
    //   4012	4019	4465	com/google/android/gms/internal/ads/zzce
    //   4019	4037	4465	com/google/android/gms/internal/ads/zzce
    //   4044	4058	4465	com/google/android/gms/internal/ads/zzce
    //   4071	4175	4465	com/google/android/gms/internal/ads/zzce
    //   4178	4183	4465	com/google/android/gms/internal/ads/zzce
    //   4188	4196	4465	com/google/android/gms/internal/ads/zzce
    //   4221	4237	4465	com/google/android/gms/internal/ads/zzce
    //   4240	4249	4465	com/google/android/gms/internal/ads/zzce
    //   4249	4252	4465	com/google/android/gms/internal/ads/zzce
    //   4255	4262	4465	com/google/android/gms/internal/ads/zzce
    //   4271	4283	4465	com/google/android/gms/internal/ads/zzce
    //   4286	4325	4465	com/google/android/gms/internal/ads/zzce
    //   4332	4359	4465	com/google/android/gms/internal/ads/zzce
    //   0	124	4509	com/google/android/gms/internal/ads/zzqj
    //   126	135	4509	com/google/android/gms/internal/ads/zzqj
    //   138	146	4509	com/google/android/gms/internal/ads/zzqj
    //   155	170	4509	com/google/android/gms/internal/ads/zzqj
    //   175	196	4509	com/google/android/gms/internal/ads/zzqj
    //   199	206	4509	com/google/android/gms/internal/ads/zzqj
    //   215	259	4509	com/google/android/gms/internal/ads/zzqj
    //   262	274	4509	com/google/android/gms/internal/ads/zzqj
    //   277	306	4509	com/google/android/gms/internal/ads/zzqj
    //   309	350	4509	com/google/android/gms/internal/ads/zzqj
    //   353	413	4509	com/google/android/gms/internal/ads/zzqj
    //   416	443	4509	com/google/android/gms/internal/ads/zzqj
    //   450	455	4509	com/google/android/gms/internal/ads/zzqj
    //   455	475	4509	com/google/android/gms/internal/ads/zzqj
    //   478	546	4509	com/google/android/gms/internal/ads/zzqj
    //   546	566	4509	com/google/android/gms/internal/ads/zzqj
    //   569	581	4509	com/google/android/gms/internal/ads/zzqj
    //   584	623	4509	com/google/android/gms/internal/ads/zzqj
    //   626	662	4509	com/google/android/gms/internal/ads/zzqj
    //   665	696	4509	com/google/android/gms/internal/ads/zzqj
    //   706	717	4509	com/google/android/gms/internal/ads/zzqj
    //   720	737	4509	com/google/android/gms/internal/ads/zzqj
    //   740	747	4509	com/google/android/gms/internal/ads/zzqj
    //   756	779	4509	com/google/android/gms/internal/ads/zzqj
    //   784	794	4509	com/google/android/gms/internal/ads/zzqj
    //   807	836	4509	com/google/android/gms/internal/ads/zzqj
    //   846	848	4509	com/google/android/gms/internal/ads/zzqj
    //   865	867	4509	com/google/android/gms/internal/ads/zzqj
    //   867	874	4509	com/google/android/gms/internal/ads/zzqj
    //   883	913	4509	com/google/android/gms/internal/ads/zzqj
    //   913	918	4509	com/google/android/gms/internal/ads/zzqj
    //   921	954	4509	com/google/android/gms/internal/ads/zzqj
    //   954	959	4509	com/google/android/gms/internal/ads/zzqj
    //   962	966	4509	com/google/android/gms/internal/ads/zzqj
    //   969	1003	4509	com/google/android/gms/internal/ads/zzqj
    //   1006	1148	4509	com/google/android/gms/internal/ads/zzqj
    //   1148	1152	4509	com/google/android/gms/internal/ads/zzqj
    //   1155	1163	4509	com/google/android/gms/internal/ads/zzqj
    //   1165	1171	4509	com/google/android/gms/internal/ads/zzqj
    //   1176	1198	4509	com/google/android/gms/internal/ads/zzqj
    //   1204	1223	4509	com/google/android/gms/internal/ads/zzqj
    //   1227	1232	4509	com/google/android/gms/internal/ads/zzqj
    //   1232	1234	4509	com/google/android/gms/internal/ads/zzqj
    //   1250	1252	4509	com/google/android/gms/internal/ads/zzqj
    //   1252	1258	4509	com/google/android/gms/internal/ads/zzqj
    //   1261	1272	4509	com/google/android/gms/internal/ads/zzqj
    //   1275	1298	4509	com/google/android/gms/internal/ads/zzqj
    //   1301	1349	4509	com/google/android/gms/internal/ads/zzqj
    //   1354	1401	4509	com/google/android/gms/internal/ads/zzqj
    //   1415	1446	4509	com/google/android/gms/internal/ads/zzqj
    //   1458	1528	4509	com/google/android/gms/internal/ads/zzqj
    //   1541	1548	4509	com/google/android/gms/internal/ads/zzqj
    //   1765	1780	4509	com/google/android/gms/internal/ads/zzqj
    //   1780	1785	4509	com/google/android/gms/internal/ads/zzqj
    //   1878	1893	4509	com/google/android/gms/internal/ads/zzqj
    //   1912	1933	4509	com/google/android/gms/internal/ads/zzqj
    //   1933	1971	4509	com/google/android/gms/internal/ads/zzqj
    //   1974	2011	4509	com/google/android/gms/internal/ads/zzqj
    //   2015	2085	4509	com/google/android/gms/internal/ads/zzqj
    //   2085	2090	4509	com/google/android/gms/internal/ads/zzqj
    //   2090	2109	4509	com/google/android/gms/internal/ads/zzqj
    //   2112	2116	4509	com/google/android/gms/internal/ads/zzqj
    //   2116	2125	4509	com/google/android/gms/internal/ads/zzqj
    //   2133	2148	4509	com/google/android/gms/internal/ads/zzqj
    //   2151	2166	4509	com/google/android/gms/internal/ads/zzqj
    //   2168	2178	4509	com/google/android/gms/internal/ads/zzqj
    //   2189	2209	4509	com/google/android/gms/internal/ads/zzqj
    //   2214	2238	4509	com/google/android/gms/internal/ads/zzqj
    //   2247	2274	4509	com/google/android/gms/internal/ads/zzqj
    //   2274	2325	4509	com/google/android/gms/internal/ads/zzqj
    //   2325	2383	4509	com/google/android/gms/internal/ads/zzqj
    //   2395	2410	4509	com/google/android/gms/internal/ads/zzqj
    //   2418	2424	4509	com/google/android/gms/internal/ads/zzqj
    //   2429	2444	4509	com/google/android/gms/internal/ads/zzqj
    //   2449	2492	4509	com/google/android/gms/internal/ads/zzqj
    //   2497	2507	4509	com/google/android/gms/internal/ads/zzqj
    //   2507	2521	4509	com/google/android/gms/internal/ads/zzqj
    //   2527	2545	4509	com/google/android/gms/internal/ads/zzqj
    //   2547	2555	4509	com/google/android/gms/internal/ads/zzqj
    //   2564	2573	4509	com/google/android/gms/internal/ads/zzqj
    //   2578	2608	4509	com/google/android/gms/internal/ads/zzqj
    //   2626	2636	4509	com/google/android/gms/internal/ads/zzqj
    //   2644	2650	4509	com/google/android/gms/internal/ads/zzqj
    //   2656	2664	4509	com/google/android/gms/internal/ads/zzqj
    //   2668	2686	4509	com/google/android/gms/internal/ads/zzqj
    //   2689	2703	4509	com/google/android/gms/internal/ads/zzqj
    //   2707	2718	4509	com/google/android/gms/internal/ads/zzqj
    //   2732	2766	4509	com/google/android/gms/internal/ads/zzqj
    //   2776	2817	4509	com/google/android/gms/internal/ads/zzqj
    //   2823	2839	4509	com/google/android/gms/internal/ads/zzqj
    //   2861	2865	4509	com/google/android/gms/internal/ads/zzqj
    //   2867	2889	4509	com/google/android/gms/internal/ads/zzqj
    //   2893	2898	4509	com/google/android/gms/internal/ads/zzqj
    //   2902	2921	4509	com/google/android/gms/internal/ads/zzqj
    //   2925	2929	4509	com/google/android/gms/internal/ads/zzqj
    //   2929	2937	4509	com/google/android/gms/internal/ads/zzqj
    //   2942	3017	4509	com/google/android/gms/internal/ads/zzqj
    //   3024	3073	4509	com/google/android/gms/internal/ads/zzqj
    //   3078	3086	4509	com/google/android/gms/internal/ads/zzqj
    //   3099	3108	4509	com/google/android/gms/internal/ads/zzqj
    //   3113	3122	4509	com/google/android/gms/internal/ads/zzqj
    //   3125	3175	4509	com/google/android/gms/internal/ads/zzqj
    //   3182	3191	4509	com/google/android/gms/internal/ads/zzqj
    //   3214	3237	4509	com/google/android/gms/internal/ads/zzqj
    //   3241	3250	4509	com/google/android/gms/internal/ads/zzqj
    //   3257	3274	4509	com/google/android/gms/internal/ads/zzqj
    //   3288	3297	4509	com/google/android/gms/internal/ads/zzqj
    //   3316	3334	4509	com/google/android/gms/internal/ads/zzqj
    //   3373	3379	4509	com/google/android/gms/internal/ads/zzqj
    //   3397	3407	4509	com/google/android/gms/internal/ads/zzqj
    //   3413	3423	4509	com/google/android/gms/internal/ads/zzqj
    //   3428	3436	4509	com/google/android/gms/internal/ads/zzqj
    //   3445	3458	4509	com/google/android/gms/internal/ads/zzqj
    //   3458	3484	4509	com/google/android/gms/internal/ads/zzqj
    //   3484	3504	4509	com/google/android/gms/internal/ads/zzqj
    //   3507	3520	4509	com/google/android/gms/internal/ads/zzqj
    //   3523	3537	4509	com/google/android/gms/internal/ads/zzqj
    //   3545	3592	4509	com/google/android/gms/internal/ads/zzqj
    //   3600	3625	4509	com/google/android/gms/internal/ads/zzqj
    //   3632	3652	4509	com/google/android/gms/internal/ads/zzqj
    //   3667	3714	4509	com/google/android/gms/internal/ads/zzqj
    //   3717	3738	4509	com/google/android/gms/internal/ads/zzqj
    //   3741	3766	4509	com/google/android/gms/internal/ads/zzqj
    //   3774	3802	4509	com/google/android/gms/internal/ads/zzqj
    //   3806	3819	4509	com/google/android/gms/internal/ads/zzqj
    //   3838	3843	4509	com/google/android/gms/internal/ads/zzqj
    //   3846	3853	4509	com/google/android/gms/internal/ads/zzqj
    //   3853	3857	4509	com/google/android/gms/internal/ads/zzqj
    //   3857	3868	4509	com/google/android/gms/internal/ads/zzqj
    //   3870	3878	4509	com/google/android/gms/internal/ads/zzqj
    //   3883	3924	4509	com/google/android/gms/internal/ads/zzqj
    //   3930	3978	4509	com/google/android/gms/internal/ads/zzqj
    //   3981	3996	4509	com/google/android/gms/internal/ads/zzqj
    //   3999	4012	4509	com/google/android/gms/internal/ads/zzqj
    //   4012	4019	4509	com/google/android/gms/internal/ads/zzqj
    //   4019	4037	4509	com/google/android/gms/internal/ads/zzqj
    //   4044	4058	4509	com/google/android/gms/internal/ads/zzqj
    //   4071	4175	4509	com/google/android/gms/internal/ads/zzqj
    //   4178	4183	4509	com/google/android/gms/internal/ads/zzqj
    //   4188	4196	4509	com/google/android/gms/internal/ads/zzqj
    //   4221	4237	4509	com/google/android/gms/internal/ads/zzqj
    //   4240	4249	4509	com/google/android/gms/internal/ads/zzqj
    //   4249	4252	4509	com/google/android/gms/internal/ads/zzqj
    //   4255	4262	4509	com/google/android/gms/internal/ads/zzqj
    //   4271	4283	4509	com/google/android/gms/internal/ads/zzqj
    //   4286	4325	4509	com/google/android/gms/internal/ads/zzqj
    //   4332	4359	4509	com/google/android/gms/internal/ads/zzqj
    //   0	124	4522	com/google/android/gms/internal/ads/zzia
    //   126	135	4522	com/google/android/gms/internal/ads/zzia
    //   138	146	4522	com/google/android/gms/internal/ads/zzia
    //   155	170	4522	com/google/android/gms/internal/ads/zzia
    //   175	196	4522	com/google/android/gms/internal/ads/zzia
    //   199	206	4522	com/google/android/gms/internal/ads/zzia
    //   215	259	4522	com/google/android/gms/internal/ads/zzia
    //   262	274	4522	com/google/android/gms/internal/ads/zzia
    //   277	306	4522	com/google/android/gms/internal/ads/zzia
    //   309	350	4522	com/google/android/gms/internal/ads/zzia
    //   353	413	4522	com/google/android/gms/internal/ads/zzia
    //   416	443	4522	com/google/android/gms/internal/ads/zzia
    //   450	455	4522	com/google/android/gms/internal/ads/zzia
    //   455	475	4522	com/google/android/gms/internal/ads/zzia
    //   478	546	4522	com/google/android/gms/internal/ads/zzia
    //   546	566	4522	com/google/android/gms/internal/ads/zzia
    //   569	581	4522	com/google/android/gms/internal/ads/zzia
    //   584	623	4522	com/google/android/gms/internal/ads/zzia
    //   626	662	4522	com/google/android/gms/internal/ads/zzia
    //   665	696	4522	com/google/android/gms/internal/ads/zzia
    //   706	717	4522	com/google/android/gms/internal/ads/zzia
    //   720	737	4522	com/google/android/gms/internal/ads/zzia
    //   740	747	4522	com/google/android/gms/internal/ads/zzia
    //   756	779	4522	com/google/android/gms/internal/ads/zzia
    //   784	794	4522	com/google/android/gms/internal/ads/zzia
    //   807	836	4522	com/google/android/gms/internal/ads/zzia
    //   846	848	4522	com/google/android/gms/internal/ads/zzia
    //   865	867	4522	com/google/android/gms/internal/ads/zzia
    //   867	874	4522	com/google/android/gms/internal/ads/zzia
    //   883	913	4522	com/google/android/gms/internal/ads/zzia
    //   913	918	4522	com/google/android/gms/internal/ads/zzia
    //   921	954	4522	com/google/android/gms/internal/ads/zzia
    //   954	959	4522	com/google/android/gms/internal/ads/zzia
    //   962	966	4522	com/google/android/gms/internal/ads/zzia
    //   969	1003	4522	com/google/android/gms/internal/ads/zzia
    //   1006	1148	4522	com/google/android/gms/internal/ads/zzia
    //   1148	1152	4522	com/google/android/gms/internal/ads/zzia
    //   1155	1163	4522	com/google/android/gms/internal/ads/zzia
    //   1165	1171	4522	com/google/android/gms/internal/ads/zzia
    //   1176	1198	4522	com/google/android/gms/internal/ads/zzia
    //   1204	1223	4522	com/google/android/gms/internal/ads/zzia
    //   1227	1232	4522	com/google/android/gms/internal/ads/zzia
    //   1232	1234	4522	com/google/android/gms/internal/ads/zzia
    //   1250	1252	4522	com/google/android/gms/internal/ads/zzia
    //   1252	1258	4522	com/google/android/gms/internal/ads/zzia
    //   1261	1272	4522	com/google/android/gms/internal/ads/zzia
    //   1275	1298	4522	com/google/android/gms/internal/ads/zzia
    //   1301	1349	4522	com/google/android/gms/internal/ads/zzia
    //   1354	1401	4522	com/google/android/gms/internal/ads/zzia
    //   1415	1446	4522	com/google/android/gms/internal/ads/zzia
    //   1458	1528	4522	com/google/android/gms/internal/ads/zzia
    //   1541	1548	4522	com/google/android/gms/internal/ads/zzia
    //   1765	1780	4522	com/google/android/gms/internal/ads/zzia
    //   1780	1785	4522	com/google/android/gms/internal/ads/zzia
    //   1878	1893	4522	com/google/android/gms/internal/ads/zzia
    //   1912	1933	4522	com/google/android/gms/internal/ads/zzia
    //   1933	1971	4522	com/google/android/gms/internal/ads/zzia
    //   1974	2011	4522	com/google/android/gms/internal/ads/zzia
    //   2015	2085	4522	com/google/android/gms/internal/ads/zzia
    //   2085	2090	4522	com/google/android/gms/internal/ads/zzia
    //   2090	2109	4522	com/google/android/gms/internal/ads/zzia
    //   2112	2116	4522	com/google/android/gms/internal/ads/zzia
    //   2116	2125	4522	com/google/android/gms/internal/ads/zzia
    //   2133	2148	4522	com/google/android/gms/internal/ads/zzia
    //   2151	2166	4522	com/google/android/gms/internal/ads/zzia
    //   2168	2178	4522	com/google/android/gms/internal/ads/zzia
    //   2189	2209	4522	com/google/android/gms/internal/ads/zzia
    //   2214	2238	4522	com/google/android/gms/internal/ads/zzia
    //   2247	2274	4522	com/google/android/gms/internal/ads/zzia
    //   2274	2325	4522	com/google/android/gms/internal/ads/zzia
    //   2325	2383	4522	com/google/android/gms/internal/ads/zzia
    //   2395	2410	4522	com/google/android/gms/internal/ads/zzia
    //   2418	2424	4522	com/google/android/gms/internal/ads/zzia
    //   2429	2444	4522	com/google/android/gms/internal/ads/zzia
    //   2449	2492	4522	com/google/android/gms/internal/ads/zzia
    //   2497	2507	4522	com/google/android/gms/internal/ads/zzia
    //   2507	2521	4522	com/google/android/gms/internal/ads/zzia
    //   2527	2545	4522	com/google/android/gms/internal/ads/zzia
    //   2547	2555	4522	com/google/android/gms/internal/ads/zzia
    //   2564	2573	4522	com/google/android/gms/internal/ads/zzia
    //   2578	2608	4522	com/google/android/gms/internal/ads/zzia
    //   2626	2636	4522	com/google/android/gms/internal/ads/zzia
    //   2644	2650	4522	com/google/android/gms/internal/ads/zzia
    //   2656	2664	4522	com/google/android/gms/internal/ads/zzia
    //   2668	2686	4522	com/google/android/gms/internal/ads/zzia
    //   2689	2703	4522	com/google/android/gms/internal/ads/zzia
    //   2707	2718	4522	com/google/android/gms/internal/ads/zzia
    //   2732	2766	4522	com/google/android/gms/internal/ads/zzia
    //   2776	2817	4522	com/google/android/gms/internal/ads/zzia
    //   2823	2839	4522	com/google/android/gms/internal/ads/zzia
    //   2861	2865	4522	com/google/android/gms/internal/ads/zzia
    //   2867	2889	4522	com/google/android/gms/internal/ads/zzia
    //   2893	2898	4522	com/google/android/gms/internal/ads/zzia
    //   2902	2921	4522	com/google/android/gms/internal/ads/zzia
    //   2925	2929	4522	com/google/android/gms/internal/ads/zzia
    //   2929	2937	4522	com/google/android/gms/internal/ads/zzia
    //   2942	3017	4522	com/google/android/gms/internal/ads/zzia
    //   3024	3073	4522	com/google/android/gms/internal/ads/zzia
    //   3078	3086	4522	com/google/android/gms/internal/ads/zzia
    //   3099	3108	4522	com/google/android/gms/internal/ads/zzia
    //   3113	3122	4522	com/google/android/gms/internal/ads/zzia
    //   3125	3175	4522	com/google/android/gms/internal/ads/zzia
    //   3182	3191	4522	com/google/android/gms/internal/ads/zzia
    //   3214	3237	4522	com/google/android/gms/internal/ads/zzia
    //   3241	3250	4522	com/google/android/gms/internal/ads/zzia
    //   3257	3274	4522	com/google/android/gms/internal/ads/zzia
    //   3288	3297	4522	com/google/android/gms/internal/ads/zzia
    //   3316	3334	4522	com/google/android/gms/internal/ads/zzia
    //   3373	3379	4522	com/google/android/gms/internal/ads/zzia
    //   3397	3407	4522	com/google/android/gms/internal/ads/zzia
    //   3413	3423	4522	com/google/android/gms/internal/ads/zzia
    //   3428	3436	4522	com/google/android/gms/internal/ads/zzia
    //   3445	3458	4522	com/google/android/gms/internal/ads/zzia
    //   3458	3484	4522	com/google/android/gms/internal/ads/zzia
    //   3484	3504	4522	com/google/android/gms/internal/ads/zzia
    //   3507	3520	4522	com/google/android/gms/internal/ads/zzia
    //   3523	3537	4522	com/google/android/gms/internal/ads/zzia
    //   3545	3592	4522	com/google/android/gms/internal/ads/zzia
    //   3600	3625	4522	com/google/android/gms/internal/ads/zzia
    //   3632	3652	4522	com/google/android/gms/internal/ads/zzia
    //   3667	3714	4522	com/google/android/gms/internal/ads/zzia
    //   3717	3738	4522	com/google/android/gms/internal/ads/zzia
    //   3741	3766	4522	com/google/android/gms/internal/ads/zzia
    //   3774	3802	4522	com/google/android/gms/internal/ads/zzia
    //   3806	3819	4522	com/google/android/gms/internal/ads/zzia
    //   3838	3843	4522	com/google/android/gms/internal/ads/zzia
    //   3846	3853	4522	com/google/android/gms/internal/ads/zzia
    //   3853	3857	4522	com/google/android/gms/internal/ads/zzia
    //   3857	3868	4522	com/google/android/gms/internal/ads/zzia
    //   3870	3878	4522	com/google/android/gms/internal/ads/zzia
    //   3883	3924	4522	com/google/android/gms/internal/ads/zzia
    //   3930	3978	4522	com/google/android/gms/internal/ads/zzia
    //   3981	3996	4522	com/google/android/gms/internal/ads/zzia
    //   3999	4012	4522	com/google/android/gms/internal/ads/zzia
    //   4012	4019	4522	com/google/android/gms/internal/ads/zzia
    //   4019	4037	4522	com/google/android/gms/internal/ads/zzia
    //   4044	4058	4522	com/google/android/gms/internal/ads/zzia
    //   4071	4175	4522	com/google/android/gms/internal/ads/zzia
    //   4178	4183	4522	com/google/android/gms/internal/ads/zzia
    //   4188	4196	4522	com/google/android/gms/internal/ads/zzia
    //   4221	4237	4522	com/google/android/gms/internal/ads/zzia
    //   4240	4249	4522	com/google/android/gms/internal/ads/zzia
    //   4249	4252	4522	com/google/android/gms/internal/ads/zzia
    //   4255	4262	4522	com/google/android/gms/internal/ads/zzia
    //   4271	4283	4522	com/google/android/gms/internal/ads/zzia
    //   4286	4325	4522	com/google/android/gms/internal/ads/zzia
    //   4332	4359	4522	com/google/android/gms/internal/ads/zzia
    //   4637	4670	4819	java/lang/Exception
  }
  
  public final void zza(zzci paramzzci)
  {
    this.zzh.zzc(16, paramzzci).zza();
  }
  
  public final Looper zzb()
  {
    return this.zzj;
  }
  
  public final void zzh()
  {
    this.zzh.zzi(22);
  }
  
  public final void zzi(zztj paramzztj)
  {
    this.zzh.zzc(8, paramzztj).zza();
  }
  
  public final void zzj()
  {
    this.zzh.zzi(10);
  }
  
  public final void zzk()
  {
    this.zzh.zzb(0).zza();
  }
  
  public final void zzl(zzcx paramzzcx, int paramInt, long paramLong)
  {
    this.zzh.zzc(3, new zzkc(paramzzcx, paramInt, paramLong)).zza();
  }
  
  public final void zzm(zzlb paramzzlb)
  {
    try
    {
      if ((!this.zzw) && (this.zzj.getThread().isAlive()))
      {
        this.zzh.zzc(14, paramzzlb).zza();
        return;
      }
      zzer.zze("ExoPlayerImplInternal", "Ignoring messages sent after release.");
      paramzzlb.zzh(false);
      return;
    }
    finally {}
  }
  
  public final void zzn(boolean paramBoolean, int paramInt)
  {
    this.zzh.zzd(1, paramBoolean, paramInt).zza();
  }
  
  public final void zzo()
  {
    this.zzh.zzb(6).zza();
  }
  
  public final boolean zzp()
  {
    try
    {
      if ((!this.zzw) && (this.zzj.getThread().isAlive()))
      {
        this.zzh.zzi(7);
        zzju localzzju = new com/google/android/gms/internal/ads/zzju;
        localzzju.<init>(this);
        zzab(localzzju, this.zzs);
        boolean bool = this.zzw;
        return bool;
      }
      return true;
    }
    finally {}
  }
  
  public final void zzq(List paramList, int paramInt, long paramLong, zzvf paramzzvf)
  {
    this.zzh.zzc(17, new zzjy(paramList, paramzzvf, paramInt, paramLong, null)).zza();
  }
}


/* Location:              C:\Users\Ria\Documents\slope apk\dex-tools-v2.4\classes-dex2jar.jar!\com\google\android\gms\internal\ads\zzkd.class
 * Java compiler version: 6 (50.0)
 * JD-Core Version:       0.7.1
 */