package com.google.android.gms.internal.ads;

public final class zzqx
  implements zzrl
{
  private final zzfpp zzb;
  private final zzfpp zzc;
  
  public zzqx(int paramInt, boolean paramBoolean)
  {
    this.zzb = localzzqv;
    this.zzc = localzzqw;
  }
  
  /* Error */
  public final zzqz zzc(zzrk paramzzrk)
    throws java.io.IOException
  {
    // Byte code:
    //   0: aload_1
    //   1: getfield 53	com/google/android/gms/internal/ads/zzrk:zza	Lcom/google/android/gms/internal/ads/zzrp;
    //   4: getfield 58	com/google/android/gms/internal/ads/zzrp:zza	Ljava/lang/String;
    //   7: astore_3
    //   8: aconst_null
    //   9: astore 4
    //   11: new 60	java/lang/StringBuilder
    //   14: astore 5
    //   16: aload 5
    //   18: invokespecial 61	java/lang/StringBuilder:<init>	()V
    //   21: aload 5
    //   23: ldc 63
    //   25: invokevirtual 67	java/lang/StringBuilder:append	(Ljava/lang/String;)Ljava/lang/StringBuilder;
    //   28: pop
    //   29: aload 5
    //   31: aload_3
    //   32: invokevirtual 67	java/lang/StringBuilder:append	(Ljava/lang/String;)Ljava/lang/StringBuilder;
    //   35: pop
    //   36: aload 5
    //   38: invokevirtual 71	java/lang/StringBuilder:toString	()Ljava/lang/String;
    //   41: astore 5
    //   43: getstatic 76	com/google/android/gms/internal/ads/zzfn:zza	I
    //   46: istore_2
    //   47: aload 5
    //   49: invokestatic 81	android/os/Trace:beginSection	(Ljava/lang/String;)V
    //   52: aload_3
    //   53: invokestatic 87	android/media/MediaCodec:createByCodecName	(Ljava/lang/String;)Landroid/media/MediaCodec;
    //   56: astore_3
    //   57: new 33	com/google/android/gms/internal/ads/zzqz
    //   60: astore 5
    //   62: aload 5
    //   64: aload_3
    //   65: aload_0
    //   66: getfield 24	com/google/android/gms/internal/ads/zzqx:zzb	Lcom/google/android/gms/internal/ads/zzfpp;
    //   69: checkcast 13	com/google/android/gms/internal/ads/zzqv
    //   72: getfield 88	com/google/android/gms/internal/ads/zzqv:zza	I
    //   75: invokestatic 90	com/google/android/gms/internal/ads/zzqx:zza	(I)Landroid/os/HandlerThread;
    //   78: aload_0
    //   79: getfield 26	com/google/android/gms/internal/ads/zzqx:zzc	Lcom/google/android/gms/internal/ads/zzfpp;
    //   82: checkcast 18	com/google/android/gms/internal/ads/zzqw
    //   85: getfield 91	com/google/android/gms/internal/ads/zzqw:zza	I
    //   88: invokestatic 93	com/google/android/gms/internal/ads/zzqx:zzb	(I)Landroid/os/HandlerThread;
    //   91: iconst_0
    //   92: aconst_null
    //   93: invokespecial 96	com/google/android/gms/internal/ads/zzqz:<init>	(Landroid/media/MediaCodec;Landroid/os/HandlerThread;Landroid/os/HandlerThread;ZLcom/google/android/gms/internal/ads/zzqy;)V
    //   96: invokestatic 99	android/os/Trace:endSection	()V
    //   99: aload 5
    //   101: aload_1
    //   102: getfield 102	com/google/android/gms/internal/ads/zzrk:zzb	Landroid/media/MediaFormat;
    //   105: aload_1
    //   106: getfield 105	com/google/android/gms/internal/ads/zzrk:zzd	Landroid/view/Surface;
    //   109: aconst_null
    //   110: iconst_0
    //   111: invokestatic 109	com/google/android/gms/internal/ads/zzqz:zzh	(Lcom/google/android/gms/internal/ads/zzqz;Landroid/media/MediaFormat;Landroid/view/Surface;Landroid/media/MediaCrypto;I)V
    //   114: aload 5
    //   116: areturn
    //   117: astore_1
    //   118: aload 5
    //   120: astore 4
    //   122: goto +10 -> 132
    //   125: astore_1
    //   126: goto +6 -> 132
    //   129: astore_1
    //   130: aconst_null
    //   131: astore_3
    //   132: aload 4
    //   134: ifnonnull +14 -> 148
    //   137: aload_3
    //   138: ifnull +15 -> 153
    //   141: aload_3
    //   142: invokevirtual 112	android/media/MediaCodec:release	()V
    //   145: goto +8 -> 153
    //   148: aload 4
    //   150: invokevirtual 115	com/google/android/gms/internal/ads/zzqz:zzl	()V
    //   153: aload_1
    //   154: athrow
    // Local variable table:
    //   start	length	slot	name	signature
    //   0	155	0	this	zzqx
    //   0	155	1	paramzzrk	zzrk
    //   46	1	2	i	int
    //   7	135	3	localObject1	Object
    //   9	140	4	localObject2	Object
    //   14	105	5	localObject3	Object
    // Exception table:
    //   from	to	target	type
    //   96	114	117	java/lang/Exception
    //   57	96	125	java/lang/Exception
    //   11	57	129	java/lang/Exception
  }
}


/* Location:              C:\Users\Ria\Documents\slope apk\dex-tools-v2.4\classes-dex2jar.jar!\com\google\android\gms\internal\ads\zzqx.class
 * Java compiler version: 6 (50.0)
 * JD-Core Version:       0.7.1
 */