package com.google.android.gms.internal.ads;

import android.net.Uri;
import java.util.Objects;

final class zzuj
  implements zzxv, zzta
{
  final zzuo zza;
  private final long zzb;
  private final Uri zzc;
  private final zzgy zzd;
  private final zzue zze;
  private final zzaar zzf;
  private final zzeb zzg;
  private final zzabk zzh;
  private volatile boolean zzi;
  private boolean zzj;
  private long zzk;
  private zzgc zzl;
  private zzabr zzm;
  private boolean zzn;
  
  public zzuj(zzuo paramzzuo, Uri paramUri, zzfx paramzzfx, zzue paramzzue, zzaar paramzzaar, zzeb paramzzeb)
  {
    this.zzc = paramUri;
    this.zzd = new zzgy(paramzzfx);
    this.zze = paramzzue;
    this.zzf = paramzzaar;
    this.zzg = paramzzeb;
    this.zzh = new zzabk();
    this.zzj = true;
    this.zzb = zztc.zza();
    this.zzl = zzi(0L);
  }
  
  private final zzgc zzi(long paramLong)
  {
    zzga localzzga = new zzga();
    localzzga.zzd(this.zzc);
    localzzga.zzc(paramLong);
    localzzga.zza(6);
    localzzga.zzb(zzuo.zzy());
    return localzzga.zze();
  }
  
  public final void zza(zzfd paramzzfd)
  {
    long l;
    if (!this.zzn) {
      l = this.zzk;
    } else {
      l = Math.max(zzuo.zzq(this.zza, true), this.zzk);
    }
    int i = paramzzfd.zza();
    zzabr localzzabr = this.zzm;
    Objects.requireNonNull(localzzabr);
    zzabp.zzb(localzzabr, paramzzfd, i);
    localzzabr.zzs(l, 1, i, 0, null);
    this.zzn = true;
  }
  
  public final void zzg()
  {
    this.zzi = true;
  }
  
  /* Error */
  public final void zzh()
    throws java.io.IOException
  {
    // Byte code:
    //   0: aload_0
    //   1: getfield 146	com/google/android/gms/internal/ads/zzuj:zzi	Z
    //   4: ifne +949 -> 953
    //   7: aload_0
    //   8: getfield 60	com/google/android/gms/internal/ads/zzuj:zzh	Lcom/google/android/gms/internal/ads/zzabk;
    //   11: getfield 83	com/google/android/gms/internal/ads/zzabk:zza	J
    //   14: lstore 6
    //   16: aload_0
    //   17: lload 6
    //   19: invokespecial 72	com/google/android/gms/internal/ads/zzuj:zzi	(J)Lcom/google/android/gms/internal/ads/zzgc;
    //   22: astore 11
    //   24: aload_0
    //   25: aload 11
    //   27: putfield 74	com/google/android/gms/internal/ads/zzuj:zzl	Lcom/google/android/gms/internal/ads/zzgc;
    //   30: aload_0
    //   31: getfield 49	com/google/android/gms/internal/ads/zzuj:zzd	Lcom/google/android/gms/internal/ads/zzgy;
    //   34: aload 11
    //   36: invokevirtual 155	com/google/android/gms/internal/ads/zzgy:zzb	(Lcom/google/android/gms/internal/ads/zzgc;)J
    //   39: lstore 8
    //   41: lload 8
    //   43: lstore 4
    //   45: lload 8
    //   47: ldc2_w 156
    //   50: lcmp
    //   51: ifeq +17 -> 68
    //   54: lload 8
    //   56: lload 6
    //   58: ladd
    //   59: lstore 4
    //   61: aload_0
    //   62: getfield 37	com/google/android/gms/internal/ads/zzuj:zza	Lcom/google/android/gms/internal/ads/zzuo;
    //   65: invokestatic 161	com/google/android/gms/internal/ads/zzuo:zzB	(Lcom/google/android/gms/internal/ads/zzuo;)V
    //   68: aload_0
    //   69: getfield 37	com/google/android/gms/internal/ads/zzuj:zza	Lcom/google/android/gms/internal/ads/zzuo;
    //   72: astore 15
    //   74: aload_0
    //   75: getfield 49	com/google/android/gms/internal/ads/zzuj:zzd	Lcom/google/android/gms/internal/ads/zzgy;
    //   78: invokevirtual 163	com/google/android/gms/internal/ads/zzgy:zze	()Ljava/util/Map;
    //   81: astore 16
    //   83: aload 16
    //   85: ldc -91
    //   87: invokeinterface 170 2 0
    //   92: checkcast 172	java/util/List
    //   95: astore 11
    //   97: aload 11
    //   99: ifnull +104 -> 203
    //   102: aload 11
    //   104: iconst_0
    //   105: invokeinterface 175 2 0
    //   110: checkcast 177	java/lang/String
    //   113: astore 11
    //   115: aload 11
    //   117: invokestatic 183	java/lang/Integer:parseInt	(Ljava/lang/String;)I
    //   120: istore_1
    //   121: iload_1
    //   122: sipush 1000
    //   125: imul
    //   126: istore_1
    //   127: iload_1
    //   128: ifle +10 -> 138
    //   131: iload_1
    //   132: istore_2
    //   133: iconst_1
    //   134: istore_1
    //   135: goto +72 -> 207
    //   138: new 185	java/lang/StringBuilder
    //   141: astore 12
    //   143: aload 12
    //   145: invokespecial 186	java/lang/StringBuilder:<init>	()V
    //   148: aload 12
    //   150: ldc -68
    //   152: invokevirtual 192	java/lang/StringBuilder:append	(Ljava/lang/String;)Ljava/lang/StringBuilder;
    //   155: pop
    //   156: aload 12
    //   158: aload 11
    //   160: invokevirtual 192	java/lang/StringBuilder:append	(Ljava/lang/String;)Ljava/lang/StringBuilder;
    //   163: pop
    //   164: ldc -62
    //   166: aload 12
    //   168: invokevirtual 198	java/lang/StringBuilder:toString	()Ljava/lang/String;
    //   171: invokestatic 203	com/google/android/gms/internal/ads/zzer:zze	(Ljava/lang/String;Ljava/lang/String;)V
    //   174: goto +29 -> 203
    //   177: astore 12
    //   179: iconst_m1
    //   180: istore_1
    //   181: ldc -62
    //   183: ldc -51
    //   185: aload 11
    //   187: invokestatic 209	java/lang/String:valueOf	(Ljava/lang/Object;)Ljava/lang/String;
    //   190: invokevirtual 213	java/lang/String:concat	(Ljava/lang/String;)Ljava/lang/String;
    //   193: invokestatic 203	com/google/android/gms/internal/ads/zzer:zze	(Ljava/lang/String;Ljava/lang/String;)V
    //   196: iload_1
    //   197: istore_2
    //   198: iconst_0
    //   199: istore_1
    //   200: goto +7 -> 207
    //   203: iconst_0
    //   204: istore_1
    //   205: iconst_m1
    //   206: istore_2
    //   207: aload 16
    //   209: ldc -41
    //   211: invokeinterface 170 2 0
    //   216: checkcast 172	java/util/List
    //   219: astore 11
    //   221: aconst_null
    //   222: astore 14
    //   224: aload 11
    //   226: ifnull +21 -> 247
    //   229: aload 11
    //   231: iconst_0
    //   232: invokeinterface 175 2 0
    //   237: checkcast 177	java/lang/String
    //   240: astore 11
    //   242: iconst_1
    //   243: istore_1
    //   244: goto +6 -> 250
    //   247: aconst_null
    //   248: astore 11
    //   250: aload 16
    //   252: ldc -39
    //   254: invokeinterface 170 2 0
    //   259: checkcast 172	java/util/List
    //   262: astore 12
    //   264: aload 12
    //   266: ifnull +21 -> 287
    //   269: aload 12
    //   271: iconst_0
    //   272: invokeinterface 175 2 0
    //   277: checkcast 177	java/lang/String
    //   280: astore 12
    //   282: iconst_1
    //   283: istore_1
    //   284: goto +6 -> 290
    //   287: aconst_null
    //   288: astore 12
    //   290: aload 16
    //   292: ldc -37
    //   294: invokeinterface 170 2 0
    //   299: checkcast 172	java/util/List
    //   302: astore 13
    //   304: aload 13
    //   306: ifnull +21 -> 327
    //   309: aload 13
    //   311: iconst_0
    //   312: invokeinterface 175 2 0
    //   317: checkcast 177	java/lang/String
    //   320: astore 13
    //   322: iconst_1
    //   323: istore_1
    //   324: goto +6 -> 330
    //   327: aconst_null
    //   328: astore 13
    //   330: aload 16
    //   332: ldc -35
    //   334: invokeinterface 170 2 0
    //   339: checkcast 172	java/util/List
    //   342: astore 17
    //   344: aload 17
    //   346: ifnull +26 -> 372
    //   349: aload 17
    //   351: iconst_0
    //   352: invokeinterface 175 2 0
    //   357: checkcast 177	java/lang/String
    //   360: ldc -33
    //   362: invokevirtual 227	java/lang/String:equals	(Ljava/lang/Object;)Z
    //   365: istore 10
    //   367: iconst_1
    //   368: istore_1
    //   369: goto +6 -> 375
    //   372: iconst_0
    //   373: istore 10
    //   375: aload 16
    //   377: ldc -27
    //   379: invokeinterface 170 2 0
    //   384: checkcast 172	java/util/List
    //   387: astore 16
    //   389: aload 16
    //   391: ifnull +92 -> 483
    //   394: aload 16
    //   396: iconst_0
    //   397: invokeinterface 175 2 0
    //   402: checkcast 177	java/lang/String
    //   405: astore 16
    //   407: aload 16
    //   409: invokestatic 183	java/lang/Integer:parseInt	(Ljava/lang/String;)I
    //   412: istore_3
    //   413: iload_3
    //   414: ifle +8 -> 422
    //   417: iconst_1
    //   418: istore_1
    //   419: goto +66 -> 485
    //   422: new 185	java/lang/StringBuilder
    //   425: astore 17
    //   427: aload 17
    //   429: invokespecial 186	java/lang/StringBuilder:<init>	()V
    //   432: aload 17
    //   434: ldc -25
    //   436: invokevirtual 192	java/lang/StringBuilder:append	(Ljava/lang/String;)Ljava/lang/StringBuilder;
    //   439: pop
    //   440: aload 17
    //   442: aload 16
    //   444: invokevirtual 192	java/lang/StringBuilder:append	(Ljava/lang/String;)Ljava/lang/StringBuilder;
    //   447: pop
    //   448: ldc -62
    //   450: aload 17
    //   452: invokevirtual 198	java/lang/StringBuilder:toString	()Ljava/lang/String;
    //   455: invokestatic 203	com/google/android/gms/internal/ads/zzer:zze	(Ljava/lang/String;Ljava/lang/String;)V
    //   458: goto +25 -> 483
    //   461: astore 17
    //   463: iconst_m1
    //   464: istore_3
    //   465: ldc -62
    //   467: ldc -25
    //   469: aload 16
    //   471: invokestatic 209	java/lang/String:valueOf	(Ljava/lang/Object;)Ljava/lang/String;
    //   474: invokevirtual 213	java/lang/String:concat	(Ljava/lang/String;)Ljava/lang/String;
    //   477: invokestatic 203	com/google/android/gms/internal/ads/zzer:zze	(Ljava/lang/String;Ljava/lang/String;)V
    //   480: goto +5 -> 485
    //   483: iconst_m1
    //   484: istore_3
    //   485: iload_1
    //   486: ifeq +23 -> 509
    //   489: new 233	com/google/android/gms/internal/ads/zzado
    //   492: astore 14
    //   494: aload 14
    //   496: iload_2
    //   497: aload 11
    //   499: aload 12
    //   501: aload 13
    //   503: iload 10
    //   505: iload_3
    //   506: invokespecial 236	com/google/android/gms/internal/ads/zzado:<init>	(ILjava/lang/String;Ljava/lang/String;Ljava/lang/String;ZI)V
    //   509: aload 15
    //   511: aload 14
    //   513: invokestatic 240	com/google/android/gms/internal/ads/zzuo:zzA	(Lcom/google/android/gms/internal/ads/zzuo;Lcom/google/android/gms/internal/ads/zzado;)V
    //   516: aload_0
    //   517: getfield 49	com/google/android/gms/internal/ads/zzuj:zzd	Lcom/google/android/gms/internal/ads/zzgy;
    //   520: astore 12
    //   522: aload_0
    //   523: getfield 37	com/google/android/gms/internal/ads/zzuj:zza	Lcom/google/android/gms/internal/ads/zzuo;
    //   526: astore 13
    //   528: aload 13
    //   530: invokestatic 244	com/google/android/gms/internal/ads/zzuo:zzw	(Lcom/google/android/gms/internal/ads/zzuo;)Lcom/google/android/gms/internal/ads/zzado;
    //   533: ifnull +64 -> 597
    //   536: aload 13
    //   538: invokestatic 244	com/google/android/gms/internal/ads/zzuo:zzw	(Lcom/google/android/gms/internal/ads/zzuo;)Lcom/google/android/gms/internal/ads/zzado;
    //   541: getfield 247	com/google/android/gms/internal/ads/zzado:zzf	I
    //   544: iconst_m1
    //   545: if_icmpeq +52 -> 597
    //   548: new 249	com/google/android/gms/internal/ads/zztb
    //   551: astore 11
    //   553: aload 11
    //   555: aload 12
    //   557: aload 13
    //   559: invokestatic 244	com/google/android/gms/internal/ads/zzuo:zzw	(Lcom/google/android/gms/internal/ads/zzuo;)Lcom/google/android/gms/internal/ads/zzado;
    //   562: getfield 247	com/google/android/gms/internal/ads/zzado:zzf	I
    //   565: aload_0
    //   566: invokespecial 252	com/google/android/gms/internal/ads/zztb:<init>	(Lcom/google/android/gms/internal/ads/zzfx;ILcom/google/android/gms/internal/ads/zzta;)V
    //   569: aload_0
    //   570: getfield 37	com/google/android/gms/internal/ads/zzuj:zza	Lcom/google/android/gms/internal/ads/zzuo;
    //   573: invokevirtual 256	com/google/android/gms/internal/ads/zzuo:zzu	()Lcom/google/android/gms/internal/ads/zzabr;
    //   576: astore 12
    //   578: aload_0
    //   579: aload 12
    //   581: putfield 127	com/google/android/gms/internal/ads/zzuj:zzm	Lcom/google/android/gms/internal/ads/zzabr;
    //   584: aload 12
    //   586: invokestatic 259	com/google/android/gms/internal/ads/zzuo:zzs	()Lcom/google/android/gms/internal/ads/zzam;
    //   589: invokeinterface 262 2 0
    //   594: goto +7 -> 601
    //   597: aload 12
    //   599: astore 11
    //   601: aload_0
    //   602: getfield 51	com/google/android/gms/internal/ads/zzuj:zze	Lcom/google/android/gms/internal/ads/zzue;
    //   605: aload 11
    //   607: aload_0
    //   608: getfield 42	com/google/android/gms/internal/ads/zzuj:zzc	Landroid/net/Uri;
    //   611: aload_0
    //   612: getfield 49	com/google/android/gms/internal/ads/zzuj:zzd	Lcom/google/android/gms/internal/ads/zzgy;
    //   615: invokevirtual 163	com/google/android/gms/internal/ads/zzgy:zze	()Ljava/util/Map;
    //   618: lload 6
    //   620: lload 4
    //   622: aload_0
    //   623: getfield 53	com/google/android/gms/internal/ads/zzuj:zzf	Lcom/google/android/gms/internal/ads/zzaar;
    //   626: invokeinterface 267 9 0
    //   631: aload_0
    //   632: getfield 37	com/google/android/gms/internal/ads/zzuj:zza	Lcom/google/android/gms/internal/ads/zzuo;
    //   635: invokestatic 244	com/google/android/gms/internal/ads/zzuo:zzw	(Lcom/google/android/gms/internal/ads/zzuo;)Lcom/google/android/gms/internal/ads/zzado;
    //   638: ifnull +12 -> 650
    //   641: aload_0
    //   642: getfield 51	com/google/android/gms/internal/ads/zzuj:zze	Lcom/google/android/gms/internal/ads/zzue;
    //   645: invokeinterface 269 1 0
    //   650: aload_0
    //   651: getfield 62	com/google/android/gms/internal/ads/zzuj:zzj	Z
    //   654: ifeq +31 -> 685
    //   657: aload_0
    //   658: getfield 51	com/google/android/gms/internal/ads/zzuj:zze	Lcom/google/android/gms/internal/ads/zzue;
    //   661: lload 6
    //   663: aload_0
    //   664: getfield 78	com/google/android/gms/internal/ads/zzuj:zzk	J
    //   667: invokeinterface 272 5 0
    //   672: aload_0
    //   673: iconst_0
    //   674: putfield 62	com/google/android/gms/internal/ads/zzuj:zzj	Z
    //   677: goto +8 -> 685
    //   680: astore 11
    //   682: goto +220 -> 902
    //   685: lload 6
    //   687: lstore 4
    //   689: iconst_0
    //   690: istore_1
    //   691: iload_1
    //   692: ifne +150 -> 842
    //   695: iload_1
    //   696: istore_2
    //   697: aload_0
    //   698: getfield 146	com/google/android/gms/internal/ads/zzuj:zzi	Z
    //   701: istore 10
    //   703: iload 10
    //   705: ifne +125 -> 830
    //   708: iload_1
    //   709: istore_2
    //   710: aload_0
    //   711: getfield 55	com/google/android/gms/internal/ads/zzuj:zzg	Lcom/google/android/gms/internal/ads/zzeb;
    //   714: invokevirtual 276	com/google/android/gms/internal/ads/zzeb:zza	()V
    //   717: iload_1
    //   718: istore_2
    //   719: aload_0
    //   720: getfield 51	com/google/android/gms/internal/ads/zzuj:zze	Lcom/google/android/gms/internal/ads/zzue;
    //   723: aload_0
    //   724: getfield 60	com/google/android/gms/internal/ads/zzuj:zzh	Lcom/google/android/gms/internal/ads/zzabk;
    //   727: invokeinterface 279 2 0
    //   732: istore_3
    //   733: iload_3
    //   734: istore_2
    //   735: aload_0
    //   736: getfield 51	com/google/android/gms/internal/ads/zzuj:zze	Lcom/google/android/gms/internal/ads/zzue;
    //   739: invokeinterface 281 1 0
    //   744: lstore 6
    //   746: iload_3
    //   747: istore_1
    //   748: iload_3
    //   749: istore_2
    //   750: lload 6
    //   752: aload_0
    //   753: getfield 37	com/google/android/gms/internal/ads/zzuj:zza	Lcom/google/android/gms/internal/ads/zzuo;
    //   756: invokestatic 284	com/google/android/gms/internal/ads/zzuo:zzn	(Lcom/google/android/gms/internal/ads/zzuo;)J
    //   759: lload 4
    //   761: ladd
    //   762: lcmp
    //   763: ifle -72 -> 691
    //   766: iload_3
    //   767: istore_2
    //   768: aload_0
    //   769: getfield 55	com/google/android/gms/internal/ads/zzuj:zzg	Lcom/google/android/gms/internal/ads/zzeb;
    //   772: invokevirtual 287	com/google/android/gms/internal/ads/zzeb:zzc	()Z
    //   775: pop
    //   776: iload_3
    //   777: istore_2
    //   778: aload_0
    //   779: getfield 37	com/google/android/gms/internal/ads/zzuj:zza	Lcom/google/android/gms/internal/ads/zzuo;
    //   782: astore 11
    //   784: iload_3
    //   785: istore_2
    //   786: aload 11
    //   788: invokestatic 291	com/google/android/gms/internal/ads/zzuo:zzr	(Lcom/google/android/gms/internal/ads/zzuo;)Landroid/os/Handler;
    //   791: aload 11
    //   793: invokestatic 295	com/google/android/gms/internal/ads/zzuo:zzx	(Lcom/google/android/gms/internal/ads/zzuo;)Ljava/lang/Runnable;
    //   796: invokevirtual 301	android/os/Handler:post	(Ljava/lang/Runnable;)Z
    //   799: pop
    //   800: lload 6
    //   802: lstore 4
    //   804: iload_3
    //   805: istore_1
    //   806: goto -115 -> 691
    //   809: astore 11
    //   811: iload_1
    //   812: istore_2
    //   813: new 303	java/io/InterruptedIOException
    //   816: astore 11
    //   818: iload_1
    //   819: istore_2
    //   820: aload 11
    //   822: invokespecial 304	java/io/InterruptedIOException:<init>	()V
    //   825: iload_1
    //   826: istore_2
    //   827: aload 11
    //   829: athrow
    //   830: iconst_0
    //   831: istore_1
    //   832: goto +10 -> 842
    //   835: astore 11
    //   837: iload_2
    //   838: istore_1
    //   839: goto +65 -> 904
    //   842: iload_1
    //   843: iconst_1
    //   844: if_icmpne +8 -> 852
    //   847: iconst_0
    //   848: istore_1
    //   849: goto +37 -> 886
    //   852: aload_0
    //   853: getfield 51	com/google/android/gms/internal/ads/zzuj:zze	Lcom/google/android/gms/internal/ads/zzue;
    //   856: astore 11
    //   858: aload 11
    //   860: invokeinterface 281 1 0
    //   865: ldc2_w 156
    //   868: lcmp
    //   869: ifeq +17 -> 886
    //   872: aload_0
    //   873: getfield 60	com/google/android/gms/internal/ads/zzuj:zzh	Lcom/google/android/gms/internal/ads/zzabk;
    //   876: aload 11
    //   878: invokeinterface 281 1 0
    //   883: putfield 83	com/google/android/gms/internal/ads/zzabk:zza	J
    //   886: aload_0
    //   887: getfield 49	com/google/android/gms/internal/ads/zzuj:zzd	Lcom/google/android/gms/internal/ads/zzgy;
    //   890: invokestatic 308	com/google/android/gms/internal/ads/zzfz:zza	(Lcom/google/android/gms/internal/ads/zzfx;)V
    //   893: iload_1
    //   894: ifeq -894 -> 0
    //   897: goto +56 -> 953
    //   900: astore 11
    //   902: iconst_0
    //   903: istore_1
    //   904: iload_1
    //   905: iconst_1
    //   906: if_icmpeq +37 -> 943
    //   909: aload_0
    //   910: getfield 51	com/google/android/gms/internal/ads/zzuj:zze	Lcom/google/android/gms/internal/ads/zzue;
    //   913: astore 12
    //   915: aload 12
    //   917: invokeinterface 281 1 0
    //   922: ldc2_w 156
    //   925: lcmp
    //   926: ifeq +17 -> 943
    //   929: aload_0
    //   930: getfield 60	com/google/android/gms/internal/ads/zzuj:zzh	Lcom/google/android/gms/internal/ads/zzabk;
    //   933: aload 12
    //   935: invokeinterface 281 1 0
    //   940: putfield 83	com/google/android/gms/internal/ads/zzabk:zza	J
    //   943: aload_0
    //   944: getfield 49	com/google/android/gms/internal/ads/zzuj:zzd	Lcom/google/android/gms/internal/ads/zzgy;
    //   947: invokestatic 308	com/google/android/gms/internal/ads/zzfz:zza	(Lcom/google/android/gms/internal/ads/zzfx;)V
    //   950: aload 11
    //   952: athrow
    //   953: return
    //   954: astore 12
    //   956: goto -775 -> 181
    //   959: astore 17
    //   961: goto -496 -> 465
    // Local variable table:
    //   start	length	slot	name	signature
    //   0	964	0	this	zzuj
    //   120	787	1	i	int
    //   132	706	2	j	int
    //   412	393	3	k	int
    //   43	760	4	l1	long
    //   14	787	6	l2	long
    //   39	16	8	l3	long
    //   365	339	10	bool	boolean
    //   22	584	11	localObject1	Object
    //   680	1	11	localObject2	Object
    //   782	10	11	localzzuo1	zzuo
    //   809	1	11	localInterruptedException	InterruptedException
    //   816	12	11	localInterruptedIOException	java.io.InterruptedIOException
    //   835	1	11	localObject3	Object
    //   856	21	11	localzzue	zzue
    //   900	51	11	localObject4	Object
    //   141	26	12	localStringBuilder	StringBuilder
    //   177	1	12	localNumberFormatException1	NumberFormatException
    //   262	672	12	localObject5	Object
    //   954	1	12	localNumberFormatException2	NumberFormatException
    //   302	256	13	localObject6	Object
    //   222	290	14	localzzado	zzado
    //   72	438	15	localzzuo2	zzuo
    //   81	389	16	localObject7	Object
    //   342	109	17	localObject8	Object
    //   461	1	17	localNumberFormatException3	NumberFormatException
    //   959	1	17	localNumberFormatException4	NumberFormatException
    // Exception table:
    //   from	to	target	type
    //   115	121	177	java/lang/NumberFormatException
    //   407	413	461	java/lang/NumberFormatException
    //   672	677	680	finally
    //   710	717	809	java/lang/InterruptedException
    //   697	703	835	finally
    //   710	717	835	finally
    //   719	733	835	finally
    //   735	746	835	finally
    //   750	766	835	finally
    //   768	776	835	finally
    //   778	784	835	finally
    //   786	800	835	finally
    //   813	818	835	finally
    //   820	825	835	finally
    //   827	830	835	finally
    //   7	41	900	finally
    //   61	68	900	finally
    //   68	97	900	finally
    //   102	115	900	finally
    //   115	121	900	finally
    //   138	174	900	finally
    //   181	196	900	finally
    //   207	221	900	finally
    //   229	242	900	finally
    //   250	264	900	finally
    //   269	282	900	finally
    //   290	304	900	finally
    //   309	322	900	finally
    //   330	344	900	finally
    //   349	367	900	finally
    //   375	389	900	finally
    //   394	407	900	finally
    //   407	413	900	finally
    //   422	458	900	finally
    //   465	480	900	finally
    //   489	509	900	finally
    //   509	594	900	finally
    //   601	650	900	finally
    //   650	672	900	finally
    //   138	174	954	java/lang/NumberFormatException
    //   422	458	959	java/lang/NumberFormatException
  }
}


/* Location:              C:\Users\Ria\Documents\slope apk\dex-tools-v2.4\classes-dex2jar.jar!\com\google\android\gms\internal\ads\zzuj.class
 * Java compiler version: 6 (50.0)
 * JD-Core Version:       0.7.1
 */