package com.google.android.gms.ads.identifier;

public final class zzc
{
  /* Error */
  public static final void zza(String paramString)
  {
    // Byte code:
    //   0: sipush 263
    //   3: invokestatic 18	com/google/android/gms/internal/ads_identifier/zzi:zzb	(I)V
    //   6: new 20	java/net/URL
    //   9: astore_3
    //   10: aload_3
    //   11: aload_0
    //   12: invokespecial 23	java/net/URL:<init>	(Ljava/lang/String;)V
    //   15: aload_3
    //   16: invokevirtual 27	java/net/URL:openConnection	()Ljava/net/URLConnection;
    //   19: checkcast 29	java/net/HttpURLConnection
    //   22: astore_3
    //   23: aload_3
    //   24: invokevirtual 33	java/net/HttpURLConnection:getResponseCode	()I
    //   27: istore_1
    //   28: iload_1
    //   29: sipush 200
    //   32: if_icmplt +10 -> 42
    //   35: iload_1
    //   36: sipush 300
    //   39: if_icmplt +66 -> 105
    //   42: aload_0
    //   43: invokestatic 39	java/lang/String:valueOf	(Ljava/lang/Object;)Ljava/lang/String;
    //   46: invokevirtual 42	java/lang/String:length	()I
    //   49: istore_2
    //   50: new 44	java/lang/StringBuilder
    //   53: astore 4
    //   55: aload 4
    //   57: iload_2
    //   58: bipush 65
    //   60: iadd
    //   61: invokespecial 46	java/lang/StringBuilder:<init>	(I)V
    //   64: aload 4
    //   66: ldc 48
    //   68: invokevirtual 52	java/lang/StringBuilder:append	(Ljava/lang/String;)Ljava/lang/StringBuilder;
    //   71: pop
    //   72: aload 4
    //   74: iload_1
    //   75: invokevirtual 55	java/lang/StringBuilder:append	(I)Ljava/lang/StringBuilder;
    //   78: pop
    //   79: aload 4
    //   81: ldc 57
    //   83: invokevirtual 52	java/lang/StringBuilder:append	(Ljava/lang/String;)Ljava/lang/StringBuilder;
    //   86: pop
    //   87: aload 4
    //   89: aload_0
    //   90: invokevirtual 52	java/lang/StringBuilder:append	(Ljava/lang/String;)Ljava/lang/StringBuilder;
    //   93: pop
    //   94: ldc 59
    //   96: aload 4
    //   98: invokevirtual 63	java/lang/StringBuilder:toString	()Ljava/lang/String;
    //   101: invokestatic 69	android/util/Log:w	(Ljava/lang/String;Ljava/lang/String;)I
    //   104: pop
    //   105: aload_3
    //   106: invokevirtual 73	java/net/HttpURLConnection:disconnect	()V
    //   109: invokestatic 75	com/google/android/gms/internal/ads_identifier/zzi:zza	()V
    //   112: return
    //   113: astore 4
    //   115: aload_3
    //   116: invokevirtual 73	java/net/HttpURLConnection:disconnect	()V
    //   119: aload 4
    //   121: athrow
    //   122: astore_0
    //   123: goto +181 -> 304
    //   126: astore_3
    //   127: goto +4 -> 131
    //   130: astore_3
    //   131: aload_3
    //   132: invokevirtual 80	java/lang/Exception:getMessage	()Ljava/lang/String;
    //   135: astore 4
    //   137: aload_0
    //   138: invokestatic 39	java/lang/String:valueOf	(Ljava/lang/Object;)Ljava/lang/String;
    //   141: invokevirtual 42	java/lang/String:length	()I
    //   144: istore_1
    //   145: aload 4
    //   147: invokestatic 39	java/lang/String:valueOf	(Ljava/lang/Object;)Ljava/lang/String;
    //   150: invokevirtual 42	java/lang/String:length	()I
    //   153: istore_2
    //   154: new 44	java/lang/StringBuilder
    //   157: astore 5
    //   159: aload 5
    //   161: iload_1
    //   162: bipush 27
    //   164: iadd
    //   165: iload_2
    //   166: iadd
    //   167: invokespecial 46	java/lang/StringBuilder:<init>	(I)V
    //   170: aload 5
    //   172: ldc 82
    //   174: invokevirtual 52	java/lang/StringBuilder:append	(Ljava/lang/String;)Ljava/lang/StringBuilder;
    //   177: pop
    //   178: aload 5
    //   180: aload_0
    //   181: invokevirtual 52	java/lang/StringBuilder:append	(Ljava/lang/String;)Ljava/lang/StringBuilder;
    //   184: pop
    //   185: aload 5
    //   187: ldc 84
    //   189: invokevirtual 52	java/lang/StringBuilder:append	(Ljava/lang/String;)Ljava/lang/StringBuilder;
    //   192: pop
    //   193: aload 5
    //   195: aload 4
    //   197: invokevirtual 52	java/lang/StringBuilder:append	(Ljava/lang/String;)Ljava/lang/StringBuilder;
    //   200: pop
    //   201: ldc 59
    //   203: aload 5
    //   205: invokevirtual 63	java/lang/StringBuilder:toString	()Ljava/lang/String;
    //   208: aload_3
    //   209: invokestatic 87	android/util/Log:w	(Ljava/lang/String;Ljava/lang/String;Ljava/lang/Throwable;)I
    //   212: pop
    //   213: invokestatic 75	com/google/android/gms/internal/ads_identifier/zzi:zza	()V
    //   216: return
    //   217: astore_3
    //   218: aload_3
    //   219: invokevirtual 88	java/lang/IndexOutOfBoundsException:getMessage	()Ljava/lang/String;
    //   222: astore 4
    //   224: aload_0
    //   225: invokestatic 39	java/lang/String:valueOf	(Ljava/lang/Object;)Ljava/lang/String;
    //   228: invokevirtual 42	java/lang/String:length	()I
    //   231: istore_2
    //   232: aload 4
    //   234: invokestatic 39	java/lang/String:valueOf	(Ljava/lang/Object;)Ljava/lang/String;
    //   237: invokevirtual 42	java/lang/String:length	()I
    //   240: istore_1
    //   241: new 44	java/lang/StringBuilder
    //   244: astore 5
    //   246: aload 5
    //   248: iload_2
    //   249: bipush 32
    //   251: iadd
    //   252: iload_1
    //   253: iadd
    //   254: invokespecial 46	java/lang/StringBuilder:<init>	(I)V
    //   257: aload 5
    //   259: ldc 90
    //   261: invokevirtual 52	java/lang/StringBuilder:append	(Ljava/lang/String;)Ljava/lang/StringBuilder;
    //   264: pop
    //   265: aload 5
    //   267: aload_0
    //   268: invokevirtual 52	java/lang/StringBuilder:append	(Ljava/lang/String;)Ljava/lang/StringBuilder;
    //   271: pop
    //   272: aload 5
    //   274: ldc 84
    //   276: invokevirtual 52	java/lang/StringBuilder:append	(Ljava/lang/String;)Ljava/lang/StringBuilder;
    //   279: pop
    //   280: aload 5
    //   282: aload 4
    //   284: invokevirtual 52	java/lang/StringBuilder:append	(Ljava/lang/String;)Ljava/lang/StringBuilder;
    //   287: pop
    //   288: ldc 59
    //   290: aload 5
    //   292: invokevirtual 63	java/lang/StringBuilder:toString	()Ljava/lang/String;
    //   295: aload_3
    //   296: invokestatic 87	android/util/Log:w	(Ljava/lang/String;Ljava/lang/String;Ljava/lang/Throwable;)I
    //   299: pop
    //   300: invokestatic 75	com/google/android/gms/internal/ads_identifier/zzi:zza	()V
    //   303: return
    //   304: invokestatic 75	com/google/android/gms/internal/ads_identifier/zzi:zza	()V
    //   307: aload_0
    //   308: athrow
    // Local variable table:
    //   start	length	slot	name	signature
    //   0	309	0	paramString	String
    //   27	227	1	i	int
    //   49	203	2	j	int
    //   9	107	3	localObject1	Object
    //   126	1	3	localRuntimeException	RuntimeException
    //   130	79	3	localIOException	java.io.IOException
    //   217	79	3	localIndexOutOfBoundsException	IndexOutOfBoundsException
    //   53	44	4	localStringBuilder1	StringBuilder
    //   113	7	4	localObject2	Object
    //   135	148	4	str	String
    //   157	134	5	localStringBuilder2	StringBuilder
    // Exception table:
    //   from	to	target	type
    //   23	28	113	finally
    //   42	105	113	finally
    //   0	23	122	finally
    //   105	109	122	finally
    //   115	122	122	finally
    //   131	213	122	finally
    //   218	300	122	finally
    //   0	23	126	java/lang/RuntimeException
    //   105	109	126	java/lang/RuntimeException
    //   115	122	126	java/lang/RuntimeException
    //   0	23	130	java/io/IOException
    //   105	109	130	java/io/IOException
    //   115	122	130	java/io/IOException
    //   0	23	217	java/lang/IndexOutOfBoundsException
    //   105	109	217	java/lang/IndexOutOfBoundsException
    //   115	122	217	java/lang/IndexOutOfBoundsException
  }
}


/* Location:              C:\Users\Ria\Documents\slope apk\dex-tools-v2.4\classes-dex2jar.jar!\com\google\android\gms\ads\identifier\zzc.class
 * Java compiler version: 6 (50.0)
 * JD-Core Version:       0.7.1
 */