package com.google.android.gms.common.api.internal;

import com.google.android.gms.common.api.Result;

final class zacy
  implements Runnable
{
  final zada zab;
  
  zacy(zada paramzada, Result paramResult) {}
  
  /* Error */
  public final void run()
  {
    // Byte code:
    //   0: getstatic 28	com/google/android/gms/common/api/internal/BasePendingResult:zaa	Ljava/lang/ThreadLocal;
    //   3: iconst_1
    //   4: invokestatic 34	java/lang/Boolean:valueOf	(Z)Ljava/lang/Boolean;
    //   7: invokevirtual 40	java/lang/ThreadLocal:set	(Ljava/lang/Object;)V
    //   10: aload_0
    //   11: getfield 14	com/google/android/gms/common/api/internal/zacy:zab	Lcom/google/android/gms/common/api/internal/zada;
    //   14: invokestatic 45	com/google/android/gms/common/api/internal/zada:zaa	(Lcom/google/android/gms/common/api/internal/zada;)Lcom/google/android/gms/common/api/ResultTransform;
    //   17: invokestatic 51	com/google/android/gms/common/internal/Preconditions:checkNotNull	(Ljava/lang/Object;)Ljava/lang/Object;
    //   20: checkcast 53	com/google/android/gms/common/api/ResultTransform
    //   23: aload_0
    //   24: getfield 16	com/google/android/gms/common/api/internal/zacy:zaa	Lcom/google/android/gms/common/api/Result;
    //   27: invokevirtual 57	com/google/android/gms/common/api/ResultTransform:onSuccess	(Lcom/google/android/gms/common/api/Result;)Lcom/google/android/gms/common/api/PendingResult;
    //   30: astore_2
    //   31: aload_0
    //   32: getfield 14	com/google/android/gms/common/api/internal/zacy:zab	Lcom/google/android/gms/common/api/internal/zada;
    //   35: astore_1
    //   36: aload_1
    //   37: invokestatic 60	com/google/android/gms/common/api/internal/zada:zab	(Lcom/google/android/gms/common/api/internal/zada;)Lcom/google/android/gms/common/api/internal/zacz;
    //   40: aload_1
    //   41: invokestatic 60	com/google/android/gms/common/api/internal/zada:zab	(Lcom/google/android/gms/common/api/internal/zada;)Lcom/google/android/gms/common/api/internal/zacz;
    //   44: iconst_0
    //   45: aload_2
    //   46: invokevirtual 66	com/google/android/gms/common/api/internal/zacz:obtainMessage	(ILjava/lang/Object;)Landroid/os/Message;
    //   49: invokevirtual 70	com/google/android/gms/common/api/internal/zacz:sendMessage	(Landroid/os/Message;)Z
    //   52: pop
    //   53: getstatic 28	com/google/android/gms/common/api/internal/BasePendingResult:zaa	Ljava/lang/ThreadLocal;
    //   56: iconst_0
    //   57: invokestatic 34	java/lang/Boolean:valueOf	(Z)Ljava/lang/Boolean;
    //   60: invokevirtual 40	java/lang/ThreadLocal:set	(Ljava/lang/Object;)V
    //   63: aload_0
    //   64: getfield 14	com/google/android/gms/common/api/internal/zacy:zab	Lcom/google/android/gms/common/api/internal/zada;
    //   67: aload_0
    //   68: getfield 16	com/google/android/gms/common/api/internal/zacy:zaa	Lcom/google/android/gms/common/api/Result;
    //   71: invokestatic 73	com/google/android/gms/common/api/internal/zada:zaf	(Lcom/google/android/gms/common/api/internal/zada;Lcom/google/android/gms/common/api/Result;)V
    //   74: aload_0
    //   75: getfield 14	com/google/android/gms/common/api/internal/zacy:zab	Lcom/google/android/gms/common/api/internal/zada;
    //   78: invokestatic 77	com/google/android/gms/common/api/internal/zada:zae	(Lcom/google/android/gms/common/api/internal/zada;)Ljava/lang/ref/WeakReference;
    //   81: invokevirtual 83	java/lang/ref/WeakReference:get	()Ljava/lang/Object;
    //   84: checkcast 85	com/google/android/gms/common/api/GoogleApiClient
    //   87: astore_1
    //   88: aload_1
    //   89: ifnull +81 -> 170
    //   92: aload_1
    //   93: aload_0
    //   94: getfield 14	com/google/android/gms/common/api/internal/zacy:zab	Lcom/google/android/gms/common/api/internal/zada;
    //   97: invokevirtual 89	com/google/android/gms/common/api/GoogleApiClient:zap	(Lcom/google/android/gms/common/api/internal/zada;)V
    //   100: return
    //   101: astore_1
    //   102: goto +69 -> 171
    //   105: astore_2
    //   106: aload_0
    //   107: getfield 14	com/google/android/gms/common/api/internal/zacy:zab	Lcom/google/android/gms/common/api/internal/zada;
    //   110: astore_1
    //   111: aload_1
    //   112: invokestatic 60	com/google/android/gms/common/api/internal/zada:zab	(Lcom/google/android/gms/common/api/internal/zada;)Lcom/google/android/gms/common/api/internal/zacz;
    //   115: aload_1
    //   116: invokestatic 60	com/google/android/gms/common/api/internal/zada:zab	(Lcom/google/android/gms/common/api/internal/zada;)Lcom/google/android/gms/common/api/internal/zacz;
    //   119: iconst_1
    //   120: aload_2
    //   121: invokevirtual 66	com/google/android/gms/common/api/internal/zacz:obtainMessage	(ILjava/lang/Object;)Landroid/os/Message;
    //   124: invokevirtual 70	com/google/android/gms/common/api/internal/zacz:sendMessage	(Landroid/os/Message;)Z
    //   127: pop
    //   128: getstatic 28	com/google/android/gms/common/api/internal/BasePendingResult:zaa	Ljava/lang/ThreadLocal;
    //   131: iconst_0
    //   132: invokestatic 34	java/lang/Boolean:valueOf	(Z)Ljava/lang/Boolean;
    //   135: invokevirtual 40	java/lang/ThreadLocal:set	(Ljava/lang/Object;)V
    //   138: aload_0
    //   139: getfield 14	com/google/android/gms/common/api/internal/zacy:zab	Lcom/google/android/gms/common/api/internal/zada;
    //   142: aload_0
    //   143: getfield 16	com/google/android/gms/common/api/internal/zacy:zaa	Lcom/google/android/gms/common/api/Result;
    //   146: invokestatic 73	com/google/android/gms/common/api/internal/zada:zaf	(Lcom/google/android/gms/common/api/internal/zada;Lcom/google/android/gms/common/api/Result;)V
    //   149: aload_0
    //   150: getfield 14	com/google/android/gms/common/api/internal/zacy:zab	Lcom/google/android/gms/common/api/internal/zada;
    //   153: invokestatic 77	com/google/android/gms/common/api/internal/zada:zae	(Lcom/google/android/gms/common/api/internal/zada;)Ljava/lang/ref/WeakReference;
    //   156: invokevirtual 83	java/lang/ref/WeakReference:get	()Ljava/lang/Object;
    //   159: checkcast 85	com/google/android/gms/common/api/GoogleApiClient
    //   162: astore_1
    //   163: aload_1
    //   164: ifnull +6 -> 170
    //   167: goto -75 -> 92
    //   170: return
    //   171: getstatic 28	com/google/android/gms/common/api/internal/BasePendingResult:zaa	Ljava/lang/ThreadLocal;
    //   174: iconst_0
    //   175: invokestatic 34	java/lang/Boolean:valueOf	(Z)Ljava/lang/Boolean;
    //   178: invokevirtual 40	java/lang/ThreadLocal:set	(Ljava/lang/Object;)V
    //   181: aload_0
    //   182: getfield 14	com/google/android/gms/common/api/internal/zacy:zab	Lcom/google/android/gms/common/api/internal/zada;
    //   185: aload_0
    //   186: getfield 16	com/google/android/gms/common/api/internal/zacy:zaa	Lcom/google/android/gms/common/api/Result;
    //   189: invokestatic 73	com/google/android/gms/common/api/internal/zada:zaf	(Lcom/google/android/gms/common/api/internal/zada;Lcom/google/android/gms/common/api/Result;)V
    //   192: aload_0
    //   193: getfield 14	com/google/android/gms/common/api/internal/zacy:zab	Lcom/google/android/gms/common/api/internal/zada;
    //   196: invokestatic 77	com/google/android/gms/common/api/internal/zada:zae	(Lcom/google/android/gms/common/api/internal/zada;)Ljava/lang/ref/WeakReference;
    //   199: invokevirtual 83	java/lang/ref/WeakReference:get	()Ljava/lang/Object;
    //   202: checkcast 85	com/google/android/gms/common/api/GoogleApiClient
    //   205: astore_2
    //   206: aload_2
    //   207: ifnonnull +6 -> 213
    //   210: goto +11 -> 221
    //   213: aload_2
    //   214: aload_0
    //   215: getfield 14	com/google/android/gms/common/api/internal/zacy:zab	Lcom/google/android/gms/common/api/internal/zada;
    //   218: invokevirtual 89	com/google/android/gms/common/api/GoogleApiClient:zap	(Lcom/google/android/gms/common/api/internal/zada;)V
    //   221: aload_1
    //   222: athrow
    // Local variable table:
    //   start	length	slot	name	signature
    //   0	223	0	this	zacy
    //   35	58	1	localObject1	Object
    //   101	1	1	localObject2	Object
    //   110	112	1	localObject3	Object
    //   30	16	2	localPendingResult	com.google.android.gms.common.api.PendingResult
    //   105	16	2	localRuntimeException	RuntimeException
    //   205	9	2	localGoogleApiClient	com.google.android.gms.common.api.GoogleApiClient
    // Exception table:
    //   from	to	target	type
    //   0	53	101	finally
    //   106	128	101	finally
    //   0	53	105	java/lang/RuntimeException
  }
}


/* Location:              C:\Users\Ria\Documents\slope apk\dex-tools-v2.4\classes-dex2jar.jar!\com\google\android\gms\common\api\internal\zacy.class
 * Java compiler version: 6 (50.0)
 * JD-Core Version:       0.7.1
 */