package com.google.android.gms.internal.consent_sdk;

import android.app.Activity;
import android.app.Application;
import android.os.Handler;
import com.google.android.ump.ConsentInformation.OnConsentInfoUpdateFailureListener;
import com.google.android.ump.ConsentInformation.OnConsentInfoUpdateSuccessListener;
import com.google.android.ump.ConsentRequestParameters;
import java.util.concurrent.Executor;

final class zzx
{
  private final Application zza;
  private final zzae zzb;
  private final Handler zzc;
  private final Executor zzd;
  private final zzas zze;
  private final zzbq zzf;
  private final zzn zzg;
  private final zzaa zzh;
  private final zzg zzi;
  
  zzx(Application paramApplication, zzae paramzzae, Handler paramHandler, Executor paramExecutor, zzas paramzzas, zzbq paramzzbq, zzn paramzzn, zzaa paramzzaa, zzg paramzzg)
  {
    this.zza = paramApplication;
    this.zzb = paramzzae;
    this.zzc = paramHandler;
    this.zzd = paramExecutor;
    this.zze = paramzzas;
    this.zzf = paramzzbq;
    this.zzg = paramzzn;
    this.zzh = paramzzaa;
    this.zzi = paramzzg;
  }
  
  /* Error */
  private final zzcm zzd(zzck paramzzck)
    throws zzi
  {
    // Byte code:
    //   0: new 55	java/net/URL
    //   3: astore_3
    //   4: aload_3
    //   5: ldc 57
    //   7: invokespecial 60	java/net/URL:<init>	(Ljava/lang/String;)V
    //   10: aload_3
    //   11: invokevirtual 64	java/net/URL:openConnection	()Ljava/net/URLConnection;
    //   14: checkcast 66	java/net/HttpURLConnection
    //   17: astore 4
    //   19: aload_0
    //   20: getfield 29	com/google/android/gms/internal/consent_sdk/zzx:zza	Landroid/app/Application;
    //   23: astore 5
    //   25: getstatic 72	android/os/Build$VERSION:SDK_INT	I
    //   28: bipush 17
    //   30: if_icmplt +12 -> 42
    //   33: aload 5
    //   35: invokestatic 78	android/webkit/WebSettings:getDefaultUserAgent	(Landroid/content/Context;)Ljava/lang/String;
    //   38: astore_3
    //   39: goto +21 -> 60
    //   42: new 80	android/webkit/WebView
    //   45: astore_3
    //   46: aload_3
    //   47: aload 5
    //   49: invokespecial 83	android/webkit/WebView:<init>	(Landroid/content/Context;)V
    //   52: aload_3
    //   53: invokevirtual 87	android/webkit/WebView:getSettings	()Landroid/webkit/WebSettings;
    //   56: invokevirtual 91	android/webkit/WebSettings:getUserAgentString	()Ljava/lang/String;
    //   59: astore_3
    //   60: aload 4
    //   62: ldc 93
    //   64: aload_3
    //   65: invokevirtual 97	java/net/HttpURLConnection:setRequestProperty	(Ljava/lang/String;Ljava/lang/String;)V
    //   68: aload 4
    //   70: sipush 10000
    //   73: invokevirtual 101	java/net/HttpURLConnection:setConnectTimeout	(I)V
    //   76: aload 4
    //   78: sipush 30000
    //   81: invokevirtual 104	java/net/HttpURLConnection:setReadTimeout	(I)V
    //   84: aload 4
    //   86: iconst_1
    //   87: invokevirtual 108	java/net/HttpURLConnection:setDoOutput	(Z)V
    //   90: aload 4
    //   92: ldc 110
    //   94: invokevirtual 113	java/net/HttpURLConnection:setRequestMethod	(Ljava/lang/String;)V
    //   97: aload 4
    //   99: ldc 115
    //   101: ldc 117
    //   103: invokevirtual 97	java/net/HttpURLConnection:setRequestProperty	(Ljava/lang/String;Ljava/lang/String;)V
    //   106: new 119	java/io/OutputStreamWriter
    //   109: astore_3
    //   110: aload_3
    //   111: aload 4
    //   113: invokevirtual 123	java/net/HttpURLConnection:getOutputStream	()Ljava/io/OutputStream;
    //   116: ldc 125
    //   118: invokespecial 128	java/io/OutputStreamWriter:<init>	(Ljava/io/OutputStream;Ljava/lang/String;)V
    //   121: new 130	android/util/JsonWriter
    //   124: astore 5
    //   126: aload 5
    //   128: aload_3
    //   129: invokespecial 133	android/util/JsonWriter:<init>	(Ljava/io/Writer;)V
    //   132: aload 5
    //   134: invokevirtual 137	android/util/JsonWriter:beginObject	()Landroid/util/JsonWriter;
    //   137: pop
    //   138: aload_1
    //   139: getfield 142	com/google/android/gms/internal/consent_sdk/zzck:zza	Ljava/lang/String;
    //   142: astore 6
    //   144: aload 6
    //   146: ifnull +19 -> 165
    //   149: aload 5
    //   151: ldc -112
    //   153: invokevirtual 148	android/util/JsonWriter:name	(Ljava/lang/String;)Landroid/util/JsonWriter;
    //   156: pop
    //   157: aload 5
    //   159: aload 6
    //   161: invokevirtual 151	android/util/JsonWriter:value	(Ljava/lang/String;)Landroid/util/JsonWriter;
    //   164: pop
    //   165: aload_1
    //   166: getfield 153	com/google/android/gms/internal/consent_sdk/zzck:zzb	Ljava/lang/String;
    //   169: astore 6
    //   171: aload 6
    //   173: ifnull +19 -> 192
    //   176: aload 5
    //   178: ldc -101
    //   180: invokevirtual 148	android/util/JsonWriter:name	(Ljava/lang/String;)Landroid/util/JsonWriter;
    //   183: pop
    //   184: aload 5
    //   186: aload 6
    //   188: invokevirtual 151	android/util/JsonWriter:value	(Ljava/lang/String;)Landroid/util/JsonWriter;
    //   191: pop
    //   192: aload_1
    //   193: getfield 158	com/google/android/gms/internal/consent_sdk/zzck:zzc	Lcom/google/android/gms/internal/consent_sdk/zzcg;
    //   196: astore 6
    //   198: aload 6
    //   200: ifnull +132 -> 332
    //   203: aload 5
    //   205: ldc -96
    //   207: invokevirtual 148	android/util/JsonWriter:name	(Ljava/lang/String;)Landroid/util/JsonWriter;
    //   210: pop
    //   211: aload 5
    //   213: invokevirtual 137	android/util/JsonWriter:beginObject	()Landroid/util/JsonWriter;
    //   216: pop
    //   217: aload 6
    //   219: getfield 164	com/google/android/gms/internal/consent_sdk/zzcg:zzc	I
    //   222: istore_2
    //   223: iload_2
    //   224: iconst_1
    //   225: if_icmpeq +45 -> 270
    //   228: aload 5
    //   230: ldc -90
    //   232: invokevirtual 148	android/util/JsonWriter:name	(Ljava/lang/String;)Landroid/util/JsonWriter;
    //   235: pop
    //   236: iinc 2 -1
    //   239: iload_2
    //   240: ifeq +22 -> 262
    //   243: iload_2
    //   244: iconst_1
    //   245: if_icmpeq +6 -> 251
    //   248: goto +22 -> 270
    //   251: aload 5
    //   253: ldc -88
    //   255: invokevirtual 151	android/util/JsonWriter:value	(Ljava/lang/String;)Landroid/util/JsonWriter;
    //   258: pop
    //   259: goto +11 -> 270
    //   262: aload 5
    //   264: ldc -86
    //   266: invokevirtual 151	android/util/JsonWriter:value	(Ljava/lang/String;)Landroid/util/JsonWriter;
    //   269: pop
    //   270: aload 6
    //   272: getfield 171	com/google/android/gms/internal/consent_sdk/zzcg:zza	Ljava/lang/String;
    //   275: astore 7
    //   277: aload 7
    //   279: ifnull +19 -> 298
    //   282: aload 5
    //   284: ldc -83
    //   286: invokevirtual 148	android/util/JsonWriter:name	(Ljava/lang/String;)Landroid/util/JsonWriter;
    //   289: pop
    //   290: aload 5
    //   292: aload 7
    //   294: invokevirtual 151	android/util/JsonWriter:value	(Ljava/lang/String;)Landroid/util/JsonWriter;
    //   297: pop
    //   298: aload 6
    //   300: getfield 176	com/google/android/gms/internal/consent_sdk/zzcg:zzb	Ljava/lang/Integer;
    //   303: astore 6
    //   305: aload 6
    //   307: ifnull +19 -> 326
    //   310: aload 5
    //   312: ldc -78
    //   314: invokevirtual 148	android/util/JsonWriter:name	(Ljava/lang/String;)Landroid/util/JsonWriter;
    //   317: pop
    //   318: aload 5
    //   320: aload 6
    //   322: invokevirtual 181	android/util/JsonWriter:value	(Ljava/lang/Number;)Landroid/util/JsonWriter;
    //   325: pop
    //   326: aload 5
    //   328: invokevirtual 184	android/util/JsonWriter:endObject	()Landroid/util/JsonWriter;
    //   331: pop
    //   332: aload_1
    //   333: getfield 186	com/google/android/gms/internal/consent_sdk/zzck:zzd	Ljava/lang/String;
    //   336: astore 6
    //   338: aload 6
    //   340: ifnull +19 -> 359
    //   343: aload 5
    //   345: ldc -68
    //   347: invokevirtual 148	android/util/JsonWriter:name	(Ljava/lang/String;)Landroid/util/JsonWriter;
    //   350: pop
    //   351: aload 5
    //   353: aload 6
    //   355: invokevirtual 151	android/util/JsonWriter:value	(Ljava/lang/String;)Landroid/util/JsonWriter;
    //   358: pop
    //   359: aload_1
    //   360: getfield 191	com/google/android/gms/internal/consent_sdk/zzck:zze	Ljava/lang/Boolean;
    //   363: astore 6
    //   365: aload 6
    //   367: ifnull +22 -> 389
    //   370: aload 5
    //   372: ldc -63
    //   374: invokevirtual 148	android/util/JsonWriter:name	(Ljava/lang/String;)Landroid/util/JsonWriter;
    //   377: pop
    //   378: aload 5
    //   380: aload 6
    //   382: invokevirtual 199	java/lang/Boolean:booleanValue	()Z
    //   385: invokevirtual 202	android/util/JsonWriter:value	(Z)Landroid/util/JsonWriter;
    //   388: pop
    //   389: aload_1
    //   390: getfield 205	com/google/android/gms/internal/consent_sdk/zzck:zzf	Ljava/util/Map;
    //   393: astore 6
    //   395: aload 6
    //   397: invokeinterface 210 1 0
    //   402: ifne +94 -> 496
    //   405: aload 5
    //   407: ldc -44
    //   409: invokevirtual 148	android/util/JsonWriter:name	(Ljava/lang/String;)Landroid/util/JsonWriter;
    //   412: pop
    //   413: aload 5
    //   415: invokevirtual 137	android/util/JsonWriter:beginObject	()Landroid/util/JsonWriter;
    //   418: pop
    //   419: aload 6
    //   421: invokeinterface 216 1 0
    //   426: invokeinterface 222 1 0
    //   431: astore 7
    //   433: aload 7
    //   435: invokeinterface 227 1 0
    //   440: ifeq +50 -> 490
    //   443: aload 7
    //   445: invokeinterface 231 1 0
    //   450: checkcast 233	java/util/Map$Entry
    //   453: astore 6
    //   455: aload 5
    //   457: aload 6
    //   459: invokeinterface 236 1 0
    //   464: checkcast 238	java/lang/String
    //   467: invokevirtual 148	android/util/JsonWriter:name	(Ljava/lang/String;)Landroid/util/JsonWriter;
    //   470: pop
    //   471: aload 5
    //   473: aload 6
    //   475: invokeinterface 241 1 0
    //   480: checkcast 238	java/lang/String
    //   483: invokevirtual 151	android/util/JsonWriter:value	(Ljava/lang/String;)Landroid/util/JsonWriter;
    //   486: pop
    //   487: goto -54 -> 433
    //   490: aload 5
    //   492: invokevirtual 184	android/util/JsonWriter:endObject	()Landroid/util/JsonWriter;
    //   495: pop
    //   496: aload_1
    //   497: getfield 244	com/google/android/gms/internal/consent_sdk/zzck:zzg	Lcom/google/android/gms/internal/consent_sdk/zzci;
    //   500: astore 6
    //   502: aload 6
    //   504: ifnull +308 -> 812
    //   507: aload 5
    //   509: ldc -10
    //   511: invokevirtual 148	android/util/JsonWriter:name	(Ljava/lang/String;)Landroid/util/JsonWriter;
    //   514: pop
    //   515: aload 5
    //   517: invokevirtual 137	android/util/JsonWriter:beginObject	()Landroid/util/JsonWriter;
    //   520: pop
    //   521: aload 6
    //   523: getfield 250	com/google/android/gms/internal/consent_sdk/zzci:zza	Ljava/lang/Integer;
    //   526: astore 7
    //   528: aload 7
    //   530: ifnull +19 -> 549
    //   533: aload 5
    //   535: ldc -4
    //   537: invokevirtual 148	android/util/JsonWriter:name	(Ljava/lang/String;)Landroid/util/JsonWriter;
    //   540: pop
    //   541: aload 5
    //   543: aload 7
    //   545: invokevirtual 181	android/util/JsonWriter:value	(Ljava/lang/Number;)Landroid/util/JsonWriter;
    //   548: pop
    //   549: aload 6
    //   551: getfield 253	com/google/android/gms/internal/consent_sdk/zzci:zzb	Ljava/lang/Integer;
    //   554: astore 7
    //   556: aload 7
    //   558: ifnull +19 -> 577
    //   561: aload 5
    //   563: ldc -1
    //   565: invokevirtual 148	android/util/JsonWriter:name	(Ljava/lang/String;)Landroid/util/JsonWriter;
    //   568: pop
    //   569: aload 5
    //   571: aload 7
    //   573: invokevirtual 181	android/util/JsonWriter:value	(Ljava/lang/Number;)Landroid/util/JsonWriter;
    //   576: pop
    //   577: aload 6
    //   579: getfield 258	com/google/android/gms/internal/consent_sdk/zzci:zzc	Ljava/lang/Double;
    //   582: astore 7
    //   584: aload 7
    //   586: ifnull +20 -> 606
    //   589: aload 5
    //   591: ldc_w 260
    //   594: invokevirtual 148	android/util/JsonWriter:name	(Ljava/lang/String;)Landroid/util/JsonWriter;
    //   597: pop
    //   598: aload 5
    //   600: aload 7
    //   602: invokevirtual 181	android/util/JsonWriter:value	(Ljava/lang/Number;)Landroid/util/JsonWriter;
    //   605: pop
    //   606: aload 6
    //   608: getfield 263	com/google/android/gms/internal/consent_sdk/zzci:zzd	Ljava/util/List;
    //   611: astore 6
    //   613: aload 6
    //   615: invokeinterface 266 1 0
    //   620: ifne +186 -> 806
    //   623: aload 5
    //   625: ldc_w 268
    //   628: invokevirtual 148	android/util/JsonWriter:name	(Ljava/lang/String;)Landroid/util/JsonWriter;
    //   631: pop
    //   632: aload 5
    //   634: invokevirtual 271	android/util/JsonWriter:beginArray	()Landroid/util/JsonWriter;
    //   637: pop
    //   638: aload 6
    //   640: invokeinterface 272 1 0
    //   645: astore 6
    //   647: aload 6
    //   649: invokeinterface 227 1 0
    //   654: ifeq +146 -> 800
    //   657: aload 6
    //   659: invokeinterface 231 1 0
    //   664: checkcast 274	com/google/android/gms/internal/consent_sdk/zzch
    //   667: astore 7
    //   669: aload 5
    //   671: invokevirtual 137	android/util/JsonWriter:beginObject	()Landroid/util/JsonWriter;
    //   674: pop
    //   675: aload 7
    //   677: getfield 275	com/google/android/gms/internal/consent_sdk/zzch:zza	Ljava/lang/Integer;
    //   680: astore 8
    //   682: aload 8
    //   684: ifnull +20 -> 704
    //   687: aload 5
    //   689: ldc_w 277
    //   692: invokevirtual 148	android/util/JsonWriter:name	(Ljava/lang/String;)Landroid/util/JsonWriter;
    //   695: pop
    //   696: aload 5
    //   698: aload 8
    //   700: invokevirtual 181	android/util/JsonWriter:value	(Ljava/lang/Number;)Landroid/util/JsonWriter;
    //   703: pop
    //   704: aload 7
    //   706: getfield 278	com/google/android/gms/internal/consent_sdk/zzch:zzb	Ljava/lang/Integer;
    //   709: astore 8
    //   711: aload 8
    //   713: ifnull +20 -> 733
    //   716: aload 5
    //   718: ldc_w 280
    //   721: invokevirtual 148	android/util/JsonWriter:name	(Ljava/lang/String;)Landroid/util/JsonWriter;
    //   724: pop
    //   725: aload 5
    //   727: aload 8
    //   729: invokevirtual 181	android/util/JsonWriter:value	(Ljava/lang/Number;)Landroid/util/JsonWriter;
    //   732: pop
    //   733: aload 7
    //   735: getfield 282	com/google/android/gms/internal/consent_sdk/zzch:zzc	Ljava/lang/Integer;
    //   738: astore 8
    //   740: aload 8
    //   742: ifnull +20 -> 762
    //   745: aload 5
    //   747: ldc_w 284
    //   750: invokevirtual 148	android/util/JsonWriter:name	(Ljava/lang/String;)Landroid/util/JsonWriter;
    //   753: pop
    //   754: aload 5
    //   756: aload 8
    //   758: invokevirtual 181	android/util/JsonWriter:value	(Ljava/lang/Number;)Landroid/util/JsonWriter;
    //   761: pop
    //   762: aload 7
    //   764: getfield 286	com/google/android/gms/internal/consent_sdk/zzch:zzd	Ljava/lang/Integer;
    //   767: astore 7
    //   769: aload 7
    //   771: ifnull +20 -> 791
    //   774: aload 5
    //   776: ldc_w 288
    //   779: invokevirtual 148	android/util/JsonWriter:name	(Ljava/lang/String;)Landroid/util/JsonWriter;
    //   782: pop
    //   783: aload 5
    //   785: aload 7
    //   787: invokevirtual 181	android/util/JsonWriter:value	(Ljava/lang/Number;)Landroid/util/JsonWriter;
    //   790: pop
    //   791: aload 5
    //   793: invokevirtual 184	android/util/JsonWriter:endObject	()Landroid/util/JsonWriter;
    //   796: pop
    //   797: goto -150 -> 647
    //   800: aload 5
    //   802: invokevirtual 291	android/util/JsonWriter:endArray	()Landroid/util/JsonWriter;
    //   805: pop
    //   806: aload 5
    //   808: invokevirtual 184	android/util/JsonWriter:endObject	()Landroid/util/JsonWriter;
    //   811: pop
    //   812: aload_1
    //   813: getfield 294	com/google/android/gms/internal/consent_sdk/zzck:zzh	Lcom/google/android/gms/internal/consent_sdk/zzce;
    //   816: astore 6
    //   818: aload 6
    //   820: ifnull +111 -> 931
    //   823: aload 5
    //   825: ldc_w 296
    //   828: invokevirtual 148	android/util/JsonWriter:name	(Ljava/lang/String;)Landroid/util/JsonWriter;
    //   831: pop
    //   832: aload 5
    //   834: invokevirtual 137	android/util/JsonWriter:beginObject	()Landroid/util/JsonWriter;
    //   837: pop
    //   838: aload 6
    //   840: getfield 299	com/google/android/gms/internal/consent_sdk/zzce:zza	Ljava/lang/String;
    //   843: astore 7
    //   845: aload 7
    //   847: ifnull +20 -> 867
    //   850: aload 5
    //   852: ldc_w 301
    //   855: invokevirtual 148	android/util/JsonWriter:name	(Ljava/lang/String;)Landroid/util/JsonWriter;
    //   858: pop
    //   859: aload 5
    //   861: aload 7
    //   863: invokevirtual 151	android/util/JsonWriter:value	(Ljava/lang/String;)Landroid/util/JsonWriter;
    //   866: pop
    //   867: aload 6
    //   869: getfield 302	com/google/android/gms/internal/consent_sdk/zzce:zzb	Ljava/lang/String;
    //   872: astore 7
    //   874: aload 7
    //   876: ifnull +20 -> 896
    //   879: aload 5
    //   881: ldc_w 304
    //   884: invokevirtual 148	android/util/JsonWriter:name	(Ljava/lang/String;)Landroid/util/JsonWriter;
    //   887: pop
    //   888: aload 5
    //   890: aload 7
    //   892: invokevirtual 151	android/util/JsonWriter:value	(Ljava/lang/String;)Landroid/util/JsonWriter;
    //   895: pop
    //   896: aload 6
    //   898: getfield 306	com/google/android/gms/internal/consent_sdk/zzce:zzc	Ljava/lang/String;
    //   901: astore 6
    //   903: aload 6
    //   905: ifnull +20 -> 925
    //   908: aload 5
    //   910: ldc_w 308
    //   913: invokevirtual 148	android/util/JsonWriter:name	(Ljava/lang/String;)Landroid/util/JsonWriter;
    //   916: pop
    //   917: aload 5
    //   919: aload 6
    //   921: invokevirtual 151	android/util/JsonWriter:value	(Ljava/lang/String;)Landroid/util/JsonWriter;
    //   924: pop
    //   925: aload 5
    //   927: invokevirtual 184	android/util/JsonWriter:endObject	()Landroid/util/JsonWriter;
    //   930: pop
    //   931: aload_1
    //   932: getfield 311	com/google/android/gms/internal/consent_sdk/zzck:zzi	Lcom/google/android/gms/internal/consent_sdk/zzcj;
    //   935: astore 6
    //   937: aload 6
    //   939: ifnull +53 -> 992
    //   942: aload 5
    //   944: ldc_w 313
    //   947: invokevirtual 148	android/util/JsonWriter:name	(Ljava/lang/String;)Landroid/util/JsonWriter;
    //   950: pop
    //   951: aload 5
    //   953: invokevirtual 137	android/util/JsonWriter:beginObject	()Landroid/util/JsonWriter;
    //   956: pop
    //   957: aload 6
    //   959: getfield 316	com/google/android/gms/internal/consent_sdk/zzcj:zza	Ljava/lang/String;
    //   962: astore 6
    //   964: aload 6
    //   966: ifnull +20 -> 986
    //   969: aload 5
    //   971: ldc_w 308
    //   974: invokevirtual 148	android/util/JsonWriter:name	(Ljava/lang/String;)Landroid/util/JsonWriter;
    //   977: pop
    //   978: aload 5
    //   980: aload 6
    //   982: invokevirtual 151	android/util/JsonWriter:value	(Ljava/lang/String;)Landroid/util/JsonWriter;
    //   985: pop
    //   986: aload 5
    //   988: invokevirtual 184	android/util/JsonWriter:endObject	()Landroid/util/JsonWriter;
    //   991: pop
    //   992: aload_1
    //   993: getfield 319	com/google/android/gms/internal/consent_sdk/zzck:zzj	Ljava/util/List;
    //   996: astore_1
    //   997: aload_1
    //   998: invokeinterface 266 1 0
    //   1003: ifne +140 -> 1143
    //   1006: aload 5
    //   1008: ldc_w 321
    //   1011: invokevirtual 148	android/util/JsonWriter:name	(Ljava/lang/String;)Landroid/util/JsonWriter;
    //   1014: pop
    //   1015: aload 5
    //   1017: invokevirtual 271	android/util/JsonWriter:beginArray	()Landroid/util/JsonWriter;
    //   1020: pop
    //   1021: aload_1
    //   1022: invokeinterface 272 1 0
    //   1027: astore_1
    //   1028: aload_1
    //   1029: invokeinterface 227 1 0
    //   1034: ifeq +103 -> 1137
    //   1037: aload_1
    //   1038: invokeinterface 231 1 0
    //   1043: checkcast 323	com/google/android/gms/internal/consent_sdk/zzcf
    //   1046: invokevirtual 327	com/google/android/gms/internal/consent_sdk/zzcf:ordinal	()I
    //   1049: istore_2
    //   1050: iload_2
    //   1051: ifeq +74 -> 1125
    //   1054: iload_2
    //   1055: iconst_1
    //   1056: if_icmpeq +57 -> 1113
    //   1059: iload_2
    //   1060: iconst_2
    //   1061: if_icmpeq +40 -> 1101
    //   1064: iload_2
    //   1065: iconst_3
    //   1066: if_icmpeq +23 -> 1089
    //   1069: iload_2
    //   1070: iconst_4
    //   1071: if_icmpeq +6 -> 1077
    //   1074: goto -46 -> 1028
    //   1077: aload 5
    //   1079: ldc_w 329
    //   1082: invokevirtual 151	android/util/JsonWriter:value	(Ljava/lang/String;)Landroid/util/JsonWriter;
    //   1085: pop
    //   1086: goto -58 -> 1028
    //   1089: aload 5
    //   1091: ldc_w 331
    //   1094: invokevirtual 151	android/util/JsonWriter:value	(Ljava/lang/String;)Landroid/util/JsonWriter;
    //   1097: pop
    //   1098: goto -70 -> 1028
    //   1101: aload 5
    //   1103: ldc_w 333
    //   1106: invokevirtual 151	android/util/JsonWriter:value	(Ljava/lang/String;)Landroid/util/JsonWriter;
    //   1109: pop
    //   1110: goto -82 -> 1028
    //   1113: aload 5
    //   1115: ldc_w 335
    //   1118: invokevirtual 151	android/util/JsonWriter:value	(Ljava/lang/String;)Landroid/util/JsonWriter;
    //   1121: pop
    //   1122: goto -94 -> 1028
    //   1125: aload 5
    //   1127: ldc_w 337
    //   1130: invokevirtual 151	android/util/JsonWriter:value	(Ljava/lang/String;)Landroid/util/JsonWriter;
    //   1133: pop
    //   1134: goto -106 -> 1028
    //   1137: aload 5
    //   1139: invokevirtual 291	android/util/JsonWriter:endArray	()Landroid/util/JsonWriter;
    //   1142: pop
    //   1143: aload 5
    //   1145: invokevirtual 184	android/util/JsonWriter:endObject	()Landroid/util/JsonWriter;
    //   1148: pop
    //   1149: aload 5
    //   1151: invokevirtual 340	android/util/JsonWriter:close	()V
    //   1154: aload_3
    //   1155: invokevirtual 343	java/io/Writer:close	()V
    //   1158: aload 4
    //   1160: invokevirtual 346	java/net/HttpURLConnection:getResponseCode	()I
    //   1163: istore_2
    //   1164: iload_2
    //   1165: sipush 200
    //   1168: if_icmpne +164 -> 1332
    //   1171: aload 4
    //   1173: ldc_w 348
    //   1176: invokevirtual 352	java/net/HttpURLConnection:getHeaderField	(Ljava/lang/String;)Ljava/lang/String;
    //   1179: astore_1
    //   1180: aload_1
    //   1181: ifnull +59 -> 1240
    //   1184: new 354	android/util/JsonReader
    //   1187: astore_3
    //   1188: new 356	java/io/StringReader
    //   1191: astore 5
    //   1193: aload 5
    //   1195: aload_1
    //   1196: invokespecial 357	java/io/StringReader:<init>	(Ljava/lang/String;)V
    //   1199: aload_3
    //   1200: aload 5
    //   1202: invokespecial 360	android/util/JsonReader:<init>	(Ljava/io/Reader;)V
    //   1205: aload_3
    //   1206: invokestatic 365	com/google/android/gms/internal/consent_sdk/zzcm:zza	(Landroid/util/JsonReader;)Lcom/google/android/gms/internal/consent_sdk/zzcm;
    //   1209: astore_1
    //   1210: new 367	java/util/Scanner
    //   1213: astore_3
    //   1214: aload_3
    //   1215: aload 4
    //   1217: invokevirtual 371	java/net/HttpURLConnection:getInputStream	()Ljava/io/InputStream;
    //   1220: invokespecial 374	java/util/Scanner:<init>	(Ljava/io/InputStream;)V
    //   1223: aload_1
    //   1224: aload_3
    //   1225: ldc_w 376
    //   1228: invokevirtual 380	java/util/Scanner:useDelimiter	(Ljava/lang/String;)Ljava/util/Scanner;
    //   1231: invokevirtual 382	java/util/Scanner:next	()Ljava/lang/String;
    //   1234: putfield 383	com/google/android/gms/internal/consent_sdk/zzcm:zza	Ljava/lang/String;
    //   1237: goto +58 -> 1295
    //   1240: new 385	java/io/BufferedReader
    //   1243: astore_3
    //   1244: new 387	java/io/InputStreamReader
    //   1247: astore_1
    //   1248: aload_1
    //   1249: aload 4
    //   1251: invokevirtual 371	java/net/HttpURLConnection:getInputStream	()Ljava/io/InputStream;
    //   1254: ldc 125
    //   1256: invokespecial 390	java/io/InputStreamReader:<init>	(Ljava/io/InputStream;Ljava/lang/String;)V
    //   1259: aload_3
    //   1260: aload_1
    //   1261: invokespecial 391	java/io/BufferedReader:<init>	(Ljava/io/Reader;)V
    //   1264: aload_3
    //   1265: invokevirtual 394	java/io/BufferedReader:readLine	()Ljava/lang/String;
    //   1268: pop
    //   1269: new 354	android/util/JsonReader
    //   1272: astore 4
    //   1274: aload 4
    //   1276: aload_3
    //   1277: invokespecial 360	android/util/JsonReader:<init>	(Ljava/io/Reader;)V
    //   1280: aload 4
    //   1282: invokestatic 365	com/google/android/gms/internal/consent_sdk/zzcm:zza	(Landroid/util/JsonReader;)Lcom/google/android/gms/internal/consent_sdk/zzcm;
    //   1285: astore_1
    //   1286: aload 4
    //   1288: invokevirtual 395	android/util/JsonReader:close	()V
    //   1291: aload_3
    //   1292: invokevirtual 396	java/io/BufferedReader:close	()V
    //   1295: aload_1
    //   1296: areturn
    //   1297: astore_1
    //   1298: aload 4
    //   1300: invokevirtual 395	android/util/JsonReader:close	()V
    //   1303: goto +11 -> 1314
    //   1306: astore 4
    //   1308: aload_1
    //   1309: aload 4
    //   1311: invokestatic 401	com/google/android/gms/internal/consent_sdk/zzr:zza	(Ljava/lang/Throwable;Ljava/lang/Throwable;)V
    //   1314: aload_1
    //   1315: athrow
    //   1316: astore_1
    //   1317: aload_3
    //   1318: invokevirtual 396	java/io/BufferedReader:close	()V
    //   1321: goto +9 -> 1330
    //   1324: astore_3
    //   1325: aload_1
    //   1326: aload_3
    //   1327: invokestatic 401	com/google/android/gms/internal/consent_sdk/zzr:zza	(Ljava/lang/Throwable;Ljava/lang/Throwable;)V
    //   1330: aload_1
    //   1331: athrow
    //   1332: new 367	java/util/Scanner
    //   1335: astore_1
    //   1336: aload_1
    //   1337: aload 4
    //   1339: invokevirtual 404	java/net/HttpURLConnection:getErrorStream	()Ljava/io/InputStream;
    //   1342: invokespecial 374	java/util/Scanner:<init>	(Ljava/io/InputStream;)V
    //   1345: aload_1
    //   1346: ldc_w 376
    //   1349: invokevirtual 380	java/util/Scanner:useDelimiter	(Ljava/lang/String;)Ljava/util/Scanner;
    //   1352: invokevirtual 382	java/util/Scanner:next	()Ljava/lang/String;
    //   1355: astore 4
    //   1357: new 53	java/io/IOException
    //   1360: astore_3
    //   1361: new 406	java/lang/StringBuilder
    //   1364: astore_1
    //   1365: aload_1
    //   1366: invokespecial 407	java/lang/StringBuilder:<init>	()V
    //   1369: aload_1
    //   1370: ldc_w 409
    //   1373: invokevirtual 413	java/lang/StringBuilder:append	(Ljava/lang/String;)Ljava/lang/StringBuilder;
    //   1376: pop
    //   1377: aload_1
    //   1378: iload_2
    //   1379: invokevirtual 416	java/lang/StringBuilder:append	(I)Ljava/lang/StringBuilder;
    //   1382: pop
    //   1383: aload_1
    //   1384: ldc_w 418
    //   1387: invokevirtual 413	java/lang/StringBuilder:append	(Ljava/lang/String;)Ljava/lang/StringBuilder;
    //   1390: pop
    //   1391: aload_1
    //   1392: aload 4
    //   1394: invokevirtual 413	java/lang/StringBuilder:append	(Ljava/lang/String;)Ljava/lang/StringBuilder;
    //   1397: pop
    //   1398: aload_3
    //   1399: aload_1
    //   1400: invokevirtual 421	java/lang/StringBuilder:toString	()Ljava/lang/String;
    //   1403: invokespecial 422	java/io/IOException:<init>	(Ljava/lang/String;)V
    //   1406: aload_3
    //   1407: athrow
    //   1408: astore_1
    //   1409: aload 5
    //   1411: invokevirtual 340	android/util/JsonWriter:close	()V
    //   1414: goto +11 -> 1425
    //   1417: astore 4
    //   1419: aload_1
    //   1420: aload 4
    //   1422: invokestatic 401	com/google/android/gms/internal/consent_sdk/zzr:zza	(Ljava/lang/Throwable;Ljava/lang/Throwable;)V
    //   1425: aload_1
    //   1426: athrow
    //   1427: astore_1
    //   1428: aload_3
    //   1429: invokevirtual 343	java/io/Writer:close	()V
    //   1432: goto +9 -> 1441
    //   1435: astore_3
    //   1436: aload_1
    //   1437: aload_3
    //   1438: invokestatic 401	com/google/android/gms/internal/consent_sdk/zzr:zza	(Ljava/lang/Throwable;Ljava/lang/Throwable;)V
    //   1441: aload_1
    //   1442: athrow
    //   1443: astore_1
    //   1444: new 49	com/google/android/gms/internal/consent_sdk/zzi
    //   1447: dup
    //   1448: iconst_2
    //   1449: ldc_w 424
    //   1452: aload_1
    //   1453: invokespecial 427	com/google/android/gms/internal/consent_sdk/zzi:<init>	(ILjava/lang/String;Ljava/lang/Throwable;)V
    //   1456: athrow
    //   1457: astore_1
    //   1458: new 49	com/google/android/gms/internal/consent_sdk/zzi
    //   1461: dup
    //   1462: iconst_4
    //   1463: ldc_w 429
    //   1466: aload_1
    //   1467: invokespecial 427	com/google/android/gms/internal/consent_sdk/zzi:<init>	(ILjava/lang/String;Ljava/lang/Throwable;)V
    //   1470: athrow
    // Local variable table:
    //   start	length	slot	name	signature
    //   0	1471	0	this	zzx
    //   0	1471	1	paramzzck	zzck
    //   222	1157	2	i	int
    //   3	1315	3	localObject1	Object
    //   1324	3	3	localThrowable1	Throwable
    //   1360	69	3	localIOException	java.io.IOException
    //   1435	3	3	localThrowable2	Throwable
    //   17	1282	4	localObject2	Object
    //   1306	32	4	localThrowable3	Throwable
    //   1355	38	4	str	String
    //   1417	4	4	localThrowable4	Throwable
    //   23	1387	5	localObject3	Object
    //   142	839	6	localObject4	Object
    //   275	616	7	localObject5	Object
    //   680	77	8	localInteger	Integer
    // Exception table:
    //   from	to	target	type
    //   1280	1286	1297	finally
    //   1298	1303	1306	finally
    //   1264	1280	1316	finally
    //   1286	1291	1316	finally
    //   1308	1314	1316	finally
    //   1314	1316	1316	finally
    //   1317	1321	1324	finally
    //   132	144	1408	finally
    //   149	165	1408	finally
    //   165	171	1408	finally
    //   176	192	1408	finally
    //   192	198	1408	finally
    //   203	223	1408	finally
    //   228	236	1408	finally
    //   251	259	1408	finally
    //   262	270	1408	finally
    //   270	277	1408	finally
    //   282	298	1408	finally
    //   298	305	1408	finally
    //   310	326	1408	finally
    //   326	332	1408	finally
    //   332	338	1408	finally
    //   343	359	1408	finally
    //   359	365	1408	finally
    //   370	389	1408	finally
    //   389	433	1408	finally
    //   433	487	1408	finally
    //   490	496	1408	finally
    //   496	502	1408	finally
    //   507	528	1408	finally
    //   533	549	1408	finally
    //   549	556	1408	finally
    //   561	577	1408	finally
    //   577	584	1408	finally
    //   589	606	1408	finally
    //   606	647	1408	finally
    //   647	682	1408	finally
    //   687	704	1408	finally
    //   704	711	1408	finally
    //   716	733	1408	finally
    //   733	740	1408	finally
    //   745	762	1408	finally
    //   762	769	1408	finally
    //   774	791	1408	finally
    //   791	797	1408	finally
    //   800	806	1408	finally
    //   806	812	1408	finally
    //   812	818	1408	finally
    //   823	845	1408	finally
    //   850	867	1408	finally
    //   867	874	1408	finally
    //   879	896	1408	finally
    //   896	903	1408	finally
    //   908	925	1408	finally
    //   925	931	1408	finally
    //   931	937	1408	finally
    //   942	964	1408	finally
    //   969	986	1408	finally
    //   986	992	1408	finally
    //   992	1028	1408	finally
    //   1028	1050	1408	finally
    //   1077	1086	1408	finally
    //   1089	1098	1408	finally
    //   1101	1110	1408	finally
    //   1113	1122	1408	finally
    //   1125	1134	1408	finally
    //   1137	1143	1408	finally
    //   1143	1149	1408	finally
    //   1409	1414	1417	finally
    //   121	132	1427	finally
    //   1149	1154	1427	finally
    //   1419	1425	1427	finally
    //   1425	1427	1427	finally
    //   1428	1432	1435	finally
    //   0	39	1443	java/io/IOException
    //   42	60	1443	java/io/IOException
    //   60	121	1443	java/io/IOException
    //   1154	1164	1443	java/io/IOException
    //   1171	1180	1443	java/io/IOException
    //   1184	1237	1443	java/io/IOException
    //   1240	1264	1443	java/io/IOException
    //   1291	1295	1443	java/io/IOException
    //   1325	1330	1443	java/io/IOException
    //   1330	1332	1443	java/io/IOException
    //   1332	1408	1443	java/io/IOException
    //   1436	1441	1443	java/io/IOException
    //   1441	1443	1443	java/io/IOException
    //   0	39	1457	java/net/SocketTimeoutException
    //   42	60	1457	java/net/SocketTimeoutException
    //   60	121	1457	java/net/SocketTimeoutException
    //   1154	1164	1457	java/net/SocketTimeoutException
    //   1171	1180	1457	java/net/SocketTimeoutException
    //   1184	1237	1457	java/net/SocketTimeoutException
    //   1240	1264	1457	java/net/SocketTimeoutException
    //   1291	1295	1457	java/net/SocketTimeoutException
    //   1325	1330	1457	java/net/SocketTimeoutException
    //   1330	1332	1457	java/net/SocketTimeoutException
    //   1332	1408	1457	java/net/SocketTimeoutException
    //   1436	1441	1457	java/net/SocketTimeoutException
    //   1441	1443	1457	java/net/SocketTimeoutException
  }
  
  final void zzc(Activity paramActivity, ConsentRequestParameters paramConsentRequestParameters, ConsentInformation.OnConsentInfoUpdateSuccessListener paramOnConsentInfoUpdateSuccessListener, ConsentInformation.OnConsentInfoUpdateFailureListener paramOnConsentInfoUpdateFailureListener)
  {
    this.zzd.execute(new zzw(this, paramActivity, paramConsentRequestParameters, paramOnConsentInfoUpdateSuccessListener, paramOnConsentInfoUpdateFailureListener));
  }
}


/* Location:              C:\Users\Ria\Documents\slope apk\dex-tools-v2.4\classes-dex2jar.jar!\com\google\android\gms\internal\consent_sdk\zzx.class
 * Java compiler version: 6 (50.0)
 * JD-Core Version:       0.7.1
 */